Workbook

Sheet Start here
B1: The Binders
B2: A workbook that walks you through twelve business playbooks in four systems, one band at a time.
B4: What it is | C4: The playbook binder that shipped with the $100M Money Models launch holds twelve playbooks in four systems: Leads (Marketing Machine, Hooks, Lead Nurture), Sales (Closing Handbook, Proof Checklist, GOATed Ads), Delivery (Retention, Lifetime Value, Branding) and Profit (Price Raise, Promo Cash, Implementation SOPs). This workbook is a companion in its own words, built from the published $100M books and public material. No book or playbook text is reproduced, and it is not affiliated with Acquisition.com.
B5: How to use it | C5: 1. Open a playbook tab (they run left to right in the order of the four systems). 2. Work down band 1, then band 2, and so on. Type into the yellow cells only. 3. Tick a checklist item by choosing Y. When every yellow cell in a band is filled and every item is Y, the band reads done. 4. Come back to Dashboard to see all twelve at once, and to Readings for every figure the binder earns. 5. Do band 1 on every playbook before going deeper. A ring lights on the Dashboard when all twelve clear a band.
B6: The six bands | C6: Band 1, Read: The one idea, and where you stand on it today (payoff: reveal). Band 2, Facts: The few numbers this playbook runs on (payoff: reveal). Band 3, Exercises: The pen and paper work the playbook asks for (payoff: reveal). Band 4, Build: Assemble the thing you will use, and tick it off (payoff: power). Band 5, Run: Use it for a stretch and log what happened (payoff: certainty). Band 6, Sharpen: The moves only visible once the numbers are real (payoff: power).
B7: The four systems | C7: Leads: How do strangers find out you exist? Sales: How does a stranger become a customer? Delivery: How does a customer stay and bring more? Profit: How does each customer pay for the next?
B8: Colours | C8: Yellow cell with blue text: yours to type. Black text: a formula, leave it. Green text: a value read from another tab, typed once and only there (price, gross margin, cost to acquire, the booking rate). Grey italic: an example answer for a made-up money coach who sells an eight-week programme; every example number is invented.
B9: Money and percentages | C9: Type money in whole dollars. Type percentages as percentages (80%). A blank cell means not known yet; it is not zero. Type 0 only when the true answer is zero.
B10: Lists | C10: Where a cell asks for one item a line, press Alt+Enter (Option+Return on a Mac) to start a new line inside the cell. Where a step asks for a small table, fill the rows under its grey header; add more rows on the sheet if eight is not enough.
B11: Rules of thumb | C11: Three to one (lifetime gross profit to cost of a customer), five minutes (first reply to a lead), nine touches (the follow-up sequence), thirty days (cash back from a new customer) are rules of thumb, not findings. Your numbers decide.
B12: Privacy | C12: This file lives wherever you save it. Nothing in it goes anywhere unless you send it.
B13: Version | C13: Built from the Binders app in the Personalfinance repository, data version 1.0, 2026-09-26.
B15: Legend
B16: Yours to type | C16: =IF(B16="","","This is what a filled cell looks like: type over the yellow.") -> This is what a filled cell looks like: type over the yellow.
B17: =1+1 -> 2 | C17: A formula in black. Leave it.
B18: ='Lifetime Value'!D1 -> Delivery system | C18: A value read from another tab, in green.
B19: an example | C19: An example answer, grey and italic. Every example number is made up.

Sheet Dashboard
B1: The Binders
B2: Twelve playbooks in four systems, six bands deep. A band means the same depth on every playbook: read the idea, type the facts, do the exercises, build the thing, run it, sharpen it.
B4: Where you stand
B5: System | C5: Playbook | D5: Levels done | E5: Working on | F5: Answered | G5: Of | H5: Ticked | I5: Of | J5: Share done | L5: Band 1 | M5: Band 2 | N5: Band 3 | O5: Band 4 | P5: Band 5 | Q5: Band 6
B6: Leads | C6: Marketing Machine | D6: ='Marketing Machine'!$D$13 -> 0 | E6: ='Marketing Machine'!$D$14 -> 1 | F6: =SUM('Marketing Machine'!$D$7:$D$12) -> 0 | G6: =SUM('Marketing Machine'!$E$7:$E$12) -> 21 | H6: =SUM('Marketing Machine'!$F$7:$F$12) -> 0 | I6: =SUM('Marketing Machine'!$G$7:$G$12) -> 14 | J6: ='Marketing Machine'!$D$15 -> 0 | L6: ='Marketing Machine'!$H$7 -> not yet | M6: ='Marketing Machine'!$H$8 -> not yet | N6: ='Marketing Machine'!$H$9 -> not yet | O6: ='Marketing Machine'!$H$10 -> not yet | P6: ='Marketing Machine'!$H$11 -> not yet | Q6: ='Marketing Machine'!$H$12 -> not yet
B7: Leads | C7: Hooks | D7: =Hooks!$D$13 -> 0 | E7: =Hooks!$D$14 -> 1 | F7: =SUM(Hooks!$D$7:$D$12) -> 0 | G7: =SUM(Hooks!$E$7:$E$12) -> 15 | H7: =SUM(Hooks!$F$7:$F$12) -> 0 | I7: =SUM(Hooks!$G$7:$G$12) -> 14 | J7: =Hooks!$D$15 -> 0 | L7: =Hooks!$H$7 -> not yet | M7: =Hooks!$H$8 -> not yet | N7: =Hooks!$H$9 -> not yet | O7: =Hooks!$H$10 -> not yet | P7: =Hooks!$H$11 -> not yet | Q7: =Hooks!$H$12 -> not yet
B8: Leads | C8: Lead Nurture | D8: ='Lead Nurture'!$D$13 -> 0 | E8: ='Lead Nurture'!$D$14 -> 1 | F8: =SUM('Lead Nurture'!$D$7:$D$12) -> 0 | G8: =SUM('Lead Nurture'!$E$7:$E$12) -> 17 | H8: =SUM('Lead Nurture'!$F$7:$F$12) -> 0 | I8: =SUM('Lead Nurture'!$G$7:$G$12) -> 15 | J8: ='Lead Nurture'!$D$15 -> 0 | L8: ='Lead Nurture'!$H$7 -> not yet | M8: ='Lead Nurture'!$H$8 -> not yet | N8: ='Lead Nurture'!$H$9 -> not yet | O8: ='Lead Nurture'!$H$10 -> not yet | P8: ='Lead Nurture'!$H$11 -> not yet | Q8: ='Lead Nurture'!$H$12 -> not yet
B9: Sales | C9: Closing Handbook | D9: ='Closing Handbook'!$D$13 -> 0 | E9: ='Closing Handbook'!$D$14 -> 1 | F9: =SUM('Closing Handbook'!$D$7:$D$12) -> 0 | G9: =SUM('Closing Handbook'!$E$7:$E$12) -> 19 | H9: =SUM('Closing Handbook'!$F$7:$F$12) -> 0 | I9: =SUM('Closing Handbook'!$G$7:$G$12) -> 17 | J9: ='Closing Handbook'!$D$15 -> 0 | L9: ='Closing Handbook'!$H$7 -> not yet | M9: ='Closing Handbook'!$H$8 -> not yet | N9: ='Closing Handbook'!$H$9 -> not yet | O9: ='Closing Handbook'!$H$10 -> not yet | P9: ='Closing Handbook'!$H$11 -> not yet | Q9: ='Closing Handbook'!$H$12 -> not yet
B10: Sales | C10: Proof Checklist | D10: ='Proof Checklist'!$D$13 -> 0 | E10: ='Proof Checklist'!$D$14 -> 1 | F10: =SUM('Proof Checklist'!$D$7:$D$12) -> 0 | G10: =SUM('Proof Checklist'!$E$7:$E$12) -> 18 | H10: =SUM('Proof Checklist'!$F$7:$F$12) -> 0 | I10: =SUM('Proof Checklist'!$G$7:$G$12) -> 15 | J10: ='Proof Checklist'!$D$15 -> 0 | L10: ='Proof Checklist'!$H$7 -> not yet | M10: ='Proof Checklist'!$H$8 -> not yet | N10: ='Proof Checklist'!$H$9 -> not yet | O10: ='Proof Checklist'!$H$10 -> not yet | P10: ='Proof Checklist'!$H$11 -> not yet | Q10: ='Proof Checklist'!$H$12 -> not yet
B11: Sales | C11: GOATed Ads | D11: ='GOATed Ads'!$D$13 -> 0 | E11: ='GOATed Ads'!$D$14 -> 1 | F11: =SUM('GOATed Ads'!$D$7:$D$12) -> 0 | G11: =SUM('GOATed Ads'!$E$7:$E$12) -> 21 | H11: =SUM('GOATed Ads'!$F$7:$F$12) -> 0 | I11: =SUM('GOATed Ads'!$G$7:$G$12) -> 15 | J11: ='GOATed Ads'!$D$15 -> 0 | L11: ='GOATed Ads'!$H$7 -> not yet | M11: ='GOATed Ads'!$H$8 -> not yet | N11: ='GOATed Ads'!$H$9 -> not yet | O11: ='GOATed Ads'!$H$10 -> not yet | P11: ='GOATed Ads'!$H$11 -> not yet | Q11: ='GOATed Ads'!$H$12 -> not yet
B12: Delivery | C12: Retention | D12: =Retention!$D$13 -> 0 | E12: =Retention!$D$14 -> 1 | F12: =SUM(Retention!$D$7:$D$12) -> 0 | G12: =SUM(Retention!$E$7:$E$12) -> 15 | H12: =SUM(Retention!$F$7:$F$12) -> 0 | I12: =SUM(Retention!$G$7:$G$12) -> 14 | J12: =Retention!$D$15 -> 0 | L12: =Retention!$H$7 -> not yet | M12: =Retention!$H$8 -> not yet | N12: =Retention!$H$9 -> not yet | O12: =Retention!$H$10 -> not yet | P12: =Retention!$H$11 -> not yet | Q12: =Retention!$H$12 -> not yet
B13: Delivery | C13: Lifetime Value | D13: ='Lifetime Value'!$D$13 -> 0 | E13: ='Lifetime Value'!$D$14 -> 1 | F13: =SUM('Lifetime Value'!$D$7:$D$12) -> 0 | G13: =SUM('Lifetime Value'!$E$7:$E$12) -> 17 | H13: =SUM('Lifetime Value'!$F$7:$F$12) -> 0 | I13: =SUM('Lifetime Value'!$G$7:$G$12) -> 11 | J13: ='Lifetime Value'!$D$15 -> 0 | L13: ='Lifetime Value'!$H$7 -> not yet | M13: ='Lifetime Value'!$H$8 -> not yet | N13: ='Lifetime Value'!$H$9 -> not yet | O13: ='Lifetime Value'!$H$10 -> not yet | P13: ='Lifetime Value'!$H$11 -> not yet | Q13: ='Lifetime Value'!$H$12 -> not yet
B14: Delivery | C14: Branding | D14: =Branding!$D$13 -> 0 | E14: =Branding!$D$14 -> 1 | F14: =SUM(Branding!$D$7:$D$12) -> 0 | G14: =SUM(Branding!$E$7:$E$12) -> 15 | H14: =SUM(Branding!$F$7:$F$12) -> 0 | I14: =SUM(Branding!$G$7:$G$12) -> 13 | J14: =Branding!$D$15 -> 0 | L14: =Branding!$H$7 -> not yet | M14: =Branding!$H$8 -> not yet | N14: =Branding!$H$9 -> not yet | O14: =Branding!$H$10 -> not yet | P14: =Branding!$H$11 -> not yet | Q14: =Branding!$H$12 -> not yet
B15: Profit | C15: Price Raise | D15: ='Price Raise'!$D$13 -> 0 | E15: ='Price Raise'!$D$14 -> 1 | F15: =SUM('Price Raise'!$D$7:$D$12) -> 0 | G15: =SUM('Price Raise'!$E$7:$E$12) -> 15 | H15: =SUM('Price Raise'!$F$7:$F$12) -> 0 | I15: =SUM('Price Raise'!$G$7:$G$12) -> 12 | J15: ='Price Raise'!$D$15 -> 0 | L15: ='Price Raise'!$H$7 -> not yet | M15: ='Price Raise'!$H$8 -> not yet | N15: ='Price Raise'!$H$9 -> not yet | O15: ='Price Raise'!$H$10 -> not yet | P15: ='Price Raise'!$H$11 -> not yet | Q15: ='Price Raise'!$H$12 -> not yet
B16: Profit | C16: Promo Cash | D16: ='Promo Cash'!$D$13 -> 0 | E16: ='Promo Cash'!$D$14 -> 1 | F16: =SUM('Promo Cash'!$D$7:$D$12) -> 0 | G16: =SUM('Promo Cash'!$E$7:$E$12) -> 17 | H16: =SUM('Promo Cash'!$F$7:$F$12) -> 0 | I16: =SUM('Promo Cash'!$G$7:$G$12) -> 12 | J16: ='Promo Cash'!$D$15 -> 0 | L16: ='Promo Cash'!$H$7 -> not yet | M16: ='Promo Cash'!$H$8 -> not yet | N16: ='Promo Cash'!$H$9 -> not yet | O16: ='Promo Cash'!$H$10 -> not yet | P16: ='Promo Cash'!$H$11 -> not yet | Q16: ='Promo Cash'!$H$12 -> not yet
B17: Profit | C17: Implementation SOPs | D17: ='Implementation SOPs'!$D$13 -> 0 | E17: ='Implementation SOPs'!$D$14 -> 1 | F17: =SUM('Implementation SOPs'!$D$7:$D$12) -> 0 | G17: =SUM('Implementation SOPs'!$E$7:$E$12) -> 13 | H17: =SUM('Implementation SOPs'!$F$7:$F$12) -> 0 | I17: =SUM('Implementation SOPs'!$G$7:$G$12) -> 13 | J17: ='Implementation SOPs'!$D$15 -> 0 | L17: ='Implementation SOPs'!$H$7 -> not yet | M17: ='Implementation SOPs'!$H$8 -> not yet | N17: ='Implementation SOPs'!$H$9 -> not yet | O17: ='Implementation SOPs'!$H$10 -> not yet | P17: ='Implementation SOPs'!$H$11 -> not yet | Q17: ='Implementation SOPs'!$H$12 -> not yet
C18: All twelve | D18: =SUM(D6:D17) -> 0 | F18: =SUM(F6:F17) -> 0 | G18: =SUM(G6:G17) -> 203 | H18: =SUM(H6:H17) -> 0 | I18: =SUM(I6:I17) -> 165 | J18: =IF(SUM(G6:G17,I6:I17)=0,0,SUM(F6:F17,H6:H17)/SUM(G6:G17,I6:I17)) -> 0 | L18: =IF(COUNTIF(L6:L17,"done")=12,"ring lit",COUNTIF(L6:L17,"done")&" of 12") -> 0 of 12 | M18: =IF(COUNTIF(M6:M17,"done")=12,"ring lit",COUNTIF(M6:M17,"done")&" of 12") -> 0 of 12 | N18: =IF(COUNTIF(N6:N17,"done")=12,"ring lit",COUNTIF(N6:N17,"done")&" of 12") -> 0 of 12 | O18: =IF(COUNTIF(O6:O17,"done")=12,"ring lit",COUNTIF(O6:O17,"done")&" of 12") -> 0 of 12 | P18: =IF(COUNTIF(P6:P17,"done")=12,"ring lit",COUNTIF(P6:P17,"done")&" of 12") -> 0 of 12 | Q18: =IF(COUNTIF(Q6:Q17,"done")=12,"ring lit",COUNTIF(Q6:Q17,"done")&" of 12") -> 0 of 12
B20: Levels done | D20: =D18&" of 72" -> 0 of 72 | F20: A band is done when every yellow cell in it holds an answer and every checklist item is Y. A ring lights when all twelve playbooks have finished a band. Start with band 1 on every playbook before going deeper: the same rule as the SPARKS planets.
B21: Rings lit | D21: =COUNTIF(L18:Q18,"ring lit")&" of 6" -> 0 of 6
B22: Answers | D22: =F18&" of "&G18 -> 0 of 203
B24: Headline readings
B25: Reading | D25: Value | E25: Playbook | F25: Rule of thumb
B26: Leads needed per month | D26: =Readings!$C$62 -> not yet | E26: Marketing Machine | F26: Customers wanted over the close and booking rates
B27: Show rate (showed / booked) | D27: =Readings!$C$5 -> not yet | E27: Closing Handbook | F27: Seven of ten
B28: Close rate, before (bought / showed) | D28: =Readings!$C$6 -> not yet | E28: Closing Handbook
B29: Lifetime gross profit per customer | D29: =Readings!$C$98 -> not yet | E29: Lifetime Value
B30: Lifetime gross profit to cost of a customer | D30: =Readings!$C$100 -> not yet | E30: Lifetime Value | F30: Three to one
B31: Monthly churn, before | D31: =Readings!$C$111 -> not yet | E31: Retention
B32: Customers you can lose and break even | D32: =Readings!$C$150 -> not yet | E32: Price Raise | F32: Raise over margin plus raise
B33: Thirty-day ratio | D33: =Readings!$C$170 -> not yet | E33: Promo Cash | F33: Above one, growth pays for itself
B34: Cost per customer, before | D34: =Readings!$C$52 -> not yet | E34: GOATed Ads | F34: Against the lifetime gross profit
B35: Procedures someone else runs | D35: =Readings!$C$178 -> not yet | E35: Implementation SOPs

Sheet Lists
A1: machine_channel_now | B1: first_channel | C1: next_move | D1: hook_format | E1: hook_next | F1: magnet_type | G1: nurture_next | H1: closing_next | I1: proof_next | J1: ad_place | K1: ads_next | L1: ret_next | M1: ltv_lever_pick | N1: ltv_next | O1: brand_next | P1: grandfather | Q1: price_next | R1: attraction_type | S1: promo_next | T1: sops_next | U1: yesno
A2: Warm outreach: people who know me | B2: Warm outreach | C2: More: double the volume on the same channel | D2: A post | E2: The frame | F2: Reveal a problem they did not know they had: an audit, a score, a checklist | G2: Faster: cut the reply time in half | H2: Show rate: fix the reminders before the call | I2: Numbers: turn stories into results with figures | J2: Short video | K2: Hook: the click rate is low | L2: Onboarding: the first week | M2: More customers | N2: Raise the price (see Price Raise) | O2: Narrower: cut who it is for | P2: The old price for a set term | Q2: Raise again in a quarter | R2: Win your money back: a result earns a refund or a credit | S2: Raise the attraction offer's string | T2: Hand off one more procedure | U2: Y
A3: Content: posting for people who do not know me yet | B3: Content | C3: Better: fix the message, same volume | D3: An email subject line | E3: The who | F3: A sample or trial of the real thing | G3: More: add three touches | H3: Close rate: tighten the label and the overview | I3: Faces: get three on video | J3: Image and text | K3: Page: clicks do not become leads | L3: Cadence: the check-ins | M3: More per purchase | N3: Add the upsell (see Promo Cash) | O3: Louder: more touches | P3: The old price for as long as they stay | Q3: Hold: the loss was near breakeven | R3: Free with a string: free now, paid after, or a deposit | S3: Raise the upsell take rate | T3: Cut a number nobody uses | U3: N
A4: Cold outreach: contacting strangers | B4: Cold outreach | C4: New: add the next channel, keep this one running | D4: An ad | E4: The claim | F4: One step of a multi-step result: the first week, the first tool | G4: Better: change the magnet | H4: Cash rate: change the payment ask | I4: Reach: get third-party marks | J4: Long video | K4: Sales: leads do not become buyers (see Closing Handbook) | L4: Fit: stop selling to the ones who leave | M4: More purchases | N4: Cut churn (see Retention) | O4: Tighter: fix the off-brand touches | P4: Nothing: everyone moves on the same day | Q4: Add a higher tier above it | R4: Commit for a discount: a term for a lower price | S4: Add continuity | T4: Fix the one number that fell
A5: Paid ads | B5: Paid ads | D5: A video opener | E5: The format it runs in | G5: Reactivate: send the short check-in to the whole old list | H5: Handoff: write the script so someone else can run it | I5: Guarantee: back the biggest doubt with a promise | J5: Search text | K5: Scale: the ratio holds, spend more | L5: Winback: reactivate the ones who left | M5: A longer stay | N5: Cut the cost to acquire (see GOATed Ads, Marketing Machine) | O5: Bigger: stand beside a name they already trust | Q5: Add a lower entry below it (see Promo Cash) | R5: Giveaway: a prize that collects many leads | S5: Cut delivery cost in the first 30 days | T5: Hire for the biggest owner-only task
A6: None yet | D6: A direct message opener | R6: Decoy: a lesser option that makes the real one obvious

Sheet Readings
B1: Readings: every figure the binder earns, as live formulas
B2: Nothing here is typed. Each figure reads the facts on its playbook sheet and says "not yet" until they exist. Rules of thumb are rules of thumb, not findings.
B4: Sales: Closing Handbook
B5: Show rate (showed / booked) | C5: =IF(OR('Closing Handbook'!$D$31="",'Closing Handbook'!$D$30="",'Closing Handbook'!$D$30=0),"not yet",'Closing Handbook'!$D$31/'Closing Handbook'!$D$30) -> not yet | H5: Seven of ten is the rule of thumb to beat.
B6: Close rate, before (bought / showed) | C6: =IF(OR('Closing Handbook'!$D$32="",'Closing Handbook'!$D$31="",'Closing Handbook'!$D$31=0),"not yet",'Closing Handbook'!$D$32/'Closing Handbook'!$D$31) -> not yet
B7: Close rate, after the run | C7: =IF(OR('Closing Handbook'!$D$75="",'Closing Handbook'!$D$74="",'Closing Handbook'!$D$74=0),"not yet",'Closing Handbook'!$D$75/'Closing Handbook'!$D$74) -> not yet
B8: Cash collected per sale | C8: =IF(OR('Closing Handbook'!$D$33="",'Closing Handbook'!$D$32="",'Closing Handbook'!$D$32=0),"not yet",'Closing Handbook'!$D$33/'Closing Handbook'!$D$32) -> not yet | H8: Compare with the price in Lifetime Value.
B9: Share of the price collected at the close | C9: =IF(OR('Lifetime Value'!$D$29="",'Lifetime Value'!$D$29=0,$C$8="not yet"),"not yet",$C$8/'Lifetime Value'!$D$29) -> not yet
B10: The funnel, last month
B11: Step | C11: Count
B12: Booked | C12: ='Closing Handbook'!$D$30 -> 0
B13: Showed | C13: ='Closing Handbook'!$D$31 -> 0
B14: Bought | C14: ='Closing Handbook'!$D$32 -> 0
B15: Objections heard
B16: Objection | C16: Times heard | D16: Answered well
B17: =IF('Closing Handbook'!$C$79="","",'Closing Handbook'!$C$79) | C17: =IF('Closing Handbook'!$D$79="","",'Closing Handbook'!$D$79) | D17: =IF('Closing Handbook'!$E$79="","",'Closing Handbook'!$E$79)
B18: =IF('Closing Handbook'!$C$80="","",'Closing Handbook'!$C$80) | C18: =IF('Closing Handbook'!$D$80="","",'Closing Handbook'!$D$80) | D18: =IF('Closing Handbook'!$E$80="","",'Closing Handbook'!$E$80)
B19: =IF('Closing Handbook'!$C$81="","",'Closing Handbook'!$C$81) | C19: =IF('Closing Handbook'!$D$81="","",'Closing Handbook'!$D$81) | D19: =IF('Closing Handbook'!$E$81="","",'Closing Handbook'!$E$81)
B20: =IF('Closing Handbook'!$C$82="","",'Closing Handbook'!$C$82) | C20: =IF('Closing Handbook'!$D$82="","",'Closing Handbook'!$D$82) | D20: =IF('Closing Handbook'!$E$82="","",'Closing Handbook'!$E$82)
B21: =IF('Closing Handbook'!$C$83="","",'Closing Handbook'!$C$83) | C21: =IF('Closing Handbook'!$D$83="","",'Closing Handbook'!$D$83) | D21: =IF('Closing Handbook'!$E$83="","",'Closing Handbook'!$E$83)
B22: =IF('Closing Handbook'!$C$84="","",'Closing Handbook'!$C$84) | C22: =IF('Closing Handbook'!$D$84="","",'Closing Handbook'!$D$84) | D22: =IF('Closing Handbook'!$E$84="","",'Closing Handbook'!$E$84)
B23: =IF('Closing Handbook'!$C$85="","",'Closing Handbook'!$C$85) | C23: =IF('Closing Handbook'!$D$85="","",'Closing Handbook'!$D$85) | D23: =IF('Closing Handbook'!$E$85="","",'Closing Handbook'!$E$85)
B24: =IF('Closing Handbook'!$C$86="","",'Closing Handbook'!$C$86) | C24: =IF('Closing Handbook'!$D$86="","",'Closing Handbook'!$D$86) | D24: =IF('Closing Handbook'!$E$86="","",'Closing Handbook'!$E$86)
B26: Sales: Proof Checklist
B27: Proof by kind
B28: Kind | C28: Count
B29: Results with a number | C29: ='Proof Checklist'!$D$30 -> 0
B30: Named testimonials | C30: ='Proof Checklist'!$D$31 -> 0
B31: Before and after | C31: ='Proof Checklist'!$D$32 -> 0
B32: Third-party marks | C32: ='Proof Checklist'!$D$33 -> 0
B33: Demonstrations | C33: ='Proof Checklist'!$D$34 -> 0
B34: Claims listed | C34: =IF('Proof Checklist'!$D$42="",0,LEN('Proof Checklist'!$D$42)-LEN(SUBSTITUTE('Proof Checklist'!$D$42,CHAR(10),""))+1) -> 0
B35: Claims with a proof beside them | C35: =COUNTIFS('Proof Checklist'!$D$63:$D$70,"<>",'Proof Checklist'!$D$63:$D$70,"<>cut") -> 0 | H35: Rows of the proof map whose second column is filled and is not the word cut.
B36: Coverage (claims with proof / claims) | C36: =IF($C$34=0,"not yet",MIN(1,$C$35/$C$34)) -> not yet
B37: Testimonials per 100 customers | C37: =IF(OR('Proof Checklist'!$D$31="",'Proof Checklist'!$D$35="",'Proof Checklist'!$D$35=0),"not yet",'Proof Checklist'!$D$31/'Proof Checklist'!$D$35*100) -> not yet
B38: Asks that came back | C38: =IF(OR('Proof Checklist'!$D$83="",'Proof Checklist'!$D$82="",'Proof Checklist'!$D$82=0),"not yet",'Proof Checklist'!$D$83/'Proof Checklist'!$D$82) -> not yet
B40: Sales: GOATed Ads
B41: The ad chain, last month
B42: Step | C42: Count
B43: Shown | C43: ='GOATed Ads'!$D$31 -> 0
B44: Clicked | C44: ='GOATed Ads'!$D$32 -> 0
B45: Leads | C45: ='GOATed Ads'!$D$33 -> 0
B46: Booked | C46: ='GOATed Ads'!$D$34 -> 0
B47: Bought | C47: ='GOATed Ads'!$D$35 -> 0
B48: Cost per thousand shown | C48: =IF(OR('GOATed Ads'!$D$30="",'GOATed Ads'!$D$31="",'GOATed Ads'!$D$31=0),"not yet",'GOATed Ads'!$D$30/'GOATed Ads'!$D$31*1000) -> not yet
B49: Click rate | C49: =IF(OR('GOATed Ads'!$D$32="",'GOATed Ads'!$D$31="",'GOATed Ads'!$D$31=0),"not yet",'GOATed Ads'!$D$32/'GOATed Ads'!$D$31) -> not yet
B50: Cost per lead, before | C50: =IF(OR('GOATed Ads'!$D$30="",'GOATed Ads'!$D$33="",'GOATed Ads'!$D$33=0),"not yet",'GOATed Ads'!$D$30/'GOATed Ads'!$D$33) -> not yet
B51: Cost per lead, after the run | C51: =IF(OR('GOATed Ads'!$D$65="",'GOATed Ads'!$D$68="",'GOATed Ads'!$D$68=0),"not yet",'GOATed Ads'!$D$65/'GOATed Ads'!$D$68) -> not yet
B52: Cost per customer, before | C52: =IF(OR('GOATed Ads'!$D$30="",'GOATed Ads'!$D$35="",'GOATed Ads'!$D$35=0),"not yet",'GOATed Ads'!$D$30/'GOATed Ads'!$D$35) -> not yet
B53: Cost per customer, after the run | C53: =IF(OR('GOATed Ads'!$D$65="",'GOATed Ads'!$D$69="",'GOATed Ads'!$D$69=0),"not yet",'GOATed Ads'!$D$65/'GOATed Ads'!$D$69) -> not yet
B55: Leads: Marketing Machine
B56: The four ways, per week
B57: Way | C57: Per week
B58: Warm outreach | C58: ='Marketing Machine'!$D$31 -> 0
B59: Content | C59: ='Marketing Machine'!$D$32 -> 0
B60: Cold outreach | C60: ='Marketing Machine'!$D$33 -> 0
B61: Paid ads ($) | C61: ='Marketing Machine'!$D$34 -> 0
B62: Leads needed per month | C62: =IF(OR('Marketing Machine'!$D$36="",$C$6="not yet",'Lead Nurture'!$D$32="",'Lead Nurture'!$D$32=0,$C$6=0),"not yet",'Marketing Machine'!$D$36/$C$6/'Lead Nurture'!$D$32) -> not yet | H62: Customers wanted, divided by the close rate (Closing Handbook) and the booking rate (Lead Nurture).
B63: Leads you have per month | C63: =IF('Marketing Machine'!$D$35="","not yet",'Marketing Machine'!$D$35) -> not yet
B64: Leads per hundred contacts, before | C64: =IF(OR('Marketing Machine'!$D$31="",'Marketing Machine'!$D$32="",'Marketing Machine'!$D$33="",'Marketing Machine'!$D$35="",('Marketing Machine'!$D$31+'Marketing Machine'!$D$32+'Marketing Machine'!$D$33)*4.33=0),"not yet",'Marketing Machine'!$D$35/(('Marketing Machine'!$D$31+'Marketing Machine'!$D$32+'Marketing Machine'!$D$33)*4.33)) -> not yet
B65: Leads per hundred contacts, after the run | C65: =IF(OR('Marketing Machine'!$D$68="",'Marketing Machine'!$D$67="",'Marketing Machine'!$D$67=0),"not yet",'Marketing Machine'!$D$68/'Marketing Machine'!$D$67) -> not yet
B67: Leads: Hooks
B68: Hook rate, before (engaged / views) | C68: =IF(OR(Hooks!$D$31="",Hooks!$D$30="",Hooks!$D$30=0),"not yet",Hooks!$D$31/Hooks!$D$30) -> not yet
B69: Hook rate, after the run | C69: =IF(OR(Hooks!$D$62="",Hooks!$D$61="",Hooks!$D$61=0),"not yet",Hooks!$D$62/Hooks!$D$61) -> not yet
B70: The three hooks, by count
B71: Hook | C71: Count
B72: =IF(Hooks!$C$65="","",Hooks!$C$65) | C72: =IF(Hooks!$D$65="","",Hooks!$D$65)
B73: =IF(Hooks!$C$66="","",Hooks!$C$66) | C73: =IF(Hooks!$D$66="","",Hooks!$D$66)
B74: =IF(Hooks!$C$67="","",Hooks!$C$67) | C74: =IF(Hooks!$D$67="","",Hooks!$D$67)
B75: =IF(Hooks!$C$68="","",Hooks!$C$68) | C75: =IF(Hooks!$D$68="","",Hooks!$D$68)
B76: =IF(Hooks!$C$69="","",Hooks!$C$69) | C76: =IF(Hooks!$D$69="","",Hooks!$D$69)
B77: =IF(Hooks!$C$70="","",Hooks!$C$70) | C77: =IF(Hooks!$D$70="","",Hooks!$D$70)
B78: =IF(Hooks!$C$71="","",Hooks!$C$71) | C78: =IF(Hooks!$D$71="","",Hooks!$D$71)
B79: =IF(Hooks!$C$72="","",Hooks!$C$72) | C79: =IF(Hooks!$D$72="","",Hooks!$D$72)
B81: Leads: Lead Nurture
B82: Minutes to first reply, before | C82: =IF('Lead Nurture'!$D$30="","not yet",'Lead Nurture'!$D$30) -> not yet | H82: Five minutes is the rule of thumb.
B83: Minutes to first reply, after the run | C83: =IF('Lead Nurture'!$D$65="","not yet",'Lead Nurture'!$D$65) -> not yet
B84: Leads who book, before | C84: =IF('Lead Nurture'!$D$32="","not yet",'Lead Nurture'!$D$32) -> not yet
B85: Leads who book, after the run | C85: =IF(OR('Lead Nurture'!$D$64="",'Lead Nurture'!$D$63="",'Lead Nurture'!$D$63=0),"not yet",'Lead Nurture'!$D$64/'Lead Nurture'!$D$63) -> not yet
B86: Replies by touch
B87: Touch | C87: Sent | D87: Replied | E87: Share
B88: =IF('Lead Nurture'!$C$68="","",'Lead Nurture'!$C$68) | C88: =IF('Lead Nurture'!$D$68="","",'Lead Nurture'!$D$68) | D88: =IF('Lead Nurture'!$E$68="","",'Lead Nurture'!$E$68) | E88: =IF(OR(C88="",C88=0),"",D88/C88)
B89: =IF('Lead Nurture'!$C$69="","",'Lead Nurture'!$C$69) | C89: =IF('Lead Nurture'!$D$69="","",'Lead Nurture'!$D$69) | D89: =IF('Lead Nurture'!$E$69="","",'Lead Nurture'!$E$69) | E89: =IF(OR(C89="",C89=0),"",D89/C89)
B90: =IF('Lead Nurture'!$C$70="","",'Lead Nurture'!$C$70) | C90: =IF('Lead Nurture'!$D$70="","",'Lead Nurture'!$D$70) | D90: =IF('Lead Nurture'!$E$70="","",'Lead Nurture'!$E$70) | E90: =IF(OR(C90="",C90=0),"",D90/C90)
B91: =IF('Lead Nurture'!$C$71="","",'Lead Nurture'!$C$71) | C91: =IF('Lead Nurture'!$D$71="","",'Lead Nurture'!$D$71) | D91: =IF('Lead Nurture'!$E$71="","",'Lead Nurture'!$E$71) | E91: =IF(OR(C91="",C91=0),"",D91/C91)
B92: =IF('Lead Nurture'!$C$72="","",'Lead Nurture'!$C$72) | C92: =IF('Lead Nurture'!$D$72="","",'Lead Nurture'!$D$72) | D92: =IF('Lead Nurture'!$E$72="","",'Lead Nurture'!$E$72) | E92: =IF(OR(C92="",C92=0),"",D92/C92)
B93: =IF('Lead Nurture'!$C$73="","",'Lead Nurture'!$C$73) | C93: =IF('Lead Nurture'!$D$73="","",'Lead Nurture'!$D$73) | D93: =IF('Lead Nurture'!$E$73="","",'Lead Nurture'!$E$73) | E93: =IF(OR(C93="",C93=0),"",D93/C93)
B94: =IF('Lead Nurture'!$C$74="","",'Lead Nurture'!$C$74) | C94: =IF('Lead Nurture'!$D$74="","",'Lead Nurture'!$D$74) | D94: =IF('Lead Nurture'!$E$74="","",'Lead Nurture'!$E$74) | E94: =IF(OR(C94="",C94=0),"",D94/C94)
B95: =IF('Lead Nurture'!$C$75="","",'Lead Nurture'!$C$75) | C95: =IF('Lead Nurture'!$D$75="","",'Lead Nurture'!$D$75) | D95: =IF('Lead Nurture'!$E$75="","",'Lead Nurture'!$E$75) | E95: =IF(OR(C95="",C95=0),"",D95/C95)
B97: Delivery: Lifetime Value
B98: Lifetime gross profit per customer | C98: =IF(OR('Lifetime Value'!$D$29="",'Lifetime Value'!$D$30="",'Lifetime Value'!$D$31=""),"not yet",'Lifetime Value'!$D$29*'Lifetime Value'!$D$30*'Lifetime Value'!$D$31) -> not yet | H98: Price, times gross margin, times purchases over the stay.
B99: Lifetime gross profit, after the quarter | C99: =IF(OR('Lifetime Value'!$D$61="",'Lifetime Value'!$D$62="",'Lifetime Value'!$D$63=""),"not yet",'Lifetime Value'!$D$61*'Lifetime Value'!$D$62*'Lifetime Value'!$D$63) -> not yet
B100: Lifetime gross profit to cost of a customer | C100: =IF(OR($C$98="not yet",'Lifetime Value'!$D$32="",'Lifetime Value'!$D$32=0),"not yet",$C$98/'Lifetime Value'!$D$32) -> not yet | H100: Three to one is the rule of thumb. Below one, every customer loses money.
B101: The same ratio, after the quarter | C101: =IF(OR($C$99="not yet",'Lifetime Value'!$D$64="",'Lifetime Value'!$D$64=0),"not yet",$C$99/'Lifetime Value'!$D$64) -> not yet
B102: A hundred customers, levers pulled at ten percent each
B103: Levers pulled | C103: Gross profit
B104: Today | C104: =IF($C$98="not yet",0,$C$98*100*1.1^0) -> 0
B105: 1 lever | C105: =IF($C$98="not yet",0,$C$98*100*1.1^1) -> 0
B106: 2 levers | C106: =IF($C$98="not yet",0,$C$98*100*1.1^2) -> 0
B107: 3 levers | C107: =IF($C$98="not yet",0,$C$98*100*1.1^3) -> 0
...

Sheet Marketing Machine
C1: Marketing Machine | D1: Leads system
C2: Four ways to let people know you exist, and how much of each you need.
C3: Advertising is letting people know about the thing you sell. There are only four ways to do it: reach out to people who already know you, post content for people who do not know you yet, reach out cold to strangers, and pay to put your message in front of them. Anyone else who gets you leads is doing one of those four on your behalf. The machine is the amount of each you do every day, on purpose, counted.
C5: Where you stand on this planet
B6: # | C6: Band | D6: Answered | E6: Of | F6: Ticked | G6: Of | H6: Status
B7: 1 | C7: Read: The one idea, and where you stand on it today | D7: =SUMIFS($E$19:$E$400,$A$19:$A$400,B7,$B$19:$B$400,"exercise") -> 0 | E7: =COUNTIFS($A$19:$A$400,B7,$B$19:$B$400,"exercise") -> 3 | F7: =SUMIFS($E$19:$E$400,$A$19:$A$400,B7,$B$19:$B$400,"check") -> 0 | G7: =COUNTIFS($A$19:$A$400,B7,$B$19:$B$400,"check") -> 2 | H7: =IF(AND(D7=E7,F7=G7),"done",IF(D7+F7>0,"started","not yet")) -> not yet | I7: =IF(H7="done",99,B7) -> 1
B8: 2 | C8: Facts: The few numbers this playbook runs on | D8: =SUMIFS($E$19:$E$400,$A$19:$A$400,B8,$B$19:$B$400,"exercise") -> 0 | E8: =COUNTIFS($A$19:$A$400,B8,$B$19:$B$400,"exercise") -> 6 | F8: =SUMIFS($E$19:$E$400,$A$19:$A$400,B8,$B$19:$B$400,"check") -> 0 | G8: =COUNTIFS($A$19:$A$400,B8,$B$19:$B$400,"check") -> 1 | H8: =IF(AND(D8=E8,F8=G8),"done",IF(D8+F8>0,"started","not yet")) -> not yet | I8: =IF(H8="done",99,B8) -> 2
B9: 3 | C9: Exercises: The pen and paper work the playbook asks for | D9: =SUMIFS($E$19:$E$400,$A$19:$A$400,B9,$B$19:$B$400,"exercise") -> 0 | E9: =COUNTIFS($A$19:$A$400,B9,$B$19:$B$400,"exercise") -> 4 | F9: =SUMIFS($E$19:$E$400,$A$19:$A$400,B9,$B$19:$B$400,"check") -> 0 | G9: =COUNTIFS($A$19:$A$400,B9,$B$19:$B$400,"check") -> 2 | H9: =IF(AND(D9=E9,F9=G9),"done",IF(D9+F9>0,"started","not yet")) -> not yet | I9: =IF(H9="done",99,B9) -> 3
B10: 4 | C10: Build: Assemble the thing you will use, and tick it off | D10: =SUMIFS($E$19:$E$400,$A$19:$A$400,B10,$B$19:$B$400,"exercise") -> 0 | E10: =COUNTIFS($A$19:$A$400,B10,$B$19:$B$400,"exercise") -> 2 | F10: =SUMIFS($E$19:$E$400,$A$19:$A$400,B10,$B$19:$B$400,"check") -> 0 | G10: =COUNTIFS($A$19:$A$400,B10,$B$19:$B$400,"check") -> 5 | H10: =IF(AND(D10=E10,F10=G10),"done",IF(D10+F10>0,"started","not yet")) -> not yet | I10: =IF(H10="done",99,B10) -> 4
B11: 5 | C11: Run: Use it for a stretch and log what happened | D11: =SUMIFS($E$19:$E$400,$A$19:$A$400,B11,$B$19:$B$400,"exercise") -> 0 | E11: =COUNTIFS($A$19:$A$400,B11,$B$19:$B$400,"exercise") -> 4 | F11: =SUMIFS($E$19:$E$400,$A$19:$A$400,B11,$B$19:$B$400,"check") -> 0 | G11: =COUNTIFS($A$19:$A$400,B11,$B$19:$B$400,"check") -> 1 | H11: =IF(AND(D11=E11,F11=G11),"done",IF(D11+F11>0,"started","not yet")) -> not yet | I11: =IF(H11="done",99,B11) -> 5
B12: 6 | C12: Sharpen: The moves only visible once the numbers are real | D12: =SUMIFS($E$19:$E$400,$A$19:$A$400,B12,$B$19:$B$400,"exercise") -> 0 | E12: =COUNTIFS($A$19:$A$400,B12,$B$19:$B$400,"exercise") -> 2 | F12: =SUMIFS($E$19:$E$400,$A$19:$A$400,B12,$B$19:$B$400,"check") -> 0 | G12: =COUNTIFS($A$19:$A$400,B12,$B$19:$B$400,"check") -> 3 | H12: =IF(AND(D12=E12,F12=G12),"done",IF(D12+F12>0,"started","not yet")) -> not yet | I12: =IF(H12="done",99,B12) -> 6
C13: Levels done | D13: =COUNTIF(H7:H12,"done") -> 0 | F13: Yellow cells are yours to fill. A band is done when every yellow cell in it holds an answer and every checklist item is Y.
C14: Working on band | D14: =IF(MIN(I7:I12)=99,"complete",MIN(I7:I12)) -> 1
C15: Share of this planet answered | D15: =IF(SUM(E7:E12,G7:G12)=0,0,SUM(D7:D12,F7:F12)/SUM(E7:E12,G7:G12)) -> 0
A18: Band | B18: Kind | C18: Exercise or step | D18: Your answer | E18: ✓ | F18: Example | G18: What counts, where to look
A19: 1 | B19: band | C19: Band 1 · Read · reveal · about 6 min: The four ways, and what you do now
B20: why | C20: Most lead problems are volume problems wearing a strategy costume. Before choosing anything, write down what actually happened last week.
A21: 1 | B21: exercise | C21: How steady is your lead flow, 1 to 5 | E21: =IF(D21<>"",1,0) -> 0 | F21: 2 | G21: One is not at all, five is fully. Your honest read today.
A22: 1 | B22: exercise | C22: What you did last week to get leads, literally | E22: =IF(D22<>"",1,0) -> 0 | F22: About thirty warm messages, five posts, twenty cold DMs. No ads worth counting. | G22: How many messages, how many posts, how many cold contacts, how many dollars. Count, do not describe.
A23: 1 | B23: exercise | C23: The channel that brings most of your leads today | E23: =IF(D23<>"",1,0) -> 0 | F23: Warm outreach: people who know me | G23: Pick one from the dropdown.
B24: head | C24: Checklist
A25: 1 | B25: check | C25: ☐ I can name the four ways to get leads without looking | E25: =IF(D25="Y",1,0) -> 0 | G25: Y when it is true.
A26: 1 | B26: check | C26: ☐ I wrote what I actually did last week, not what I meant to do | E26: =IF(D26="Y",1,0) -> 0 | G26: Y when it is true.
B27: checkpoint | C27: When this band is done: The planet shows where you start and the four ways are named.
A29: 2 | B29: band | C29: Band 2 · Facts · reveal · about 8 min: The weekly counts
B30: why | C30: A machine has dials. These are the dials: how much of each way you do in a normal week, and how many people raise a hand because of it.
A31: 2 | B31: exercise | C31: Warm reach-outs per week | E31: =IF(D31<>"",1,0) -> 0 | F31: 30 | G31: Messages to people who already know you: contacts, followers, past customers.
A32: 2 | B32: exercise | C32: Pieces of content per week | E32: =IF(D32<>"",1,0) -> 0 | F32: 5 | G32: Posts, emails, videos: anything for people who do not know you yet.
A33: 2 | B33: exercise | C33: Cold contacts per week | E33: =IF(D33<>"",1,0) -> 0 | F33: 20 | G33: Strangers you reached out to first: calls, DMs, emails, doors.
A34: 2 | B34: exercise | C34: Ad spend per week | E34: =IF(D34<>"",1,0) -> 0 | F34: 100 | G34: Dollars paid for attention. Zero is a number; leave it blank if you do not know. Whole dollars.
A35: 2 | B35: exercise | C35: Engaged leads per month | E35: =IF(D35<>"",1,0) -> 0 | F35: 25 | G35: People who replied, booked, or opted in. A view is not a lead.
A36: 2 | B36: exercise | C36: New customers you want per month | E36: =IF(D36<>"",1,0) -> 0 | F36: 8 | G36: The target the machine has to produce.
B37: head | C37: Checklist
A38: 2 | B38: check | C38: ☐ Every count comes from a log, a sent folder or a receipt, not from memory | E38: =IF(D38="Y",1,0) -> 0 | G38: Y when it is true.
B39: checkpoint | C39: When this band is done: The machine mix draws, and the leads-needed figure computes once Closing and Lead Nurture have their rates.
A41: 3 | B41: band | C41: Band 3 · Exercises · reveal · about 25 min: The warm list, the topics, the cold sources
B42: why | C42: Warm outreach is the cheapest lead you will ever get, and almost nobody does it fully. Content starts with questions you already get asked. Cold outreach starts with a list that already exists somewhere.
A43: 3 | B43: exercise | C43: Your warm list, one name a line | E43: =IF(D43<>"",1,0) -> 0 | F43: Jordan (old colleague) Sam (gym) Priya (newsletter reply) Alex (cousin) Dev (podcast guest) | G43: Everyone who has your number, follows you, or has emailed you. Aim for 100. Stop when you run out, not when you get bored. One a line: Alt+Enter starts a new line inside the cell.
A44: 3 | B44: exercise | C44: Ten things a customer asked you this month, one a line | E44: =IF(D44<>"",1,0) -> 0 | F44: Should I pay off the loan or invest? How much emergency fund is enough? Is my 401k match worth it? | G44: Each is a piece of content. Their question is the hook. One a line: Alt+Enter starts a new line inside the cell.
A45: 3 | B45: exercise | C45: Three places a list of your strangers already exists | E45: =IF(D45<>"",1,0) -> 0 | G45: A directory, a group, a conference list, a public register. One a line: Alt+Enter starts a new line inside the cell.
A46: 3 | B46: exercise | C46: The one channel you will max out first | E46: =IF(D46<>"",1,0) -> 0 | G46: One. The rule is: max one channel before adding the next. Pick one from the dropdown.
B47: head | C47: Checklist
A48: 3 | B48: check | C48: ☐ The warm list is every name I have, not a sample | E48: =IF(D48="Y",1,0) -> 0 | G48: Y when it is true.
A49: 3 | B49: check | C49: ☐ The ten topics are real questions, in the words they were asked | E49: =IF(D49="Y",1,0) -> 0 | G49: Y when it is true.
B50: checkpoint | C50: When this band is done: Three lists exist and one channel is chosen.
A52: 4 | B52: band | C52: Band 4 · Build · power · about 10 min: The daily minimum
B53: why | C53: A number you hit every day beats a plan you admire. Write the minimum as counts per day, then put someone in charge of it, even if that someone is you on Friday.
A54: 4 | B54: exercise | C54: Your daily advertising minimum | E54: =IF(D54<>"",1,0) -> 0 | G54: Per day: how many warm messages, how many pieces of content, how many cold contacts, how many ad dollars. Small and daily beats big and monthly.
A55: 4 | B55: exercise | C55: Where the daily count is logged | E55: =IF(D55<>"",1,0) -> 0 | G55: A sheet, a note, a wall. It has to exist before day one.
B56: head | C56: Checklist
A57: 4 | B57: check | C57: ☐ A place to log every day's count exists | E57: =IF(D57="Y",1,0) -> 0 | G57: Y when it is true.
A58: 4 | B58: check | C58: ☐ The warm list has 100 names or every name I have | E58: =IF(D58="Y",1,0) -> 0 | G58: Y when it is true.
A59: 4 | B59: check | C59: ☐ The first channel has a daily number attached | E59: =IF(D59="Y",1,0) -> 0 | G59: Y when it is true.
A60: 4 | B60: check | C60: ☐ Someone is accountable for the number by Friday, even if it is me | E60: =IF(D60="Y",1,0) -> 0 | G60: Y when it is true.
A61: 4 | B61: check | C61: ☐ The minimum is small enough to hit on a bad day | E61: =IF(D61="Y",1,0) -> 0 | G61: Y when it is true.
B62: checkpoint | C62: When this band is done: The plan is written and the log is ready.
A64: 5 | B64: band | C64: Band 5 · Run · certainty · about 15 min: Run it for two weeks
B65: why | C65: Now the machine gets numbers of its own. Count reach and count leads. The ratio between them is the first honest reading of your message.
A66: 5 | B66: exercise | C66: Days you ran the daily minimum | E66: =IF(D66<>"",1,0) -> 0
A67: 5 | B67: exercise | C67: Contacts made in the run | E67: =IF(D67<>"",1,0) -> 0 | G67: Every warm message, post, cold contact and thousand ad views, all counted as one each.
A68: 5 | B68: exercise | C68: Engaged leads from the run | E68: =IF(D68<>"",1,0) -> 0 | G68: Replied, booked or opted in.
A69: 5 | B69: exercise | C69: Days the minimum was actually hit | E69: =IF(D69<>"",1,0) -> 0
B70: head | C70: Checklist
A71: 5 | B71: check | C71: ☐ The daily minimum was hit at least four days in five | E71: =IF(D71="Y",1,0) -> 0 | G71: Y when it is true.
B72: checkpoint | C72: When this band is done: Your lead rate shows beside the rate you had before.
A74: 6 | B74: band | C74: Band 6 · Sharpen · power · about 10 min: More, better, new
B75: why | C75: When the machine works a little, the temptation is to add a channel. The rule is: more of the same first, then better, then new. Lead getters (customers who refer, employees, agencies, affiliates) are the four ways done by other people.
A76: 6 | B76: exercise | C76: The next move | E76: =IF(D76<>"",1,0) -> 0 | G76: Take More unless volume is truly maxed. Take New last. Pick one from the dropdown.
A77: 6 | B77: exercise | C77: One person for each lead getter that applies | E77: =IF(D77<>"",1,0) -> 0 | G77: A past customer who would refer, an employee who could do outreach, an agency, an affiliate. Name a real person or write none. One a line: Alt+Enter starts a new line inside the cell.
B78: head | C78: Checklist
A79: 6 | B79: check | C79: ☐ I doubled the volume before I changed the channel | E79: =IF(D79="Y",1,0) -> 0 | G79: Y when it is true.
A80: 6 | B80: check | C80: ☐ A referral ask is written into the delivery (see Retention) | E80: =IF(D80="Y",1,0) -> 0 | G80: Y when it is true.
A81: 6 | B81: check | C81: ☐ The weekly counts are on the scorecard (see Implementation SOPs) | E81: =IF(D81="Y",1,0) -> 0 | G81: Y when it is true.
B82: checkpoint | C82: When this band is done: The next move is decided and a lead getter is named.

Sheet Hooks
C1: Hooks | D1: Leads system
C2: The first line earns the second. Nothing you make gets read without one.
C3: A hook is the part of a message people see before they decide whether to keep going: the headline, the first sentence, the first second of a video, the subject line. Most attention is lost right there. The work is not to write one good hook and hope. It is to write many, score them, run the best few, and keep the winners in a bank you draw on for years.
C5: Where you stand on this planet
B6: # | C6: Band | D6: Answered | E6: Of | F6: Ticked | G6: Of | H6: Status
B7: 1 | C7: Read: The one idea, and where you stand on it today | D7: =SUMIFS($E$19:$E$400,$A$19:$A$400,B7,$B$19:$B$400,"exercise") -> 0 | E7: =COUNTIFS($A$19:$A$400,B7,$B$19:$B$400,"exercise") -> 2 | F7: =SUMIFS($E$19:$E$400,$A$19:$A$400,B7,$B$19:$B$400,"check") -> 0 | G7: =COUNTIFS($A$19:$A$400,B7,$B$19:$B$400,"check") -> 2 | H7: =IF(AND(D7=E7,F7=G7),"done",IF(D7+F7>0,"started","not yet")) -> not yet | I7: =IF(H7="done",99,B7) -> 1
B8: 2 | C8: Facts: The few numbers this playbook runs on | D8: =SUMIFS($E$19:$E$400,$A$19:$A$400,B8,$B$19:$B$400,"exercise") -> 0 | E8: =COUNTIFS($A$19:$A$400,B8,$B$19:$B$400,"exercise") -> 3 | F8: =SUMIFS($E$19:$E$400,$A$19:$A$400,B8,$B$19:$B$400,"check") -> 0 | G8: =COUNTIFS($A$19:$A$400,B8,$B$19:$B$400,"check") -> 1 | H8: =IF(AND(D8=E8,F8=G8),"done",IF(D8+F8>0,"started","not yet")) -> not yet | I8: =IF(H8="done",99,B8) -> 2
B9: 3 | C9: Exercises: The pen and paper work the playbook asks for | D9: =SUMIFS($E$19:$E$400,$A$19:$A$400,B9,$B$19:$B$400,"exercise") -> 0 | E9: =COUNTIFS($A$19:$A$400,B9,$B$19:$B$400,"exercise") -> 3 | F9: =SUMIFS($E$19:$E$400,$A$19:$A$400,B9,$B$19:$B$400,"check") -> 0 | G9: =COUNTIFS($A$19:$A$400,B9,$B$19:$B$400,"check") -> 3 | H9: =IF(AND(D9=E9,F9=G9),"done",IF(D9+F9>0,"started","not yet")) -> not yet | I9: =IF(H9="done",99,B9) -> 3
B10: 4 | C10: Build: Assemble the thing you will use, and tick it off | D10: =SUMIFS($E$19:$E$400,$A$19:$A$400,B10,$B$19:$B$400,"exercise") -> 0 | E10: =COUNTIFS($A$19:$A$400,B10,$B$19:$B$400,"exercise") -> 2 | F10: =SUMIFS($E$19:$E$400,$A$19:$A$400,B10,$B$19:$B$400,"check") -> 0 | G10: =COUNTIFS($A$19:$A$400,B10,$B$19:$B$400,"check") -> 4 | H10: =IF(AND(D10=E10,F10=G10),"done",IF(D10+F10>0,"started","not yet")) -> not yet | I10: =IF(H10="done",99,B10) -> 4
B11: 5 | C11: Run: Use it for a stretch and log what happened | D11: =SUMIFS($E$19:$E$400,$A$19:$A$400,B11,$B$19:$B$400,"exercise") -> 0 | E11: =COUNTIFS($A$19:$A$400,B11,$B$19:$B$400,"exercise") -> 3 | F11: =SUMIFS($E$19:$E$400,$A$19:$A$400,B11,$B$19:$B$400,"check") -> 0 | G11: =COUNTIFS($A$19:$A$400,B11,$B$19:$B$400,"check") -> 1 | H11: =IF(AND(D11=E11,F11=G11),"done",IF(D11+F11>0,"started","not yet")) -> not yet | I11: =IF(H11="done",99,B11) -> 5
B12: 6 | C12: Sharpen: The moves only visible once the numbers are real | D12: =SUMIFS($E$19:$E$400,$A$19:$A$400,B12,$B$19:$B$400,"exercise") -> 0 | E12: =COUNTIFS($A$19:$A$400,B12,$B$19:$B$400,"exercise") -> 2 | F12: =SUMIFS($E$19:$E$400,$A$19:$A$400,B12,$B$19:$B$400,"check") -> 0 | G12: =COUNTIFS($A$19:$A$400,B12,$B$19:$B$400,"check") -> 3 | H12: =IF(AND(D12=E12,F12=G12),"done",IF(D12+F12>0,"started","not yet")) -> not yet | I12: =IF(H12="done",99,B12) -> 6
C13: Levels done | D13: =COUNTIF(H7:H12,"done") -> 0 | F13: Yellow cells are yours to fill. A band is done when every yellow cell in it holds an answer and every checklist item is Y.
C14: Working on band | D14: =IF(MIN(I7:I12)=99,"complete",MIN(I7:I12)) -> 1
C15: Share of this planet answered | D15: =IF(SUM(E7:E12,G7:G12)=0,0,SUM(D7:D12,F7:F12)/SUM(E7:E12,G7:G12)) -> 0
A18: Band | B18: Kind | C18: Exercise or step | D18: Your answer | E18: ✓ | F18: Example | G18: What counts, where to look
A19: 1 | B19: band | C19: Band 1 · Read · reveal · about 5 min: Read your last three first lines as a stranger
B20: why | C20: You cannot fix what you have not looked at. Pull up the last three things you sent or posted and read only the first line of each.
A21: 1 | B21: exercise | C21: How often does what you post or send get a reply or a click, 1 to 5 | E21: =IF(D21<>"",1,0) -> 0 | F21: 2 | G21: One is not at all, five is fully. Your honest read today.
A22: 1 | B22: exercise | C22: Your last three hooks, pasted in | E22: =IF(D22<>"",1,0) -> 0 | G22: The headline, the first line, the subject line. As they were, not as you would fix them.
B23: head | C23: Checklist
A24: 1 | B24: check | C24: ☐ I read my last three first lines as a stranger would | E24: =IF(D24="Y",1,0) -> 0 | G24: Y when it is true.
A25: 1 | B25: check | C25: ☐ I can say who each one was for | E25: =IF(D25="Y",1,0) -> 0 | G25: Y when it is true.
B26: checkpoint | C26: When this band is done: Your starting point on the planet is set.
A28: 2 | B28: band | C28: Band 2 · Facts · reveal · about 5 min: Last week's attention
B29: why | C29: Two counts turn a feeling into a rate: how many people saw the first line, and how many did anything after it.
A30: 2 | B30: exercise | C30: Views or opens last week, total | E30: =IF(D30<>"",1,0) -> 0 | F30: 4000 | G30: Across every post, email and ad.
A31: 2 | B31: exercise | C31: Replies, clicks or saves last week, total | E31: =IF(D31<>"",1,0) -> 0 | F31: 90
A32: 2 | B32: exercise | C32: Hooks you drafted last week | E32: =IF(D32<>"",1,0) -> 0 | F32: 3 | G32: Drafts, not posts. Zero is a number.
B33: head | C33: Checklist
A34: 2 | B34: check | C34: ☐ The counts come from the platform, not a guess | E34: =IF(D34="Y",1,0) -> 0 | G34: Y when it is true.
B35: checkpoint | C35: When this band is done: Your hook rate shows.
A37: 3 | B37: band | C37: Band 3 · Exercises · reveal · about 25 min: Twenty hooks for one idea
B38: why | C38: Volume is the method. Twenty hooks for one idea, using different frames, gets you two good ones. One hook gets you one hope.
A39: 3 | B39: exercise | C39: Who it is for, in the words they use for themselves | E39: =IF(D39<>"",1,0) -> 0
A40: 3 | B40: exercise | C40: The one fact or result that backs the idea | E40: =IF(D40<>"",1,0) -> 0 | G40: A number, a name, a before and after. If there is none, see Proof Checklist.
A41: 3 | B41: exercise | C41: Twenty hooks for the idea, one a line | E41: =IF(D41<>"",1,0) -> 0 | G41: Frames to rotate: a question, a number, a claim with a condition, a common mistake, a before and after, a call-out of who it is for, a short story opener. One a line: Alt+Enter starts a new line inside the cell.
B42: head | C42: Checklist
A43: 3 | B43: check | C43: ☐ All twenty are for the same idea | E43: =IF(D43="Y",1,0) -> 0 | G43: Y when it is true.
A44: 3 | B44: check | C44: ☐ At least five different frames were used | E44: =IF(D44="Y",1,0) -> 0 | G44: Y when it is true.
A45: 3 | B45: check | C45: ☐ None promises more than the proof can back | E45: =IF(D45="Y",1,0) -> 0 | G45: Y when it is true.
B46: checkpoint | C46: When this band is done: A hook bank exists.
A48: 4 | B48: band | C48: Band 4 · Build · power · about 10 min: Pick three and place them
B49: why | C49: Score each hook on four things: it is specific, it is for someone, it makes you curious, and it is true. Take the top three, and make sure they are three different frames, not one hook three ways.
A50: 4 | B50: exercise | C50: Your top three, one a line, highest score first | E50: =IF(D50<>"",1,0) -> 0 | G50: One a line: Alt+Enter starts a new line inside the cell.
A51: 4 | B51: exercise | C51: Where the three will run | E51: =IF(D51<>"",1,0) -> 0 | G51: Pick one from the dropdown.
B52: head | C52: Checklist
A53: 4 | B53: check | C53: ☐ Each of the three names who it is for or what it is about in the first five words | E53: =IF(D53="Y",1,0) -> 0 | G53: Y when it is true.
A54: 4 | B54: check | C54: ☐ None of the three promises something the proof cannot back | E54: =IF(D54="Y",1,0) -> 0 | G54: Y when it is true.
A55: 4 | B55: check | C55: ☐ The three are different frames, not one hook three ways | E55: =IF(D55="Y",1,0) -> 0 | G55: Y when it is true.
A56: 4 | B56: check | C56: ☐ Each one is scheduled to run at least three times | E56: =IF(D56="Y",1,0) -> 0 | G56: Y when it is true.
B57: checkpoint | C57: When this band is done: Three hooks are placed and scheduled.
A59: 5 | B59: band | C59: Band 5 · Run · certainty · about 10 min: Run the three
B60: why | C60: Run each hook enough times to compare. Count the same thing for each: replies, clicks or saves. Then write the count beside each hook.
A61: 5 | B61: exercise | C61: Times the three ran in total | E61: =IF(D61<>"",1,0) -> 0 | F61: 9 | G61: Posts sent, emails sent, or ad views in hundreds.
A62: 5 | B62: exercise | C62: Replies, clicks or saves the three got, total | E62: =IF(D62<>"",1,0) -> 0 | F62: 80
A63: 5 | B63: exercise | C63: Each hook with its count, hook | count | D63: =IF(COUNTA(C65:D72)>0,"logged","") | E63: =IF(COUNTA(C65:D72)>0,1,0) -> 0 | F63: e.g. The 401k mistake I see every week | 41 | G63: One a line. The bar beside it draws from the number after the bar. Fill the small table below, one row a line.
B64: logrow | C64: Hook | D64: Count
B65: logrow
B66: logrow
B67: logrow
B68: logrow
B69: logrow
B70: logrow
B71: logrow
B72: logrow
B73: head | C73: Checklist
A74: 5 | B74: check | C74: ☐ Each hook ran at least three times before I judged it | E74: =IF(D74="Y",1,0) -> 0 | G74: Y when it is true.
B75: checkpoint | C75: When this band is done: Before and after hook rates sit side by side, and the three are ranked.
A77: 6 | B77: band | C77: Band 6 · Sharpen · power · about 8 min: Keep the winners, mark the losers
B78: why | C78: A hook that beat the average goes in the bank and gets reused. A hook that lost goes in the bank too, marked, so you never rewrite it by accident.
A79: 6 | B79: exercise | C79: Winners to keep in the bank, one a line | E79: =IF(D79<>"",1,0) -> 0 | G79: Used more than once and beat the average. One a line: Alt+Enter starts a new line inside the cell.
A80: 6 | B80: exercise | C80: What to change next | E80: =IF(D80<>"",1,0) -> 0 | G80: Pick one from the dropdown.
B81: head | C81: Checklist
A82: 6 | B82: check | C82: ☐ Winning hooks are in a bank I can open in ten seconds | E82: =IF(D82="Y",1,0) -> 0 | G82: Y when it is true.
A83: 6 | B83: check | C83: ☐ Losing hooks are in the bank too, marked as losers | E83: =IF(D83="Y",1,0) -> 0 | G83: Y when it is true.
A84: 6 | B84: check | C84: ☐ Next week's twenty are on the calendar | E84: =IF(D84="Y",1,0) -> 0 | G84: Y when it is true.
B85: checkpoint | C85: When this band is done: The bank has winners and the next twenty are scheduled.

Sheet Lead Nurture
C1: Lead Nurture | D1: Leads system
C2: A lead is a person who raised a hand. The next hour and the next thirty days decide whether it counts.
C3: Most leads are lost between the hand-raise and the conversation. Speed is the first lever: a reply inside minutes is worth many replies tomorrow. Persistence is the second: most people need to hear from you more times than feels polite, and they are not annoyed, they are busy. A lead magnet, a small free thing that solves one narrow problem and shows the next one, gives every follow-up a reason to exist.
C5: Where you stand on this planet
B6: # | C6: Band | D6: Answered | E6: Of | F6: Ticked | G6: Of | H6: Status
B7: 1 | C7: Read: The one idea, and where you stand on it today | D7: =SUMIFS($E$19:$E$400,$A$19:$A$400,B7,$B$19:$B$400,"exercise") -> 0 | E7: =COUNTIFS($A$19:$A$400,B7,$B$19:$B$400,"exercise") -> 2 | F7: =SUMIFS($E$19:$E$400,$A$19:$A$400,B7,$B$19:$B$400,"check") -> 0 | G7: =COUNTIFS($A$19:$A$400,B7,$B$19:$B$400,"check") -> 2 | H7: =IF(AND(D7=E7,F7=G7),"done",IF(D7+F7>0,"started","not yet")) -> not yet | I7: =IF(H7="done",99,B7) -> 1
B8: 2 | C8: Facts: The few numbers this playbook runs on | D8: =SUMIFS($E$19:$E$400,$A$19:$A$400,B8,$B$19:$B$400,"exercise") -> 0 | E8: =COUNTIFS($A$19:$A$400,B8,$B$19:$B$400,"exercise") -> 3 | F8: =SUMIFS($E$19:$E$400,$A$19:$A$400,B8,$B$19:$B$400,"check") -> 0 | G8: =COUNTIFS($A$19:$A$400,B8,$B$19:$B$400,"check") -> 1 | H8: =IF(AND(D8=E8,F8=G8),"done",IF(D8+F8>0,"started","not yet")) -> not yet | I8: =IF(H8="done",99,B8) -> 2
B9: 3 | C9: Exercises: The pen and paper work the playbook asks for | D9: =SUMIFS($E$19:$E$400,$A$19:$A$400,B9,$B$19:$B$400,"exercise") -> 0 | E9: =COUNTIFS($A$19:$A$400,B9,$B$19:$B$400,"exercise") -> 4 | F9: =SUMIFS($E$19:$E$400,$A$19:$A$400,B9,$B$19:$B$400,"check") -> 0 | G9: =COUNTIFS($A$19:$A$400,B9,$B$19:$B$400,"check") -> 3 | H9: =IF(AND(D9=E9,F9=G9),"done",IF(D9+F9>0,"started","not yet")) -> not yet | I9: =IF(H9="done",99,B9) -> 3
B10: 4 | C10: Build: Assemble the thing you will use, and tick it off | D10: =SUMIFS($E$19:$E$400,$A$19:$A$400,B10,$B$19:$B$400,"exercise") -> 0 | E10: =COUNTIFS($A$19:$A$400,B10,$B$19:$B$400,"exercise") -> 2 | F10: =SUMIFS($E$19:$E$400,$A$19:$A$400,B10,$B$19:$B$400,"check") -> 0 | G10: =COUNTIFS($A$19:$A$400,B10,$B$19:$B$400,"check") -> 5 | H10: =IF(AND(D10=E10,F10=G10),"done",IF(D10+F10>0,"started","not yet")) -> not yet | I10: =IF(H10="done",99,B10) -> 4
B11: 5 | C11: Run: Use it for a stretch and log what happened | D11: =SUMIFS($E$19:$E$400,$A$19:$A$400,B11,$B$19:$B$400,"exercise") -> 0 | E11: =COUNTIFS($A$19:$A$400,B11,$B$19:$B$400,"exercise") -> 4 | F11: =SUMIFS($E$19:$E$400,$A$19:$A$400,B11,$B$19:$B$400,"check") -> 0 | G11: =COUNTIFS($A$19:$A$400,B11,$B$19:$B$400,"check") -> 1 | H11: =IF(AND(D11=E11,F11=G11),"done",IF(D11+F11>0,"started","not yet")) -> not yet | I11: =IF(H11="done",99,B11) -> 5
B12: 6 | C12: Sharpen: The moves only visible once the numbers are real | D12: =SUMIFS($E$19:$E$400,$A$19:$A$400,B12,$B$19:$B$400,"exercise") -> 0 | E12: =COUNTIFS($A$19:$A$400,B12,$B$19:$B$400,"exercise") -> 2 | F12: =SUMIFS($E$19:$E$400,$A$19:$A$400,B12,$B$19:$B$400,"check") -> 0 | G12: =COUNTIFS($A$19:$A$400,B12,$B$19:$B$400,"check") -> 3 | H12: =IF(AND(D12=E12,F12=G12),"done",IF(D12+F12>0,"started","not yet")) -> not yet | I12: =IF(H12="done",99,B12) -> 6
C13: Levels done | D13: =COUNTIF(H7:H12,"done") -> 0 | F13: Yellow cells are yours to fill. A band is done when every yellow cell in it holds an answer and every checklist item is Y.
C14: Working on band | D14: =IF(MIN(I7:I12)=99,"complete",MIN(I7:I12)) -> 1
C15: Share of this planet answered | D15: =IF(SUM(E7:E12,G7:G12)=0,0,SUM(D7:D12,F7:F12)/SUM(E7:E12,G7:G12)) -> 0
A18: Band | B18: Kind | C18: Exercise or step | D18: Your answer | E18: ✓ | F18: Example | G18: What counts, where to look
A19: 1 | B19: band | C19: Band 1 · Read · reveal · about 6 min: What happens when a hand goes up
B20: why | C20: Time it. Count it. Most people are shocked by both numbers the first time they look.
A21: 1 | B21: exercise | C21: How fast and how many times a new lead hears from you, 1 to 5 | E21: =IF(D21<>"",1,0) -> 0 | F21: 2 | G21: One is not at all, five is fully. Your honest read today.
A22: 1 | B22: exercise | C22: What happens today when someone raises a hand | E22: =IF(D22<>"",1,0) -> 0 | G22: Who replies, in how long, how many times, with what. Step by step.
B23: head | C23: Checklist
A24: 1 | B24: check | C24: ☐ I timed my last reply to a new lead | E24: =IF(D24="Y",1,0) -> 0 | G24: Y when it is true.
A25: 1 | B25: check | C25: ☐ I counted how many touches a lead gets before I stop | E25: =IF(D25="Y",1,0) -> 0 | G25: Y when it is true.
B26: checkpoint | C26: When this band is done: Your starting point on the planet is set.
A28: 2 | B28: band | C28: Band 2 · Facts · reveal · about 6 min: Speed, touches, and the booking rate
B29: why | C29: Three numbers describe the whole system: how fast, how many times, and what share of leads end up in a conversation.
A30: 2 | B30: exercise | C30: Minutes from hand-raise to first reply, typical | E30: =IF(D30<>"",1,0) -> 0 | F30: 90 | G30: In working hours. Look at the last five leads and take the middle one.
A31: 2 | B31: exercise | C31: Touches a lead gets before you stop | E31: =IF(D31<>"",1,0) -> 0 | F31: 3 | G31: Messages, calls, emails: every attempt counts as one.
A32: 2 | B32: exercise | C32: Of engaged leads, the share who book a conversation [shared: other playbooks read this] | E32: =IF(D32<>"",1,0) -> 0 | F32: 0.4 | G32: Booked, not shown. Showing is measured in Closing Handbook. Type it as a percentage, for example 80%.
B33: head | C33: Checklist
A34: 2 | B34: check | C34: ☐ The reply time is measured from five real leads, not one | E34: =IF(D34="Y",1,0) -> 0 | G34: Y when it is true.
B35: checkpoint | C35: When this band is done: Reply speed and the booking rate show.
A37: 3 | B37: band | C37: Band 3 · Exercises · reveal · about 30 min: The magnet, the sequence, the short check-in
B38: why | C38: A lead magnet is a free thing that solves a narrow problem completely and reveals the next problem, which your paid thing solves. The sequence is the nine or so touches after it. The short check-in is the one-line question you send to every lead that has gone quiet.
A39: 3 | B39: exercise | C39: Your lead magnet kind | E39: =IF(D39<>"",1,0) -> 0 | G39: Pick one from the dropdown.
A40: 3 | B40: exercise | C40: Name it as the result it gives | E40: =IF(D40<>"",1,0) -> 0 | G40: Not what it is, what they get.
A41: 3 | B41: exercise | C41: The follow-up sequence, one touch a line: day, channel, what it says | E41: =IF(D41<>"",1,0) -> 0 | G41: Aim for nine touches over thirty days, on at least two channels. Every touch has one ask. One a line: Alt+Enter starts a new line inside the cell.
A42: 3 | B42: exercise | C42: Your short check-in for a quiet lead | E42: =IF(D42<>"",1,0) -> 0 | G42: One question, under fifteen words, easy to answer with one word.
B43: head | C43: Checklist
A44: 3 | B44: check | C44: ☐ The magnet solves its problem completely, not a teaser | E44: =IF(D44="Y",1,0) -> 0 | G44: Y when it is true.
A45: 3 | B45: check | C45: ☐ The sequence uses at least two channels | E45: =IF(D45="Y",1,0) -> 0 | G45: Y when it is true.
A46: 3 | B46: check | C46: ☐ Every touch has exactly one ask | E46: =IF(D46="Y",1,0) -> 0 | G46: Y when it is true.
B47: checkpoint | C47: When this band is done: The magnet, the sequence and the check-in are written.
A49: 4 | B49: band | C49: Band 4 · Build · power · about 12 min: Put a person on the five minutes
B50: why | C50: Speed is a staffing decision. Someone gets told about every new lead, and answers inside five minutes in working hours. The sequence is scheduled, not remembered.
A51: 4 | B51: exercise | C51: Who replies to a new lead within five minutes, and how they find out | E51: =IF(D51<>"",1,0) -> 0 | G51: A name and a notification. If it is you, say what buzzes.
A52: 4 | B52: exercise | C52: Where the sequence is scheduled | E52: =IF(D52<>"",1,0) -> 0 | G52: A tool, a calendar, a checklist on the wall.
B53: head | C53: Checklist
A54: 4 | B54: check | C54: ☐ The lead magnet exists and can be sent as one link | E54: =IF(D54="Y",1,0) -> 0 | G54: Y when it is true.
A55: 4 | B55: check | C55: ☐ Every new lead gets a reply within five minutes in working hours | E55: =IF(D55="Y",1,0) -> 0 | G55: Y when it is true.
A56: 4 | B56: check | C56: ☐ The nine touches are scheduled, not remembered | E56: =IF(D56="Y",1,0) -> 0 | G56: Y when it is true.
A57: 4 | B57: check | C57: ☐ Every quiet lead gets the short check-in after thirty days | E57: =IF(D57="Y",1,0) -> 0 | G57: Y when it is true.
A58: 4 | B58: check | C58: ☐ Every touch has one ask | E58: =IF(D58="Y",1,0) -> 0 | G58: Y when it is true.
B59: checkpoint | C59: When this band is done: The system runs without anyone remembering it.
A61: 5 | B61: band | C61: Band 5 · Run · certainty · about 12 min: Thirty days of leads
B62: why | C62: Now measure the same three numbers on leads that went through the new sequence. Log how many replied at each touch: that curve tells you where the sequence earns its keep.
A63: 5 | B63: exercise | C63: Leads that entered the sequence in the run | E63: =IF(D63<>"",1,0) -> 0 | F63: 30
A64: 5 | B64: exercise | C64: Of those, how many booked a conversation | E64: =IF(D64<>"",1,0) -> 0 | F64: 16
A65: 5 | B65: exercise | C65: Median minutes to first reply in the run | E65: =IF(D65<>"",1,0) -> 0 | F65: 8
A66: 5 | B66: exercise | C66: Replies by touch | D66: =IF(COUNTA(C68:E75)>0,"logged","") | E66: =IF(COUNTA(C68:E75)>0,1,0) -> 0 | F66: e.g. 1 | 30 | 9 | G66: One row a touch: how many were sent that touch, how many replied to it. Fill the small table below, one row a line.
B67: logrow | C67: touch | D67: sent | E67: replied
B68: logrow
B69: logrow
B70: logrow
B71: logrow
B72: logrow
B73: logrow
B74: logrow
B75: logrow
B76: head | C76: Checklist
A77: 5 | B77: check | C77: ☐ The run covered at least thirty days so the late touches had time to land | E77: =IF(D77="Y",1,0) -> 0 | G77: Y when it is true.
B78: checkpoint | C78: When this band is done: Before and after booking rates, reply speed, and the touch curve all show.
A80: 6 | B80: band | C80: Band 6 · Sharpen · power · about 10 min: Faster, more, better, or reactivate
B81: why | C81: With a curve in hand the next move is obvious. If late touches still get replies, add more. If nobody replies after touch two, fix the magnet. And the old list is the cheapest campaign you will ever run.
A82: 6 | B82: exercise | C82: The next move | E82: =IF(D82<>"",1,0) -> 0 | G82: Pick one from the dropdown.
A83: 6 | B83: exercise | C83: Leads on the old list who never bought | E83: =IF(D83<>"",1,0) -> 0 | G83: They get the short check-in this month.
B84: head | C84: Checklist
A85: 6 | B85: check | C85: ☐ The old list got the short check-in this month | E85: =IF(D85="Y",1,0) -> 0 | G85: Y when it is true.
A86: 6 | B86: check | C86: ☐ The magnet's next-problem points at the paid thing | E86: =IF(D86="Y",1,0) -> 0 | G86: Y when it is true.
A87: 6 | B87: check | C87: ☐ Reply time is on the weekly scorecard | E87: =IF(D87="Y",1,0) -> 0 | G87: Y when it is true.
B88: checkpoint | C88: When this band is done: The next move is decided and the old list is in play.

Sheet Closing Handbook
C1: Closing Handbook | D1: Sales system
C2: A sale is a conversation with a shape. Learn the shape and the pressure goes out of it.
C3: The conversation runs in six moves, and the letters spell CLOSER: clarify why they came, label the problem back to them in their words, overview what they have tried and why it did not hold, sell the outcome and not the method, explain away the concerns that remain, and reinforce the decision the moment they say yes. Concerns come in three kinds: about circumstances (time, money), about other people (a partner, a boss), and about themselves (fit, doubt). Each kind has an answer you write once and say many times.
C5: Where you stand on this planet
B6: # | C6: Band | D6: Answered | E6: Of | F6: Ticked | G6: Of | H6: Status
B7: 1 | C7: Read: The one idea, and where you stand on it today | D7: =SUMIFS($E$19:$E$400,$A$19:$A$400,B7,$B$19:$B$400,"exercise") -> 0 | E7: =COUNTIFS($A$19:$A$400,B7,$B$19:$B$400,"exercise") -> 2 | F7: =SUMIFS($E$19:$E$400,$A$19:$A$400,B7,$B$19:$B$400,"check") -> 0 | G7: =COUNTIFS($A$19:$A$400,B7,$B$19:$B$400,"check") -> 2 | H7: =IF(AND(D7=E7,F7=G7),"done",IF(D7+F7>0,"started","not yet")) -> not yet | I7: =IF(H7="done",99,B7) -> 1
B8: 2 | C8: Facts: The few numbers this playbook runs on | D8: =SUMIFS($E$19:$E$400,$A$19:$A$400,B8,$B$19:$B$400,"exercise") -> 0 | E8: =COUNTIFS($A$19:$A$400,B8,$B$19:$B$400,"exercise") -> 4 | F8: =SUMIFS($E$19:$E$400,$A$19:$A$400,B8,$B$19:$B$400,"check") -> 0 | G8: =COUNTIFS($A$19:$A$400,B8,$B$19:$B$400,"check") -> 1 | H8: =IF(AND(D8=E8,F8=G8),"done",IF(D8+F8>0,"started","not yet")) -> not yet | I8: =IF(H8="done",99,B8) -> 2
B9: 3 | C9: Exercises: The pen and paper work the playbook asks for | D9: =SUMIFS($E$19:$E$400,$A$19:$A$400,B9,$B$19:$B$400,"exercise") -> 0 | E9: =COUNTIFS($A$19:$A$400,B9,$B$19:$B$400,"exercise") -> 6 | F9: =SUMIFS($E$19:$E$400,$A$19:$A$400,B9,$B$19:$B$400,"check") -> 0 | G9: =COUNTIFS($A$19:$A$400,B9,$B$19:$B$400,"check") -> 2 | H9: =IF(AND(D9=E9,F9=G9),"done",IF(D9+F9>0,"started","not yet")) -> not yet | I9: =IF(H9="done",99,B9) -> 3
B10: 4 | C10: Build: Assemble the thing you will use, and tick it off | D10: =SUMIFS($E$19:$E$400,$A$19:$A$400,B10,$B$19:$B$400,"exercise") -> 0 | E10: =COUNTIFS($A$19:$A$400,B10,$B$19:$B$400,"exercise") -> 1 | F10: =SUMIFS($E$19:$E$400,$A$19:$A$400,B10,$B$19:$B$400,"check") -> 0 | G10: =COUNTIFS($A$19:$A$400,B10,$B$19:$B$400,"check") -> 6 | H10: =IF(AND(D10=E10,F10=G10),"done",IF(D10+F10>0,"started","not yet")) -> not yet | I10: =IF(H10="done",99,B10) -> 4
B11: 5 | C11: Run: Use it for a stretch and log what happened | D11: =SUMIFS($E$19:$E$400,$A$19:$A$400,B11,$B$19:$B$400,"exercise") -> 0 | E11: =COUNTIFS($A$19:$A$400,B11,$B$19:$B$400,"exercise") -> 4 | F11: =SUMIFS($E$19:$E$400,$A$19:$A$400,B11,$B$19:$B$400,"check") -> 0 | G11: =COUNTIFS($A$19:$A$400,B11,$B$19:$B$400,"check") -> 2 | H11: =IF(AND(D11=E11,F11=G11),"done",IF(D11+F11>0,"started","not yet")) -> not yet | I11: =IF(H11="done",99,B11) -> 5
B12: 6 | C12: Sharpen: The moves only visible once the numbers are real | D12: =SUMIFS($E$19:$E$400,$A$19:$A$400,B12,$B$19:$B$400,"exercise") -> 0 | E12: =COUNTIFS($A$19:$A$400,B12,$B$19:$B$400,"exercise") -> 2 | F12: =SUMIFS($E$19:$E$400,$A$19:$A$400,B12,$B$19:$B$400,"check") -> 0 | G12: =COUNTIFS($A$19:$A$400,B12,$B$19:$B$400,"check") -> 4 | H12: =IF(AND(D12=E12,F12=G12),"done",IF(D12+F12>0,"started","not yet")) -> not yet | I12: =IF(H12="done",99,B12) -> 6
C13: Levels done | D13: =COUNTIF(H7:H12,"done") -> 0 | F13: Yellow cells are yours to fill. A band is done when every yellow cell in it holds an answer and every checklist item is Y.
C14: Working on band | D14: =IF(MIN(I7:I12)=99,"complete",MIN(I7:I12)) -> 1
C15: Share of this planet answered | D15: =IF(SUM(E7:E12,G7:G12)=0,0,SUM(D7:D12,F7:F12)/SUM(E7:E12,G7:G12)) -> 0
A18: Band | B18: Kind | C18: Exercise or step | D18: Your answer | E18: ✓ | F18: Example | G18: What counts, where to look
A19: 1 | B19: band | C19: Band 1 · Read · reveal · about 8 min: Your last conversation, in six lines
B20: why | C20: Write up your last sales conversation from open to close. Where did it drift? Where did you talk most? Where did you lose them, if you did?
A21: 1 | B21: exercise | C21: How confident are you in a sales conversation, 1 to 5 | E21: =IF(D21<>"",1,0) -> 0 | F21: 3 | G21: One is not at all, five is fully. Your honest read today.
A22: 1 | B22: exercise | C22: Your last sales conversation, open to close, in six lines | E22: =IF(D22<>"",1,0) -> 0 | F22: Opened with my story, showed the programme, said the price, got a maybe. | G22: One line per move if you can. If you cannot find six moves, that is the finding.
B23: head | C23: Checklist
A24: 1 | B24: check | C24: ☐ I recorded or wrote up my last call | E24: =IF(D24="Y",1,0) -> 0 | G24: Y when it is true.
A25: 1 | B25: check | C25: ☐ I know where in the call I lose people | E25: =IF(D25="Y",1,0) -> 0 | G25: Y when it is true.
B26: checkpoint | C26: When this band is done: Your starting point on the planet is set.
A28: 2 | B28: band | C28: Band 2 · Facts · reveal · about 8 min: The funnel of one month
B29: why | C29: Booked, shown, bought, paid. Four counts make three rates, and each rate has its own playbook.
A30: 2 | B30: exercise | C30: Conversations booked last month | E30: =IF(D30<>"",1,0) -> 0 | F30: 20
A31: 2 | B31: exercise | C31: Of those, how many showed up | E31: =IF(D31<>"",1,0) -> 0 | F31: 14
A32: 2 | B32: exercise | C32: Of those, how many bought | E32: =IF(D32<>"",1,0) -> 0 | F32: 5
A33: 2 | B33: exercise | C33: Cash collected at the close last month, total | E33: =IF(D33<>"",1,0) -> 0 | F33: 6000 | G33: What actually arrived, not what was promised. Whole dollars.
B34: head | C34: Checklist
A35: 2 | B35: check | C35: ☐ The four counts come from a calendar and a bank statement, not memory | E35: =IF(D35="Y",1,0) -> 0 | G35: Y when it is true.
B36: checkpoint | C36: When this band is done: Show rate, close rate and cash per sale show, and the Marketing Machine can compute leads needed.
A38: 3 | B38: band | C38: Band 3 · Exercises · reveal · about 35 min: Write your six moves
B39: why | C39: One paragraph per letter, in your own words, as you would say it to a friend across a table.
A40: 3 | B40: exercise | C40: Clarify: the two questions you open with | E40: =IF(D40<>"",1,0) -> 0 | G40: Why now? What made you reach out? Their answer is the rest of the call.
A41: 3 | B41: exercise | C41: Label: the sentence that names their problem back to them | E41: =IF(D41<>"",1,0) -> 0 | G41: In their words. Then ask: is that right?
A42: 3 | B42: exercise | C42: Overview: the question that draws out what they tried and why it did not hold | E42: =IF(D42<>"",1,0) -> 0 | G42: The point is that they hear themselves say it.
A43: 3 | B43: exercise | C43: Sell the vacation: the outcome, in three sentences, with no method in it | E43: =IF(D43<>"",1,0) -> 0 | G43: The beach, not the plane.
A44: 3 | B44: exercise | C44: Explain away: your answer to each of the three kinds of concern | E44: =IF(D44<>"",1,0) -> 0 | G44: Circumstances (time, money). Other people (a partner, a boss). Themselves (fit, doubt). One answer each.
A45: 3 | B45: exercise | C45: Reinforce: what happens in the first 24 hours after yes | E45: =IF(D45<>"",1,0) -> 0 | G45: A message, a call, a small gift. The decision needs a second yes from their future self.
B46: head | C46: Checklist
A47: 3 | B47: check | C47: ☐ Each move is written as I would say it, not as a script sounds | E47: =IF(D47="Y",1,0) -> 0 | G47: Y when it is true.
A48: 3 | B48: check | C48: ☐ The label uses their words, not mine | E48: =IF(D48="Y",1,0) -> 0 | G48: Y when it is true.
B49: checkpoint | C49: When this band is done: The six moves exist in your voice.
A51: 4 | B51: band | C51: Band 4 · Build · power · about 15 min: One page, and the objection bank
B52: why | C52: The script fits on one page or it will not be used. The objection bank grows after every call and never shrinks.
A53: 4 | B53: exercise | C53: The objection bank: concern | your answer, one a line | D53: =IF(COUNTA(C55:D62)>0,"logged","") | E53: =IF(COUNTA(C55:D62)>0,1,0) -> 0 | G53: Every concern you have ever heard, with the answer after the bar. Add to it after every call. Fill the small table below, one row a line.
B54: logrow | C54: Concern heard | D54: Your answer
B55: logrow
B56: logrow
B57: logrow
B58: logrow
B59: logrow
B60: logrow
B61: logrow
B62: logrow
B63: head | C63: Checklist
A64: 4 | B64: check | C64: ☐ The script fits on one page | E64: =IF(D64="Y",1,0) -> 0 | G64: Y when it is true.
A65: 4 | B65: check | C65: ☐ Every question in it is one I would ask a friend | E65: =IF(D65="Y",1,0) -> 0 | G65: Y when it is true.
A66: 4 | B66: check | C66: ☐ The price is said once, plainly, with no apology | E66: =IF(D66="Y",1,0) -> 0 | G66: Y when it is true.
A67: 4 | B67: check | C67: ☐ Silence after the price is written into the script | E67: =IF(D67="Y",1,0) -> 0 | G67: Y when it is true.
A68: 4 | B68: check | C68: ☐ The three concern answers are memorised, not read | E68: =IF(D68="Y",1,0) -> 0 | G68: Y when it is true.
A69: 4 | B69: check | C69: ☐ Reinforce happens the same day, every time | E69: =IF(D69="Y",1,0) -> 0 | G69: Y when it is true.
B70: checkpoint | C70: When this band is done: The one-page script and the bank are ready.
A72: 5 | B72: band | C72: Band 5 · Run · certainty · about 12 min: A month on the script
B73: why | C73: Run the script on every conversation for a month. Count the same four things. Log which objections came up and how often you answered them well.
A74: 5 | B74: exercise | C74: Conversations in the run | E74: =IF(D74<>"",1,0) -> 0 | F74: 16 | G74: Shown, not booked.
A75: 5 | B75: exercise | C75: Sales in the run | E75: =IF(D75<>"",1,0) -> 0 | F75: 7
A76: 5 | B76: exercise | C76: Cash collected at the close in the run, total | E76: =IF(D76<>"",1,0) -> 0 | F76: 9000 | G76: Whole dollars.
A77: 5 | B77: exercise | C77: Objections heard | D77: =IF(COUNTA(C79:E86)>0,"logged","") | E77: =IF(COUNTA(C79:E86)>0,1,0) -> 0 | F77: e.g. Need to think about it | 6 | 2 | G77: One row an objection. Fill the small table below, one row a line.
B78: logrow | C78: objection | D78: times heard | E78: answered well
B79: logrow
B80: logrow
B81: logrow
B82: logrow
B83: logrow
B84: logrow
B85: logrow
B86: logrow
B87: head | C87: Checklist
A88: 5 | B88: check | C88: ☐ Every conversation in the run used the script | E88: =IF(D88="Y",1,0) -> 0 | G88: Y when it is true.
A89: 5 | B89: check | C89: ☐ One conversation a week was reviewed from a recording | E89: =IF(D89="Y",1,0) -> 0 | G89: Y when it is true.
B90: checkpoint | C90: When this band is done: Before and after close rates, and the objection bars, show.
A92: 6 | B92: band | C92: Band 6 · Sharpen · power · about 8 min: Which rate, and who else can run it
B93: why | C93: Each rate points at a different fix. And the script only counts once someone other than you can close with it.
A94: 6 | B94: exercise | C94: The rate to work next | E94: =IF(D94<>"",1,0) -> 0 | G94: Pick one from the dropdown.
A95: 6 | B95: exercise | C95: Who runs the script next, other than you | E95: =IF(D95<>"",1,0) -> 0 | G95: A name, or none yet.
B96: head | C96: Checklist
A97: 6 | B97: check | C97: ☐ Calls are recorded and one a week is reviewed | E97: =IF(D97="Y",1,0) -> 0 | G97: Y when it is true.
A98: 6 | B98: check | C98: ☐ The objection bank grew after every call | E98: =IF(D98="Y",1,0) -> 0 | G98: Y when it is true.
A99: 6 | B99: check | C99: ☐ Reinforce runs the same day, every time | E99: =IF(D99="Y",1,0) -> 0 | G99: Y when it is true.
A100: 6 | B100: check | C100: ☐ Close rate is on the weekly scorecard | E100: =IF(D100="Y",1,0) -> 0 | G100: Y when it is true.
B101: checkpoint | C101: When this band is done: The next rate to work is decided.

Sheet Proof Checklist
C1: Proof Checklist | D1: Sales system
C2: People do not buy the promise. They buy the evidence that the promise held for someone like them.
C3: Whether someone believes an outcome will happen for them is half of what a thing is worth to them. Proof moves that belief. It comes in kinds: results with a number, before and after pairs, named testimonials, third-party marks (reviews, press, credentials), and demonstrations. The checklist is a habit rather than a project: collect proof at every win, put a proof beside every claim, and match the kind of proof to the doubt it answers.
C5: Where you stand on this planet
B6: # | C6: Band | D6: Answered | E6: Of | F6: Ticked | G6: Of | H6: Status
B7: 1 | C7: Read: The one idea, and where you stand on it today | D7: =SUMIFS($E$19:$E$400,$A$19:$A$400,B7,$B$19:$B$400,"exercise") -> 0 | E7: =COUNTIFS($A$19:$A$400,B7,$B$19:$B$400,"exercise") -> 2 | F7: =SUMIFS($E$19:$E$400,$A$19:$A$400,B7,$B$19:$B$400,"check") -> 0 | G7: =COUNTIFS($A$19:$A$400,B7,$B$19:$B$400,"check") -> 2 | H7: =IF(AND(D7=E7,F7=G7),"done",IF(D7+F7>0,"started","not yet")) -> not yet | I7: =IF(H7="done",99,B7) -> 1
B8: 2 | C8: Facts: The few numbers this playbook runs on | D8: =SUMIFS($E$19:$E$400,$A$19:$A$400,B8,$B$19:$B$400,"exercise") -> 0 | E8: =COUNTIFS($A$19:$A$400,B8,$B$19:$B$400,"exercise") -> 6 | F8: =SUMIFS($E$19:$E$400,$A$19:$A$400,B8,$B$19:$B$400,"check") -> 0 | G8: =COUNTIFS($A$19:$A$400,B8,$B$19:$B$400,"check") -> 1 | H8: =IF(AND(D8=E8,F8=G8),"done",IF(D8+F8>0,"started","not yet")) -> not yet | I8: =IF(H8="done",99,B8) -> 2
B9: 3 | C9: Exercises: The pen and paper work the playbook asks for | D9: =SUMIFS($E$19:$E$400,$A$19:$A$400,B9,$B$19:$B$400,"exercise") -> 0 | E9: =COUNTIFS($A$19:$A$400,B9,$B$19:$B$400,"exercise") -> 3 | F9: =SUMIFS($E$19:$E$400,$A$19:$A$400,B9,$B$19:$B$400,"check") -> 0 | G9: =COUNTIFS($A$19:$A$400,B9,$B$19:$B$400,"check") -> 2 | H9: =IF(AND(D9=E9,F9=G9),"done",IF(D9+F9>0,"started","not yet")) -> not yet | I9: =IF(H9="done",99,B9) -> 3
B10: 4 | C10: Build: Assemble the thing you will use, and tick it off | D10: =SUMIFS($E$19:$E$400,$A$19:$A$400,B10,$B$19:$B$400,"exercise") -> 0 | E10: =COUNTIFS($A$19:$A$400,B10,$B$19:$B$400,"exercise") -> 2 | F10: =SUMIFS($E$19:$E$400,$A$19:$A$400,B10,$B$19:$B$400,"check") -> 0 | G10: =COUNTIFS($A$19:$A$400,B10,$B$19:$B$400,"check") -> 5 | H10: =IF(AND(D10=E10,F10=G10),"done",IF(D10+F10>0,"started","not yet")) -> not yet | I10: =IF(H10="done",99,B10) -> 4
B11: 5 | C11: Run: Use it for a stretch and log what happened | D11: =SUMIFS($E$19:$E$400,$A$19:$A$400,B11,$B$19:$B$400,"exercise") -> 0 | E11: =COUNTIFS($A$19:$A$400,B11,$B$19:$B$400,"exercise") -> 3 | F11: =SUMIFS($E$19:$E$400,$A$19:$A$400,B11,$B$19:$B$400,"check") -> 0 | G11: =COUNTIFS($A$19:$A$400,B11,$B$19:$B$400,"check") -> 2 | H11: =IF(AND(D11=E11,F11=G11),"done",IF(D11+F11>0,"started","not yet")) -> not yet | I11: =IF(H11="done",99,B11) -> 5
B12: 6 | C12: Sharpen: The moves only visible once the numbers are real | D12: =SUMIFS($E$19:$E$400,$A$19:$A$400,B12,$B$19:$B$400,"exercise") -> 0 | E12: =COUNTIFS($A$19:$A$400,B12,$B$19:$B$400,"exercise") -> 2 | F12: =SUMIFS($E$19:$E$400,$A$19:$A$400,B12,$B$19:$B$400,"check") -> 0 | G12: =COUNTIFS($A$19:$A$400,B12,$B$19:$B$400,"check") -> 3 | H12: =IF(AND(D12=E12,F12=G12),"done",IF(D12+F12>0,"started","not yet")) -> not yet | I12: =IF(H12="done",99,B12) -> 6
C13: Levels done | D13: =COUNTIF(H7:H12,"done") -> 0 | F13: Yellow cells are yours to fill. A band is done when every yellow cell in it holds an answer and every checklist item is Y.
C14: Working on band | D14: =IF(MIN(I7:I12)=99,"complete",MIN(I7:I12)) -> 1
C15: Share of this planet answered | D15: =IF(SUM(E7:E12,G7:G12)=0,0,SUM(D7:D12,F7:F12)/SUM(E7:E12,G7:G12)) -> 0
A18: Band | B18: Kind | C18: Exercise or step | D18: Your answer | E18: ✓ | F18: Example | G18: What counts, where to look
A19: 1 | B19: band | C19: Band 1 · Read · reveal · about 8 min: Read your pitch as a doubter
B20: why | C20: Open your sales page or your pitch and read it as someone who has been burned before. Mark every claim that has nothing beside it.
A21: 1 | B21: exercise | C21: How much evidence backs your offer today, 1 to 5 | E21: =IF(D21<>"",1,0) -> 0 | F21: 2 | G21: One is not at all, five is fully. Your honest read today.
A22: 1 | B22: exercise | C22: Every piece of proof you can put your hands on in five minutes | E22: =IF(D22<>"",1,0) -> 0 | G22: Screenshots, messages, reviews, numbers. List them.
B23: head | C23: Checklist
A24: 1 | B24: check | C24: ☐ I read my pitch as a doubter | E24: =IF(D24="Y",1,0) -> 0 | G24: Y when it is true.
A25: 1 | B25: check | C25: ☐ I marked every claim with no proof beside it | E25: =IF(D25="Y",1,0) -> 0 | G25: Y when it is true.
B26: checkpoint | C26: When this band is done: Your starting point on the planet is set.
A28: 2 | B28: band | C28: Band 2 · Facts · reveal · about 8 min: Count the proof by kind
B29: why | C29: Five kinds, five counts. The shape of the count tells you what to collect next.
A30: 2 | B30: exercise | C30: Results with a number | E30: =IF(D30<>"",1,0) -> 0 | F30: 2 | G30: A client got X in Y. Counted individually.
A31: 2 | B31: exercise | C31: Named testimonials, written or on video | E31: =IF(D31<>"",1,0) -> 0 | F31: 6
A32: 2 | B32: exercise | C32: Before and after pairs | E32: =IF(D32<>"",1,0) -> 0 | F32: 1 | G32: Pictures, screenshots, two numbers.
A33: 2 | B33: exercise | C33: Third-party marks | E33: =IF(D33<>"",1,0) -> 0 | F33: 3 | G33: Reviews on a platform, press, credentials, awards.
A34: 2 | B34: exercise | C34: Demonstrations | E34: =IF(D34<>"",1,0) -> 0 | F34: 1 | G34: A free sample, a live walkthrough, a recorded one.
A35: 2 | B35: exercise | C35: Customers you have served, total | E35: =IF(D35<>"",1,0) -> 0 | F35: 40 | G35: Ever. The proof inventory is measured against this.
B36: head | C36: Checklist
A37: 2 | B37: check | C37: ☐ Each count is of things I could show today, not things I could get | E37: =IF(D37="Y",1,0) -> 0 | G37: Y when it is true.
B38: checkpoint | C38: When this band is done: The proof inventory draws, by kind.
A40: 3 | B40: band | C40: Band 3 · Exercises · reveal · about 20 min: Claims, doubts, and ten people to ask
B41: why | C41: Every claim your offer makes needs a proof or a cut. Every doubt a buyer has needs a proof that answers it. And ten past customers are one message away from a testimonial.
A42: 3 | B42: exercise | C42: Every claim your offer makes, one a line | E42: =IF(D42<>"",1,0) -> 0 | F42: Control of your money in eight weeks No finance degree needed Keep the life you have | G42: One a line: Alt+Enter starts a new line inside the cell.
A43: 3 | B43: exercise | C43: The five doubts a buyer has before paying, in their words | E43: =IF(D43<>"",1,0) -> 0 | G43: Will it work for me? What if I fail? Is this person real? One a line: Alt+Enter starts a new line inside the cell.
A44: 3 | B44: exercise | C44: Ten past customers to ask this week, one a line, with what to ask each for | D44: =IF(COUNTA(C46:E53)>0,"logged","") | E44: =IF(COUNTA(C46:E53)>0,1,0) -> 0 | G44: Name | the specific result to ask about | the kind of proof (a number, a story, a screenshot). Fill the small table below, one row a line.
B45: logrow | C45: Name | D45: Result to ask about | E45: Kind of proof
B46: logrow
B47: logrow
B48: logrow
B49: logrow
B50: logrow
B51: logrow
B52: logrow
B53: logrow
B54: head | C54: Checklist
A55: 3 | B55: check | C55: ☐ The doubts are in the buyer's words, not mine | E55: =IF(D55="Y",1,0) -> 0 | G55: Y when it is true.
A56: 3 | B56: check | C56: ☐ Each of the ten asks names a specific result | E56: =IF(D56="Y",1,0) -> 0 | G56: Y when it is true.
B57: checkpoint | C57: When this band is done: Claims, doubts and the ask list exist.
A59: 4 | B59: band | C59: Band 4 · Build · power · about 15 min: A proof beside every claim
B60: why | C60: Map each claim to the proof beside it. A claim with nothing beside it is cut or held until the proof arrives.
A61: 4 | B61: exercise | C61: Claim | the proof beside it | the kind, one a line | D61: =IF(COUNTA(C63:E70)>0,"logged","") | E61: =IF(COUNTA(C63:E70)>0,1,0) -> 0 | F61: e.g. Control in eight weeks | Sam's before and after | before and after | G61: A claim with no proof gets the word cut after the bar. Fill the small table below, one row a line.
B62: logrow | C62: Claim | D62: The proof beside it (or: cut) | E62: Kind
B63: logrow
B64: logrow
B65: logrow
B66: logrow
B67: logrow
B68: logrow
B69: logrow
B70: logrow
A71: 4 | B71: exercise | C71: Where the proof lives | E71: =IF(D71<>"",1,0) -> 0 | G71: One folder anyone on the team can reach.
B72: head | C72: Checklist
A73: 4 | B73: check | C73: ☐ Every claim has a proof beside it or is cut | E73: =IF(D73="Y",1,0) -> 0 | G73: Y when it is true.
A74: 4 | B74: check | C74: ☐ The three biggest doubts each have a proof that answers them | E74: =IF(D74="Y",1,0) -> 0 | G74: Y when it is true.
A75: 4 | B75: check | C75: ☐ Asking for proof happens at the moment of a win, inside the delivery | E75: =IF(D75="Y",1,0) -> 0 | G75: Y when it is true.
A76: 4 | B76: check | C76: ☐ Proof is stored in one folder anyone on the team can reach | E76: =IF(D76="Y",1,0) -> 0 | G76: Y when it is true.
A77: 4 | B77: check | C77: ☐ Every name and number in the proof is real and permitted | E77: =IF(D77="Y",1,0) -> 0 | G77: Y when it is true.
B78: checkpoint | C78: When this band is done: Every live claim has evidence beside it.
A80: 5 | B80: band | C80: Band 5 · Run · certainty · about 8 min: A week of asking
B81: why | C81: Send the ten asks. Count what came back. Count where you placed it.
A82: 5 | B82: exercise | C82: Testimonials asked for in the run | E82: =IF(D82<>"",1,0) -> 0 | F82: 10
A83: 5 | B83: exercise | C83: Testimonials received | E83: =IF(D83<>"",1,0) -> 0 | F83: 4
A84: 5 | B84: exercise | C84: Places proof was added | E84: =IF(D84<>"",1,0) -> 0 | F84: 3 | G84: The page, the script, an ad, an email: each counts as one.
B85: head | C85: Checklist
A86: 5 | B86: check | C86: ☐ Every ask named a specific result | E86: =IF(D86="Y",1,0) -> 0 | G86: Y when it is true.
A87: 5 | B87: check | C87: ☐ Every proof received was placed somewhere within a week | E87: =IF(D87="Y",1,0) -> 0 | G87: Y when it is true.
B88: checkpoint | C88: When this band is done: The ask rate and the placements show.
A90: 6 | B90: band | C90: Band 6 · Sharpen · power · about 8 min: Numbers, faces, marks, or a guarantee
B91: why | C91: The strongest proof for the biggest doubt is a promise you will make good on. A guarantee names the outcome and the term, and it is priced in.
A92: 6 | B92: exercise | C92: The next kind to build | E92: =IF(D92<>"",1,0) -> 0 | G92: Pick one from the dropdown.
A93: 6 | B93: exercise | C93: The guarantee, in one sentence | E93: =IF(D93<>"",1,0) -> 0 | G93: What outcome, by when, or what happens. Or none yet.
B94: head | C94: Checklist
A95: 6 | B95: check | C95: ☐ A proof ask is written into the delivery (see Retention) | E95: =IF(D95="Y",1,0) -> 0 | G95: Y when it is true.
A96: 6 | B96: check | C96: ☐ The guarantee names the outcome and the term | E96: =IF(D96="Y",1,0) -> 0 | G96: Y when it is true.
A97: 6 | B97: check | C97: ☐ Proof is refreshed every quarter, oldest out | E97: =IF(D97="Y",1,0) -> 0 | G97: Y when it is true.
B98: checkpoint | C98: When this band is done: The next kind of proof is decided.

Sheet GOATed Ads
C1: GOATed Ads | D1: Sales system
C2: A paid ad is a call-out, a reason, and an ask, bought by the thousand and judged by the cost of a customer.
C3: Paid ads are the fourth of the four ways to get leads and the one that scales fastest once the math works. An ad has three parts: a call-out that says who it is for, value that gives them a reason to keep watching, and a call to action that says the one thing to do next. The math is a chain: cost per thousand views, the share who click, the share who become leads, the share who book, the share who buy. An ad is good when the lifetime gross profit of a customer is at least three times what it cost to get them.
C5: Where you stand on this planet
B6: # | C6: Band | D6: Answered | E6: Of | F6: Ticked | G6: Of | H6: Status
B7: 1 | C7: Read: The one idea, and where you stand on it today | D7: =SUMIFS($E$19:$E$400,$A$19:$A$400,B7,$B$19:$B$400,"exercise") -> 0 | E7: =COUNTIFS($A$19:$A$400,B7,$B$19:$B$400,"exercise") -> 2 | F7: =SUMIFS($E$19:$E$400,$A$19:$A$400,B7,$B$19:$B$400,"check") -> 0 | G7: =COUNTIFS($A$19:$A$400,B7,$B$19:$B$400,"check") -> 2 | H7: =IF(AND(D7=E7,F7=G7),"done",IF(D7+F7>0,"started","not yet")) -> not yet | I7: =IF(H7="done",99,B7) -> 1
B8: 2 | C8: Facts: The few numbers this playbook runs on | D8: =SUMIFS($E$19:$E$400,$A$19:$A$400,B8,$B$19:$B$400,"exercise") -> 0 | E8: =COUNTIFS($A$19:$A$400,B8,$B$19:$B$400,"exercise") -> 6 | F8: =SUMIFS($E$19:$E$400,$A$19:$A$400,B8,$B$19:$B$400,"check") -> 0 | G8: =COUNTIFS($A$19:$A$400,B8,$B$19:$B$400,"check") -> 1 | H8: =IF(AND(D8=E8,F8=G8),"done",IF(D8+F8>0,"started","not yet")) -> not yet | I8: =IF(H8="done",99,B8) -> 2
B9: 3 | C9: Exercises: The pen and paper work the playbook asks for | D9: =SUMIFS($E$19:$E$400,$A$19:$A$400,B9,$B$19:$B$400,"exercise") -> 0 | E9: =COUNTIFS($A$19:$A$400,B9,$B$19:$B$400,"exercise") -> 3 | F9: =SUMIFS($E$19:$E$400,$A$19:$A$400,B9,$B$19:$B$400,"check") -> 0 | G9: =COUNTIFS($A$19:$A$400,B9,$B$19:$B$400,"check") -> 2 | H9: =IF(AND(D9=E9,F9=G9),"done",IF(D9+F9>0,"started","not yet")) -> not yet | I9: =IF(H9="done",99,B9) -> 3
B10: 4 | C10: Build: Assemble the thing you will use, and tick it off | D10: =SUMIFS($E$19:$E$400,$A$19:$A$400,B10,$B$19:$B$400,"exercise") -> 0 | E10: =COUNTIFS($A$19:$A$400,B10,$B$19:$B$400,"exercise") -> 3 | F10: =SUMIFS($E$19:$E$400,$A$19:$A$400,B10,$B$19:$B$400,"check") -> 0 | G10: =COUNTIFS($A$19:$A$400,B10,$B$19:$B$400,"check") -> 5 | H10: =IF(AND(D10=E10,F10=G10),"done",IF(D10+F10>0,"started","not yet")) -> not yet | I10: =IF(H10="done",99,B10) -> 4
B11: 5 | C11: Run: Use it for a stretch and log what happened | D11: =SUMIFS($E$19:$E$400,$A$19:$A$400,B11,$B$19:$B$400,"exercise") -> 0 | E11: =COUNTIFS($A$19:$A$400,B11,$B$19:$B$400,"exercise") -> 5 | F11: =SUMIFS($E$19:$E$400,$A$19:$A$400,B11,$B$19:$B$400,"check") -> 0 | G11: =COUNTIFS($A$19:$A$400,B11,$B$19:$B$400,"check") -> 2 | H11: =IF(AND(D11=E11,F11=G11),"done",IF(D11+F11>0,"started","not yet")) -> not yet | I11: =IF(H11="done",99,B11) -> 5
B12: 6 | C12: Sharpen: The moves only visible once the numbers are real | D12: =SUMIFS($E$19:$E$400,$A$19:$A$400,B12,$B$19:$B$400,"exercise") -> 0 | E12: =COUNTIFS($A$19:$A$400,B12,$B$19:$B$400,"exercise") -> 2 | F12: =SUMIFS($E$19:$E$400,$A$19:$A$400,B12,$B$19:$B$400,"check") -> 0 | G12: =COUNTIFS($A$19:$A$400,B12,$B$19:$B$400,"check") -> 3 | H12: =IF(AND(D12=E12,F12=G12),"done",IF(D12+F12>0,"started","not yet")) -> not yet | I12: =IF(H12="done",99,B12) -> 6
C13: Levels done | D13: =COUNTIF(H7:H12,"done") -> 0 | F13: Yellow cells are yours to fill. A band is done when every yellow cell in it holds an answer and every checklist item is Y.
C14: Working on band | D14: =IF(MIN(I7:I12)=99,"complete",MIN(I7:I12)) -> 1
C15: Share of this planet answered | D15: =IF(SUM(E7:E12,G7:G12)=0,0,SUM(D7:D12,F7:F12)/SUM(E7:E12,G7:G12)) -> 0
A18: Band | B18: Kind | C18: Exercise or step | D18: Your answer | E18: ✓ | F18: Example | G18: What counts, where to look
A19: 1 | B19: band | C19: Band 1 · Read · reveal · about 6 min: What you spend and what comes back
B20: why | C20: Most people know their spend and not their cost per customer. Write the honest version, including "not yet".
A21: 1 | B21: exercise | C21: How well do you know your cost per customer from ads, 1 to 5 | E21: =IF(D21<>"",1,0) -> 0 | F21: 1 | G21: One is not at all, five is fully. Your honest read today.
A22: 1 | B22: exercise | C22: What you spend, where, and what you get, a sentence each | E22: =IF(D22<>"",1,0) -> 0 | G22: If you have never run an ad, write that, and write the top ad in your space in its three parts.
B23: head | C23: Checklist
A24: 1 | B24: check | C24: ☐ I have a number for cost per lead or I wrote not yet | E24: =IF(D24="Y",1,0) -> 0 | G24: Y when it is true.
A25: 1 | B25: check | C25: ☐ I looked at the best ad in my space and wrote its three parts | E25: =IF(D25="Y",1,0) -> 0 | G25: Y when it is true.
B26: checkpoint | C26: When this band is done: Your starting point on the planet is set.
A28: 2 | B28: band | C28: Band 2 · Facts · reveal · about 8 min: The chain, last month
B29: why | C29: Six counts, from the platform and the calendar. Each link in the chain is a rate you can fix on its own.
A30: 2 | B30: exercise | C30: Ad spend last month | E30: =IF(D30<>"",1,0) -> 0 | F30: 400 | G30: Whole dollars.
A31: 2 | B31: exercise | C31: Impressions last month | E31: =IF(D31<>"",1,0) -> 0 | F31: 50000 | G31: Times the ad was shown.
A32: 2 | B32: exercise | C32: Clicks last month | E32: =IF(D32<>"",1,0) -> 0 | F32: 900
A33: 2 | B33: exercise | C33: Leads from ads last month | E33: =IF(D33<>"",1,0) -> 0 | F33: 60 | G33: Opted in, replied or booked.
A34: 2 | B34: exercise | C34: Conversations booked from ads last month | E34: =IF(D34<>"",1,0) -> 0 | F34: 12
A35: 2 | B35: exercise | C35: Customers from ads last month | E35: =IF(D35<>"",1,0) -> 0 | F35: 3
B36: head | C36: Checklist
A37: 2 | B37: check | C37: ☐ The counts come from the platform and the calendar for the same month | E37: =IF(D37="Y",1,0) -> 0 | G37: Y when it is true.
B38: checkpoint | C38: When this band is done: The chain draws, the costs compute, and the ratio shows once Lifetime Value has its facts.
A40: 3 | B40: band | C40: Band 3 · Exercises · reveal · about 25 min: Ten call-outs, ten reasons, five asks
B41: why | C41: Write the three parts separately and in volume. The best ad is a combination you have not tried yet.
A42: 3 | B42: exercise | C42: Ten call-outs: who it is for, in their words, one a line | E42: =IF(D42<>"",1,0) -> 0 | G42: A job, a situation, a place, a thing they own, a thing they want. One a line: Alt+Enter starts a new line inside the cell.
A43: 3 | B43: exercise | C43: Ten value lines: the reason to keep watching, one a line | E43: =IF(D43<>"",1,0) -> 0 | G43: A result, a mistake, a number, a story, a demonstration. One a line: Alt+Enter starts a new line inside the cell.
A44: 3 | B44: exercise | C44: Five calls to action, one a line | E44: =IF(D44<>"",1,0) -> 0 | G44: One verb, one place, one reason to do it now. One a line: Alt+Enter starts a new line inside the cell.
B45: head | C45: Checklist
A46: 3 | B46: check | C46: ☐ Every call-out would make the right person stop | E46: =IF(D46="Y",1,0) -> 0 | G46: Y when it is true.
A47: 3 | B47: check | C47: ☐ Every value line is a claim the proof can back (see Proof Checklist) | E47: =IF(D47="Y",1,0) -> 0 | G47: Y when it is true.
B48: checkpoint | C48: When this band is done: The parts exist in volume.
A50: 4 | B50: band | C50: Band 4 · Build · power · about 20 min: The ad, in three versions
B51: why | C51: Assemble one ad from the parts, then two more with different hooks and the same offer. The landing place has to say the same thing as the ad.
A52: 4 | B52: exercise | C52: The ad, written out: call-out, value, call to action | E52: =IF(D52<>"",1,0) -> 0
A53: 4 | B53: exercise | C53: The format | E53: =IF(D53<>"",1,0) -> 0 | G53: Pick one from the dropdown.
A54: 4 | B54: exercise | C54: Where the click lands, and the one thing it asks | E54: =IF(D54<>"",1,0) -> 0
B55: head | C55: Checklist
A56: 4 | B56: check | C56: ☐ The call-out names the person in the first two seconds or the first line | E56: =IF(D56="Y",1,0) -> 0 | G56: Y when it is true.
A57: 4 | B57: check | C57: ☐ The value is a claim the proof can back | E57: =IF(D57="Y",1,0) -> 0 | G57: Y when it is true.
A58: 4 | B58: check | C58: ☐ One call to action, one place to go | E58: =IF(D58="Y",1,0) -> 0 | G58: Y when it is true.
A59: 4 | B59: check | C59: ☐ The landing place says the same thing as the ad | E59: =IF(D59="Y",1,0) -> 0 | G59: Y when it is true.
A60: 4 | B60: check | C60: ☐ Three versions exist: same offer, three hooks (see Hooks) | E60: =IF(D60="Y",1,0) -> 0 | G60: Y when it is true.
B61: checkpoint | C61: When this band is done: Three versions are ready to run.
A63: 5 | B63: band | C63: Band 5 · Run · certainty · about 10 min: Two weeks of spend
B64: why | C64: Run the three versions on a budget you can afford to lose. Count the chain again.
A65: 5 | B65: exercise | C65: Spend in the run | E65: =IF(D65<>"",1,0) -> 0 | G65: Whole dollars.
A66: 5 | B66: exercise | C66: Impressions in the run | E66: =IF(D66<>"",1,0) -> 0
A67: 5 | B67: exercise | C67: Clicks in the run | E67: =IF(D67<>"",1,0) -> 0
A68: 5 | B68: exercise | C68: Leads in the run | E68: =IF(D68<>"",1,0) -> 0
A69: 5 | B69: exercise | C69: Customers in the run | E69: =IF(D69<>"",1,0) -> 0
B70: head | C70: Checklist
A71: 5 | B71: check | C71: ☐ The budget was one I could lose without harm | E71: =IF(D71="Y",1,0) -> 0 | G71: Y when it is true.
A72: 5 | B72: check | C72: ☐ Each version got the same spend | E72: =IF(D72="Y",1,0) -> 0 | G72: Y when it is true.
B73: checkpoint | C73: When this band is done: Before and after costs per customer show.
A75: 6 | B75: band | C75: Band 6 · Sharpen · power · about 8 min: Which link, or scale
B76: why | C76: A weak click rate is a hook problem. Clicks that do not become leads is a page problem. Leads that do not buy is a sales problem. If the ratio holds at three to one, spend more.
A77: 6 | B77: exercise | C77: The next move | E77: =IF(D77<>"",1,0) -> 0 | G77: Pick one from the dropdown.
A78: 6 | B78: exercise | C78: Next month's budget | E78: =IF(D78<>"",1,0) -> 0 | G78: Whole dollars.
B79: head | C79: Checklist
A80: 6 | B80: check | C80: ☐ Cost per customer is on the weekly scorecard | E80: =IF(D80="Y",1,0) -> 0 | G80: Y when it is true.
A81: 6 | B81: check | C81: ☐ Losing versions are turned off inside a week | E81: =IF(D81="Y",1,0) -> 0 | G81: Y when it is true.
A82: 6 | B82: check | C82: ☐ The winning ad has a new hook in test beside it | E82: =IF(D82="Y",1,0) -> 0 | G82: Y when it is true.
B83: checkpoint | C83: When this band is done: The next move and the budget are decided.

Sheet Retention
C1: Retention | D1: Delivery system
C2: Keeping a customer is the cheapest sale you will ever make. The first days decide it.
C3: Every month a share of customers leave. That share sets how long an average customer stays: one divided by the monthly churn. Churn is highest early, so the first days matter most: a fast first win, a clear next step, and a person who checks in. Most churn has a reason you can name, and the reasons cluster. Count them, fix the biggest, and ask the ones who stay to bring a friend.
C5: Where you stand on this planet
B6: # | C6: Band | D6: Answered | E6: Of | F6: Ticked | G6: Of | H6: Status
B7: 1 | C7: Read: The one idea, and where you stand on it today | D7: =SUMIFS($E$19:$E$400,$A$19:$A$400,B7,$B$19:$B$400,"exercise") -> 0 | E7: =COUNTIFS($A$19:$A$400,B7,$B$19:$B$400,"exercise") -> 2 | F7: =SUMIFS($E$19:$E$400,$A$19:$A$400,B7,$B$19:$B$400,"check") -> 0 | G7: =COUNTIFS($A$19:$A$400,B7,$B$19:$B$400,"check") -> 2 | H7: =IF(AND(D7=E7,F7=G7),"done",IF(D7+F7>0,"started","not yet")) -> not yet | I7: =IF(H7="done",99,B7) -> 1
B8: 2 | C8: Facts: The few numbers this playbook runs on | D8: =SUMIFS($E$19:$E$400,$A$19:$A$400,B8,$B$19:$B$400,"exercise") -> 0 | E8: =COUNTIFS($A$19:$A$400,B8,$B$19:$B$400,"exercise") -> 3 | F8: =SUMIFS($E$19:$E$400,$A$19:$A$400,B8,$B$19:$B$400,"check") -> 0 | G8: =COUNTIFS($A$19:$A$400,B8,$B$19:$B$400,"check") -> 1 | H8: =IF(AND(D8=E8,F8=G8),"done",IF(D8+F8>0,"started","not yet")) -> not yet | I8: =IF(H8="done",99,B8) -> 2
B9: 3 | C9: Exercises: The pen and paper work the playbook asks for | D9: =SUMIFS($E$19:$E$400,$A$19:$A$400,B9,$B$19:$B$400,"exercise") -> 0 | E9: =COUNTIFS($A$19:$A$400,B9,$B$19:$B$400,"exercise") -> 3 | F9: =SUMIFS($E$19:$E$400,$A$19:$A$400,B9,$B$19:$B$400,"check") -> 0 | G9: =COUNTIFS($A$19:$A$400,B9,$B$19:$B$400,"check") -> 2 | H9: =IF(AND(D9=E9,F9=G9),"done",IF(D9+F9>0,"started","not yet")) -> not yet | I9: =IF(H9="done",99,B9) -> 3
B10: 4 | C10: Build: Assemble the thing you will use, and tick it off | D10: =SUMIFS($E$19:$E$400,$A$19:$A$400,B10,$B$19:$B$400,"exercise") -> 0 | E10: =COUNTIFS($A$19:$A$400,B10,$B$19:$B$400,"exercise") -> 2 | F10: =SUMIFS($E$19:$E$400,$A$19:$A$400,B10,$B$19:$B$400,"check") -> 0 | G10: =COUNTIFS($A$19:$A$400,B10,$B$19:$B$400,"check") -> 5 | H10: =IF(AND(D10=E10,F10=G10),"done",IF(D10+F10>0,"started","not yet")) -> not yet | I10: =IF(H10="done",99,B10) -> 4
B11: 5 | C11: Run: Use it for a stretch and log what happened | D11: =SUMIFS($E$19:$E$400,$A$19:$A$400,B11,$B$19:$B$400,"exercise") -> 0 | E11: =COUNTIFS($A$19:$A$400,B11,$B$19:$B$400,"exercise") -> 3 | F11: =SUMIFS($E$19:$E$400,$A$19:$A$400,B11,$B$19:$B$400,"check") -> 0 | G11: =COUNTIFS($A$19:$A$400,B11,$B$19:$B$400,"check") -> 1 | H11: =IF(AND(D11=E11,F11=G11),"done",IF(D11+F11>0,"started","not yet")) -> not yet | I11: =IF(H11="done",99,B11) -> 5
B12: 6 | C12: Sharpen: The moves only visible once the numbers are real | D12: =SUMIFS($E$19:$E$400,$A$19:$A$400,B12,$B$19:$B$400,"exercise") -> 0 | E12: =COUNTIFS($A$19:$A$400,B12,$B$19:$B$400,"exercise") -> 2 | F12: =SUMIFS($E$19:$E$400,$A$19:$A$400,B12,$B$19:$B$400,"check") -> 0 | G12: =COUNTIFS($A$19:$A$400,B12,$B$19:$B$400,"check") -> 3 | H12: =IF(AND(D12=E12,F12=G12),"done",IF(D12+F12>0,"started","not yet")) -> not yet | I12: =IF(H12="done",99,B12) -> 6
C13: Levels done | D13: =COUNTIF(H7:H12,"done") -> 0 | F13: Yellow cells are yours to fill. A band is done when every yellow cell in it holds an answer and every checklist item is Y.
C14: Working on band | D14: =IF(MIN(I7:I12)=99,"complete",MIN(I7:I12)) -> 1
C15: Share of this planet answered | D15: =IF(SUM(E7:E12,G7:G12)=0,0,SUM(D7:D12,F7:F12)/SUM(E7:E12,G7:G12)) -> 0
A18: Band | B18: Kind | C18: Exercise or step | D18: Your answer | E18: ✓ | F18: Example | G18: What counts, where to look
A19: 1 | B19: band | C19: Band 1 · Read · reveal · about 8 min: The first 48 hours, as they are
B20: why | C20: Write what a new customer experiences in their first two days with you, step by step. Then ask the last person who left why they went.
A21: 1 | B21: exercise | C21: How well do you know why customers leave, 1 to 5 | E21: =IF(D21<>"",1,0) -> 0 | F21: 2 | G21: One is not at all, five is fully. Your honest read today.
A22: 1 | B22: exercise | C22: A customer's first 48 hours, step by step | E22: =IF(D22<>"",1,0) -> 0 | G22: What arrives, who calls, what they are asked to do.
B23: head | C23: Checklist
A24: 1 | B24: check | C24: ☐ I know how many customers left last month | E24: =IF(D24="Y",1,0) -> 0 | G24: Y when it is true.
A25: 1 | B25: check | C25: ☐ I asked the last one who left why | E25: =IF(D25="Y",1,0) -> 0 | G25: Y when it is true.
B26: checkpoint | C26: When this band is done: Your starting point on the planet is set.
A28: 2 | B28: band | C28: Band 2 · Facts · reveal · about 6 min: Last month's churn
B29: why | C29: Two counts make the churn. One more says how long the first win takes.
A30: 2 | B30: exercise | C30: Customers at the start of last month | E30: =IF(D30<>"",1,0) -> 0 | F30: 30
A31: 2 | B31: exercise | C31: Customers who left during last month | E31: =IF(D31<>"",1,0) -> 0 | F31: 3
A32: 2 | B32: exercise | C32: Days until a new customer sees a first result, typical | E32: =IF(D32<>"",1,0) -> 0 | F32: 10
B33: head | C33: Checklist
A34: 2 | B34: check | C34: ☐ Left means stopped paying or cancelled, counted from the records | E34: =IF(D34="Y",1,0) -> 0 | G34: Y when it is true.
B35: checkpoint | C35: When this band is done: Churn, expected lifetime and the retention curve show.
A37: 3 | B37: band | C37: Band 3 · Exercises · reveal · about 25 min: The first win, the reasons, the steps
B38: why | C38: The first win is the smallest result a customer can get in week one. The reasons are every explanation you have heard for leaving, with a count. The steps are the first 48 hours rewritten.
A39: 3 | B39: exercise | C39: The first win, and the step that gets it | E39: =IF(D39<>"",1,0) -> 0 | G39: The smallest result a new customer can see in the first week.
A40: 3 | B40: exercise | C40: Every reason a customer gave for leaving, reason | count, one a line | D40: =IF(COUNTA(C42:D49)>0,"logged","") | E40: =IF(COUNTA(C42:D49)>0,1,0) -> 0 | G40: Fill the small table below, one row a line.
B41: logrow | C41: Reason given | D41: Count
B42: logrow
B43: logrow
B44: logrow
B45: logrow
B46: logrow
B47: logrow
B48: logrow
B49: logrow
A50: 3 | B50: exercise | C50: The first 48 hours, rewritten, one step a line | E50: =IF(D50<>"",1,0) -> 0 | G50: Who does what, when. One a line: Alt+Enter starts a new line inside the cell.
B51: head | C51: Checklist
A52: 3 | B52: check | C52: ☐ The first win is something a customer can see, not something I can see | E52: =IF(D52="Y",1,0) -> 0 | G52: Y when it is true.
A53: 3 | B53: check | C53: ☐ The reasons come from real customers, not guesses | E53: =IF(D53="Y",1,0) -> 0 | G53: Y when it is true.
B54: checkpoint | C54: When this band is done: The first win, the reasons and the new steps exist.
A56: 4 | B56: band | C56: Band 4 · Build · power · about 12 min: The check-ins and the referral ask
B57: why | C57: A person, not a form, checks in on day two and day seven. Every leaving customer is asked one question. Every staying customer is asked for a referral at the first win.
A58: 4 | B58: exercise | C58: The referral ask, word for word | E58: =IF(D58<>"",1,0) -> 0 | G58: Said at the first win, by a person.
A59: 4 | B59: exercise | C59: The one question a leaving customer is asked | E59: =IF(D59<>"",1,0) -> 0
B60: head | C60: Checklist
A61: 4 | B61: check | C61: ☐ The first win is scheduled inside the first week for every new customer | E61: =IF(D61="Y",1,0) -> 0 | G61: Y when it is true.
A62: 4 | B62: check | C62: ☐ A person checks in on day 2 and day 7 | E62: =IF(D62="Y",1,0) -> 0 | G62: Y when it is true.
A63: 4 | B63: check | C63: ☐ The next step is always visible to the customer | E63: =IF(D63="Y",1,0) -> 0 | G63: Y when it is true.
A64: 4 | B64: check | C64: ☐ A leaving customer is asked one question before they go | E64: =IF(D64="Y",1,0) -> 0 | G64: Y when it is true.
A65: 4 | B65: check | C65: ☐ A staying customer is asked for a referral at the first win | E65: =IF(D65="Y",1,0) -> 0 | G65: Y when it is true.
B66: checkpoint | C66: When this band is done: The delivery has check-ins, an exit question and a referral ask built in.
A68: 5 | B68: band | C68: Band 5 · Run · certainty · about 10 min: A month of the new first week
B69: why | C69: Count churn again on a month where every new customer got the new first week. Log each month's starters and how many are still here.
A70: 5 | B70: exercise | C70: Customers at the start of the run month | E70: =IF(D70<>"",1,0) -> 0 | F70: 32
A71: 5 | B71: exercise | C71: Customers who left in the run month | E71: =IF(D71<>"",1,0) -> 0 | F71: 2
A72: 5 | B72: exercise | C72: Cohorts: customers who started in a month and how many are still here | D72: =IF(COUNTA(C74:E81)>0,"logged","") | E72: =IF(COUNTA(C74:E81)>0,1,0) -> 0 | F72: e.g. Jan | 8 | 6 | G72: Fill the small table below, one row a line.
B73: logrow | C73: month | D73: started | E73: still here
B74: logrow
B75: logrow
B76: logrow
B77: logrow
B78: logrow
B79: logrow
B80: logrow
B81: logrow
B82: head | C82: Checklist
A83: 5 | B83: check | C83: ☐ Every new customer in the run got the day 2 and day 7 check-ins | E83: =IF(D83="Y",1,0) -> 0 | G83: Y when it is true.
B84: checkpoint | C84: When this band is done: Before and after churn, and the cohort bars, show.
A86: 6 | B86: band | C86: Band 6 · Sharpen · power · about 8 min: Onboarding, cadence, fit, or winback
B87: why | C87: The biggest churn reason gets an owner and a date. Everyone who left this quarter gets a winback message. Some churn is a sales problem: stop selling to the ones who leave.
A88: 6 | B88: exercise | C88: The next move | E88: =IF(D88<>"",1,0) -> 0 | G88: Pick one from the dropdown.
A89: 6 | B89: exercise | C89: The top churn reason, its owner, and the fix date | E89: =IF(D89<>"",1,0) -> 0
B90: head | C90: Checklist
A91: 6 | B91: check | C91: ☐ The top churn reason has an owner and a fix date | E91: =IF(D91="Y",1,0) -> 0 | G91: Y when it is true.
A92: 6 | B92: check | C92: ☐ A winback message went to everyone who left this quarter | E92: =IF(D92="Y",1,0) -> 0 | G92: Y when it is true.
A93: 6 | B93: check | C93: ☐ Churn is on the weekly scorecard | E93: =IF(D93="Y",1,0) -> 0 | G93: Y when it is true.
B94: checkpoint | C94: When this band is done: The next move is decided and the top reason has an owner.

Sheet Lifetime Value
C1: Lifetime Value | D1: Delivery system
C2: What a customer is worth over their whole stay, in gross profit. Every other number answers to this one.
C3: Lifetime gross profit is what a customer pays you over their stay, minus what it costs to deliver to them. It is the price, times the gross margin, times how many times they buy. There are only four ways to raise it: more customers, more per purchase, more purchases, and a longer stay. Know the number, then compare it to what a customer costs to get. Three to one is the rule of thumb below which a business feels like a treadmill.
C5: Where you stand on this planet
B6: # | C6: Band | D6: Answered | E6: Of | F6: Ticked | G6: Of | H6: Status
B7: 1 | C7: Read: The one idea, and where you stand on it today | D7: =SUMIFS($E$19:$E$400,$A$19:$A$400,B7,$B$19:$B$400,"exercise") -> 0 | E7: =COUNTIFS($A$19:$A$400,B7,$B$19:$B$400,"exercise") -> 2 | F7: =SUMIFS($E$19:$E$400,$A$19:$A$400,B7,$B$19:$B$400,"check") -> 0 | G7: =COUNTIFS($A$19:$A$400,B7,$B$19:$B$400,"check") -> 1 | H7: =IF(AND(D7=E7,F7=G7),"done",IF(D7+F7>0,"started","not yet")) -> not yet | I7: =IF(H7="done",99,B7) -> 1
B8: 2 | C8: Facts: The few numbers this playbook runs on | D8: =SUMIFS($E$19:$E$400,$A$19:$A$400,B8,$B$19:$B$400,"exercise") -> 0 | E8: =COUNTIFS($A$19:$A$400,B8,$B$19:$B$400,"exercise") -> 4 | F8: =SUMIFS($E$19:$E$400,$A$19:$A$400,B8,$B$19:$B$400,"check") -> 0 | G8: =COUNTIFS($A$19:$A$400,B8,$B$19:$B$400,"check") -> 2 | H8: =IF(AND(D8=E8,F8=G8),"done",IF(D8+F8>0,"started","not yet")) -> not yet | I8: =IF(H8="done",99,B8) -> 2
B9: 3 | C9: Exercises: The pen and paper work the playbook asks for | D9: =SUMIFS($E$19:$E$400,$A$19:$A$400,B9,$B$19:$B$400,"exercise") -> 0 | E9: =COUNTIFS($A$19:$A$400,B9,$B$19:$B$400,"exercise") -> 4 | F9: =SUMIFS($E$19:$E$400,$A$19:$A$400,B9,$B$19:$B$400,"check") -> 0 | G9: =COUNTIFS($A$19:$A$400,B9,$B$19:$B$400,"check") -> 1 | H9: =IF(AND(D9=E9,F9=G9),"done",IF(D9+F9>0,"started","not yet")) -> not yet | I9: =IF(H9="done",99,B9) -> 3
B10: 4 | C10: Build: Assemble the thing you will use, and tick it off | D10: =SUMIFS($E$19:$E$400,$A$19:$A$400,B10,$B$19:$B$400,"exercise") -> 0 | E10: =COUNTIFS($A$19:$A$400,B10,$B$19:$B$400,"exercise") -> 2 | F10: =SUMIFS($E$19:$E$400,$A$19:$A$400,B10,$B$19:$B$400,"check") -> 0 | G10: =COUNTIFS($A$19:$A$400,B10,$B$19:$B$400,"check") -> 4 | H10: =IF(AND(D10=E10,F10=G10),"done",IF(D10+F10>0,"started","not yet")) -> not yet | I10: =IF(H10="done",99,B10) -> 4
B11: 5 | C11: Run: Use it for a stretch and log what happened | D11: =SUMIFS($E$19:$E$400,$A$19:$A$400,B11,$B$19:$B$400,"exercise") -> 0 | E11: =COUNTIFS($A$19:$A$400,B11,$B$19:$B$400,"exercise") -> 4 | F11: =SUMIFS($E$19:$E$400,$A$19:$A$400,B11,$B$19:$B$400,"check") -> 0 | G11: =COUNTIFS($A$19:$A$400,B11,$B$19:$B$400,"check") -> 1 | H11: =IF(AND(D11=E11,F11=G11),"done",IF(D11+F11>0,"started","not yet")) -> not yet | I11: =IF(H11="done",99,B11) -> 5
B12: 6 | C12: Sharpen: The moves only visible once the numbers are real | D12: =SUMIFS($E$19:$E$400,$A$19:$A$400,B12,$B$19:$B$400,"exercise") -> 0 | E12: =COUNTIFS($A$19:$A$400,B12,$B$19:$B$400,"exercise") -> 1 | F12: =SUMIFS($E$19:$E$400,$A$19:$A$400,B12,$B$19:$B$400,"check") -> 0 | G12: =COUNTIFS($A$19:$A$400,B12,$B$19:$B$400,"check") -> 2 | H12: =IF(AND(D12=E12,F12=G12),"done",IF(D12+F12>0,"started","not yet")) -> not yet | I12: =IF(H12="done",99,B12) -> 6
C13: Levels done | D13: =COUNTIF(H7:H12,"done") -> 0 | F13: Yellow cells are yours to fill. A band is done when every yellow cell in it holds an answer and every checklist item is Y.
C14: Working on band | D14: =IF(MIN(I7:I12)=99,"complete",MIN(I7:I12)) -> 1
C15: Share of this planet answered | D15: =IF(SUM(E7:E12,G7:G12)=0,0,SUM(D7:D12,F7:F12)/SUM(E7:E12,G7:G12)) -> 0
A18: Band | B18: Kind | C18: Exercise or step | D18: Your answer | E18: ✓ | F18: Example | G18: What counts, where to look
A19: 1 | B19: band | C19: Band 1 · Read · reveal · about 4 min: Guess first
B20: why | C20: Write your guess before you look anything up. The gap between the guess and the number is the lesson.
A21: 1 | B21: exercise | C21: How sure are you what a customer is worth, 1 to 5 | E21: =IF(D21<>"",1,0) -> 0 | F21: 2 | G21: One is not at all, five is fully. Your honest read today.
A22: 1 | B22: exercise | C22: Your guess: what a customer pays you in total, and what it costs you to deliver | E22: =IF(D22<>"",1,0) -> 0 | F22: Maybe fifteen hundred, costs me a couple hundred to deliver.
B23: head | C23: Checklist
A24: 1 | B24: check | C24: ☐ I wrote the guess before looking anything up | E24: =IF(D24="Y",1,0) -> 0 | G24: Y when it is true.
B25: checkpoint | C25: When this band is done: Your starting point on the planet is set.
A27: 2 | B27: band | C27: Band 2 · Facts · reveal · about 10 min: Price, margin, purchases, cost to acquire
B28: why | C28: Four facts. Three make the value, the fourth is what it cost. These four are read by other playbooks, so they are typed here and nowhere else.
A29: 2 | B29: exercise | C29: Price of the main thing you sell, per purchase [shared: other playbooks read this] | E29: =IF(D29<>"",1,0) -> 0 | F29: 1500 | G29: Whole dollars.
A30: 2 | B30: exercise | C30: Gross margin: the share of the price left after delivery costs [shared: other playbooks read this] | E30: =IF(D30<>"",1,0) -> 0 | F30: 0.8 | G30: If it costs you 30 of every 100 to deliver, the margin is 70. Type it as a percentage, for example 80%.
A31: 2 | B31: exercise | C31: Purchases per customer over their stay | E31: =IF(D31<>"",1,0) -> 0 | F31: 1.5 | G31: For a monthly thing, the months they stay. See Retention for the churn that sets it.
A32: 2 | B32: exercise | C32: Cost to get one customer [shared: other playbooks read this] | E32: =IF(D32<>"",1,0) -> 0 | F32: 400 | G32: All marketing and sales spend in a month, divided by new customers that month. Whole dollars.
B33: head | C33: Checklist
A34: 2 | B34: check | C34: ☐ Gross margin is measured from real delivery costs, not guessed | E34: =IF(D34="Y",1,0) -> 0 | G34: Y when it is true.
A35: 2 | B35: check | C35: ☐ Cost to acquire includes people's time, not only ad spend | E35: =IF(D35="Y",1,0) -> 0 | G35: Y when it is true.
B36: checkpoint | C36: When this band is done: Lifetime gross profit and its ratio to acquisition cost show.
A38: 3 | B38: band | C38: Band 3 · Exercises · reveal · about 15 min: One move per lever
B39: why | C39: Four levers, one move each. Write the move, not the wish.
A40: 3 | B40: exercise | C40: More customers: the one move | E40: =IF(D40<>"",1,0) -> 0
A41: 3 | B41: exercise | C41: More per purchase: what could ride along with the main thing | E41: =IF(D41<>"",1,0) -> 0
A42: 3 | B42: exercise | C42: More purchases: what brings them back sooner | E42: =IF(D42<>"",1,0) -> 0
A43: 3 | B43: exercise | C43: A longer stay: what makes staying easy or leaving costly | E43: =IF(D43<>"",1,0) -> 0
B44: head | C44: Checklist
A45: 3 | B45: check | C45: ☐ Each move is something that could start this month | E45: =IF(D45="Y",1,0) -> 0 | G45: Y when it is true.
B46: checkpoint | C46: When this band is done: Four moves exist.
A48: 4 | B48: band | C48: Band 4 · Build · power · about 6 min: Pick one lever for the quarter
B49: why | C49: One lever, one target, ninety days. The picture shows what each lever does to the value at ten percent.
A50: 4 | B50: exercise | C50: The lever for this quarter | E50: =IF(D50<>"",1,0) -> 0 | G50: Pick one from the dropdown.
A51: 4 | B51: exercise | C51: The target for that lever in ninety days, as a number | E51: =IF(D51<>"",1,0) -> 0
B52: head | C52: Checklist
A53: 4 | B53: check | C53: ☐ Gross margin is measured, not guessed | E53: =IF(D53="Y",1,0) -> 0 | G53: Y when it is true.
A54: 4 | B54: check | C54: ☐ The four levers each have one move written | E54: =IF(D54="Y",1,0) -> 0 | G54: Y when it is true.
A55: 4 | B55: check | C55: ☐ One lever is picked for the quarter | E55: =IF(D55="Y",1,0) -> 0 | G55: Y when it is true.
A56: 4 | B56: check | C56: ☐ The ratio of value to cost is on the weekly scorecard | E56: =IF(D56="Y",1,0) -> 0 | G56: Y when it is true.
B57: checkpoint | C57: When this band is done: One lever is chosen with a number on it.
A59: 5 | B59: band | C59: Band 5 · Run · certainty · about 8 min: The quarter's numbers
B60: why | C60: Same four facts, ninety days later.
A61: 5 | B61: exercise | C61: Price after the quarter | E61: =IF(D61<>"",1,0) -> 0 | G61: Whole dollars.
A62: 5 | B62: exercise | C62: Gross margin after the quarter | E62: =IF(D62<>"",1,0) -> 0 | G62: Type it as a percentage, for example 80%.
A63: 5 | B63: exercise | C63: Purchases per customer after the quarter | E63: =IF(D63<>"",1,0) -> 0
A64: 5 | B64: exercise | C64: Cost to get one customer after the quarter | E64: =IF(D64<>"",1,0) -> 0 | G64: Whole dollars.
B65: head | C65: Checklist
A66: 5 | B66: check | C66: ☐ The four numbers were recomputed from records, not adjusted from memory | E66: =IF(D66="Y",1,0) -> 0 | G66: Y when it is true.
B67: checkpoint | C67: When this band is done: Before and after value and ratio show.
A69: 6 | B69: band | C69: Band 6 · Sharpen · power · about 4 min: Which playbook moves it next
B70: why | C70: Each lever has a playbook. The ratio tells you which one you need.
A71: 6 | B71: exercise | C71: The next playbook | E71: =IF(D71<>"",1,0) -> 0 | G71: Pick one from the dropdown.
B72: head | C72: Checklist
A73: 6 | B73: check | C73: ☐ Lifetime gross profit is recomputed monthly from real numbers | E73: =IF(D73="Y",1,0) -> 0 | G73: Y when it is true.
A74: 6 | B74: check | C74: ☐ Every offer decision is checked against the ratio first | E74: =IF(D74="Y",1,0) -> 0 | G74: Y when it is true.
B75: checkpoint | C75: When this band is done: The next playbook is chosen.

Sheet Branding
C1: Branding | D1: Delivery system
C2: A brand is what people already like, tied to your name, on purpose, over and over.
C3: A brand is an association: you, paired with things a group of people already wants, enough times that the pairing sticks. It is built by choosing who you are for, what you stand beside, and what you will never do, and then being boringly consistent about all three. The test is simple: can a customer describe you in one sentence, and does it match the sentence you wrote.
C5: Where you stand on this planet
B6: # | C6: Band | D6: Answered | E6: Of | F6: Ticked | G6: Of | H6: Status
B7: 1 | C7: Read: The one idea, and where you stand on it today | D7: =SUMIFS($E$19:$E$400,$A$19:$A$400,B7,$B$19:$B$400,"exercise") -> 0 | E7: =COUNTIFS($A$19:$A$400,B7,$B$19:$B$400,"exercise") -> 2 | F7: =SUMIFS($E$19:$E$400,$A$19:$A$400,B7,$B$19:$B$400,"check") -> 0 | G7: =COUNTIFS($A$19:$A$400,B7,$B$19:$B$400,"check") -> 2 | H7: =IF(AND(D7=E7,F7=G7),"done",IF(D7+F7>0,"started","not yet")) -> not yet | I7: =IF(H7="done",99,B7) -> 1
B8: 2 | C8: Facts: The few numbers this playbook runs on | D8: =SUMIFS($E$19:$E$400,$A$19:$A$400,B8,$B$19:$B$400,"exercise") -> 0 | E8: =COUNTIFS($A$19:$A$400,B8,$B$19:$B$400,"exercise") -> 3 | F8: =SUMIFS($E$19:$E$400,$A$19:$A$400,B8,$B$19:$B$400,"check") -> 0 | G8: =COUNTIFS($A$19:$A$400,B8,$B$19:$B$400,"check") -> 1 | H8: =IF(AND(D8=E8,F8=G8),"done",IF(D8+F8>0,"started","not yet")) -> not yet | I8: =IF(H8="done",99,B8) -> 2
B9: 3 | C9: Exercises: The pen and paper work the playbook asks for | D9: =SUMIFS($E$19:$E$400,$A$19:$A$400,B9,$B$19:$B$400,"exercise") -> 0 | E9: =COUNTIFS($A$19:$A$400,B9,$B$19:$B$400,"exercise") -> 3 | F9: =SUMIFS($E$19:$E$400,$A$19:$A$400,B9,$B$19:$B$400,"check") -> 0 | G9: =COUNTIFS($A$19:$A$400,B9,$B$19:$B$400,"check") -> 2 | H9: =IF(AND(D9=E9,F9=G9),"done",IF(D9+F9>0,"started","not yet")) -> not yet | I9: =IF(H9="done",99,B9) -> 3
B10: 4 | C10: Build: Assemble the thing you will use, and tick it off | D10: =SUMIFS($E$19:$E$400,$A$19:$A$400,B10,$B$19:$B$400,"exercise") -> 0 | E10: =COUNTIFS($A$19:$A$400,B10,$B$19:$B$400,"exercise") -> 2 | F10: =SUMIFS($E$19:$E$400,$A$19:$A$400,B10,$B$19:$B$400,"check") -> 0 | G10: =COUNTIFS($A$19:$A$400,B10,$B$19:$B$400,"check") -> 5 | H10: =IF(AND(D10=E10,F10=G10),"done",IF(D10+F10>0,"started","not yet")) -> not yet | I10: =IF(H10="done",99,B10) -> 4
B11: 5 | C11: Run: Use it for a stretch and log what happened | D11: =SUMIFS($E$19:$E$400,$A$19:$A$400,B11,$B$19:$B$400,"exercise") -> 0 | E11: =COUNTIFS($A$19:$A$400,B11,$B$19:$B$400,"exercise") -> 3 | F11: =SUMIFS($E$19:$E$400,$A$19:$A$400,B11,$B$19:$B$400,"check") -> 0 | G11: =COUNTIFS($A$19:$A$400,B11,$B$19:$B$400,"check") -> 1 | H11: =IF(AND(D11=E11,F11=G11),"done",IF(D11+F11>0,"started","not yet")) -> not yet | I11: =IF(H11="done",99,B11) -> 5
B12: 6 | C12: Sharpen: The moves only visible once the numbers are real | D12: =SUMIFS($E$19:$E$400,$A$19:$A$400,B12,$B$19:$B$400,"exercise") -> 0 | E12: =COUNTIFS($A$19:$A$400,B12,$B$19:$B$400,"exercise") -> 2 | F12: =SUMIFS($E$19:$E$400,$A$19:$A$400,B12,$B$19:$B$400,"check") -> 0 | G12: =COUNTIFS($A$19:$A$400,B12,$B$19:$B$400,"check") -> 2 | H12: =IF(AND(D12=E12,F12=G12),"done",IF(D12+F12>0,"started","not yet")) -> not yet | I12: =IF(H12="done",99,B12) -> 6
C13: Levels done | D13: =COUNTIF(H7:H12,"done") -> 0 | F13: Yellow cells are yours to fill. A band is done when every yellow cell in it holds an answer and every checklist item is Y.
C14: Working on band | D14: =IF(MIN(I7:I12)=99,"complete",MIN(I7:I12)) -> 1
C15: Share of this planet answered | D15: =IF(SUM(E7:E12,G7:G12)=0,0,SUM(D7:D12,F7:F12)/SUM(E7:E12,G7:G12)) -> 0
A18: Band | B18: Kind | C18: Exercise or step | D18: Your answer | E18: ✓ | F18: Example | G18: What counts, where to look
A19: 1 | B19: band | C19: Band 1 · Read · reveal · about 10 min: Three customers describe you
B20: why | C20: Ask three real customers to describe you in one sentence. Write their words exactly. The gap between their sentence and yours is the work.
A21: 1 | B21: exercise | C21: Could a stranger say what you stand for after one look, 1 to 5 | E21: =IF(D21<>"",1,0) -> 0 | F21: 2 | G21: One is not at all, five is fully. Your honest read today.
A22: 1 | B22: exercise | C22: Three customers describe you in a sentence each | E22: =IF(D22<>"",1,0) -> 0 | G22: Their words, not yours.
B23: head | C23: Checklist
A24: 1 | B24: check | C24: ☐ I asked three real people | E24: =IF(D24="Y",1,0) -> 0 | G24: Y when it is true.
A25: 1 | B25: check | C25: ☐ I wrote their words, not mine | E25: =IF(D25="Y",1,0) -> 0 | G25: Y when it is true.
B26: checkpoint | C26: When this band is done: Your starting point on the planet is set.
A28: 2 | B28: band | C28: Band 2 · Facts · reveal · about 6 min: The sentence and the touches
B29: why | C29: Your sentence, and how often your people see you in a week, and how many of those times looked like the same brand.
A30: 2 | B30: exercise | C30: Your sentence: who you are for and what you stand beside | E30: =IF(D30<>"",1,0) -> 0 | F30: For young professionals who freeze at money: calm, plain, no judgement.
A31: 2 | B31: exercise | C31: Times a week your name shows up in front of your people | E31: =IF(D31<>"",1,0) -> 0 | F31: 12 | G31: Posts, emails, mentions, ads.
A32: 2 | B32: exercise | C32: Of those, how many looked and sounded like the same brand | E32: =IF(D32<>"",1,0) -> 0 | F32: 7
B33: head | C33: Checklist
A34: 2 | B34: check | C34: ☐ The touches were counted from a week's actual output | E34: =IF(D34="Y",1,0) -> 0 | G34: Y when it is true.
B35: checkpoint | C35: When this band is done: Consistency shows as a meter.
A37: 3 | B37: band | C37: Band 3 · Exercises · reveal · about 20 min: Ten to stand beside, five to never touch
B38: why | C38: Associations are chosen, not discovered. Ten things your people already love that you can honestly stand beside. Five things you will never do or be seen with. Five fixed elements so the pairing looks the same every time.
A39: 3 | B39: exercise | C39: Ten things your people already love that you can honestly stand beside, one a line | E39: =IF(D39<>"",1,0) -> 0 | F39: Calm Plain words Index funds Small wins No judgement | G39: Ideas, results, places, values, people. One a line: Alt+Enter starts a new line inside the cell.
A40: 3 | B40: exercise | C40: Five things you will never do or be seen with, one a line | E40: =IF(D40<>"",1,0) -> 0 | F40: Crypto tips Shame | G40: One a line: Alt+Enter starts a new line inside the cell.
A41: 3 | B41: exercise | C41: The five fixed elements, one a line | E41: =IF(D41<>"",1,0) -> 0 | F41: Deep blue One question a week | G41: A colour, a font, a phrase, a format, a name for your people. One a line: Alt+Enter starts a new line inside the cell.
B42: head | C42: Checklist
A43: 3 | B43: check | C43: ☐ Each of the ten is something I would still stand beside in five years | E43: =IF(D43="Y",1,0) -> 0 | G43: Y when it is true.
A44: 3 | B44: check | C44: ☐ The never list has things I have actually been tempted by | E44: =IF(D44="Y",1,0) -> 0 | G44: Y when it is true.
B45: checkpoint | C45: When this band is done: The lists exist.
A47: 4 | B47: band | C47: Band 4 · Build · power · about 12 min: The one-page guide
B48: why | C48: Everything on one page: the sentence, the ten, the five nevers, the five fixed elements. Then one format that repeats weekly under the same name.
A49: 4 | B49: exercise | C49: Where the one-page guide lives | E49: =IF(D49<>"",1,0) -> 0
A50: 4 | B50: exercise | C50: The weekly format and its name | E50: =IF(D50<>"",1,0) -> 0 | G50: The Friday number, the Monday question: a format your people can expect.
B51: head | C51: Checklist
A52: 4 | B52: check | C52: ☐ The sentence is on the home page and the profile | E52: =IF(D52="Y",1,0) -> 0 | G52: Y when it is true.
A53: 4 | B53: check | C53: ☐ The five fixed elements are in a one-page guide | E53: =IF(D53="Y",1,0) -> 0 | G53: Y when it is true.
A54: 4 | B54: check | C54: ☐ Every post this week pairs the name with one of the ten | E54: =IF(D54="Y",1,0) -> 0 | G54: Y when it is true.
A55: 4 | B55: check | C55: ☐ Nothing this week touches the never list | E55: =IF(D55="Y",1,0) -> 0 | G55: Y when it is true.
A56: 4 | B56: check | C56: ☐ One format repeats weekly under the same name | E56: =IF(D56="Y",1,0) -> 0 | G56: Y when it is true.
B57: checkpoint | C57: When this band is done: The guide is written and the weekly format is named.
A59: 5 | B59: band | C59: Band 5 · Run · certainty · about 10 min: A month on brand
B60: why | C60: Count the touches and how many matched the guide. Then ask three customers again.
A61: 5 | B61: exercise | C61: Touches in the run month | E61: =IF(D61<>"",1,0) -> 0
A62: 5 | B62: exercise | C62: Touches that matched the guide | E62: =IF(D62<>"",1,0) -> 0
A63: 5 | B63: exercise | C63: Three customers describe you again, after the run | E63: =IF(D63<>"",1,0) -> 0
B64: head | C64: Checklist
A65: 5 | B65: check | C65: ☐ The three were asked the same question as in band 1 | E65: =IF(D65="Y",1,0) -> 0 | G65: Y when it is true.
B66: checkpoint | C66: When this band is done: Before and after consistency show, and the descriptions sit beside the sentence.
A68: 6 | B68: band | C68: Band 6 · Sharpen · power · about 6 min: Narrower, louder, tighter, or bigger
B69: why | C69: If the descriptions match the sentence, get louder. If they do not, narrow who it is for or tighten the touches. Pairing with a name your people already trust is the fastest jump.
A70: 6 | B70: exercise | C70: The next move | E70: =IF(D70<>"",1,0) -> 0 | G70: Pick one from the dropdown.
A71: 6 | B71: exercise | C71: The name you could stand beside, and how | E71: =IF(D71<>"",1,0) -> 0 | G71: A person, a place, an event, a cause. Or none yet.
B72: head | C72: Checklist
A73: 6 | B73: check | C73: ☐ Off-brand touches went to zero for a month | E73: =IF(D73="Y",1,0) -> 0 | G73: Y when it is true.
A74: 6 | B74: check | C74: ☐ The three descriptions match the sentence | E74: =IF(D74="Y",1,0) -> 0 | G74: Y when it is true.
B75: checkpoint | C75: When this band is done: The next move is decided.

Sheet Price Raise
C1: Price Raise | D1: Profit system
C2: Most businesses are underpriced. The math says how many customers you can lose on a raise and still come out ahead.
C3: Price is the number the value earns. When you raise it some customers leave, and the question is how many you can lose before the raise stops paying. With a gross margin, the breakeven loss is the raise divided by the margin plus the raise: at a 70 percent margin, a 20 percent raise can lose about a fifth of customers and make the same profit. Raise price after you have raised value, tell existing customers before, and give them a reason the new price is fair.
C5: Where you stand on this planet
B6: # | C6: Band | D6: Answered | E6: Of | F6: Ticked | G6: Of | H6: Status
B7: 1 | C7: Read: The one idea, and where you stand on it today | D7: =SUMIFS($E$19:$E$400,$A$19:$A$400,B7,$B$19:$B$400,"exercise") -> 0 | E7: =COUNTIFS($A$19:$A$400,B7,$B$19:$B$400,"exercise") -> 3 | F7: =SUMIFS($E$19:$E$400,$A$19:$A$400,B7,$B$19:$B$400,"check") -> 0 | G7: =COUNTIFS($A$19:$A$400,B7,$B$19:$B$400,"check") -> 1 | H7: =IF(AND(D7=E7,F7=G7),"done",IF(D7+F7>0,"started","not yet")) -> not yet | I7: =IF(H7="done",99,B7) -> 1
B8: 2 | C8: Facts: The few numbers this playbook runs on | D8: =SUMIFS($E$19:$E$400,$A$19:$A$400,B8,$B$19:$B$400,"exercise") -> 0 | E8: =COUNTIFS($A$19:$A$400,B8,$B$19:$B$400,"exercise") -> 4 | F8: =SUMIFS($E$19:$E$400,$A$19:$A$400,B8,$B$19:$B$400,"check") -> 0 | G8: =COUNTIFS($A$19:$A$400,B8,$B$19:$B$400,"check") -> 1 | H8: =IF(AND(D8=E8,F8=G8),"done",IF(D8+F8>0,"started","not yet")) -> not yet | I8: =IF(H8="done",99,B8) -> 2
B9: 3 | C9: Exercises: The pen and paper work the playbook asks for | D9: =SUMIFS($E$19:$E$400,$A$19:$A$400,B9,$B$19:$B$400,"exercise") -> 0 | E9: =COUNTIFS($A$19:$A$400,B9,$B$19:$B$400,"exercise") -> 3 | F9: =SUMIFS($E$19:$E$400,$A$19:$A$400,B9,$B$19:$B$400,"check") -> 0 | G9: =COUNTIFS($A$19:$A$400,B9,$B$19:$B$400,"check") -> 2 | H9: =IF(AND(D9=E9,F9=G9),"done",IF(D9+F9>0,"started","not yet")) -> not yet | I9: =IF(H9="done",99,B9) -> 3
B10: 4 | C10: Build: Assemble the thing you will use, and tick it off | D10: =SUMIFS($E$19:$E$400,$A$19:$A$400,B10,$B$19:$B$400,"exercise") -> 0 | E10: =COUNTIFS($A$19:$A$400,B10,$B$19:$B$400,"exercise") -> 2 | F10: =SUMIFS($E$19:$E$400,$A$19:$A$400,B10,$B$19:$B$400,"check") -> 0 | G10: =COUNTIFS($A$19:$A$400,B10,$B$19:$B$400,"check") -> 5 | H10: =IF(AND(D10=E10,F10=G10),"done",IF(D10+F10>0,"started","not yet")) -> not yet | I10: =IF(H10="done",99,B10) -> 4
B11: 5 | C11: Run: Use it for a stretch and log what happened | D11: =SUMIFS($E$19:$E$400,$A$19:$A$400,B11,$B$19:$B$400,"exercise") -> 0 | E11: =COUNTIFS($A$19:$A$400,B11,$B$19:$B$400,"exercise") -> 2 | F11: =SUMIFS($E$19:$E$400,$A$19:$A$400,B11,$B$19:$B$400,"check") -> 0 | G11: =COUNTIFS($A$19:$A$400,B11,$B$19:$B$400,"check") -> 1 | H11: =IF(AND(D11=E11,F11=G11),"done",IF(D11+F11>0,"started","not yet")) -> not yet | I11: =IF(H11="done",99,B11) -> 5
B12: 6 | C12: Sharpen: The moves only visible once the numbers are real | D12: =SUMIFS($E$19:$E$400,$A$19:$A$400,B12,$B$19:$B$400,"exercise") -> 0 | E12: =COUNTIFS($A$19:$A$400,B12,$B$19:$B$400,"exercise") -> 1 | F12: =SUMIFS($E$19:$E$400,$A$19:$A$400,B12,$B$19:$B$400,"check") -> 0 | G12: =COUNTIFS($A$19:$A$400,B12,$B$19:$B$400,"check") -> 2 | H12: =IF(AND(D12=E12,F12=G12),"done",IF(D12+F12>0,"started","not yet")) -> not yet | I12: =IF(H12="done",99,B12) -> 6
C13: Levels done | D13: =COUNTIF(H7:H12,"done") -> 0 | F13: Yellow cells are yours to fill. A band is done when every yellow cell in it holds an answer and every checklist item is Y.
C14: Working on band | D14: =IF(MIN(I7:I12)=99,"complete",MIN(I7:I12)) -> 1
C15: Share of this planet answered | D15: =IF(SUM(E7:E12,G7:G12)=0,0,SUM(D7:D12,F7:F12)/SUM(E7:E12,G7:G12)) -> 0
A18: Band | B18: Kind | C18: Exercise or step | D18: Your answer | E18: ✓ | F18: Example | G18: What counts, where to look
A19: 1 | B19: band | C19: Band 1 · Read · reveal · about 6 min: Why is your price what it is
B20: why | C20: Most prices are inherited, copied, or set once in a nervous moment. Write the honest reason, and find the highest price in your market.
A21: 1 | B21: exercise | C21: How recent is your last raise, 1 (years ago or never) to 5 (this quarter) | E21: =IF(D21<>"",1,0) -> 0 | F21: 1 | G21: One is not at all, five is fully. Your honest read today.
A22: 1 | B22: exercise | C22: Why your price is what it is, honestly | E22: =IF(D22<>"",1,0) -> 0
A23: 1 | B23: exercise | C23: The highest price in your market, and who charges it | E23: =IF(D23<>"",1,0) -> 0 | F23: 5000 | G23: The number. Put the name in the line above if you like. Whole dollars.
B24: head | C24: Checklist
A25: 1 | B25: check | C25: ☐ I know the highest price in my market and who charges it | E25: =IF(D25="Y",1,0) -> 0 | G25: Y when it is true.
B26: checkpoint | C26: When this band is done: Your starting point on the planet is set.
A28: 2 | B28: band | C28: Band 2 · Facts · reveal · about 5 min: The raise you are considering
B29: why | C29: The price and the margin are read from Lifetime Value. Add how many buy a month and the raise you have in mind.
A30: 2 | B30: exercise | C30: Price of the main thing you sell, per purchase (read from Lifetime Value, band 2) | D30: =IF('Lifetime Value'!$D$29="","",'Lifetime Value'!$D$29) | E30: =IF(D30<>"",1,0) -> 0 | G30: Typed once, in Lifetime Value. This cell only reads it.
A31: 2 | B31: exercise | C31: Gross margin: the share of the price left after delivery costs (read from Lifetime Value, band 2) | D31: =IF('Lifetime Value'!$D$30="","",'Lifetime Value'!$D$30) | E31: =IF(D31<>"",1,0) -> 0 | G31: Typed once, in Lifetime Value. This cell only reads it.
A32: 2 | B32: exercise | C32: Customers who buy per month at the current price | E32: =IF(D32<>"",1,0) -> 0 | F32: 5
A33: 2 | B33: exercise | C33: The raise you are considering, as a share of the price | E33: =IF(D33<>"",1,0) -> 0 | F33: 0.2 | G33: 20 means a fifth more. Type it as a percentage, for example 80%.
B34: head | C34: Checklist
A35: 2 | B35: check | C35: ☐ The raise is a number, not a feeling | E35: =IF(D35="Y",1,0) -> 0 | G35: Y when it is true.
B36: checkpoint | C36: When this band is done: The breakeven loss and the profit curve show.
A38: 3 | B38: band | C38: Band 3 · Exercises · reveal · about 15 min: Raise the value first, then write the message
B39: why | C39: Value goes up before price does: faster, surer, easier, less effort. Then the message to existing customers, and the choice of what they keep.
A40: 3 | B40: exercise | C40: Five ways to raise the value before the price, one a line | E40: =IF(D40<>"",1,0) -> 0 | G40: Faster to the result, more likely to work, easier to do, less to give up. One a line: Alt+Enter starts a new line inside the cell.
A41: 3 | B41: exercise | C41: The message to existing customers | E41: =IF(D41<>"",1,0) -> 0 | G41: What changed, when, and what they keep.
A42: 3 | B42: exercise | C42: What existing customers keep | E42: =IF(D42<>"",1,0) -> 0 | G42: Pick one from the dropdown.
B43: head | C43: Checklist
A44: 3 | B44: check | C44: ☐ At least two of the five value adds can ship this month | E44: =IF(D44="Y",1,0) -> 0 | G44: Y when it is true.
A45: 3 | B45: check | C45: ☐ The message says a date | E45: =IF(D45="Y",1,0) -> 0 | G45: Y when it is true.
B46: checkpoint | C46: When this band is done: The value adds and the message exist.
A48: 4 | B48: band | C48: Band 4 · Build · power · about 6 min: The new price and the date
B49: why | C49: A number and a day. Everything that shows a price changes on that day.
A50: 4 | B50: exercise | C50: The new price | E50: =IF(D50<>"",1,0) -> 0 | G50: Whole dollars.
A51: 4 | B51: exercise | C51: The date it takes effect | E51: =IF(D51<>"",1,0) -> 0
B52: head | C52: Checklist
A53: 4 | B53: check | C53: ☐ The value adds ship before the raise | E53: =IF(D53="Y",1,0) -> 0 | G53: Y when it is true.
A54: 4 | B54: check | C54: ☐ Existing customers hear it from a person, before the date | E54: =IF(D54="Y",1,0) -> 0 | G54: Y when it is true.
A55: 4 | B55: check | C55: ☐ The new price is on every page and script on the date | E55: =IF(D55="Y",1,0) -> 0 | G55: Y when it is true.
A56: 4 | B56: check | C56: ☐ The sales script says the price once, without apology (see Closing Handbook) | E56: =IF(D56="Y",1,0) -> 0 | G56: Y when it is true.
A57: 4 | B57: check | C57: ☐ The breakeven loss is written down and watched | E57: =IF(D57="Y",1,0) -> 0 | G57: Y when it is true.
B58: checkpoint | C58: When this band is done: The raise is scheduled.
A60: 5 | B60: band | C60: Band 5 · Run · certainty · about 6 min: The first month at the new price
B61: why | C61: Count who bought and what they actually paid.
A62: 5 | B62: exercise | C62: Customers who bought in the first month at the new price | E62: =IF(D62<>"",1,0) -> 0
A63: 5 | B63: exercise | C63: Average price actually paid that month | E63: =IF(D63<>"",1,0) -> 0 | G63: Whole dollars.
B64: head | C64: Checklist
A65: 5 | B65: check | C65: ☐ Discounts given in the month are in the average, not hidden | E65: =IF(D65="Y",1,0) -> 0 | G65: Y when it is true.
B66: checkpoint | C66: When this band is done: Profit before and after shows, against the breakeven line.
A68: 6 | B68: band | C68: Band 6 · Sharpen · power · about 4 min: Again, hold, above, or below
B69: why | C69: If the loss was well under breakeven, raise again next quarter. If it was near, hold. A tier above and an entry below are both ways to raise the average without touching the middle.
A70: 6 | B70: exercise | C70: The next move | E70: =IF(D70<>"",1,0) -> 0 | G70: Pick one from the dropdown.
B71: head | C71: Checklist
A72: 6 | B72: check | C72: ☐ Price is reviewed every quarter, on the calendar | E72: =IF(D72="Y",1,0) -> 0 | G72: Y when it is true.
A73: 6 | B73: check | C73: ☐ The highest tier is priced above the market's highest | E73: =IF(D73="Y",1,0) -> 0 | G73: Y when it is true.
B74: checkpoint | C74: When this band is done: The next move is decided.

Sheet Promo Cash
C1: Promo Cash | D1: Profit system
C2: Make more from a customer in the first thirty days than it costs to get and serve them. Then growth pays for itself.
C3: A money model is the order of offers a customer meets. It starts with an attraction offer that gets a stranger to say yes: win your money back, a free thing with a string attached, a discount for a commitment, a giveaway, or a decoy beside the real thing. Then the offers that follow: an upsell at the moment of yes, a downsell for the no, and continuity so the money keeps arriving. The target is that the gross profit collected in the first thirty days is more than it cost to acquire and deliver. Then every customer funds the next one.
C5: Where you stand on this planet
B6: # | C6: Band | D6: Answered | E6: Of | F6: Ticked | G6: Of | H6: Status
B7: 1 | C7: Read: The one idea, and where you stand on it today | D7: =SUMIFS($E$19:$E$400,$A$19:$A$400,B7,$B$19:$B$400,"exercise") -> 0 | E7: =COUNTIFS($A$19:$A$400,B7,$B$19:$B$400,"exercise") -> 2 | F7: =SUMIFS($E$19:$E$400,$A$19:$A$400,B7,$B$19:$B$400,"check") -> 0 | G7: =COUNTIFS($A$19:$A$400,B7,$B$19:$B$400,"check") -> 1 | H7: =IF(AND(D7=E7,F7=G7),"done",IF(D7+F7>0,"started","not yet")) -> not yet | I7: =IF(H7="done",99,B7) -> 1
B8: 2 | C8: Facts: The few numbers this playbook runs on | D8: =SUMIFS($E$19:$E$400,$A$19:$A$400,B8,$B$19:$B$400,"exercise") -> 0 | E8: =COUNTIFS($A$19:$A$400,B8,$B$19:$B$400,"exercise") -> 4 | F8: =SUMIFS($E$19:$E$400,$A$19:$A$400,B8,$B$19:$B$400,"check") -> 0 | G8: =COUNTIFS($A$19:$A$400,B8,$B$19:$B$400,"check") -> 1 | H8: =IF(AND(D8=E8,F8=G8),"done",IF(D8+F8>0,"started","not yet")) -> not yet | I8: =IF(H8="done",99,B8) -> 2
B9: 3 | C9: Exercises: The pen and paper work the playbook asks for | D9: =SUMIFS($E$19:$E$400,$A$19:$A$400,B9,$B$19:$B$400,"exercise") -> 0 | E9: =COUNTIFS($A$19:$A$400,B9,$B$19:$B$400,"exercise") -> 5 | F9: =SUMIFS($E$19:$E$400,$A$19:$A$400,B9,$B$19:$B$400,"check") -> 0 | G9: =COUNTIFS($A$19:$A$400,B9,$B$19:$B$400,"check") -> 2 | H9: =IF(AND(D9=E9,F9=G9),"done",IF(D9+F9>0,"started","not yet")) -> not yet | I9: =IF(H9="done",99,B9) -> 3
B10: 4 | C10: Build: Assemble the thing you will use, and tick it off | D10: =SUMIFS($E$19:$E$400,$A$19:$A$400,B10,$B$19:$B$400,"exercise") -> 0 | E10: =COUNTIFS($A$19:$A$400,B10,$B$19:$B$400,"exercise") -> 2 | F10: =SUMIFS($E$19:$E$400,$A$19:$A$400,B10,$B$19:$B$400,"check") -> 0 | G10: =COUNTIFS($A$19:$A$400,B10,$B$19:$B$400,"check") -> 5 | H10: =IF(AND(D10=E10,F10=G10),"done",IF(D10+F10>0,"started","not yet")) -> not yet | I10: =IF(H10="done",99,B10) -> 4
B11: 5 | C11: Run: Use it for a stretch and log what happened | D11: =SUMIFS($E$19:$E$400,$A$19:$A$400,B11,$B$19:$B$400,"exercise") -> 0 | E11: =COUNTIFS($A$19:$A$400,B11,$B$19:$B$400,"exercise") -> 3 | F11: =SUMIFS($E$19:$E$400,$A$19:$A$400,B11,$B$19:$B$400,"check") -> 0 | G11: =COUNTIFS($A$19:$A$400,B11,$B$19:$B$400,"check") -> 1 | H11: =IF(AND(D11=E11,F11=G11),"done",IF(D11+F11>0,"started","not yet")) -> not yet | I11: =IF(H11="done",99,B11) -> 5
B12: 6 | C12: Sharpen: The moves only visible once the numbers are real | D12: =SUMIFS($E$19:$E$400,$A$19:$A$400,B12,$B$19:$B$400,"exercise") -> 0 | E12: =COUNTIFS($A$19:$A$400,B12,$B$19:$B$400,"exercise") -> 1 | F12: =SUMIFS($E$19:$E$400,$A$19:$A$400,B12,$B$19:$B$400,"check") -> 0 | G12: =COUNTIFS($A$19:$A$400,B12,$B$19:$B$400,"check") -> 2 | H12: =IF(AND(D12=E12,F12=G12),"done",IF(D12+F12>0,"started","not yet")) -> not yet | I12: =IF(H12="done",99,B12) -> 6
C13: Levels done | D13: =COUNTIF(H7:H12,"done") -> 0 | F13: Yellow cells are yours to fill. A band is done when every yellow cell in it holds an answer and every checklist item is Y.
C14: Working on band | D14: =IF(MIN(I7:I12)=99,"complete",MIN(I7:I12)) -> 1
C15: Share of this planet answered | D15: =IF(SUM(E7:E12,G7:G12)=0,0,SUM(D7:D12,F7:F12)/SUM(E7:E12,G7:G12)) -> 0
A18: Band | B18: Kind | C18: Exercise or step | D18: Your answer | E18: ✓ | F18: Example | G18: What counts, where to look
A19: 1 | B19: band | C19: Band 1 · Read · reveal · about 5 min: The order of offers, as it is
B20: why | C20: Write the sequence a customer meets today, first offer to last. Most businesses have one.
A21: 1 | B21: exercise | C21: Does a new customer pay for their own acquisition in 30 days, 1 (no idea) to 5 (yes, measured) | E21: =IF(D21<>"",1,0) -> 0 | F21: 1 | G21: One is not at all, five is fully. Your honest read today.
A22: 1 | B22: exercise | C22: The order of offers a customer meets today, first to last | E22: =IF(D22<>"",1,0) -> 0
B23: head | C23: Checklist
A24: 1 | B24: check | C24: ☐ I wrote the order as it is, not as I wish it were | E24: =IF(D24="Y",1,0) -> 0 | G24: Y when it is true.
B25: checkpoint | C25: When this band is done: Your starting point on the planet is set.
A27: 2 | B27: band | C27: Band 2 · Facts · reveal · about 8 min: Thirty-day cash and cost
B28: why | C28: What a new customer pays in their first thirty days, what it costs to serve them in that time, and the cost to get them, which is read from Lifetime Value.
A29: 2 | B29: exercise | C29: Cost to get one customer (read from Lifetime Value, band 2) | D29: =IF('Lifetime Value'!$D$32="","",'Lifetime Value'!$D$32) | E29: =IF(D29<>"",1,0) -> 0 | G29: Typed once, in Lifetime Value. This cell only reads it.
A30: 2 | B30: exercise | C30: Cash collected from a new customer in the first 30 days, typical | E30: =IF(D30<>"",1,0) -> 0 | F30: 1500 | G30: Whole dollars.
A31: 2 | B31: exercise | C31: Cost to deliver to that customer in the first 30 days | E31: =IF(D31<>"",1,0) -> 0 | F31: 200 | G31: Whole dollars.
A32: 2 | B32: exercise | C32: Share of new customers who take an upsell today | E32: =IF(D32<>"",1,0) -> 0 | F32: 0 | G32: Zero if there is no upsell. Blank if you do not know. Type it as a percentage, for example 80%.
B33: head | C33: Checklist
A34: 2 | B34: check | C34: ☐ Cash is what arrived, not what was invoiced | E34: =IF(D34="Y",1,0) -> 0 | G34: Y when it is true.
B35: checkpoint | C35: When this band is done: The thirty-day cash picture and its ratio show.
A37: 3 | B37: band | C37: Band 3 · Exercises · reveal · about 20 min: Attraction, upsell, downsell, continuity
B38: why | C38: Four offers, one sentence each. The attraction offer gets the yes. The upsell rides the yes. The downsell keeps the no in the door. Continuity keeps the money arriving.
A39: 3 | B39: exercise | C39: Your attraction offer kind | E39: =IF(D39<>"",1,0) -> 0 | G39: Pick one from the dropdown.
A40: 3 | B40: exercise | C40: The attraction offer in one sentence | E40: =IF(D40<>"",1,0) -> 0
A41: 3 | B41: exercise | C41: The upsell offered at the moment of yes, and its price | E41: =IF(D41<>"",1,0) -> 0
A42: 3 | B42: exercise | C42: The downsell for the no | E42: =IF(D42<>"",1,0) -> 0 | G42: A payment plan, a trial, a smaller version.
A43: 3 | B43: exercise | C43: The continuity, and the reason to stay | E43: =IF(D43<>"",1,0) -> 0 | G43: A bonus, a waived fee, a term price.
B44: head | C44: Checklist
A45: 3 | B45: check | C45: ☐ The attraction offer has a string that leads to the paid thing | E45: =IF(D45="Y",1,0) -> 0 | G45: Y when it is true.
A46: 3 | B46: check | C46: ☐ The upsell is offered inside the yes, not a week later | E46: =IF(D46="Y",1,0) -> 0 | G46: Y when it is true.
B47: checkpoint | C47: When this band is done: The four offers exist.
A49: 4 | B49: band | C49: Band 4 · Build · power · about 6 min: Price the upsell and expect a take rate
B50: why | C50: A number for the upsell and a share you expect to take it. The picture redraws with them.
A51: 4 | B51: exercise | C51: The upsell price | E51: =IF(D51<>"",1,0) -> 0 | F51: 500 | G51: Whole dollars.
A52: 4 | B52: exercise | C52: The share you expect to take the upsell | E52: =IF(D52<>"",1,0) -> 0 | F52: 0.3 | G52: Type it as a percentage, for example 80%.
B53: head | C53: Checklist
A54: 4 | B54: check | C54: ☐ The attraction offer has a string that leads to the paid thing | E54: =IF(D54="Y",1,0) -> 0 | G54: Y when it is true.
A55: 4 | B55: check | C55: ☐ The upsell is offered inside the yes | E55: =IF(D55="Y",1,0) -> 0 | G55: Y when it is true.
A56: 4 | B56: check | C56: ☐ The downsell keeps a no in the door | E56: =IF(D56="Y",1,0) -> 0 | G56: Y when it is true.
A57: 4 | B57: check | C57: ☐ Continuity has a reason to stay written into it | E57: =IF(D57="Y",1,0) -> 0 | G57: Y when it is true.
A58: 4 | B58: check | C58: ☐ Thirty-day cash is measured per customer, not per month | E58: =IF(D58="Y",1,0) -> 0 | G58: Y when it is true.
B59: checkpoint | C59: When this band is done: The money model is priced.
A61: 5 | B61: band | C61: Band 5 · Run · certainty · about 8 min: A month of new customers
B62: why | C62: Every new customer in the run month, their cash in thirty days, and what they cost to get and serve.
A63: 5 | B63: exercise | C63: New customers in the run month | E63: =IF(D63<>"",1,0) -> 0
A64: 5 | B64: exercise | C64: Cash collected from them in their first 30 days, total | E64: =IF(D64<>"",1,0) -> 0 | G64: Whole dollars.
A65: 5 | B65: exercise | C65: Cost to acquire and deliver them in 30 days, total | E65: =IF(D65<>"",1,0) -> 0 | G65: Whole dollars.
B66: head | C66: Checklist
A67: 5 | B67: check | C67: ☐ Every new customer met the full sequence | E67: =IF(D67="Y",1,0) -> 0 | G67: Y when it is true.
B68: checkpoint | C68: When this band is done: Before and after thirty-day ratios show.
A70: 6 | B70: band | C70: Band 6 · Sharpen · power · about 4 min: The string, the take, continuity, or cost
B71: why | C71: Four ways to move the ratio. Draw the model on one page: offer, then offer, then offer.
A72: 6 | B72: exercise | C72: The next move | E72: =IF(D72<>"",1,0) -> 0 | G72: Pick one from the dropdown.
B73: head | C73: Checklist
A74: 6 | B74: check | C74: ☐ The thirty-day ratio is on the weekly scorecard | E74: =IF(D74="Y",1,0) -> 0 | G74: Y when it is true.
A75: 6 | B75: check | C75: ☐ The money model is drawn on one page: offer, then offer, then offer | E75: =IF(D75="Y",1,0) -> 0 | G75: Y when it is true.
B76: checkpoint | C76: When this band is done: The next move is decided.

Sheet Implementation SOPs
C1: Implementation SOPs | D1: Profit system
C2: A playbook only counts when someone other than you can run it. Write it down, give it a number, look at the number weekly.
C3: The other eleven playbooks each end with a thing to run and a number to watch. This one turns them into an operating rhythm: a one-page procedure for each (purpose, owner, steps, the checklist, the number it moves), a weekly scorecard with the few numbers that matter, and a meeting short enough to happen every week. The test of a written procedure is a new person running it without you in the room.
C5: Where you stand on this planet
B6: # | C6: Band | D6: Answered | E6: Of | F6: Ticked | G6: Of | H6: Status
B7: 1 | C7: Read: The one idea, and where you stand on it today | D7: =SUMIFS($E$19:$E$400,$A$19:$A$400,B7,$B$19:$B$400,"exercise") -> 0 | E7: =COUNTIFS($A$19:$A$400,B7,$B$19:$B$400,"exercise") -> 2 | F7: =SUMIFS($E$19:$E$400,$A$19:$A$400,B7,$B$19:$B$400,"check") -> 0 | G7: =COUNTIFS($A$19:$A$400,B7,$B$19:$B$400,"check") -> 1 | H7: =IF(AND(D7=E7,F7=G7),"done",IF(D7+F7>0,"started","not yet")) -> not yet | I7: =IF(H7="done",99,B7) -> 1
B8: 2 | C8: Facts: The few numbers this playbook runs on | D8: =SUMIFS($E$19:$E$400,$A$19:$A$400,B8,$B$19:$B$400,"exercise") -> 0 | E8: =COUNTIFS($A$19:$A$400,B8,$B$19:$B$400,"exercise") -> 3 | F8: =SUMIFS($E$19:$E$400,$A$19:$A$400,B8,$B$19:$B$400,"check") -> 0 | G8: =COUNTIFS($A$19:$A$400,B8,$B$19:$B$400,"check") -> 1 | H8: =IF(AND(D8=E8,F8=G8),"done",IF(D8+F8>0,"started","not yet")) -> not yet | I8: =IF(H8="done",99,B8) -> 2
B9: 3 | C9: Exercises: The pen and paper work the playbook asks for | D9: =SUMIFS($E$19:$E$400,$A$19:$A$400,B9,$B$19:$B$400,"exercise") -> 0 | E9: =COUNTIFS($A$19:$A$400,B9,$B$19:$B$400,"exercise") -> 3 | F9: =SUMIFS($E$19:$E$400,$A$19:$A$400,B9,$B$19:$B$400,"check") -> 0 | G9: =COUNTIFS($A$19:$A$400,B9,$B$19:$B$400,"check") -> 2 | H9: =IF(AND(D9=E9,F9=G9),"done",IF(D9+F9>0,"started","not yet")) -> not yet | I9: =IF(H9="done",99,B9) -> 3
B10: 4 | C10: Build: Assemble the thing you will use, and tick it off | D10: =SUMIFS($E$19:$E$400,$A$19:$A$400,B10,$B$19:$B$400,"exercise") -> 0 | E10: =COUNTIFS($A$19:$A$400,B10,$B$19:$B$400,"exercise") -> 1 | F10: =SUMIFS($E$19:$E$400,$A$19:$A$400,B10,$B$19:$B$400,"check") -> 0 | G10: =COUNTIFS($A$19:$A$400,B10,$B$19:$B$400,"check") -> 5 | H10: =IF(AND(D10=E10,F10=G10),"done",IF(D10+F10>0,"started","not yet")) -> not yet | I10: =IF(H10="done",99,B10) -> 4
B11: 5 | C11: Run: Use it for a stretch and log what happened | D11: =SUMIFS($E$19:$E$400,$A$19:$A$400,B11,$B$19:$B$400,"exercise") -> 0 | E11: =COUNTIFS($A$19:$A$400,B11,$B$19:$B$400,"exercise") -> 2 | F11: =SUMIFS($E$19:$E$400,$A$19:$A$400,B11,$B$19:$B$400,"check") -> 0 | G11: =COUNTIFS($A$19:$A$400,B11,$B$19:$B$400,"check") -> 1 | H11: =IF(AND(D11=E11,F11=G11),"done",IF(D11+F11>0,"started","not yet")) -> not yet | I11: =IF(H11="done",99,B11) -> 5
B12: 6 | C12: Sharpen: The moves only visible once the numbers are real | D12: =SUMIFS($E$19:$E$400,$A$19:$A$400,B12,$B$19:$B$400,"exercise") -> 0 | E12: =COUNTIFS($A$19:$A$400,B12,$B$19:$B$400,"exercise") -> 2 | F12: =SUMIFS($E$19:$E$400,$A$19:$A$400,B12,$B$19:$B$400,"check") -> 0 | G12: =COUNTIFS($A$19:$A$400,B12,$B$19:$B$400,"check") -> 3 | H12: =IF(AND(D12=E12,F12=G12),"done",IF(D12+F12>0,"started","not yet")) -> not yet | I12: =IF(H12="done",99,B12) -> 6
C13: Levels done | D13: =COUNTIF(H7:H12,"done") -> 0 | F13: Yellow cells are yours to fill. A band is done when every yellow cell in it holds an answer and every checklist item is Y.
C14: Working on band | D14: =IF(MIN(I7:I12)=99,"complete",MIN(I7:I12)) -> 1
C15: Share of this planet answered | D15: =IF(SUM(E7:E12,G7:G12)=0,0,SUM(D7:D12,F7:F12)/SUM(E7:E12,G7:G12)) -> 0
A18: Band | B18: Kind | C18: Exercise or step | D18: Your answer | E18: ✓ | F18: Example | G18: What counts, where to look
A19: 1 | B19: band | C19: Band 1 · Read · reveal · about 6 min: The things only you can do
B20: why | C20: List them without softening. Each one is a procedure that has not been written yet.
A21: 1 | B21: exercise | C21: How much of your business runs without you, 1 to 5 | E21: =IF(D21<>"",1,0) -> 0 | F21: 1 | G21: One is not at all, five is fully. Your honest read today.
A22: 1 | B22: exercise | C22: The things only you can do today, one a line | E22: =IF(D22<>"",1,0) -> 0 | G22: One a line: Alt+Enter starts a new line inside the cell.
B23: head | C23: Checklist
A24: 1 | B24: check | C24: ☐ I wrote the list without softening it | E24: =IF(D24="Y",1,0) -> 0 | G24: Y when it is true.
B25: checkpoint | C25: When this band is done: Your starting point on the planet is set.
A27: 2 | B27: band | C27: Band 2 · Facts · reveal · about 6 min: Written, handed off, and your hours
B28: why | C28: Three counts: procedures that exist on paper, procedures someone else runs, and the hours a week you spend on work someone else could do.
A29: 2 | B29: exercise | C29: Procedures written down today | E29: =IF(D29<>"",1,0) -> 0 | F29: 4
A30: 2 | B30: exercise | C30: Of those, how many someone else runs | E30: =IF(D30<>"",1,0) -> 0 | F30: 1
A31: 2 | B31: exercise | C31: Hours a week you spend on work someone else could do | E31: =IF(D31<>"",1,0) -> 0 | F31: 15
B32: head | C32: Checklist
A33: 2 | B33: check | C33: ☐ The hours come from a week actually tracked | E33: =IF(D33="Y",1,0) -> 0 | G33: Y when it is true.
B34: checkpoint | C34: When this band is done: The handoff meter and the owner hours show.
A36: 3 | B36: band | C36: Band 3 · Exercises · reveal · about 25 min: Twelve procedures, one written now, the scorecard
B37: why | C37: One line per playbook with an owner. Then write one procedure in full to learn the shape. Then choose the scorecard: at most eight numbers.
A38: 3 | B38: exercise | C38: The twelve procedures, one a line: procedure | owner | D38: =IF(COUNTA(C40:D47)>0,"logged","") | E38: =IF(COUNTA(C40:D47)>0,1,0) -> 0 | G38: Fill the small table below, one row a line.
B39: logrow | C39: Procedure | D39: Owner
B40: logrow
B41: logrow
B42: logrow
B43: logrow
B44: logrow
B45: logrow
B46: logrow
B47: logrow
A48: 3 | B48: exercise | C48: One procedure, in full | E48: =IF(D48<>"",1,0) -> 0 | G48: Purpose. Owner. Steps. The checklist. The number it moves.
A49: 3 | B49: exercise | C49: The scorecard, at most eight numbers, one a line: number | the playbook it comes from | D49: =IF(COUNTA(C51:D58)>0,"logged","") | E49: =IF(COUNTA(C51:D58)>0,1,0) -> 0 | G49: Fill the small table below, one row a line.
B50: logrow | C50: Number | D50: Playbook it comes from
B51: logrow
B52: logrow
B53: logrow
B54: logrow
B55: logrow
B56: logrow
B57: logrow
B58: logrow
B59: head | C59: Checklist
A60: 3 | B60: check | C60: ☐ Every procedure has a named owner, even if it is me for now | E60: =IF(D60="Y",1,0) -> 0 | G60: Y when it is true.
A61: 3 | B61: check | C61: ☐ The scorecard has no number nobody would act on | E61: =IF(D61="Y",1,0) -> 0 | G61: Y when it is true.
B62: checkpoint | C62: When this band is done: The list, one full procedure and the scorecard exist.
A64: 4 | B64: band | C64: Band 4 · Build · power · about 5 min: The weekly meeting
B65: why | C65: Day, time, length, who. The scorecard is filled before it, and it ends with one change.
A66: 4 | B66: exercise | C66: The weekly meeting: day, time, length, who | E66: =IF(D66<>"",1,0) -> 0
B67: head | C67: Checklist
A68: 4 | B68: check | C68: ☐ Every procedure fits on one page | E68: =IF(D68="Y",1,0) -> 0 | G68: Y when it is true.
A69: 4 | B69: check | C69: ☐ Every procedure names a number | E69: =IF(D69="Y",1,0) -> 0 | G69: Y when it is true.
A70: 4 | B70: check | C70: ☐ The scorecard is filled before the meeting, not in it | E70: =IF(D70="Y",1,0) -> 0 | G70: Y when it is true.
A71: 4 | B71: check | C71: ☐ One procedure was run by someone else this week | E71: =IF(D71="Y",1,0) -> 0 | G71: Y when it is true.
A72: 4 | B72: check | C72: ☐ The meeting ends with one change, not ten | E72: =IF(D72="Y",1,0) -> 0 | G72: Y when it is true.
B73: checkpoint | C73: When this band is done: The rhythm is set.
A75: 5 | B75: band | C75: Band 5 · Run · certainty · about 10 min: Four weeks of scorecard
B76: why | C76: One row a week. Four numbers are enough to start: leads, sales, customers kept, cash collected.
A77: 5 | B77: exercise | C77: The scorecard, one row a week | D77: =IF(COUNTA(C79:G86)>0,"logged","") | E77: =IF(COUNTA(C79:G86)>0,1,0) -> 0 | F77: e.g. 1 | 22 | 4 | 30 | 5000 | G77: Cash in whole dollars. Fill the small table below, one row a line.
B78: logrow | C78: week | D78: leads | E78: sales | F78: kept | G78: cash
B79: logrow
B80: logrow
B81: logrow
B82: logrow
B83: logrow
B84: logrow
B85: logrow
B86: logrow
A87: 5 | B87: exercise | C87: Hours a week on work someone else could do, after four weeks | E87: =IF(D87<>"",1,0) -> 0 | F87: 9
B88: head | C88: Checklist
A89: 5 | B89: check | C89: ☐ Four weeks in a row were filled before the meeting | E89: =IF(D89="Y",1,0) -> 0 | G89: Y when it is true.
B90: checkpoint | C90: When this band is done: The scorecard draws as lines, and owner hours before and after show.
A92: 6 | B92: band | C92: Band 6 · Sharpen · power · about 5 min: Hand off, cut, fix, or hire
B93: why | C93: One more procedure handed off. One number cut if nobody uses it. The one that fell, fixed. And the biggest owner-only task is a hire.
A94: 6 | B94: exercise | C94: The next move | E94: =IF(D94<>"",1,0) -> 0 | G94: Pick one from the dropdown.
A95: 6 | B95: exercise | C95: The procedure to hand off next, and to whom | E95: =IF(D95<>"",1,0) -> 0
B96: head | C96: Checklist
A97: 6 | B97: check | C97: ☐ Four weeks of scorecard exist | E97: =IF(D97="Y",1,0) -> 0 | G97: Y when it is true.
A98: 6 | B98: check | C98: ☐ Owner-only hours fell this month | E98: =IF(D98="Y",1,0) -> 0 | G98: Y when it is true.
A99: 6 | B99: check | C99: ☐ Every playbook in this binder has its procedure written | E99: =IF(D99="Y",1,0) -> 0 | G99: Y when it is true.
B100: checkpoint | C100: When this band is done: The next move is decided.
