Workbook

Sheet Start Here
A1: SLAM
A2: Stress Less About Money. How every decision flows to profit, in one workbook.
A4: Three steps
A5: 1 | B5: Open the My Numbers tab and fill the pink cells. | C5: Start with just three: contacts last month, how many booked, and your price. Every other pink cell already holds a typical number; change it when you know better.
A6: 2 | B6: Read This Month. | C6: Your profit, what each business brings, and the one step where the money leaks. Everything on it updates itself.
A7: 3 | B7: Each week, add a row to Check-in. | C7: Five numbers, one minute. After four weeks the sheet tells you whether your real weeks match the model.
A9: How to read the cells
B10: Pink cell | C10: Yours to type. Nothing else needs touching.
B11: White cell | C11: Computed. It updates itself; leave it alone.
B12: Gold note | C12: An estimate or a caution the sheet wants you to see.
B13: Green note | C13: Good news: on track, or above the goal.
A15: The tabs
B16: My Numbers | C16: Every number you can change, with a typical value and where to find yours.
B17: This Month | C17: Profit, gross profit, hours, each business, the bottleneck, and the charts.
B18: Levers | C18: What one small move on each number does to your month.
B19: Three Futures | C19: Normal, Dream and Disaster side by side, and how long your cash lasts.
B20: Plan | C20: What your goal needs, what your offer is worth per hour, and what a client is worth over time.
B21: Check-in | C21: One row a week. Four weeks in, the sheet compares your real weeks to the model.
B22: Clients | C22: A list of aliases and stages. Never names, never documents.
B23: Definitions | C23: Every word and every formula, in plain English.
A25: Three promises
B26: Empty is not zero. Leave a pink cell blank and This Month counts the blanks and tells you, rather than quietly treating it as a zero.
B27: Screening is never a sales step. Nothing here suggests loosening it.
B28: This file is yours. Keep it somewhere private. Its name says nothing about what you do.
B30: SLAM gives no legal, tax or investment advice; for those, ask a professional. Some frameworks follow ideas published by Alex Hormozi; SLAM is independent and not affiliated.

Sheet My Numbers
A1: My Numbers
A2: Pink cells are yours. Each one comes with a typical number already in it, so every tab works from the first minute. Change what you know; leave the rest.
A4: Shared: the numbers every business reads
B5: What | C5: Yours | D5: Typical | E5: Where to look, and what to do with no idea
B6: Hours a week you can work (all of it: sessions, messages, posting, admin) | C6: 40 | D6: 30 | E6: Think of last week: days worked times hours each. Most land between 20 and 40.
B7: Days off a week (never zero) | C7: 2 | D7: 2 | E7: How many days in the last two weeks were fully off? Two is common.
B8: Money that leaves every month whether you work or not | C8: 1500 | D8: 1500 | E8: Last month's bank statement: rent for a space, subscriptions, phone, insurance, tools. Guess low rather than skip.
B9: What you want left for yourself each month | C9: 10000 | D9: 6000 | E9: Your rent and bills plus what you want on top. Start with what makes you feel safe.
B10: Share to set aside for tax (a reminder line only) | C10: 0.25 | D10: 0.25 | E10: Ask an accountant for your rate; a quarter is a common placeholder. No tax advice here.
B11: Cash you could live on if nothing came in | C11: 9000 | E11: Savings you could reach this week. Leave empty and Runway says "not yet".
B12: What an hour of your time is worth to you | C12: 100 | D12: 100 | E12: Profit last month divided by hours worked is a fine start. Used to compare a move's hours with its money.
B13: Money spent finding clients a month (ads, listings, promo) | C13: 0 | D13: 0 | E13: Card statement. If you pay nothing to be found, 0 is right.
B14: Hours a month spent finding clients (posting, replying, listings) | C14: 0 | D14: 10 | E14: A normal week times four.
A16: In person
B17: What | C17: Yours | D17: Typical | E17: Where to look, and what to do with no idea
B18: Counted? (Yes or No) | C18: Yes | D18: Yes | E18: No means it leaves every total.
B19: Priority (1 = your main engine; it gets your hours first) | C19: 1 | D19: 1 | E19: Each counted business needs a different number.
B20: People who contacted you last month | C20: 60 | D20: 60 | E20: Inbox, DMs, booking form. Count new names once, before screening. No idea? Count last week and multiply by four.
B21: Share who pass your screening | C21: 0.5 | D21: 0.5 | E21: Of the last 10 who contacted you, how many passed? Times 10 is the percent. Your screening is yours; nothing here suggests loosening it.
B22: Share of screened people who book | C22: 0.4 | D22: 0.4 | E22: Of the last 10 who passed, how many booked? Type contacts and bookings on This Month if that is easier.
B23: Share of bookings who turn up | C23: 0.85 | D23: 0.85 | E23: Of your last 10 bookings, how many happened? 8 or 9 in 10 with a deposit.
B24: Extra sessions per new client (30% = every 10 new clients bring 3 more sessions) | C24: 0.3 | D24: 0.3 | E24: Of your last 10 new clients, how many booked again? Times 10 is the percent.
B25: Most sessions you want in a month (blank = no cap; your hours still cap it) | C25: 18 | E25: Your busiest month you would happily repeat.
B26: Price of one session | C26: 500 | D26: 500 | E26: Your rate card.
B27: What one session costs you to deliver (space, travel, supplies) | C27: 100 | D27: 100 | E27: Think of your last one and what you paid out to make it happen. Guess low.
B28: Hours one session really takes, all in (prep, travel, the session, recovery, messages) | C28: 4 | D28: 4 | E28: Most people undercount. Double what the session itself takes.
B29: Cut a platform or processor takes from each sale | C29: 0.05 | D29: 0.05 | E29: Payouts page, or the gap between the price and what lands in your account.
B30: Add-on offered? (Yes or No) | C30: Yes | D30: Yes
B31: Add-on price | C31: 200 | D31: 200 | E31: Your rate card.
B32: Share of new clients who take the add-on | C32: 0.25 | D32: 0.25 | E32: Of your last 10 new clients, how many took it?
B33: Retainer offered? (Yes or No) | C33: Yes | D33: Yes
B34: Retainer price a month | C34: 1500 | D34: 1500 | E34: Your arrangement.
B35: Sessions a month the retainer includes | C35: 2 | D35: 2
B36: Share of new clients who take the retainer | C36: 0.1 | D36: 0.1 | E36: One in ten is a common start.
B37: Months a retainer client usually stays | C37: 4 | D37: 4 | E37: Think of the last few. How long did they stay?
B38: Program (several sessions over weeks) as the main offer? (Yes or No) | C38: No | D38: No | E38: Yes turns the funnel into consultations: price, sessions, close rate and hours below apply, and the single session, add-on and retainer are not counted.
B39: Program price | C39: 3000 | D39: 3000
B40: Sessions the program includes | C40: 4 | D40: 4
B41: Share of consultations that say yes | C41: 0.4 | D41: 0.4 | E41: Of your last 10 conversations, how many went ahead?
B42: What the whole program costs you to deliver | C42: 400 | D42: 400
B43: Cut taken on the program | C43: 0.05 | D43: 0.05
B44: Hours the whole program takes, all in | C44: 14 | D44: 14
A46: Content
B47: What | C47: Yours | D47: Typical | E47: Where to look, and what to do with no idea
B48: Counted? (Yes or No) | C48: Yes | D48: Yes
B49: Priority | C49: 2 | D49: 2
B50: Followers, all platforms together | C50: 5000 | D50: 5000 | E50: Each app shows it on your profile. Add the two biggest and stop.
B51: Share of followers who subscribe each month | C51: 0.01 | D51: 0.01 | E51: New subscribers last month divided by followers.
B52: Paying subscribers right now | C52: 150 | D52: 150 | E52: The app knows; copy the number.
B53: Share of subscribers who leave each month | C53: 0.2 | D53: 0.2 | E53: Cancelled this month divided by subscribers. One in five is common.
B54: Subscription price a month | C54: 15 | D54: 15 | E54: Your profile shows it.
B55: Cut the platform keeps on subscriptions | C55: 0.2 | D55: 0.2 | E55: 20% means you keep 80.
B56: Customs a month | C56: 10 | D56: 10 | E56: Your messages or order list.
B57: Custom price | C57: 100 | D57: 100
B58: Cut the platform keeps on customs | C58: 0.2 | D58: 0.2
B59: Hours one custom takes | C59: 1 | D59: 1
B60: Digital products sold a month | C60: 0 | D60: 0 | E60: 0 if you do not sell these.
B61: Digital product price | C61: 150 | D61: 150
B62: What you keep of it | C62: 140 | D62: 140
B63: Hours a month on content, all in | C63: 40 | D63: 40 | E63: A normal week times four.
A65: Calls
B66: What | C66: Yours | D66: Typical | E66: Where to look, and what to do with no idea
B67: Counted? (Yes or No) | C67: Yes | D67: Yes
B68: Priority | C68: 3 | D68: 3
B69: Calls a month (rebooks included) | C69: 8 | D69: 8 | E69: Your calendar. Count last week and multiply by four.
B70: Share who do not show | C70: 0 | D70: 0.1 | E70: Of your last 10 calls, how many did not happen?
B71: Paid even when they do not show? (Yes or No) | C71: No | D71: Yes | E71: If people pay before the call, Yes.
B72: Price per block | C72: 200 | D72: 200
B73: Cut the platform keeps | C73: 0.1 | D73: 0.1
B74: Hours one call really takes | C74: 1 | D74: 1
A76: Regulars
B77: What | C77: Yours | D77: Typical | E77: Where to look, and what to do with no idea
B78: Counted? (Yes or No) | C78: Yes | D78: Yes
B79: Priority | C79: 4 | D79: 4
B80: People who send you something every month right now | C80: 4 | D80: 4 | E80: Last month's payments grouped by person.
B81: What a regular sends a month, on average | C81: 500 | D81: 500 | E81: Add last month's payments from regulars and divide by how many.
B82: Cut the processor keeps | C82: 0.1 | D82: 0.1
B83: Months a regular usually stays | C83: 6 | D83: 6
B84: Share lost to chargebacks | C84: 0 | D84: 0 | E84: Your processor's disputes page. If it has not happened, 0.
B85: Followers who could send one-off tributes | C85: 2000 | D85: 2000
B86: Share of followers who send a one-off tribute each month | C86: 0 | D86: 0.001 | E86: New senders last month divided by followers. Small numbers are normal.
B87: Typical one-off tribute | C87: 50 | D87: 50
B88: Hours a month on this, all in | C88: 10 | D88: 10
A90: Three futures: how far the futures move
B91: What | C91: Yours | D91: Typical | E91: What it means
B92: Dream: contacts and audience change by | C92: 0.3 | D92: 0.3 | E92: +30% means 60 contacts become 78.
B93: Dream: conversion (close rate, follower to subscriber or tribute) changes by | C93: 0.2 | D93: 0.2 | E93: Never touches screening, booking or show rates.
B94: Disaster: contacts and audience change by | C94: -0.4 | D94: -0.4
B95: Disaster: conversion changes by | C95: -0.25 | D95: -0.25
B96: Disaster event: share of contacts that stop if your main source stops | C96: 1 | D96: 1 | E96: 100% if one source sends everyone.
B97: Disaster event: price cut in a price war | C97: 0.15 | D97: 0.15
B98: Switch on: the source stops? (Yes or No) | C98: No | D98: No
B99: Switch on: price war? (Yes or No) | C99: No | D99: No
B100: Switch on: a month off sick? (Yes or No) | C100: No | D100: No | E100: Sessions, calls and customs stop; subscriptions and regulars continue.

Sheet This Month
A1: This Month
A2: From your numbers. Every white cell recomputes when a pink cell changes. Charts are on the right.
A4: The month in four numbers
B5: Profit this month | C5: ='This Month'!$C$75 -> 13155.217
B6: Gross profit | C6: ='This Month'!$C$72 -> 14655.217
B7: Sessions (in person) | C7: ='This Month'!$C$29 -> 18
B8: Hours used of sellable | C8: =IF('This Month'!$C$12="",TEXT('This Month'!$E$69,"0")&" (set your hours)",TEXT('This Month'!$E$69,"0")&" of "&TEXT('This Month'!$C$12,"0")) -> 144 of 173
B9: The bottleneck | C9: ='This Month'!$C$86 -> Capacity: you are full. Raise price or add a retainer or program.
B10: Blank pink cells on My Numbers | C10: =IF((COUNTBLANK('My Numbers'!$C$6:$C$14)+COUNTBLANK('My Numbers'!$C$18:$C$24)+COUNTBLANK('My Numbers'!$C$26:$C$44)+COUNTBLANK('My Numbers'!$C$48:$C$63)+COUNTBLANK('My Numbers'!$C$67:$C$74)+COUNTBLANK('My Numbers'!$C$78:$C$88)+COUNTBLANK('My Numbers'!$C$92:$C$100))=0,"None. Every number is filled in.",(COUNTBLANK('My Numbers'!$C$6:$C$14)+COUNTBLANK('My Numbers'!$C$18:$C$24)+COUNTBLANK('My Numbers'!$C$26:$C$44)+COUNTBLANK('My Numbers'!$C$48:$C$63)+COUNTBLANK('My Numbers'!$C$67:$C$74)+COUNTBLANK('My Numbers'!$C$78:$C$88)+COUNTBLANK('My Numbers'!$C$92:$C$100))&" blank. A blank counts as zero here, so fill it in or copy the typical number.") -> None. Every number is filled in.
A11: Shared hours
B12: Sellable hours a month (hours a week × 52 ÷ 12) | C12: =IF('My Numbers'!$C$6="","",'My Numbers'!$C$6*52/12) -> 173.33333
B13: Working days a week | C13: =7-'My Numbers'!$C$7 -> 5
A15: In person: from contacts to sessions
B16: New clients = contacts × pass × booking × show | C16: ='My Numbers'!$C$20*'My Numbers'!$C$21*'My Numbers'!$C$22*'My Numbers'!$C$23 -> 10.2
B17: Retainer clients = new clients × retainer take | C17: =IF(('My Numbers'!$C$33="Yes"),'This Month'!$C$16*'My Numbers'!$C$36,0) -> 1.02
B18: Single sessions = (new − retainer clients) × (1 + rebook) + retainer clients' first sessions | C18: =('This Month'!$C$16-'This Month'!$C$17)*(1+'My Numbers'!$C$24)+'This Month'!$C$17 -> 12.954
B19: Continuity sessions = retainer clients × sessions a month × months | C19: ='This Month'!$C$17*'My Numbers'!$C$35*'My Numbers'!$C$37 -> 8.16
B20: Program clients = new clients × close rate (only when the program is the main offer) | C20: =IF(('My Numbers'!$C$38="Yes"),'This Month'!$C$16*'My Numbers'!$C$41,0) -> 0
B21: Sessions wanted (demand) | C21: =IF(('My Numbers'!$C$38="Yes"),'This Month'!$C$20*'My Numbers'!$C$40,'This Month'!$C$18+'This Month'!$C$19) -> 21.114
B22: Hours per session, all in | C22: =IF(('My Numbers'!$C$38="Yes"),IF('My Numbers'!$C$40>0,'My Numbers'!$C$44/'My Numbers'!$C$40,0),'My Numbers'!$C$28) -> 4
B23: Hours the demand would take | C23: ='This Month'!$C$21*'This Month'!$C$22 -> 84.456
B24: Hours available to in person (after higher-priority businesses) | C24: =IF('This Month'!$C$12="","",IFERROR(INDEX('This Month'!$G$58:$G$61,MATCH("In person",'This Month'!$C$58:$C$61,0)),0)) -> 173.33333
B25: Cap from hours = hours available ÷ hours per session | C25: =IF(OR('This Month'!$C$12="",'This Month'!$C$22=0),"",'This Month'!$C$24/'This Month'!$C$22) -> 43.333333
B26: Cap from your session ceiling | C26: =IF('My Numbers'!$C$25="","",'My Numbers'!$C$25) -> 18
B27: Capacity = the tighter of the two | C27: =IF(AND('This Month'!$C$25="",'This Month'!$C$26=""),"",IF('This Month'!$C$25="",'This Month'!$C$26,IF('This Month'!$C$26="",'This Month'!$C$25,MIN('This Month'!$C$25,'This Month'!$C$26)))) -> 18
B28: Scale = capacity ÷ demand when demand is above it, else 1 | C28: =IF('This Month'!$C$27="",1,IF('This Month'!$C$21>'This Month'!$C$27,'This Month'!$C$27/'This Month'!$C$21,1)) -> 0.85251492
B29: Sessions this month | C29: ='This Month'!$C$21*'This Month'!$C$28 -> 18
B30: Gross profit per session = price × (1 − cut) − delivery | C30: ='My Numbers'!$C$26*(1-'My Numbers'!$C$29)-'My Numbers'!$C$27 -> 375
B31: From single sessions | C31: =IF(('My Numbers'!$C$38="Yes"),0,'This Month'!$C$18*'This Month'!$C$28*'This Month'!$C$30) -> 4141.3043
B32: From add-ons = new clients × take × add-on price × (1 − cut) | C32: =IF(AND(('My Numbers'!$C$30="Yes"),NOT(('My Numbers'!$C$38="Yes"))),'This Month'!$C$16*'My Numbers'!$C$32*'This Month'!$C$28*'My Numbers'!$C$31*(1-'My Numbers'!$C$29),0) -> 413.04348
B33: From retainers = retainer clients × months × (price × (1 − cut) − sessions × delivery) | C33: =IF(AND(('My Numbers'!$C$33="Yes"),NOT(('My Numbers'!$C$38="Yes"))),'This Month'!$C$17*'My Numbers'!$C$37*'This Month'!$C$28*('My Numbers'!$C$34*(1-'My Numbers'!$C$29)-'My Numbers'!$C$35*'My Numbers'!$C$27),0) -> 4260.8696
B34: From the program = program clients × (price × (1 − cut) − delivery) | C34: =IF(('My Numbers'!$C$38="Yes"),'This Month'!$C$20*'This Month'!$C$28*('My Numbers'!$C$39*(1-'My Numbers'!$C$43)-'My Numbers'!$C$42),0) -> 0
B35: In person gross profit a month | C35: =IF(('My Numbers'!$C$18="Yes"),'This Month'!$C$31+'This Month'!$C$32+'This Month'!$C$33+'This Month'!$C$34,0) -> 8815.2174
B36: In person hours used | C36: =IF(('My Numbers'!$C$18="Yes"),'This Month'!$C$29*'This Month'!$C$22,0) -> 72 | M36: The funnel this month (feeds the chart)
B37: Gross profit per contact (before any cap) | C37: =IF('My Numbers'!$C$20>0,IF(('My Numbers'!$C$38="Yes"),'This Month'!$C$20*('My Numbers'!$C$39*(1-'My Numbers'!$C$43)-'My Numbers'!$C$42),'This Month'!$C$18*'This Month'!$C$30+IF(('My Numbers'!$C$30="Yes"),'This Month'!$C$16*'My Numbers'!$C$32*'My Numbers'!$C$31*(1-'My Numbers'!$C$29),0)+IF(('My Numbers'!$C$33="Yes"),'This Month'!$C$17*'My Numbers'!$C$37*('My Numbers'!$C$34*(1-'My Numbers'!$C$29)-'My Numbers'!$C$35*'My Numbers'!$C$27),0))/'My Numbers'!$C$20,"") -> 172.3375 | M37: Contacts | N37: ='My Numbers'!$C$20 -> 60
B38: Sessions per contact (before any cap) | C38: =IF('My Numbers'!$C$20>0,'This Month'!$C$21/'My Numbers'!$C$20,"") -> 0.3519 | M38: Passed | N38: ='My Numbers'!$C$20*'My Numbers'!$C$21 -> 30
M39: Booked | N39: ='My Numbers'!$C$20*'My Numbers'!$C$21*'My Numbers'!$C$22 -> 12
A40: Content, Calls, Regulars | M40: Showed | N40: ='This Month'!$C$16 -> 10.2
B41: Content: subscriptions = subscribers × price × (1 − cut) | C41: ='My Numbers'!$C$52*'My Numbers'!$C$54*(1-'My Numbers'!$C$55) -> 1800 | M41: Sessions | N41: ='This Month'!$C$29 -> 18
B42: Content: customs = customs × price × (1 − cut) | C42: ='My Numbers'!$C$56*'My Numbers'!$C$57*(1-'My Numbers'!$C$58) -> 800
B43: Content: digital = sold × what you keep | C43: ='My Numbers'!$C$60*'My Numbers'!$C$62 -> 0
B44: Content gross profit a month, before the hours share | C44: ='This Month'!$C$41+'This Month'!$C$42+'This Month'!$C$43 -> 2600
B45: Content hours wanted | C45: ='My Numbers'!$C$63+'My Numbers'!$C$56*'My Numbers'!$C$59 -> 50
B46: Content: new subscribers a month = followers × rate | C46: ='My Numbers'!$C$50*'My Numbers'!$C$51 -> 50
B47: Content: months a subscriber stays = 1 ÷ churn | C47: =IF('My Numbers'!$C$53>0,1/'My Numbers'!$C$53,"") -> 5
B48: Calls: paid calls = calls × (1 − no-shows that go unpaid) | C48: ='My Numbers'!$C$69*(1-'My Numbers'!$C$70*IF(('My Numbers'!$C$71="Yes"),0,1)) -> 8
B49: Calls gross profit a month, before the hours share = paid calls × price × (1 − cut) | C49: ='This Month'!$C$48*'My Numbers'!$C$72*(1-'My Numbers'!$C$73) -> 1440
B50: Calls hours wanted | C50: ='My Numbers'!$C$69*'My Numbers'!$C$74 -> 8
B51: Regulars: per regular a month = average × (1 − chargebacks) × (1 − cut) | C51: ='My Numbers'!$C$81*(1-'My Numbers'!$C$84)*(1-'My Numbers'!$C$82) -> 450
B52: Regulars: new one-off tributes = followers × rate × typical × (1 − chargebacks) × (1 − cut) | C52: ='My Numbers'!$C$85*'My Numbers'!$C$86*'My Numbers'!$C$87*(1-'My Numbers'!$C$84)*(1-'My Numbers'!$C$82) -> 0
B53: Regulars gross profit a month, before the hours share | C53: ='My Numbers'!$C$80*'This Month'!$C$51+'This Month'!$C$52 -> 1800
B54: Regulars hours wanted | C54: ='My Numbers'!$C$88+'My Numbers'!$C$80*1 -> 14
A56: Hours in priority order (your #1 takes its hours first)
B57: Rank | C57: Business | D57: Hours wanted | E57: Hours allowed | F57: Share allowed | G57: Hours open to it | I57: helper: business | J57: priority | K57: hours wanted
B58: 1 | C58: =IFERROR(INDEX('This Month'!$I$58:$I$61,MATCH(SMALL('This Month'!$J$58:$J$61,1),'This Month'!$J$58:$J$61,0)),"") -> In person | D58: =IFERROR(INDEX('This Month'!$K$58:$K$61,MATCH(SMALL('This Month'!$J$58:$J$61,1),'This Month'!$J$58:$J$61,0)),0) -> 84.456 | E58: =IF('This Month'!$C$12="",D58,MAX(0,MIN(D58,'This Month'!$C$12))) -> 84.456 | F58: =IF(D58>0,E58/D58,1) -> 1 | G58: =IF('This Month'!$C$12="","",MAX(0,'This Month'!$C$12)) -> 173.33333 | I58: In person | J58: =IF(('My Numbers'!$C$18="Yes"),'My Numbers'!$C$19,99) -> 1 | K58: =IF(('My Numbers'!$C$18="Yes"),'This Month'!$C$23,0) -> 84.456
B59: 2 | C59: =IFERROR(INDEX('This Month'!$I$58:$I$61,MATCH(SMALL('This Month'!$J$58:$J$61,2),'This Month'!$J$58:$J$61,0)),"") -> Content | D59: =IFERROR(INDEX('This Month'!$K$58:$K$61,MATCH(SMALL('This Month'!$J$58:$J$61,2),'This Month'!$J$58:$J$61,0)),0) -> 50 | E59: =IF('This Month'!$C$12="",D59,MAX(0,MIN(D59,'This Month'!$C$12-SUM($E$58:$E$58)))) -> 50 | F59: =IF(D59>0,E59/D59,1) -> 1 | G59: =IF('This Month'!$C$12="","",MAX(0,'This Month'!$C$12-SUM($E$58:$E$58))) -> 88.877333 | I59: Content | J59: =IF(('My Numbers'!$C$48="Yes"),'My Numbers'!$C$49,99) -> 2 | K59: =IF(('My Numbers'!$C$48="Yes"),'This Month'!$C$45,0) -> 50
B60: 3 | C60: =IFERROR(INDEX('This Month'!$I$58:$I$61,MATCH(SMALL('This Month'!$J$58:$J$61,3),'This Month'!$J$58:$J$61,0)),"") -> Calls | D60: =IFERROR(INDEX('This Month'!$K$58:$K$61,MATCH(SMALL('This Month'!$J$58:$J$61,3),'This Month'!$J$58:$J$61,0)),0) -> 8 | E60: =IF('This Month'!$C$12="",D60,MAX(0,MIN(D60,'This Month'!$C$12-SUM($E$58:$E$59)))) -> 8 | F60: =IF(D60>0,E60/D60,1) -> 1 | G60: =IF('This Month'!$C$12="","",MAX(0,'This Month'!$C$12-SUM($E$58:$E$59))) -> 38.877333 | I60: Calls | J60: =IF(('My Numbers'!$C$67="Yes"),'My Numbers'!$C$68,99) -> 3 | K60: =IF(('My Numbers'!$C$67="Yes"),'This Month'!$C$50,0) -> 8
B61: 4 | C61: =IFERROR(INDEX('This Month'!$I$58:$I$61,MATCH(SMALL('This Month'!$J$58:$J$61,4),'This Month'!$J$58:$J$61,0)),"") -> Regulars | D61: =IFERROR(INDEX('This Month'!$K$58:$K$61,MATCH(SMALL('This Month'!$J$58:$J$61,4),'This Month'!$J$58:$J$61,0)),0) -> 14 | E61: =IF('This Month'!$C$12="",D61,MAX(0,MIN(D61,'This Month'!$C$12-SUM($E$58:$E$60)))) -> 14 | F61: =IF(D61>0,E61/D61,1) -> 1 | G61: =IF('This Month'!$C$12="","",MAX(0,'This Month'!$C$12-SUM($E$58:$E$60))) -> 30.877333 | I61: Regulars | J61: =IF(('My Numbers'!$C$78="Yes"),'My Numbers'!$C$79,99) -> 4 | K61: =IF(('My Numbers'!$C$78="Yes"),'This Month'!$C$54,0) -> 14
A63: Each business, counted
B64: Business | C64: Gross profit | D64: Share | E64: Hours used | F64: Note
B65: In person | C65: ='This Month'!$C$35 -> 8815.2174 | D65: =IF($C$69>0,C65/$C$69,0) -> 0.60150711 | E65: ='This Month'!$C$36 -> 72 | F65: =IF(NOT(('My Numbers'!$C$18="Yes")),"Not counted",IF('This Month'!$C$27="","",IF('This Month'!$C$21>'This Month'!$C$27,"At capacity: more contacts would not become more money",""))) -> At capacity: more contacts would not become more money
B66: Content | C66: =IF(('My Numbers'!$C$48="Yes"),'This Month'!$C$44*IFERROR(INDEX('This Month'!$F$58:$F$61,MATCH("Content",'This Month'!$C$58:$C$61,0)),1),0) -> 2600 | D66: =IF($C$69>0,C66/$C$69,0) -> 0.17741122 | E66: =IF(('My Numbers'!$C$48="Yes"),IFERROR(INDEX('This Month'!$E$58:$E$61,MATCH("Content",'This Month'!$C$58:$C$61,0)),0),0) -> 50 | F66: =IF(NOT(('My Numbers'!$C$48="Yes")),"Not counted",IF(IFERROR(INDEX('This Month'!$F$58:$F$61,MATCH("Content",'This Month'!$C$58:$C$61,0)),1)<1,"Fewer hours than it wanted; #1 took its hours first",""))
B67: Calls | C67: =IF(('My Numbers'!$C$67="Yes"),'This Month'!$C$49*IFERROR(INDEX('This Month'!$F$58:$F$61,MATCH("Calls",'This Month'!$C$58:$C$61,0)),1),0) -> 1440 | D67: =IF($C$69>0,C67/$C$69,0) -> 0.098258522 | E67: =IF(('My Numbers'!$C$67="Yes"),IFERROR(INDEX('This Month'!$E$58:$E$61,MATCH("Calls",'This Month'!$C$58:$C$61,0)),0),0) -> 8 | F67: =IF(NOT(('My Numbers'!$C$67="Yes")),"Not counted",IF(IFERROR(INDEX('This Month'!$F$58:$F$61,MATCH("Calls",'This Month'!$C$58:$C$61,0)),1)<1,"Fewer hours than it wanted",""))
B68: Regulars | C68: =IF(('My Numbers'!$C$78="Yes"),'This Month'!$C$53*IFERROR(INDEX('This Month'!$F$58:$F$61,MATCH("Regulars",'This Month'!$C$58:$C$61,0)),1),0) -> 1800 | D68: =IF($C$69>0,C68/$C$69,0) -> 0.12282315 | E68: =IF(('My Numbers'!$C$78="Yes"),IFERROR(INDEX('This Month'!$E$58:$E$61,MATCH("Regulars",'This Month'!$C$58:$C$61,0)),0),0) -> 14 | F68: =IF(NOT(('My Numbers'!$C$78="Yes")),"Not counted",IF(IFERROR(INDEX('This Month'!$F$58:$F$61,MATCH("Regulars",'This Month'!$C$58:$C$61,0)),1)<1,"Fewer hours than it wanted",""))
B69: Total | C69: =SUM(C65:C68) -> 14655.217 | D69: =SUM(D65:D68) -> 1 | E69: =SUM(E65:E68) -> 144
A71: Profit
B72: Gross profit, all counted businesses | C72: ='This Month'!$C$69 -> 14655.217
B73: Fixed costs | C73: =-'My Numbers'!$C$8 -> -1500
B74: Spent finding clients | C74: =-'My Numbers'!$C$13 -> 0
B75: Profit = gross profit − finding clients − fixed costs | C75: ='This Month'!$C$72+'This Month'!$C$73+'This Month'!$C$74 -> 13155.217
B76: Set aside for tax (a reminder, never advice) | C76: =MAX(0,'This Month'!$C$75)*'My Numbers'!$C$10 -> 3288.8043
B77: Yours to keep after the set-aside | C77: ='This Month'!$C$75-'This Month'!$C$76 -> 9866.413
B78: Against your goal (positive = above it) | C78: ='This Month'!$C$75-'My Numbers'!$C$9 -> 3155.2174
A80: The bottleneck: which step is furthest below typical, and what it is worth
B81: Step | C81: Yours | D81: Typical | E81: Worth a month at typical | F81: Note
B82: Booking rate | C82: ='My Numbers'!$C$22 -> 0.4 | D82: 0.4 | E82: =IF(('My Numbers'!$C$38="Yes"),0,IF('My Numbers'!$C$22<D82,(((('My Numbers'!$C$20*'My Numbers'!$C$21*$D$82*'My Numbers'!$C$23)-(IF(('My Numbers'!$C$33="Yes"),('My Numbers'!$C$20*'My Numbers'!$C$21*$D$82*'My Numbers'!$C$23)*'My Numbers'!$C$36,0)))*(1+'My Numbers'!$C$24)+(IF(('My Numbers'!$C$33="Yes"),('My Numbers'!$C$20*'My Numbers'!$C$21*$D$82*'My Numbers'!$C$23)*'My Numbers'!$C$36,0)))*('My Numbers'!$C$26*(1-'My Numbers'!$C$29)-'My Numbers'!$C$27)+IF(('My Numbers'!$C$30="Yes"),('My Numbers'!$C$20*'My Numbers'!$C$21*$D$82*'My Numbers'!$C$23)*'My Numbers'!$C$32*'My Numbers'!$C$31*(1-'My Numbers'!$C$29),0)+IF(('My Numbers'!$C$33="Yes"),(IF(('My Numbers'!$C$33="Yes"),('My Numbers'!$C$20*'My Numbers'!$C$21*$D$82*'My Numbers'!$C$23)*'My Numbers'!$C$36,0))*'My Numbers'!$C$37*('My Numbers'!$C$34*(1-'My Numbers'!$C$29)-'My Numbers'!$C$35*'My Numbers'!$C$27),0))*(IF('This Month'!$C$27="",1,IF((((('My Numbers'!$C$20*'My Numbers'!$C$21*$D$82*'My Numbers'!$C$23)-(IF(('My Numbers'!$C$33="Yes"),('My Numbers'!$C$20*'My Numbers'!$C$21*$D$82*'My Numbers'!$C$23)*'My Numbers'!$C$36,0)))*(1+'My Numbers'!$C$24)+(IF(('My Numbers'!$C$33="Yes"),('My Numbers'!$C$20*'My Numbers'!$C$21*$D$82*'My Numbers'!$C$23)*'My Numbers'!$C$36,0)))+((IF(('My Numbers'!$C$33="Yes"),('My Numbers'!$C$20*'My Numbers'!$C$21*$D$82*'My Numbers'!$C$23)*'My Numbers'!$C$36,0))*'My Numbers'!$C$35*'My Numbers'!$C$37))>'This Month'!$C$27,'This Month'!$C$27/(((('My Numbers'!$C$20*'My Numbers'!$C$21*$D$82*'My Numbers'!$C$23)-(IF(('My Numbers'!$C$33="Yes"),('My Numbers'!$C$20*'My Numbers'!$C$21*$D$82*'My Numbers'!$C$23)*'My Numbers'!$C$36,0)))*(1+'My Numbers'!$C$24)+(IF(('My Numbers'!$C$33="Yes"),('My Numbers'!$C$20*'My Numbers'!$C$21*$D$82*'My Numbers'!$C$23)*'My Numbers'!$C$36,0)))+((IF(('My Numbers'!$C$33="Yes"),('My Numbers'!$C$20*'My Numbers'!$C$21*$D$82*'My Numbers'!$C$23)*'My Numbers'!$C$36,0))*'My Numbers'!$C$35*'My Numbers'!$C$37)),1)))-(((('My Numbers'!$C$20*'My Numbers'!$C$21*'My Numbers'!$C$22*'My Numbers'!$C$23)-(IF(('My Numbers'!$C$33="Yes"),('My Numbers'!$C$20*'My Numbers'!$C$21*'My Numbers'!$C$22*'My Numbers'!$C$23)*'My Numbers'!$C$36,0)))*(1+'My Numbers'!$C$24)+(IF(('My Numbers'!$C$33="Yes"),('My Numbers'!$C$20*'My Numbers'!$C$21*'My Numbers'!$C$22*'My Numbers'!$C$23)*'My Numbers'!$C$36,0)))*('My Numbers'!$C$26*(1-'My Numbers'!$C$29)-'My Numbers'!$C$27)+IF(('My Numbers'!$C$30="Yes"),('My Numbers'!$C$20*'My Numbers'!$C$21*'My Numbers'!$C$22*'My Numbers'!$C$23)*'My Numbers'!$C$32*'My Numbers'!$C$31*(1-'My Numbers'!$C$29),0)+IF(('My Numbers'!$C$33="Yes"),(IF(('My Numbers'!$C$33="Yes"),('My Numbers'!$C$20*'My Numbers'!$C$21*'My Numbers'!$C$22*'My Numbers'!$C$23)*'My Numbers'!$C$36,0))*'My Numbers'!$C$37*('My Numbers'!$C$34*(1-'My Numbers'!$C$29)-'My Numbers'!$C$35*'My Numbers'!$C$27),0))*(IF('This Month'!$C$27="",1,IF((((('My Numbers'!$C$20*'My Numbers'!$C$21*'My Numbers'!$C$22*'My Numbers'!$C$23)-(IF(('My Numbers'!$C$33="Yes"),('My Numbers'!$C$20*'My Numbers'!$C$21*'My Numbers'!$C$22*'My Numbers'!$C$23)*'My Numbers'!$C$36,0)))*(1+'My Numbers'!$C$24)+(IF(('My Numbers'!$C$33="Yes"),('My Numbers'!$C$20*'My Numbers'!$C$21*'My Numbers'!$C$22*'My Numbers'!$C$23)*'My Numbers'!$C$36,0)))+((IF(('My Numbers'!$C$33="Yes"),('My Numbers'!$C$20*'My Numbers'!$C$21*'My Numbers'!$C$22*'My Numbers'!$C$23)*'My Numbers'!$C$36,0))*'My Numbers'!$C$35*'My Numbers'!$C$37))>'This Month'!$C$27,'This Month'!$C$27/(((('My Numbers'!$C$20*'My Numbers'!$C$21*'My Numbers'!$C$22*'My Numbers'!$C$23)-(IF(('My Numbers'!$C$33="Yes"),('My Numbers'!$C$20*'My Numbers'!$C$21*'My Numbers'!$C$22*'My Numbers'!$C$23)*'My Numbers'!$C$36,0)))*(1+'My Numbers'!$C$24)+(IF(('My Numbers'!$C$33="Yes"),('My Numbers'!$C$20*'My Numbers'!$C$21*'My Numbers'!$C$22*'My Numbers'!$C$23)*'My Numbers'!$C$36,0)))+((IF(('My Numbers'!$C$33="Yes"),('My Numbers'!$C$20*'My Numbers'!$C$21*'My Numbers'!$C$22*'My Numbers'!$C$23)*'My Numbers'!$C$36,0))*'My Numbers'!$C$35*'My Numbers'!$C$37)),1))),0)) -> 0
B83: Show rate | C83: ='My Numbers'!$C$23 -> 0.85 | D83: 0.85 | E83: =IF(('My Numbers'!$C$38="Yes"),0,IF('My Numbers'!$C$23<D83,(((('My Numbers'!$C$20*'My Numbers'!$C$21*'My Numbers'!$C$22*$D$83)-(IF(('My Numbers'!$C$33="Yes"),('My Numbers'!$C$20*'My Numbers'!$C$21*'My Numbers'!$C$22*$D$83)*'My Numbers'!$C$36,0)))*(1+'My Numbers'!$C$24)+(IF(('My Numbers'!$C$33="Yes"),('My Numbers'!$C$20*'My Numbers'!$C$21*'My Numbers'!$C$22*$D$83)*'My Numbers'!$C$36,0)))*('My Numbers'!$C$26*(1-'My Numbers'!$C$29)-'My Numbers'!$C$27)+IF(('My Numbers'!$C$30="Yes"),('My Numbers'!$C$20*'My Numbers'!$C$21*'My Numbers'!$C$22*$D$83)*'My Numbers'!$C$32*'My Numbers'!$C$31*(1-'My Numbers'!$C$29),0)+IF(('My Numbers'!$C$33="Yes"),(IF(('My Numbers'!$C$33="Yes"),('My Numbers'!$C$20*'My Numbers'!$C$21*'My Numbers'!$C$22*$D$83)*'My Numbers'!$C$36,0))*'My Numbers'!$C$37*('My Numbers'!$C$34*(1-'My Numbers'!$C$29)-'My Numbers'!$C$35*'My Numbers'!$C$27),0))*(IF('This Month'!$C$27="",1,IF((((('My Numbers'!$C$20*'My Numbers'!$C$21*'My Numbers'!$C$22*$D$83)-(IF(('My Numbers'!$C$33="Yes"),('My Numbers'!$C$20*'My Numbers'!$C$21*'My Numbers'!$C$22*$D$83)*'My Numbers'!$C$36,0)))*(1+'My Numbers'!$C$24)+(IF(('My Numbers'!$C$33="Yes"),('My Numbers'!$C$20*'My Numbers'!$C$21*'My Numbers'!$C$22*$D$83)*'My Numbers'!$C$36,0)))+((IF(('My Numbers'!$C$33="Yes"),('My Numbers'!$C$20*'My Numbers'!$C$21*'My Numbers'!$C$22*$D$83)*'My Numbers'!$C$36,0))*'My Numbers'!$C$35*'My Numbers'!$C$37))>'This Month'!$C$27,'This Month'!$C$27/(((('My Numbers'!$C$20*'My Numbers'!$C$21*'My Numbers'!$C$22*$D$83)-(IF(('My Numbers'!$C$33="Yes"),('My Numbers'!$C$20*'My Numbers'!$C$21*'My Numbers'!$C$22*$D$83)*'My Numbers'!$C$36,0)))*(1+'My Numbers'!$C$24)+(IF(('My Numbers'!$C$33="Yes"),('My Numbers'!$C$20*'My Numbers'!$C$21*'My Numbers'!$C$22*$D$83)*'My Numbers'!$C$36,0)))+((IF(('My Numbers'!$C$33="Yes"),('My Numbers'!$C$20*'My Numbers'!$C$21*'My Numbers'!$C$22*$D$83)*'My Numbers'!$C$36,0))*'My Numbers'!$C$35*'My Numbers'!$C$37)),1)))-(((('My Numbers'!$C$20*'My Numbers'!$C$21*'My Numbers'!$C$22*'My Numbers'!$C$23)-(IF(('My Numbers'!$C$33="Yes"),('My Numbers'!$C$20*'My Numbers'!$C$21*'My Numbers'!$C$22*'My Numbers'!$C$23)*'My Numbers'!$C$36,0)))*(1+'My Numbers'!$C$24)+(IF(('My Numbers'!$C$33="Yes"),('My Numbers'!$C$20*'My Numbers'!$C$21*'My Numbers'!$C$22*'My Numbers'!$C$23)*'My Numbers'!$C$36,0)))*('My Numbers'!$C$26*(1-'My Numbers'!$C$29)-'My Numbers'!$C$27)+IF(('My Numbers'!$C$30="Yes"),('My Numbers'!$C$20*'My Numbers'!$C$21*'My Numbers'!$C$22*'My Numbers'!$C$23)*'My Numbers'!$C$32*'My Numbers'!$C$31*(1-'My Numbers'!$C$29),0)+IF(('My Numbers'!$C$33="Yes"),(IF(('My Numbers'!$C$33="Yes"),('My Numbers'!$C$20*'My Numbers'!$C$21*'My Numbers'!$C$22*'My Numbers'!$C$23)*'My Numbers'!$C$36,0))*'My Numbers'!$C$37*('My Numbers'!$C$34*(1-'My Numbers'!$C$29)-'My Numbers'!$C$35*'My Numbers'!$C$27),0))*(IF('This Month'!$C$27="",1,IF((((('My Numbers'!$C$20*'My Numbers'!$C$21*'My Numbers'!$C$22*'My Numbers'!$C$23)-(IF(('My Numbers'!$C$33="Yes"),('My Numbers'!$C$20*'My Numbers'!$C$21*'My Numbers'!$C$22*'My Numbers'!$C$23)*'My Numbers'!$C$36,0)))*(1+'My Numbers'!$C$24)+(IF(('My Numbers'!$C$33="Yes"),('My Numbers'!$C$20*'My Numbers'!$C$21*'My Numbers'!$C$22*'My Numbers'!$C$23)*'My Numbers'!$C$36,0)))+((IF(('My Numbers'!$C$33="Yes"),('My Numbers'!$C$20*'My Numbers'!$C$21*'My Numbers'!$C$22*'My Numbers'!$C$23)*'My Numbers'!$C$36,0))*'My Numbers'!$C$35*'My Numbers'!$C$37))>'This Month'!$C$27,'This Month'!$C$27/(((('My Numbers'!$C$20*'My Numbers'!$C$21*'My Numbers'!$C$22*'My Numbers'!$C$23)-(IF(('My Numbers'!$C$33="Yes"),('My Numbers'!$C$20*'My Numbers'!$C$21*'My Numbers'!$C$22*'My Numbers'!$C$23)*'My Numbers'!$C$36,0)))*(1+'My Numbers'!$C$24)+(IF(('My Numbers'!$C$33="Yes"),('My Numbers'!$C$20*'My Numbers'!$C$21*'My Numbers'!$C$22*'My Numbers'!$C$23)*'My Numbers'!$C$36,0)))+((IF(('My Numbers'!$C$33="Yes"),('My Numbers'!$C$20*'My Numbers'!$C$21*'My Numbers'!$C$22*'My Numbers'!$C$23)*'My Numbers'!$C$36,0))*'My Numbers'!$C$35*'My Numbers'!$C$37)),1))),0)) -> 0
B84: Rebook rate | C84: ='My Numbers'!$C$24 -> 0.3 | D84: 0.3 | E84: =IF(('My Numbers'!$C$38="Yes"),0,IF('My Numbers'!$C$24<D84,(((('My Numbers'!$C$20*'My Numbers'!$C$21*'My Numbers'!$C$22*'My Numbers'!$C$23)-(IF(('My Numbers'!$C$33="Yes"),('My Numbers'!$C$20*'My Numbers'!$C$21*'My Numbers'!$C$22*'My Numbers'!$C$23)*'My Numbers'!$C$36,0)))*(1+$D$84)+(IF(('My Numbers'!$C$33="Yes"),('My Numbers'!$C$20*'My Numbers'!$C$21*'My Numbers'!$C$22*'My Numbers'!$C$23)*'My Numbers'!$C$36,0)))*('My Numbers'!$C$26*(1-'My Numbers'!$C$29)-'My Numbers'!$C$27)+IF(('My Numbers'!$C$30="Yes"),('My Numbers'!$C$20*'My Numbers'!$C$21*'My Numbers'!$C$22*'My Numbers'!$C$23)*'My Numbers'!$C$32*'My Numbers'!$C$31*(1-'My Numbers'!$C$29),0)+IF(('My Numbers'!$C$33="Yes"),(IF(('My Numbers'!$C$33="Yes"),('My Numbers'!$C$20*'My Numbers'!$C$21*'My Numbers'!$C$22*'My Numbers'!$C$23)*'My Numbers'!$C$36,0))*'My Numbers'!$C$37*('My Numbers'!$C$34*(1-'My Numbers'!$C$29)-'My Numbers'!$C$35*'My Numbers'!$C$27),0))*(IF('This Month'!$C$27="",1,IF((((('My Numbers'!$C$20*'My Numbers'!$C$21*'My Numbers'!$C$22*'My Numbers'!$C$23)-(IF(('My Numbers'!$C$33="Yes"),('My Numbers'!$C$20*'My Numbers'!$C$21*'My Numbers'!$C$22*'My Numbers'!$C$23)*'My Numbers'!$C$36,0)))*(1+$D$84)+(IF(('My Numbers'!$C$33="Yes"),('My Numbers'!$C$20*'My Numbers'!$C$21*'My Numbers'!$C$22*'My Numbers'!$C$23)*'My Numbers'!$C$36,0)))+((IF(('My Numbers'!$C$33="Yes"),('My Numbers'!$C$20*'My Numbers'!$C$21*'My Numbers'!$C$22*'My Numbers'!$C$23)*'My Numbers'!$C$36,0))*'My Numbers'!$C$35*'My Numbers'!$C$37))>'This Month'!$C$27,'This Month'!$C$27/(((('My Numbers'!$C$20*'My Numbers'!$C$21*'My Numbers'!$C$22*'My Numbers'!$C$23)-(IF(('My Numbers'!$C$33="Yes"),('My Numbers'!$C$20*'My Numbers'!$C$21*'My Numbers'!$C$22*'My Numbers'!$C$23)*'My Numbers'!$C$36,0)))*(1+$D$84)+(IF(('My Numbers'!$C$33="Yes"),('My Numbers'!$C$20*'My Numbers'!$C$21*'My Numbers'!$C$22*'My Numbers'!$C$23)*'My Numbers'!$C$36,0)))+((IF(('My Numbers'!$C$33="Yes"),('My Numbers'!$C$20*'My Numbers'!$C$21*'My Numbers'!$C$22*'My Numbers'!$C$23)*'My Numbers'!$C$36,0))*'My Numbers'!$C$35*'My Numbers'!$C$37)),1)))-(((('My Numbers'!$C$20*'My Numbers'!$C$21*'My Numbers'!$C$22*'My Numbers'!$C$23)-(IF(('My Numbers'!$C$33="Yes"),('My Numbers'!$C$20*'My Numbers'!$C$21*'My Numbers'!$C$22*'My Numbers'!$C$23)*'My Numbers'!$C$36,0)))*(1+'My Numbers'!$C$24)+(IF(('My Numbers'!$C$33="Yes"),('My Numbers'!$C$20*'My Numbers'!$C$21*'My Numbers'!$C$22*'My Numbers'!$C$23)*'My Numbers'!$C$36,0)))*('My Numbers'!$C$26*(1-'My Numbers'!$C$29)-'My Numbers'!$C$27)+IF(('My Numbers'!$C$30="Yes"),('My Numbers'!$C$20*'My Numbers'!$C$21*'My Numbers'!$C$22*'My Numbers'!$C$23)*'My Numbers'!$C$32*'My Numbers'!$C$31*(1-'My Numbers'!$C$29),0)+IF(('My Numbers'!$C$33="Yes"),(IF(('My Numbers'!$C$33="Yes"),('My Numbers'!$C$20*'My Numbers'!$C$21*'My Numbers'!$C$22*'My Numbers'!$C$23)*'My Numbers'!$C$36,0))*'My Numbers'!$C$37*('My Numbers'!$C$34*(1-'My Numbers'!$C$29)-'My Numbers'!$C$35*'My Numbers'!$C$27),0))*(IF('This Month'!$C$27="",1,IF((((('My Numbers'!$C$20*'My Numbers'!$C$21*'My Numbers'!$C$22*'My Numbers'!$C$23)-(IF(('My Numbers'!$C$33="Yes"),('My Numbers'!$C$20*'My Numbers'!$C$21*'My Numbers'!$C$22*'My Numbers'!$C$23)*'My Numbers'!$C$36,0)))*(1+'My Numbers'!$C$24)+(IF(('My Numbers'!$C$33="Yes"),('My Numbers'!$C$20*'My Numbers'!$C$21*'My Numbers'!$C$22*'My Numbers'!$C$23)*'My Numbers'!$C$36,0)))+((IF(('My Numbers'!$C$33="Yes"),('My Numbers'!$C$20*'My Numbers'!$C$21*'My Numbers'!$C$22*'My Numbers'!$C$23)*'My Numbers'!$C$36,0))*'My Numbers'!$C$35*'My Numbers'!$C$37))>'This Month'!$C$27,'This Month'!$C$27/(((('My Numbers'!$C$20*'My Numbers'!$C$21*'My Numbers'!$C$22*'My Numbers'!$C$23)-(IF(('My Numbers'!$C$33="Yes"),('My Numbers'!$C$20*'My Numbers'!$C$21*'My Numbers'!$C$22*'My Numbers'!$C$23)*'My Numbers'!$C$36,0)))*(1+'My Numbers'!$C$24)+(IF(('My Numbers'!$C$33="Yes"),('My Numbers'!$C$20*'My Numbers'!$C$21*'My Numbers'!$C$22*'My Numbers'!$C$23)*'My Numbers'!$C$36,0)))+((IF(('My Numbers'!$C$33="Yes"),('My Numbers'!$C$20*'My Numbers'!$C$21*'My Numbers'!$C$22*'My Numbers'!$C$23)*'My Numbers'!$C$36,0))*'My Numbers'!$C$35*'My Numbers'!$C$37)),1))),0)) -> 0
B85: Session price | C85: ='My Numbers'!$C$26 -> 500 | D85: 500 | E85: =IF(('My Numbers'!$C$38="Yes"),0,IF('My Numbers'!$C$26<D85,(((('My Numbers'!$C$20*'My Numbers'!$C$21*'My Numbers'!$C$22*'My Numbers'!$C$23)-(IF(('My Numbers'!$C$33="Yes"),('My Numbers'!$C$20*'My Numbers'!$C$21*'My Numbers'!$C$22*'My Numbers'!$C$23)*'My Numbers'!$C$36,0)))*(1+'My Numbers'!$C$24)+(IF(('My Numbers'!$C$33="Yes"),('My Numbers'!$C$20*'My Numbers'!$C$21*'My Numbers'!$C$22*'My Numbers'!$C$23)*'My Numbers'!$C$36,0)))*($D$85*(1-'My Numbers'!$C$29)-'My Numbers'!$C$27)+IF(('My Numbers'!$C$30="Yes"),('My Numbers'!$C$20*'My Numbers'!$C$21*'My Numbers'!$C$22*'My Numbers'!$C$23)*'My Numbers'!$C$32*'My Numbers'!$C$31*(1-'My Numbers'!$C$29),0)+IF(('My Numbers'!$C$33="Yes"),(IF(('My Numbers'!$C$33="Yes"),('My Numbers'!$C$20*'My Numbers'!$C$21*'My Numbers'!$C$22*'My Numbers'!$C$23)*'My Numbers'!$C$36,0))*'My Numbers'!$C$37*('My Numbers'!$C$34*(1-'My Numbers'!$C$29)-'My Numbers'!$C$35*'My Numbers'!$C$27),0))*(IF('This Month'!$C$27="",1,IF((((('My Numbers'!$C$20*'My Numbers'!$C$21*'My Numbers'!$C$22*'My Numbers'!$C$23)-(IF(('My Numbers'!$C$33="Yes"),('My Numbers'!$C$20*'My Numbers'!$C$21*'My Numbers'!$C$22*'My Numbers'!$C$23)*'My Numbers'!$C$36,0)))*(1+'My Numbers'!$C$24)+(IF(('My Numbers'!$C$33="Yes"),('My Numbers'!$C$20*'My Numbers'!$C$21*'My Numbers'!$C$22*'My Numbers'!$C$23)*'My Numbers'!$C$36,0)))+((IF(('My Numbers'!$C$33="Yes"),('My Numbers'!$C$20*'My Numbers'!$C$21*'My Numbers'!$C$22*'My Numbers'!$C$23)*'My Numbers'!$C$36,0))*'My Numbers'!$C$35*'My Numbers'!$C$37))>'This Month'!$C$27,'This Month'!$C$27/(((('My Numbers'!$C$20*'My Numbers'!$C$21*'My Numbers'!$C$22*'My Numbers'!$C$23)-(IF(('My Numbers'!$C$33="Yes"),('My Numbers'!$C$20*'My Numbers'!$C$21*'My Numbers'!$C$22*'My Numbers'!$C$23)*'My Numbers'!$C$36,0)))*(1+'My Numbers'!$C$24)+(IF(('My Numbers'!$C$33="Yes"),('My Numbers'!$C$20*'My Numbers'!$C$21*'My Numbers'!$C$22*'My Numbers'!$C$23)*'My Numbers'!$C$36,0)))+((IF(('My Numbers'!$C$33="Yes"),('My Numbers'!$C$20*'My Numbers'!$C$21*'My Numbers'!$C$22*'My Numbers'!$C$23)*'My Numbers'!$C$36,0))*'My Numbers'!$C$35*'My Numbers'!$C$37)),1)))-(((('My Numbers'!$C$20*'My Numbers'!$C$21*'My Numbers'!$C$22*'My Numbers'!$C$23)-(IF(('My Numbers'!$C$33="Yes"),('My Numbers'!$C$20*'My Numbers'!$C$21*'My Numbers'!$C$22*'My Numbers'!$C$23)*'My Numbers'!$C$36,0)))*(1+'My Numbers'!$C$24)+(IF(('My Numbers'!$C$33="Yes"),('My Numbers'!$C$20*'My Numbers'!$C$21*'My Numbers'!$C$22*'My Numbers'!$C$23)*'My Numbers'!$C$36,0)))*('My Numbers'!$C$26*(1-'My Numbers'!$C$29)-'My Numbers'!$C$27)+IF(('My Numbers'!$C$30="Yes"),('My Numbers'!$C$20*'My Numbers'!$C$21*'My Numbers'!$C$22*'My Numbers'!$C$23)*'My Numbers'!$C$32*'My Numbers'!$C$31*(1-'My Numbers'!$C$29),0)+IF(('My Numbers'!$C$33="Yes"),(IF(('My Numbers'!$C$33="Yes"),('My Numbers'!$C$20*'My Numbers'!$C$21*'My Numbers'!$C$22*'My Numbers'!$C$23)*'My Numbers'!$C$36,0))*'My Numbers'!$C$37*('My Numbers'!$C$34*(1-'My Numbers'!$C$29)-'My Numbers'!$C$35*'My Numbers'!$C$27),0))*(IF('This Month'!$C$27="",1,IF((((('My Numbers'!$C$20*'My Numbers'!$C$21*'My Numbers'!$C$22*'My Numbers'!$C$23)-(IF(('My Numbers'!$C$33="Yes"),('My Numbers'!$C$20*'My Numbers'!$C$21*'My Numbers'!$C$22*'My Numbers'!$C$23)*'My Numbers'!$C$36,0)))*(1+'My Numbers'!$C$24)+(IF(('My Numbers'!$C$33="Yes"),('My Numbers'!$C$20*'My Numbers'!$C$21*'My Numbers'!$C$22*'My Numbers'!$C$23)*'My Numbers'!$C$36,0)))+((IF(('My Numbers'!$C$33="Yes"),('My Numbers'!$C$20*'My Numbers'!$C$21*'My Numbers'!$C$22*'My Numbers'!$C$23)*'My Numbers'!$C$36,0))*'My Numbers'!$C$35*'My Numbers'!$C$37))>'This Month'!$C$27,'This Month'!$C$27/(((('My Numbers'!$C$20*'My Numbers'!$C$21*'My Numbers'!$C$22*'My Numbers'!$C$23)-(IF(('My Numbers'!$C$33="Yes"),('My Numbers'!$C$20*'My Numbers'!$C$21*'My Numbers'!$C$22*'My Numbers'!$C$23)*'My Numbers'!$C$36,0)))*(1+'My Numbers'!$C$24)+(IF(('My Numbers'!$C$33="Yes"),('My Numbers'!$C$20*'My Numbers'!$C$21*'My Numbers'!$C$22*'My Numbers'!$C$23)*'My Numbers'!$C$36,0)))+((IF(('My Numbers'!$C$33="Yes"),('My Numbers'!$C$20*'My Numbers'!$C$21*'My Numbers'!$C$22*'My Numbers'!$C$23)*'My Numbers'!$C$36,0))*'My Numbers'!$C$35*'My Numbers'!$C$37)),1))),0)) -> 0
B86: The bottleneck | C86: =IF('This Month'!$C$27<>"",IF('This Month'!$C$21>'This Month'!$C$27,"Capacity: you are full. Raise price or add a retainer or program.",IF(MAX(E82:E85)>0,INDEX(B82:B85,MATCH(MAX(E82:E85),E82:E85,0))&": worth "&TEXT(MAX(E82:E85),"$#,##0")&" a month at typical.","Nothing is below typical: it is a volume problem. See Plan.")),IF(MAX(E82:E85)>0,INDEX(B82:B85,MATCH(MAX(E82:E85),E82:E85,0))&": worth "&TEXT(MAX(E82:E85),"$#,##0")&" a month at typical.","Nothing is below typical: it is a volume problem. See Plan.")) -> Capacity: you are full. Raise price or add a retainer or program.
B87: Screening is not on this list on purpose. Your screening is yours.

Sheet Levers
A1: Levers
A2: What one small move on each number does to in-person gross profit this month. Biggest first is the one to work on. Screening is not here on purpose.
B4: Move | C4: Change a month | D4: How it is worked out
B5: Booking rate +1 point | C5: =IF(('My Numbers'!$C$38="Yes"),"program on",(((('My Numbers'!$C$20*'My Numbers'!$C$21*('My Numbers'!$C$22+0.01)*'My Numbers'!$C$23)-(IF(('My Numbers'!$C$33="Yes"),('My Numbers'!$C$20*'My Numbers'!$C$21*('My Numbers'!$C$22+0.01)*'My Numbers'!$C$23)*'My Numbers'!$C$36,0)))*(1+'My Numbers'!$C$24)+(IF(('My Numbers'!$C$33="Yes"),('My Numbers'!$C$20*'My Numbers'!$C$21*('My Numbers'!$C$22+0.01)*'My Numbers'!$C$23)*'My Numbers'!$C$36,0)))*('My Numbers'!$C$26*(1-'My Numbers'!$C$29)-'My Numbers'!$C$27)+IF(('My Numbers'!$C$30="Yes"),('My Numbers'!$C$20*'My Numbers'!$C$21*('My Numbers'!$C$22+0.01)*'My Numbers'!$C$23)*'My Numbers'!$C$32*'My Numbers'!$C$31*(1-'My Numbers'!$C$29),0)+IF(('My Numbers'!$C$33="Yes"),(IF(('My Numbers'!$C$33="Yes"),('My Numbers'!$C$20*'My Numbers'!$C$21*('My Numbers'!$C$22+0.01)*'My Numbers'!$C$23)*'My Numbers'!$C$36,0))*'My Numbers'!$C$37*('My Numbers'!$C$34*(1-'My Numbers'!$C$29)-'My Numbers'!$C$35*'My Numbers'!$C$27),0))*(IF('This Month'!$C$27="",1,IF((((('My Numbers'!$C$20*'My Numbers'!$C$21*('My Numbers'!$C$22+0.01)*'My Numbers'!$C$23)-(IF(('My Numbers'!$C$33="Yes"),('My Numbers'!$C$20*'My Numbers'!$C$21*('My Numbers'!$C$22+0.01)*'My Numbers'!$C$23)*'My Numbers'!$C$36,0)))*(1+'My Numbers'!$C$24)+(IF(('My Numbers'!$C$33="Yes"),('My Numbers'!$C$20*'My Numbers'!$C$21*('My Numbers'!$C$22+0.01)*'My Numbers'!$C$23)*'My Numbers'!$C$36,0)))+((IF(('My Numbers'!$C$33="Yes"),('My Numbers'!$C$20*'My Numbers'!$C$21*('My Numbers'!$C$22+0.01)*'My Numbers'!$C$23)*'My Numbers'!$C$36,0))*'My Numbers'!$C$35*'My Numbers'!$C$37))>'This Month'!$C$27,'This Month'!$C$27/(((('My Numbers'!$C$20*'My Numbers'!$C$21*('My Numbers'!$C$22+0.01)*'My Numbers'!$C$23)-(IF(('My Numbers'!$C$33="Yes"),('My Numbers'!$C$20*'My Numbers'!$C$21*('My Numbers'!$C$22+0.01)*'My Numbers'!$C$23)*'My Numbers'!$C$36,0)))*(1+'My Numbers'!$C$24)+(IF(('My Numbers'!$C$33="Yes"),('My Numbers'!$C$20*'My Numbers'!$C$21*('My Numbers'!$C$22+0.01)*'My Numbers'!$C$23)*'My Numbers'!$C$36,0)))+((IF(('My Numbers'!$C$33="Yes"),('My Numbers'!$C$20*'My Numbers'!$C$21*('My Numbers'!$C$22+0.01)*'My Numbers'!$C$23)*'My Numbers'!$C$36,0))*'My Numbers'!$C$35*'My Numbers'!$C$37)),1)))-(((('My Numbers'!$C$20*'My Numbers'!$C$21*'My Numbers'!$C$22*'My Numbers'!$C$23)-(IF(('My Numbers'!$C$33="Yes"),('My Numbers'!$C$20*'My Numbers'!$C$21*'My Numbers'!$C$22*'My Numbers'!$C$23)*'My Numbers'!$C$36,0)))*(1+'My Numbers'!$C$24)+(IF(('My Numbers'!$C$33="Yes"),('My Numbers'!$C$20*'My Numbers'!$C$21*'My Numbers'!$C$22*'My Numbers'!$C$23)*'My Numbers'!$C$36,0)))*('My Numbers'!$C$26*(1-'My Numbers'!$C$29)-'My Numbers'!$C$27)+IF(('My Numbers'!$C$30="Yes"),('My Numbers'!$C$20*'My Numbers'!$C$21*'My Numbers'!$C$22*'My Numbers'!$C$23)*'My Numbers'!$C$32*'My Numbers'!$C$31*(1-'My Numbers'!$C$29),0)+IF(('My Numbers'!$C$33="Yes"),(IF(('My Numbers'!$C$33="Yes"),('My Numbers'!$C$20*'My Numbers'!$C$21*'My Numbers'!$C$22*'My Numbers'!$C$23)*'My Numbers'!$C$36,0))*'My Numbers'!$C$37*('My Numbers'!$C$34*(1-'My Numbers'!$C$29)-'My Numbers'!$C$35*'My Numbers'!$C$27),0))*(IF('This Month'!$C$27="",1,IF((((('My Numbers'!$C$20*'My Numbers'!$C$21*'My Numbers'!$C$22*'My Numbers'!$C$23)-(IF(('My Numbers'!$C$33="Yes"),('My Numbers'!$C$20*'My Numbers'!$C$21*'My Numbers'!$C$22*'My Numbers'!$C$23)*'My Numbers'!$C$36,0)))*(1+'My Numbers'!$C$24)+(IF(('My Numbers'!$C$33="Yes"),('My Numbers'!$C$20*'My Numbers'!$C$21*'My Numbers'!$C$22*'My Numbers'!$C$23)*'My Numbers'!$C$36,0)))+((IF(('My Numbers'!$C$33="Yes"),('My Numbers'!$C$20*'My Numbers'!$C$21*'My Numbers'!$C$22*'My Numbers'!$C$23)*'My Numbers'!$C$36,0))*'My Numbers'!$C$35*'My Numbers'!$C$37))>'This Month'!$C$27,'This Month'!$C$27/(((('My Numbers'!$C$20*'My Numbers'!$C$21*'My Numbers'!$C$22*'My Numbers'!$C$23)-(IF(('My Numbers'!$C$33="Yes"),('My Numbers'!$C$20*'My Numbers'!$C$21*'My Numbers'!$C$22*'My Numbers'!$C$23)*'My Numbers'!$C$36,0)))*(1+'My Numbers'!$C$24)+(IF(('My Numbers'!$C$33="Yes"),('My Numbers'!$C$20*'My Numbers'!$C$21*'My Numbers'!$C$22*'My Numbers'!$C$23)*'My Numbers'!$C$36,0)))+((IF(('My Numbers'!$C$33="Yes"),('My Numbers'!$C$20*'My Numbers'!$C$21*'My Numbers'!$C$22*'My Numbers'!$C$23)*'My Numbers'!$C$36,0))*'My Numbers'!$C$35*'My Numbers'!$C$37)),1)))) -> 0 | D5: The booking rate raised by one point, everything else the same.
B6: Show rate +1 point | C6: =IF(('My Numbers'!$C$38="Yes"),"program on",(((('My Numbers'!$C$20*'My Numbers'!$C$21*'My Numbers'!$C$22*('My Numbers'!$C$23+0.01))-(IF(('My Numbers'!$C$33="Yes"),('My Numbers'!$C$20*'My Numbers'!$C$21*'My Numbers'!$C$22*('My Numbers'!$C$23+0.01))*'My Numbers'!$C$36,0)))*(1+'My Numbers'!$C$24)+(IF(('My Numbers'!$C$33="Yes"),('My Numbers'!$C$20*'My Numbers'!$C$21*'My Numbers'!$C$22*('My Numbers'!$C$23+0.01))*'My Numbers'!$C$36,0)))*('My Numbers'!$C$26*(1-'My Numbers'!$C$29)-'My Numbers'!$C$27)+IF(('My Numbers'!$C$30="Yes"),('My Numbers'!$C$20*'My Numbers'!$C$21*'My Numbers'!$C$22*('My Numbers'!$C$23+0.01))*'My Numbers'!$C$32*'My Numbers'!$C$31*(1-'My Numbers'!$C$29),0)+IF(('My Numbers'!$C$33="Yes"),(IF(('My Numbers'!$C$33="Yes"),('My Numbers'!$C$20*'My Numbers'!$C$21*'My Numbers'!$C$22*('My Numbers'!$C$23+0.01))*'My Numbers'!$C$36,0))*'My Numbers'!$C$37*('My Numbers'!$C$34*(1-'My Numbers'!$C$29)-'My Numbers'!$C$35*'My Numbers'!$C$27),0))*(IF('This Month'!$C$27="",1,IF((((('My Numbers'!$C$20*'My Numbers'!$C$21*'My Numbers'!$C$22*('My Numbers'!$C$23+0.01))-(IF(('My Numbers'!$C$33="Yes"),('My Numbers'!$C$20*'My Numbers'!$C$21*'My Numbers'!$C$22*('My Numbers'!$C$23+0.01))*'My Numbers'!$C$36,0)))*(1+'My Numbers'!$C$24)+(IF(('My Numbers'!$C$33="Yes"),('My Numbers'!$C$20*'My Numbers'!$C$21*'My Numbers'!$C$22*('My Numbers'!$C$23+0.01))*'My Numbers'!$C$36,0)))+((IF(('My Numbers'!$C$33="Yes"),('My Numbers'!$C$20*'My Numbers'!$C$21*'My Numbers'!$C$22*('My Numbers'!$C$23+0.01))*'My Numbers'!$C$36,0))*'My Numbers'!$C$35*'My Numbers'!$C$37))>'This Month'!$C$27,'This Month'!$C$27/(((('My Numbers'!$C$20*'My Numbers'!$C$21*'My Numbers'!$C$22*('My Numbers'!$C$23+0.01))-(IF(('My Numbers'!$C$33="Yes"),('My Numbers'!$C$20*'My Numbers'!$C$21*'My Numbers'!$C$22*('My Numbers'!$C$23+0.01))*'My Numbers'!$C$36,0)))*(1+'My Numbers'!$C$24)+(IF(('My Numbers'!$C$33="Yes"),('My Numbers'!$C$20*'My Numbers'!$C$21*'My Numbers'!$C$22*('My Numbers'!$C$23+0.01))*'My Numbers'!$C$36,0)))+((IF(('My Numbers'!$C$33="Yes"),('My Numbers'!$C$20*'My Numbers'!$C$21*'My Numbers'!$C$22*('My Numbers'!$C$23+0.01))*'My Numbers'!$C$36,0))*'My Numbers'!$C$35*'My Numbers'!$C$37)),1)))-(((('My Numbers'!$C$20*'My Numbers'!$C$21*'My Numbers'!$C$22*'My Numbers'!$C$23)-(IF(('My Numbers'!$C$33="Yes"),('My Numbers'!$C$20*'My Numbers'!$C$21*'My Numbers'!$C$22*'My Numbers'!$C$23)*'My Numbers'!$C$36,0)))*(1+'My Numbers'!$C$24)+(IF(('My Numbers'!$C$33="Yes"),('My Numbers'!$C$20*'My Numbers'!$C$21*'My Numbers'!$C$22*'My Numbers'!$C$23)*'My Numbers'!$C$36,0)))*('My Numbers'!$C$26*(1-'My Numbers'!$C$29)-'My Numbers'!$C$27)+IF(('My Numbers'!$C$30="Yes"),('My Numbers'!$C$20*'My Numbers'!$C$21*'My Numbers'!$C$22*'My Numbers'!$C$23)*'My Numbers'!$C$32*'My Numbers'!$C$31*(1-'My Numbers'!$C$29),0)+IF(('My Numbers'!$C$33="Yes"),(IF(('My Numbers'!$C$33="Yes"),('My Numbers'!$C$20*'My Numbers'!$C$21*'My Numbers'!$C$22*'My Numbers'!$C$23)*'My Numbers'!$C$36,0))*'My Numbers'!$C$37*('My Numbers'!$C$34*(1-'My Numbers'!$C$29)-'My Numbers'!$C$35*'My Numbers'!$C$27),0))*(IF('This Month'!$C$27="",1,IF((((('My Numbers'!$C$20*'My Numbers'!$C$21*'My Numbers'!$C$22*'My Numbers'!$C$23)-(IF(('My Numbers'!$C$33="Yes"),('My Numbers'!$C$20*'My Numbers'!$C$21*'My Numbers'!$C$22*'My Numbers'!$C$23)*'My Numbers'!$C$36,0)))*(1+'My Numbers'!$C$24)+(IF(('My Numbers'!$C$33="Yes"),('My Numbers'!$C$20*'My Numbers'!$C$21*'My Numbers'!$C$22*'My Numbers'!$C$23)*'My Numbers'!$C$36,0)))+((IF(('My Numbers'!$C$33="Yes"),('My Numbers'!$C$20*'My Numbers'!$C$21*'My Numbers'!$C$22*'My Numbers'!$C$23)*'My Numbers'!$C$36,0))*'My Numbers'!$C$35*'My Numbers'!$C$37))>'This Month'!$C$27,'This Month'!$C$27/(((('My Numbers'!$C$20*'My Numbers'!$C$21*'My Numbers'!$C$22*'My Numbers'!$C$23)-(IF(('My Numbers'!$C$33="Yes"),('My Numbers'!$C$20*'My Numbers'!$C$21*'My Numbers'!$C$22*'My Numbers'!$C$23)*'My Numbers'!$C$36,0)))*(1+'My Numbers'!$C$24)+(IF(('My Numbers'!$C$33="Yes"),('My Numbers'!$C$20*'My Numbers'!$C$21*'My Numbers'!$C$22*'My Numbers'!$C$23)*'My Numbers'!$C$36,0)))+((IF(('My Numbers'!$C$33="Yes"),('My Numbers'!$C$20*'My Numbers'!$C$21*'My Numbers'!$C$22*'My Numbers'!$C$23)*'My Numbers'!$C$36,0))*'My Numbers'!$C$35*'My Numbers'!$C$37)),1)))) -> 0
B7: Rebook rate +1 point | C7: =IF(('My Numbers'!$C$38="Yes"),"program on",(((('My Numbers'!$C$20*'My Numbers'!$C$21*'My Numbers'!$C$22*'My Numbers'!$C$23)-(IF(('My Numbers'!$C$33="Yes"),('My Numbers'!$C$20*'My Numbers'!$C$21*'My Numbers'!$C$22*'My Numbers'!$C$23)*'My Numbers'!$C$36,0)))*(1+('My Numbers'!$C$24+0.01))+(IF(('My Numbers'!$C$33="Yes"),('My Numbers'!$C$20*'My Numbers'!$C$21*'My Numbers'!$C$22*'My Numbers'!$C$23)*'My Numbers'!$C$36,0)))*('My Numbers'!$C$26*(1-'My Numbers'!$C$29)-'My Numbers'!$C$27)+IF(('My Numbers'!$C$30="Yes"),('My Numbers'!$C$20*'My Numbers'!$C$21*'My Numbers'!$C$22*'My Numbers'!$C$23)*'My Numbers'!$C$32*'My Numbers'!$C$31*(1-'My Numbers'!$C$29),0)+IF(('My Numbers'!$C$33="Yes"),(IF(('My Numbers'!$C$33="Yes"),('My Numbers'!$C$20*'My Numbers'!$C$21*'My Numbers'!$C$22*'My Numbers'!$C$23)*'My Numbers'!$C$36,0))*'My Numbers'!$C$37*('My Numbers'!$C$34*(1-'My Numbers'!$C$29)-'My Numbers'!$C$35*'My Numbers'!$C$27),0))*(IF('This Month'!$C$27="",1,IF((((('My Numbers'!$C$20*'My Numbers'!$C$21*'My Numbers'!$C$22*'My Numbers'!$C$23)-(IF(('My Numbers'!$C$33="Yes"),('My Numbers'!$C$20*'My Numbers'!$C$21*'My Numbers'!$C$22*'My Numbers'!$C$23)*'My Numbers'!$C$36,0)))*(1+('My Numbers'!$C$24+0.01))+(IF(('My Numbers'!$C$33="Yes"),('My Numbers'!$C$20*'My Numbers'!$C$21*'My Numbers'!$C$22*'My Numbers'!$C$23)*'My Numbers'!$C$36,0)))+((IF(('My Numbers'!$C$33="Yes"),('My Numbers'!$C$20*'My Numbers'!$C$21*'My Numbers'!$C$22*'My Numbers'!$C$23)*'My Numbers'!$C$36,0))*'My Numbers'!$C$35*'My Numbers'!$C$37))>'This Month'!$C$27,'This Month'!$C$27/(((('My Numbers'!$C$20*'My Numbers'!$C$21*'My Numbers'!$C$22*'My Numbers'!$C$23)-(IF(('My Numbers'!$C$33="Yes"),('My Numbers'!$C$20*'My Numbers'!$C$21*'My Numbers'!$C$22*'My Numbers'!$C$23)*'My Numbers'!$C$36,0)))*(1+('My Numbers'!$C$24+0.01))+(IF(('My Numbers'!$C$33="Yes"),('My Numbers'!$C$20*'My Numbers'!$C$21*'My Numbers'!$C$22*'My Numbers'!$C$23)*'My Numbers'!$C$36,0)))+((IF(('My Numbers'!$C$33="Yes"),('My Numbers'!$C$20*'My Numbers'!$C$21*'My Numbers'!$C$22*'My Numbers'!$C$23)*'My Numbers'!$C$36,0))*'My Numbers'!$C$35*'My Numbers'!$C$37)),1)))-(((('My Numbers'!$C$20*'My Numbers'!$C$21*'My Numbers'!$C$22*'My Numbers'!$C$23)-(IF(('My Numbers'!$C$33="Yes"),('My Numbers'!$C$20*'My Numbers'!$C$21*'My Numbers'!$C$22*'My Numbers'!$C$23)*'My Numbers'!$C$36,0)))*(1+'My Numbers'!$C$24)+(IF(('My Numbers'!$C$33="Yes"),('My Numbers'!$C$20*'My Numbers'!$C$21*'My Numbers'!$C$22*'My Numbers'!$C$23)*'My Numbers'!$C$36,0)))*('My Numbers'!$C$26*(1-'My Numbers'!$C$29)-'My Numbers'!$C$27)+IF(('My Numbers'!$C$30="Yes"),('My Numbers'!$C$20*'My Numbers'!$C$21*'My Numbers'!$C$22*'My Numbers'!$C$23)*'My Numbers'!$C$32*'My Numbers'!$C$31*(1-'My Numbers'!$C$29),0)+IF(('My Numbers'!$C$33="Yes"),(IF(('My Numbers'!$C$33="Yes"),('My Numbers'!$C$20*'My Numbers'!$C$21*'My Numbers'!$C$22*'My Numbers'!$C$23)*'My Numbers'!$C$36,0))*'My Numbers'!$C$37*('My Numbers'!$C$34*(1-'My Numbers'!$C$29)-'My Numbers'!$C$35*'My Numbers'!$C$27),0))*(IF('This Month'!$C$27="",1,IF((((('My Numbers'!$C$20*'My Numbers'!$C$21*'My Numbers'!$C$22*'My Numbers'!$C$23)-(IF(('My Numbers'!$C$33="Yes"),('My Numbers'!$C$20*'My Numbers'!$C$21*'My Numbers'!$C$22*'My Numbers'!$C$23)*'My Numbers'!$C$36,0)))*(1+'My Numbers'!$C$24)+(IF(('My Numbers'!$C$33="Yes"),('My Numbers'!$C$20*'My Numbers'!$C$21*'My Numbers'!$C$22*'My Numbers'!$C$23)*'My Numbers'!$C$36,0)))+((IF(('My Numbers'!$C$33="Yes"),('My Numbers'!$C$20*'My Numbers'!$C$21*'My Numbers'!$C$22*'My Numbers'!$C$23)*'My Numbers'!$C$36,0))*'My Numbers'!$C$35*'My Numbers'!$C$37))>'This Month'!$C$27,'This Month'!$C$27/(((('My Numbers'!$C$20*'My Numbers'!$C$21*'My Numbers'!$C$22*'My Numbers'!$C$23)-(IF(('My Numbers'!$C$33="Yes"),('My Numbers'!$C$20*'My Numbers'!$C$21*'My Numbers'!$C$22*'My Numbers'!$C$23)*'My Numbers'!$C$36,0)))*(1+'My Numbers'!$C$24)+(IF(('My Numbers'!$C$33="Yes"),('My Numbers'!$C$20*'My Numbers'!$C$21*'My Numbers'!$C$22*'My Numbers'!$C$23)*'My Numbers'!$C$36,0)))+((IF(('My Numbers'!$C$33="Yes"),('My Numbers'!$C$20*'My Numbers'!$C$21*'My Numbers'!$C$22*'My Numbers'!$C$23)*'My Numbers'!$C$36,0))*'My Numbers'!$C$35*'My Numbers'!$C$37)),1)))) -> -8.940335
B8: Session price +1% | C8: =IF(('My Numbers'!$C$38="Yes"),"program on",(((('My Numbers'!$C$20*'My Numbers'!$C$21*'My Numbers'!$C$22*'My Numbers'!$C$23)-(IF(('My Numbers'!$C$33="Yes"),('My Numbers'!$C$20*'My Numbers'!$C$21*'My Numbers'!$C$22*'My Numbers'!$C$23)*'My Numbers'!$C$36,0)))*(1+'My Numbers'!$C$24)+(IF(('My Numbers'!$C$33="Yes"),('My Numbers'!$C$20*'My Numbers'!$C$21*'My Numbers'!$C$22*'My Numbers'!$C$23)*'My Numbers'!$C$36,0)))*(('My Numbers'!$C$26*1.01)*(1-'My Numbers'!$C$29)-'My Numbers'!$C$27)+IF(('My Numbers'!$C$30="Yes"),('My Numbers'!$C$20*'My Numbers'!$C$21*'My Numbers'!$C$22*'My Numbers'!$C$23)*'My Numbers'!$C$32*'My Numbers'!$C$31*(1-'My Numbers'!$C$29),0)+IF(('My Numbers'!$C$33="Yes"),(IF(('My Numbers'!$C$33="Yes"),('My Numbers'!$C$20*'My Numbers'!$C$21*'My Numbers'!$C$22*'My Numbers'!$C$23)*'My Numbers'!$C$36,0))*'My Numbers'!$C$37*('My Numbers'!$C$34*(1-'My Numbers'!$C$29)-'My Numbers'!$C$35*'My Numbers'!$C$27),0))*(IF('This Month'!$C$27="",1,IF((((('My Numbers'!$C$20*'My Numbers'!$C$21*'My Numbers'!$C$22*'My Numbers'!$C$23)-(IF(('My Numbers'!$C$33="Yes"),('My Numbers'!$C$20*'My Numbers'!$C$21*'My Numbers'!$C$22*'My Numbers'!$C$23)*'My Numbers'!$C$36,0)))*(1+'My Numbers'!$C$24)+(IF(('My Numbers'!$C$33="Yes"),('My Numbers'!$C$20*'My Numbers'!$C$21*'My Numbers'!$C$22*'My Numbers'!$C$23)*'My Numbers'!$C$36,0)))+((IF(('My Numbers'!$C$33="Yes"),('My Numbers'!$C$20*'My Numbers'!$C$21*'My Numbers'!$C$22*'My Numbers'!$C$23)*'My Numbers'!$C$36,0))*'My Numbers'!$C$35*'My Numbers'!$C$37))>'This Month'!$C$27,'This Month'!$C$27/(((('My Numbers'!$C$20*'My Numbers'!$C$21*'My Numbers'!$C$22*'My Numbers'!$C$23)-(IF(('My Numbers'!$C$33="Yes"),('My Numbers'!$C$20*'My Numbers'!$C$21*'My Numbers'!$C$22*'My Numbers'!$C$23)*'My Numbers'!$C$36,0)))*(1+'My Numbers'!$C$24)+(IF(('My Numbers'!$C$33="Yes"),('My Numbers'!$C$20*'My Numbers'!$C$21*'My Numbers'!$C$22*'My Numbers'!$C$23)*'My Numbers'!$C$36,0)))+((IF(('My Numbers'!$C$33="Yes"),('My Numbers'!$C$20*'My Numbers'!$C$21*'My Numbers'!$C$22*'My Numbers'!$C$23)*'My Numbers'!$C$36,0))*'My Numbers'!$C$35*'My Numbers'!$C$37)),1)))-(((('My Numbers'!$C$20*'My Numbers'!$C$21*'My Numbers'!$C$22*'My Numbers'!$C$23)-(IF(('My Numbers'!$C$33="Yes"),('My Numbers'!$C$20*'My Numbers'!$C$21*'My Numbers'!$C$22*'My Numbers'!$C$23)*'My Numbers'!$C$36,0)))*(1+'My Numbers'!$C$24)+(IF(('My Numbers'!$C$33="Yes"),('My Numbers'!$C$20*'My Numbers'!$C$21*'My Numbers'!$C$22*'My Numbers'!$C$23)*'My Numbers'!$C$36,0)))*('My Numbers'!$C$26*(1-'My Numbers'!$C$29)-'My Numbers'!$C$27)+IF(('My Numbers'!$C$30="Yes"),('My Numbers'!$C$20*'My Numbers'!$C$21*'My Numbers'!$C$22*'My Numbers'!$C$23)*'My Numbers'!$C$32*'My Numbers'!$C$31*(1-'My Numbers'!$C$29),0)+IF(('My Numbers'!$C$33="Yes"),(IF(('My Numbers'!$C$33="Yes"),('My Numbers'!$C$20*'My Numbers'!$C$21*'My Numbers'!$C$22*'My Numbers'!$C$23)*'My Numbers'!$C$36,0))*'My Numbers'!$C$37*('My Numbers'!$C$34*(1-'My Numbers'!$C$29)-'My Numbers'!$C$35*'My Numbers'!$C$27),0))*(IF('This Month'!$C$27="",1,IF((((('My Numbers'!$C$20*'My Numbers'!$C$21*'My Numbers'!$C$22*'My Numbers'!$C$23)-(IF(('My Numbers'!$C$33="Yes"),('My Numbers'!$C$20*'My Numbers'!$C$21*'My Numbers'!$C$22*'My Numbers'!$C$23)*'My Numbers'!$C$36,0)))*(1+'My Numbers'!$C$24)+(IF(('My Numbers'!$C$33="Yes"),('My Numbers'!$C$20*'My Numbers'!$C$21*'My Numbers'!$C$22*'My Numbers'!$C$23)*'My Numbers'!$C$36,0)))+((IF(('My Numbers'!$C$33="Yes"),('My Numbers'!$C$20*'My Numbers'!$C$21*'My Numbers'!$C$22*'My Numbers'!$C$23)*'My Numbers'!$C$36,0))*'My Numbers'!$C$35*'My Numbers'!$C$37))>'This Month'!$C$27,'This Month'!$C$27/(((('My Numbers'!$C$20*'My Numbers'!$C$21*'My Numbers'!$C$22*'My Numbers'!$C$23)-(IF(('My Numbers'!$C$33="Yes"),('My Numbers'!$C$20*'My Numbers'!$C$21*'My Numbers'!$C$22*'My Numbers'!$C$23)*'My Numbers'!$C$36,0)))*(1+'My Numbers'!$C$24)+(IF(('My Numbers'!$C$33="Yes"),('My Numbers'!$C$20*'My Numbers'!$C$21*'My Numbers'!$C$22*'My Numbers'!$C$23)*'My Numbers'!$C$36,0)))+((IF(('My Numbers'!$C$33="Yes"),('My Numbers'!$C$20*'My Numbers'!$C$21*'My Numbers'!$C$22*'My Numbers'!$C$23)*'My Numbers'!$C$36,0))*'My Numbers'!$C$35*'My Numbers'!$C$37)),1)))) -> 52.456522
B9: Contacts +1% | C9: =IF(('My Numbers'!$C$38="Yes"),"program on",((((('My Numbers'!$C$20*1.01)*'My Numbers'!$C$21*'My Numbers'!$C$22*'My Numbers'!$C$23)-(IF(('My Numbers'!$C$33="Yes"),(('My Numbers'!$C$20*1.01)*'My Numbers'!$C$21*'My Numbers'!$C$22*'My Numbers'!$C$23)*'My Numbers'!$C$36,0)))*(1+'My Numbers'!$C$24)+(IF(('My Numbers'!$C$33="Yes"),(('My Numbers'!$C$20*1.01)*'My Numbers'!$C$21*'My Numbers'!$C$22*'My Numbers'!$C$23)*'My Numbers'!$C$36,0)))*('My Numbers'!$C$26*(1-'My Numbers'!$C$29)-'My Numbers'!$C$27)+IF(('My Numbers'!$C$30="Yes"),(('My Numbers'!$C$20*1.01)*'My Numbers'!$C$21*'My Numbers'!$C$22*'My Numbers'!$C$23)*'My Numbers'!$C$32*'My Numbers'!$C$31*(1-'My Numbers'!$C$29),0)+IF(('My Numbers'!$C$33="Yes"),(IF(('My Numbers'!$C$33="Yes"),(('My Numbers'!$C$20*1.01)*'My Numbers'!$C$21*'My Numbers'!$C$22*'My Numbers'!$C$23)*'My Numbers'!$C$36,0))*'My Numbers'!$C$37*('My Numbers'!$C$34*(1-'My Numbers'!$C$29)-'My Numbers'!$C$35*'My Numbers'!$C$27),0))*(IF('This Month'!$C$27="",1,IF(((((('My Numbers'!$C$20*1.01)*'My Numbers'!$C$21*'My Numbers'!$C$22*'My Numbers'!$C$23)-(IF(('My Numbers'!$C$33="Yes"),(('My Numbers'!$C$20*1.01)*'My Numbers'!$C$21*'My Numbers'!$C$22*'My Numbers'!$C$23)*'My Numbers'!$C$36,0)))*(1+'My Numbers'!$C$24)+(IF(('My Numbers'!$C$33="Yes"),(('My Numbers'!$C$20*1.01)*'My Numbers'!$C$21*'My Numbers'!$C$22*'My Numbers'!$C$23)*'My Numbers'!$C$36,0)))+((IF(('My Numbers'!$C$33="Yes"),(('My Numbers'!$C$20*1.01)*'My Numbers'!$C$21*'My Numbers'!$C$22*'My Numbers'!$C$23)*'My Numbers'!$C$36,0))*'My Numbers'!$C$35*'My Numbers'!$C$37))>'This Month'!$C$27,'This Month'!$C$27/((((('My Numbers'!$C$20*1.01)*'My Numbers'!$C$21*'My Numbers'!$C$22*'My Numbers'!$C$23)-(IF(('My Numbers'!$C$33="Yes"),(('My Numbers'!$C$20*1.01)*'My Numbers'!$C$21*'My Numbers'!$C$22*'My Numbers'!$C$23)*'My Numbers'!$C$36,0)))*(1+'My Numbers'!$C$24)+(IF(('My Numbers'!$C$33="Yes"),(('My Numbers'!$C$20*1.01)*'My Numbers'!$C$21*'My Numbers'!$C$22*'My Numbers'!$C$23)*'My Numbers'!$C$36,0)))+((IF(('My Numbers'!$C$33="Yes"),(('My Numbers'!$C$20*1.01)*'My Numbers'!$C$21*'My Numbers'!$C$22*'My Numbers'!$C$23)*'My Numbers'!$C$36,0))*'My Numbers'!$C$35*'My Numbers'!$C$37)),1)))-(((('My Numbers'!$C$20*'My Numbers'!$C$21*'My Numbers'!$C$22*'My Numbers'!$C$23)-(IF(('My Numbers'!$C$33="Yes"),('My Numbers'!$C$20*'My Numbers'!$C$21*'My Numbers'!$C$22*'My Numbers'!$C$23)*'My Numbers'!$C$36,0)))*(1+'My Numbers'!$C$24)+(IF(('My Numbers'!$C$33="Yes"),('My Numbers'!$C$20*'My Numbers'!$C$21*'My Numbers'!$C$22*'My Numbers'!$C$23)*'My Numbers'!$C$36,0)))*('My Numbers'!$C$26*(1-'My Numbers'!$C$29)-'My Numbers'!$C$27)+IF(('My Numbers'!$C$30="Yes"),('My Numbers'!$C$20*'My Numbers'!$C$21*'My Numbers'!$C$22*'My Numbers'!$C$23)*'My Numbers'!$C$32*'My Numbers'!$C$31*(1-'My Numbers'!$C$29),0)+IF(('My Numbers'!$C$33="Yes"),(IF(('My Numbers'!$C$33="Yes"),('My Numbers'!$C$20*'My Numbers'!$C$21*'My Numbers'!$C$22*'My Numbers'!$C$23)*'My Numbers'!$C$36,0))*'My Numbers'!$C$37*('My Numbers'!$C$34*(1-'My Numbers'!$C$29)-'My Numbers'!$C$35*'My Numbers'!$C$27),0))*(IF('This Month'!$C$27="",1,IF((((('My Numbers'!$C$20*'My Numbers'!$C$21*'My Numbers'!$C$22*'My Numbers'!$C$23)-(IF(('My Numbers'!$C$33="Yes"),('My Numbers'!$C$20*'My Numbers'!$C$21*'My Numbers'!$C$22*'My Numbers'!$C$23)*'My Numbers'!$C$36,0)))*(1+'My Numbers'!$C$24)+(IF(('My Numbers'!$C$33="Yes"),('My Numbers'!$C$20*'My Numbers'!$C$21*'My Numbers'!$C$22*'My Numbers'!$C$23)*'My Numbers'!$C$36,0)))+((IF(('My Numbers'!$C$33="Yes"),('My Numbers'!$C$20*'My Numbers'!$C$21*'My Numbers'!$C$22*'My Numbers'!$C$23)*'My Numbers'!$C$36,0))*'My Numbers'!$C$35*'My Numbers'!$C$37))>'This Month'!$C$27,'This Month'!$C$27/(((('My Numbers'!$C$20*'My Numbers'!$C$21*'My Numbers'!$C$22*'My Numbers'!$C$23)-(IF(('My Numbers'!$C$33="Yes"),('My Numbers'!$C$20*'My Numbers'!$C$21*'My Numbers'!$C$22*'My Numbers'!$C$23)*'My Numbers'!$C$36,0)))*(1+'My Numbers'!$C$24)+(IF(('My Numbers'!$C$33="Yes"),('My Numbers'!$C$20*'My Numbers'!$C$21*'My Numbers'!$C$22*'My Numbers'!$C$23)*'My Numbers'!$C$36,0)))+((IF(('My Numbers'!$C$33="Yes"),('My Numbers'!$C$20*'My Numbers'!$C$21*'My Numbers'!$C$22*'My Numbers'!$C$23)*'My Numbers'!$C$36,0))*'My Numbers'!$C$35*'My Numbers'!$C$37)),1)))) -> 0
B10: Delivery cost −1% | C10: =IF(('My Numbers'!$C$38="Yes"),"program on",(((('My Numbers'!$C$20*'My Numbers'!$C$21*'My Numbers'!$C$22*'My Numbers'!$C$23)-(IF(('My Numbers'!$C$33="Yes"),('My Numbers'!$C$20*'My Numbers'!$C$21*'My Numbers'!$C$22*'My Numbers'!$C$23)*'My Numbers'!$C$36,0)))*(1+'My Numbers'!$C$24)+(IF(('My Numbers'!$C$33="Yes"),('My Numbers'!$C$20*'My Numbers'!$C$21*'My Numbers'!$C$22*'My Numbers'!$C$23)*'My Numbers'!$C$36,0)))*('My Numbers'!$C$26*(1-'My Numbers'!$C$29)-('My Numbers'!$C$27*0.99))+IF(('My Numbers'!$C$30="Yes"),('My Numbers'!$C$20*'My Numbers'!$C$21*'My Numbers'!$C$22*'My Numbers'!$C$23)*'My Numbers'!$C$32*'My Numbers'!$C$31*(1-'My Numbers'!$C$29),0)+IF(('My Numbers'!$C$33="Yes"),(IF(('My Numbers'!$C$33="Yes"),('My Numbers'!$C$20*'My Numbers'!$C$21*'My Numbers'!$C$22*'My Numbers'!$C$23)*'My Numbers'!$C$36,0))*'My Numbers'!$C$37*('My Numbers'!$C$34*(1-'My Numbers'!$C$29)-'My Numbers'!$C$35*('My Numbers'!$C$27*0.99)),0))*(IF('This Month'!$C$27="",1,IF((((('My Numbers'!$C$20*'My Numbers'!$C$21*'My Numbers'!$C$22*'My Numbers'!$C$23)-(IF(('My Numbers'!$C$33="Yes"),('My Numbers'!$C$20*'My Numbers'!$C$21*'My Numbers'!$C$22*'My Numbers'!$C$23)*'My Numbers'!$C$36,0)))*(1+'My Numbers'!$C$24)+(IF(('My Numbers'!$C$33="Yes"),('My Numbers'!$C$20*'My Numbers'!$C$21*'My Numbers'!$C$22*'My Numbers'!$C$23)*'My Numbers'!$C$36,0)))+((IF(('My Numbers'!$C$33="Yes"),('My Numbers'!$C$20*'My Numbers'!$C$21*'My Numbers'!$C$22*'My Numbers'!$C$23)*'My Numbers'!$C$36,0))*'My Numbers'!$C$35*'My Numbers'!$C$37))>'This Month'!$C$27,'This Month'!$C$27/(((('My Numbers'!$C$20*'My Numbers'!$C$21*'My Numbers'!$C$22*'My Numbers'!$C$23)-(IF(('My Numbers'!$C$33="Yes"),('My Numbers'!$C$20*'My Numbers'!$C$21*'My Numbers'!$C$22*'My Numbers'!$C$23)*'My Numbers'!$C$36,0)))*(1+'My Numbers'!$C$24)+(IF(('My Numbers'!$C$33="Yes"),('My Numbers'!$C$20*'My Numbers'!$C$21*'My Numbers'!$C$22*'My Numbers'!$C$23)*'My Numbers'!$C$36,0)))+((IF(('My Numbers'!$C$33="Yes"),('My Numbers'!$C$20*'My Numbers'!$C$21*'My Numbers'!$C$22*'My Numbers'!$C$23)*'My Numbers'!$C$36,0))*'My Numbers'!$C$35*'My Numbers'!$C$37)),1)))-(((('My Numbers'!$C$20*'My Numbers'!$C$21*'My Numbers'!$C$22*'My Numbers'!$C$23)-(IF(('My Numbers'!$C$33="Yes"),('My Numbers'!$C$20*'My Numbers'!$C$21*'My Numbers'!$C$22*'My Numbers'!$C$23)*'My Numbers'!$C$36,0)))*(1+'My Numbers'!$C$24)+(IF(('My Numbers'!$C$33="Yes"),('My Numbers'!$C$20*'My Numbers'!$C$21*'My Numbers'!$C$22*'My Numbers'!$C$23)*'My Numbers'!$C$36,0)))*('My Numbers'!$C$26*(1-'My Numbers'!$C$29)-'My Numbers'!$C$27)+IF(('My Numbers'!$C$30="Yes"),('My Numbers'!$C$20*'My Numbers'!$C$21*'My Numbers'!$C$22*'My Numbers'!$C$23)*'My Numbers'!$C$32*'My Numbers'!$C$31*(1-'My Numbers'!$C$29),0)+IF(('My Numbers'!$C$33="Yes"),(IF(('My Numbers'!$C$33="Yes"),('My Numbers'!$C$20*'My Numbers'!$C$21*'My Numbers'!$C$22*'My Numbers'!$C$23)*'My Numbers'!$C$36,0))*'My Numbers'!$C$37*('My Numbers'!$C$34*(1-'My Numbers'!$C$29)-'My Numbers'!$C$35*'My Numbers'!$C$27),0))*(IF('This Month'!$C$27="",1,IF((((('My Numbers'!$C$20*'My Numbers'!$C$21*'My Numbers'!$C$22*'My Numbers'!$C$23)-(IF(('My Numbers'!$C$33="Yes"),('My Numbers'!$C$20*'My Numbers'!$C$21*'My Numbers'!$C$22*'My Numbers'!$C$23)*'My Numbers'!$C$36,0)))*(1+'My Numbers'!$C$24)+(IF(('My Numbers'!$C$33="Yes"),('My Numbers'!$C$20*'My Numbers'!$C$21*'My Numbers'!$C$22*'My Numbers'!$C$23)*'My Numbers'!$C$36,0)))+((IF(('My Numbers'!$C$33="Yes"),('My Numbers'!$C$20*'My Numbers'!$C$21*'My Numbers'!$C$22*'My Numbers'!$C$23)*'My Numbers'!$C$36,0))*'My Numbers'!$C$35*'My Numbers'!$C$37))>'This Month'!$C$27,'This Month'!$C$27/(((('My Numbers'!$C$20*'My Numbers'!$C$21*'My Numbers'!$C$22*'My Numbers'!$C$23)-(IF(('My Numbers'!$C$33="Yes"),('My Numbers'!$C$20*'My Numbers'!$C$21*'My Numbers'!$C$22*'My Numbers'!$C$23)*'My Numbers'!$C$36,0)))*(1+'My Numbers'!$C$24)+(IF(('My Numbers'!$C$33="Yes"),('My Numbers'!$C$20*'My Numbers'!$C$21*'My Numbers'!$C$22*'My Numbers'!$C$23)*'My Numbers'!$C$36,0)))+((IF(('My Numbers'!$C$33="Yes"),('My Numbers'!$C$20*'My Numbers'!$C$21*'My Numbers'!$C$22*'My Numbers'!$C$23)*'My Numbers'!$C$36,0))*'My Numbers'!$C$35*'My Numbers'!$C$37)),1)))) -> 18
B12: The biggest single move | C12: =IFERROR(INDEX(B5:B10,MATCH(MAX(C5:C10),C5:C10,0)),"") -> Session price +1%
B13: =IF('This Month'!$C$27="","",IF('This Month'!$C$21>'This Month'!$C$27,"You are at capacity, so more contacts or bookings add nothing until you raise the price, add a retainer, or lift the cap. A move can even read below zero: it fills the same hours with cheaper sessions.","")) -> You are at capacity, so more contacts or bookings add nothing until you raise the price, add a retainer, or lift the cap. A move can even read below zero: it fills the same hours with cheaper sessions.

Sheet Three Futures
A1: Three Futures
A2: Normal is your numbers as they stand. Dream and Disaster move contacts, audience and conversion by the amounts on My Numbers; the Disaster switches add events. Runway is how many months your cash covers the gap to your goal.
C4: Disaster | D4: Normal | E4: Dream
B5: In person | C5: =IF(('My Numbers'!$C$18="Yes"),IF(('My Numbers'!$C$38="Yes"),(((('My Numbers'!$C$20*(1+'My Numbers'!$C$94)*IF(('My Numbers'!$C$98="Yes"),1-'My Numbers'!$C$96,1)*IF(('My Numbers'!$C$100="Yes"),0,1))*'My Numbers'!$C$21*'My Numbers'!$C$22*'My Numbers'!$C$23)*MIN(1,'My Numbers'!$C$41*(1+'My Numbers'!$C$95)))*('My Numbers'!$C$39*IF(('My Numbers'!$C$99="Yes"),1-'My Numbers'!$C$97,1)*(1-'My Numbers'!$C$43)-'My Numbers'!$C$42)),((((('My Numbers'!$C$20*(1+'My Numbers'!$C$94)*IF(('My Numbers'!$C$98="Yes"),1-'My Numbers'!$C$96,1)*IF(('My Numbers'!$C$100="Yes"),0,1))*'My Numbers'!$C$21*'My Numbers'!$C$22*'My Numbers'!$C$23)-(IF(('My Numbers'!$C$33="Yes"),(('My Numbers'!$C$20*(1+'My Numbers'!$C$94)*IF(('My Numbers'!$C$98="Yes"),1-'My Numbers'!$C$96,1)*IF(('My Numbers'!$C$100="Yes"),0,1))*'My Numbers'!$C$21*'My Numbers'!$C$22*'My Numbers'!$C$23)*'My Numbers'!$C$36,0)))*(1+'My Numbers'!$C$24)+(IF(('My Numbers'!$C$33="Yes"),(('My Numbers'!$C$20*(1+'My Numbers'!$C$94)*IF(('My Numbers'!$C$98="Yes"),1-'My Numbers'!$C$96,1)*IF(('My Numbers'!$C$100="Yes"),0,1))*'My Numbers'!$C$21*'My Numbers'!$C$22*'My Numbers'!$C$23)*'My Numbers'!$C$36,0)))*(('My Numbers'!$C$26*IF(('My Numbers'!$C$99="Yes"),1-'My Numbers'!$C$97,1))*(1-'My Numbers'!$C$29)-'My Numbers'!$C$27)+IF(('My Numbers'!$C$30="Yes"),(('My Numbers'!$C$20*(1+'My Numbers'!$C$94)*IF(('My Numbers'!$C$98="Yes"),1-'My Numbers'!$C$96,1)*IF(('My Numbers'!$C$100="Yes"),0,1))*'My Numbers'!$C$21*'My Numbers'!$C$22*'My Numbers'!$C$23)*'My Numbers'!$C$32*'My Numbers'!$C$31*IF(('My Numbers'!$C$99="Yes"),1-'My Numbers'!$C$97,1)*(1-'My Numbers'!$C$29),0)+IF(('My Numbers'!$C$33="Yes"),(IF(('My Numbers'!$C$33="Yes"),(('My Numbers'!$C$20*(1+'My Numbers'!$C$94)*IF(('My Numbers'!$C$98="Yes"),1-'My Numbers'!$C$96,1)*IF(('My Numbers'!$C$100="Yes"),0,1))*'My Numbers'!$C$21*'My Numbers'!$C$22*'My Numbers'!$C$23)*'My Numbers'!$C$36,0))*'My Numbers'!$C$37*('My Numbers'!$C$34*IF(('My Numbers'!$C$99="Yes"),1-'My Numbers'!$C$97,1)*(1-'My Numbers'!$C$29)-'My Numbers'!$C$35*'My Numbers'!$C$27),0)))*(IF('This Month'!$C$27="",1,IF((IF(('My Numbers'!$C$38="Yes"),((('My Numbers'!$C$20*(1+'My Numbers'!$C$94)*IF(('My Numbers'!$C$98="Yes"),1-'My Numbers'!$C$96,1)*IF(('My Numbers'!$C$100="Yes"),0,1))*'My Numbers'!$C$21*'My Numbers'!$C$22*'My Numbers'!$C$23)*MIN(1,'My Numbers'!$C$41*(1+'My Numbers'!$C$95)))*'My Numbers'!$C$40,(((('My Numbers'!$C$20*(1+'My Numbers'!$C$94)*IF(('My Numbers'!$C$98="Yes"),1-'My Numbers'!$C$96,1)*IF(('My Numbers'!$C$100="Yes"),0,1))*'My Numbers'!$C$21*'My Numbers'!$C$22*'My Numbers'!$C$23)-(IF(('My Numbers'!$C$33="Yes"),(('My Numbers'!$C$20*(1+'My Numbers'!$C$94)*IF(('My Numbers'!$C$98="Yes"),1-'My Numbers'!$C$96,1)*IF(('My Numbers'!$C$100="Yes"),0,1))*'My Numbers'!$C$21*'My Numbers'!$C$22*'My Numbers'!$C$23)*'My Numbers'!$C$36,0)))*(1+'My Numbers'!$C$24)+(IF(('My Numbers'!$C$33="Yes"),(('My Numbers'!$C$20*(1+'My Numbers'!$C$94)*IF(('My Numbers'!$C$98="Yes"),1-'My Numbers'!$C$96,1)*IF(('My Numbers'!$C$100="Yes"),0,1))*'My Numbers'!$C$21*'My Numbers'!$C$22*'My Numbers'!$C$23)*'My Numbers'!$C$36,0)))+((IF(('My Numbers'!$C$33="Yes"),(('My Numbers'!$C$20*(1+'My Numbers'!$C$94)*IF(('My Numbers'!$C$98="Yes"),1-'My Numbers'!$C$96,1)*IF(('My Numbers'!$C$100="Yes"),0,1))*'My Numbers'!$C$21*'My Numbers'!$C$22*'My Numbers'!$C$23)*'My Numbers'!$C$36,0))*'My Numbers'!$C$35*'My Numbers'!$C$37)))>'This Month'!$C$27,'This Month'!$C$27/(IF(('My Numbers'!$C$38="Yes"),((('My Numbers'!$C$20*(1+'My Numbers'!$C$94)*IF(('My Numbers'!$C$98="Yes"),1-'My Numbers'!$C$96,1)*IF(('My Numbers'!$C$100="Yes"),0,1))*'My Numbers'!$C$21*'My Numbers'!$C$22*'My Numbers'!$C$23)*MIN(1,'My Numbers'!$C$41*(1+'My Numbers'!$C$95)))*'My Numbers'!$C$40,(((('My Numbers'!$C$20*(1+'My Numbers'!$C$94)*IF(('My Numbers'!$C$98="Yes"),1-'My Numbers'!$C$96,1)*IF(('My Numbers'!$C$100="Yes"),0,1))*'My Numbers'!$C$21*'My Numbers'!$C$22*'My Numbers'!$C$23)-(IF(('My Numbers'!$C$33="Yes"),(('My Numbers'!$C$20*(1+'My Numbers'!$C$94)*IF(('My Numbers'!$C$98="Yes"),1-'My Numbers'!$C$96,1)*IF(('My Numbers'!$C$100="Yes"),0,1))*'My Numbers'!$C$21*'My Numbers'!$C$22*'My Numbers'!$C$23)*'My Numbers'!$C$36,0)))*(1+'My Numbers'!$C$24)+(IF(('My Numbers'!$C$33="Yes"),(('My Numbers'!$C$20*(1+'My Numbers'!$C$94)*IF(('My Numbers'!$C$98="Yes"),1-'My Numbers'!$C$96,1)*IF(('My Numbers'!$C$100="Yes"),0,1))*'My Numbers'!$C$21*'My Numbers'!$C$22*'My Numbers'!$C$23)*'My Numbers'!$C$36,0)))+((IF(('My Numbers'!$C$33="Yes"),(('My Numbers'!$C$20*(1+'My Numbers'!$C$94)*IF(('My Numbers'!$C$98="Yes"),1-'My Numbers'!$C$96,1)*IF(('My Numbers'!$C$100="Yes"),0,1))*'My Numbers'!$C$21*'My Numbers'!$C$22*'My Numbers'!$C$23)*'My Numbers'!$C$36,0))*'My Numbers'!$C$35*'My Numbers'!$C$37))),1))),0) -> 6204.15 | D5: =IF(('My Numbers'!$C$18="Yes"),IF(('My Numbers'!$C$38="Yes"),(((('My Numbers'!$C$20*1*IF(FALSE(),1-'My Numbers'!$C$96,1)*IF(FALSE(),0,1))*'My Numbers'!$C$21*'My Numbers'!$C$22*'My Numbers'!$C$23)*MIN(1,'My Numbers'!$C$41*1))*('My Numbers'!$C$39*IF(FALSE(),1-'My Numbers'!$C$97,1)*(1-'My Numbers'!$C$43)-'My Numbers'!$C$42)),((((('My Numbers'!$C$20*1*IF(FALSE(),1-'My Numbers'!$C$96,1)*IF(FALSE(),0,1))*'My Numbers'!$C$21*'My Numbers'!$C$22*'My Numbers'!$C$23)-(IF(('My Numbers'!$C$33="Yes"),(('My Numbers'!$C$20*1*IF(FALSE(),1-'My Numbers'!$C$96,1)*IF(FALSE(),0,1))*'My Numbers'!$C$21*'My Numbers'!$C$22*'My Numbers'!$C$23)*'My Numbers'!$C$36,0)))*(1+'My Numbers'!$C$24)+(IF(('My Numbers'!$C$33="Yes"),(('My Numbers'!$C$20*1*IF(FALSE(),1-'My Numbers'!$C$96,1)*IF(FALSE(),0,1))*'My Numbers'!$C$21*'My Numbers'!$C$22*'My Numbers'!$C$23)*'My Numbers'!$C$36,0)))*(('My Numbers'!$C$26*IF(FALSE(),1-'My Numbers'!$C$97,1))*(1-'My Numbers'!$C$29)-'My Numbers'!$C$27)+IF(('My Numbers'!$C$30="Yes"),(('My Numbers'!$C$20*1*IF(FALSE(),1-'My Numbers'!$C$96,1)*IF(FALSE(),0,1))*'My Numbers'!$C$21*'My Numbers'!$C$22*'My Numbers'!$C$23)*'My Numbers'!$C$32*'My Numbers'!$C$31*IF(FALSE(),1-'My Numbers'!$C$97,1)*(1-'My Numbers'!$C$29),0)+IF(('My Numbers'!$C$33="Yes"),(IF(('My Numbers'!$C$33="Yes"),(('My Numbers'!$C$20*1*IF(FALSE(),1-'My Numbers'!$C$96,1)*IF(FALSE(),0,1))*'My Numbers'!$C$21*'My Numbers'!$C$22*'My Numbers'!$C$23)*'My Numbers'!$C$36,0))*'My Numbers'!$C$37*('My Numbers'!$C$34*IF(FALSE(),1-'My Numbers'!$C$97,1)*(1-'My Numbers'!$C$29)-'My Numbers'!$C$35*'My Numbers'!$C$27),0)))*(IF('This Month'!$C$27="",1,IF((IF(('My Numbers'!$C$38="Yes"),((('My Numbers'!$C$20*1*IF(FALSE(),1-'My Numbers'!$C$96,1)*IF(FALSE(),0,1))*'My Numbers'!$C$21*'My Numbers'!$C$22*'My Numbers'!$C$23)*MIN(1,'My Numbers'!$C$41*1))*'My Numbers'!$C$40,(((('My Numbers'!$C$20*1*IF(FALSE(),1-'My Numbers'!$C$96,1)*IF(FALSE(),0,1))*'My Numbers'!$C$21*'My Numbers'!$C$22*'My Numbers'!$C$23)-(IF(('My Numbers'!$C$33="Yes"),(('My Numbers'!$C$20*1*IF(FALSE(),1-'My Numbers'!$C$96,1)*IF(FALSE(),0,1))*'My Numbers'!$C$21*'My Numbers'!$C$22*'My Numbers'!$C$23)*'My Numbers'!$C$36,0)))*(1+'My Numbers'!$C$24)+(IF(('My Numbers'!$C$33="Yes"),(('My Numbers'!$C$20*1*IF(FALSE(),1-'My Numbers'!$C$96,1)*IF(FALSE(),0,1))*'My Numbers'!$C$21*'My Numbers'!$C$22*'My Numbers'!$C$23)*'My Numbers'!$C$36,0)))+((IF(('My Numbers'!$C$33="Yes"),(('My Numbers'!$C$20*1*IF(FALSE(),1-'My Numbers'!$C$96,1)*IF(FALSE(),0,1))*'My Numbers'!$C$21*'My Numbers'!$C$22*'My Numbers'!$C$23)*'My Numbers'!$C$36,0))*'My Numbers'!$C$35*'My Numbers'!$C$37)))>'This Month'!$C$27,'This Month'!$C$27/(IF(('My Numbers'!$C$38="Yes"),((('My Numbers'!$C$20*1*IF(FALSE(),1-'My Numbers'!$C$96,1)*IF(FALSE(),0,1))*'My Numbers'!$C$21*'My Numbers'!$C$22*'My Numbers'!$C$23)*MIN(1,'My Numbers'!$C$41*1))*'My Numbers'!$C$40,(((('My Numbers'!$C$20*1*IF(FALSE(),1-'My Numbers'!$C$96,1)*IF(FALSE(),0,1))*'My Numbers'!$C$21*'My Numbers'!$C$22*'My Numbers'!$C$23)-(IF(('My Numbers'!$C$33="Yes"),(('My Numbers'!$C$20*1*IF(FALSE(),1-'My Numbers'!$C$96,1)*IF(FALSE(),0,1))*'My Numbers'!$C$21*'My Numbers'!$C$22*'My Numbers'!$C$23)*'My Numbers'!$C$36,0)))*(1+'My Numbers'!$C$24)+(IF(('My Numbers'!$C$33="Yes"),(('My Numbers'!$C$20*1*IF(FALSE(),1-'My Numbers'!$C$96,1)*IF(FALSE(),0,1))*'My Numbers'!$C$21*'My Numbers'!$C$22*'My Numbers'!$C$23)*'My Numbers'!$C$36,0)))+((IF(('My Numbers'!$C$33="Yes"),(('My Numbers'!$C$20*1*IF(FALSE(),1-'My Numbers'!$C$96,1)*IF(FALSE(),0,1))*'My Numbers'!$C$21*'My Numbers'!$C$22*'My Numbers'!$C$23)*'My Numbers'!$C$36,0))*'My Numbers'!$C$35*'My Numbers'!$C$37))),1))),0) -> 8815.2174 | E5: =IF(('My Numbers'!$C$18="Yes"),IF(('My Numbers'!$C$38="Yes"),(((('My Numbers'!$C$20*(1+'My Numbers'!$C$92)*IF(FALSE(),1-'My Numbers'!$C$96,1)*IF(FALSE(),0,1))*'My Numbers'!$C$21*'My Numbers'!$C$22*'My Numbers'!$C$23)*MIN(1,'My Numbers'!$C$41*(1+'My Numbers'!$C$93)))*('My Numbers'!$C$39*IF(FALSE(),1-'My Numbers'!$C$97,1)*(1-'My Numbers'!$C$43)-'My Numbers'!$C$42)),((((('My Numbers'!$C$20*(1+'My Numbers'!$C$92)*IF(FALSE(),1-'My Numbers'!$C$96,1)*IF(FALSE(),0,1))*'My Numbers'!$C$21*'My Numbers'!$C$22*'My Numbers'!$C$23)-(IF(('My Numbers'!$C$33="Yes"),(('My Numbers'!$C$20*(1+'My Numbers'!$C$92)*IF(FALSE(),1-'My Numbers'!$C$96,1)*IF(FALSE(),0,1))*'My Numbers'!$C$21*'My Numbers'!$C$22*'My Numbers'!$C$23)*'My Numbers'!$C$36,0)))*(1+'My Numbers'!$C$24)+(IF(('My Numbers'!$C$33="Yes"),(('My Numbers'!$C$20*(1+'My Numbers'!$C$92)*IF(FALSE(),1-'My Numbers'!$C$96,1)*IF(FALSE(),0,1))*'My Numbers'!$C$21*'My Numbers'!$C$22*'My Numbers'!$C$23)*'My Numbers'!$C$36,0)))*(('My Numbers'!$C$26*IF(FALSE(),1-'My Numbers'!$C$97,1))*(1-'My Numbers'!$C$29)-'My Numbers'!$C$27)+IF(('My Numbers'!$C$30="Yes"),(('My Numbers'!$C$20*(1+'My Numbers'!$C$92)*IF(FALSE(),1-'My Numbers'!$C$96,1)*IF(FALSE(),0,1))*'My Numbers'!$C$21*'My Numbers'!$C$22*'My Numbers'!$C$23)*'My Numbers'!$C$32*'My Numbers'!$C$31*IF(FALSE(),1-'My Numbers'!$C$97,1)*(1-'My Numbers'!$C$29),0)+IF(('My Numbers'!$C$33="Yes"),(IF(('My Numbers'!$C$33="Yes"),(('My Numbers'!$C$20*(1+'My Numbers'!$C$92)*IF(FALSE(),1-'My Numbers'!$C$96,1)*IF(FALSE(),0,1))*'My Numbers'!$C$21*'My Numbers'!$C$22*'My Numbers'!$C$23)*'My Numbers'!$C$36,0))*'My Numbers'!$C$37*('My Numbers'!$C$34*IF(FALSE(),1-'My Numbers'!$C$97,1)*(1-'My Numbers'!$C$29)-'My Numbers'!$C$35*'My Numbers'!$C$27),0)))*(IF('This Month'!$C$27="",1,IF((IF(('My Numbers'!$C$38="Yes"),((('My Numbers'!$C$20*(1+'My Numbers'!$C$92)*IF(FALSE(),1-'My Numbers'!$C$96,1)*IF(FALSE(),0,1))*'My Numbers'!$C$21*'My Numbers'!$C$22*'My Numbers'!$C$23)*MIN(1,'My Numbers'!$C$41*(1+'My Numbers'!$C$93)))*'My Numbers'!$C$40,(((('My Numbers'!$C$20*(1+'My Numbers'!$C$92)*IF(FALSE(),1-'My Numbers'!$C$96,1)*IF(FALSE(),0,1))*'My Numbers'!$C$21*'My Numbers'!$C$22*'My Numbers'!$C$23)-(IF(('My Numbers'!$C$33="Yes"),(('My Numbers'!$C$20*(1+'My Numbers'!$C$92)*IF(FALSE(),1-'My Numbers'!$C$96,1)*IF(FALSE(),0,1))*'My Numbers'!$C$21*'My Numbers'!$C$22*'My Numbers'!$C$23)*'My Numbers'!$C$36,0)))*(1+'My Numbers'!$C$24)+(IF(('My Numbers'!$C$33="Yes"),(('My Numbers'!$C$20*(1+'My Numbers'!$C$92)*IF(FALSE(),1-'My Numbers'!$C$96,1)*IF(FALSE(),0,1))*'My Numbers'!$C$21*'My Numbers'!$C$22*'My Numbers'!$C$23)*'My Numbers'!$C$36,0)))+((IF(('My Numbers'!$C$33="Yes"),(('My Numbers'!$C$20*(1+'My Numbers'!$C$92)*IF(FALSE(),1-'My Numbers'!$C$96,1)*IF(FALSE(),0,1))*'My Numbers'!$C$21*'My Numbers'!$C$22*'My Numbers'!$C$23)*'My Numbers'!$C$36,0))*'My Numbers'!$C$35*'My Numbers'!$C$37)))>'This Month'!$C$27,'This Month'!$C$27/(IF(('My Numbers'!$C$38="Yes"),((('My Numbers'!$C$20*(1+'My Numbers'!$C$92)*IF(FALSE(),1-'My Numbers'!$C$96,1)*IF(FALSE(),0,1))*'My Numbers'!$C$21*'My Numbers'!$C$22*'My Numbers'!$C$23)*MIN(1,'My Numbers'!$C$41*(1+'My Numbers'!$C$93)))*'My Numbers'!$C$40,(((('My Numbers'!$C$20*(1+'My Numbers'!$C$92)*IF(FALSE(),1-'My Numbers'!$C$96,1)*IF(FALSE(),0,1))*'My Numbers'!$C$21*'My Numbers'!$C$22*'My Numbers'!$C$23)-(IF(('My Numbers'!$C$33="Yes"),(('My Numbers'!$C$20*(1+'My Numbers'!$C$92)*IF(FALSE(),1-'My Numbers'!$C$96,1)*IF(FALSE(),0,1))*'My Numbers'!$C$21*'My Numbers'!$C$22*'My Numbers'!$C$23)*'My Numbers'!$C$36,0)))*(1+'My Numbers'!$C$24)+(IF(('My Numbers'!$C$33="Yes"),(('My Numbers'!$C$20*(1+'My Numbers'!$C$92)*IF(FALSE(),1-'My Numbers'!$C$96,1)*IF(FALSE(),0,1))*'My Numbers'!$C$21*'My Numbers'!$C$22*'My Numbers'!$C$23)*'My Numbers'!$C$36,0)))+((IF(('My Numbers'!$C$33="Yes"),(('My Numbers'!$C$20*(1+'My Numbers'!$C$92)*IF(FALSE(),1-'My Numbers'!$C$96,1)*IF(FALSE(),0,1))*'My Numbers'!$C$21*'My Numbers'!$C$22*'My Numbers'!$C$23)*'My Numbers'!$C$36,0))*'My Numbers'!$C$35*'My Numbers'!$C$37))),1))),0) -> 8815.2174
B6: Content | C6: =IF(('My Numbers'!$C$48="Yes"),('My Numbers'!$C$52*(1+'My Numbers'!$C$94)*'My Numbers'!$C$54*IF(('My Numbers'!$C$99="Yes"),1-'My Numbers'!$C$97,1)*(1-'My Numbers'!$C$55)+IF(('My Numbers'!$C$100="Yes"),0,'My Numbers'!$C$56*(1+'My Numbers'!$C$94)*'My Numbers'!$C$57*IF(('My Numbers'!$C$99="Yes"),1-'My Numbers'!$C$97,1)*(1-'My Numbers'!$C$58)+'My Numbers'!$C$60*(1+'My Numbers'!$C$94)*'My Numbers'!$C$62*IF(('My Numbers'!$C$99="Yes"),1-'My Numbers'!$C$97,1)))*IFERROR(INDEX('This Month'!$F$58:$F$61,MATCH("Content",'This Month'!$C$58:$C$61,0)),1),0) -> 1560 | D6: =IF(('My Numbers'!$C$48="Yes"),('My Numbers'!$C$52*1*'My Numbers'!$C$54*IF(FALSE(),1-'My Numbers'!$C$97,1)*(1-'My Numbers'!$C$55)+IF(FALSE(),0,'My Numbers'!$C$56*1*'My Numbers'!$C$57*IF(FALSE(),1-'My Numbers'!$C$97,1)*(1-'My Numbers'!$C$58)+'My Numbers'!$C$60*1*'My Numbers'!$C$62*IF(FALSE(),1-'My Numbers'!$C$97,1)))*IFERROR(INDEX('This Month'!$F$58:$F$61,MATCH("Content",'This Month'!$C$58:$C$61,0)),1),0) -> 2600 | E6: =IF(('My Numbers'!$C$48="Yes"),('My Numbers'!$C$52*(1+'My Numbers'!$C$92)*'My Numbers'!$C$54*IF(FALSE(),1-'My Numbers'!$C$97,1)*(1-'My Numbers'!$C$55)+IF(FALSE(),0,'My Numbers'!$C$56*(1+'My Numbers'!$C$92)*'My Numbers'!$C$57*IF(FALSE(),1-'My Numbers'!$C$97,1)*(1-'My Numbers'!$C$58)+'My Numbers'!$C$60*(1+'My Numbers'!$C$92)*'My Numbers'!$C$62*IF(FALSE(),1-'My Numbers'!$C$97,1)))*IFERROR(INDEX('This Month'!$F$58:$F$61,MATCH("Content",'This Month'!$C$58:$C$61,0)),1),0) -> 3380
B7: Calls | C7: =IF(('My Numbers'!$C$67="Yes"),IF(('My Numbers'!$C$100="Yes"),0,'My Numbers'!$C$69*(1+'My Numbers'!$C$94)*(1-'My Numbers'!$C$70*IF(('My Numbers'!$C$71="Yes"),0,1))*'My Numbers'!$C$72*IF(('My Numbers'!$C$99="Yes"),1-'My Numbers'!$C$97,1)*(1-'My Numbers'!$C$73))*IFERROR(INDEX('This Month'!$F$58:$F$61,MATCH("Calls",'This Month'!$C$58:$C$61,0)),1),0) -> 864 | D7: =IF(('My Numbers'!$C$67="Yes"),IF(FALSE(),0,'My Numbers'!$C$69*1*(1-'My Numbers'!$C$70*IF(('My Numbers'!$C$71="Yes"),0,1))*'My Numbers'!$C$72*IF(FALSE(),1-'My Numbers'!$C$97,1)*(1-'My Numbers'!$C$73))*IFERROR(INDEX('This Month'!$F$58:$F$61,MATCH("Calls",'This Month'!$C$58:$C$61,0)),1),0) -> 1440 | E7: =IF(('My Numbers'!$C$67="Yes"),IF(FALSE(),0,'My Numbers'!$C$69*(1+'My Numbers'!$C$92)*(1-'My Numbers'!$C$70*IF(('My Numbers'!$C$71="Yes"),0,1))*'My Numbers'!$C$72*IF(FALSE(),1-'My Numbers'!$C$97,1)*(1-'My Numbers'!$C$73))*IFERROR(INDEX('This Month'!$F$58:$F$61,MATCH("Calls",'This Month'!$C$58:$C$61,0)),1),0) -> 1872
B8: Regulars | C8: =IF(('My Numbers'!$C$78="Yes"),('My Numbers'!$C$80*(1+'My Numbers'!$C$94)*'My Numbers'!$C$81*IF(('My Numbers'!$C$99="Yes"),1-'My Numbers'!$C$97,1)*(1-'My Numbers'!$C$84)*(1-'My Numbers'!$C$82)+IF(('My Numbers'!$C$100="Yes"),0,'My Numbers'!$C$85*(1+'My Numbers'!$C$94)*MIN(1,'My Numbers'!$C$86*(1+'My Numbers'!$C$95))*'My Numbers'!$C$87*IF(('My Numbers'!$C$99="Yes"),1-'My Numbers'!$C$97,1)*(1-'My Numbers'!$C$84)*(1-'My Numbers'!$C$82)))*IFERROR(INDEX('This Month'!$F$58:$F$61,MATCH("Regulars",'This Month'!$C$58:$C$61,0)),1),0) -> 1080 | D8: =IF(('My Numbers'!$C$78="Yes"),('My Numbers'!$C$80*1*'My Numbers'!$C$81*IF(FALSE(),1-'My Numbers'!$C$97,1)*(1-'My Numbers'!$C$84)*(1-'My Numbers'!$C$82)+IF(FALSE(),0,'My Numbers'!$C$85*1*MIN(1,'My Numbers'!$C$86*1)*'My Numbers'!$C$87*IF(FALSE(),1-'My Numbers'!$C$97,1)*(1-'My Numbers'!$C$84)*(1-'My Numbers'!$C$82)))*IFERROR(INDEX('This Month'!$F$58:$F$61,MATCH("Regulars",'This Month'!$C$58:$C$61,0)),1),0) -> 1800 | E8: =IF(('My Numbers'!$C$78="Yes"),('My Numbers'!$C$80*(1+'My Numbers'!$C$92)*'My Numbers'!$C$81*IF(FALSE(),1-'My Numbers'!$C$97,1)*(1-'My Numbers'!$C$84)*(1-'My Numbers'!$C$82)+IF(FALSE(),0,'My Numbers'!$C$85*(1+'My Numbers'!$C$92)*MIN(1,'My Numbers'!$C$86*(1+'My Numbers'!$C$93))*'My Numbers'!$C$87*IF(FALSE(),1-'My Numbers'!$C$97,1)*(1-'My Numbers'!$C$84)*(1-'My Numbers'!$C$82)))*IFERROR(INDEX('This Month'!$F$58:$F$61,MATCH("Regulars",'This Month'!$C$58:$C$61,0)),1),0) -> 2340
B9: Gross profit | C9: =SUM(C5:C8) -> 9708.15 | D9: =SUM(D5:D8) -> 14655.217 | E9: =SUM(E5:E8) -> 16407.217
B10: Fixed costs and finding clients | C10: =-'My Numbers'!$C$8-'My Numbers'!$C$13 -> -1500 | D10: =-'My Numbers'!$C$8-'My Numbers'!$C$13 -> -1500 | E10: =-'My Numbers'!$C$8-'My Numbers'!$C$13 -> -1500
B11: Profit | C11: =C9+C10 -> 8208.15 | D11: =D9+D10 -> 13155.217 | E11: =E9+E10 -> 14907.217
B12: Gap to your goal (negative = short) | C12: =C11-'My Numbers'!$C$9 -> -1791.85 | D12: =D11-'My Numbers'!$C$9 -> 3155.2174 | E12: =E11-'My Numbers'!$C$9 -> 4907.2174
B13: Runway: months your cash covers the gap | C13: =IF('My Numbers'!$C$11="","not yet",IF(C12>=0,"not needed",'My Numbers'!$C$11/(-C12))) -> 5.0227419 | D13: =IF('My Numbers'!$C$11="","not yet",IF(D12>=0,"not needed",'My Numbers'!$C$11/(-D12))) -> not needed | E13: =IF('My Numbers'!$C$11="","not yet",IF(E12>=0,"not needed",'My Numbers'!$C$11/(-E12))) -> not needed
B15: Disaster switches live on My Numbers: the source stops, a price war, a month off sick. Dream adds nothing on top of its multipliers; add your own upside in the pink cells.

Sheet Plan
A1: Plan
A2: What your goal needs, what your offer is worth per hour of you, and what a client is worth over time against what one costs to find.
A4: What the goal needs (in person)
B5: Gross profit needed = goal + fixed costs + finding clients | C5: ='My Numbers'!$C$9+'My Numbers'!$C$8+'My Numbers'!$C$13 -> 11500
B6: Gross profit one contact brings (before any cap) | C6: ='This Month'!$C$37 -> 172.3375
B7: Contacts a month the goal needs | C7: =IF(OR(C6="",C6<=0),"not yet",ROUNDUP(C5/C6,0)) -> 67
B8: You have | C8: ='My Numbers'!$C$20 -> 60
B9: Sessions that would mean | C9: =IF(C7="not yet","not yet",C7*'This Month'!$C$38) -> 23.5773
B10: Within your capacity? | C10: =IF(C9="not yet","not yet",IF('This Month'!$C$27="","No cap set",IF(C9<='This Month'!$C$27,"Yes","No: at these prices the goal needs more than you can deliver. Raise price or add an offer before chasing volume."))) -> No: at these prices the goal needs more than you can deliver. Raise price or add an offer before chasing volume.
A12: Your offer, per hour of you
B13: Gross profit per session = price × (1 − cut) − delivery | C13: ='This Month'!$C$30 -> 375
B14: Per all-in hour = (price − delivery) ÷ all-in hours | C14: =IF('My Numbers'!$C$28>0,('My Numbers'!$C$26-'My Numbers'!$C$27)/'My Numbers'!$C$28,"not yet") -> 100
B15: Program: gross profit per client | C15: ='My Numbers'!$C$39*(1-'My Numbers'!$C$43)-'My Numbers'!$C$42 -> 2450
B16: Program: clients a month for the goal, and hours | C16: =IF(C15>0,'My Numbers'!$C$9/C15,"not yet") -> 4.0816327 | D16: =IF(C15>0,TEXT('My Numbers'!$C$9/C15*'My Numbers'!$C$44,"0.0")&" hours a month","") -> 57.1 hours a month
A18: The value stack: what a client gets, in dollars, next to the price
B19: Piece | C19: Worth to them | D19: Leave a piece empty if it does not apply
B20: The core result: what the time itself is worth to them | C20: 800
B21: Preparation done for them before they arrive | C21: 200
B22: Aftercare and follow-up | C22: 150
B23: Priority access or a guaranteed date | C23: 300
B24: Something only you do | C24: 400
B25: A bonus that costs you little and means a lot | C25: 100
B26: The stack adds up to | C26: =SUM(C20:C25) -> 1950
B27: Stack ÷ price (3x or more makes the price feel small) | C27: =IF('My Numbers'!$C$26>0,C26/'My Numbers'!$C$26,"") -> 3.9
B28: Price the stack supports at 3x | C28: =C26/3 -> 650
B29: Value equation and value stack after Alex Hormozi ($100M Offers). SLAM is independent; no book text is reproduced.
A31: What a client is worth, against what one costs to find
B32: Worth over their time = gross profit per session × (1 + rebook) | C32: ='This Month'!$C$30*(1+'My Numbers'!$C$24) -> 487.5
B33: Cost to find one = (spend + hours × your hourly value) ÷ new clients | C33: =IF('This Month'!$C$16>0,('My Numbers'!$C$13+'My Numbers'!$C$14*'My Numbers'!$C$12)/'This Month'!$C$16,"not yet") -> 0
B34: Worth : cost (aim for 3 : 1 or better) | C34: =IF(OR(C33="not yet",C33<=0),"no cost yet",C32/C33) -> no cost yet
B35: Days to pay back = cost ÷ (gross profit per session ÷ 30) | C35: =IF(OR(C33="not yet",'This Month'!$C$30<=0),"not yet",C33/('This Month'!$C$30/30)) -> 0
B36: Worth-to-cost after Alex Hormozi ($100M Leads). SLAM is independent.

Sheet Check-in
A1: Check-in
A2: One row a week, one minute. Type the Monday date and what happened. After four rows the sheet compares your real weeks to the model.
B4: Week of | C4: Contacts | D4: Bookings | E4: Sessions or calls held | F4: Reach actions (posts, messages) | G4: Energy 1-5 | H4: Note (keep it plain)
B5: 46272 | C5: 12 | D5: 3 | E5: 2 | F5: 20 | G5: 4 | H5: example row: replace with your own week
B6: 46279 | C6: 15 | D6: 4 | E6: 3 | F6: 24 | G6: 3
B7: 46286 | C7: 11 | D7: 2 | E7: 3 | F7: 18 | G7: 4
A32: Your last four weeks against the model
B33: Contacts a week, average of the last four | C33: =IFERROR(AVERAGE(INDEX(C5:C30,MAX(1,COUNT(C5:C30)-3)):INDEX(C5:C30,COUNT(C5:C30))),"") -> 12.666667
B34: That is, a month | C34: =IF(C33="","",C33*52/12) -> 54.888889
B35: The model assumes | C35: ='My Numbers'!$C$20 -> 60
B36: Gap | C36: =IF(C34="","log four weeks first",IF('My Numbers'!$C$20>0,TEXT((C34-'My Numbers'!$C$20)/'My Numbers'!$C$20,"+0%;-0%")&IF(ABS((C34-'My Numbers'!$C$20)/'My Numbers'!$C$20)>0.1,": consider typing "&TEXT(C34,"0")&" as your contacts on My Numbers",": close enough"),"")) -> -9%: close enough
B37: Bookings a week, last four | C37: =IFERROR(AVERAGE(INDEX(D5:D30,MAX(1,COUNT(D5:D30)-3)):INDEX(D5:D30,COUNT(D5:D30))),"") -> 3
B38: Reach actions a week, last four | C38: =IFERROR(AVERAGE(INDEX(F5:F30,MAX(1,COUNT(F5:F30)-3)):INDEX(F5:F30,COUNT(F5:F30))),"") -> 20.666667
B39: Contacts per reach action | C39: =IF(OR(C33="",C38="",C38=0),"",C33/C38) -> 0.61290323
B40: Check-ins saved | C40: =COUNT(C5:C30) -> 3
B41: Momentum shows after four check-ins of real numbers. Volume is what moves contacts; consistency beats bursts.

Sheet Clients
A1: Clients
A2: Aliases only. Never names, documents, photos or addresses. Screening keeps a result, never a reason. Regulars carry an agreed monthly budget; the sheet flags anyone past it.
B4: Alias | C4: Business | D4: Stage | E4: Screening result | F4: Deposit | G4: Agreed budget a month | H4: Sent this month | I4: Next action
B5: Blue | C5: In person | D5: Client | E5: Passed | F5: Paid | I5: example row: replace with your own
B6: Fern | C6: Regulars | D6: Regular | E6: Passed | F6: None | G6: 500 | H6: 620 | I6: past their budget: time for a check-in
A46: Where everyone is
B47: Contacted | C47: =COUNTIF(D5:D44,"Contacted") -> 0
B48: Screening | C48: =COUNTIF(D5:D44,"Screening") -> 0
B49: Booked | C49: =COUNTIF(D5:D44,"Booked") -> 0
B50: Showed | C50: =COUNTIF(D5:D44,"Showed") -> 0
B51: Client | C51: =COUNTIF(D5:D44,"Client") -> 1
B52: Regular | C52: =COUNTIF(D5:D44,"Regular") -> 1
B53: Lost | C53: =COUNTIF(D5:D44,"Lost") -> 0
A55: From your log (last 40 rows)
B56: Contacts logged | C56: =COUNTA(B5:B44) -> 2
B57: Passed screening | C57: =COUNTIF(E5:E44,"Passed") -> 2
B58: Booked or further | C58: =COUNTIF(D5:D44,"Booked")+COUNTIF(D5:D44,"Showed")+COUNTIF(D5:D44,"Client")+COUNTIF(D5:D44,"Regular") -> 2
B59: Pass rate from your log | C59: =IF(C56>0,C57/C56,"") -> 1
B60: Booking rate from your log | C60: =IF(C57>0,C58/C57,"") -> 1
B61: After ten contacts these can replace the estimates on My Numbers. Copy them across when they look right.

Sheet Definitions
A1: Definitions
A2: Every word and every formula in this workbook, in plain English.
B4: Contacts | C4: Every new person who reached out in a month, counted once.
B5: Pass rate | C5: The share of contacts who pass your screening. Never a sales lever.
B6: Booking rate | C6: The share of screened people who book.
B7: Show rate | C7: The share of bookings who turn up.
B8: Rebook rate | C8: Extra sessions each new client brings over time. 30% = every 10 new clients bring 3 more sessions.
B9: Take rate | C9: The share of new clients who add an offer on.
B10: Gross profit | C10: Price × (1 − cut) − what it cost to deliver, added up.
B11: Fixed costs | C11: Money that leaves every month whether you work or not.
B12: Profit | C12: Gross profit − money spent finding clients − fixed costs.
B13: All-in hours | C13: Everything one sale really costs in time: prep, travel, the thing itself, recovery, messages.
B14: Capacity | C14: The most sessions a month allows: your session ceiling or your hours ÷ all-in hours, whichever is tighter.
B15: Runway | C15: Months your cash covers the gap between profit and your goal.
... B31: Credit | C31: The value equation, value stack, volume and worth-to-cost follow ideas published by Alex Hormozi. SLAM is independent and not affiliated; no book text is reproduced.
