Workbook

Sheet Start Here
A1: The Leads Ladder: $100M Leads by Alex Hormozi, as a workbook
A2: The book restated as exercises. The lead magnet is the sun and everything orbits it; warm outreach, free content, cold outreach and paid ads are the core four; referrals, employees, agencies and affiliates are the lead getters. Every planet has the same five bands: Learn, Sketch, Do, Measure, Scale.
A3: How to use this sheet: type only in the yellow cells (blue text). Everything in black is worked out for you. A blank yellow cell means "not yet", not zero. Choose Y in a checklist cell to tick it.
A5: Start here: seven answers | B5: Your answer | D5: Why it is asked
A6: These answers are the example (an invented piano teacher). Replace them with yours.
A7: What you sell, in one line | B7: Piano lessons for adults who gave up as kids | D7: for example: Piano lessons for adults who gave up as kids
A8: Who it is for, in one line | B8: Busy adults in their 30s and 40s | D8: for example: Busy adults in their 30s and 40s who want to play again
A9: Paying customers today | B9: One to ten | D9: for example:
A10: Money you could spend on ads each month | B10: Some; and I could afford to lose it while I learn | D10: for example:
A11: Who does the work | B11: Just me | D11: for example:
A12: Engaged leads you want each week | B12: 20 | D12: An engaged lead is someone who gave you a way to reach them and showed interest. The book's whole point is that this is the number to chase.
A13: The one core four planet you will start with | B13: Warm outreach: I know people | D13: The book's order for a one-person business is warm outreach first, then content, then cold, then paid.
A14: The rule of 100: a hundred primary actions a day on your first planet. A hundred warm messages. A hundred minutes making content. A hundred cold reach-outs. A hundred dollars of ads. Every day, until the goal is hit.
A16: Where you stand | B16: Sheet | D16: Applies? | E16: Learn | F16: Sketch | G16: Do | H16: Measure | I16: Scale
A17: The Lead Magnet (the sun) | B17: Magnet | D17: =IF(TRUE(),"yes","not yet") -> yes | E17: =COUNTIFS(Magnet!$E$1:$E$600,1,Magnet!$H$1:$H$600,"Done")&" of "&COUNTIF(Magnet!$E$1:$E$600,1) -> 0 of 2 | F17: =COUNTIFS(Magnet!$E$1:$E$600,2,Magnet!$H$1:$H$600,"Done")&" of "&COUNTIF(Magnet!$E$1:$E$600,2) -> 0 of 2 | G17: =COUNTIFS(Magnet!$E$1:$E$600,3,Magnet!$H$1:$H$600,"Done")&" of "&COUNTIF(Magnet!$E$1:$E$600,3) -> 0 of 3 | H17: =COUNTIFS(Magnet!$E$1:$E$600,4,Magnet!$H$1:$H$600,"Done")&" of "&COUNTIF(Magnet!$E$1:$E$600,4) -> 0 of 1 | I17: =COUNTIFS(Magnet!$E$1:$E$600,5,Magnet!$H$1:$H$600,"Done")&" of "&COUNTIF(Magnet!$E$1:$E$600,5) -> 0 of 1
A18: Warm Outreach | B18: Warm | D18: =IF(TRUE(),"yes","not yet") -> yes | E18: =COUNTIFS(Warm!$E$1:$E$600,1,Warm!$H$1:$H$600,"Done")&" of "&COUNTIF(Warm!$E$1:$E$600,1) -> 0 of 2 | F18: =COUNTIFS(Warm!$E$1:$E$600,2,Warm!$H$1:$H$600,"Done")&" of "&COUNTIF(Warm!$E$1:$E$600,2) -> 0 of 3 | G18: =COUNTIFS(Warm!$E$1:$E$600,3,Warm!$H$1:$H$600,"Done")&" of "&COUNTIF(Warm!$E$1:$E$600,3) -> 0 of 3 | H18: =COUNTIFS(Warm!$E$1:$E$600,4,Warm!$H$1:$H$600,"Done")&" of "&COUNTIF(Warm!$E$1:$E$600,4) -> 0 of 1 | I18: =COUNTIFS(Warm!$E$1:$E$600,5,Warm!$H$1:$H$600,"Done")&" of "&COUNTIF(Warm!$E$1:$E$600,5) -> 0 of 1
A19: Free Content | B19: Content | D19: =IF(TRUE(),"yes","not yet") -> yes | E19: =COUNTIFS(Content!$E$1:$E$600,1,Content!$H$1:$H$600,"Done")&" of "&COUNTIF(Content!$E$1:$E$600,1) -> 0 of 2 | F19: =COUNTIFS(Content!$E$1:$E$600,2,Content!$H$1:$H$600,"Done")&" of "&COUNTIF(Content!$E$1:$E$600,2) -> 0 of 3 | G19: =COUNTIFS(Content!$E$1:$E$600,3,Content!$H$1:$H$600,"Done")&" of "&COUNTIF(Content!$E$1:$E$600,3) -> 0 of 2 | H19: =COUNTIFS(Content!$E$1:$E$600,4,Content!$H$1:$H$600,"Done")&" of "&COUNTIF(Content!$E$1:$E$600,4) -> 0 of 1 | I19: =COUNTIFS(Content!$E$1:$E$600,5,Content!$H$1:$H$600,"Done")&" of "&COUNTIF(Content!$E$1:$E$600,5) -> 0 of 1
A20: Cold Outreach | B20: Cold | D20: =IF(TRUE(),"yes","not yet") -> yes | E20: =COUNTIFS(Cold!$E$1:$E$600,1,Cold!$H$1:$H$600,"Done")&" of "&COUNTIF(Cold!$E$1:$E$600,1) -> 0 of 1 | F20: =COUNTIFS(Cold!$E$1:$E$600,2,Cold!$H$1:$H$600,"Done")&" of "&COUNTIF(Cold!$E$1:$E$600,2) -> 0 of 3 | G20: =COUNTIFS(Cold!$E$1:$E$600,3,Cold!$H$1:$H$600,"Done")&" of "&COUNTIF(Cold!$E$1:$E$600,3) -> 0 of 2 | H20: =COUNTIFS(Cold!$E$1:$E$600,4,Cold!$H$1:$H$600,"Done")&" of "&COUNTIF(Cold!$E$1:$E$600,4) -> 0 of 1 | I20: =COUNTIFS(Cold!$E$1:$E$600,5,Cold!$H$1:$H$600,"Done")&" of "&COUNTIF(Cold!$E$1:$E$600,5) -> 0 of 1
A21: Paid Ads | B21: Ads | D21: =IF($B$10="Some; and I could afford to lose it while I learn","yes","not yet") -> yes | E21: =COUNTIFS(Ads!$E$1:$E$600,1,Ads!$H$1:$H$600,"Done")&" of "&COUNTIF(Ads!$E$1:$E$600,1) -> 0 of 2 | F21: =COUNTIFS(Ads!$E$1:$E$600,2,Ads!$H$1:$H$600,"Done")&" of "&COUNTIF(Ads!$E$1:$E$600,2) -> 0 of 2 | G21: =COUNTIFS(Ads!$E$1:$E$600,3,Ads!$H$1:$H$600,"Done")&" of "&COUNTIF(Ads!$E$1:$E$600,3) -> 0 of 2 | H21: =COUNTIFS(Ads!$E$1:$E$600,4,Ads!$H$1:$H$600,"Done")&" of "&COUNTIF(Ads!$E$1:$E$600,4) -> 2 of 2 | I21: =COUNTIFS(Ads!$E$1:$E$600,5,Ads!$H$1:$H$600,"Done")&" of "&COUNTIF(Ads!$E$1:$E$600,5) -> 0 of 1
A22: Referrals | B22: Referrals | D22: =IF(OR($B$9="One to ten",$B$9="More than ten"),"yes","not yet") -> yes | E22: =COUNTIFS(Referrals!$E$1:$E$600,1,Referrals!$H$1:$H$600,"Done")&" of "&COUNTIF(Referrals!$E$1:$E$600,1) -> 0 of 1 | F22: =COUNTIFS(Referrals!$E$1:$E$600,2,Referrals!$H$1:$H$600,"Done")&" of "&COUNTIF(Referrals!$E$1:$E$600,2) -> 0 of 2 | G22: =COUNTIFS(Referrals!$E$1:$E$600,3,Referrals!$H$1:$H$600,"Done")&" of "&COUNTIF(Referrals!$E$1:$E$600,3) -> 0 of 1 | H22: =COUNTIFS(Referrals!$E$1:$E$600,4,Referrals!$H$1:$H$600,"Done")&" of "&COUNTIF(Referrals!$E$1:$E$600,4) -> 1 of 1 | I22: =COUNTIFS(Referrals!$E$1:$E$600,5,Referrals!$H$1:$H$600,"Done")&" of "&COUNTIF(Referrals!$E$1:$E$600,5) -> 0 of 1
A23: Employees | B23: Employees | D23: =IF(OR($B$11="A team",$B$11="Me; and I am hiring"),"yes","not yet") -> not yet | E23: =COUNTIFS(Employees!$E$1:$E$600,1,Employees!$H$1:$H$600,"Done")&" of "&COUNTIF(Employees!$E$1:$E$600,1) -> 0 of 1 | F23: =COUNTIFS(Employees!$E$1:$E$600,2,Employees!$H$1:$H$600,"Done")&" of "&COUNTIF(Employees!$E$1:$E$600,2) -> 0 of 1 | G23: =COUNTIFS(Employees!$E$1:$E$600,3,Employees!$H$1:$H$600,"Done")&" of "&COUNTIF(Employees!$E$1:$E$600,3) -> 0 of 1 | H23: =COUNTIFS(Employees!$E$1:$E$600,4,Employees!$H$1:$H$600,"Done")&" of "&COUNTIF(Employees!$E$1:$E$600,4) -> 0 of 1 | I23: =COUNTIFS(Employees!$E$1:$E$600,5,Employees!$H$1:$H$600,"Done")&" of "&COUNTIF(Employees!$E$1:$E$600,5) -> 0 of 1
A24: Agencies | B24: Agencies | D24: =IF($B$10="Some; and I could afford to lose it while I learn","yes","not yet") -> yes | E24: =COUNTIFS(Agencies!$E$1:$E$600,1,Agencies!$H$1:$H$600,"Done")&" of "&COUNTIF(Agencies!$E$1:$E$600,1) -> 0 of 1 | F24: =COUNTIFS(Agencies!$E$1:$E$600,2,Agencies!$H$1:$H$600,"Done")&" of "&COUNTIF(Agencies!$E$1:$E$600,2) -> 0 of 1 | G24: =COUNTIFS(Agencies!$E$1:$E$600,3,Agencies!$H$1:$H$600,"Done")&" of "&COUNTIF(Agencies!$E$1:$E$600,3) -> 0 of 1 | H24: =COUNTIFS(Agencies!$E$1:$E$600,4,Agencies!$H$1:$H$600,"Done")&" of "&COUNTIF(Agencies!$E$1:$E$600,4) -> 0 of 1 | I24: =COUNTIFS(Agencies!$E$1:$E$600,5,Agencies!$H$1:$H$600,"Done")&" of "&COUNTIF(Agencies!$E$1:$E$600,5) -> 0 of 1
A25: Affiliates | B25: Affiliates | D25: =IF(OR($B$9="One to ten",$B$9="More than ten"),"yes","not yet") -> yes | E25: =COUNTIFS(Affiliates!$E$1:$E$600,1,Affiliates!$H$1:$H$600,"Done")&" of "&COUNTIF(Affiliates!$E$1:$E$600,1) -> 0 of 1 | F25: =COUNTIFS(Affiliates!$E$1:$E$600,2,Affiliates!$H$1:$H$600,"Done")&" of "&COUNTIF(Affiliates!$E$1:$E$600,2) -> 0 of 2 | G25: =COUNTIFS(Affiliates!$E$1:$E$600,3,Affiliates!$H$1:$H$600,"Done")&" of "&COUNTIF(Affiliates!$E$1:$E$600,3) -> 0 of 1 | H25: =COUNTIFS(Affiliates!$E$1:$E$600,4,Affiliates!$H$1:$H$600,"Done")&" of "&COUNTIF(Affiliates!$E$1:$E$600,4) -> 0 of 1 | I25: =COUNTIFS(Affiliates!$E$1:$E$600,5,Affiliates!$H$1:$H$600,"Done")&" of "&COUNTIF(Affiliates!$E$1:$E$600,5) -> 0 of 1
A26: Ring cleared? (every planet that applies has finished the band) | E26: =IF(SUM((TRUE())*(COUNTIFS(Magnet!$E$1:$E$600,1,Magnet!$H$1:$H$600,"Done")<COUNTIF(Magnet!$E$1:$E$600,1)),(TRUE())*(COUNTIFS(Warm!$E$1:$E$600,1,Warm!$H$1:$H$600,"Done")<COUNTIF(Warm!$E$1:$E$600,1)),(TRUE())*(COUNTIFS(Content!$E$1:$E$600,1,Content!$H$1:$H$600,"Done")<COUNTIF(Content!$E$1:$E$600,1)),(TRUE())*(COUNTIFS(Cold!$E$1:$E$600,1,Cold!$H$1:$H$600,"Done")<COUNTIF(Cold!$E$1:$E$600,1)),($B$10="Some; and I could afford to lose it while I learn")*(COUNTIFS(Ads!$E$1:$E$600,1,Ads!$H$1:$H$600,"Done")<COUNTIF(Ads!$E$1:$E$600,1)),(OR($B$9="One to ten",$B$9="More than ten"))*(COUNTIFS(Referrals!$E$1:$E$600,1,Referrals!$H$1:$H$600,"Done")<COUNTIF(Referrals!$E$1:$E$600,1)),(OR($B$11="A team",$B$11="Me; and I am hiring"))*(COUNTIFS(Employees!$E$1:$E$600,1,Employees!$H$1:$H$600,"Done")<COUNTIF(Employees!$E$1:$E$600,1)),($B$10="Some; and I could afford to lose it while I learn")*(COUNTIFS(Agencies!$E$1:$E$600,1,Agencies!$H$1:$H$600,"Done")<COUNTIF(Agencies!$E$1:$E$600,1)),(OR($B$9="One to ten",$B$9="More than ten"))*(COUNTIFS(Affiliates!$E$1:$E$600,1,Affiliates!$H$1:$H$600,"Done")<COUNTIF(Affiliates!$E$1:$E$600,1)))=0,"cleared","open") -> open | F26: =IF(SUM((TRUE())*(COUNTIFS(Magnet!$E$1:$E$600,2,Magnet!$H$1:$H$600,"Done")<COUNTIF(Magnet!$E$1:$E$600,2)),(TRUE())*(COUNTIFS(Warm!$E$1:$E$600,2,Warm!$H$1:$H$600,"Done")<COUNTIF(Warm!$E$1:$E$600,2)),(TRUE())*(COUNTIFS(Content!$E$1:$E$600,2,Content!$H$1:$H$600,"Done")<COUNTIF(Content!$E$1:$E$600,2)),(TRUE())*(COUNTIFS(Cold!$E$1:$E$600,2,Cold!$H$1:$H$600,"Done")<COUNTIF(Cold!$E$1:$E$600,2)),($B$10="Some; and I could afford to lose it while I learn")*(COUNTIFS(Ads!$E$1:$E$600,2,Ads!$H$1:$H$600,"Done")<COUNTIF(Ads!$E$1:$E$600,2)),(OR($B$9="One to ten",$B$9="More than ten"))*(COUNTIFS(Referrals!$E$1:$E$600,2,Referrals!$H$1:$H$600,"Done")<COUNTIF(Referrals!$E$1:$E$600,2)),(OR($B$11="A team",$B$11="Me; and I am hiring"))*(COUNTIFS(Employees!$E$1:$E$600,2,Employees!$H$1:$H$600,"Done")<COUNTIF(Employees!$E$1:$E$600,2)),($B$10="Some; and I could afford to lose it while I learn")*(COUNTIFS(Agencies!$E$1:$E$600,2,Agencies!$H$1:$H$600,"Done")<COUNTIF(Agencies!$E$1:$E$600,2)),(OR($B$9="One to ten",$B$9="More than ten"))*(COUNTIFS(Affiliates!$E$1:$E$600,2,Affiliates!$H$1:$H$600,"Done")<COUNTIF(Affiliates!$E$1:$E$600,2)))=0,"cleared","open") -> open | G26: =IF(SUM((TRUE())*(COUNTIFS(Magnet!$E$1:$E$600,3,Magnet!$H$1:$H$600,"Done")<COUNTIF(Magnet!$E$1:$E$600,3)),(TRUE())*(COUNTIFS(Warm!$E$1:$E$600,3,Warm!$H$1:$H$600,"Done")<COUNTIF(Warm!$E$1:$E$600,3)),(TRUE())*(COUNTIFS(Content!$E$1:$E$600,3,Content!$H$1:$H$600,"Done")<COUNTIF(Content!$E$1:$E$600,3)),(TRUE())*(COUNTIFS(Cold!$E$1:$E$600,3,Cold!$H$1:$H$600,"Done")<COUNTIF(Cold!$E$1:$E$600,3)),($B$10="Some; and I could afford to lose it while I learn")*(COUNTIFS(Ads!$E$1:$E$600,3,Ads!$H$1:$H$600,"Done")<COUNTIF(Ads!$E$1:$E$600,3)),(OR($B$9="One to ten",$B$9="More than ten"))*(COUNTIFS(Referrals!$E$1:$E$600,3,Referrals!$H$1:$H$600,"Done")<COUNTIF(Referrals!$E$1:$E$600,3)),(OR($B$11="A team",$B$11="Me; and I am hiring"))*(COUNTIFS(Employees!$E$1:$E$600,3,Employees!$H$1:$H$600,"Done")<COUNTIF(Employees!$E$1:$E$600,3)),($B$10="Some; and I could afford to lose it while I learn")*(COUNTIFS(Agencies!$E$1:$E$600,3,Agencies!$H$1:$H$600,"Done")<COUNTIF(Agencies!$E$1:$E$600,3)),(OR($B$9="One to ten",$B$9="More than ten"))*(COUNTIFS(Affiliates!$E$1:$E$600,3,Affiliates!$H$1:$H$600,"Done")<COUNTIF(Affiliates!$E$1:$E$600,3)))=0,"cleared","open") -> open | H26: =IF(SUM((TRUE())*(COUNTIFS(Magnet!$E$1:$E$600,4,Magnet!$H$1:$H$600,"Done")<COUNTIF(Magnet!$E$1:$E$600,4)),(TRUE())*(COUNTIFS(Warm!$E$1:$E$600,4,Warm!$H$1:$H$600,"Done")<COUNTIF(Warm!$E$1:$E$600,4)),(TRUE())*(COUNTIFS(Content!$E$1:$E$600,4,Content!$H$1:$H$600,"Done")<COUNTIF(Content!$E$1:$E$600,4)),(TRUE())*(COUNTIFS(Cold!$E$1:$E$600,4,Cold!$H$1:$H$600,"Done")<COUNTIF(Cold!$E$1:$E$600,4)),($B$10="Some; and I could afford to lose it while I learn")*(COUNTIFS(Ads!$E$1:$E$600,4,Ads!$H$1:$H$600,"Done")<COUNTIF(Ads!$E$1:$E$600,4)),(OR($B$9="One to ten",$B$9="More than ten"))*(COUNTIFS(Referrals!$E$1:$E$600,4,Referrals!$H$1:$H$600,"Done")<COUNTIF(Referrals!$E$1:$E$600,4)),(OR($B$11="A team",$B$11="Me; and I am hiring"))*(COUNTIFS(Employees!$E$1:$E$600,4,Employees!$H$1:$H$600,"Done")<COUNTIF(Employees!$E$1:$E$600,4)),($B$10="Some; and I could afford to lose it while I learn")*(COUNTIFS(Agencies!$E$1:$E$600,4,Agencies!$H$1:$H$600,"Done")<COUNTIF(Agencies!$E$1:$E$600,4)),(OR($B$9="One to ten",$B$9="More than ten"))*(COUNTIFS(Affiliates!$E$1:$E$600,4,Affiliates!$H$1:$H$600,"Done")<COUNTIF(Affiliates!$E$1:$E$600,4)))=0,"cleared","open") -> open | I26: =IF(SUM((TRUE())*(COUNTIFS(Magnet!$E$1:$E$600,5,Magnet!$H$1:$H$600,"Done")<COUNTIF(Magnet!$E$1:$E$600,5)),(TRUE())*(COUNTIFS(Warm!$E$1:$E$600,5,Warm!$H$1:$H$600,"Done")<COUNTIF(Warm!$E$1:$E$600,5)),(TRUE())*(COUNTIFS(Content!$E$1:$E$600,5,Content!$H$1:$H$600,"Done")<COUNTIF(Content!$E$1:$E$600,5)),(TRUE())*(COUNTIFS(Cold!$E$1:$E$600,5,Cold!$H$1:$H$600,"Done")<COUNTIF(Cold!$E$1:$E$600,5)),($B$10="Some; and I could afford to lose it while I learn")*(COUNTIFS(Ads!$E$1:$E$600,5,Ads!$H$1:$H$600,"Done")<COUNTIF(Ads!$E$1:$E$600,5)),(OR($B$9="One to ten",$B$9="More than ten"))*(COUNTIFS(Referrals!$E$1:$E$600,5,Referrals!$H$1:$H$600,"Done")<COUNTIF(Referrals!$E$1:$E$600,5)),(OR($B$11="A team",$B$11="Me; and I am hiring"))*(COUNTIFS(Employees!$E$1:$E$600,5,Employees!$H$1:$H$600,"Done")<COUNTIF(Employees!$E$1:$E$600,5)),($B$10="Some; and I could afford to lose it while I learn")*(COUNTIFS(Agencies!$E$1:$E$600,5,Agencies!$H$1:$H$600,"Done")<COUNTIF(Agencies!$E$1:$E$600,5)),(OR($B$9="One to ten",$B$9="More than ten"))*(COUNTIFS(Affiliates!$E$1:$E$600,5,Affiliates!$H$1:$H$600,"Done")<COUNTIF(Affiliates!$E$1:$E$600,5)))=0,"cleared","open") -> open
A28: Levels done, for the picture | B28: Done | D28: Of
A29: The Lead Magnet | B29: =COUNTIF(Magnet!$H$1:$H$600,"Done") -> 0 | D29: =COUNT(Magnet!$E$1:$E$600) -> 9
A30: Warm Outreach | B30: =COUNTIF(Warm!$H$1:$H$600,"Done") -> 0 | D30: =COUNT(Warm!$E$1:$E$600) -> 10
A31: Free Content | B31: =COUNTIF(Content!$H$1:$H$600,"Done") -> 0 | D31: =COUNT(Content!$E$1:$E$600) -> 9
A32: Cold Outreach | B32: =COUNTIF(Cold!$H$1:$H$600,"Done") -> 0 | D32: =COUNT(Cold!$E$1:$E$600) -> 8
A33: Paid Ads | B33: =COUNTIF(Ads!$H$1:$H$600,"Done") -> 2 | D33: =COUNT(Ads!$E$1:$E$600) -> 9
A34: Referrals | B34: =COUNTIF(Referrals!$H$1:$H$600,"Done") -> 1 | D34: =COUNT(Referrals!$E$1:$E$600) -> 6
A35: Employees | B35: =COUNTIF(Employees!$H$1:$H$600,"Done") -> 0 | D35: =COUNT(Employees!$E$1:$E$600) -> 5
A36: Agencies | B36: =COUNTIF(Agencies!$H$1:$H$600,"Done") -> 0 | D36: =COUNT(Agencies!$E$1:$E$600) -> 5
A37: Affiliates | B37: =COUNTIF(Affiliates!$H$1:$H$600,"Done") -> 0 | D37: =COUNT(Affiliates!$E$1:$E$600) -> 6
A38: The whole book | B38: =SUM(B29:B37) -> 3 | D38: =SUM(D29:D37) -> 67 | E38: =IF(D38=0,"",B38/D38) -> 0.044776119
A40: The Machine, in brief | B40: Value | D40: Goal
A41: Engaged leads a week at your numbers | B41: =IF(Machine!B29="","not yet",Machine!B29) -> 25.384615 | D41: =IF($B$12="","set the goal above",IF(B41="not yet","fill the Machine",IF(B41>=$B$12,"hit","short by "&TEXT($B$12-B41,"0.0")))) -> hit
A42: Customers a month | B42: =IF(Machine!B28="","not yet",Machine!B28) -> 9.24
A43: Lifetime gross profit over cost per customer | B43: =IF(Machine!B41="","not yet",Machine!B41) -> 4.0964 | D43: the book says three or more
A44: First thirty days over cost per customer | B44: =IF(Machine!B42="","not yet",Machine!B42) -> 1.078 | D44: the book says two or more
A46: The book, chapter by chapter | B46: Sheet | D46: What it is
A47: Chapters 1 and 3 | B47: Start Here | D47: The core four, and which one first
A48: Chapter 12 | B48: Start Here | D48: The rule of 100, and the one-year promise
A49: Chapter 2 | B49: Magnet | D49: The Lead Magnet (the sun)
A50: Chapter 4 | B50: Warm | D50: Warm Outreach (core four)
A51: Chapter 5 | B51: Content | D51: Free Content (core four)
A52: Chapter 6 | B52: Cold | D52: Cold Outreach (core four)
A53: Chapter 7 | B53: Ads | D53: Paid Ads (core four)
A54: Chapter 8 | B54: Referrals | D54: Referrals (a lead getter)
A55: Chapter 9 | B55: Employees | D55: Employees (a lead getter)
A56: Chapter 10 | B56: Agencies | D56: Agencies (a lead getter)
A57: Chapter 11 | B57: Affiliates | D57: Affiliates (a lead getter)
... A60: The words | B60: Words | D60: The glossary
A62: The frameworks of $100M Leads (Alex Hormozi, 2023), restated in this app's own words and turned into exercises. The book is the reference; nothing here quotes it. Chapter numbers point the reader back to it. Frameworks and exercises, not figures. The one rule of thumb carried as a number is the book's: lifetime gross profit should be at least three times what a customer cost to get, and the first thirty days should pay back twice that cost before you scale ads. Every example number in this workbook is invented.

Sheet Machine
A1: The Machine: the numbers behind the book
A2: Reach, the rates, what a customer costs and is worth, the book's two checks, the levers, referrals against churn. The Measure levels on the planet sheets read from here.
A3: How to use this sheet: type only in the yellow cells (blue text). Everything in black is worked out for you. A blank yellow cell means "not yet", not zero. Choose Y in a checklist cell to tick it.
A5: Your numbers | B5: Value | F5: What it means
A6: These are the example numbers of an invented piano teacher. Replace every one with yours.
A7: Primary actions a day | B7: 100 | F7: Messages, reach-outs, or ad impressions bought. The rule of 100 says a hundred.
A8: Days a month you do them | B8: 22
A9: Reach-outs that become engaged leads | B9: 0.05 | F9: Replied, clicked, or took the magnet and gave a way to reach them.
A10: Engaged leads that book a call or a visit | B10: 0.4
A11: Bookings that show up | B11: 0.7
A12: Shows that buy | B12: 0.3
A13: What a new customer pays up front ($) | B13: 300
A14: What they pay each month after that ($) | B14: 200 | F14: Zero if nothing, and zero is an answer.
A15: Months a customer stays, on average | B15: 8
A16: Gross margin: what is left after delivering | B16: 0.7
A17: Ad spend a month ($) | B17: 3000 | F17: Zero if you run no ads.
A18: Pay for the people doing outreach and content, a month ($) | B18: 0 | F18: Zero if it is only you. Zero is an answer.
A19: Paying customers today | B19: 12
A20: Share of customers who leave in a month | B20: 0.08
A21: Share of customers who bring one in a month | B21: 0.1
A23: A month at these numbers | B23: Value | F23: How it is worked out
A24: Reached a month | B24: =IF(COUNT(B7,B8)=2,B7*B8,"") -> 2200 | F24: actions a day times days a month
A25: Engaged leads a month | B25: =IF(OR(B24="",B9=""),"",B24*B9) -> 110 | F25: reached times the reply rate
A26: Booked | B26: =IF(OR(B25="",B10=""),"",B25*B10) -> 44 | F26: engaged times the booking rate
A27: Showed | B27: =IF(OR(B26="",B11=""),"",B26*B11) -> 30.8 | F27: booked times the show rate
A28: Customers a month | B28: =IF(OR(B27="",B12=""),"",B27*B12) -> 9.24 | F28: showed times the close rate
A29: Engaged leads a week | B29: =IF(B25="","",B25*12/52) -> 25.384615 | F29: engaged a month, as a week (against the goal on Start Here)
A31: What a lead and a customer cost | B31: Value | F31: How it is worked out
A32: Spend on getting leads, a month | B32: =IF(COUNT(B17,B18)=2,B17+B18,"") -> 3000 | F32: ads plus pay
A33: Cost per engaged lead | B33: =IF(OR(B32="",B25=""),"",IF(B25=0,"none made",B32/B25)) -> 27.272727 | F33: spend over engaged leads
A34: Cost per customer | B34: =IF(OR(B32="",B28=""),"",IF(B28=0,"none made",B32/B28)) -> 324.67532 | F34: spend over customers
A36: What a customer is worth | B36: Value | F36: How it is worked out
A37: Lifetime gross profit | B37: =IF(COUNT(B13,B14,B15,B16)=4,(B13+B14*B15)*B16,"") -> 1330 | F37: (up front + monthly times months kept) times margin
A38: Gross profit in the first thirty days | B38: =IF(COUNT(B13,B14,B15,B16)=4,(B13+B14)*B16,"") -> 350 | F38: (up front + one month) times margin
A40: The book's two checks | B40: Value | C40: Rule | F40: Verdict
A41: Lifetime gross profit over cost per customer | B41: =IF(OR(B37="",B32=""),"",IF(B32=0,"free",IF(ISNUMBER(B34),B37/B34,""))) -> 4.0964 | C41: 3 | F41: =IF(B41="","needs the numbers above",IF(B41="free","Your leads cost nothing you counted, so every customer is profit.",IF(B41>=C41,"Passes: a customer is worth more than three times what they cost.","Under three to one: fix the offer, the margin, or the funnel before spending more."))) -> Passes: a customer is worth more than three times what they cost.
A42: First thirty days over cost per customer | B42: =IF(OR(B38="",B32=""),"",IF(B32=0,"free",IF(ISNUMBER(B34),B38/B34,""))) -> 1.078 | C42: 2 | F42: =IF(B42="","needs the numbers above",IF(B42="free","Nothing to pay back.",IF(B42>=C42,"Passes: the first month pays for the next one. The book says this is when you can scale.","The first month does not pay back twice. Growth will eat cash; raise the up-front price or lower the cost."))) -> The first month does not pay back twice. Growth will eat cash; raise the up-front price or lower the cost.
A44: The levers: one small change | B44: Customers a month | C44: Extra customers | D44: Change | F44: Why this matters
A45: As entered | B45: =IF(COUNT(B7,B8,B9,B10,B11,B12)=6,B7*B8*B9*B10*B11*B12,"") -> 9.24 | F45: Every rate multiplies the same chain, so a tenth more of any rate is the same tenth more customers. One point is different: a point on a low rate is worth far more than a point on a high one. The biggest number in "Extra customers" is your lowest rate, and that is where "better" beats "more".
A46: Reply rate up one point | B46: =IF(COUNT(B7,B8,B9,B10,B11,B12)=6,B7*B8*MIN(1,B9+0.01)*B10*B11*B12,"") -> 11.088 | C46: =IF(B46="","",B46-$B$45) -> 1.848 | D46: +1 point
A47: Booking rate up one point | B47: =IF(COUNT(B7,B8,B9,B10,B11,B12)=6,B7*B8*B9*MIN(1,B10+0.01)*B11*B12,"") -> 9.471 | C47: =IF(B47="","",B47-$B$45) -> 0.231 | D47: +1 point
A48: Show rate up one point | B48: =IF(COUNT(B7,B8,B9,B10,B11,B12)=6,B7*B8*B9*B10*MIN(1,B11+0.01)*B12,"") -> 9.372 | C48: =IF(B48="","",B48-$B$45) -> 0.132 | D48: +1 point
A49: Close rate up one point | B49: =IF(COUNT(B7,B8,B9,B10,B11,B12)=6,B7*B8*B9*B10*B11*MIN(1,B12+0.01),"") -> 9.548 | C49: =IF(B49="","",B49-$B$45) -> 0.308 | D49: +1 point
A50: Ten more actions a day | B50: =IF(COUNT(B7,B8,B9,B10,B11,B12)=6,(B7+10)*B8*B9*B10*B11*B12,"") -> 10.164 | C50: =IF(B50="","",B50-$B$45) -> 0.924 | D50: +10 a day
A52: Referrals against churn: a year of customers | B52: With referrals as entered | C52: If nobody referred | F52: What it means
A53: Now | B53: =IF(COUNT(B19,B20,B21)=3,B19,"") -> 12 | C53: =IF(COUNT(B19,B20,B21)=3,B19,"") -> 12 | F53: =IF(NOT(COUNT(B19,B20,B21)=3),"needs customers today, churn and the referral rate",IF(B21>B20,"Referrals outnumber the customers who leave: the business grows on its own, before any lead you buy.",IF(B21=B20,"Referrals exactly replace the customers who leave. Every new customer is growth, none of it free.","More customers leave each month than referrals bring. Growth has to be bought until the referral rate passes the churn."))) -> Referrals outnumber the customers who leave: the business grows on its own, before any lead you buy.
A54: Month 1 | B54: =IF(B53="","",B53*(1-B20+B21)+IF(B28="",0,B28)) -> 21.48 | C54: =IF(C53="","",C53*(1-B20)+IF(B28="",0,B28)) -> 20.28
A55: Month 2 | B55: =IF(B54="","",B54*(1-B20+B21)+IF(B28="",0,B28)) -> 31.1496 | C55: =IF(C54="","",C54*(1-B20)+IF(B28="",0,B28)) -> 27.8976
A56: Month 3 | B56: =IF(B55="","",B55*(1-B20+B21)+IF(B28="",0,B28)) -> 41.012592 | C56: =IF(C55="","",C55*(1-B20)+IF(B28="",0,B28)) -> 34.905792
A57: Month 4 | B57: =IF(B56="","",B56*(1-B20+B21)+IF(B28="",0,B28)) -> 51.072844 | C57: =IF(C56="","",C56*(1-B20)+IF(B28="",0,B28)) -> 41.353329
A58: Month 5 | B58: =IF(B57="","",B57*(1-B20+B21)+IF(B28="",0,B28)) -> 61.334301 | C58: =IF(C57="","",C57*(1-B20)+IF(B28="",0,B28)) -> 47.285062
A59: Month 6 | B59: =IF(B58="","",B58*(1-B20+B21)+IF(B28="",0,B28)) -> 71.800987 | C59: =IF(C58="","",C58*(1-B20)+IF(B28="",0,B28)) -> 52.742257
A60: Month 7 | B60: =IF(B59="","",B59*(1-B20+B21)+IF(B28="",0,B28)) -> 82.477006 | C60: =IF(C59="","",C59*(1-B20)+IF(B28="",0,B28)) -> 57.762877
A61: Month 8 | B61: =IF(B60="","",B60*(1-B20+B21)+IF(B28="",0,B28)) -> 93.366547 | C61: =IF(C60="","",C60*(1-B20)+IF(B28="",0,B28)) -> 62.381847
A62: Month 9 | B62: =IF(B61="","",B61*(1-B20+B21)+IF(B28="",0,B28)) -> 104.47388 | C62: =IF(C61="","",C61*(1-B20)+IF(B28="",0,B28)) -> 66.631299
A63: Month 10 | B63: =IF(B62="","",B62*(1-B20+B21)+IF(B28="",0,B28)) -> 115.80336 | C63: =IF(C62="","",C62*(1-B20)+IF(B28="",0,B28)) -> 70.540795
A64: Month 11 | B64: =IF(B63="","",B63*(1-B20+B21)+IF(B28="",0,B28)) -> 127.35942 | C64: =IF(C63="","",C63*(1-B20)+IF(B28="",0,B28)) -> 74.137531
A65: Month 12 | B65: =IF(B64="","",B64*(1-B20+B21)+IF(B28="",0,B28)) -> 139.14661 | C65: =IF(C64="","",C64*(1-B20)+IF(B28="",0,B28)) -> 77.446529
A66: The gap after a year | B66: =IF(B65="","",B65-C65) -> 61.700082 | F66: customers, what asking for referrals is worth

Sheet Magnet
A1: The Lead Magnet (the sun)
A2: Chapter 2, Leads alone are not enough. Everything orbits this: one free thing that solves one narrow problem for the people you want, so they raise a hand.
A3: How to use this sheet: type only in the yellow cells (blue text). Everything in black is worked out for you. A blank yellow cell means "not yet", not zero. Choose Y in a checklist cell to tick it.
A4: Band | B4: Levels done | C4: Of | E4: Band | F4: Done items | G4: Of | H4: Status
A5: 1. Learn: The idea, in one sitting | B5: =COUNTIFS($E$1:$E$600,1,$H$1:$H$600,"Done") -> 0 | C5: =COUNTIF($E$1:$E$600,1) -> 2
A6: 2. Sketch: Write your version of it | B6: =COUNTIFS($E$1:$E$600,2,$H$1:$H$600,"Done") -> 0 | C6: =COUNTIF($E$1:$E$600,2) -> 2
A7: 3. Do: Run it, with a checklist | B7: =COUNTIFS($E$1:$E$600,3,$H$1:$H$600,"Done") -> 0 | C7: =COUNTIF($E$1:$E$600,3) -> 3
A8: 4. Measure: Put numbers on it | B8: =COUNTIFS($E$1:$E$600,4,$H$1:$H$600,"Done") -> 0 | C8: =COUNTIF($E$1:$E$600,4) -> 1
A9: 5. Scale: More, better, new | B9: =COUNTIFS($E$1:$E$600,5,$H$1:$H$600,"Done") -> 0 | C9: =COUNTIF($E$1:$E$600,5) -> 1
A10: This planet | B10: =SUM(B5:B9) -> 0 | C10: =SUM(C5:C9) -> 9 | E10: The columns E to H on the right are the workings for each level: its band, how many of its items are done, how many there are, and its status. Leave them be.
A12: Band 1: Learn. The idea, in one sitting. Payoff: clarity.
A13: A lead is not an engaged lead | B13: about 5 min | C13: Chapter 2 | E13: 1 | F13: =0+(B15<>"")+(B16<>"") -> 0 | G13: 2 | H13: =IF(F13=G13,"Done",IF(F13>0,"In progress","Not yet")) -> Not yet
A14: A lead is anyone you could contact. An engaged lead is someone who showed interest and gave you a way to reach them. Only engaged leads matter, and a lead magnet is how you make them: one free thing that solves one narrow problem for one kind of person.
A15: The person the magnet is for | C15: for example: Adults who quit piano as kids
A16: The narrow problem it solves, the first step of the bigger one | C16: for example: Not knowing which songs are easy enough to start with
A17: You have leveled this when: You can say who you serve and the one narrow problem the magnet will solve.
A19: Pick the kind of magnet | B19: about 5 min | C19: Chapter 2, step 2 | E19: 1 | F19: =0+(B21<>"")+(B22<>"") -> 0 | G19: 2 | H19: =IF(F19=G19,"Done",IF(F19>0,"In progress","Not yet")) -> Not yet
A20: There are three kinds. One reveals a problem they did not know they had (a test, a check, an audit). One is a sample or a trial of the real thing. One is a single step of a many-step process, done for them.
A21: The kind | C21: choose one: Reveal a problem / A sample or a trial / One step of a bigger process
A22: Why this kind fits the problem | C22: for example: They do not know how rusty they are, so a five-minute playing check shows them where to start.
A23: You have leveled this when: One kind chosen, with a reason.
A25: Band 2: Sketch. Write your version of it. Payoff: a draft you can use tomorrow.
A26: How it is delivered | B26: about 5 min | C26: Chapter 2, step 3 | E26: 2 | F26: =0+(B28<>"")+(B29<>"") -> 0 | G26: 2 | H26: =IF(F26=G26,"Done",IF(F26>0,"In progress","Not yet")) -> Not yet
A27: A magnet arrives as software, as information, as a service done for them, or as a physical thing. Pick the one they would actually use. Information is easiest to make; a service is hardest to ignore.
A28: Delivered as | C28: choose one: Software or a tool / Information: a guide, a video, a list / A service done for them / A physical thing
A29: What it is, in one line | C29: for example: A twelve-minute video that finds your level and gives you three songs
A30: You have leveled this when: One delivery picked.
A32: Name it, three ways | B32: about 10 min | C32: Chapter 2, step 4 | E32: 2 | F32: =0+(B34<>"")+(B35<>"")+(B36<>"")+(B37<>"") -> 0 | G32: 4 | H32: =IF(F32=G32,"Done",IF(F32>0,"In progress","Not yet")) -> Not yet
A33: The name is the headline: what they get, for whom, and why now. Write three, then pick the one a stranger would understand fastest. Test the others later as ad hooks.
A34: Name one | C34: for example: The Rusty Fingers Test
A35: Name two | C35: for example: Find your first three songs in twelve minutes
A36: Name three | C36: for example: The adult beginner's starting map
A37: The one you will use | C37: choose one: Name one / Name two / Name three
A38: You have leveled this when: Three names written, one chosen.
A40: Band 3: Do. Run it, with a checklist. Payoff: leads.
A41: Make it easy to take in | B41: about 15 min | C41: Chapter 2, step 5 | E41: 3 | F41: =0+(B43="Y")+(B44="Y")+(B45="Y")+(B46="Y")+(B47="Y") -> 0 | G41: 5 | H41: =IF(F41=G41,"Done",IF(F41>0,"In progress","Not yet")) -> Not yet
A42: The fastest magnet wins. Offer it in the formats people already use, keep it short, and ask for nothing but a way to reach them.
A43: [ ] It takes under fifteen minutes to use | C43: Y when true
A44: [ ] It works on a phone | C44: Y when true
A45: [ ] It comes in the format they prefer (text, video, audio, a tool) | C45: Y when true
A46: [ ] No account or download is needed to get value from it | C46: Y when true
A47: [ ] It asks for one thing only: a way to reach them | C47: Y when true
A48: You have leveled this when: Every box ticked for the magnet as it exists today.
A50: Make it so good they would pay | B50: about 20 min | C50: Chapter 2, step 6 | E50: 3 | F50: =0+(B52="Y")+(B53="Y")+(B54="Y")+(B55="Y")+(B56="Y") -> 0 | G50: 5 | H50: =IF(F50=G50,"Done",IF(F50>0,"In progress","Not yet")) -> Not yet
A51: Give away the thing you could charge for. A magnet that solves the narrow problem completely earns trust for the bigger one. A weak magnet costs you the lead and the reputation.
A52: [ ] It solves the narrow problem completely, not half of it | C52: Y when true
A53: [ ] Someone would pay for it as it stands | C53: Y when true
A54: [ ] It gives a result before they buy anything | C54: Y when true
A55: [ ] It is the best free thing of its kind that you know of | C55: Y when true
A56: [ ] You have used it yourself, start to finish, as a stranger would | C56: Y when true
A57: You have leveled this when: Every box ticked honestly.
A59: Tell them what to do next | B59: about 10 min | C59: Chapter 2, step 7 | E59: 3 | F59: =0+(B61<>"")+(B62<>"") -> 0 | G59: 2 | H59: =IF(F59=G59,"Done",IF(F59>0,"In progress","Not yet")) -> Not yet
A60: A magnet ends with a call to action: say exactly what to do, and give a reason to do it now. Scarcity, a deadline, or a bonus that goes away all work. A magnet with no ask is a gift, not advertising.
A61: The ask, word for word | C61: for example: Book a free twenty-minute first lesson this week.
A62: The reason to act now | C62: choose one: Only so many spots / A deadline / A bonus that goes away / None yet, I will add one
A63: You have leveled this when: The ask is written and it says why now.
A65: Band 4: Measure. Put numbers on it. Payoff: certainty.
A66: Count who took it and who engaged | B66: about 5 min | C66: Chapter 2 | E66: 4 | F66: =0+(B68<>"")+(B69<>"") -> 0 | G66: 2 | H66: =IF(F66=G66,"Done",IF(F66>0,"In progress","Not yet")) -> Not yet
A67: Two numbers a month: how many people took the magnet, and how many of those became engaged leads (replied, booked, asked). If the second is a small share of the first, the ask is weak or the magnet drew the wrong people.
A68: People who took the magnet last month | C68: for example: 60
A69: Of them, engaged leads | C69: for example: 18
A70: Engaged share | B70: =IF(OR(B69="",B68=""),"not yet",IF(B68=0,"none",B69/B68)) -> not yet
A71: You have leveled this when: Both numbers entered for the last month.
A73: Band 5: Scale. More, better, new. Payoff: power.
A74: More magnets, better magnets, new problems | B74: about 20 min | C74: Chapter 2 | E74: 5 | F74: =0+(B76="Y")+(B77="Y")+(B78="Y")+(B79="Y") -> 0 | G74: 4 | H74: =IF(F74=G74,"Done",IF(F74>0,"In progress","Not yet")) -> Not yet
A75: Once one magnet works, make the next: a second narrow problem, a second format, or one magnet per planet. Retire the weakest. The magnet is the start of every planet's funnel, so a better magnet lifts all of them.
A76: [ ] Each planet you use has a magnet that fits how it reaches people | C76: Y when true
A77: [ ] The weakest magnet of the last quarter was retired or rewritten | C77: Y when true
A78: [ ] A second narrow problem has its own magnet | C78: Y when true
A79: [ ] Every magnet ends with the same next step into the paid offer | C79: Y when true
A80: You have leveled this when: Every box ticked.

Sheet Warm
A1: Warm Outreach (core four: people who know you, one to one)
A2: Chapter 4, Warm outreach. Reach out, one at a time, to people who already know you. The cheapest way to your first customers.
A3: How to use this sheet: type only in the yellow cells (blue text). Everything in black is worked out for you. A blank yellow cell means "not yet", not zero. Choose Y in a checklist cell to tick it.
A4: Band | B4: Levels done | C4: Of | E4: Band | F4: Done items | G4: Of | H4: Status
A5: 1. Learn: The idea, in one sitting | B5: =COUNTIFS($E$1:$E$600,1,$H$1:$H$600,"Done") -> 0 | C5: =COUNTIF($E$1:$E$600,1) -> 2
A6: 2. Sketch: Write your version of it | B6: =COUNTIFS($E$1:$E$600,2,$H$1:$H$600,"Done") -> 0 | C6: =COUNTIF($E$1:$E$600,2) -> 3
A7: 3. Do: Run it, with a checklist | B7: =COUNTIFS($E$1:$E$600,3,$H$1:$H$600,"Done") -> 0 | C7: =COUNTIF($E$1:$E$600,3) -> 3
A8: 4. Measure: Put numbers on it | B8: =COUNTIFS($E$1:$E$600,4,$H$1:$H$600,"Done") -> 0 | C8: =COUNTIF($E$1:$E$600,4) -> 1
A9: 5. Scale: More, better, new | B9: =COUNTIFS($E$1:$E$600,5,$H$1:$H$600,"Done") -> 0 | C9: =COUNTIF($E$1:$E$600,5) -> 1
A10: This planet | B10: =SUM(B5:B9) -> 0 | C10: =SUM(C5:C9) -> 10 | E10: The columns E to H on the right are the workings for each level: its band, how many of its items are done, how many there are, and its status. Leave them be.
A12: Band 1: Learn. The idea, in one sitting. Payoff: clarity.
A13: What warm outreach is | B13: about 5 min | C13: Chapter 4 | E13: 1 | F13: =0+(B15="Y") -> 0 | G13: 1 | H13: =IF(F13=G13,"Done",IF(F13>0,"In progress","Not yet")) -> Not yet
A14: One-to-one messages to people who already know you: your contacts, your followers, past customers. It costs nothing but time, and it is where the book says a business with no customers starts. The rule of 100 applies: a hundred reach-outs a day.
A15: Read it? Put Y here when you have.
A16: You have leveled this when: Read, and confirmed.
A18: Acknowledge, compliment, ask | B18: about 10 min | C18: Chapter 4, step 3 | E18: 1 | F18: =0+(B20<>"")+(B21<>"") -> 0 | G18: 2 | H18: =IF(F18=G18,"Done",IF(F18>0,"In progress","Not yet")) -> Not yet
A19: A warm message is personal or it is spam. Acknowledge something true about them, compliment something real, then ask a question they will want to answer. No pitch in the first message. The pitch comes after they reply.
A20: A real contact (first name is fine) | C20: for example: Sam
A21: Your acknowledge, compliment, ask | C21: for example: Saw you finished the marathon, that is a serious year of training. How are the knees holding up?
A22: You have leveled this when: One real message written for one real person.
A24: Band 2: Sketch. Write your version of it. Payoff: a draft you can use tomorrow.
A25: Get your list | B25: about 20 min | C25: Chapter 4, step 1 | E25: 2 | F25: =0+(B27<>"")+(B28<>"")+(B29<>"") -> 0 | G25: 3 | H25: =IF(F25=G25,"Done",IF(F25>0,"In progress","Not yet")) -> Not yet
A26: Everyone you can reach is your list: phone contacts, email contacts, and followers on every platform. Count them. Most people are surprised how many hundreds they already know.
A27: Phone contacts | C27: for example: 420
A28: Email contacts | C28: for example: 310
A29: Followers and connections, all platforms | C29: for example: 900
A30: Your list | B30: =IF(COUNT(B27,B28,B29)<3,"not yet",SUM(B27,B28,B29)) -> not yet
A31: You have leveled this when: Every count entered. Zero is fine, blank is not.
A33: Pick the platform | B33: about 5 min | C33: Chapter 4, step 2 | E33: 2 | F33: =0+(B35<>"")+(B36<>"") -> 0 | G33: 2 | H33: =IF(F33=G33,"Done",IF(F33>0,"In progress","Not yet")) -> Not yet
A34: Reach people where they already answer you. One platform to start. Text if they text you, email if they email you, direct messages if that is where the list lives.
A35: Where you will message first | C35: choose one: Text messages / Direct messages on a social platform / Email / Phone calls / In person
A36: Why there | C36: for example: Most of my list is in my phone and they reply to texts within the day
A37: You have leveled this when: One platform picked.
A39: Write the offer sentence | B39: about 15 min | C39: Chapter 4, step 6 | E39: 2 | F39: =0+(B41<>"")+(B42<>"")+(B43<>"")+(B44<>"") -> 0 | G39: 4 | H39: =IF(F39=G39,"Done",IF(F39>0,"In progress","Not yet")) -> Not yet
A40: When someone replies, you tell them what you do in one sentence: I help this kind of person get this result in this much time without this pain. Then the ask: do you know anyone who would want that? Asking about others is easier to say yes to, and often they say me.
A41: I help | C41: for example: adults who quit piano as kids
A42: get | C42: for example: playing a song they love
A43: in | C43: for example: thirty days
A44: without | C44: for example: scales, theory, or a teacher who sighs
A45: Your offer | B45: =IF(COUNTA(B41,B42,B43,B44)<4,"fill every blank and it reads back here","I help "&B41&" get "&B42&" in "&B43&" without "&B44&". Do you know anyone who would want that?") -> fill every blank and it reads back here
A46: You have leveled this when: All four blanks filled and the sentence reads well out loud.
A48: Band 3: Do. Run it, with a checklist. Payoff: leads.
A49: The daily hundred | B49: about 90 min | C49: Chapter 4, steps 4 and 5 | E49: 3 | F49: =0+(B51="Y")+(B52="Y")+(B53="Y")+(B54="Y")+(B55="Y")+(B56="Y") -> 0 | G49: 6 | H49: =IF(F49=G49,"Done",IF(F49>0,"In progress","Not yet")) -> Not yet
A50: A hundred personal messages a day, from your list, on your platform. Warm each reply with another acknowledge, compliment, ask before the offer. Log the count. The book's promise is simple: do this every day and the first customers come.
A51: [ ] The list is open and sorted so you never hunt for the next name | C51: Y when true
A52: [ ] One hundred messages sent, each with a real acknowledge and compliment | C52: Y when true
A53: [ ] Every reply got a second personal message before any offer | C53: Y when true
A54: [ ] The offer sentence was said to everyone who engaged | C54: Y when true
A55: [ ] Everyone who said no was asked if they know someone | C55: Y when true
A56: [ ] Today's count is logged | C56: Y when true
A57: You have leveled this when: A day where every box is true. Tick it, then log the count on the Machine page.
A59: Free, then proof, then a price | B59: about 30 min | C59: Chapter 4, steps 7 and 8 | E59: 3 | F59: =0+(B61="Y")+(B62="Y")+(B63="Y")+(B64="Y")+(B65="Y") -> 0 | G59: 5 | H59: =IF(F59=G59,"Done",IF(F59>0,"In progress","Not yet")) -> Not yet
A60: The first few customers pay with feedback and a testimonial, not money. Serve them so well the results are undeniable. Ask for the testimonial and a referral. Then charge the next batch, and raise the price a little with every batch after that.
A61: [ ] Five people said yes to the free version | C61: Y when true
A62: [ ] Each got more than was promised | C62: Y when true
A63: [ ] Each gave a testimonial in their own words | C63: Y when true
A64: [ ] Each was asked for one referral | C64: Y when true
A65: [ ] The next batch was charged, and the price goes up with each batch | C65: Y when true
A66: You have leveled this when: Every box ticked.
A68: Keep the list warm | B68: about 30 min | C68: Chapter 4, step 9 | E68: 3 | F68: =0+(B70="Y")+(B71="Y")+(B72="Y") -> 0 | G68: 3 | H68: =IF(F68=G68,"Done",IF(F68>0,"In progress","Not yet")) -> Not yet
A69: A list goes cold if you only show up to sell. Touch it regularly with something useful or personal, and add every new person you meet to it the same day.
A70: [ ] A monthly note goes to the whole list with something useful, no ask | C70: Y when true
A71: [ ] Every new person you meet is added to the list the same day | C71: Y when true
A72: [ ] Past customers hear from you as often as prospects do | C72: Y when true
A73: You have leveled this when: Every box ticked.
A75: Band 4: Measure. Put numbers on it. Payoff: certainty.
A76: Your warm numbers | B76: about 5 min | C76: Chapter 4 | E76: 4 | F76: =0+(B78<>"")+(B79<>"")+(B80<>"")+(B81<>"") -> 0 | G76: 4 | H76: =IF(F76=G76,"Done",IF(F76>0,"In progress","Not yet")) -> Not yet
A77: Four numbers a week: messages sent, replies, offers made, and yeses. Reply rate tells you whether the messages are personal. Yes rate tells you whether the offer is good.
A78: Messages sent | C78: for example: 500
A79: Replies | C79: for example: 140
A80: Offers made | C80: for example: 60
A81: Yeses | C81: for example: 9
A82: Last seven days | B82: each step as a share of the one before
A83: Replies, as a share | B83: =IF(OR(B78="",B79=""),"not yet",IF(B78=0,"none",B79/B78)) -> not yet
A84: Offers made, as a share | B84: =IF(OR(B79="",B80=""),"not yet",IF(B79=0,"none",B80/B79)) -> not yet
A85: Yeses, as a share | B85: =IF(OR(B80="",B81=""),"not yet",IF(B80=0,"none",B81/B80)) -> not yet
A86: You have leveled this when: All four entered for the last seven days.
A88: Band 5: Scale. More, better, new. Payoff: power.
A89: More, better, new | B89: about 20 min | C89: Chapters 4 and 12 | E89: 5 | F89: =0+(B91="Y")+(B92="Y")+(B93="Y")+(B94="Y") -> 0 | G89: 4 | H89: =IF(F89=G89,"Done",IF(F89>0,"In progress","Not yet")) -> Not yet
A90: More: a bigger list, from everyone you meet and every customer's circle. Better: a tighter offer sentence and a referral ask every time. New: when warm outreach runs every day without you thinking about it, add the next planet, not before.
A91: [ ] The list grows every week and the growth is counted | C91: Y when true
A92: [ ] The offer sentence was rewritten from what people actually said yes to | C92: Y when true
A93: [ ] Warm outreach runs daily, and someone else could run it from the checklist | C93: Y when true
A94: [ ] The next planet is chosen | C94: Y when true
A95: You have leveled this when: Every box ticked.

Sheet Content
A1: Free Content (core four: people who know you, one to many)
A2: Chapter 5, Post free content. Post things worth keeping, so strangers become people who know you, and some of them ask.
A3: How to use this sheet: type only in the yellow cells (blue text). Everything in black is worked out for you. A blank yellow cell means "not yet", not zero. Choose Y in a checklist cell to tick it.
A4: Band | B4: Levels done | C4: Of | E4: Band | F4: Done items | G4: Of | H4: Status
A5: 1. Learn: The idea, in one sitting | B5: =COUNTIFS($E$1:$E$600,1,$H$1:$H$600,"Done") -> 0 | C5: =COUNTIF($E$1:$E$600,1) -> 2
A6: 2. Sketch: Write your version of it | B6: =COUNTIFS($E$1:$E$600,2,$H$1:$H$600,"Done") -> 0 | C6: =COUNTIF($E$1:$E$600,2) -> 3
A7: 3. Do: Run it, with a checklist | B7: =COUNTIFS($E$1:$E$600,3,$H$1:$H$600,"Done") -> 0 | C7: =COUNTIF($E$1:$E$600,3) -> 2
A8: 4. Measure: Put numbers on it | B8: =COUNTIFS($E$1:$E$600,4,$H$1:$H$600,"Done") -> 0 | C8: =COUNTIF($E$1:$E$600,4) -> 1
A9: 5. Scale: More, better, new | B9: =COUNTIFS($E$1:$E$600,5,$H$1:$H$600,"Done") -> 0 | C9: =COUNTIF($E$1:$E$600,5) -> 1
A10: This planet | B10: =SUM(B5:B9) -> 0 | C10: =SUM(C5:C9) -> 9 | E10: The columns E to H on the right are the workings for each level: its band, how many of its items are done, how many there are, and its status. Leave them be.
A12: Band 1: Learn. The idea, in one sitting. Payoff: clarity.
A13: The content unit: hook, retain, reward | B13: about 5 min | C13: Chapter 5 | E13: 1 | F13: =0+(B15="Y") -> 0 | G13: 1 | H13: =IF(F13=G13,"Done",IF(F13>0,"In progress","Not yet")) -> Not yet
A14: Every piece of content does three jobs. The hook earns the first second of attention. The middle keeps it, with a list, steps, or a story. The reward is what they walk away with, so they come back. Post it where the people you want already spend their time.
A15: Read it? Put Y here when you have.
A16: You have leveled this when: Read, and confirmed.
A18: Give, give, give, ask | B18: about 5 min | C18: Chapter 5 | E18: 1 | F18: =0+(B20<>"")+(B21<>"") -> 0 | G18: 2 | H18: =IF(F18=G18,"Done",IF(F18>0,"In progress","Not yet")) -> Not yet
A19: Most content gives and never asks. Some content asks. The ratio is yours to set, and the book's advice is to give far more than you ask. An ask can sit inside a giving piece (integrated) or be its own piece now and then (intermittent).
A20: Giving pieces for every asking piece | C20: choose one: Three gives, one ask / Five gives, one ask / Ten gives, one ask
A21: How you will ask | C21: choose one: A line inside giving pieces / A whole piece, now and then / Both
A22: You have leveled this when: A ratio chosen.
A24: Band 2: Sketch. Write your version of it. Payoff: a draft you can use tomorrow.
A25: Five hooks from five places | B25: about 20 min | C25: Chapter 5, hooks | E25: 2 | F25: =0+(B27<>"")+(B28<>"")+(B29<>"")+(B30<>"")+(B31<>"") -> 0 | G25: 5 | H25: =IF(F25=G25,"Done",IF(F25>0,"In progress","Not yet")) -> Not yet
A26: Hooks come from topics, and topics come from five places: your far past, your recent past, what is happening now, what is trending, and something you make happen. Write one hook from each. A hook is a headline: a question, a bold claim, a number, or the start of a story.
A27: From your far past | C27: for example: I quit piano at nine. Here is what I would tell that kid.
A28: From your recent past | C28: for example: A student played her wedding song last week after six lessons.
A29: From right now | C29: for example: Teaching the same song to three adults today. Three different mistakes.
A30: From a trend | C30: for example: That viral piano clip? Here is the one trick that makes it easy.
A31: Something you made happen | C31: for example: I asked twenty adults why they quit. All twenty said the same thing.
A32: You have leveled this when: Five hooks written.
A34: Three shapes that keep attention | B34: about 20 min | C34: Chapter 5, retain | E34: 2 | F34: =0+(B36<>"")+(B37<>"")+(B38<>"") -> 0 | G34: 3 | H34: =IF(F34=G34,"Done",IF(F34>0,"In progress","Not yet")) -> Not yet
A35: People stay for lists, for steps, and for stories. Outline one piece in each shape from your hooks. Short pieces do one shape; long pieces stack them.
A36: A list piece (the hook, then the items) | C36: for example: Five songs adults can play in week one: 1. ... 2. ...
A37: A steps piece (the hook, then the order) | C37: for example: How to relearn a song in a week: day one ... day two ...
A38: A story piece (the hook, the turn, the lesson) | C38: for example: She had not touched a piano in twenty years. Then ...
A39: You have leveled this when: Three outlines written.
A41: The reward, and the platform | B41: about 10 min | C41: Chapter 5, reward | E41: 2 | F41: =0+(B43<>"")+(B44<>"") -> 0 | G41: 2 | H41: =IF(F41=G41,"Done",IF(F41>0,"In progress","Not yet")) -> Not yet
A42: The reward is the reason they follow: they got something they can use. Say what each piece leaves them with. Then pick one platform, the one where your people already are, and stay there until it works.
A43: The one platform to start | C43: for example: Instagram
A44: What a viewer leaves with | C44: for example: One thing to try at the piano tonight
A45: You have leveled this when: A platform picked and the reward written.
A47: Band 3: Do. Run it, with a checklist. Payoff: leads.
A48: A week of posting | B48: about 120 min | C48: Chapter 5 | E48: 3 | F48: =0+(B50="Y")+(B51="Y")+(B52="Y")+(B53="Y")+(B54="Y")+(B55="Y") -> 0 | G48: 6 | H48: =IF(F48=G48,"Done",IF(F48>0,"In progress","Not yet")) -> Not yet
A49: Plan seven pieces, post one a day, and answer everyone who comments. Content compounds: the first week feels like talking to a room with nobody in it. The book says post anyway.
A50: [ ] Seven pieces planned, each with a hook from the five places | C50: Y when true
A51: [ ] Each piece has one shape: list, steps, or story | C51: Y when true
A52: [ ] Each piece names what the viewer leaves with | C52: Y when true
A53: [ ] The give-to-ask ratio was kept | C53: Y when true
A54: [ ] One piece was posted every day | C54: Y when true
A55: [ ] Every comment got a reply | C55: Y when true
A56: You have leveled this when: A week where every box is true.
A58: A hundred minutes a day | B58: about 100 min | C58: Chapters 5 and 12 | E58: 3 | F58: =0+(B60="Y")+(B61="Y")+(B62="Y") -> 0 | G58: 3 | H58: =IF(F58=G58,"Done",IF(F58>0,"In progress","Not yet")) -> Not yet
A59: The rule of 100 for content is time: a hundred minutes a day making and posting. Log it. Days you skip are days the room stays empty.
A60: [ ] A hundred minutes on content today, timed | C60: Y when true
A61: [ ] At least one piece posted | C61: Y when true
A62: [ ] Today's minutes are logged | C62: Y when true
A63: You have leveled this when: A day with the minutes logged.
A65: Band 4: Measure. Put numbers on it. Payoff: certainty.
A66: Your content numbers | B66: about 5 min | C66: Chapter 5 | E66: 4 | F66: =0+(B68<>"")+(B69<>"")+(B70<>"") -> 0 | G66: 3 | H66: =IF(F66=G66,"Done",IF(F66>0,"In progress","Not yet")) -> Not yet
A67: Three numbers a month: pieces posted, followers gained, and engaged leads that came from content. Pieces tell you if you are doing the work. Followers tell you if the hooks work. Engaged leads tell you if the asks work.
A68: Pieces posted | C68: for example: 28
A69: Followers gained | C69: for example: 240
A70: Engaged leads from content | C70: for example: 12
A71: You have leveled this when: All three entered for the last month.
A73: Band 5: Scale. More, better, new. Payoff: power.
A74: More, better, new | B74: about 30 min | C74: Chapter 5, grow | E74: 5 | F74: =0+(B76="Y")+(B77="Y")+(B78="Y")+(B79="Y") -> 0 | G74: 4 | H74: =IF(F74=G74,"Done",IF(F74>0,"In progress","Not yet")) -> Not yet
A75: More: post more often. Better: look at the ten best pieces and make more like them. New: cut long pieces into short ones, take the winners to a second platform, then hand the cutting to someone else.
A76: [ ] The ten best pieces of the quarter are listed with what their hooks had in common | C76: Y when true
A77: [ ] Posting frequency went up and stayed up | C77: Y when true
A78: [ ] Winners are repurposed to a second platform | C78: Y when true
A79: [ ] Someone else cuts long pieces into short ones | C79: Y when true
A80: You have leveled this when: Every box ticked.

Sheet Cold
A1: Cold Outreach (core four: strangers, one to one)
A2: Chapter 6, Cold outreach. Reach out, one at a time, to people who have never heard of you. Volume, personal first lines, and something of value up front.
A3: How to use this sheet: type only in the yellow cells (blue text). Everything in black is worked out for you. A blank yellow cell means "not yet", not zero. Choose Y in a checklist cell to tick it.
A4: Band | B4: Levels done | C4: Of | E4: Band | F4: Done items | G4: Of | H4: Status
A5: 1. Learn: The idea, in one sitting | B5: =COUNTIFS($E$1:$E$600,1,$H$1:$H$600,"Done") -> 0 | C5: =COUNTIF($E$1:$E$600,1) -> 1
A6: 2. Sketch: Write your version of it | B6: =COUNTIFS($E$1:$E$600,2,$H$1:$H$600,"Done") -> 0 | C6: =COUNTIF($E$1:$E$600,2) -> 3
A7: 3. Do: Run it, with a checklist | B7: =COUNTIFS($E$1:$E$600,3,$H$1:$H$600,"Done") -> 0 | C7: =COUNTIF($E$1:$E$600,3) -> 2
A8: 4. Measure: Put numbers on it | B8: =COUNTIFS($E$1:$E$600,4,$H$1:$H$600,"Done") -> 0 | C8: =COUNTIF($E$1:$E$600,4) -> 1
A9: 5. Scale: More, better, new | B9: =COUNTIFS($E$1:$E$600,5,$H$1:$H$600,"Done") -> 0 | C9: =COUNTIF($E$1:$E$600,5) -> 1
A10: This planet | B10: =SUM(B5:B9) -> 0 | C10: =SUM(C5:C9) -> 8 | E10: The columns E to H on the right are the workings for each level: its band, how many of its items are done, how many there are, and its status. Leave them be.
A12: Band 1: Learn. The idea, in one sitting. Payoff: clarity.
A13: What cold outreach is | B13: about 5 min | C13: Chapter 6 | E13: 1 | F13: =0+(B15="Y") -> 0 | G13: 1 | H13: =IF(F13=G13,"Done",IF(F13>0,"In progress","Not yet")) -> Not yet
A14: One-to-one messages to strangers who fit your customer. It works on four things: a list of the right people, a first line that proves you looked at them, something of real value in the first message, and volume, because most will not answer. Expect to reach many to get one.
A15: Read it? Put Y here when you have.
A16: You have leveled this when: Read, and confirmed.
A18: Band 2: Sketch. Write your version of it. Payoff: a draft you can use tomorrow.
A19: Get the list | B19: about 30 min | C19: Chapter 6, lists | E19: 2 | F19: =0+(B21<>"")+(B22<>"") -> 0 | G19: 2 | H19: =IF(F19=G19,"Done",IF(F19>0,"In progress","Not yet")) -> Not yet
A20: Three ways to get names: a tool that finds them, a list you buy, or a list you build by hand from where your customers gather. Start with the one you can have by tomorrow.
A21: Where the names come from | C21: choose one: A tool that finds them / A list I buy / A list I build by hand
A22: Names in the list today | C22: for example: 800
A23: You have leveled this when: A source picked and a count of names in hand.
A25: The first line, and the gift | B25: about 20 min | C25: Chapter 6, personalize and value | E25: 2 | F25: =0+(B27<>"")+(B28<>"") -> 0 | G25: 2 | H25: =IF(F25=G25,"Done",IF(F25>0,"In progress","Not yet")) -> Not yet
A26: The first line is about them, and it proves a person wrote it. Then give something of value before you ask anything: the lead magnet, a fix, a result they can see fast. Big, fast value is what makes a stranger answer.
A27: A first line for one name on the list | C27: for example: Your studio's spring recital video has 2,000 views, and the adult students got the loudest cheers.
A28: What you give in that first message | C28: for example: A free twelve-minute level check for any adult student who wants to restart.
A29: You have leveled this when: Both written.
A31: The follow-up plan | B31: about 10 min | C31: Chapter 6, follow up | E31: 2 | F31: =0+(B33<>"")+(COUNTIF(B35:B39,"Y")>0) -> 0 | G31: 2 | H31: =IF(F31=G31,"Done",IF(F31>0,"In progress","Not yet")) -> Not yet
A32: A stranger who did not answer has not said no. Follow up more times than feels comfortable, in more than one way: message, email, a call, a voice note. Decide the number of touches and the channels before you start, so the plan runs itself.
A33: Touches before you stop | C33: for example: 7
A34: Channels you will use (Y beside each that applies)
A35: Email
A36: Direct message
A37: Phone
A38: Voice note
A39: Physical mail
A40: You have leveled this when: A number of touches and at least two channels.
A42: Band 3: Do. Run it, with a checklist. Payoff: leads.
A43: The daily hundred | B43: about 120 min | C43: Chapter 6 | E43: 3 | F43: =0+(B45="Y")+(B46="Y")+(B47="Y")+(B48="Y")+(B49="Y") -> 0 | G43: 5 | H43: =IF(F43=G43,"Done",IF(F43>0,"In progress","Not yet")) -> Not yet
A44: A hundred new cold reach-outs a day, plus every follow-up that is due. Personal first line, the gift, the ask. Log the count.
A45: [ ] One hundred new reach-outs sent | C45: Y when true
A46: [ ] Each had a first line about them | C46: Y when true
A47: [ ] Each gave the gift before any ask | C47: Y when true
A48: [ ] Every follow-up that was due went out, on the planned channel | C48: Y when true
A49: [ ] Today's count is logged | C49: Y when true
A50: You have leveled this when: A day where every box is true.
A52: Make the volume run itself | B52: about 60 min | C52: Chapter 6, volume | E52: 3 | F52: =0+(B54="Y")+(B55="Y")+(B56="Y")+(B57="Y") -> 0 | G52: 4 | H52: =IF(F52=G52,"Done",IF(F52>0,"In progress","Not yet")) -> Not yet
A53: Volume is the whole game, and volume needs a system: templates with a personal first line, a tool that sends and tracks, a list refilled every week, and, when it works, someone else doing the sending.
A54: [ ] Templates exist for the first message and every follow-up | C54: Y when true
A55: [ ] A tool sends, tracks and reminds you of follow-ups | C55: Y when true
A56: [ ] The list is refilled every week before it runs out | C56: Y when true
A57: [ ] Someone else can run a day from the checklist | C57: Y when true
A58: You have leveled this when: Every box ticked.
A60: Band 4: Measure. Put numbers on it. Payoff: certainty.
A61: Your cold numbers | B61: about 5 min | C61: Chapter 6 | E61: 4 | F61: =0+(B63<>"")+(B64<>"")+(B65<>"") -> 0 | G61: 3 | H61: =IF(F61=G61,"Done",IF(F61>0,"In progress","Not yet")) -> Not yet
A62: Three numbers a week: reach-outs, replies, and bookings. The reply rate tests the first line and the gift. The booking rate tests the ask.
A63: Reach-outs sent | C63: for example: 500
A64: Replies | C64: for example: 25
A65: Bookings | C65: for example: 6
A66: Last seven days | B66: each step as a share of the one before
A67: Replies, as a share | B67: =IF(OR(B63="",B64=""),"not yet",IF(B63=0,"none",B64/B63)) -> not yet
A68: Bookings, as a share | B68: =IF(OR(B64="",B65=""),"not yet",IF(B64=0,"none",B65/B64)) -> not yet
A69: You have leveled this when: All three entered for the last seven days.
A71: Band 5: Scale. More, better, new. Payoff: power.
A72: More, better, new | B72: about 30 min | C72: Chapter 6 | E72: 5 | F72: =0+(B74="Y")+(B75="Y")+(B76="Y")+(B77="Y") -> 0 | G72: 4 | H72: =IF(F72=G72,"Done",IF(F72>0,"In progress","Not yet")) -> Not yet
A73: More: more senders and a bigger list. Better: test first lines and gifts against each other and keep the winner. New: a new list source or a new channel once the current one is steady.
A74: [ ] Two first lines were tested against each other this month and the winner kept | C74: Y when true
A75: [ ] Two gifts were tested the same way | C75: Y when true
A76: [ ] Daily volume went up | C76: Y when true
A77: [ ] A second channel or list source is running | C77: Y when true
A78: You have leveled this when: Every box ticked.

Sheet Ads
A1: Paid Ads (core four: strangers, one to many)
A2: Chapter 7, Run paid ads. Pay to put your lead magnet in front of strangers. Fast, and it costs money while you learn.
A3: How to use this sheet: type only in the yellow cells (blue text). Everything in black is worked out for you. A blank yellow cell means "not yet", not zero. Choose Y in a checklist cell to tick it.
A4: Band | B4: Levels done | C4: Of | E4: Band | F4: Done items | G4: Of | H4: Status
A5: 1. Learn: The idea, in one sitting | B5: =COUNTIFS($E$1:$E$600,1,$H$1:$H$600,"Done") -> 0 | C5: =COUNTIF($E$1:$E$600,1) -> 2
A6: 2. Sketch: Write your version of it | B6: =COUNTIFS($E$1:$E$600,2,$H$1:$H$600,"Done") -> 0 | C6: =COUNTIF($E$1:$E$600,2) -> 2
A7: 3. Do: Run it, with a checklist | B7: =COUNTIFS($E$1:$E$600,3,$H$1:$H$600,"Done") -> 0 | C7: =COUNTIF($E$1:$E$600,3) -> 2
A8: 4. Measure: Put numbers on it | B8: =COUNTIFS($E$1:$E$600,4,$H$1:$H$600,"Done") -> 2 | C8: =COUNTIF($E$1:$E$600,4) -> 2
A9: 5. Scale: More, better, new | B9: =COUNTIFS($E$1:$E$600,5,$H$1:$H$600,"Done") -> 0 | C9: =COUNTIF($E$1:$E$600,5) -> 1
A10: This planet | B10: =SUM(B5:B9) -> 2 | C10: =SUM(C5:C9) -> 9 | E10: The columns E to H on the right are the workings for each level: its band, how many of its items are done, how many there are, and its status. Leave them be.
A12: Band 1: Learn. The idea, in one sitting. Payoff: clarity.
A13: What paid ads are, and the money rule | B13: about 10 min | C13: Chapter 7 | E13: 1 | F13: =0+(B15="Y") -> 0 | G13: 1 | H13: =IF(F13=G13,"Done",IF(F13>0,"In progress","Not yet")) -> Not yet
A14: You pay a platform to show your lead magnet to strangers. It is the fastest way to reach many, and the only one that costs cash while you learn. Two rules from the book keep it safe: over a customer's life, gross profit should be at least three times what they cost to get, and the first thirty days should bring in twice that cost before you spend more.
A15: Read it? Put Y here when you have.
A16: You have leveled this when: Read, and confirmed.
A18: The parts of an ad | B18: about 5 min | C18: Chapter 7, part 1 | E18: 1 | F18: =0+(B20="Y") -> 0 | G18: 1 | H18: =IF(F18=G18,"Done",IF(F18>0,"In progress","Not yet")) -> Not yet
A19: Call out the person so the right people stop and the wrong ones scroll on. Hook them the way content does. Give them the value: what they get, for whom, and why now. Then the call to action: the magnet, and one clear step.
A20: Read it? Put Y here when you have.
A21: You have leveled this when: Read, and confirmed.
A23: Band 2: Sketch. Write your version of it. Payoff: a draft you can use tomorrow.
A24: The platform and the call-out | B24: about 15 min | C24: Chapter 7, part 1 | E24: 2 | F24: =0+(B26<>"")+(B27<>"")+(B28<>"") -> 0 | G24: 3 | H24: =IF(F24=G24,"Done",IF(F24>0,"In progress","Not yet")) -> Not yet
A25: Advertise where your people already are. Then write the labels that call them out: who should see this, and who should not. A good call-out makes a stranger feel found.
A26: The platform | C26: for example: Facebook and Instagram
A27: Who this is for (the labels) | C27: for example: Adults over 35 who used to play piano
A28: Who should scroll past | C28: for example: Parents looking for kids' lessons
A29: You have leveled this when: All three written.
A31: Write the ad | B31: about 30 min | C31: Chapter 7, part 1 | E31: 2 | F31: =0+(B33<>"")+(B34<>"")+(B35<>"")+(B36<>"") -> 0 | G31: 4 | H31: =IF(F31=G31,"Done",IF(F31>0,"In progress","Not yet")) -> Not yet
A32: Four pieces, in order. Write it plain. The magnet is the offer in the ad; the paid product comes later.
A33: The hook | C33: for example: Quit piano as a kid? Your hands remember more than you think.
A34: The value: what, for whom, why now | C34: for example: A free twelve-minute level check that finds three songs you can play this month. For adults who stopped. Ten spots this week.
A35: The call to action | C35: for example: Tap to get your level check.
A36: The magnet it points to | C36: for example: The Rusty Fingers Test
A37: You have leveled this when: All four written.
A39: Band 3: Do. Run it, with a checklist. Payoff: leads.
A40: Launch day | B40: about 60 min | C40: Chapter 7 | E40: 3 | F40: =0+(B42="Y")+(B43="Y")+(B44="Y")+(B45="Y")+(B46="Y") -> 0 | G40: 5 | H40: =IF(F40=G40,"Done",IF(F40>0,"In progress","Not yet")) -> Not yet
A41: A hundred dollars a day is the book's rule of 100 for ads: enough to learn, small enough to lose. Launch a few versions, capture the contact, and make sure you can see what each lead cost from day one.
A42: [ ] The daily budget is set and you can afford to lose it while you learn | C42: Y when true
A43: [ ] At least three versions of the ad are live (different hooks) | C43: Y when true
A44: [ ] The ad points to the magnet, and the magnet asks for a way to reach them | C44: Y when true
A45: [ ] Cost per lead is visible in the dashboard | C45: Y when true
A46: [ ] A person or a system follows up with every lead the same day | C46: Y when true
A47: You have leveled this when: Every box ticked on launch day.
A49: The testing loop | B49: about 30 min | C49: Chapter 7, part 2 | E49: 3 | F49: =0+(B51="Y")+(B52="Y")+(B53="Y")+(B54="Y") -> 0 | G49: 4 | H49: =IF(F49=G49,"Done",IF(F49>0,"In progress","Not yet")) -> Not yet
A50: Every week: keep the winner, kill the losers, launch new challengers. Change one thing at a time, the hook most often. The loop never stops; that is the job.
A51: [ ] The losing versions were turned off | C51: Y when true
A52: [ ] New challengers went live against the winner | C52: Y when true
A53: [ ] One thing changed per challenger | C53: Y when true
A54: [ ] Cost per engaged lead was compared, not just cost per lead | C54: Y when true
A55: You have leveled this when: Every box ticked for the last week.
A57: Band 4: Measure. Put numbers on it. Payoff: certainty.
A58: Cost per lead, cost per engaged lead, cost per customer | B58: about 5 min | C58: Chapter 7, part 2 | E58: 4 | F58: =0+(Machine!$B$17<>"")+(Machine!$B$7<>"")+(Machine!$B$8<>"")+(Machine!$B$9<>"")+(Machine!$B$10<>"")+(Machine!$B$11<>"")+(Machine!$B$12<>"") -> 7 | G58: 7 | H58: =IF(F58=G58,"Done",IF(F58>0,"In progress","Not yet")) -> Done
A59: Three costs, and they belong on the Machine page where the whole funnel lives: what you spent, how many engaged leads it made, and how many customers. The Machine turns them into the cost of one engaged lead and the cost of one customer.
A60: From the Machine sheet: Ad spend a month ($) | B60: =IF(Machine!$B$17="","not yet",Machine!$B$17) -> 3000 | C60: type it on the Machine sheet, it shows here
A61: From the Machine sheet: Primary actions a day | B61: =IF(Machine!$B$7="","not yet",Machine!$B$7) -> 100 | C61: type it on the Machine sheet, it shows here
A62: From the Machine sheet: Days a month you do them | B62: =IF(Machine!$B$8="","not yet",Machine!$B$8) -> 22 | C62: type it on the Machine sheet, it shows here
A63: From the Machine sheet: Reach-outs that become engaged leads | B63: =IF(Machine!$B$9="","not yet",Machine!$B$9) -> 0.05 | C63: type it on the Machine sheet, it shows here
A64: From the Machine sheet: Engaged leads that book a call or a visit | B64: =IF(Machine!$B$10="","not yet",Machine!$B$10) -> 0.4 | C64: type it on the Machine sheet, it shows here
A65: From the Machine sheet: Bookings that show up | B65: =IF(Machine!$B$11="","not yet",Machine!$B$11) -> 0.7 | C65: type it on the Machine sheet, it shows here
A66: From the Machine sheet: Shows that buy | B66: =IF(Machine!$B$12="","not yet",Machine!$B$12) -> 0.3 | C66: type it on the Machine sheet, it shows here
A67: You have leveled this when: The Machine has your monthly spend, your funnel rates, and your working days.
A69: The three-to-one check | B69: about 5 min | C69: Chapter 7, part 2 | E69: 4 | F69: =0+(Machine!$B$13<>"")+(Machine!$B$14<>"")+(Machine!$B$15<>"")+(Machine!$B$16<>"") -> 4 | G69: 4 | H69: =IF(F69=G69,"Done",IF(F69>0,"In progress","Not yet")) -> Done
A70: Lifetime gross profit divided by the cost of a customer. Under three, fix the offer or the funnel before spending more. The thirty-day check sits beside it: gross profit in the first month against twice the cost of a customer.
A71: From the Machine sheet: What a new customer pays up front ($) | B71: =IF(Machine!$B$13="","not yet",Machine!$B$13) -> 300 | C71: type it on the Machine sheet, it shows here
A72: From the Machine sheet: What they pay each month after that ($) | B72: =IF(Machine!$B$14="","not yet",Machine!$B$14) -> 200 | C72: type it on the Machine sheet, it shows here
A73: From the Machine sheet: Months a customer stays, on average | B73: =IF(Machine!$B$15="","not yet",Machine!$B$15) -> 8 | C73: type it on the Machine sheet, it shows here
A74: From the Machine sheet: Gross margin: what is left after delivering | B74: =IF(Machine!$B$16="","not yet",Machine!$B$16) -> 0.7 | C74: type it on the Machine sheet, it shows here
A75: You have leveled this when: The Machine has the price, the margin, and how long a customer stays.
A77: Band 5: Scale. More, better, new. Payoff: power.
A78: More, better, new | B78: about 20 min | C78: Chapter 7, part 2 | E78: 5 | F78: =0+(B80="Y")+(B81="Y")+(B82="Y")+(B83="Y") -> 0 | G78: 4 | H78: =IF(F78=G78,"Done",IF(F78>0,"In progress","Not yet")) -> Not yet
A79: More: raise the budget while the three-to-one and thirty-day checks hold, and stop the moment they do not. Better: better hooks, tighter call-outs, a stronger magnet. New: a second platform, once the first is boring.
A80: [ ] The budget only rises when both money checks pass | C80: Y when true
A81: [ ] There is a rule for when it falls back | C81: Y when true
A82: [ ] The best hook of the quarter is known and reused | C82: Y when true
A83: [ ] A second platform is being tested with its own small budget | C83: Y when true
A84: You have leveled this when: Every box ticked.

Sheet Referrals
A1: Referrals (a lead getter)
A2: Chapter 8, Customer referrals. Customers who bring customers. The best leads there are, and the only growth that costs nothing.
A3: How to use this sheet: type only in the yellow cells (blue text). Everything in black is worked out for you. A blank yellow cell means "not yet", not zero. Choose Y in a checklist cell to tick it.
A4: Band | B4: Levels done | C4: Of | E4: Band | F4: Done items | G4: Of | H4: Status
A5: 1. Learn: The idea, in one sitting | B5: =COUNTIFS($E$1:$E$600,1,$H$1:$H$600,"Done") -> 0 | C5: =COUNTIF($E$1:$E$600,1) -> 1
A6: 2. Sketch: Write your version of it | B6: =COUNTIFS($E$1:$E$600,2,$H$1:$H$600,"Done") -> 0 | C6: =COUNTIF($E$1:$E$600,2) -> 2
A7: 3. Do: Run it, with a checklist | B7: =COUNTIFS($E$1:$E$600,3,$H$1:$H$600,"Done") -> 0 | C7: =COUNTIF($E$1:$E$600,3) -> 1
A8: 4. Measure: Put numbers on it | B8: =COUNTIFS($E$1:$E$600,4,$H$1:$H$600,"Done") -> 1 | C8: =COUNTIF($E$1:$E$600,4) -> 1
A9: 5. Scale: More, better, new | B9: =COUNTIFS($E$1:$E$600,5,$H$1:$H$600,"Done") -> 0 | C9: =COUNTIF($E$1:$E$600,5) -> 1
A10: This planet | B10: =SUM(B5:B9) -> 1 | C10: =SUM(C5:C9) -> 6 | E10: The columns E to H on the right are the workings for each level: its band, how many of its items are done, how many there are, and its status. Leave them be.
A12: Band 1: Learn. The idea, in one sitting. Payoff: clarity.
A13: Why referrals beat everything | B13: about 5 min | C13: Chapter 8 | E13: 1 | F13: =0+(B15="Y") -> 0 | G13: 1 | H13: =IF(F13=G13,"Done",IF(F13>0,"In progress","Not yet")) -> Not yet
A14: A referred customer costs nothing to get, buys more, and stays longer. A business grows on its own only when the customers coming in from referrals outnumber the customers leaving. Referrals come from goodwill, and goodwill is the gap between what you promised and what they got.
A15: Read it? Put Y here when you have.
A16: You have leveled this when: Read, and confirmed.
A18: Band 2: Sketch. Write your version of it. Payoff: a draft you can use tomorrow.
A19: Make it worth referring | B19: about 20 min | C19: Chapter 8 | E19: 2 | F19: =0+(B21<>"")+(B22<>"") -> 0 | G19: 2 | H19: =IF(F19=G19,"Done",IF(F19>0,"In progress","Not yet")) -> Not yet
A20: Before asking, make the product more referable. The book lists the ways: sell to better-fit customers, set better expectations, get more of them to a result, get them there faster, and keep them longer. Pick the one you will do this quarter.
A21: This quarter | C21: choose one: Sell to better-fit customers / Set better expectations / Get more customers to a result / Get them there faster / Keep them longer
A22: The change, in one line | C22: for example: Every new student plays a full song in lesson one, so the first week has a win.
A23: You have leveled this when: One picked and the change written.
A25: How you will ask | B25: about 20 min | C25: Chapter 8 | E25: 2 | F25: =0+(COUNTIF(B28:B33,"Y")>0)+(B34<>"") -> 0 | G25: 2 | H25: =IF(F25=G25,"Done",IF(F25>0,"In progress","Not yet")) -> Not yet
A26: Six ways to ask, from the book: a reward for the referrer, a reward for both, asking right after a win, bonuses that unlock when they refer, referral events, and a standing program. Choose the ones you will run and write the offer.
A27: The ways you will use (Y beside each that applies)
A28: A reward for the referrer
A29: A reward for both
A30: Ask right after a win
A31: Bonuses that unlock
A32: A referral event
A33: A standing program
A34: The referral offer, word for word | C34: for example: Bring a friend to their first lesson and you both get the next one free.
A35: You have leveled this when: At least one way chosen and the offer written.
A37: Band 3: Do. Run it, with a checklist. Payoff: leads.
A38: Ask every time | B38: about 30 min | C38: Chapter 8 | E38: 3 | F38: =0+(B40="Y")+(B41="Y")+(B42="Y")+(B43="Y")+(B44="Y") -> 0 | G38: 5 | H38: =IF(F38=G38,"Done",IF(F38>0,"In progress","Not yet")) -> Not yet
A39: The ask lives at two moments: when they buy, and when they win. Make both automatic, track who sent whom, and thank the referrer within the day.
A40: [ ] Every new customer hears the referral offer at signup | C40: Y when true
A41: [ ] Every first win is followed by the ask | C41: Y when true
A42: [ ] Who referred whom is written down | C42: Y when true
A43: [ ] Every referrer is thanked the same day | C43: Y when true
A44: [ ] The referral offer is somewhere customers can find it without asking | C44: Y when true
A45: You have leveled this when: Every box ticked.
A47: Band 4: Measure. Put numbers on it. Payoff: certainty.
A48: Referrals in, customers out | B48: about 5 min | C48: Chapter 8 | E48: 4 | F48: =0+(Machine!$B$19<>"")+(Machine!$B$21<>"")+(Machine!$B$20<>"") -> 3 | G48: 3 | H48: =IF(F48=G48,"Done",IF(F48>0,"In progress","Not yet")) -> Done
A49: Two rates a month, and the Machine draws what they do over a year: the share of customers who brought a new one, and the share who left. When the first is bigger than the second, the business grows without ads.
A50: From the Machine sheet: Paying customers today | B50: =IF(Machine!$B$19="","not yet",Machine!$B$19) -> 12 | C50: type it on the Machine sheet, it shows here
A51: From the Machine sheet: Share of customers who bring one in a month | B51: =IF(Machine!$B$21="","not yet",Machine!$B$21) -> 0.1 | C51: type it on the Machine sheet, it shows here
A52: From the Machine sheet: Share of customers who leave in a month | B52: =IF(Machine!$B$20="","not yet",Machine!$B$20) -> 0.08 | C52: type it on the Machine sheet, it shows here
A53: You have leveled this when: The Machine has your customer count, your referral rate and your churn.
A55: Band 5: Scale. More, better, new. Payoff: power.
A56: More, better, new | B56: about 20 min | C56: Chapter 8 | E56: 5 | F56: =0+(B58="Y")+(B59="Y")+(B60="Y") -> 0 | G56: 3 | H56: =IF(F56=G56,"Done",IF(F56>0,"In progress","Not yet")) -> Not yet
A57: More: ask at more moments. Better: a bigger reward for the referrer whose people stay. New: the customers who refer most are your first affiliates.
A58: [ ] The referral rate is higher than it was last quarter | C58: Y when true
A59: [ ] The best referrers are named | C59: Y when true
A60: [ ] The best referrers were offered the affiliate deal | C60: Y when true
A61: You have leveled this when: Every box ticked.

Sheet Employees
A1: Employees (a lead getter)
A2: Chapter 9, Employees. People on your team who do the core four for you. Document, demonstrate, duplicate.
A3: How to use this sheet: type only in the yellow cells (blue text). Everything in black is worked out for you. A blank yellow cell means "not yet", not zero. Choose Y in a checklist cell to tick it.
A4: Band | B4: Levels done | C4: Of | E4: Band | F4: Done items | G4: Of | H4: Status
A5: 1. Learn: The idea, in one sitting | B5: =COUNTIFS($E$1:$E$600,1,$H$1:$H$600,"Done") -> 0 | C5: =COUNTIF($E$1:$E$600,1) -> 1
A6: 2. Sketch: Write your version of it | B6: =COUNTIFS($E$1:$E$600,2,$H$1:$H$600,"Done") -> 0 | C6: =COUNTIF($E$1:$E$600,2) -> 1
A7: 3. Do: Run it, with a checklist | B7: =COUNTIFS($E$1:$E$600,3,$H$1:$H$600,"Done") -> 0 | C7: =COUNTIF($E$1:$E$600,3) -> 1
A8: 4. Measure: Put numbers on it | B8: =COUNTIFS($E$1:$E$600,4,$H$1:$H$600,"Done") -> 0 | C8: =COUNTIF($E$1:$E$600,4) -> 1
A9: 5. Scale: More, better, new | B9: =COUNTIFS($E$1:$E$600,5,$H$1:$H$600,"Done") -> 0 | C9: =COUNTIF($E$1:$E$600,5) -> 1
A10: This planet | B10: =SUM(B5:B9) -> 0 | C10: =SUM(C5:C9) -> 5 | E10: The columns E to H on the right are the workings for each level: its band, how many of its items are done, how many there are, and its status. Leave them be.
A12: Band 1: Learn. The idea, in one sitting. Payoff: clarity.
A13: Someone else does the core four | B13: about 5 min | C13: Chapter 9 | E13: 1 | F13: =0+(B15="Y") -> 0 | G13: 1 | H13: =IF(F13=G13,"Done",IF(F13>0,"In progress","Not yet")) -> Not yet
A14: An employee who does one of the core four for you is a lead getter. Training is three steps: document what you do, demonstrate it while they watch, then duplicate: they do it while you watch, until their numbers match yours.
A15: Read it? Put Y here when you have.
A16: You have leveled this when: Read, and confirmed.
A18: Band 2: Sketch. Write your version of it. Payoff: a draft you can use tomorrow.
A19: Document one job | B19: about 45 min | C19: Chapter 9, document | E19: 2 | F19: =0+(B21<>"")+(B22<>"") -> 0 | G19: 2 | H19: =IF(F19=G19,"Done",IF(F19>0,"In progress","Not yet")) -> Not yet
A20: Pick the core four action you do every day and write it as a checklist a stranger could follow. The daily hundred on that planet is the checklist; add the words you say and the numbers you expect.
A21: The job to hand off first | C21: choose one: Warm outreach / Content / Cold outreach / Paid ads
A22: The checklist, step by step | C22: for example: 1. Open the list. 2. Send 100 messages using the template, first line personal. 3. ...
A23: You have leveled this when: A job picked and its checklist written.
A25: Band 3: Do. Run it, with a checklist. Payoff: leads.
A26: Demonstrate, then duplicate | B26: about 120 min | C26: Chapter 9 | E26: 3 | F26: =0+(B28="Y")+(B29="Y")+(B30="Y")+(B31="Y") -> 0 | G26: 4 | H26: =IF(F26=G26,"Done",IF(F26>0,"In progress","Not yet")) -> Not yet
A27: They watch you do a full day. Then you watch them do a full day. Then they do it alone and you check the numbers. Pay for outcomes you can count.
A28: [ ] They watched a whole day of the job, with the checklist in hand | C28: Y when true
A29: [ ] You watched them do a whole day | C29: Y when true
A30: [ ] They did a week alone and the numbers were checked daily | C30: Y when true
A31: [ ] Their pay is tied to a number they control | C31: Y when true
A32: You have leveled this when: Every box ticked.
A34: Band 4: Measure. Put numbers on it. Payoff: certainty.
A35: Their numbers against yours | B35: about 5 min | C35: Chapter 9 | E35: 4 | F35: =0+(B37<>"")+(B38<>"") -> 0 | G35: 2 | H35: =IF(F35=G35,"Done",IF(F35>0,"In progress","Not yet")) -> Not yet
A36: One comparison a week: their daily actions and results beside yours from the same job. Train until the gap closes.
A37: Their actions a day | C37: for example: 80
A38: Your actions a day, same job | C38: for example: 100
A39: Of your pace | B39: =IF(OR(B37="",B38=""),"not yet",IF(B38=0,"none",B37/B38)) -> not yet
A40: You have leveled this when: Both entered.
A42: Band 5: Scale. More, better, new. Payoff: power.
A43: More, better, new | B43: about 20 min | C43: Chapter 9 | E43: 5 | F43: =0+(B45="Y")+(B46="Y")+(B47="Y")+(B48="Y") -> 0 | G43: 4 | H43: =IF(F43=G43,"Done",IF(F43>0,"In progress","Not yet")) -> Not yet
A44: More: a second person on the same job. Better: the best of them trains the next. New: a person on the next planet, and eventually someone who runs the people.
A45: [ ] Two people run the first job | C45: Y when true
A46: [ ] The best of them trains new hires from the checklist | C46: Y when true
A47: [ ] A second planet has its own person | C47: Y when true
A48: [ ] Someone other than you checks the daily numbers | C48: Y when true
A49: You have leveled this when: Every box ticked.

Sheet Agencies
A1: Agencies (a lead getter)
A2: Chapter 10, Agencies. Hire an agency to learn a channel from, then bring it in-house.
A3: How to use this sheet: type only in the yellow cells (blue text). Everything in black is worked out for you. A blank yellow cell means "not yet", not zero. Choose Y in a checklist cell to tick it.
A4: Band | B4: Levels done | C4: Of | E4: Band | F4: Done items | G4: Of | H4: Status
A5: 1. Learn: The idea, in one sitting | B5: =COUNTIFS($E$1:$E$600,1,$H$1:$H$600,"Done") -> 0 | C5: =COUNTIF($E$1:$E$600,1) -> 1
A6: 2. Sketch: Write your version of it | B6: =COUNTIFS($E$1:$E$600,2,$H$1:$H$600,"Done") -> 0 | C6: =COUNTIF($E$1:$E$600,2) -> 1
A7: 3. Do: Run it, with a checklist | B7: =COUNTIFS($E$1:$E$600,3,$H$1:$H$600,"Done") -> 0 | C7: =COUNTIF($E$1:$E$600,3) -> 1
A8: 4. Measure: Put numbers on it | B8: =COUNTIFS($E$1:$E$600,4,$H$1:$H$600,"Done") -> 0 | C8: =COUNTIF($E$1:$E$600,4) -> 1
A9: 5. Scale: More, better, new | B9: =COUNTIFS($E$1:$E$600,5,$H$1:$H$600,"Done") -> 0 | C9: =COUNTIF($E$1:$E$600,5) -> 1
A10: This planet | B10: =SUM(B5:B9) -> 0 | C10: =SUM(C5:C9) -> 5 | E10: The columns E to H on the right are the workings for each level: its band, how many of its items are done, how many there are, and its status. Leave them be.
A12: Band 1: Learn. The idea, in one sitting. Payoff: clarity.
A13: Rent the skill, then own it | B13: about 5 min | C13: Chapter 10 | E13: 1 | F13: =0+(B15="Y") -> 0 | G13: 1 | H13: =IF(F13=G13,"Done",IF(F13>0,"In progress","Not yet")) -> Not yet
A14: An agency is a way to learn a channel from people who already know it. The book's play: hire one that is good, say up front you plan to bring the work in-house, have your person sit in on everything, then hire a cheaper one to sustain while your person takes over.
A15: Read it? Put Y here when you have.
A16: You have leveled this when: Read, and confirmed.
A18: Band 2: Sketch. Write your version of it. Payoff: a draft you can use tomorrow.
A19: The interview | B19: about 30 min | C19: Chapter 10 | E19: 2 | F19: =0+(B21<>"")+(B22="Y")+(B23="Y")+(B24="Y")+(B25="Y")+(B26="Y") -> 0 | G19: 6 | H19: =IF(F19=G19,"Done",IF(F19>0,"In progress","Not yet")) -> Not yet
A20: Ask every agency the same questions and write the answers down. The channel is theirs to run; the learning is yours to keep.
A21: The agency you chose, and why | C21: for example: Northside, because their person will train mine on the calls
A22: [ ] Who exactly will run my account, and how many others do they run | C22: Y when true
A23: [ ] What does the first ninety days look like, week by week | C23: Y when true
A24: [ ] Can my person sit in on every call and see every setting | C24: Y when true
A25: [ ] Show me results for a business like mine, with the numbers | C25: Y when true
A26: [ ] I told them I intend to bring this in-house and asked how they will help | C26: Y when true
A27: You have leveled this when: Every question asked of at least two agencies.
A29: Band 3: Do. Run it, with a checklist. Payoff: leads.
A30: Run the engagement | B30: about 30 min | C30: Chapter 10 | E30: 3 | F30: =0+(B32="Y")+(B33="Y")+(B34="Y")+(B35="Y")+(B36="Y") -> 0 | G30: 5 | H30: =IF(F30=G30,"Done",IF(F30>0,"In progress","Not yet")) -> Not yet
A31: Fixed term, weekly calls with your person in the room, every account in your name, and the numbers in your hands every month. When your person can do it, the expensive agency's job is done.
A32: [ ] The contract has an end date | C32: Y when true
A33: [ ] The ad accounts and the pages belong to you, not the agency | C33: Y when true
A34: [ ] Your person is on every weekly call | C34: Y when true
A35: [ ] You get spend, leads, engaged leads and customers every month | C35: Y when true
A36: [ ] Your person has a date to take over | C36: Y when true
A37: You have leveled this when: Every box ticked.
A39: Band 4: Measure. Put numbers on it. Payoff: certainty.
A40: What the agency costs per lead | B40: about 5 min | C40: Chapter 10 | E40: 4 | F40: =0+(B42<>"")+(B43<>"")+(B44<>"") -> 0 | G40: 3 | H40: =IF(F40=G40,"Done",IF(F40>0,"In progress","Not yet")) -> Not yet
A41: The fee plus the spend, over the engaged leads it made. Compare it with what your own planets cost per engaged lead; that is the number that says when to bring it home.
A42: Agency fee last month | C42: for example: $3000
A43: Ad spend last month | C43: for example: $3000
A44: Engaged leads it produced | C44: for example: 120
A45: Cost per engaged lead | B45: =IF(OR(COUNT(B42,B43)<2,B44=""),"not yet",IF(B44=0,"none",SUM(B42,B43)/B44)) -> not yet
A46: You have leveled this when: All three entered for last month.
A48: Band 5: Scale. More, better, new. Payoff: power.
A49: Bring it home | B49: about 20 min | C49: Chapter 10 | E49: 5 | F49: =0+(B51="Y")+(B52="Y")+(B53="Y") -> 0 | G49: 3 | H49: =IF(F49=G49,"Done",IF(F49>0,"In progress","Not yet")) -> Not yet
A50: Your person runs it. A cheaper agency, or none, sustains it. The learning stays.
A51: [ ] Your person runs the channel day to day | C51: Y when true
A52: [ ] The expensive agency is done, or on a smaller retainer | C52: Y when true
A53: [ ] Cost per engaged lead held or fell after the handover | C53: Y when true
A54: You have leveled this when: Every box ticked.

Sheet Affiliates
A1: Affiliates (a lead getter)
A2: Chapter 11, Affiliates. Other businesses that already serve your customer, sending them to you for a cut.
A3: How to use this sheet: type only in the yellow cells (blue text). Everything in black is worked out for you. A blank yellow cell means "not yet", not zero. Choose Y in a checklist cell to tick it.
A4: Band | B4: Levels done | C4: Of | E4: Band | F4: Done items | G4: Of | H4: Status
A5: 1. Learn: The idea, in one sitting | B5: =COUNTIFS($E$1:$E$600,1,$H$1:$H$600,"Done") -> 0 | C5: =COUNTIF($E$1:$E$600,1) -> 1
A6: 2. Sketch: Write your version of it | B6: =COUNTIFS($E$1:$E$600,2,$H$1:$H$600,"Done") -> 0 | C6: =COUNTIF($E$1:$E$600,2) -> 2
A7: 3. Do: Run it, with a checklist | B7: =COUNTIFS($E$1:$E$600,3,$H$1:$H$600,"Done") -> 0 | C7: =COUNTIF($E$1:$E$600,3) -> 1
A8: 4. Measure: Put numbers on it | B8: =COUNTIFS($E$1:$E$600,4,$H$1:$H$600,"Done") -> 0 | C8: =COUNTIF($E$1:$E$600,4) -> 1
A9: 5. Scale: More, better, new | B9: =COUNTIFS($E$1:$E$600,5,$H$1:$H$600,"Done") -> 0 | C9: =COUNTIF($E$1:$E$600,5) -> 1
A10: This planet | B10: =SUM(B5:B9) -> 0 | C10: =SUM(C5:C9) -> 6 | E10: The columns E to H on the right are the workings for each level: its band, how many of its items are done, how many there are, and its status. Leave them be.
A12: Band 1: Learn. The idea, in one sitting. Payoff: clarity.
A13: Other businesses that send you customers | B13: about 5 min | C13: Chapter 11 | E13: 1 | F13: =0+(B15="Y") -> 0 | G13: 1 | H13: =IF(F13=G13,"Done",IF(F13>0,"In progress","Not yet")) -> Not yet
A14: An affiliate already sells to the people you want. Recruiting them is a core four campaign of its own: find them, reach out, make them an offer, get them started, and pay them. One good affiliate can outdo a planet.
A15: Read it? Put Y here when you have.
A16: You have leveled this when: Read, and confirmed.
A18: Band 2: Sketch. Write your version of it. Payoff: a draft you can use tomorrow.
A19: Who your affiliates are | B19: about 30 min | C19: Chapter 11 | E19: 2 | F19: =0+(B21<>"")+(B22<>"") -> 0 | G19: 2 | H19: =IF(F19=G19,"Done",IF(F19>0,"In progress","Not yet")) -> Not yet
A20: Describe the business that already serves your customer and does not compete with you. Then list twenty of them by name.
A21: The ideal affiliate, in one line | C21: for example: Piano shops and tuners who meet adults with a piano gathering dust
A22: Named candidates on your list | C22: for example: 20
A23: You have leveled this when: The profile written and twenty names counted.
A25: The affiliate offer | B25: about 30 min | C25: Chapter 11 | E25: 2 | F25: =0+(B27<>"")+(B28<>"")+(B29<>"") -> 0 | G25: 3 | H25: =IF(F25=G25,"Done",IF(F25>0,"In progress","Not yet")) -> Not yet
A26: What do they get: a share of each sale, a fee per lead, or your product to give their customers. What gets them started: the book favours having them use or buy the product first, and launching together. Write it.
A27: How they are paid | C27: choose one: A share of each sale / A fee per lead / Product for their customers / A mix
A28: What gets them started | C28: choose one: They use or buy it first / A launch we run together / Both
A29: The offer, word for word | C29: for example: Send us an adult who restarts and we pay you a third of their first month, every time.
A30: You have leveled this when: Both chosen and the offer written.
A32: Band 3: Do. Run it, with a checklist. Payoff: leads.
A33: Recruit and launch | B33: about 120 min | C33: Chapter 11 | E33: 3 | F33: =0+(B35="Y")+(B36="Y")+(B37="Y")+(B38="Y")+(B39="Y") -> 0 | G33: 5 | H33: =IF(F33=G33,"Done",IF(F33>0,"In progress","Not yet")) -> Not yet
A34: Reach the twenty the way you reach any lead: warm if you know them, cold if you do not. Get the first ones started with a launch you run together, and give them everything they need to sell without thinking.
A35: [ ] All twenty were contacted, with the offer | C35: Y when true
A36: [ ] The first affiliate used or bought the product | C36: Y when true
A37: [ ] A launch was run together and the results shared | C37: Y when true
A38: [ ] Every affiliate has ready-made messages, links and the magnet | C38: Y when true
A39: [ ] Payouts go out on a fixed day | C39: Y when true
A40: You have leveled this when: Every box ticked.
A42: Band 4: Measure. Put numbers on it. Payoff: certainty.
A43: Your affiliate numbers | B43: about 5 min | C43: Chapter 11 | E43: 4 | F43: =0+(B45<>"")+(B46<>"") -> 0 | G43: 2 | H43: =IF(F43=G43,"Done",IF(F43>0,"In progress","Not yet")) -> Not yet
A44: Two numbers a month: affiliates who sent at least one lead, and the engaged leads they sent. The first says whether they are activated; the second says whether it is worth more of your time.
A45: Affiliates who sent a lead | C45: for example: 4
A46: Engaged leads from affiliates | C46: for example: 22
A47: You have leveled this when: Both entered for last month.
A49: Band 5: Scale. More, better, new. Payoff: power.
A50: More, better, new | B50: about 20 min | C50: Chapter 11 | E50: 5 | F50: =0+(B52="Y")+(B53="Y")+(B54="Y")+(B55="Y") -> 0 | G50: 4 | H50: =IF(F50=G50,"Done",IF(F50>0,"In progress","Not yet")) -> Not yet
A51: More: recruit every month. Better: a leaderboard, tiers and prizes for the ones who send the most. New: a person whose whole job is affiliates.
A52: [ ] Recruiting runs monthly, from a list that is refilled | C52: Y when true
A53: [ ] Affiliates can see how they rank | C53: Y when true
A54: [ ] The top tier earns more | C54: Y when true
A55: [ ] Someone owns the affiliate program | C55: Y when true
A56: You have leveled this when: Every box ticked.

Sheet Daily Log
A1: The rule of 100: your daily log
A2: A hundred primary actions a day on your chosen planet: messages, minutes of content, reach-outs, or dollars. Log every day. A day you skip is a blank row, not a zero.
A3: How to use this sheet: type only in the yellow cells (blue text). Everything in black is worked out for you. A blank yellow cell means "not yet", not zero. Choose Y in a checklist cell to tick it.
A4: Day | B4: Planet | C4: Count | E4: The last thirty days (from today) | F4: Value
A5: 46278 | B5: Warm outreach | C5: 100 | E5: Days logged | F5: =COUNTIFS($A$5:$A$218,">="&TODAY()-29,$C$5:$C$218,"<>") -> 13 | G5: These fourteen rows are example days. Replace them with yours; blank rows below are ready.
A6: 46279 | B6: Warm outreach | C6: 110 | E6: Days at 100 or more | F6: =COUNTIFS($A$5:$A$218,">="&TODAY()-29,$C$5:$C$218,">=100") -> 11
A7: 46280 | B7: Warm outreach | C7: 95 | E7: Actions in the last thirty days | F7: =SUMIFS($C$5:$C$218,$A$5:$A$218,">="&TODAY()-29) -> 1335
A8: 46281 | E8: Average on a logged day | F8: =IF(F5=0,"not yet",F7/F5) -> 102.69231
A9: 46282 | B9: Warm outreach | C9: 120
A10: 46283 | B10: Warm outreach | C10: 100
A11: 46284 | B11: Warm outreach | C11: 100
A12: 46285 | B12: Warm outreach | C12: 130
A13: 46286 | B13: Warm outreach | C13: 60
A14: 46287 | B14: Warm outreach | C14: 100
A15: 46288 | B15: Warm outreach | C15: 105
A16: 46289 | B16: Warm outreach | C16: 100
A17: 46290 | B17: Warm outreach | C17: 100
A18: 46291 | B18: Warm outreach | C18: 115

Sheet Words
A1: The words
A2: Every term the book leans on, in one sentence.
A3: Term | B3: Meaning
A4: Lead | B4: Anyone you could contact.
A5: Engaged lead | B5: Someone who showed interest and gave you a way to reach them. The number the whole book is about.
A6: Lead magnet | B6: A free thing that solves one narrow problem for the person you want, in exchange for a way to reach them.
A7: Core four | B7: The only four ways to get leads: warm outreach, free content, cold outreach, paid ads. Two are to people who know you and two are to strangers; two are one to one and two are one to many.
A8: Lead getter | B8: Someone who does the core four for you: a customer who refers, an employee, an agency, an affiliate.
A9: Rule of 100 | B9: A hundred primary actions a day on your chosen planet: messages, minutes of content, reach-outs, or dollars.
A10: Open to goal | B10: You do not stop for the day when the hundred is done; you stop when the goal is hit, or the hundred, whichever is later.
A11: Acknowledge, compliment, ask | B11: The shape of a warm message: something true about them, something you like, a question they want to answer.
A12: Hook, retain, reward | B12: The three jobs of a piece of content.
A13: Big fast value | B13: What a cold message gives before it asks anything.
A14: More, better, new | B14: The three ways to scale any planet: do more of it, do it better, add a new place to do it.
... A22: Document, demonstrate, duplicate | B22: How you train someone to do a job: write it down, show them, watch them.
