Workbook

Sheet Dashboard
A1: 🏠 BUY vs. RENT + FIRE CALCULATOR
A2: 🟡 Yellow cells = YOUR INPUTS │ Gray cells = auto-calculated (do not edit) │ All formulas locked & protected
B4: 🏡 BUYING | E4: 🏢 RENTING | H4: 📊 RESULTS | K4: 🔥 FIRE
B5: PROPERTY | E5: RENT COSTS | H5: SELECT VIEW YEAR | K5: YOUR FINANCES
B6: Home Price | C6: 500000 | E6: Monthly Rent | F6: 2500 | H6: View at Year → | I6: 30 | K6: Annual Gross Income | L6: 75000
B7: Down Payment % | C7: 0.2 | E7: Annual Rent Increase | F7: 0.03 | K7: Annual Expenses | L7: 48000
B8: Down Payment $ | C8: =C6*C7 -> 100000 | E8: Renters Insurance ($/mo) | F8: 20 | H8: BUYER NET WORTH | K8: Savings Rate | L8: 0.3
B9: MORTGAGE | E9: Security Deposit (mo.) | F9: 2 | H9: =IFERROR(INDEX(Schedule!$H:$H,I6+3),0) -> -1927405.9 | K9: Current Savings/Invest. | L9: 25000
B10: Interest Rate (annual) | C10: 0.07 | E10: INVESTMENT ASSUMPTIONS | K10: FIRE SETTINGS
B11: Loan Term (years) | C11: 30 | E11: Stock Return (annual) | F11: 0.08 | H11: RENTER NET WORTH | K11: Withdrawal Rate (4% rule) | L11: 0.04
B12: ONGOING COSTS | E12: Capital Gains Tax Rate | F12: 0.15 | H12: =IFERROR(INDEX(Schedule!$S:$S,I6+3),0) -> 1044391 | K12: Investment Return | L12: 0.07
B13: Property Tax (% of value/yr) | C13: 0.012 | E13: Extra Monthly Invest ($) | F13: 0 | K13: Inflation Rate | L13: 0.03
B14: Home Insurance ($/mo) | C14: 150 | E14: ANALYSIS PERIOD | H14: =IFERROR(IF(INDEX(Schedule!$H:$H,I6+3)>INDEX(Schedule!$S:$S,I6+3),"🏡 BUYING wins by $"&TEXT(INDEX(Schedule!$H:$H,I6+3)-INDEX(Schedule!$S:$S,I6+3),"#,##0"),"🏢 RENTING wins by $"&TEXT(INDEX(Schedule!$S:$S,I6+3)-INDEX(Schedule!$H:$H,I6+3),"#,##0")),"—") -> 🏢 RENTING wins by $2,971,797 | K14: FIRE — BUY vs RENT
B15: HOA Fees ($/mo) | C15: 0 | E15: Years to Analyze (1–100) | F15: 30 | K15: Monthly Savings if Renting | L15: =MAX(C6*C19+C8,0)/12 -> 9583.3333
B16: Maintenance (% value/yr) | C16: 0.01 | H16: Monthly Cost | I16: =TEXT(C29,"$#,##0") -> $1,067 | K16: Monthly Savings if Buying | L16: =MAX(0,0) -> 0
B17: PMI Rate (if <20% down) | C17: 0.005 | H17: Cum. Cash Spent | I17: =TEXT(IFERROR(INDEX(Schedule!$G:$G,I6+3),0),"$#,##0") -> $756,724 | K17: Your FIRE Number (25x expenses) | L17: =L7*25 -> 1200000
B18: TRANSACTION & GROWTH | H18: Asset Value | I18: =TEXT(IFERROR(INDEX(Schedule!$B:$B,I6+3),0),"$#,##0") -> $1,403,397 | K18: Yrs to FIRE — If Renting | L18: =IFERROR(LOG((L17*L12/(L6*L8)+1),(1+L12)),99) -> 22.977546
B19: Buying Closing Costs % | C19: 0.03 | H19: Cum. Interest Paid | I19: =TEXT(IFERROR(INDEX(Schedule!$E:$E,I6+3),0),"$#,##0") -> $3,488,323 | K19: Yrs to FIRE — If Buying | L19: =IFERROR(LOG((L17*L12/(L6*L8*0.8)+1),(1+L12)),99) -> 25.637536
B20: Selling Costs % | C20: 0.06
B21: Home Appreciation (yr %) | C21: 0.035
B22: Marginal Tax Rate | C22: 0.28
B25: MONTHLY PAYMENT BREAKDOWN | E25: RENTER MATH
B26: Monthly Mortgage (P&I) | C26: =IFERROR((C6-C8)*($$c10/12)*(1+$$c10/12)^($$c11*12)/((1+$$c10/12)^($$c11*12)-1),0) -> 0 | E26: Renter Invests Upfront | F26: =C8+C6*C19 -> 115000
B27: Monthly Property Tax | C27: =C6*C13/12 -> 500 | E27: Renter Security Deposit | F27: =F6*F9 -> 5000
B28: Monthly PMI | C28: =IF(C7<0.2,(C6-C8)*C17/12,0) -> 0 | E28: Monthly Diff Invested by Renter | F28: =MAX(C26+C27+C14+C15+C6*C16/12+C28-(F6+F8),0)+F13 -> 0
B29: TOTAL Monthly (Buyer) | C29: =C26+C27+C14+C15+C6*C16/12+C28 -> 1066.6667 | E29: TOTAL Monthly (Renter) | F29: =F6+F8 -> 2520

Sheet Schedule
A1: Yr | B1: Home Value | C1: Loan Balance | D1: Annual Buyer Cost | E1: Cum. Interest | F1: Cum. Principal | G1: Buyer Cash Spent | H1: Buyer Net Worth ★ | I1: Ann. Mortgage | J1: Ann. Prop Tax | K1: Ann. Insurance | L1: Ann. Mainten. | M1: Ann. PMI | O1: Cum. Rent | P1: Annual Rent Cost | Q1: Portfolio Value | R1: Renter Cash Spent | S1: Renter Net Worth ★ | T1: Annual Rent | U1: Ann. RentIns
A2: ★ Buyer Net Worth = home sale proceeds − loan balance ★ Renter Net Worth = portfolio after cap gains tax Year 0 = row 3, Year 100 = row 103 | Yellow cells = inputs on Dashboard
A3: 0 | B3: =Dashboard!$C6 -> 500000 | C3: =Dashboard!$C6-Dashboard!$C8 -> 400000 | D3: 0 | E3: 0 | F3: 0 | G3: =Dashboard!$C8+Dashboard!$C6*Dashboard!$C19 -> 115000 | H3: =B3*(1-Dashboard!$C20)-C3 -> 70000 | I3: 0 | J3: 0 | K3: 0 | L3: 0 | M3: 0 | O3: 0 | P3: 0 | Q3: =Dashboard!$C8+Dashboard!$C6*Dashboard!$C19+Dashboard!$F6*Dashboard!$F9 -> 120000 | R3: =Dashboard!$F6*Dashboard!$F9 -> 5000 | S3: =Q3 -> 120000 | T3: 0 | U3: 0
A4: 1 | B4: =B3*(1+Dashboard!$C21) -> 517500 | C4: =MAX((Dashboard!$C6-Dashboard!$C8)*(1+Dashboard!$C10/12)^(1*12)-Dashboard!$C26*((1+Dashboard!$C10/12)^(1*12)-1)/(Dashboard!$C10/12),0) -> 428916.03 | D4: =I4+J4+K4+L4+M4 -> 13185 | E4: =E3+(D4-(C3-C4)) -> 42101.032 | F4: =(Dashboard!$C6-Dashboard!$C8)-C4 -> -28916.032 | G4: =G3+D4 -> 128185 | H4: =B4*(1-Dashboard!$C20)-C4 -> 57533.968 | I4: =IF(C3>0,Dashboard!$C26*12,0) -> 0 | J4: =B4*Dashboard!$C13 -> 6210 | K4: =Dashboard!$C14*12 -> 1800 | L4: =B4*Dashboard!$C16 -> 5175 | M4: =IF(Dashboard!$C7<0.2,C4*Dashboard!$C17,0) -> 0 | O4: =O3+T4 -> 30000 | P4: =T4+U4 -> 30240 | Q4: =Q3*(1+Dashboard!$F11)+Dashboard!$F28*12 -> 129600 | R4: =Dashboard!$F6*Dashboard!$F9+O4+U4*1 -> 35240 | S4: =Q4-MAX(Q4-(Dashboard!$C8+Dashboard!$C6*Dashboard!$C19+Dashboard!$F6*Dashboard!$F9),0)*Dashboard!$F12 -> 128160 | T4: =Dashboard!$F6*(1+Dashboard!$F7)^(1-1)*12 -> 30000 | U4: =Dashboard!$F8*12 -> 240
A5: 2 | B5: =B4*(1+Dashboard!$C21) -> 535612.5 | C5: =MAX((Dashboard!$C6-Dashboard!$C8)*(1+Dashboard!$C10/12)^(2*12)-Dashboard!$C26*((1+Dashboard!$C10/12)^(2*12)-1)/(Dashboard!$C10/12),0) -> 459922.41 | D5: =I5+J5+K5+L5+M5 -> 13583.475 | E5: =E4+(D5-(C4-C5)) -> 86690.882 | F5: =(Dashboard!$C6-Dashboard!$C8)-C5 -> -59922.407 | G5: =G4+D5 -> 141768.48 | H5: =B5*(1-Dashboard!$C20)-C5 -> 43553.343 | I5: =IF(C4>0,Dashboard!$C26*12,0) -> 0 | J5: =B5*Dashboard!$C13 -> 6427.35 | K5: =Dashboard!$C14*12 -> 1800 | L5: =B5*Dashboard!$C16 -> 5356.125 | M5: =IF(Dashboard!$C7<0.2,C5*Dashboard!$C17,0) -> 0 | O5: =O4+T5 -> 60900 | P5: =T5+U5 -> 31140 | Q5: =Q4*(1+Dashboard!$F11)+Dashboard!$F28*12 -> 139968 | R5: =Dashboard!$F6*Dashboard!$F9+O5+U5*2 -> 66380 | S5: =Q5-MAX(Q5-(Dashboard!$C8+Dashboard!$C6*Dashboard!$C19+Dashboard!$F6*Dashboard!$F9),0)*Dashboard!$F12 -> 136972.8 | T5: =Dashboard!$F6*(1+Dashboard!$F7)^(2-1)*12 -> 30900 | U5: =Dashboard!$F8*12 -> 240
A6: 3 | B6: =B5*(1+Dashboard!$C21) -> 554358.94 | C6: =MAX((Dashboard!$C6-Dashboard!$C8)*(1+Dashboard!$C10/12)^(3*12)-Dashboard!$C26*((1+Dashboard!$C10/12)^(3*12)-1)/(Dashboard!$C10/12),0) -> 493170.23 | D6: =I6+J6+K6+L6+M6 -> 13995.897 | E6: =E5+(D6-(C5-C6)) -> 133934.61 | F6: =(Dashboard!$C6-Dashboard!$C8)-C6 -> -93170.235 | G6: =G5+D6 -> 155764.37 | H6: =B6*(1-Dashboard!$C20)-C6 -> 27927.166 | I6: =IF(C5>0,Dashboard!$C26*12,0) -> 0 | J6: =B6*Dashboard!$C13 -> 6652.3072 | K6: =Dashboard!$C14*12 -> 1800 | L6: =B6*Dashboard!$C16 -> 5543.5894 | M6: =IF(Dashboard!$C7<0.2,C6*Dashboard!$C17,0) -> 0 | O6: =O5+T6 -> 92727 | P6: =T6+U6 -> 32067 | Q6: =Q5*(1+Dashboard!$F11)+Dashboard!$F28*12 -> 151165.44 | R6: =Dashboard!$F6*Dashboard!$F9+O6+U6*3 -> 98447 | S6: =Q6-MAX(Q6-(Dashboard!$C8+Dashboard!$C6*Dashboard!$C19+Dashboard!$F6*Dashboard!$F9),0)*Dashboard!$F12 -> 146490.62 | T6: =Dashboard!$F6*(1+Dashboard!$F7)^(3-1)*12 -> 31827 | U6: =Dashboard!$F8*12 -> 240
A7: 4 | B7: =B6*(1+Dashboard!$C21) -> 573761.5 | C7: =MAX((Dashboard!$C6-Dashboard!$C8)*(1+Dashboard!$C10/12)^(4*12)-Dashboard!$C26*((1+Dashboard!$C10/12)^(4*12)-1)/(Dashboard!$C10/12),0) -> 528821.55 | D7: =I7+J7+K7+L7+M7 -> 14422.753 | E7: =E6+(D7-(C6-C7)) -> 184008.68 | F7: =(Dashboard!$C6-Dashboard!$C8)-C7 -> -128821.55 | G7: =G6+D7 -> 170187.12 | H7: =B7*(1-Dashboard!$C20)-C7 -> 10514.259 | I7: =IF(C6>0,Dashboard!$C26*12,0) -> 0 | J7: =B7*Dashboard!$C13 -> 6885.138 | K7: =Dashboard!$C14*12 -> 1800 | L7: =B7*Dashboard!$C16 -> 5737.615 | M7: =IF(Dashboard!$C7<0.2,C7*Dashboard!$C17,0) -> 0 | O7: =O6+T7 -> 125508.81 | P7: =T7+U7 -> 33021.81 | Q7: =Q6*(1+Dashboard!$F11)+Dashboard!$F28*12 -> 163258.68 | R7: =Dashboard!$F6*Dashboard!$F9+O7+U7*4 -> 131468.81 | S7: =Q7-MAX(Q7-(Dashboard!$C8+Dashboard!$C6*Dashboard!$C19+Dashboard!$F6*Dashboard!$F9),0)*Dashboard!$F12 -> 156769.87 | T7: =Dashboard!$F6*(1+Dashboard!$F7)^(4-1)*12 -> 32781.81 | U7: =Dashboard!$F8*12 -> 240
A8: 5 | B8: =B7*(1+Dashboard!$C21) -> 593843.15 | C8: =MAX((Dashboard!$C6-Dashboard!$C8)*(1+Dashboard!$C10/12)^(5*12)-Dashboard!$C26*((1+Dashboard!$C10/12)^(5*12)-1)/(Dashboard!$C10/12),0) -> 567050.1 | D8: =I8+J8+K8+L8+M8 -> 14864.549 | E8: =E7+(D8-(C7-C8)) -> 237101.78 | F8: =(Dashboard!$C6-Dashboard!$C8)-C8 -> -167050.1 | G8: =G7+D8 -> 185051.67 | H8: =B8*(1-Dashboard!$C20)-C8 -> -8837.5402 | I8: =IF(C7>0,Dashboard!$C26*12,0) -> 0 | J8: =B8*Dashboard!$C13 -> 7126.1178 | K8: =Dashboard!$C14*12 -> 1800 | L8: =B8*Dashboard!$C16 -> 5938.4315 | M8: =IF(Dashboard!$C7<0.2,C8*Dashboard!$C17,0) -> 0 | O8: =O7+T8 -> 159274.07 | P8: =T8+U8 -> 34005.264 | Q8: =Q7*(1+Dashboard!$F11)+Dashboard!$F28*12 -> 176319.37 | R8: =Dashboard!$F6*Dashboard!$F9+O8+U8*5 -> 165474.07 | S8: =Q8-MAX(Q8-(Dashboard!$C8+Dashboard!$C6*Dashboard!$C19+Dashboard!$F6*Dashboard!$F9),0)*Dashboard!$F12 -> 167871.46 | T8: =Dashboard!$F6*(1+Dashboard!$F7)^(5-1)*12 -> 33765.264 | U8: =Dashboard!$F8*12 -> 240
A9: 6 | B9: =B8*(1+Dashboard!$C21) -> 614627.66 | C9: =MAX((Dashboard!$C6-Dashboard!$C8)*(1+Dashboard!$C10/12)^(6*12)-Dashboard!$C26*((1+Dashboard!$C10/12)^(6*12)-1)/(Dashboard!$C10/12),0) -> 608042.2 | D9: =I9+J9+K9+L9+M9 -> 15321.809 | E9: =E8+(D9-(C8-C9)) -> 293415.68 | F9: =(Dashboard!$C6-Dashboard!$C8)-C9 -> -208042.2 | G9: =G8+D9 -> 200373.48 | H9: =B9*(1-Dashboard!$C20)-C9 -> -30292.198 | I9: =IF(C8>0,Dashboard!$C26*12,0) -> 0 | J9: =B9*Dashboard!$C13 -> 7375.532 | K9: =Dashboard!$C14*12 -> 1800 | L9: =B9*Dashboard!$C16 -> 6146.2766 | M9: =IF(Dashboard!$C7<0.2,C9*Dashboard!$C17,0) -> 0 | O9: =O8+T9 -> 194052.3 | P9: =T9+U9 -> 35018.222 | Q9: =Q8*(1+Dashboard!$F11)+Dashboard!$F28*12 -> 190424.92 | R9: =Dashboard!$F6*Dashboard!$F9+O9+U9*6 -> 200492.3 | S9: =Q9-MAX(Q9-(Dashboard!$C8+Dashboard!$C6*Dashboard!$C19+Dashboard!$F6*Dashboard!$F9),0)*Dashboard!$F12 -> 179861.18 | T9: =Dashboard!$F6*(1+Dashboard!$F7)^(6-1)*12 -> 34778.222 | U9: =Dashboard!$F8*12 -> 240
A10: 7 | B10: =B9*(1+Dashboard!$C21) -> 636139.63 | C10: =MAX((Dashboard!$C6-Dashboard!$C8)*(1+Dashboard!$C10/12)^(7*12)-Dashboard!$C26*((1+Dashboard!$C10/12)^(7*12)-1)/(Dashboard!$C10/12),0) -> 651997.62 | D10: =I10+J10+K10+L10+M10 -> 15795.072 | E10: =E9+(D10-(C9-C10)) -> 353166.18 | F10: =(Dashboard!$C6-Dashboard!$C8)-C10 -> -251997.62 | G10: =G9+D10 -> 216168.55 | H10: =B10*(1-Dashboard!$C20)-C10 -> -54026.368 | I10: =IF(C9>0,Dashboard!$C26*12,0) -> 0 | J10: =B10*Dashboard!$C13 -> 7633.6756 | K10: =Dashboard!$C14*12 -> 1800 | L10: =B10*Dashboard!$C16 -> 6361.3963 | M10: =IF(Dashboard!$C7<0.2,C10*Dashboard!$C17,0) -> 0 | O10: =O9+T10 -> 229873.87 | P10: =T10+U10 -> 36061.569 | Q10: =Q9*(1+Dashboard!$F11)+Dashboard!$F28*12 -> 205658.91 | R10: =Dashboard!$F6*Dashboard!$F9+O10+U10*7 -> 236553.87 | S10: =Q10-MAX(Q10-(Dashboard!$C8+Dashboard!$C6*Dashboard!$C19+Dashboard!$F6*Dashboard!$F9),0)*Dashboard!$F12 -> 192810.08 | T10: =Dashboard!$F6*(1+Dashboard!$F7)^(7-1)*12 -> 35821.569 | U10: =Dashboard!$F8*12 -> 240
A11: 8 | B11: =B10*(1+Dashboard!$C21) -> 658404.52 | C11: =MAX((Dashboard!$C6-Dashboard!$C8)*(1+Dashboard!$C10/12)^(8*12)-Dashboard!$C26*((1+Dashboard!$C10/12)^(8*12)-1)/(Dashboard!$C10/12),0) -> 699130.58 | D11: =I11+J11+K11+L11+M11 -> 16284.899 | E11: =E10+(D11-(C10-C11)) -> 416584.04 | F11: =(Dashboard!$C6-Dashboard!$C8)-C11 -> -299130.58 | G11: =G10+D11 -> 232453.45 | H11: =B11*(1-Dashboard!$C20)-C11 -> -80230.335 | I11: =IF(C10>0,Dashboard!$C26*12,0) -> 0 | J11: =B11*Dashboard!$C13 -> 7900.8542 | K11: =Dashboard!$C14*12 -> 1800 | L11: =B11*Dashboard!$C16 -> 6584.0452 | M11: =IF(Dashboard!$C7<0.2,C11*Dashboard!$C17,0) -> 0 | O11: =O10+T11 -> 266770.08 | P11: =T11+U11 -> 37136.216 | Q11: =Q10*(1+Dashboard!$F11)+Dashboard!$F28*12 -> 222111.63 | R11: =Dashboard!$F6*Dashboard!$F9+O11+U11*8 -> 273690.08 | S11: =Q11-MAX(Q11-(Dashboard!$C8+Dashboard!$C6*Dashboard!$C19+Dashboard!$F6*Dashboard!$F9),0)*Dashboard!$F12 -> 206794.88 | T11: =Dashboard!$F6*(1+Dashboard!$F7)^(8-1)*12 -> 36896.216 | U11: =Dashboard!$F8*12 -> 240
A12: 9 | B12: =B11*(1+Dashboard!$C21) -> 681448.68 | C12: =MAX((Dashboard!$C6-Dashboard!$C8)*(1+Dashboard!$C10/12)^(9*12)-Dashboard!$C26*((1+Dashboard!$C10/12)^(9*12)-1)/(Dashboard!$C10/12),0) -> 749670.79 | D12: =I12+J12+K12+L12+M12 -> 16791.871 | E12: =E11+(D12-(C11-C12)) -> 483916.11 | F12: =(Dashboard!$C6-Dashboard!$C8)-C12 -> -349670.79 | G12: =G11+D12 -> 249245.32 | H12: =B12*(1-Dashboard!$C20)-C12 -> -109109.03 | I12: =IF(C11>0,Dashboard!$C26*12,0) -> 0 | J12: =B12*Dashboard!$C13 -> 8177.3841 | K12: =Dashboard!$C14*12 -> 1800 | L12: =B12*Dashboard!$C16 -> 6814.4868 | M12: =IF(Dashboard!$C7<0.2,C12*Dashboard!$C17,0) -> 0 | O12: =O11+T12 -> 304773.18 | P12: =T12+U12 -> 38243.102 | Q12: =Q11*(1+Dashboard!$F11)+Dashboard!$F28*12 -> 239880.56 | R12: =Dashboard!$F6*Dashboard!$F9+O12+U12*9 -> 311933.18 | S12: =Q12-MAX(Q12-(Dashboard!$C8+Dashboard!$C6*Dashboard!$C19+Dashboard!$F6*Dashboard!$F9),0)*Dashboard!$F12 -> 221898.47 | T12: =Dashboard!$F6*(1+Dashboard!$F7)^(9-1)*12 -> 38003.102 | U12: =Dashboard!$F8*12 -> 240
A13: 10 | B13: =B12*(1+Dashboard!$C21) -> 705299.38 | C13: =MAX((Dashboard!$C6-Dashboard!$C8)*(1+Dashboard!$C10/12)^(10*12)-Dashboard!$C26*((1+Dashboard!$C10/12)^(10*12)-1)/(Dashboard!$C10/12),0) -> 803864.55 | D13: =I13+J13+K13+L13+M13 -> 17316.586 | E13: =E12+(D13-(C12-C13)) -> 555426.46 | F13: =(Dashboard!$C6-Dashboard!$C8)-C13 -> -403864.55 | G13: =G12+D13 -> 266561.91 | H13: =B13*(1-Dashboard!$C20)-C13 -> -140883.13 | I13: =IF(C12>0,Dashboard!$C26*12,0) -> 0 | J13: =B13*Dashboard!$C13 -> 8463.5926 | K13: =Dashboard!$C14*12 -> 1800 | L13: =B13*Dashboard!$C16 -> 7052.9938 | M13: =IF(Dashboard!$C7<0.2,C13*Dashboard!$C17,0) -> 0 | O13: =O12+T13 -> 343916.38 | P13: =T13+U13 -> 39383.196 | Q13: =Q12*(1+Dashboard!$F11)+Dashboard!$F28*12 -> 259071 | R13: =Dashboard!$F6*Dashboard!$F9+O13+U13*10 -> 351316.38 | S13: =Q13-MAX(Q13-(Dashboard!$C8+Dashboard!$C6*Dashboard!$C19+Dashboard!$F6*Dashboard!$F9),0)*Dashboard!$F12 -> 238210.35 | T13: =Dashboard!$F6*(1+Dashboard!$F7)^(10-1)*12 -> 39143.196 | U13: =Dashboard!$F8*12 -> 240
A14: 11 | B14: =B13*(1+Dashboard!$C21) -> 729984.86 | C14: =MAX((Dashboard!$C6-Dashboard!$C8)*(1+Dashboard!$C10/12)^(11*12)-Dashboard!$C26*((1+Dashboard!$C10/12)^(11*12)-1)/(Dashboard!$C10/12),0) -> 861975.98 | D14: =I14+J14+K14+L14+M14 -> 17859.667 | E14: =E13+(D14-(C13-C14)) -> 631397.56 | F14: =(Dashboard!$C6-Dashboard!$C8)-C14 -> -461975.98 | G14: =G13+D14 -> 284421.58 | H14: =B14*(1-Dashboard!$C20)-C14 -> -175790.22 | I14: =IF(C13>0,Dashboard!$C26*12,0) -> 0 | J14: =B14*Dashboard!$C13 -> 8759.8183 | K14: =Dashboard!$C14*12 -> 1800 | L14: =B14*Dashboard!$C16 -> 7299.8486 | M14: =IF(Dashboard!$C7<0.2,C14*Dashboard!$C17,0) -> 0 | O14: =O13+T14 -> 384233.87 | P14: =T14+U14 -> 40557.491 | Q14: =Q13*(1+Dashboard!$F11)+Dashboard!$F28*12 -> 279796.68 | R14: =Dashboard!$F6*Dashboard!$F9+O14+U14*11 -> 391873.87 | S14: =Q14-MAX(Q14-(Dashboard!$C8+Dashboard!$C6*Dashboard!$C19+Dashboard!$F6*Dashboard!$F9),0)*Dashboard!$F12 -> 255827.18 | T14: =Dashboard!$F6*(1+Dashboard!$F7)^(11-1)*12 -> 40317.491 | U14: =Dashboard!$F8*12 -> 240
A15: 12 | B15: =B14*(1+Dashboard!$C21) -> 755534.33 | C15: =MAX((Dashboard!$C6-Dashboard!$C8)*(1+Dashboard!$C10/12)^(12*12)-Dashboard!$C26*((1+Dashboard!$C10/12)^(12*12)-1)/(Dashboard!$C10/12),0) -> 924288.3 | D15: =I15+J15+K15+L15+M15 -> 18421.755 | E15: =E14+(D15-(C14-C15)) -> 712131.63 | F15: =(Dashboard!$C6-Dashboard!$C8)-C15 -> -524288.3 | G15: =G14+D15 -> 302843.33 | H15: =B15*(1-Dashboard!$C20)-C15 -> -214086.03 | I15: =IF(C14>0,Dashboard!$C26*12,0) -> 0 | J15: =B15*Dashboard!$C13 -> 9066.4119 | K15: =Dashboard!$C14*12 -> 1800 | L15: =B15*Dashboard!$C16 -> 7555.3433 | M15: =IF(Dashboard!$C7<0.2,C15*Dashboard!$C17,0) -> 0 | O15: =O14+T15 -> 425760.89 | P15: =T15+U15 -> 41767.016 | Q15: =Q14*(1+Dashboard!$F11)+Dashboard!$F28*12 -> 302180.41 | R15: =Dashboard!$F6*Dashboard!$F9+O15+U15*12 -> 433640.89 | S15: =Q15-MAX(Q15-(Dashboard!$C8+Dashboard!$C6*Dashboard!$C19+Dashboard!$F6*Dashboard!$F9),0)*Dashboard!$F12 -> 274853.35 | T15: =Dashboard!$F6*(1+Dashboard!$F7)^(12-1)*12 -> 41527.016 | U15: =Dashboard!$F8*12 -> 240
A16: 13 | B16: =B15*(1+Dashboard!$C21) -> 781978.03 | C16: =MAX((Dashboard!$C6-Dashboard!$C8)*(1+Dashboard!$C10/12)^(13*12)-Dashboard!$C26*((1+Dashboard!$C10/12)^(13*12)-1)/(Dashboard!$C10/12),0) -> 991105.17 | D16: =I16+J16+K16+L16+M16 -> 19003.517 | E16: =E15+(D16-(C15-C16)) -> 797952.02 | F16: =(Dashboard!$C6-Dashboard!$C8)-C16 -> -591105.17 | G16: =G15+D16 -> 321846.85 | H16: =B16*(1-Dashboard!$C20)-C16 -> -256045.83 | I16: =IF(C15>0,Dashboard!$C26*12,0) -> 0 | J16: =B16*Dashboard!$C13 -> 9383.7364 | K16: =Dashboard!$C14*12 -> 1800 | L16: =B16*Dashboard!$C16 -> 7819.7803 | M16: =IF(Dashboard!$C7<0.2,C16*Dashboard!$C17,0) -> 0 | O16: =O15+T16 -> 468533.71 | P16: =T16+U16 -> 43012.827 | Q16: =Q15*(1+Dashboard!$F11)+Dashboard!$F28*12 -> 326354.85 | R16: =Dashboard!$F6*Dashboard!$F9+O16+U16*13 -> 476653.71 | S16: =Q16-MAX(Q16-(Dashboard!$C8+Dashboard!$C6*Dashboard!$C19+Dashboard!$F6*Dashboard!$F9),0)*Dashboard!$F12 -> 295401.62 | T16: =Dashboard!$F6*(1+Dashboard!$F7)^(13-1)*12 -> 42772.827 | U16: =Dashboard!$F8*12 -> 240
A17: 14 | B17: =B16*(1+Dashboard!$C21) -> 809347.26 | C17: =MAX((Dashboard!$C6-Dashboard!$C8)*(1+Dashboard!$C10/12)^(14*12)-Dashboard!$C26*((1+Dashboard!$C10/12)^(14*12)-1)/(Dashboard!$C10/12),0) -> 1062752.2 | D17: =I17+J17+K17+L17+M17 -> 19605.64 | E17: =E16+(D17-(C16-C17)) -> 889204.74 | F17: =(Dashboard!$C6-Dashboard!$C8)-C17 -> -662752.25 | G17: =G16+D17 -> 341452.49 | H17: =B17*(1-Dashboard!$C20)-C17 -> -301965.82 | I17: =IF(C16>0,Dashboard!$C26*12,0) -> 0 | J17: =B17*Dashboard!$C13 -> 9712.1671 | K17: =Dashboard!$C14*12 -> 1800 | L17: =B17*Dashboard!$C16 -> 8093.4726 | M17: =IF(Dashboard!$C7<0.2,C17*Dashboard!$C17,0) -> 0 | O17: =O16+T17 -> 512589.72 | P17: =T17+U17 -> 44296.011 | Q17: =Q16*(1+Dashboard!$F11)+Dashboard!$F28*12 -> 352463.23 | R17: =Dashboard!$F6*Dashboard!$F9+O17+U17*14 -> 520949.72 | S17: =Q17-MAX(Q17-(Dashboard!$C8+Dashboard!$C6*Dashboard!$C19+Dashboard!$F6*Dashboard!$F9),0)*Dashboard!$F12 -> 317593.75 | T17: =Dashboard!$F6*(1+Dashboard!$F7)^(14-1)*12 -> 44056.011 | U17: =Dashboard!$F8*12 -> 240
A18: 15 | B18: =B17*(1+Dashboard!$C21) -> 837674.42 | C18: =MAX((Dashboard!$C6-Dashboard!$C8)*(1+Dashboard!$C10/12)^(15*12)-Dashboard!$C26*((1+Dashboard!$C10/12)^(15*12)-1)/(Dashboard!$C10/12),0) -> 1139578.7 | D18: =I18+J18+K18+L18+M18 -> 20228.837 | E18: =E17+(D18-(C17-C18)) -> 986260.02 | F18: =(Dashboard!$C6-Dashboard!$C8)-C18 -> -739578.69 | G18: =G17+D18 -> 361681.33 | H18: =B18*(1-Dashboard!$C20)-C18 -> -352164.74 | I18: =IF(C17>0,Dashboard!$C26*12,0) -> 0 | J18: =B18*Dashboard!$C13 -> 10052.093 | K18: =Dashboard!$C14*12 -> 1800 | L18: =B18*Dashboard!$C16 -> 8376.7442 | M18: =IF(Dashboard!$C7<0.2,C18*Dashboard!$C17,0) -> 0 | O18: =O17+T18 -> 557967.42 | P18: =T18+U18 -> 45617.692 | Q18: =Q17*(1+Dashboard!$F11)+Dashboard!$F28*12 -> 380660.29 | R18: =Dashboard!$F6*Dashboard!$F9+O18+U18*15 -> 566567.42 | S18: =Q18-MAX(Q18-(Dashboard!$C8+Dashboard!$C6*Dashboard!$C19+Dashboard!$F6*Dashboard!$F9),0)*Dashboard!$F12 -> 341561.25 | T18: =Dashboard!$F6*(1+Dashboard!$F7)^(15-1)*12 -> 45377.692 | U18: =Dashboard!$F8*12 -> 240
A19: 16 | B19: =B18*(1+Dashboard!$C21) -> 866993.02 | C19: =MAX((Dashboard!$C6-Dashboard!$C8)*(1+Dashboard!$C10/12)^(16*12)-Dashboard!$C26*((1+Dashboard!$C10/12)^(16*12)-1)/(Dashboard!$C10/12),0) -> 1221958.9 | D19: =I19+J19+K19+L19+M19 -> 20873.846 | E19: =E18+(D19-(C18-C19)) -> 1089514.1 | F19: =(Dashboard!$C6-Dashboard!$C8)-C19 -> -821958.93 | G19: =G18+D19 -> 382555.17 | H19: =B19*(1-Dashboard!$C20)-C19 -> -406985.49 | I19: =IF(C18>0,Dashboard!$C26*12,0) -> 0 | J19: =B19*Dashboard!$C13 -> 10403.916 | K19: =Dashboard!$C14*12 -> 1800 | L19: =B19*Dashboard!$C16 -> 8669.9302 | M19: =IF(Dashboard!$C7<0.2,C19*Dashboard!$C17,0) -> 0 | O19: =O18+T19 -> 604706.44 | P19: =T19+U19 -> 46979.022 | Q19: =Q18*(1+Dashboard!$F11)+Dashboard!$F28*12 -> 411113.12 | R19: =Dashboard!$F6*Dashboard!$F9+O19+U19*16 -> 613546.44 | S19: =Q19-MAX(Q19-(Dashboard!$C8+Dashboard!$C6*Dashboard!$C19+Dashboard!$F6*Dashboard!$F9),0)*Dashboard!$F12 -> 367446.15 | T19: =Dashboard!$F6*(1+Dashboard!$F7)^(16-1)*12 -> 46739.022 | U19: =Dashboard!$F8*12 -> 240
A20: 17 | B20: =B19*(1+Dashboard!$C21) -> 897337.78 | C20: =MAX((Dashboard!$C6-Dashboard!$C8)*(1+Dashboard!$C10/12)^(17*12)-Dashboard!$C26*((1+Dashboard!$C10/12)^(17*12)-1)/(Dashboard!$C10/12),0) -> 1310294.4 | D20: =I20+J20+K20+L20+M20 -> 21541.431 | E20: =E19+(D20-(C19-C20)) -> 1199391 | F20: =(Dashboard!$C6-Dashboard!$C8)-C20 -> -910294.44 | G20: =G19+D20 -> 404096.6 | H20: =B20*(1-Dashboard!$C20)-C20 -> -466796.93 | I20: =IF(C19>0,Dashboard!$C26*12,0) -> 0 | J20: =B20*Dashboard!$C13 -> 10768.053 | K20: =Dashboard!$C14*12 -> 1800 | L20: =B20*Dashboard!$C16 -> 8973.3778 | M20: =IF(Dashboard!$C7<0.2,C20*Dashboard!$C17,0) -> 0 | O20: =O19+T20 -> 652847.63 | P20: =T20+U20 -> 48381.193 | Q20: =Q19*(1+Dashboard!$F11)+Dashboard!$F28*12 -> 444002.17 | R20: =Dashboard!$F6*Dashboard!$F9+O20+U20*17 -> 661927.63 | S20: =Q20-MAX(Q20-(Dashboard!$C8+Dashboard!$C6*Dashboard!$C19+Dashboard!$F6*Dashboard!$F9),0)*Dashboard!$F12 -> 395401.84 | T20: =Dashboard!$F6*(1+Dashboard!$F7)^(17-1)*12 -> 48141.193 | U20: =Dashboard!$F8*12 -> 240
A21: 18 | B21: =B20*(1+Dashboard!$C21) -> 928744.6 | C21: =MAX((Dashboard!$C6-Dashboard!$C8)*(1+Dashboard!$C10/12)^(18*12)-Dashboard!$C26*((1+Dashboard!$C10/12)^(18*12)-1)/(Dashboard!$C10/12),0) -> 1405015.7 | D21: =I21+J21+K21+L21+M21 -> 22232.381 | E21: =E20+(D21-(C20-C21)) -> 1316344.7 | F21: =(Dashboard!$C6-Dashboard!$C8)-C21 -> -1005015.7 | G21: =G20+D21 -> 426328.99 | H21: =B21*(1-Dashboard!$C20)-C21 -> -531995.81 | I21: =IF(C20>0,Dashboard!$C26*12,0) -> 0 | J21: =B21*Dashboard!$C13 -> 11144.935 | K21: =Dashboard!$C14*12 -> 1800 | L21: =B21*Dashboard!$C16 -> 9287.446 | M21: =IF(Dashboard!$C7<0.2,C21*Dashboard!$C17,0) -> 0 | O21: =O20+T21 -> 702433.06 | P21: =T21+U21 -> 49825.429 | Q21: =Q20*(1+Dashboard!$F11)+Dashboard!$F28*12 -> 479522.34 | R21: =Dashboard!$F6*Dashboard!$F9+O21+U21*18 -> 711753.06 | S21: =Q21-MAX(Q21-(Dashboard!$C8+Dashboard!$C6*Dashboard!$C19+Dashboard!$F6*Dashboard!$F9),0)*Dashboard!$F12 -> 425593.99 | T21: =Dashboard!$F6*(1+Dashboard!$F7)^(18-1)*12 -> 49585.429 | U21: =Dashboard!$F8*12 -> 240
A22: 19 | B22: =B21*(1+Dashboard!$C21) -> 961250.66 | C22: =MAX((Dashboard!$C6-Dashboard!$C8)*(1+Dashboard!$C10/12)^(19*12)-Dashboard!$C26*((1+Dashboard!$C10/12)^(19*12)-1)/(Dashboard!$C10/12),0) -> 1506584.4 | D22: =I22+J22+K22+L22+M22 -> 22947.514 | E22: =E21+(D22-(C21-C22)) -> 1440860.9 | F22: =(Dashboard!$C6-Dashboard!$C8)-C22 -> -1106584.4 | G22: =G21+D22 -> 449276.5 | H22: =B22*(1-Dashboard!$C20)-C22 -> -603008.81 | I22: =IF(C21>0,Dashboard!$C26*12,0) -> 0 | J22: =B22*Dashboard!$C13 -> 11535.008 | K22: =Dashboard!$C14*12 -> 1800 | L22: =B22*Dashboard!$C16 -> 9612.5066 | M22: =IF(Dashboard!$C7<0.2,C22*Dashboard!$C17,0) -> 0 | O22: =O21+T22 -> 753506.05 | P22: =T22+U22 -> 51312.992 | Q22: =Q21*(1+Dashboard!$F11)+Dashboard!$F28*12 -> 517884.13 | R22: =Dashboard!$F6*Dashboard!$F9+O22+U22*19 -> 763066.05 | S22: =Q22-MAX(Q22-(Dashboard!$C8+Dashboard!$C6*Dashboard!$C19+Dashboard!$F6*Dashboard!$F9),0)*Dashboard!$F12 -> 458201.51 | T22: =Dashboard!$F6*(1+Dashboard!$F7)^(19-1)*12 -> 51072.992 | U22: =Dashboard!$F8*12 -> 240
A23: 20 | B23: =B22*(1+Dashboard!$C21) -> 994894.43 | C23: =MAX((Dashboard!$C6-Dashboard!$C8)*(1+Dashboard!$C10/12)^(20*12)-Dashboard!$C26*((1+Dashboard!$C10/12)^(20*12)-1)/(Dashboard!$C10/12),0) -> 1615495.5 | D23: =I23+J23+K23+L23+M23 -> 23687.677 | E23: =E22+(D23-(C22-C23)) -> 1573459.7 | F23: =(Dashboard!$C6-Dashboard!$C8)-C23 -> -1215495.5 | G23: =G22+D23 -> 472964.18 | H23: =B23*(1-Dashboard!$C20)-C23 -> -680294.77 | I23: =IF(C22>0,Dashboard!$C26*12,0) -> 0 | J23: =B23*Dashboard!$C13 -> 11938.733 | K23: =Dashboard!$C14*12 -> 1800 | L23: =B23*Dashboard!$C16 -> 9948.9443 | M23: =IF(Dashboard!$C7<0.2,C23*Dashboard!$C17,0) -> 0 | O23: =O22+T23 -> 806111.23 | P23: =T23+U23 -> 52845.182 | Q23: =Q22*(1+Dashboard!$F11)+Dashboard!$F28*12 -> 559314.86 | R23: =Dashboard!$F6*Dashboard!$F9+O23+U23*20 -> 815911.23 | S23: =Q23-MAX(Q23-(Dashboard!$C8+Dashboard!$C6*Dashboard!$C19+Dashboard!$F6*Dashboard!$F9),0)*Dashboard!$F12 -> 493417.63 | T23: =Dashboard!$F6*(1+Dashboard!$F7)^(20-1)*12 -> 52605.182 | U23: =Dashboard!$F8*12 -> 240
A24: 21 | B24: =B23*(1+Dashboard!$C21) -> 1029715.7 | C24: =MAX((Dashboard!$C6-Dashboard!$C8)*(1+Dashboard!$C10/12)^(21*12)-Dashboard!$C26*((1+Dashboard!$C10/12)^(21*12)-1)/(Dashboard!$C10/12),0) -> 1732279.8 | D24: =I24+J24+K24+L24+M24 -> 24453.746 | E24: =E23+(D24-(C23-C24)) -> 1714697.8 | F24: =(Dashboard!$C6-Dashboard!$C8)-C24 -> -1332279.8 | G24: =G23+D24 -> 497417.92 | H24: =B24*(1-Dashboard!$C20)-C24 -> -764347.05 | I24: =IF(C23>0,Dashboard!$C26*12,0) -> 0 | J24: =B24*Dashboard!$C13 -> 12356.589 | K24: =Dashboard!$C14*12 -> 1800 | L24: =B24*Dashboard!$C16 -> 10297.157 | M24: =IF(Dashboard!$C7<0.2,C24*Dashboard!$C17,0) -> 0 | O24: =O23+T24 -> 860294.57 | P24: =T24+U24 -> 54423.337 | Q24: =Q23*(1+Dashboard!$F11)+Dashboard!$F28*12 -> 604060.05 | R24: =Dashboard!$F6*Dashboard!$F9+O24+U24*21 -> 870334.57 | S24: =Q24-MAX(Q24-(Dashboard!$C8+Dashboard!$C6*Dashboard!$C19+Dashboard!$F6*Dashboard!$F9),0)*Dashboard!$F12 -> 531451.04 | T24: =Dashboard!$F6*(1+Dashboard!$F7)^(21-1)*12 -> 54183.337 | U24: =Dashboard!$F8*12 -> 240
A25: 22 | B25: =B24*(1+Dashboard!$C21) -> 1065755.8 | C25: =MAX((Dashboard!$C6-Dashboard!$C8)*(1+Dashboard!$C10/12)^(22*12)-Dashboard!$C26*((1+Dashboard!$C10/12)^(22*12)-1)/(Dashboard!$C10/12),0) -> 1857506.5 | D25: =I25+J25+K25+L25+M25 -> 25246.627 | E25: =E24+(D25-(C24-C25)) -> 1865171 | F25: =(Dashboard!$C6-Dashboard!$C8)-C25 -> -1457506.5 | G25: =G24+D25 -> 522664.55 | H25: =B25*(1-Dashboard!$C20)-C25 -> -855696.05 | I25: =IF(C24>0,Dashboard!$C26*12,0) -> 0 | J25: =B25*Dashboard!$C13 -> 12789.069 | K25: =Dashboard!$C14*12 -> 1800 | L25: =B25*Dashboard!$C16 -> 10657.558 | M25: =IF(Dashboard!$C7<0.2,C25*Dashboard!$C17,0) -> 0 | O25: =O24+T25 -> 916103.41 | P25: =T25+U25 -> 56048.837 | Q25: =Q24*(1+Dashboard!$F11)+Dashboard!$F28*12 -> 652384.85 | R25: =Dashboard!$F6*Dashboard!$F9+O25+U25*22 -> 926383.41 | S25: =Q25-MAX(Q25-(Dashboard!$C8+Dashboard!$C6*Dashboard!$C19+Dashboard!$F6*Dashboard!$F9),0)*Dashboard!$F12 -> 572527.12 | T25: =Dashboard!$F6*(1+Dashboard!$F7)^(22-1)*12 -> 55808.837 | U25: =Dashboard!$F8*12 -> 240
A26: 23 | B26: =B25*(1+Dashboard!$C21) -> 1103057.2 | C26: =MAX((Dashboard!$C6-Dashboard!$C8)*(1+Dashboard!$C10/12)^(23*12)-Dashboard!$C26*((1+Dashboard!$C10/12)^(23*12)-1)/(Dashboard!$C10/12),0) -> 1991785.8 | D26: =I26+J26+K26+L26+M26 -> 26067.259 | E26: =E25+(D26-(C25-C26)) -> 2025517.6 | F26: =(Dashboard!$C6-Dashboard!$C8)-C26 -> -1591785.8 | G26: =G25+D26 -> 548731.81 | H26: =B26*(1-Dashboard!$C20)-C26 -> -954911.98 | I26: =IF(C25>0,Dashboard!$C26*12,0) -> 0 | J26: =B26*Dashboard!$C13 -> 13236.687 | K26: =Dashboard!$C14*12 -> 1800 | L26: =B26*Dashboard!$C16 -> 11030.572 | M26: =IF(Dashboard!$C7<0.2,C26*Dashboard!$C17,0) -> 0 | O26: =O25+T26 -> 973586.51 | P26: =T26+U26 -> 57723.102 | Q26: =Q25*(1+Dashboard!$F11)+Dashboard!$F28*12 -> 704575.64 | R26: =Dashboard!$F6*Dashboard!$F9+O26+U26*23 -> 984106.51 | S26: =Q26-MAX(Q26-(Dashboard!$C8+Dashboard!$C6*Dashboard!$C19+Dashboard!$F6*Dashboard!$F9),0)*Dashboard!$F12 -> 616889.29 | T26: =Dashboard!$F6*(1+Dashboard!$F7)^(23-1)*12 -> 57483.102 | U26: =Dashboard!$F8*12 -> 240
A27: 24 | B27: =B26*(1+Dashboard!$C21) -> 1141664.2 | C27: =MAX((Dashboard!$C6-Dashboard!$C8)*(1+Dashboard!$C10/12)^(24*12)-Dashboard!$C26*((1+Dashboard!$C10/12)^(24*12)-1)/(Dashboard!$C10/12),0) -> 2135772.1 | D27: =I27+J27+K27+L27+M27 -> 26916.613 | E27: =E26+(D27-(C26-C27)) -> 2196420.6 | F27: =(Dashboard!$C6-Dashboard!$C8)-C27 -> -1735772.1 | G27: =G26+D27 -> 575648.42 | H27: =B27*(1-Dashboard!$C20)-C27 -> -1062607.8 | I27: =IF(C26>0,Dashboard!$C26*12,0) -> 0 | J27: =B27*Dashboard!$C13 -> 13699.971 | K27: =Dashboard!$C14*12 -> 1800 | L27: =B27*Dashboard!$C16 -> 11416.642 | M27: =IF(Dashboard!$C7<0.2,C27*Dashboard!$C17,0) -> 0 | O27: =O26+T27 -> 1032794.1 | P27: =T27+U27 -> 59447.595 | Q27: =Q26*(1+Dashboard!$F11)+Dashboard!$F28*12 -> 760941.69 | R27: =Dashboard!$F6*Dashboard!$F9+O27+U27*24 -> 1043554.1 | S27: =Q27-MAX(Q27-(Dashboard!$C8+Dashboard!$C6*Dashboard!$C19+Dashboard!$F6*Dashboard!$F9),0)*Dashboard!$F12 -> 664800.44 | T27: =Dashboard!$F6*(1+Dashboard!$F7)^(24-1)*12 -> 59207.595 | U27: =Dashboard!$F8*12 -> 240
A28: 25 | B28: =B27*(1+Dashboard!$C21) -> 1181622.5 | C28: =MAX((Dashboard!$C6-Dashboard!$C8)*(1+Dashboard!$C10/12)^(25*12)-Dashboard!$C26*((1+Dashboard!$C10/12)^(25*12)-1)/(Dashboard!$C10/12),0) -> 2290167.3 | D28: =I28+J28+K28+L28+M28 -> 27795.695 | E28: =E27+(D28-(C27-C28)) -> 2378611.4 | F28: =(Dashboard!$C6-Dashboard!$C8)-C28 -> -1890167.3 | G28: =G27+D28 -> 603444.12 | H28: =B28*(1-Dashboard!$C20)-C28 -> -1179442.1 | I28: =IF(C27>0,Dashboard!$C26*12,0) -> 0 | J28: =B28*Dashboard!$C13 -> 14179.47 | K28: =Dashboard!$C14*12 -> 1800 | L28: =B28*Dashboard!$C16 -> 11816.225 | M28: =IF(Dashboard!$C7<0.2,C28*Dashboard!$C17,0) -> 0 | O28: =O27+T28 -> 1093777.9 | P28: =T28+U28 -> 61223.823 | Q28: =Q27*(1+Dashboard!$F11)+Dashboard!$F28*12 -> 821817.02 | R28: =Dashboard!$F6*Dashboard!$F9+O28+U28*25 -> 1104777.9 | S28: =Q28-MAX(Q28-(Dashboard!$C8+Dashboard!$C6*Dashboard!$C19+Dashboard!$F6*Dashboard!$F9),0)*Dashboard!$F12 -> 716544.47 | T28: =Dashboard!$F6*(1+Dashboard!$F7)^(25-1)*12 -> 60983.823 | U28: =Dashboard!$F8*12 -> 240
A29: 26 | B29: =B28*(1+Dashboard!$C21) -> 1222979.3 | C29: =MAX((Dashboard!$C6-Dashboard!$C8)*(1+Dashboard!$C10/12)^(26*12)-Dashboard!$C26*((1+Dashboard!$C10/12)^(26*12)-1)/(Dashboard!$C10/12),0) -> 2455723.7 | D29: =I29+J29+K29+L29+M29 -> 28705.544 | E29: =E28+(D29-(C28-C29)) -> 2572873.3 | F29: =(Dashboard!$C6-Dashboard!$C8)-C29 -> -2055723.7 | G29: =G28+D29 -> 632149.66 | H29: =B29*(1-Dashboard!$C20)-C29 -> -1306123.1 | I29: =IF(C28>0,Dashboard!$C26*12,0) -> 0 | J29: =B29*Dashboard!$C13 -> 14675.751 | K29: =Dashboard!$C14*12 -> 1800 | L29: =B29*Dashboard!$C16 -> 12229.793 | M29: =IF(Dashboard!$C7<0.2,C29*Dashboard!$C17,0) -> 0 | O29: =O28+T29 -> 1156591.3 | P29: =T29+U29 -> 63053.338 | Q29: =Q28*(1+Dashboard!$F11)+Dashboard!$F28*12 -> 887562.39 | R29: =Dashboard!$F6*Dashboard!$F9+O29+U29*26 -> 1167831.3 | S29: =Q29-MAX(Q29-(Dashboard!$C8+Dashboard!$C6*Dashboard!$C19+Dashboard!$F6*Dashboard!$F9),0)*Dashboard!$F12 -> 772428.03 | T29: =Dashboard!$F6*(1+Dashboard!$F7)^(26-1)*12 -> 62813.338 | U29: =Dashboard!$F8*12 -> 240
A30: 27 | B30: =B29*(1+Dashboard!$C21) -> 1265783.6 | C30: =MAX((Dashboard!$C6-Dashboard!$C8)*(1+Dashboard!$C10/12)^(27*12)-Dashboard!$C26*((1+Dashboard!$C10/12)^(27*12)-1)/(Dashboard!$C10/12),0) -> 2633248.1 | D30: =I30+J30+K30+L30+M30 -> 29647.238 | E30: =E29+(D30-(C29-C30)) -> 2780045 | F30: =(Dashboard!$C6-Dashboard!$C8)-C30 -> -2233248.1 | G30: =G29+D30 -> 661796.9 | H30: =B30*(1-Dashboard!$C20)-C30 -> -1443411.6 | I30: =IF(C29>0,Dashboard!$C26*12,0) -> 0 | J30: =B30*Dashboard!$C13 -> 15189.403 | K30: =Dashboard!$C14*12 -> 1800 | L30: =B30*Dashboard!$C16 -> 12657.836 | M30: =IF(Dashboard!$C7<0.2,C30*Dashboard!$C17,0) -> 0 | O30: =O29+T30 -> 1221289 | P30: =T30+U30 -> 64937.738 | Q30: =Q29*(1+Dashboard!$F11)+Dashboard!$F28*12 -> 958567.38 | R30: =Dashboard!$F6*Dashboard!$F9+O30+U30*27 -> 1232769 | S30: =Q30-MAX(Q30-(Dashboard!$C8+Dashboard!$C6*Dashboard!$C19+Dashboard!$F6*Dashboard!$F9),0)*Dashboard!$F12 -> 832782.27 | T30: =Dashboard!$F6*(1+Dashboard!$F7)^(27-1)*12 -> 64697.738 | U30: =Dashboard!$F8*12 -> 240
A31: 28 | B31: =B30*(1+Dashboard!$C21) -> 1310086 | C31: =MAX((Dashboard!$C6-Dashboard!$C8)*(1+Dashboard!$C10/12)^(28*12)-Dashboard!$C26*((1+Dashboard!$C10/12)^(28*12)-1)/(Dashboard!$C10/12),0) -> 2823605.8 | D31: =I31+J31+K31+L31+M31 -> 30621.892 | E31: =E30+(D31-(C30-C31)) -> 3001024.6 | F31: =(Dashboard!$C6-Dashboard!$C8)-C31 -> -2423605.8 | G31: =G30+D31 -> 692418.79 | H31: =B31*(1-Dashboard!$C20)-C31 -> -1592125 | I31: =IF(C30>0,Dashboard!$C26*12,0) -> 0 | J31: =B31*Dashboard!$C13 -> 15721.032 | K31: =Dashboard!$C14*12 -> 1800 | L31: =B31*Dashboard!$C16 -> 13100.86 | M31: =IF(Dashboard!$C7<0.2,C31*Dashboard!$C17,0) -> 0 | O31: =O30+T31 -> 1287927.7 | P31: =T31+U31 -> 66878.67 | Q31: =Q30*(1+Dashboard!$F11)+Dashboard!$F28*12 -> 1035252.8 | R31: =Dashboard!$F6*Dashboard!$F9+O31+U31*28 -> 1299647.7 | S31: =Q31-MAX(Q31-(Dashboard!$C8+Dashboard!$C6*Dashboard!$C19+Dashboard!$F6*Dashboard!$F9),0)*Dashboard!$F12 -> 897964.85 | T31: =Dashboard!$F6*(1+Dashboard!$F7)^(28-1)*12 -> 66638.67 | U31: =Dashboard!$F8*12 -> 240
A32: 29 | B32: =B31*(1+Dashboard!$C21) -> 1355939 | C32: =MAX((Dashboard!$C6-Dashboard!$C8)*(1+Dashboard!$C10/12)^(29*12)-Dashboard!$C26*((1+Dashboard!$C10/12)^(29*12)-1)/(Dashboard!$C10/12),0) -> 3027724.5 | D32: =I32+J32+K32+L32+M32 -> 31630.658 | E32: =E31+(D32-(C31-C32)) -> 3236774 | F32: =(Dashboard!$C6-Dashboard!$C8)-C32 -> -2627724.5 | G32: =G31+D32 -> 724049.45 | H32: =B32*(1-Dashboard!$C20)-C32 -> -1753141.9 | I32: =IF(C31>0,Dashboard!$C26*12,0) -> 0 | J32: =B32*Dashboard!$C13 -> 16271.268 | K32: =Dashboard!$C14*12 -> 1800 | L32: =B32*Dashboard!$C16 -> 13559.39 | M32: =IF(Dashboard!$C7<0.2,C32*Dashboard!$C17,0) -> 0 | O32: =O31+T32 -> 1356565.5 | P32: =T32+U32 -> 68877.83 | Q32: =Q31*(1+Dashboard!$F11)+Dashboard!$F28*12 -> 1118073 | R32: =Dashboard!$F6*Dashboard!$F9+O32+U32*29 -> 1368525.5 | S32: =Q32-MAX(Q32-(Dashboard!$C8+Dashboard!$C6*Dashboard!$C19+Dashboard!$F6*Dashboard!$F9),0)*Dashboard!$F12 -> 968362.04 | T32: =Dashboard!$F6*(1+Dashboard!$F7)^(29-1)*12 -> 68637.83 | U32: =Dashboard!$F8*12 -> 240
A33: 30 | B33: =B32*(1+Dashboard!$C21) -> 1403396.9 | C33: =MAX((Dashboard!$C6-Dashboard!$C8)*(1+Dashboard!$C10/12)^(30*12)-Dashboard!$C26*((1+Dashboard!$C10/12)^(30*12)-1)/(Dashboard!$C10/12),0) -> 3246599 | D33: =I33+J33+K33+L33+M33 -> 32674.731 | E33: =E32+(D33-(C32-C33)) -> 3488323.2 | F33: =(Dashboard!$C6-Dashboard!$C8)-C33 -> -2846599 | G33: =G32+D33 -> 756724.18 | H33: =B33*(1-Dashboard!$C20)-C33 -> -1927405.9 | I33: =IF(C32>0,Dashboard!$C26*12,0) -> 0 | J33: =B33*Dashboard!$C13 -> 16840.762 | K33: =Dashboard!$C14*12 -> 1800 | L33: =B33*Dashboard!$C16 -> 14033.969 | M33: =IF(Dashboard!$C7<0.2,C33*Dashboard!$C17,0) -> 0 | O33: =O32+T33 -> 1427262.5 | P33: =T33+U33 -> 70936.965 | Q33: =Q32*(1+Dashboard!$F11)+Dashboard!$F28*12 -> 1207518.8 | R33: =Dashboard!$F6*Dashboard!$F9+O33+U33*30 -> 1439462.5 | S33: =Q33-MAX(Q33-(Dashboard!$C8+Dashboard!$C6*Dashboard!$C19+Dashboard!$F6*Dashboard!$F9),0)*Dashboard!$F12 -> 1044391 | T33: =Dashboard!$F6*(1+Dashboard!$F7)^(30-1)*12 -> 70696.965 | U33: =Dashboard!$F8*12 -> 240
A34: 31 | B34: =B33*(1+Dashboard!$C21) -> 1452515.7 | C34: =MAX((Dashboard!$C6-Dashboard!$C8)*(1+Dashboard!$C10/12)^(31*12)-Dashboard!$C26*((1+Dashboard!$C10/12)^(31*12)-1)/(Dashboard!$C10/12),0) -> 3481295.9 | D34: =I34+J34+K34+L34+M34 -> 33755.346 | E34: =E33+(D34-(C33-C34)) -> 3756775.4 | F34: =(Dashboard!$C6-Dashboard!$C8)-C34 -> -3081295.9 | G34: =G33+D34 -> 790479.53 | H34: =B34*(1-Dashboard!$C20)-C34 -> -2115931.1 | I34: =IF(C33>0,Dashboard!$C26*12,0) -> 0 | J34: =B34*Dashboard!$C13 -> 17430.189 | K34: =Dashboard!$C14*12 -> 1800 | L34: =B34*Dashboard!$C16 -> 14525.157 | M34: =IF(Dashboard!$C7<0.2,C34*Dashboard!$C17,0) -> 0 | O34: =O33+T34 -> 1500080.3 | P34: =T34+U34 -> 73057.874 | Q34: =Q33*(1+Dashboard!$F11)+Dashboard!$F28*12 -> 1304120.3 | R34: =Dashboard!$F6*Dashboard!$F9+O34+U34*31 -> 1512520.3 | S34: =Q34-MAX(Q34-(Dashboard!$C8+Dashboard!$C6*Dashboard!$C19+Dashboard!$F6*Dashboard!$F9),0)*Dashboard!$F12 -> 1126502.3 | T34: =Dashboard!$F6*(1+Dashboard!$F7)^(31-1)*12 -> 72817.874 | U34: =Dashboard!$F8*12 -> 240
A35: 32 | B35: =B34*(1+Dashboard!$C21) -> 1503353.8 | C35: =MAX((Dashboard!$C6-Dashboard!$C8)*(1+Dashboard!$C10/12)^(32*12)-Dashboard!$C26*((1+Dashboard!$C10/12)^(32*12)-1)/(Dashboard!$C10/12),0) -> 3732959.1 | D35: =I35+J35+K35+L35+M35 -> 34873.783 | E35: =E34+(D35-(C34-C35)) -> 4043312.4 | F35: =(Dashboard!$C6-Dashboard!$C8)-C35 -> -3332959.1 | G35: =G34+D35 -> 825353.31 | H35: =B35*(1-Dashboard!$C20)-C35 -> -2319806.5 | I35: =IF(C34>0,Dashboard!$C26*12,0) -> 0 | J35: =B35*Dashboard!$C13 -> 18040.246 | K35: =Dashboard!$C14*12 -> 1800 | L35: =B35*Dashboard!$C16 -> 15033.538 | M35: =IF(Dashboard!$C7<0.2,C35*Dashboard!$C17,0) -> 0 | O35: =O34+T35 -> 1575082.8 | P35: =T35+U35 -> 75242.41 | Q35: =Q34*(1+Dashboard!$F11)+Dashboard!$F28*12 -> 1408450 | R35: =Dashboard!$F6*Dashboard!$F9+O35+U35*32 -> 1587762.8 | S35: =Q35-MAX(Q35-(Dashboard!$C8+Dashboard!$C6*Dashboard!$C19+Dashboard!$F6*Dashboard!$F9),0)*Dashboard!$F12 -> 1215182.5 | T35: =Dashboard!$F6*(1+Dashboard!$F7)^(32-1)*12 -> 75002.41 | U35: =Dashboard!$F8*12 -> 240
A36: 33 | B36: =B35*(1+Dashboard!$C21) -> 1555971.2 | C36: =MAX((Dashboard!$C6-Dashboard!$C8)*(1+Dashboard!$C10/12)^(33*12)-Dashboard!$C26*((1+Dashboard!$C10/12)^(33*12)-1)/(Dashboard!$C10/12),0) -> 4002815 | D36: =I36+J36+K36+L36+M36 -> 36031.366 | E36: =E35+(D36-(C35-C36)) -> 4349199.6 | F36: =(Dashboard!$C6-Dashboard!$C8)-C36 -> -3602815 | G36: =G35+D36 -> 861384.68 | H36: =B36*(1-Dashboard!$C20)-C36 -> -2540202.1 | I36: =IF(C35>0,Dashboard!$C26*12,0) -> 0 | J36: =B36*Dashboard!$C13 -> 18671.654 | K36: =Dashboard!$C14*12 -> 1800 | L36: =B36*Dashboard!$C16 -> 15559.712 | M36: =IF(Dashboard!$C7<0.2,C36*Dashboard!$C17,0) -> 0 | O36: =O35+T36 -> 1652335.2 | P36: =T36+U36 -> 77492.483 | Q36: =Q35*(1+Dashboard!$F11)+Dashboard!$F28*12 -> 1521126 | R36: =Dashboard!$F6*Dashboard!$F9+O36+U36*33 -> 1665255.2 | S36: =Q36-MAX(Q36-(Dashboard!$C8+Dashboard!$C6*Dashboard!$C19+Dashboard!$F6*Dashboard!$F9),0)*Dashboard!$F12 -> 1310957.1 | T36: =Dashboard!$F6*(1+Dashboard!$F7)^(33-1)*12 -> 77252.483 | U36: =Dashboard!$F8*12 -> 240
A37: 34 | B37: =B36*(1+Dashboard!$C21) -> 1610430.2 | C37: =MAX((Dashboard!$C6-Dashboard!$C8)*(1+Dashboard!$C10/12)^(34*12)-Dashboard!$C26*((1+Dashboard!$C10/12)^(34*12)-1)/(Dashboard!$C10/12),0) -> 4292178.8 | D37: =I37+J37+K37+L37+M37 -> 37229.464 | E37: =E36+(D37-(C36-C37)) -> 4675792.9 | F37: =(Dashboard!$C6-Dashboard!$C8)-C37 -> -3892178.8 | G37: =G36+D37 -> 898614.14 | H37: =B37*(1-Dashboard!$C20)-C37 -> -2778374.4 | I37: =IF(C36>0,Dashboard!$C26*12,0) -> 0 | J37: =B37*Dashboard!$C13 -> 19325.162 | K37: =Dashboard!$C14*12 -> 1800 | L37: =B37*Dashboard!$C16 -> 16104.302 | M37: =IF(Dashboard!$C7<0.2,C37*Dashboard!$C17,0) -> 0 | O37: =O36+T37 -> 1731905.3 | P37: =T37+U37 -> 79810.057 | Q37: =Q36*(1+Dashboard!$F11)+Dashboard!$F28*12 -> 1642816 | R37: =Dashboard!$F6*Dashboard!$F9+O37+U37*34 -> 1745065.3 | S37: =Q37-MAX(Q37-(Dashboard!$C8+Dashboard!$C6*Dashboard!$C19+Dashboard!$F6*Dashboard!$F9),0)*Dashboard!$F12 -> 1414393.6 | T37: =Dashboard!$F6*(1+Dashboard!$F7)^(34-1)*12 -> 79570.057 | U37: =Dashboard!$F8*12 -> 240
A38: 35 | B38: =B37*(1+Dashboard!$C21) -> 1666795.2 | C38: =MAX((Dashboard!$C6-Dashboard!$C8)*(1+Dashboard!$C10/12)^(35*12)-Dashboard!$C26*((1+Dashboard!$C10/12)^(35*12)-1)/(Dashboard!$C10/12),0) -> 4602460.7 | D38: =I38+J38+K38+L38+M38 -> 38469.495 | E38: =E37+(D38-(C37-C38)) -> 5024544.4 | F38: =(Dashboard!$C6-Dashboard!$C8)-C38 -> -4202460.7 | G38: =G37+D38 -> 937083.64 | H38: =B38*(1-Dashboard!$C20)-C38 -> -3035673.2 | I38: =IF(C37>0,Dashboard!$C26*12,0) -> 0 | J38: =B38*Dashboard!$C13 -> 20001.543 | K38: =Dashboard!$C14*12 -> 1800 | L38: =B38*Dashboard!$C16 -> 16667.952 | M38: =IF(Dashboard!$C7<0.2,C38*Dashboard!$C17,0) -> 0 | O38: =O37+T38 -> 1813862.5 | P38: =T38+U38 -> 82197.159 | Q38: =Q37*(1+Dashboard!$F11)+Dashboard!$F28*12 -> 1774241.3 | R38: =Dashboard!$F6*Dashboard!$F9+O38+U38*35 -> 1827262.5 | S38: =Q38-MAX(Q38-(Dashboard!$C8+Dashboard!$C6*Dashboard!$C19+Dashboard!$F6*Dashboard!$F9),0)*Dashboard!$F12 -> 1526105.1 | T38: =Dashboard!$F6*(1+Dashboard!$F7)^(35-1)*12 -> 81957.159 | U38: =Dashboard!$F8*12 -> 240
A39: 36 | B39: =B38*(1+Dashboard!$C21) -> 1725133.1 | C39: =MAX((Dashboard!$C6-Dashboard!$C8)*(1+Dashboard!$C10/12)^(36*12)-Dashboard!$C26*((1+Dashboard!$C10/12)^(36*12)-1)/(Dashboard!$C10/12),0) -> 4935173 | D39: =I39+J39+K39+L39+M39 -> 39752.927 | E39: =E38+(D39-(C38-C39)) -> 5397009.6 | F39: =(Dashboard!$C6-Dashboard!$C8)-C39 -> -4535173 | G39: =G38+D39 -> 976836.56 | H39: =B39*(1-Dashboard!$C20)-C39 -> -3313547.9 | I39: =IF(C38>0,Dashboard!$C26*12,0) -> 0 | J39: =B39*Dashboard!$C13 -> 20701.597 | K39: =Dashboard!$C14*12 -> 1800 | L39: =B39*Dashboard!$C16 -> 17251.331 | M39: =IF(Dashboard!$C7<0.2,C39*Dashboard!$C17,0) -> 0 | O39: =O38+T39 -> 1898278.3 | P39: =T39+U39 -> 84655.874 | Q39: =Q38*(1+Dashboard!$F11)+Dashboard!$F28*12 -> 1916180.6 | R39: =Dashboard!$F6*Dashboard!$F9+O39+U39*36 -> 1911918.3 | S39: =Q39-MAX(Q39-(Dashboard!$C8+Dashboard!$C6*Dashboard!$C19+Dashboard!$F6*Dashboard!$F9),0)*Dashboard!$F12 -> 1646753.5 | T39: =Dashboard!$F6*(1+Dashboard!$F7)^(36-1)*12 -> 84415.874 | U39: =Dashboard!$F8*12 -> 240
A40: 37 | B40: =B39*(1+Dashboard!$C21) -> 1785512.7 | C40: =MAX((Dashboard!$C6-Dashboard!$C8)*(1+Dashboard!$C10/12)^(37*12)-Dashboard!$C26*((1+Dashboard!$C10/12)^(37*12)-1)/(Dashboard!$C10/12),0) -> 5291937 | D40: =I40+J40+K40+L40+M40 -> 41081.28 | E40: =E39+(D40-(C39-C40)) -> 5794854.9 | F40: =(Dashboard!$C6-Dashboard!$C8)-C40 -> -4891937 | G40: =G39+D40 -> 1017917.8 | H40: =B40*(1-Dashboard!$C20)-C40 -> -3613555.1 | I40: =IF(C39>0,Dashboard!$C26*12,0) -> 0 | J40: =B40*Dashboard!$C13 -> 21426.153 | K40: =Dashboard!$C14*12 -> 1800 | L40: =B40*Dashboard!$C16 -> 17855.127 | M40: =IF(Dashboard!$C7<0.2,C40*Dashboard!$C17,0) -> 0 | O40: =O39+T40 -> 1985226.7 | P40: =T40+U40 -> 87188.35 | Q40: =Q39*(1+Dashboard!$F11)+Dashboard!$F28*12 -> 2069475.1 | R40: =Dashboard!$F6*Dashboard!$F9+O40+U40*37 -> 1999106.7 | S40: =Q40-MAX(Q40-(Dashboard!$C8+Dashboard!$C6*Dashboard!$C19+Dashboard!$F6*Dashboard!$F9),0)*Dashboard!$F12 -> 1777053.8 | T40: =Dashboard!$F6*(1+Dashboard!$F7)^(37-1)*12 -> 86948.35 | U40: =Dashboard!$F8*12 -> 240
A41: 38 | B41: =B40*(1+Dashboard!$C21) -> 1848005.7 | C41: =MAX((Dashboard!$C6-Dashboard!$C8)*(1+Dashboard!$C10/12)^(38*12)-Dashboard!$C26*((1+Dashboard!$C10/12)^(38*12)-1)/(Dashboard!$C10/12),0) -> 5674491.6 | D41: =I41+J41+K41+L41+M41 -> 42456.124 | E41: =E40+(D41-(C40-C41)) -> 6219865.6 | F41: =(Dashboard!$C6-Dashboard!$C8)-C41 -> -5274491.6 | G41: =G40+D41 -> 1060374 | H41: =B41*(1-Dashboard!$C20)-C41 -> -3937366.3 | I41: =IF(C40>0,Dashboard!$C26*12,0) -> 0 | J41: =B41*Dashboard!$C13 -> 22176.068 | K41: =Dashboard!$C14*12 -> 1800 | L41: =B41*Dashboard!$C16 -> 18480.057 | M41: =IF(Dashboard!$C7<0.2,C41*Dashboard!$C17,0) -> 0 | O41: =O40+T41 -> 2074783.5 | P41: =T41+U41 -> 89796.8 | Q41: =Q40*(1+Dashboard!$F11)+Dashboard!$F28*12 -> 2235033.1 | R41: =Dashboard!$F6*Dashboard!$F9+O41+U41*38 -> 2088903.5 | S41: =Q41-MAX(Q41-(Dashboard!$C8+Dashboard!$C6*Dashboard!$C19+Dashboard!$F6*Dashboard!$F9),0)*Dashboard!$F12 -> 1917778.1 | T41: =Dashboard!$F6*(1+Dashboard!$F7)^(38-1)*12 -> 89556.8 | U41: =Dashboard!$F8*12 -> 240
A42: 39 | B42: =B41*(1+Dashboard!$C21) -> 1912685.9 | C42: =MAX((Dashboard!$C6-Dashboard!$C8)*(1+Dashboard!$C10/12)^(39*12)-Dashboard!$C26*((1+Dashboard!$C10/12)^(39*12)-1)/(Dashboard!$C10/12),0) -> 6084701.1 | D42: =I42+J42+K42+L42+M42 -> 43879.089 | E42: =E41+(D42-(C41-C42)) -> 6673954.1 | F42: =(Dashboard!$C6-Dashboard!$C8)-C42 -> -5684701.1 | G42: =G41+D42 -> 1104253.1 | H42: =B42*(1-Dashboard!$C20)-C42 -> -4286776.4 | I42: =IF(C41>0,Dashboard!$C26*12,0) -> 0 | J42: =B42*Dashboard!$C13 -> 22952.23 | K42: =Dashboard!$C14*12 -> 1800 | L42: =B42*Dashboard!$C16 -> 19126.859 | M42: =IF(Dashboard!$C7<0.2,C42*Dashboard!$C17,0) -> 0 | O42: =O41+T42 -> 2167027 | P42: =T42+U42 -> 92483.504 | Q42: =Q41*(1+Dashboard!$F11)+Dashboard!$F28*12 -> 2413835.7 | R42: =Dashboard!$F6*Dashboard!$F9+O42+U42*39 -> 2181387 | S42: =Q42-MAX(Q42-(Dashboard!$C8+Dashboard!$C6*Dashboard!$C19+Dashboard!$F6*Dashboard!$F9),0)*Dashboard!$F12 -> 2069760.4 | T42: =Dashboard!$F6*(1+Dashboard!$F7)^(39-1)*12 -> 92243.504 | U42: =Dashboard!$F8*12 -> 240
A43: 40 | B43: =B42*(1+Dashboard!$C21) -> 1979629.9 | C43: =MAX((Dashboard!$C6-Dashboard!$C8)*(1+Dashboard!$C10/12)^(40*12)-Dashboard!$C26*((1+Dashboard!$C10/12)^(40*12)-1)/(Dashboard!$C10/12),0) -> 6524564.6 | D43: =I43+J43+K43+L43+M43 -> 45351.857 | E43: =E42+(D43-(C42-C43)) -> 7159169.5 | F43: =(Dashboard!$C6-Dashboard!$C8)-C43 -> -6124564.6 | G43: =G42+D43 -> 1149604.9 | H43: =B43*(1-Dashboard!$C20)-C43 -> -4663712.5 | I43: =IF(C42>0,Dashboard!$C26*12,0) -> 0 | J43: =B43*Dashboard!$C13 -> 23755.558 | K43: =Dashboard!$C14*12 -> 1800 | L43: =B43*Dashboard!$C16 -> 19796.299 | M43: =IF(Dashboard!$C7<0.2,C43*Dashboard!$C17,0) -> 0 | O43: =O42+T43 -> 2262037.8 | P43: =T43+U43 -> 95250.809 | Q43: =Q42*(1+Dashboard!$F11)+Dashboard!$F28*12 -> 2606942.6 | R43: =Dashboard!$F6*Dashboard!$F9+O43+U43*40 -> 2276637.8 | S43: =Q43-MAX(Q43-(Dashboard!$C8+Dashboard!$C6*Dashboard!$C19+Dashboard!$F6*Dashboard!$F9),0)*Dashboard!$F12 -> 2233901.2 | T43: =Dashboard!$F6*(1+Dashboard!$F7)^(40-1)*12 -> 95010.809 | U43: =Dashboard!$F8*12 -> 240
A44: 41 | B44: =B43*(1+Dashboard!$C21) -> 2048916.9 | C44: =MAX((Dashboard!$C6-Dashboard!$C8)*(1+Dashboard!$C10/12)^(41*12)-Dashboard!$C26*((1+Dashboard!$C10/12)^(41*12)-1)/(Dashboard!$C10/12),0) -> 6996225.9 | D44: =I44+J44+K44+L44+M44 -> 46876.172 | E44: =E43+(D44-(C43-C44)) -> 7677707 | F44: =(Dashboard!$C6-Dashboard!$C8)-C44 -> -6596225.9 | G44: =G43+D44 -> 1196481.1 | H44: =B44*(1-Dashboard!$C20)-C44 -> -5070244 | I44: =IF(C43>0,Dashboard!$C26*12,0) -> 0 | J44: =B44*Dashboard!$C13 -> 24587.003 | K44: =Dashboard!$C14*12 -> 1800 | L44: =B44*Dashboard!$C16 -> 20489.169 | M44: =IF(Dashboard!$C7<0.2,C44*Dashboard!$C17,0) -> 0 | O44: =O43+T44 -> 2359898.9 | P44: =T44+U44 -> 98101.134 | Q44: =Q43*(1+Dashboard!$F11)+Dashboard!$F28*12 -> 2815498 | R44: =Dashboard!$F6*Dashboard!$F9+O44+U44*41 -> 2374738.9 | S44: =Q44-MAX(Q44-(Dashboard!$C8+Dashboard!$C6*Dashboard!$C19+Dashboard!$F6*Dashboard!$F9),0)*Dashboard!$F12 -> 2411173.3 | T44: =Dashboard!$F6*(1+Dashboard!$F7)^(41-1)*12 -> 97861.134 | U44: =Dashboard!$F8*12 -> 240
A45: 42 | B45: =B44*(1+Dashboard!$C21) -> 2120629 | C45: =MAX((Dashboard!$C6-Dashboard!$C8)*(1+Dashboard!$C10/12)^(42*12)-Dashboard!$C26*((1+Dashboard!$C10/12)^(42*12)-1)/(Dashboard!$C10/12),0) -> 7501983.6 | D45: =I45+J45+K45+L45+M45 -> 48453.838 | E45: =E44+(D45-(C44-C45)) -> 8231918.6 | F45: =(Dashboard!$C6-Dashboard!$C8)-C45 -> -7101983.6 | G45: =G44+D45 -> 1244934.9 | H45: =B45*(1-Dashboard!$C20)-C45 -> -5508592.4 | I45: =IF(C44>0,Dashboard!$C26*12,0) -> 0 | J45: =B45*Dashboard!$C13 -> 25447.548 | K45: =Dashboard!$C14*12 -> 1800 | L45: =B45*Dashboard!$C16 -> 21206.29 | M45: =IF(Dashboard!$C7<0.2,C45*Dashboard!$C17,0) -> 0 | O45: =O44+T45 -> 2460695.9 | P45: =T45+U45 -> 101036.97 | Q45: =Q44*(1+Dashboard!$F11)+Dashboard!$F28*12 -> 3040737.8 | R45: =Dashboard!$F6*Dashboard!$F9+O45+U45*42 -> 2475775.9 | S45: =Q45-MAX(Q45-(Dashboard!$C8+Dashboard!$C6*Dashboard!$C19+Dashboard!$F6*Dashboard!$F9),0)*Dashboard!$F12 -> 2602627.2 | T45: =Dashboard!$F6*(1+Dashboard!$F7)^(42-1)*12 -> 100796.97 | U45: =Dashboard!$F8*12 -> 240
A46: 43 | B46: =B45*(1+Dashboard!$C21) -> 2194851 | C46: =MAX((Dashboard!$C6-Dashboard!$C8)*(1+Dashboard!$C10/12)^(43*12)-Dashboard!$C26*((1+Dashboard!$C10/12)^(43*12)-1)/(Dashboard!$C10/12),0) -> 8044302.6 | D46: =I46+J46+K46+L46+M46 -> 50086.722 | E46: =E45+(D46-(C45-C46)) -> 8824324.3 | F46: =(Dashboard!$C6-Dashboard!$C8)-C46 -> -7644302.6 | G46: =G45+D46 -> 1295021.6 | H46: =B46*(1-Dashboard!$C20)-C46 -> -5981142.7 | I46: =IF(C45>0,Dashboard!$C26*12,0) -> 0 | J46: =B46*Dashboard!$C13 -> 26338.212 | K46: =Dashboard!$C14*12 -> 1800 | L46: =B46*Dashboard!$C16 -> 21948.51 | M46: =IF(Dashboard!$C7<0.2,C46*Dashboard!$C17,0) -> 0 | O46: =O45+T46 -> 2564516.8 | P46: =T46+U46 -> 104060.88 | Q46: =Q45*(1+Dashboard!$F11)+Dashboard!$F28*12 -> 3283996.9 | R46: =Dashboard!$F6*Dashboard!$F9+O46+U46*43 -> 2579836.8 | S46: =Q46-MAX(Q46-(Dashboard!$C8+Dashboard!$C6*Dashboard!$C19+Dashboard!$F6*Dashboard!$F9),0)*Dashboard!$F12 -> 2809397.3 | T46: =Dashboard!$F6*(1+Dashboard!$F7)^(43-1)*12 -> 103820.88 | U46: =Dashboard!$F8*12 -> 240
A47: 44 | B47: =B46*(1+Dashboard!$C21) -> 2271670.8 | C47: =MAX((Dashboard!$C6-Dashboard!$C8)*(1+Dashboard!$C10/12)^(44*12)-Dashboard!$C26*((1+Dashboard!$C10/12)^(44*12)-1)/(Dashboard!$C10/12),0) -> 8625825.9 | D47: =I47+J47+K47+L47+M47 -> 51776.758 | E47: =E46+(D47-(C46-C47)) -> 9457624.3 | F47: =(Dashboard!$C6-Dashboard!$C8)-C47 -> -8225825.9 | G47: =G46+D47 -> 1346798.4 | H47: =B47*(1-Dashboard!$C20)-C47 -> -6490455.4 | I47: =IF(C46>0,Dashboard!$C26*12,0) -> 0 | J47: =B47*Dashboard!$C13 -> 27260.05 | K47: =Dashboard!$C14*12 -> 1800 | L47: =B47*Dashboard!$C16 -> 22716.708 | M47: =IF(Dashboard!$C7<0.2,C47*Dashboard!$C17,0) -> 0 | O47: =O46+T47 -> 2671452.3 | P47: =T47+U47 -> 107175.5 | Q47: =Q46*(1+Dashboard!$F11)+Dashboard!$F28*12 -> 3546716.6 | R47: =Dashboard!$F6*Dashboard!$F9+O47+U47*44 -> 2687012.3 | S47: =Q47-MAX(Q47-(Dashboard!$C8+Dashboard!$C6*Dashboard!$C19+Dashboard!$F6*Dashboard!$F9),0)*Dashboard!$F12 -> 3032709.1 | T47: =Dashboard!$F6*(1+Dashboard!$F7)^(44-1)*12 -> 106935.5 | U47: =Dashboard!$F8*12 -> 240
A48: 45 | B48: =B47*(1+Dashboard!$C21) -> 2351179.3 | C48: =MAX((Dashboard!$C6-Dashboard!$C8)*(1+Dashboard!$C10/12)^(45*12)-Dashboard!$C26*((1+Dashboard!$C10/12)^(45*12)-1)/(Dashboard!$C10/12),0) -> 9249387.6 | D48: =I48+J48+K48+L48+M48 -> 53525.944 | E48: =E47+(D48-(C47-C48)) -> 10134712 | F48: =(Dashboard!$C6-Dashboard!$C8)-C48 -> -8849387.6 | G48: =G47+D48 -> 1400324.3 | H48: =B48*(1-Dashboard!$C20)-C48 -> -7039279.1 | I48: =IF(C47>0,Dashboard!$C26*12,0) -> 0 | J48: =B48*Dashboard!$C13 -> 28214.151 | K48: =Dashboard!$C14*12 -> 1800 | L48: =B48*Dashboard!$C16 -> 23511.793 | M48: =IF(Dashboard!$C7<0.2,C48*Dashboard!$C17,0) -> 0 | O48: =O47+T48 -> 2781595.8 | P48: =T48+U48 -> 110383.57 | Q48: =Q47*(1+Dashboard!$F11)+Dashboard!$F28*12 -> 3830453.9 | R48: =Dashboard!$F6*Dashboard!$F9+O48+U48*45 -> 2797395.8 | S48: =Q48-MAX(Q48-(Dashboard!$C8+Dashboard!$C6*Dashboard!$C19+Dashboard!$F6*Dashboard!$F9),0)*Dashboard!$F12 -> 3273885.8 | T48: =Dashboard!$F6*(1+Dashboard!$F7)^(45-1)*12 -> 110143.57 | U48: =Dashboard!$F8*12 -> 240
A49: 46 | B49: =B48*(1+Dashboard!$C21) -> 2433470.6 | C49: =MAX((Dashboard!$C6-Dashboard!$C8)*(1+Dashboard!$C10/12)^(46*12)-Dashboard!$C26*((1+Dashboard!$C10/12)^(46*12)-1)/(Dashboard!$C10/12),0) -> 9918026.6 | D49: =I49+J49+K49+L49+M49 -> 55336.352 | E49: =E48+(D49-(C48-C49)) -> 10858687 | F49: =(Dashboard!$C6-Dashboard!$C8)-C49 -> -9518026.6 | G49: =G48+D49 -> 1455660.7 | H49: =B49*(1-Dashboard!$C20)-C49 -> -7630564.2 | I49: =IF(C48>0,Dashboard!$C26*12,0) -> 0 | J49: =B49*Dashboard!$C13 -> 29201.647 | K49: =Dashboard!$C14*12 -> 1800 | L49: =B49*Dashboard!$C16 -> 24334.706 | M49: =IF(Dashboard!$C7<0.2,C49*Dashboard!$C17,0) -> 0 | O49: =O48+T49 -> 2895043.7 | P49: =T49+U49 -> 113687.88 | Q49: =Q48*(1+Dashboard!$F11)+Dashboard!$F28*12 -> 4136890.2 | R49: =Dashboard!$F6*Dashboard!$F9+O49+U49*46 -> 2911083.7 | S49: =Q49-MAX(Q49-(Dashboard!$C8+Dashboard!$C6*Dashboard!$C19+Dashboard!$F6*Dashboard!$F9),0)*Dashboard!$F12 -> 3534356.7 | T49: =Dashboard!$F6*(1+Dashboard!$F7)^(46-1)*12 -> 113447.88 | U49: =Dashboard!$F8*12 -> 240
A50: 47 | B50: =B49*(1+Dashboard!$C21) -> 2518642 | C50: =MAX((Dashboard!$C6-Dashboard!$C8)*(1+Dashboard!$C10/12)^(47*12)-Dashboard!$C26*((1+Dashboard!$C10/12)^(47*12)-1)/(Dashboard!$C10/12),0) -> 10635001 | D50: =I50+J50+K50+L50+M50 -> 57210.124 | E50: =E49+(D50-(C49-C50)) -> 11632872 | F50: =(Dashboard!$C6-Dashboard!$C8)-C50 -> -10235001 | G50: =G49+D50 -> 1512870.8 | H50: =B50*(1-Dashboard!$C20)-C50 -> -8267478 | I50: =IF(C49>0,Dashboard!$C26*12,0) -> 0 | J50: =B50*Dashboard!$C13 -> 30223.704 | K50: =Dashboard!$C14*12 -> 1800 | L50: =B50*Dashboard!$C16 -> 25186.42 | M50: =IF(Dashboard!$C7<0.2,C50*Dashboard!$C17,0) -> 0 | O50: =O49+T50 -> 3011895 | P50: =T50+U50 -> 117091.31 | Q50: =Q49*(1+Dashboard!$F11)+Dashboard!$F28*12 -> 4467841.5 | R50: =Dashboard!$F6*Dashboard!$F9+O50+U50*47 -> 3028175 | S50: =Q50-MAX(Q50-(Dashboard!$C8+Dashboard!$C6*Dashboard!$C19+Dashboard!$F6*Dashboard!$F9),0)*Dashboard!$F12 -> 3815665.2 | T50: =Dashboard!$F6*(1+Dashboard!$F7)^(47-1)*12 -> 116851.31 | U50: =Dashboard!$F8*12 -> 240
A51: 48 | B51: =B50*(1+Dashboard!$C21) -> 2606794.5 | C51: =MAX((Dashboard!$C6-Dashboard!$C8)*(1+Dashboard!$C10/12)^(48*12)-Dashboard!$C26*((1+Dashboard!$C10/12)^(48*12)-1)/(Dashboard!$C10/12),0) -> 11403807 | D51: =I51+J51+K51+L51+M51 -> 59149.479 | E51: =E50+(D51-(C50-C51)) -> 12460827 | F51: =(Dashboard!$C6-Dashboard!$C8)-C51 -> -11003807 | G51: =G50+D51 -> 1572020.3 | H51: =B51*(1-Dashboard!$C20)-C51 -> -8953419.8 | I51: =IF(C50>0,Dashboard!$C26*12,0) -> 0 | J51: =B51*Dashboard!$C13 -> 31281.534 | K51: =Dashboard!$C14*12 -> 1800 | L51: =B51*Dashboard!$C16 -> 26067.945 | M51: =IF(Dashboard!$C7<0.2,C51*Dashboard!$C17,0) -> 0 | O51: =O50+T51 -> 3132251.9 | P51: =T51+U51 -> 120596.85 | Q51: =Q50*(1+Dashboard!$F11)+Dashboard!$F28*12 -> 4825268.8 | R51: =Dashboard!$F6*Dashboard!$F9+O51+U51*48 -> 3148771.9 | S51: =Q51-MAX(Q51-(Dashboard!$C8+Dashboard!$C6*Dashboard!$C19+Dashboard!$F6*Dashboard!$F9),0)*Dashboard!$F12 -> 4119478.5 | T51: =Dashboard!$F6*(1+Dashboard!$F7)^(48-1)*12 -> 120356.85 | U51: =Dashboard!$F8*12 -> 240
A52: 49 | B52: =B51*(1+Dashboard!$C21) -> 2698032.3 | C52: =MAX((Dashboard!$C6-Dashboard!$C8)*(1+Dashboard!$C10/12)^(49*12)-Dashboard!$C26*((1+Dashboard!$C10/12)^(49*12)-1)/(Dashboard!$C10/12),0) -> 12228189 | D52: =I52+J52+K52+L52+M52 -> 61156.711 | E52: =E51+(D52-(C51-C52)) -> 13346366 | F52: =(Dashboard!$C6-Dashboard!$C8)-C52 -> -11828189 | G52: =G51+D52 -> 1633177 | H52: =B52*(1-Dashboard!$C20)-C52 -> -9692038.4 | I52: =IF(C51>0,Dashboard!$C26*12,0) -> 0 | J52: =B52*Dashboard!$C13 -> 32376.388 | K52: =Dashboard!$C14*12 -> 1800 | L52: =B52*Dashboard!$C16 -> 26980.323 | M52: =IF(Dashboard!$C7<0.2,C52*Dashboard!$C17,0) -> 0 | O52: =O51+T52 -> 3256219.4 | P52: =T52+U52 -> 124207.56 | Q52: =Q51*(1+Dashboard!$F11)+Dashboard!$F28*12 -> 5211290.3 | R52: =Dashboard!$F6*Dashboard!$F9+O52+U52*49 -> 3272979.4 | S52: =Q52-MAX(Q52-(Dashboard!$C8+Dashboard!$C6*Dashboard!$C19+Dashboard!$F6*Dashboard!$F9),0)*Dashboard!$F12 -> 4447596.7 | T52: =Dashboard!$F6*(1+Dashboard!$F7)^(49-1)*12 -> 123967.56 | U52: =Dashboard!$F8*12 -> 240
A53: 50 | B53: =B52*(1+Dashboard!$C21) -> 2792463.4 | C53: =MAX((Dashboard!$C6-Dashboard!$C8)*(1+Dashboard!$C10/12)^(50*12)-Dashboard!$C26*((1+Dashboard!$C10/12)^(50*12)-1)/(Dashboard!$C10/12),0) -> 13112165 | D53: =I53+J53+K53+L53+M53 -> 63234.195 | E53: =E52+(D53-(C52-C53)) -> 14293577 | F53: =(Dashboard!$C6-Dashboard!$C8)-C53 -> -12712165 | G53: =G52+D53 -> 1696411.2 | H53: =B53*(1-Dashboard!$C20)-C53 -> -10487250 | I53: =IF(C52>0,Dashboard!$C26*12,0) -> 0 | J53: =B53*Dashboard!$C13 -> 33509.561 | K53: =Dashboard!$C14*12 -> 1800 | L53: =B53*Dashboard!$C16 -> 27924.634 | M53: =IF(Dashboard!$C7<0.2,C53*Dashboard!$C17,0) -> 0 | O53: =O52+T53 -> 3383906 | P53: =T53+U53 -> 127926.58 | Q53: =Q52*(1+Dashboard!$F11)+Dashboard!$F28*12 -> 5628193.5 | R53: =Dashboard!$F6*Dashboard!$F9+O53+U53*50 -> 3400906 | S53: =Q53-MAX(Q53-(Dashboard!$C8+Dashboard!$C6*Dashboard!$C19+Dashboard!$F6*Dashboard!$F9),0)*Dashboard!$F12 -> 4801964.5 | T53: =Dashboard!$F6*(1+Dashboard!$F7)^(50-1)*12 -> 127686.58 | U53: =Dashboard!$F8*12 -> 240
A54: 51 | B54: =B53*(1+Dashboard!$C21) -> 2890199.6 | C54: =MAX((Dashboard!$C6-Dashboard!$C8)*(1+Dashboard!$C10/12)^(51*12)-Dashboard!$C26*((1+Dashboard!$C10/12)^(51*12)-1)/(Dashboard!$C10/12),0) -> 14060045 | D54: =I54+J54+K54+L54+M54 -> 65384.392 | E54: =E53+(D54-(C53-C54)) -> 15306841 | F54: =(Dashboard!$C6-Dashboard!$C8)-C54 -> -13660045 | G54: =G53+D54 -> 1761795.6 | H54: =B54*(1-Dashboard!$C20)-C54 -> -11343257 | I54: =IF(C53>0,Dashboard!$C26*12,0) -> 0 | J54: =B54*Dashboard!$C13 -> 34682.396 | K54: =Dashboard!$C14*12 -> 1800 | L54: =B54*Dashboard!$C16 -> 28901.996 | M54: =IF(Dashboard!$C7<0.2,C54*Dashboard!$C17,0) -> 0 | O54: =O53+T54 -> 3515423.2 | P54: =T54+U54 -> 131757.18 | Q54: =Q53*(1+Dashboard!$F11)+Dashboard!$F28*12 -> 6078449 | R54: =Dashboard!$F6*Dashboard!$F9+O54+U54*51 -> 3532663.2 | S54: =Q54-MAX(Q54-(Dashboard!$C8+Dashboard!$C6*Dashboard!$C19+Dashboard!$F6*Dashboard!$F9),0)*Dashboard!$F12 -> 5184681.6 | T54: =Dashboard!$F6*(1+Dashboard!$F7)^(51-1)*12 -> 131517.18 | U54: =Dashboard!$F8*12 -> 240
A55: 52 | B55: =B54*(1+Dashboard!$C21) -> 2991356.6 | C55: =MAX((Dashboard!$C6-Dashboard!$C8)*(1+Dashboard!$C10/12)^(52*12)-Dashboard!$C26*((1+Dashboard!$C10/12)^(52*12)-1)/(Dashboard!$C10/12),0) -> 15076447 | D55: =I55+J55+K55+L55+M55 -> 67609.846 | E55: =E54+(D55-(C54-C55)) -> 16390852 | F55: =(Dashboard!$C6-Dashboard!$C8)-C55 -> -14676447 | G55: =G54+D55 -> 1829405.4 | H55: =B55*(1-Dashboard!$C20)-C55 -> -12264572 | I55: =IF(C54>0,Dashboard!$C26*12,0) -> 0 | J55: =B55*Dashboard!$C13 -> 35896.28 | K55: =Dashboard!$C14*12 -> 1800 | L55: =B55*Dashboard!$C16 -> 29913.566 | M55: =IF(Dashboard!$C7<0.2,C55*Dashboard!$C17,0) -> 0 | O55: =O54+T55 -> 3650885.9 | P55: =T55+U55 -> 135702.7 | Q55: =Q54*(1+Dashboard!$F11)+Dashboard!$F28*12 -> 6564724.9 | R55: =Dashboard!$F6*Dashboard!$F9+O55+U55*52 -> 3668365.9 | S55: =Q55-MAX(Q55-(Dashboard!$C8+Dashboard!$C6*Dashboard!$C19+Dashboard!$F6*Dashboard!$F9),0)*Dashboard!$F12 -> 5598016.2 | T55: =Dashboard!$F6*(1+Dashboard!$F7)^(52-1)*12 -> 135462.7 | U55: =Dashboard!$F8*12 -> 240
A56: 53 | B56: =B55*(1+Dashboard!$C21) -> 3096054.1 | C56: =MAX((Dashboard!$C6-Dashboard!$C8)*(1+Dashboard!$C10/12)^(53*12)-Dashboard!$C26*((1+Dashboard!$C10/12)^(53*12)-1)/(Dashboard!$C10/12),0) -> 16166324 | D56: =I56+J56+K56+L56+M56 -> 69913.191 | E56: =E55+(D56-(C55-C56)) -> 17550643 | F56: =(Dashboard!$C6-Dashboard!$C8)-C56 -> -15766324 | G56: =G55+D56 -> 1899318.6 | H56: =B56*(1-Dashboard!$C20)-C56 -> -13256033 | I56: =IF(C55>0,Dashboard!$C26*12,0) -> 0 | J56: =B56*Dashboard!$C13 -> 37152.649 | K56: =Dashboard!$C14*12 -> 1800 | L56: =B56*Dashboard!$C16 -> 30960.541 | M56: =IF(Dashboard!$C7<0.2,C56*Dashboard!$C17,0) -> 0 | O56: =O55+T56 -> 3790412.5 | P56: =T56+U56 -> 139766.58 | Q56: =Q55*(1+Dashboard!$F11)+Dashboard!$F28*12 -> 7089902.9 | R56: =Dashboard!$F6*Dashboard!$F9+O56+U56*53 -> 3808132.5 | S56: =Q56-MAX(Q56-(Dashboard!$C8+Dashboard!$C6*Dashboard!$C19+Dashboard!$F6*Dashboard!$F9),0)*Dashboard!$F12 -> 6044417.5 | T56: =Dashboard!$F6*(1+Dashboard!$F7)^(53-1)*12 -> 139526.58 | U56: =Dashboard!$F8*12 -> 240
A57: 54 | B57: =B56*(1+Dashboard!$C21) -> 3204416 | C57: =MAX((Dashboard!$C6-Dashboard!$C8)*(1+Dashboard!$C10/12)^(54*12)-Dashboard!$C26*((1+Dashboard!$C10/12)^(54*12)-1)/(Dashboard!$C10/12),0) -> 17334989 | D57: =I57+J57+K57+L57+M57 -> 72297.152 | E57: =E56+(D57-(C56-C57)) -> 18791605 | F57: =(Dashboard!$C6-Dashboard!$C8)-C57 -> -16934989 | G57: =G56+D57 -> 1971615.8 | H57: =B57*(1-Dashboard!$C20)-C57 -> -14322838 | I57: =IF(C56>0,Dashboard!$C26*12,0) -> 0 | J57: =B57*Dashboard!$C13 -> 38452.992 | K57: =Dashboard!$C14*12 -> 1800 | L57: =B57*Dashboard!$C16 -> 32044.16 | M57: =IF(Dashboard!$C7<0.2,C57*Dashboard!$C17,0) -> 0 | O57: =O56+T57 -> 3934124.8 | P57: =T57+U57 -> 143952.37 | Q57: =Q56*(1+Dashboard!$F11)+Dashboard!$F28*12 -> 7657095.1 | R57: =Dashboard!$F6*Dashboard!$F9+O57+U57*54 -> 3952084.8 | S57: =Q57-MAX(Q57-(Dashboard!$C8+Dashboard!$C6*Dashboard!$C19+Dashboard!$F6*Dashboard!$F9),0)*Dashboard!$F12 -> 6526530.9 | T57: =Dashboard!$F6*(1+Dashboard!$F7)^(54-1)*12 -> 143712.37 | U57: =Dashboard!$F8*12 -> 240
A58: 55 | B58: =B57*(1+Dashboard!$C21) -> 3316570.6 | C58: =MAX((Dashboard!$C6-Dashboard!$C8)*(1+Dashboard!$C10/12)^(55*12)-Dashboard!$C26*((1+Dashboard!$C10/12)^(55*12)-1)/(Dashboard!$C10/12),0) -> 18588137 | D58: =I58+J58+K58+L58+M58 -> 74764.553 | E58: =E57+(D58-(C57-C58)) -> 20119517 | F58: =(Dashboard!$C6-Dashboard!$C8)-C58 -> -18188137 | G58: =G57+D58 -> 2046380.3 | H58: =B58*(1-Dashboard!$C20)-C58 -> -15470561 | I58: =IF(C57>0,Dashboard!$C26*12,0) -> 0 | J58: =B58*Dashboard!$C13 -> 39798.847 | K58: =Dashboard!$C14*12 -> 1800 | L58: =B58*Dashboard!$C16 -> 33165.706 | M58: =IF(Dashboard!$C7<0.2,C58*Dashboard!$C17,0) -> 0 | O58: =O57+T58 -> 4082148.6 | P58: =T58+U58 -> 148263.75 | Q58: =Q57*(1+Dashboard!$F11)+Dashboard!$F28*12 -> 8269662.7 | R58: =Dashboard!$F6*Dashboard!$F9+O58+U58*55 -> 4100348.6 | S58: =Q58-MAX(Q58-(Dashboard!$C8+Dashboard!$C6*Dashboard!$C19+Dashboard!$F6*Dashboard!$F9),0)*Dashboard!$F12 -> 7047213.3 | T58: =Dashboard!$F6*(1+Dashboard!$F7)^(55-1)*12 -> 148023.75 | U58: =Dashboard!$F8*12 -> 240
A59: 56 | B59: =B58*(1+Dashboard!$C21) -> 3432650.5 | C59: =MAX((Dashboard!$C6-Dashboard!$C8)*(1+Dashboard!$C10/12)^(56*12)-Dashboard!$C26*((1+Dashboard!$C10/12)^(56*12)-1)/(Dashboard!$C10/12),0) -> 19931875 | D59: =I59+J59+K59+L59+M59 -> 77318.312 | E59: =E58+(D59-(C58-C59)) -> 21540574 | F59: =(Dashboard!$C6-Dashboard!$C8)-C59 -> -19531875 | G59: =G58+D59 -> 2123698.7 | H59: =B59*(1-Dashboard!$C20)-C59 -> -16705183 | I59: =IF(C58>0,Dashboard!$C26*12,0) -> 0 | J59: =B59*Dashboard!$C13 -> 41191.807 | K59: =Dashboard!$C14*12 -> 1800 | L59: =B59*Dashboard!$C16 -> 34326.505 | M59: =IF(Dashboard!$C7<0.2,C59*Dashboard!$C17,0) -> 0 | O59: =O58+T59 -> 4234613 | P59: =T59+U59 -> 152704.46 | Q59: =Q58*(1+Dashboard!$F11)+Dashboard!$F28*12 -> 8931235.8 | R59: =Dashboard!$F6*Dashboard!$F9+O59+U59*56 -> 4253053 | S59: =Q59-MAX(Q59-(Dashboard!$C8+Dashboard!$C6*Dashboard!$C19+Dashboard!$F6*Dashboard!$F9),0)*Dashboard!$F12 -> 7609550.4 | T59: =Dashboard!$F6*(1+Dashboard!$F7)^(56-1)*12 -> 152464.46 | U59: =Dashboard!$F8*12 -> 240
A60: 57 | B60: =B59*(1+Dashboard!$C21) -> 3552793.3 | C60: =MAX((Dashboard!$C6-Dashboard!$C8)*(1+Dashboard!$C10/12)^(57*12)-Dashboard!$C26*((1+Dashboard!$C10/12)^(57*12)-1)/(Dashboard!$C10/12),0) -> 21372752 | D60: =I60+J60+K60+L60+M60 -> 79961.453 | E60: =E59+(D60-(C59-C60)) -> 23061412 | F60: =(Dashboard!$C6-Dashboard!$C8)-C60 -> -20972752 | G60: =G59+D60 -> 2203660.1 | H60: =B60*(1-Dashboard!$C20)-C60 -> -18033126 | I60: =IF(C59>0,Dashboard!$C26*12,0) -> 0 | J60: =B60*Dashboard!$C13 -> 42633.52 | K60: =Dashboard!$C14*12 -> 1800 | L60: =B60*Dashboard!$C16 -> 35527.933 | M60: =IF(Dashboard!$C7<0.2,C60*Dashboard!$C17,0) -> 0 | O60: =O59+T60 -> 4391651.4 | P60: =T60+U60 -> 157278.39 | Q60: =Q59*(1+Dashboard!$F11)+Dashboard!$F28*12 -> 9645734.6 | R60: =Dashboard!$F6*Dashboard!$F9+O60+U60*57 -> 4410331.4 | S60: =Q60-MAX(Q60-(Dashboard!$C8+Dashboard!$C6*Dashboard!$C19+Dashboard!$F6*Dashboard!$F9),0)*Dashboard!$F12 -> 8216874.4 | T60: =Dashboard!$F6*(1+Dashboard!$F7)^(57-1)*12 -> 157038.39 | U60: =Dashboard!$F8*12 -> 240
A61: 58 | B61: =B60*(1+Dashboard!$C21) -> 3677141.1 | C61: =MAX((Dashboard!$C6-Dashboard!$C8)*(1+Dashboard!$C10/12)^(58*12)-Dashboard!$C26*((1+Dashboard!$C10/12)^(58*12)-1)/(Dashboard!$C10/12),0) -> 22917790 | D61: =I61+J61+K61+L61+M61 -> 82697.104 | E61: =E60+(D61-(C60-C61)) -> 24689147 | F61: =(Dashboard!$C6-Dashboard!$C8)-C61 -> -22517790 | G61: =G60+D61 -> 2286357.2 | H61: =B61*(1-Dashboard!$C20)-C61 -> -19461277 | I61: =IF(C60>0,Dashboard!$C26*12,0) -> 0 | J61: =B61*Dashboard!$C13 -> 44125.693 | K61: =Dashboard!$C14*12 -> 1800 | L61: =B61*Dashboard!$C16 -> 36771.411 | M61: =IF(Dashboard!$C7<0.2,C61*Dashboard!$C17,0) -> 0 | O61: =O60+T61 -> 4553401 | P61: =T61+U61 -> 161989.54 | Q61: =Q60*(1+Dashboard!$F11)+Dashboard!$F28*12 -> 10417393 | R61: =Dashboard!$F6*Dashboard!$F9+O61+U61*58 -> 4572321 | S61: =Q61-MAX(Q61-(Dashboard!$C8+Dashboard!$C6*Dashboard!$C19+Dashboard!$F6*Dashboard!$F9),0)*Dashboard!$F12 -> 8872784.4 | T61: =Dashboard!$F6*(1+Dashboard!$F7)^(58-1)*12 -> 161749.54 | U61: =Dashboard!$F8*12 -> 240
A62: 59 | B62: =B61*(1+Dashboard!$C21) -> 3805841 | C62: =MAX((Dashboard!$C6-Dashboard!$C8)*(1+Dashboard!$C10/12)^(59*12)-Dashboard!$C26*((1+Dashboard!$C10/12)^(59*12)-1)/(Dashboard!$C10/12),0) -> 24574519 | D62: =I62+J62+K62+L62+M62 -> 85528.502 | E62: =E61+(D62-(C61-C62)) -> 26431404 | F62: =(Dashboard!$C6-Dashboard!$C8)-C62 -> -24174519 | G62: =G61+D62 -> 2371885.7 | H62: =B62*(1-Dashboard!$C20)-C62 -> -20997028 | I62: =IF(C61>0,Dashboard!$C26*12,0) -> 0 | J62: =B62*Dashboard!$C13 -> 45670.092 | K62: =Dashboard!$C14*12 -> 1800 | L62: =B62*Dashboard!$C16 -> 38058.41 | M62: =IF(Dashboard!$C7<0.2,C62*Dashboard!$C17,0) -> 0 | O62: =O61+T62 -> 4720003 | P62: =T62+U62 -> 166842.03 | Q62: =Q61*(1+Dashboard!$F11)+Dashboard!$F28*12 -> 11250785 | R62: =Dashboard!$F6*Dashboard!$F9+O62+U62*59 -> 4739163 | S62: =Q62-MAX(Q62-(Dashboard!$C8+Dashboard!$C6*Dashboard!$C19+Dashboard!$F6*Dashboard!$F9),0)*Dashboard!$F12 -> 9581167.1 | T62: =Dashboard!$F6*(1+Dashboard!$F7)^(59-1)*12 -> 166602.03 | U62: =Dashboard!$F8*12 -> 240
A63: 60 | B63: =B62*(1+Dashboard!$C21) -> 3939045.5 | C63: =MAX((Dashboard!$C6-Dashboard!$C8)*(1+Dashboard!$C10/12)^(60*12)-Dashboard!$C26*((1+Dashboard!$C10/12)^(60*12)-1)/(Dashboard!$C10/12),0) -> 26351013 | D63: =I63+J63+K63+L63+M63 -> 88459 | E63: =E62+(D63-(C62-C63)) -> 28296357 | F63: =(Dashboard!$C6-Dashboard!$C8)-C63 -> -25951013 | G63: =G62+D63 -> 2460344.7 | H63: =B63*(1-Dashboard!$C20)-C63 -> -22648310 | I63: =IF(C62>0,Dashboard!$C26*12,0) -> 0 | J63: =B63*Dashboard!$C13 -> 47268.545 | K63: =Dashboard!$C14*12 -> 1800 | L63: =B63*Dashboard!$C16 -> 39390.455 | M63: =IF(Dashboard!$C7<0.2,C63*Dashboard!$C17,0) -> 0 | O63: =O62+T63 -> 4891603.1 | P63: =T63+U63 -> 171840.09 | Q63: =Q62*(1+Dashboard!$F11)+Dashboard!$F28*12 -> 12150848 | R63: =Dashboard!$F6*Dashboard!$F9+O63+U63*60 -> 4911003.1 | S63: =Q63-MAX(Q63-(Dashboard!$C8+Dashboard!$C6*Dashboard!$C19+Dashboard!$F6*Dashboard!$F9),0)*Dashboard!$F12 -> 10346220 | T63: =Dashboard!$F6*(1+Dashboard!$F7)^(60-1)*12 -> 171600.09 | U63: =Dashboard!$F8*12 -> 240
A64: 61 | B64: =B63*(1+Dashboard!$C21) -> 4076912 | C64: =MAX((Dashboard!$C6-Dashboard!$C8)*(1+Dashboard!$C10/12)^(61*12)-Dashboard!$C26*((1+Dashboard!$C10/12)^(61*12)-1)/(Dashboard!$C10/12),0) -> 28255929 | D64: =I64+J64+K64+L64+M64 -> 91492.065 | E64: =E63+(D64-(C63-C64)) -> 30292766 | F64: =(Dashboard!$C6-Dashboard!$C8)-C64 -> -27855929 | G64: =G63+D64 -> 2551836.8 | H64: =B64*(1-Dashboard!$C20)-C64 -> -24423632 | I64: =IF(C63>0,Dashboard!$C26*12,0) -> 0 | J64: =B64*Dashboard!$C13 -> 48922.944 | K64: =Dashboard!$C14*12 -> 1800 | L64: =B64*Dashboard!$C16 -> 40769.12 | M64: =IF(Dashboard!$C7<0.2,C64*Dashboard!$C17,0) -> 0 | O64: =O63+T64 -> 5068351.2 | P64: =T64+U64 -> 176988.09 | Q64: =Q63*(1+Dashboard!$F11)+Dashboard!$F28*12 -> 13122915 | R64: =Dashboard!$F6*Dashboard!$F9+O64+U64*61 -> 5087991.2 | S64: =Q64-MAX(Q64-(Dashboard!$C8+Dashboard!$C6*Dashboard!$C19+Dashboard!$F6*Dashboard!$F9),0)*Dashboard!$F12 -> 11172478 | T64: =Dashboard!$F6*(1+Dashboard!$F7)^(61-1)*12 -> 176748.09 | U64: =Dashboard!$F8*12 -> 240
A65: 62 | B65: =B64*(1+Dashboard!$C21) -> 4219604 | C65: =MAX((Dashboard!$C6-Dashboard!$C8)*(1+Dashboard!$C10/12)^(62*12)-Dashboard!$C26*((1+Dashboard!$C10/12)^(62*12)-1)/(Dashboard!$C10/12),0) -> 30298553 | D65: =I65+J65+K65+L65+M65 -> 94631.287 | E65: =E64+(D65-(C64-C65)) -> 32430021 | F65: =(Dashboard!$C6-Dashboard!$C8)-C65 -> -29898553 | G65: =G64+D65 -> 2646468.1 | H65: =B65*(1-Dashboard!$C20)-C65 -> -26332125 | I65: =IF(C64>0,Dashboard!$C26*12,0) -> 0 | J65: =B65*Dashboard!$C13 -> 50635.248 | K65: =Dashboard!$C14*12 -> 1800 | L65: =B65*Dashboard!$C16 -> 42196.04 | M65: =IF(Dashboard!$C7<0.2,C65*Dashboard!$C17,0) -> 0 | O65: =O64+T65 -> 5250401.7 | P65: =T65+U65 -> 182290.54 | Q65: =Q64*(1+Dashboard!$F11)+Dashboard!$F28*12 -> 14172749 | R65: =Dashboard!$F6*Dashboard!$F9+O65+U65*62 -> 5270281.7 | S65: =Q65-MAX(Q65-(Dashboard!$C8+Dashboard!$C6*Dashboard!$C19+Dashboard!$F6*Dashboard!$F9),0)*Dashboard!$F12 -> 12064836 | T65: =Dashboard!$F6*(1+Dashboard!$F7)^(62-1)*12 -> 182050.54 | U65: =Dashboard!$F8*12 -> 240
A66: 63 | B66: =B65*(1+Dashboard!$C21) -> 4367290.1 | C66: =MAX((Dashboard!$C6-Dashboard!$C8)*(1+Dashboard!$C10/12)^(63*12)-Dashboard!$C26*((1+Dashboard!$C10/12)^(63*12)-1)/(Dashboard!$C10/12),0) -> 32488838 | D66: =I66+J66+K66+L66+M66 -> 97880.382 | E66: =E65+(D66-(C65-C66)) -> 34718186 | F66: =(Dashboard!$C6-Dashboard!$C8)-C66 -> -32088838 | G66: =G65+D66 -> 2744348.4 | H66: =B66*(1-Dashboard!$C20)-C66 -> -28383585 | I66: =IF(C65>0,Dashboard!$C26*12,0) -> 0 | J66: =B66*Dashboard!$C13 -> 52407.481 | K66: =Dashboard!$C14*12 -> 1800 | L66: =B66*Dashboard!$C16 -> 43672.901 | M66: =IF(Dashboard!$C7<0.2,C66*Dashboard!$C17,0) -> 0 | O66: =O65+T66 -> 5437913.8 | P66: =T66+U66 -> 187752.05 | Q66: =Q65*(1+Dashboard!$F11)+Dashboard!$F28*12 -> 15306569 | R66: =Dashboard!$F6*Dashboard!$F9+O66+U66*63 -> 5458033.8 | S66: =Q66-MAX(Q66-(Dashboard!$C8+Dashboard!$C6*Dashboard!$C19+Dashboard!$F6*Dashboard!$F9),0)*Dashboard!$F12 -> 13028583 | T66: =Dashboard!$F6*(1+Dashboard!$F7)^(63-1)*12 -> 187512.05 | U66: =Dashboard!$F8*12 -> 240
A67: 64 | B67: =B66*(1+Dashboard!$C21) -> 4520145.3 | C67: =MAX((Dashboard!$C6-Dashboard!$C8)*(1+Dashboard!$C10/12)^(64*12)-Dashboard!$C26*((1+Dashboard!$C10/12)^(64*12)-1)/(Dashboard!$C10/12),0) -> 34837458 | D67: =I67+J67+K67+L67+M67 -> 101243.2 | E67: =E66+(D67-(C66-C67)) -> 37168050 | F67: =(Dashboard!$C6-Dashboard!$C8)-C67 -> -34437458 | G67: =G66+D67 -> 2845591.6 | H67: =B67*(1-Dashboard!$C20)-C67 -> -30588522 | I67: =IF(C66>0,Dashboard!$C26*12,0) -> 0 | J67: =B67*Dashboard!$C13 -> 54241.743 | K67: =Dashboard!$C14*12 -> 1800 | L67: =B67*Dashboard!$C16 -> 45201.453 | M67: =IF(Dashboard!$C7<0.2,C67*Dashboard!$C17,0) -> 0 | O67: =O66+T67 -> 5631051.2 | P67: =T67+U67 -> 193377.41 | Q67: =Q66*(1+Dashboard!$F11)+Dashboard!$F28*12 -> 16531094 | R67: =Dashboard!$F6*Dashboard!$F9+O67+U67*64 -> 5651411.2 | S67: =Q67-MAX(Q67-(Dashboard!$C8+Dashboard!$C6*Dashboard!$C19+Dashboard!$F6*Dashboard!$F9),0)*Dashboard!$F12 -> 14069430 | T67: =Dashboard!$F6*(1+Dashboard!$F7)^(64-1)*12 -> 193137.41 | U67: =Dashboard!$F8*12 -> 240
A68: 65 | B68: =B67*(1+Dashboard!$C21) -> 4678350.3 | C68: =MAX((Dashboard!$C6-Dashboard!$C8)*(1+Dashboard!$C10/12)^(65*12)-Dashboard!$C26*((1+Dashboard!$C10/12)^(65*12)-1)/(Dashboard!$C10/12),0) -> 37355861 | D68: =I68+J68+K68+L68+M68 -> 104723.71 | E68: =E67+(D68-(C67-C68)) -> 39791176 | F68: =(Dashboard!$C6-Dashboard!$C8)-C68 -> -36955861 | G68: =G67+D68 -> 2950315.3 | H68: =B68*(1-Dashboard!$C20)-C68 -> -32958212 | I68: =IF(C67>0,Dashboard!$C26*12,0) -> 0 | J68: =B68*Dashboard!$C13 -> 56140.204 | K68: =Dashboard!$C14*12 -> 1800 | L68: =B68*Dashboard!$C16 -> 46783.503 | M68: =IF(Dashboard!$C7<0.2,C68*Dashboard!$C17,0) -> 0 | O68: =O67+T68 -> 5829982.7 | P68: =T68+U68 -> 199171.54 | Q68: =Q67*(1+Dashboard!$F11)+Dashboard!$F28*12 -> 17853582 | R68: =Dashboard!$F6*Dashboard!$F9+O68+U68*65 -> 5850582.7 | S68: =Q68-MAX(Q68-(Dashboard!$C8+Dashboard!$C6*Dashboard!$C19+Dashboard!$F6*Dashboard!$F9),0)*Dashboard!$F12 -> 15193544 | T68: =Dashboard!$F6*(1+Dashboard!$F7)^(65-1)*12 -> 198931.54 | U68: =Dashboard!$F8*12 -> 240
A69: 66 | B69: =B68*(1+Dashboard!$C21) -> 4842092.6 | C69: =MAX((Dashboard!$C6-Dashboard!$C8)*(1+Dashboard!$C10/12)^(66*12)-Dashboard!$C26*((1+Dashboard!$C10/12)^(66*12)-1)/(Dashboard!$C10/12),0) -> 40056319 | D69: =I69+J69+K69+L69+M69 -> 108326.04 | E69: =E68+(D69-(C68-C69)) -> 42599961 | F69: =(Dashboard!$C6-Dashboard!$C8)-C69 -> -39656319 | G69: =G68+D69 -> 3058641.4 | H69: =B69*(1-Dashboard!$C20)-C69 -> -35504752 | I69: =IF(C68>0,Dashboard!$C26*12,0) -> 0 | J69: =B69*Dashboard!$C13 -> 58105.111 | K69: =Dashboard!$C14*12 -> 1800 | L69: =B69*Dashboard!$C16 -> 48420.926 | M69: =IF(Dashboard!$C7<0.2,C69*Dashboard!$C17,0) -> 0 | O69: =O68+T69 -> 6034882.2 | P69: =T69+U69 -> 205139.48 | Q69: =Q68*(1+Dashboard!$F11)+Dashboard!$F28*12 -> 19281868 | R69: =Dashboard!$F6*Dashboard!$F9+O69+U69*66 -> 6055722.2 | S69: =Q69-MAX(Q69-(Dashboard!$C8+Dashboard!$C6*Dashboard!$C19+Dashboard!$F6*Dashboard!$F9),0)*Dashboard!$F12 -> 16407588 | T69: =Dashboard!$F6*(1+Dashboard!$F7)^(66-1)*12 -> 204899.48 | U69: =Dashboard!$F8*12 -> 240
A70: 67 | B70: =B69*(1+Dashboard!$C21) -> 5011565.8 | C70: =MAX((Dashboard!$C6-Dashboard!$C8)*(1+Dashboard!$C10/12)^(67*12)-Dashboard!$C26*((1+Dashboard!$C10/12)^(67*12)-1)/(Dashboard!$C10/12),0) -> 42951994 | D70: =I70+J70+K70+L70+M70 -> 112054.45 | E70: =E69+(D70-(C69-C70)) -> 45607690 | F70: =(Dashboard!$C6-Dashboard!$C8)-C70 -> -42551994 | G70: =G69+D70 -> 3170695.8 | H70: =B70*(1-Dashboard!$C20)-C70 -> -38241122 | I70: =IF(C69>0,Dashboard!$C26*12,0) -> 0 | J70: =B70*Dashboard!$C13 -> 60138.79 | K70: =Dashboard!$C14*12 -> 1800 | L70: =B70*Dashboard!$C16 -> 50115.658 | M70: =IF(Dashboard!$C7<0.2,C70*Dashboard!$C17,0) -> 0 | O70: =O69+T70 -> 6245928.7 | P70: =T70+U70 -> 211286.47 | Q70: =Q69*(1+Dashboard!$F11)+Dashboard!$F28*12 -> 20824418 | R70: =Dashboard!$F6*Dashboard!$F9+O70+U70*67 -> 6267008.7 | S70: =Q70-MAX(Q70-(Dashboard!$C8+Dashboard!$C6*Dashboard!$C19+Dashboard!$F6*Dashboard!$F9),0)*Dashboard!$F12 -> 17718755 | T70: =Dashboard!$F6*(1+Dashboard!$F7)^(67-1)*12 -> 211046.47 | U70: =Dashboard!$F8*12 -> 240
A71: 68 | B71: =B70*(1+Dashboard!$C21) -> 5186970.6 | C71: =MAX((Dashboard!$C6-Dashboard!$C8)*(1+Dashboard!$C10/12)^(68*12)-Dashboard!$C26*((1+Dashboard!$C10/12)^(68*12)-1)/(Dashboard!$C10/12),0) -> 46056997 | D71: =I71+J71+K71+L71+M71 -> 115913.35 | E71: =E70+(D71-(C70-C71)) -> 48828606 | F71: =(Dashboard!$C6-Dashboard!$C8)-C71 -> -45656997 | G71: =G70+D71 -> 3286609.2 | H71: =B71*(1-Dashboard!$C20)-C71 -> -41181244 | I71: =IF(C70>0,Dashboard!$C26*12,0) -> 0 | J71: =B71*Dashboard!$C13 -> 62243.648 | K71: =Dashboard!$C14*12 -> 1800 | L71: =B71*Dashboard!$C16 -> 51869.706 | M71: =IF(Dashboard!$C7<0.2,C71*Dashboard!$C17,0) -> 0 | O71: =O70+T71 -> 6463306.5 | P71: =T71+U71 -> 217617.86 | Q71: =Q70*(1+Dashboard!$F11)+Dashboard!$F28*12 -> 22490371 | R71: =Dashboard!$F6*Dashboard!$F9+O71+U71*68 -> 6484626.5 | S71: =Q71-MAX(Q71-(Dashboard!$C8+Dashboard!$C6*Dashboard!$C19+Dashboard!$F6*Dashboard!$F9),0)*Dashboard!$F12 -> 19134815 | T71: =Dashboard!$F6*(1+Dashboard!$F7)^(68-1)*12 -> 217377.86 | U71: =Dashboard!$F8*12 -> 240
A72: 69 | B72: =B71*(1+Dashboard!$C21) -> 5368514.6 | C72: =MAX((Dashboard!$C6-Dashboard!$C8)*(1+Dashboard!$C10/12)^(69*12)-Dashboard!$C26*((1+Dashboard!$C10/12)^(69*12)-1)/(Dashboard!$C10/12),0) -> 49386461 | D72: =I72+J72+K72+L72+M72 -> 119907.32 | E72: =E71+(D72-(C71-C72)) -> 52277977 | F72: =(Dashboard!$C6-Dashboard!$C8)-C72 -> -48986461 | G72: =G71+D72 -> 3406516.5 | H72: =B72*(1-Dashboard!$C20)-C72 -> -44340057 | I72: =IF(C71>0,Dashboard!$C26*12,0) -> 0 | J72: =B72*Dashboard!$C13 -> 64422.175 | K72: =Dashboard!$C14*12 -> 1800 | L72: =B72*Dashboard!$C16 -> 53685.146 | M72: =IF(Dashboard!$C7<0.2,C72*Dashboard!$C17,0) -> 0 | O72: =O71+T72 -> 6687205.7 | P72: =T72+U72 -> 224139.2 | Q72: =Q71*(1+Dashboard!$F11)+Dashboard!$F28*12 -> 24289601 | R72: =Dashboard!$F6*Dashboard!$F9+O72+U72*69 -> 6708765.7 | S72: =Q72-MAX(Q72-(Dashboard!$C8+Dashboard!$C6*Dashboard!$C19+Dashboard!$F6*Dashboard!$F9),0)*Dashboard!$F12 -> 20664161 | T72: =Dashboard!$F6*(1+Dashboard!$F7)^(69-1)*12 -> 223899.2 | U72: =Dashboard!$F8*12 -> 240
A73: 70 | B73: =B72*(1+Dashboard!$C21) -> 5556412.6 | C73: =MAX((Dashboard!$C6-Dashboard!$C8)*(1+Dashboard!$C10/12)^(70*12)-Dashboard!$C26*((1+Dashboard!$C10/12)^(70*12)-1)/(Dashboard!$C10/12),0) -> 52956612 | D73: =I73+J73+K73+L73+M73 -> 124041.08 | E73: =E72+(D73-(C72-C73)) -> 55972170 | F73: =(Dashboard!$C6-Dashboard!$C8)-C73 -> -52556612 | G73: =G72+D73 -> 3530557.6 | H73: =B73*(1-Dashboard!$C20)-C73 -> -47733584 | I73: =IF(C72>0,Dashboard!$C26*12,0) -> 0 | J73: =B73*Dashboard!$C13 -> 66676.952 | K73: =Dashboard!$C14*12 -> 1800 | L73: =B73*Dashboard!$C16 -> 55564.126 | M73: =IF(Dashboard!$C7<0.2,C73*Dashboard!$C17,0) -> 0 | O73: =O72+T73 -> 6917821.9 | P73: =T73+U73 -> 230856.17 | Q73: =Q72*(1+Dashboard!$F11)+Dashboard!$F28*12 -> 26232769 | R73: =Dashboard!$F6*Dashboard!$F9+O73+U73*70 -> 6939621.9 | S73: =Q73-MAX(Q73-(Dashboard!$C8+Dashboard!$C6*Dashboard!$C19+Dashboard!$F6*Dashboard!$F9),0)*Dashboard!$F12 -> 22315853 | T73: =Dashboard!$F6*(1+Dashboard!$F7)^(70-1)*12 -> 230616.17 | U73: =Dashboard!$F8*12 -> 240
A74: 71 | B74: =B73*(1+Dashboard!$C21) -> 5750887.1 | C74: =MAX((Dashboard!$C6-Dashboard!$C8)*(1+Dashboard!$C10/12)^(71*12)-Dashboard!$C26*((1+Dashboard!$C10/12)^(71*12)-1)/(Dashboard!$C10/12),0) -> 56784850 | D74: =I74+J74+K74+L74+M74 -> 128319.52 | E74: =E73+(D74-(C73-C74)) -> 59928727 | F74: =(Dashboard!$C6-Dashboard!$C8)-C74 -> -56384850 | G74: =G73+D74 -> 3658877.1 | H74: =B74*(1-Dashboard!$C20)-C74 -> -51379016 | I74: =IF(C73>0,Dashboard!$C26*12,0) -> 0 | J74: =B74*Dashboard!$C13 -> 69010.645 | K74: =Dashboard!$C14*12 -> 1800 | L74: =B74*Dashboard!$C16 -> 57508.871 | M74: =IF(Dashboard!$C7<0.2,C74*Dashboard!$C17,0) -> 0 | O74: =O73+T74 -> 7155356.6 | P74: =T74+U74 -> 237774.66 | Q74: =Q73*(1+Dashboard!$F11)+Dashboard!$F28*12 -> 28331390 | R74: =Dashboard!$F6*Dashboard!$F9+O74+U74*71 -> 7177396.6 | S74: =Q74-MAX(Q74-(Dashboard!$C8+Dashboard!$C6*Dashboard!$C19+Dashboard!$F6*Dashboard!$F9),0)*Dashboard!$F12 -> 24099682 | T74: =Dashboard!$F6*(1+Dashboard!$F7)^(71-1)*12 -> 237534.66 | U74: =Dashboard!$F8*12 -> 240
A75: 72 | B75: =B74*(1+Dashboard!$C21) -> 5952168.1 | C75: =MAX((Dashboard!$C6-Dashboard!$C8)*(1+Dashboard!$C10/12)^(72*12)-Dashboard!$C26*((1+Dashboard!$C10/12)^(72*12)-1)/(Dashboard!$C10/12),0) -> 60889831 | D75: =I75+J75+K75+L75+M75 -> 132747.7 | E75: =E74+(D75-(C74-C75)) -> 64166456 | F75: =(Dashboard!$C6-Dashboard!$C8)-C75 -> -60489831 | G75: =G74+D75 -> 3791624.8 | H75: =B75*(1-Dashboard!$C20)-C75 -> -55294793 | I75: =IF(C74>0,Dashboard!$C26*12,0) -> 0 | J75: =B75*Dashboard!$C13 -> 71426.017 | K75: =Dashboard!$C14*12 -> 1800 | L75: =B75*Dashboard!$C16 -> 59521.681 | M75: =IF(Dashboard!$C7<0.2,C75*Dashboard!$C17,0) -> 0 | O75: =O74+T75 -> 7400017.3 | P75: =T75+U75 -> 244900.7 | Q75: =Q74*(1+Dashboard!$F11)+Dashboard!$F28*12 -> 30597901 | R75: =Dashboard!$F6*Dashboard!$F9+O75+U75*72 -> 7422297.3 | S75: =Q75-MAX(Q75-(Dashboard!$C8+Dashboard!$C6*Dashboard!$C19+Dashboard!$F6*Dashboard!$F9),0)*Dashboard!$F12 -> 26026216 | T75: =Dashboard!$F6*(1+Dashboard!$F7)^(72-1)*12 -> 244660.7 | U75: =Dashboard!$F8*12 -> 240
A76: 73 | B76: =B75*(1+Dashboard!$C21) -> 6160494 | C76: =MAX((Dashboard!$C6-Dashboard!$C8)*(1+Dashboard!$C10/12)^(73*12)-Dashboard!$C26*((1+Dashboard!$C10/12)^(73*12)-1)/(Dashboard!$C10/12),0) -> 65291562 | D76: =I76+J76+K76+L76+M76 -> 137330.87 | E76: =E75+(D76-(C75-C76)) -> 68705518 | F76: =(Dashboard!$C6-Dashboard!$C8)-C76 -> -64891562 | G76: =G75+D76 -> 3928955.7 | H76: =B76*(1-Dashboard!$C20)-C76 -> -59500698 | I76: =IF(C75>0,Dashboard!$C26*12,0) -> 0 | J76: =B76*Dashboard!$C13 -> 73925.928 | K76: =Dashboard!$C14*12 -> 1800 | L76: =B76*Dashboard!$C16 -> 61604.94 | M76: =IF(Dashboard!$C7<0.2,C76*Dashboard!$C17,0) -> 0 | O76: =O75+T76 -> 7652017.8 | P76: =T76+U76 -> 252240.52 | Q76: =Q75*(1+Dashboard!$F11)+Dashboard!$F28*12 -> 33045734 | R76: =Dashboard!$F6*Dashboard!$F9+O76+U76*73 -> 7674537.8 | S76: =Q76-MAX(Q76-(Dashboard!$C8+Dashboard!$C6*Dashboard!$C19+Dashboard!$F6*Dashboard!$F9),0)*Dashboard!$F12 -> 28106874 | T76: =Dashboard!$F6*(1+Dashboard!$F7)^(73-1)*12 -> 252000.52 | U76: =Dashboard!$F8*12 -> 240
A77: 74 | B77: =B76*(1+Dashboard!$C21) -> 6376111.3 | C77: =MAX((Dashboard!$C6-Dashboard!$C8)*(1+Dashboard!$C10/12)^(74*12)-Dashboard!$C26*((1+Dashboard!$C10/12)^(74*12)-1)/(Dashboard!$C10/12),0) -> 70011494 | D77: =I77+J77+K77+L77+M77 -> 142074.45 | E77: =E76+(D77-(C76-C77)) -> 73567524 | F77: =(Dashboard!$C6-Dashboard!$C8)-C77 -> -69611494 | G77: =G76+D77 -> 4071030.1 | H77: =B77*(1-Dashboard!$C20)-C77 -> -64017950 | I77: =IF(C76>0,Dashboard!$C26*12,0) -> 0 | J77: =B77*Dashboard!$C13 -> 76513.336 | K77: =Dashboard!$C14*12 -> 1800 | L77: =B77*Dashboard!$C16 -> 63761.113 | M77: =IF(Dashboard!$C7<0.2,C77*Dashboard!$C17,0) -> 0 | O77: =O76+T77 -> 7911578.3 | P77: =T77+U77 -> 259800.53 | Q77: =Q76*(1+Dashboard!$F11)+Dashboard!$F28*12 -> 35689392 | R77: =Dashboard!$F6*Dashboard!$F9+O77+U77*74 -> 7934338.3 | S77: =Q77-MAX(Q77-(Dashboard!$C8+Dashboard!$C6*Dashboard!$C19+Dashboard!$F6*Dashboard!$F9),0)*Dashboard!$F12 -> 30353983 | T77: =Dashboard!$F6*(1+Dashboard!$F7)^(74-1)*12 -> 259560.53 | U77: =Dashboard!$F8*12 -> 240
A78: 75 | B78: =B77*(1+Dashboard!$C21) -> 6599275.2 | C78: =MAX((Dashboard!$C6-Dashboard!$C8)*(1+Dashboard!$C10/12)^(75*12)-Dashboard!$C26*((1+Dashboard!$C10/12)^(75*12)-1)/(Dashboard!$C10/12),0) -> 75072631 | D78: =I78+J78+K78+L78+M78 -> 146984.05 | E78: =E77+(D78-(C77-C78)) -> 78775645 | F78: =(Dashboard!$C6-Dashboard!$C8)-C78 -> -74672631 | G78: =G77+D78 -> 4218014.2 | H78: =B78*(1-Dashboard!$C20)-C78 -> -68869312 | I78: =IF(C77>0,Dashboard!$C26*12,0) -> 0 | J78: =B78*Dashboard!$C13 -> 79191.302 | K78: =Dashboard!$C14*12 -> 1800 | L78: =B78*Dashboard!$C16 -> 65992.752 | M78: =IF(Dashboard!$C7<0.2,C78*Dashboard!$C17,0) -> 0 | O78: =O77+T78 -> 8178925.7 | P78: =T78+U78 -> 267587.35 | Q78: =Q77*(1+Dashboard!$F11)+Dashboard!$F28*12 -> 38544544 | R78: =Dashboard!$F6*Dashboard!$F9+O78+U78*75 -> 8201925.7 | S78: =Q78-MAX(Q78-(Dashboard!$C8+Dashboard!$C6*Dashboard!$C19+Dashboard!$F6*Dashboard!$F9),0)*Dashboard!$F12 -> 32780862 | T78: =Dashboard!$F6*(1+Dashboard!$F7)^(75-1)*12 -> 267347.35 | U78: =Dashboard!$F8*12 -> 240
A79: 76 | B79: =B78*(1+Dashboard!$C21) -> 6830249.8 | C79: =MAX((Dashboard!$C6-Dashboard!$C8)*(1+Dashboard!$C10/12)^(76*12)-Dashboard!$C26*((1+Dashboard!$C10/12)^(76*12)-1)/(Dashboard!$C10/12),0) -> 80499637 | D79: =I79+J79+K79+L79+M79 -> 152065.5 | E79: =E78+(D79-(C78-C79)) -> 84354717 | F79: =(Dashboard!$C6-Dashboard!$C8)-C79 -> -80099637 | G79: =G78+D79 -> 4370079.7 | H79: =B79*(1-Dashboard!$C20)-C79 -> -74079203 | I79: =IF(C78>0,Dashboard!$C26*12,0) -> 0 | J79: =B79*Dashboard!$C13 -> 81962.998 | K79: =Dashboard!$C14*12 -> 1800 | L79: =B79*Dashboard!$C16 -> 68302.498 | M79: =IF(Dashboard!$C7<0.2,C79*Dashboard!$C17,0) -> 0 | O79: =O78+T79 -> 8454293.4 | P79: =T79+U79 -> 275607.77 | Q79: =Q78*(1+Dashboard!$F11)+Dashboard!$F28*12 -> 41628107 | R79: =Dashboard!$F6*Dashboard!$F9+O79+U79*76 -> 8477533.4 | S79: =Q79-MAX(Q79-(Dashboard!$C8+Dashboard!$C6*Dashboard!$C19+Dashboard!$F6*Dashboard!$F9),0)*Dashboard!$F12 -> 35401891 | T79: =Dashboard!$F6*(1+Dashboard!$F7)^(76-1)*12 -> 275367.77 | U79: =Dashboard!$F8*12 -> 240
A80: 77 | B80: =B79*(1+Dashboard!$C21) -> 7069308.6 | C80: =MAX((Dashboard!$C6-Dashboard!$C8)*(1+Dashboard!$C10/12)^(77*12)-Dashboard!$C26*((1+Dashboard!$C10/12)^(77*12)-1)/(Dashboard!$C10/12),0) -> 86318963 | D80: =I80+J80+K80+L80+M80 -> 157324.79 | E80: =E79+(D80-(C79-C80)) -> 90331367 | F80: =(Dashboard!$C6-Dashboard!$C8)-C80 -> -85918963 | G80: =G79+D80 -> 4527404.5 | H80: =B80*(1-Dashboard!$C20)-C80 -> -79673813 | I80: =IF(C79>0,Dashboard!$C26*12,0) -> 0 | J80: =B80*Dashboard!$C13 -> 84831.703 | K80: =Dashboard!$C14*12 -> 1800 | L80: =B80*Dashboard!$C16 -> 70693.086 | M80: =IF(Dashboard!$C7<0.2,C80*Dashboard!$C17,0) -> 0 | O80: =O79+T80 -> 8737922.2 | P80: =T80+U80 -> 283868.8 | Q80: =Q79*(1+Dashboard!$F11)+Dashboard!$F28*12 -> 44958356 | R80: =Dashboard!$F6*Dashboard!$F9+O80+U80*77 -> 8761402.2 | S80: =Q80-MAX(Q80-(Dashboard!$C8+Dashboard!$C6*Dashboard!$C19+Dashboard!$F6*Dashboard!$F9),0)*Dashboard!$F12 -> 38232602 | T80: =Dashboard!$F6*(1+Dashboard!$F7)^(77-1)*12 -> 283628.8 | U80: =Dashboard!$F8*12 -> 240
A81: 78 | B81: =B80*(1+Dashboard!$C21) -> 7316734.4 | C81: =MAX((Dashboard!$C6-Dashboard!$C8)*(1+Dashboard!$C10/12)^(78*12)-Dashboard!$C26*((1+Dashboard!$C10/12)^(78*12)-1)/(Dashboard!$C10/12),0) -> 92558968 | D81: =I81+J81+K81+L81+M81 -> 162768.16 | E81: =E80+(D81-(C80-C81)) -> 96734140 | F81: =(Dashboard!$C6-Dashboard!$C8)-C81 -> -92158968 | G81: =G80+D81 -> 4690172.6 | H81: =B81*(1-Dashboard!$C20)-C81 -> -85681237 | I81: =IF(C80>0,Dashboard!$C26*12,0) -> 0 | J81: =B81*Dashboard!$C13 -> 87800.812 | K81: =Dashboard!$C14*12 -> 1800 | L81: =B81*Dashboard!$C16 -> 73167.344 | M81: =IF(Dashboard!$C7<0.2,C81*Dashboard!$C17,0) -> 0 | O81: =O80+T81 -> 9030059.9 | P81: =T81+U81 -> 292377.67 | Q81: =Q80*(1+Dashboard!$F11)+Dashboard!$F28*12 -> 48555024 | R81: =Dashboard!$F6*Dashboard!$F9+O81+U81*78 -> 9053779.9 | S81: =Q81-MAX(Q81-(Dashboard!$C8+Dashboard!$C6*Dashboard!$C19+Dashboard!$F6*Dashboard!$F9),0)*Dashboard!$F12 -> 41289770 | T81: =Dashboard!$F6*(1+Dashboard!$F7)^(78-1)*12 -> 292137.67 | U81: =Dashboard!$F8*12 -> 240
A82: 79 | B82: =B81*(1+Dashboard!$C21) -> 7572820.1 | C82: =MAX((Dashboard!$C6-Dashboard!$C8)*(1+Dashboard!$C10/12)^(79*12)-Dashboard!$C26*((1+Dashboard!$C10/12)^(79*12)-1)/(Dashboard!$C10/12),0) -> 99250063 | D82: =I82+J82+K82+L82+M82 -> 168402.04 | E82: =E81+(D82-(C81-C82)) -> 1.0359364e+08 | F82: =(Dashboard!$C6-Dashboard!$C8)-C82 -> -98850063 | G82: =G81+D82 -> 4858574.7 | H82: =B82*(1-Dashboard!$C20)-C82 -> -92131612 | I82: =IF(C81>0,Dashboard!$C26*12,0) -> 0 | J82: =B82*Dashboard!$C13 -> 90873.841 | K82: =Dashboard!$C14*12 -> 1800 | L82: =B82*Dashboard!$C16 -> 75728.201 | M82: =IF(Dashboard!$C7<0.2,C82*Dashboard!$C17,0) -> 0 | O82: =O81+T82 -> 9330961.7 | P82: =T82+U82 -> 301141.8 | Q82: =Q81*(1+Dashboard!$F11)+Dashboard!$F28*12 -> 52439426 | R82: =Dashboard!$F6*Dashboard!$F9+O82+U82*79 -> 9354921.7 | S82: =Q82-MAX(Q82-(Dashboard!$C8+Dashboard!$C6*Dashboard!$C19+Dashboard!$F6*Dashboard!$F9),0)*Dashboard!$F12 -> 44591512 | T82: =Dashboard!$F6*(1+Dashboard!$F7)^(79-1)*12 -> 300901.8 | U82: =Dashboard!$F8*12 -> 240
A83: 80 | B83: =B82*(1+Dashboard!$C21) -> 7837868.8 | C83: =MAX((Dashboard!$C6-Dashboard!$C8)*(1+Dashboard!$C10/12)^(80*12)-Dashboard!$C26*((1+Dashboard!$C10/12)^(80*12)-1)/(Dashboard!$C10/12),0) -> 1.0642486e+08 | D83: =I83+J83+K83+L83+M83 -> 174233.11 | E83: =E82+(D83-(C82-C83)) -> 1.1094267e+08 | F83: =(Dashboard!$C6-Dashboard!$C8)-C83 -> -1.0602486e+08 | G83: =G82+D83 -> 5032807.8 | H83: =B83*(1-Dashboard!$C20)-C83 -> -99057261 | I83: =IF(C82>0,Dashboard!$C26*12,0) -> 0 | J83: =B83*Dashboard!$C13 -> 94054.425 | K83: =Dashboard!$C14*12 -> 1800 | L83: =B83*Dashboard!$C16 -> 78378.688 | M83: =IF(Dashboard!$C7<0.2,C83*Dashboard!$C17,0) -> 0 | O83: =O82+T83 -> 9640890.6 | P83: =T83+U83 -> 310168.85 | Q83: =Q82*(1+Dashboard!$F11)+Dashboard!$F28*12 -> 56634580 | R83: =Dashboard!$F6*Dashboard!$F9+O83+U83*80 -> 9665090.6 | S83: =Q83-MAX(Q83-(Dashboard!$C8+Dashboard!$C6*Dashboard!$C19+Dashboard!$F6*Dashboard!$F9),0)*Dashboard!$F12 -> 48157393 | T83: =Dashboard!$F6*(1+Dashboard!$F7)^(80-1)*12 -> 309928.85 | U83: =Dashboard!$F8*12 -> 240
A84: 81 | B84: =B83*(1+Dashboard!$C21) -> 8112194.2 | C84: =MAX((Dashboard!$C6-Dashboard!$C8)*(1+Dashboard!$C10/12)^(81*12)-Dashboard!$C26*((1+Dashboard!$C10/12)^(81*12)-1)/(Dashboard!$C10/12),0) -> 1.1411832e+08 | D84: =I84+J84+K84+L84+M84 -> 180268.27 | E84: =E83+(D84-(C83-C84)) -> 1.188164e+08 | F84: =(Dashboard!$C6-Dashboard!$C8)-C84 -> -1.1371832e+08 | G84: =G83+D84 -> 5213076 | H84: =B84*(1-Dashboard!$C20)-C84 -> -1.0649286e+08 | I84: =IF(C83>0,Dashboard!$C26*12,0) -> 0 | J84: =B84*Dashboard!$C13 -> 97346.33 | K84: =Dashboard!$C14*12 -> 1800 | L84: =B84*Dashboard!$C16 -> 81121.942 | M84: =IF(Dashboard!$C7<0.2,C84*Dashboard!$C17,0) -> 0 | O84: =O83+T84 -> 9960117.3 | P84: =T84+U84 -> 319466.72 | Q84: =Q83*(1+Dashboard!$F11)+Dashboard!$F28*12 -> 61165347 | R84: =Dashboard!$F6*Dashboard!$F9+O84+U84*81 -> 9984557.3 | S84: =Q84-MAX(Q84-(Dashboard!$C8+Dashboard!$C6*Dashboard!$C19+Dashboard!$F6*Dashboard!$F9),0)*Dashboard!$F12 -> 52008545 | T84: =Dashboard!$F6*(1+Dashboard!$F7)^(81-1)*12 -> 319226.72 | U84: =Dashboard!$F8*12 -> 240
A85: 82 | B85: =B84*(1+Dashboard!$C21) -> 8396121 | C85: =MAX((Dashboard!$C6-Dashboard!$C8)*(1+Dashboard!$C10/12)^(82*12)-Dashboard!$C26*((1+Dashboard!$C10/12)^(82*12)-1)/(Dashboard!$C10/12),0) -> 1.2236794e+08 | D85: =I85+J85+K85+L85+M85 -> 186514.66 | E85: =E84+(D85-(C84-C85)) -> 1.2725253e+08 | F85: =(Dashboard!$C6-Dashboard!$C8)-C85 -> -1.2196794e+08 | G85: =G84+D85 -> 5399590.7 | H85: =B85*(1-Dashboard!$C20)-C85 -> -1.1447559e+08 | I85: =IF(C84>0,Dashboard!$C26*12,0) -> 0 | J85: =B85*Dashboard!$C13 -> 100753.45 | K85: =Dashboard!$C14*12 -> 1800 | L85: =B85*Dashboard!$C16 -> 83961.21 | M85: =IF(Dashboard!$C7<0.2,C85*Dashboard!$C17,0) -> 0 | O85: =O84+T85 -> 10288921 | P85: =T85+U85 -> 329043.52 | Q85: =Q84*(1+Dashboard!$F11)+Dashboard!$F28*12 -> 66058574 | R85: =Dashboard!$F6*Dashboard!$F9+O85+U85*82 -> 10313601 | S85: =Q85-MAX(Q85-(Dashboard!$C8+Dashboard!$C6*Dashboard!$C19+Dashboard!$F6*Dashboard!$F9),0)*Dashboard!$F12 -> 56167788 | T85: =Dashboard!$F6*(1+Dashboard!$F7)^(82-1)*12 -> 328803.52 | U85: =Dashboard!$F8*12 -> 240
A86: 83 | B86: =B85*(1+Dashboard!$C21) -> 8689985.2 | C86: =MAX((Dashboard!$C6-Dashboard!$C8)*(1+Dashboard!$C10/12)^(83*12)-Dashboard!$C26*((1+Dashboard!$C10/12)^(83*12)-1)/(Dashboard!$C10/12),0) -> 1.3121393e+08 | D86: =I86+J86+K86+L86+M86 -> 192979.67 | E86: =E85+(D86-(C85-C86)) -> 1.362915e+08 | F86: =(Dashboard!$C6-Dashboard!$C8)-C86 -> -1.3081393e+08 | G86: =G85+D86 -> 5592570.4 | H86: =B86*(1-Dashboard!$C20)-C86 -> -1.2304534e+08 | I86: =IF(C85>0,Dashboard!$C26*12,0) -> 0 | J86: =B86*Dashboard!$C13 -> 104279.82 | K86: =Dashboard!$C14*12 -> 1800 | L86: =B86*Dashboard!$C16 -> 86899.852 | M86: =IF(Dashboard!$C7<0.2,C86*Dashboard!$C17,0) -> 0 | O86: =O85+T86 -> 10627588 | P86: =T86+U86 -> 338907.62 | Q86: =Q85*(1+Dashboard!$F11)+Dashboard!$F28*12 -> 71343260 | R86: =Dashboard!$F6*Dashboard!$F9+O86+U86*83 -> 10652508 | S86: =Q86-MAX(Q86-(Dashboard!$C8+Dashboard!$C6*Dashboard!$C19+Dashboard!$F6*Dashboard!$F9),0)*Dashboard!$F12 -> 60659771 | T86: =Dashboard!$F6*(1+Dashboard!$F7)^(83-1)*12 -> 338667.62 | U86: =Dashboard!$F8*12 -> 240
A87: 84 | B87: =B86*(1+Dashboard!$C21) -> 8994134.7 | C87: =MAX((Dashboard!$C6-Dashboard!$C8)*(1+Dashboard!$C10/12)^(84*12)-Dashboard!$C26*((1+Dashboard!$C10/12)^(84*12)-1)/(Dashboard!$C10/12),0) -> 1.406994e+08 | D87: =I87+J87+K87+L87+M87 -> 199670.96 | E87: =E86+(D87-(C86-C87)) -> 1.4597664e+08 | F87: =(Dashboard!$C6-Dashboard!$C8)-C87 -> -1.402994e+08 | G87: =G86+D87 -> 5792241.3 | H87: =B87*(1-Dashboard!$C20)-C87 -> -1.3224491e+08 | I87: =IF(C86>0,Dashboard!$C26*12,0) -> 0 | J87: =B87*Dashboard!$C13 -> 107929.62 | K87: =Dashboard!$C14*12 -> 1800 | L87: =B87*Dashboard!$C16 -> 89941.347 | M87: =IF(Dashboard!$C7<0.2,C87*Dashboard!$C17,0) -> 0 | O87: =O86+T87 -> 10976416 | P87: =T87+U87 -> 349067.65 | Q87: =Q86*(1+Dashboard!$F11)+Dashboard!$F28*12 -> 77050721 | R87: =Dashboard!$F6*Dashboard!$F9+O87+U87*84 -> 11001576 | S87: =Q87-MAX(Q87-(Dashboard!$C8+Dashboard!$C6*Dashboard!$C19+Dashboard!$F6*Dashboard!$F9),0)*Dashboard!$F12 -> 65511113 | T87: =Dashboard!$F6*(1+Dashboard!$F7)^(84-1)*12 -> 348827.65 | U87: =Dashboard!$F8*12 -> 240
A88: 85 | B88: =B87*(1+Dashboard!$C21) -> 9308929.4 | C88: =MAX((Dashboard!$C6-Dashboard!$C8)*(1+Dashboard!$C10/12)^(85*12)-Dashboard!$C26*((1+Dashboard!$C10/12)^(85*12)-1)/(Dashboard!$C10/12),0) -> 1.5087057e+08 | D88: =I88+J88+K88+L88+M88 -> 206596.45 | E88: =E87+(D88-(C87-C88)) -> 1.563544e+08 | F88: =(Dashboard!$C6-Dashboard!$C8)-C88 -> -1.5047057e+08 | G88: =G87+D88 -> 5998837.8 | H88: =B88*(1-Dashboard!$C20)-C88 -> -1.4212017e+08 | I88: =IF(C87>0,Dashboard!$C26*12,0) -> 0 | J88: =B88*Dashboard!$C13 -> 111707.15 | K88: =Dashboard!$C14*12 -> 1800 | L88: =B88*Dashboard!$C16 -> 93089.294 | M88: =IF(Dashboard!$C7<0.2,C88*Dashboard!$C17,0) -> 0 | O88: =O87+T88 -> 11335709 | P88: =T88+U88 -> 359532.48 | Q88: =Q87*(1+Dashboard!$F11)+Dashboard!$F28*12 -> 83214779 | R88: =Dashboard!$F6*Dashboard!$F9+O88+U88*85 -> 11361109 | S88: =Q88-MAX(Q88-(Dashboard!$C8+Dashboard!$C6*Dashboard!$C19+Dashboard!$F6*Dashboard!$F9),0)*Dashboard!$F12 -> 70750562 | T88: =Dashboard!$F6*(1+Dashboard!$F7)^(85-1)*12 -> 359292.48 | U88: =Dashboard!$F8*12 -> 240
A89: 86 | B89: =B88*(1+Dashboard!$C21) -> 9634741.9 | C89: =MAX((Dashboard!$C6-Dashboard!$C8)*(1+Dashboard!$C10/12)^(86*12)-Dashboard!$C26*((1+Dashboard!$C10/12)^(86*12)-1)/(Dashboard!$C10/12),0) -> 1.6177701e+08 | D89: =I89+J89+K89+L89+M89 -> 213764.32 | E89: =E88+(D89-(C88-C89)) -> 1.6747461e+08 | F89: =(Dashboard!$C6-Dashboard!$C8)-C89 -> -1.6137701e+08 | G89: =G88+D89 -> 6212602.1 | H89: =B89*(1-Dashboard!$C20)-C89 -> -1.5272035e+08 | I89: =IF(C88>0,Dashboard!$C26*12,0) -> 0 | J89: =B89*Dashboard!$C13 -> 115616.9 | K89: =Dashboard!$C14*12 -> 1800 | L89: =B89*Dashboard!$C16 -> 96347.419 | M89: =IF(Dashboard!$C7<0.2,C89*Dashboard!$C17,0) -> 0 | O89: =O88+T89 -> 11705780 | P89: =T89+U89 -> 370311.26 | Q89: =Q88*(1+Dashboard!$F11)+Dashboard!$F28*12 -> 89871961 | R89: =Dashboard!$F6*Dashboard!$F9+O89+U89*86 -> 11731420 | S89: =Q89-MAX(Q89-(Dashboard!$C8+Dashboard!$C6*Dashboard!$C19+Dashboard!$F6*Dashboard!$F9),0)*Dashboard!$F12 -> 76409167 | T89: =Dashboard!$F6*(1+Dashboard!$F7)^(86-1)*12 -> 370071.26 | U89: =Dashboard!$F8*12 -> 240
A90: 87 | B90: =B89*(1+Dashboard!$C21) -> 9971957.9 | C90: =MAX((Dashboard!$C6-Dashboard!$C8)*(1+Dashboard!$C10/12)^(87*12)-Dashboard!$C26*((1+Dashboard!$C10/12)^(87*12)-1)/(Dashboard!$C10/12),0) -> 1.7347189e+08 | D90: =I90+J90+K90+L90+M90 -> 221183.07 | E90: =E89+(D90-(C89-C90)) -> 1.7939067e+08 | F90: =(Dashboard!$C6-Dashboard!$C8)-C90 -> -1.7307189e+08 | G90: =G89+D90 -> 6433785.2 | H90: =B90*(1-Dashboard!$C20)-C90 -> -1.6409825e+08 | I90: =IF(C89>0,Dashboard!$C26*12,0) -> 0 | J90: =B90*Dashboard!$C13 -> 119663.49 | K90: =Dashboard!$C14*12 -> 1800 | L90: =B90*Dashboard!$C16 -> 99719.579 | M90: =IF(Dashboard!$C7<0.2,C90*Dashboard!$C17,0) -> 0 | O90: =O89+T90 -> 12086953 | P90: =T90+U90 -> 381413.39 | Q90: =Q89*(1+Dashboard!$F11)+Dashboard!$F28*12 -> 97061718 | R90: =Dashboard!$F6*Dashboard!$F9+O90+U90*87 -> 12112833 | S90: =Q90-MAX(Q90-(Dashboard!$C8+Dashboard!$C6*Dashboard!$C19+Dashboard!$F6*Dashboard!$F9),0)*Dashboard!$F12 -> 82520460 | T90: =Dashboard!$F6*(1+Dashboard!$F7)^(87-1)*12 -> 381173.39 | U90: =Dashboard!$F8*12 -> 240
A91: 88 | B91: =B90*(1+Dashboard!$C21) -> 10320976 | C91: =MAX((Dashboard!$C6-Dashboard!$C8)*(1+Dashboard!$C10/12)^(88*12)-Dashboard!$C26*((1+Dashboard!$C10/12)^(88*12)-1)/(Dashboard!$C10/12),0) -> 1.8601218e+08 | D91: =I91+J91+K91+L91+M91 -> 228861.48 | E91: =E90+(D91-(C90-C91)) -> 1.9215983e+08 | F91: =(Dashboard!$C6-Dashboard!$C8)-C91 -> -1.8561218e+08 | G91: =G90+D91 -> 6662646.7 | H91: =B91*(1-Dashboard!$C20)-C91 -> -1.7631046e+08 | I91: =IF(C90>0,Dashboard!$C26*12,0) -> 0 | J91: =B91*Dashboard!$C13 -> 123851.72 | K91: =Dashboard!$C14*12 -> 1800 | L91: =B91*Dashboard!$C16 -> 103209.76 | M91: =IF(Dashboard!$C7<0.2,C91*Dashboard!$C17,0) -> 0 | O91: =O90+T91 -> 12479562 | P91: =T91+U91 -> 392848.6 | Q91: =Q90*(1+Dashboard!$F11)+Dashboard!$F28*12 -> 1.0482666e+08 | R91: =Dashboard!$F6*Dashboard!$F9+O91+U91*88 -> 12505682 | S91: =Q91-MAX(Q91-(Dashboard!$C8+Dashboard!$C6*Dashboard!$C19+Dashboard!$F6*Dashboard!$F9),0)*Dashboard!$F12 -> 89120657 | T91: =Dashboard!$F6*(1+Dashboard!$F7)^(88-1)*12 -> 392608.6 | U91: =Dashboard!$F8*12 -> 240
A92: 89 | B92: =B91*(1+Dashboard!$C21) -> 10682211 | C92: =MAX((Dashboard!$C6-Dashboard!$C8)*(1+Dashboard!$C10/12)^(89*12)-Dashboard!$C26*((1+Dashboard!$C10/12)^(89*12)-1)/(Dashboard!$C10/12),0) -> 1.9945902e+08 | D92: =I92+J92+K92+L92+M92 -> 236808.63 | E92: =E91+(D92-(C91-C92)) -> 2.0584347e+08 | F92: =(Dashboard!$C6-Dashboard!$C8)-C92 -> -1.9905902e+08 | G92: =G91+D92 -> 6899455.3 | H92: =B92*(1-Dashboard!$C20)-C92 -> -1.8941774e+08 | I92: =IF(C91>0,Dashboard!$C26*12,0) -> 0 | J92: =B92*Dashboard!$C13 -> 128186.53 | K92: =Dashboard!$C14*12 -> 1800 | L92: =B92*Dashboard!$C16 -> 106822.11 | M92: =IF(Dashboard!$C7<0.2,C92*Dashboard!$C17,0) -> 0 | O92: =O91+T92 -> 12883949 | P92: =T92+U92 -> 404626.85 | Q92: =Q91*(1+Dashboard!$F11)+Dashboard!$F28*12 -> 1.1321279e+08 | R92: =Dashboard!$F6*Dashboard!$F9+O92+U92*89 -> 12910309 | S92: =Q92-MAX(Q92-(Dashboard!$C8+Dashboard!$C6*Dashboard!$C19+Dashboard!$F6*Dashboard!$F9),0)*Dashboard!$F12 -> 96248870 | T92: =Dashboard!$F6*(1+Dashboard!$F7)^(89-1)*12 -> 404386.85 | U92: =Dashboard!$F8*12 -> 240
A93: 90 | B93: =B92*(1+Dashboard!$C21) -> 11056088 | C93: =MAX((Dashboard!$C6-Dashboard!$C8)*(1+Dashboard!$C10/12)^(90*12)-Dashboard!$C26*((1+Dashboard!$C10/12)^(90*12)-1)/(Dashboard!$C10/12),0) -> 2.1387793e+08 | D93: =I93+J93+K93+L93+M93 -> 245033.94 | E93: =E92+(D93-(C92-C93)) -> 2.2050742e+08 | F93: =(Dashboard!$C6-Dashboard!$C8)-C93 -> -2.1347793e+08 | G93: =G92+D93 -> 7144489.2 | H93: =B93*(1-Dashboard!$C20)-C93 -> -2.034852e+08 | I93: =IF(C92>0,Dashboard!$C26*12,0) -> 0 | J93: =B93*Dashboard!$C13 -> 132673.06 | K93: =Dashboard!$C14*12 -> 1800 | L93: =B93*Dashboard!$C16 -> 110560.88 | M93: =IF(Dashboard!$C7<0.2,C93*Dashboard!$C17,0) -> 0 | O93: =O92+T93 -> 13300467 | P93: =T93+U93 -> 416758.46 | Q93: =Q92*(1+Dashboard!$F11)+Dashboard!$F28*12 -> 1.2226981e+08 | R93: =Dashboard!$F6*Dashboard!$F9+O93+U93*90 -> 13327067 | S93: =Q93-MAX(Q93-(Dashboard!$C8+Dashboard!$C6*Dashboard!$C19+Dashboard!$F6*Dashboard!$F9),0)*Dashboard!$F12 -> 1.0394734e+08 | T93: =Dashboard!$F6*(1+Dashboard!$F7)^(90-1)*12 -> 416518.46 | U93: =Dashboard!$F8*12 -> 240
A94: 91 | B94: =B93*(1+Dashboard!$C21) -> 11443051 | C94: =MAX((Dashboard!$C6-Dashboard!$C8)*(1+Dashboard!$C10/12)^(91*12)-Dashboard!$C26*((1+Dashboard!$C10/12)^(91*12)-1)/(Dashboard!$C10/12),0) -> 2.2933918e+08 | D94: =I94+J94+K94+L94+M94 -> 253547.12 | E94: =E93+(D94-(C93-C94)) -> 2.3622222e+08 | F94: =(Dashboard!$C6-Dashboard!$C8)-C94 -> -2.2893918e+08 | G94: =G93+D94 -> 7398036.4 | H94: =B94*(1-Dashboard!$C20)-C94 -> -2.1858271e+08 | I94: =IF(C93>0,Dashboard!$C26*12,0) -> 0 | J94: =B94*Dashboard!$C13 -> 137316.61 | K94: =Dashboard!$C14*12 -> 1800 | L94: =B94*Dashboard!$C16 -> 114430.51 | M94: =IF(Dashboard!$C7<0.2,C94*Dashboard!$C17,0) -> 0 | O94: =O93+T94 -> 13729481 | P94: =T94+U94 -> 429254.01 | Q94: =Q93*(1+Dashboard!$F11)+Dashboard!$F28*12 -> 1.320514e+08 | R94: =Dashboard!$F6*Dashboard!$F9+O94+U94*91 -> 13756321 | S94: =Q94-MAX(Q94-(Dashboard!$C8+Dashboard!$C6*Dashboard!$C19+Dashboard!$F6*Dashboard!$F9),0)*Dashboard!$F12 -> 1.1226169e+08 | T94: =Dashboard!$F6*(1+Dashboard!$F7)^(91-1)*12 -> 429014.01 | U94: =Dashboard!$F8*12 -> 240
A95: 92 | B95: =B94*(1+Dashboard!$C21) -> 11843558 | C95: =MAX((Dashboard!$C6-Dashboard!$C8)*(1+Dashboard!$C10/12)^(92*12)-Dashboard!$C26*((1+Dashboard!$C10/12)^(92*12)-1)/(Dashboard!$C10/12),0) -> 2.4591813e+08 | D95: =I95+J95+K95+L95+M95 -> 262358.27 | E95: =E94+(D95-(C94-C95)) -> 2.5306352e+08 | F95: =(Dashboard!$C6-Dashboard!$C8)-C95 -> -2.4551813e+08 | G95: =G94+D95 -> 7660394.6 | H95: =B95*(1-Dashboard!$C20)-C95 -> -2.3478518e+08 | I95: =IF(C94>0,Dashboard!$C26*12,0) -> 0 | J95: =B95*Dashboard!$C13 -> 142122.69 | K95: =Dashboard!$C14*12 -> 1800 | L95: =B95*Dashboard!$C16 -> 118435.58 | M95: =IF(Dashboard!$C7<0.2,C95*Dashboard!$C17,0) -> 0 | O95: =O94+T95 -> 14171366 | P95: =T95+U95 -> 442124.43 | Q95: =Q94*(1+Dashboard!$F11)+Dashboard!$F28*12 -> 1.4261551e+08 | R95: =Dashboard!$F6*Dashboard!$F9+O95+U95*92 -> 14198446 | S95: =Q95-MAX(Q95-(Dashboard!$C8+Dashboard!$C6*Dashboard!$C19+Dashboard!$F6*Dashboard!$F9),0)*Dashboard!$F12 -> 1.2124118e+08 | T95: =Dashboard!$F6*(1+Dashboard!$F7)^(92-1)*12 -> 441884.43 | U95: =Dashboard!$F8*12 -> 240
A96: 93 | B96: =B95*(1+Dashboard!$C21) -> 12258082 | C96: =MAX((Dashboard!$C6-Dashboard!$C8)*(1+Dashboard!$C10/12)^(93*12)-Dashboard!$C26*((1+Dashboard!$C10/12)^(93*12)-1)/(Dashboard!$C10/12),0) -> 2.6369557e+08 | D96: =I96+J96+K96+L96+M96 -> 271477.81 | E96: =E95+(D96-(C95-C96)) -> 2.7111244e+08 | F96: =(Dashboard!$C6-Dashboard!$C8)-C96 -> -2.6329557e+08 | G96: =G95+D96 -> 7931872.4 | H96: =B96*(1-Dashboard!$C20)-C96 -> -2.5217297e+08 | I96: =IF(C95>0,Dashboard!$C26*12,0) -> 0 | J96: =B96*Dashboard!$C13 -> 147096.99 | K96: =Dashboard!$C14*12 -> 1800 | L96: =B96*Dashboard!$C16 -> 122580.82 | M96: =IF(Dashboard!$C7<0.2,C96*Dashboard!$C17,0) -> 0 | O96: =O95+T96 -> 14626507 | P96: =T96+U96 -> 455380.97 | Q96: =Q95*(1+Dashboard!$F11)+Dashboard!$F28*12 -> 1.5402475e+08 | R96: =Dashboard!$F6*Dashboard!$F9+O96+U96*93 -> 14653827 | S96: =Q96-MAX(Q96-(Dashboard!$C8+Dashboard!$C6*Dashboard!$C19+Dashboard!$F6*Dashboard!$F9),0)*Dashboard!$F12 -> 1.3093904e+08 | T96: =Dashboard!$F6*(1+Dashboard!$F7)^(93-1)*12 -> 455140.97 | U96: =Dashboard!$F8*12 -> 240
A97: 94 | B97: =B96*(1+Dashboard!$C21) -> 12687115 | C97: =MAX((Dashboard!$C6-Dashboard!$C8)*(1+Dashboard!$C10/12)^(94*12)-Dashboard!$C26*((1+Dashboard!$C10/12)^(94*12)-1)/(Dashboard!$C10/12),0) -> 2.8275814e+08 | D97: =I97+J97+K97+L97+M97 -> 280916.54 | E97: =E96+(D97-(C96-C97)) -> 2.9045593e+08 | F97: =(Dashboard!$C6-Dashboard!$C8)-C97 -> -2.8235814e+08 | G97: =G96+D97 -> 8212789 | H97: =B97*(1-Dashboard!$C20)-C97 -> -2.7083225e+08 | I97: =IF(C96>0,Dashboard!$C26*12,0) -> 0 | J97: =B97*Dashboard!$C13 -> 152245.38 | K97: =Dashboard!$C14*12 -> 1800 | L97: =B97*Dashboard!$C16 -> 126871.15 | M97: =IF(Dashboard!$C7<0.2,C97*Dashboard!$C17,0) -> 0 | O97: =O96+T97 -> 15095302 | P97: =T97+U97 -> 469035.2 | Q97: =Q96*(1+Dashboard!$F11)+Dashboard!$F28*12 -> 1.6634673e+08 | R97: =Dashboard!$F6*Dashboard!$F9+O97+U97*94 -> 15122862 | S97: =Q97-MAX(Q97-(Dashboard!$C8+Dashboard!$C6*Dashboard!$C19+Dashboard!$F6*Dashboard!$F9),0)*Dashboard!$F12 -> 1.4141272e+08 | T97: =Dashboard!$F6*(1+Dashboard!$F7)^(94-1)*12 -> 468795.2 | U97: =Dashboard!$F8*12 -> 240
A98: 95 | B98: =B97*(1+Dashboard!$C21) -> 13131164 | C98: =MAX((Dashboard!$C6-Dashboard!$C8)*(1+Dashboard!$C10/12)^(95*12)-Dashboard!$C26*((1+Dashboard!$C10/12)^(95*12)-1)/(Dashboard!$C10/12),0) -> 3.0319875e+08 | D98: =I98+J98+K98+L98+M98 -> 290685.61 | E98: =E97+(D98-(C97-C98)) -> 3.1118723e+08 | F98: =(Dashboard!$C6-Dashboard!$C8)-C98 -> -3.0279875e+08 | G98: =G97+D98 -> 8503474.6 | H98: =B98*(1-Dashboard!$C20)-C98 -> -2.9085546e+08 | I98: =IF(C97>0,Dashboard!$C26*12,0) -> 0 | J98: =B98*Dashboard!$C13 -> 157573.97 | K98: =Dashboard!$C14*12 -> 1800 | L98: =B98*Dashboard!$C16 -> 131311.64 | M98: =IF(Dashboard!$C7<0.2,C98*Dashboard!$C17,0) -> 0 | O98: =O97+T98 -> 15578161 | P98: =T98+U98 -> 483099.05 | Q98: =Q97*(1+Dashboard!$F11)+Dashboard!$F28*12 -> 1.7965447e+08 | R98: =Dashboard!$F6*Dashboard!$F9+O98+U98*95 -> 15605961 | S98: =Q98-MAX(Q98-(Dashboard!$C8+Dashboard!$C6*Dashboard!$C19+Dashboard!$F6*Dashboard!$F9),0)*Dashboard!$F12 -> 1.527243e+08 | T98: =Dashboard!$F6*(1+Dashboard!$F7)^(95-1)*12 -> 482859.05 | U98: =Dashboard!$F8*12 -> 240
A99: 96 | B99: =B98*(1+Dashboard!$C21) -> 13590755 | C99: =MAX((Dashboard!$C6-Dashboard!$C8)*(1+Dashboard!$C10/12)^(96*12)-Dashboard!$C26*((1+Dashboard!$C10/12)^(96*12)-1)/(Dashboard!$C10/12),0) -> 3.2511701e+08 | D99: =I99+J99+K99+L99+M99 -> 300796.61 | E99: =E98+(D99-(C98-C99)) -> 3.3340628e+08 | F99: =(Dashboard!$C6-Dashboard!$C8)-C99 -> -3.2471701e+08 | G99: =G98+D99 -> 8804271.2 | H99: =B99*(1-Dashboard!$C20)-C99 -> -3.123417e+08 | I99: =IF(C98>0,Dashboard!$C26*12,0) -> 0 | J99: =B99*Dashboard!$C13 -> 163089.06 | K99: =Dashboard!$C14*12 -> 1800 | L99: =B99*Dashboard!$C16 -> 135907.55 | M99: =IF(Dashboard!$C7<0.2,C99*Dashboard!$C17,0) -> 0 | O99: =O98+T99 -> 16075506 | P99: =T99+U99 -> 497584.82 | Q99: =Q98*(1+Dashboard!$F11)+Dashboard!$F28*12 -> 1.9402682e+08 | R99: =Dashboard!$F6*Dashboard!$F9+O99+U99*96 -> 16103546 | S99: =Q99-MAX(Q99-(Dashboard!$C8+Dashboard!$C6*Dashboard!$C19+Dashboard!$F6*Dashboard!$F9),0)*Dashboard!$F12 -> 1.649408e+08 | T99: =Dashboard!$F6*(1+Dashboard!$F7)^(96-1)*12 -> 497344.82 | U99: =Dashboard!$F8*12 -> 240
A100: 97 | B100: =B99*(1+Dashboard!$C21) -> 14066431 | C100: =MAX((Dashboard!$C6-Dashboard!$C8)*(1+Dashboard!$C10/12)^(97*12)-Dashboard!$C26*((1+Dashboard!$C10/12)^(97*12)-1)/(Dashboard!$C10/12),0) -> 3.4861975e+08 | D100: =I100+J100+K100+L100+M100 -> 311261.49 | E100: =E99+(D100-(C99-C100)) -> 3.5722028e+08 | F100: =(Dashboard!$C6-Dashboard!$C8)-C100 -> -3.4821975e+08 | G100: =G99+D100 -> 9115532.7 | H100: =B100*(1-Dashboard!$C20)-C100 -> -3.353973e+08 | I100: =IF(C99>0,Dashboard!$C26*12,0) -> 0 | J100: =B100*Dashboard!$C13 -> 168797.18 | K100: =Dashboard!$C14*12 -> 1800 | L100: =B100*Dashboard!$C16 -> 140664.31 | M100: =IF(Dashboard!$C7<0.2,C100*Dashboard!$C17,0) -> 0 | O100: =O99+T100 -> 16587771 | P100: =T100+U100 -> 512505.17 | Q100: =Q99*(1+Dashboard!$F11)+Dashboard!$F28*12 -> 2.0954897e+08 | R100: =Dashboard!$F6*Dashboard!$F9+O100+U100*97 -> 16616051 | S100: =Q100-MAX(Q100-(Dashboard!$C8+Dashboard!$C6*Dashboard!$C19+Dashboard!$F6*Dashboard!$F9),0)*Dashboard!$F12 -> 1.7813462e+08 | T100: =Dashboard!$F6*(1+Dashboard!$F7)^(97-1)*12 -> 512265.17 | U100: =Dashboard!$F8*12 -> 240
...

Sheet Charts
A1: 📈 INTERACTIVE CHARTS — Net Worth Timeline & Expense Breakdown
A2: CHART CUSTOMIZATION — Change these to update charts
A3: Chart Start Year | B3: 1 | C3: Chart End Year | D3: 30
A5: CHART DATA (auto-calculated from Schedule & Dashboard)
A6: Year | B6: Buyer Net Worth | C6: Renter Net Worth | D6: Buyer Cash Spent | E6: Renter Cash Spent | F6: Home Value | G6: Portfolio Value | H6: Ann. Buyer Cost | I6: Ann. Rent Cost
A7: 0 | B7: =IFERROR(Schedule!$H$3,0) -> 70000 | C7: =IFERROR(Schedule!$S$3,0) -> 120000 | D7: =IFERROR(Schedule!$G$3,0) -> 115000 | E7: =IFERROR(Schedule!$R$3,0) -> 5000 | F7: =IFERROR(Schedule!$B$3,0) -> 500000 | G7: =IFERROR(Schedule!$Q$3,0) -> 120000 | H7: =IFERROR(Schedule!$D$3,0) -> 0 | I7: =IFERROR(Schedule!$P$3,0) -> 0
A8: 1 | B8: =IFERROR(Schedule!$H$4,0) -> 57533.968 | C8: =IFERROR(Schedule!$S$4,0) -> 128160 | D8: =IFERROR(Schedule!$G$4,0) -> 128185 | E8: =IFERROR(Schedule!$R$4,0) -> 35240 | F8: =IFERROR(Schedule!$B$4,0) -> 517500 | G8: =IFERROR(Schedule!$Q$4,0) -> 129600 | H8: =IFERROR(Schedule!$D$4,0) -> 13185 | I8: =IFERROR(Schedule!$P$4,0) -> 30240
A9: 2 | B9: =IFERROR(Schedule!$H$5,0) -> 43553.343 | C9: =IFERROR(Schedule!$S$5,0) -> 136972.8 | D9: =IFERROR(Schedule!$G$5,0) -> 141768.48 | E9: =IFERROR(Schedule!$R$5,0) -> 66380 | F9: =IFERROR(Schedule!$B$5,0) -> 535612.5 | G9: =IFERROR(Schedule!$Q$5,0) -> 139968 | H9: =IFERROR(Schedule!$D$5,0) -> 13583.475 | I9: =IFERROR(Schedule!$P$5,0) -> 31140
A10: 3 | B10: =IFERROR(Schedule!$H$6,0) -> 27927.166 | C10: =IFERROR(Schedule!$S$6,0) -> 146490.62 | D10: =IFERROR(Schedule!$G$6,0) -> 155764.37 | E10: =IFERROR(Schedule!$R$6,0) -> 98447 | F10: =IFERROR(Schedule!$B$6,0) -> 554358.94 | G10: =IFERROR(Schedule!$Q$6,0) -> 151165.44 | H10: =IFERROR(Schedule!$D$6,0) -> 13995.897 | I10: =IFERROR(Schedule!$P$6,0) -> 32067
A11: 4 | B11: =IFERROR(Schedule!$H$7,0) -> 10514.259 | C11: =IFERROR(Schedule!$S$7,0) -> 156769.87 | D11: =IFERROR(Schedule!$G$7,0) -> 170187.12 | E11: =IFERROR(Schedule!$R$7,0) -> 131468.81 | F11: =IFERROR(Schedule!$B$7,0) -> 573761.5 | G11: =IFERROR(Schedule!$Q$7,0) -> 163258.68 | H11: =IFERROR(Schedule!$D$7,0) -> 14422.753 | I11: =IFERROR(Schedule!$P$7,0) -> 33021.81
A12: 5 | B12: =IFERROR(Schedule!$H$8,0) -> -8837.5402 | C12: =IFERROR(Schedule!$S$8,0) -> 167871.46 | D12: =IFERROR(Schedule!$G$8,0) -> 185051.67 | E12: =IFERROR(Schedule!$R$8,0) -> 165474.07 | F12: =IFERROR(Schedule!$B$8,0) -> 593843.15 | G12: =IFERROR(Schedule!$Q$8,0) -> 176319.37 | H12: =IFERROR(Schedule!$D$8,0) -> 14864.549 | I12: =IFERROR(Schedule!$P$8,0) -> 34005.264
A13: 6 | B13: =IFERROR(Schedule!$H$9,0) -> -30292.198 | C13: =IFERROR(Schedule!$S$9,0) -> 179861.18 | D13: =IFERROR(Schedule!$G$9,0) -> 200373.48 | E13: =IFERROR(Schedule!$R$9,0) -> 200492.3 | F13: =IFERROR(Schedule!$B$9,0) -> 614627.66 | G13: =IFERROR(Schedule!$Q$9,0) -> 190424.92 | H13: =IFERROR(Schedule!$D$9,0) -> 15321.809 | I13: =IFERROR(Schedule!$P$9,0) -> 35018.222
A14: 7 | B14: =IFERROR(Schedule!$H$10,0) -> -54026.368 | C14: =IFERROR(Schedule!$S$10,0) -> 192810.08 | D14: =IFERROR(Schedule!$G$10,0) -> 216168.55 | E14: =IFERROR(Schedule!$R$10,0) -> 236553.87 | F14: =IFERROR(Schedule!$B$10,0) -> 636139.63 | G14: =IFERROR(Schedule!$Q$10,0) -> 205658.91 | H14: =IFERROR(Schedule!$D$10,0) -> 15795.072 | I14: =IFERROR(Schedule!$P$10,0) -> 36061.569
A15: 8 | B15: =IFERROR(Schedule!$H$11,0) -> -80230.335 | C15: =IFERROR(Schedule!$S$11,0) -> 206794.88 | D15: =IFERROR(Schedule!$G$11,0) -> 232453.45 | E15: =IFERROR(Schedule!$R$11,0) -> 273690.08 | F15: =IFERROR(Schedule!$B$11,0) -> 658404.52 | G15: =IFERROR(Schedule!$Q$11,0) -> 222111.63 | H15: =IFERROR(Schedule!$D$11,0) -> 16284.899 | I15: =IFERROR(Schedule!$P$11,0) -> 37136.216
A16: 9 | B16: =IFERROR(Schedule!$H$12,0) -> -109109.03 | C16: =IFERROR(Schedule!$S$12,0) -> 221898.47 | D16: =IFERROR(Schedule!$G$12,0) -> 249245.32 | E16: =IFERROR(Schedule!$R$12,0) -> 311933.18 | F16: =IFERROR(Schedule!$B$12,0) -> 681448.68 | G16: =IFERROR(Schedule!$Q$12,0) -> 239880.56 | H16: =IFERROR(Schedule!$D$12,0) -> 16791.871 | I16: =IFERROR(Schedule!$P$12,0) -> 38243.102
A17: 10 | B17: =IFERROR(Schedule!$H$13,0) -> -140883.13 | C17: =IFERROR(Schedule!$S$13,0) -> 238210.35 | D17: =IFERROR(Schedule!$G$13,0) -> 266561.91 | E17: =IFERROR(Schedule!$R$13,0) -> 351316.38 | F17: =IFERROR(Schedule!$B$13,0) -> 705299.38 | G17: =IFERROR(Schedule!$Q$13,0) -> 259071 | H17: =IFERROR(Schedule!$D$13,0) -> 17316.586 | I17: =IFERROR(Schedule!$P$13,0) -> 39383.196
A18: 11 | B18: =IFERROR(Schedule!$H$14,0) -> -175790.22 | C18: =IFERROR(Schedule!$S$14,0) -> 255827.18 | D18: =IFERROR(Schedule!$G$14,0) -> 284421.58 | E18: =IFERROR(Schedule!$R$14,0) -> 391873.87 | F18: =IFERROR(Schedule!$B$14,0) -> 729984.86 | G18: =IFERROR(Schedule!$Q$14,0) -> 279796.68 | H18: =IFERROR(Schedule!$D$14,0) -> 17859.667 | I18: =IFERROR(Schedule!$P$14,0) -> 40557.491
A19: 12 | B19: =IFERROR(Schedule!$H$15,0) -> -214086.03 | C19: =IFERROR(Schedule!$S$15,0) -> 274853.35 | D19: =IFERROR(Schedule!$G$15,0) -> 302843.33 | E19: =IFERROR(Schedule!$R$15,0) -> 433640.89 | F19: =IFERROR(Schedule!$B$15,0) -> 755534.33 | G19: =IFERROR(Schedule!$Q$15,0) -> 302180.41 | H19: =IFERROR(Schedule!$D$15,0) -> 18421.755 | I19: =IFERROR(Schedule!$P$15,0) -> 41767.016
A20: 13 | B20: =IFERROR(Schedule!$H$16,0) -> -256045.83 | C20: =IFERROR(Schedule!$S$16,0) -> 295401.62 | D20: =IFERROR(Schedule!$G$16,0) -> 321846.85 | E20: =IFERROR(Schedule!$R$16,0) -> 476653.71 | F20: =IFERROR(Schedule!$B$16,0) -> 781978.03 | G20: =IFERROR(Schedule!$Q$16,0) -> 326354.85 | H20: =IFERROR(Schedule!$D$16,0) -> 19003.517 | I20: =IFERROR(Schedule!$P$16,0) -> 43012.827
A21: 14 | B21: =IFERROR(Schedule!$H$17,0) -> -301965.82 | C21: =IFERROR(Schedule!$S$17,0) -> 317593.75 | D21: =IFERROR(Schedule!$G$17,0) -> 341452.49 | E21: =IFERROR(Schedule!$R$17,0) -> 520949.72 | F21: =IFERROR(Schedule!$B$17,0) -> 809347.26 | G21: =IFERROR(Schedule!$Q$17,0) -> 352463.23 | H21: =IFERROR(Schedule!$D$17,0) -> 19605.64 | I21: =IFERROR(Schedule!$P$17,0) -> 44296.011
A22: 15 | B22: =IFERROR(Schedule!$H$18,0) -> -352164.74 | C22: =IFERROR(Schedule!$S$18,0) -> 341561.25 | D22: =IFERROR(Schedule!$G$18,0) -> 361681.33 | E22: =IFERROR(Schedule!$R$18,0) -> 566567.42 | F22: =IFERROR(Schedule!$B$18,0) -> 837674.42 | G22: =IFERROR(Schedule!$Q$18,0) -> 380660.29 | H22: =IFERROR(Schedule!$D$18,0) -> 20228.837 | I22: =IFERROR(Schedule!$P$18,0) -> 45617.692
A23: 16 | B23: =IFERROR(Schedule!$H$19,0) -> -406985.49 | C23: =IFERROR(Schedule!$S$19,0) -> 367446.15 | D23: =IFERROR(Schedule!$G$19,0) -> 382555.17 | E23: =IFERROR(Schedule!$R$19,0) -> 613546.44 | F23: =IFERROR(Schedule!$B$19,0) -> 866993.02 | G23: =IFERROR(Schedule!$Q$19,0) -> 411113.12 | H23: =IFERROR(Schedule!$D$19,0) -> 20873.846 | I23: =IFERROR(Schedule!$P$19,0) -> 46979.022
A24: 17 | B24: =IFERROR(Schedule!$H$20,0) -> -466796.93 | C24: =IFERROR(Schedule!$S$20,0) -> 395401.84 | D24: =IFERROR(Schedule!$G$20,0) -> 404096.6 | E24: =IFERROR(Schedule!$R$20,0) -> 661927.63 | F24: =IFERROR(Schedule!$B$20,0) -> 897337.78 | G24: =IFERROR(Schedule!$Q$20,0) -> 444002.17 | H24: =IFERROR(Schedule!$D$20,0) -> 21541.431 | I24: =IFERROR(Schedule!$P$20,0) -> 48381.193
A25: 18 | B25: =IFERROR(Schedule!$H$21,0) -> -531995.81 | C25: =IFERROR(Schedule!$S$21,0) -> 425593.99 | D25: =IFERROR(Schedule!$G$21,0) -> 426328.99 | E25: =IFERROR(Schedule!$R$21,0) -> 711753.06 | F25: =IFERROR(Schedule!$B$21,0) -> 928744.6 | G25: =IFERROR(Schedule!$Q$21,0) -> 479522.34 | H25: =IFERROR(Schedule!$D$21,0) -> 22232.381 | I25: =IFERROR(Schedule!$P$21,0) -> 49825.429
A26: 19 | B26: =IFERROR(Schedule!$H$22,0) -> -603008.81 | C26: =IFERROR(Schedule!$S$22,0) -> 458201.51 | D26: =IFERROR(Schedule!$G$22,0) -> 449276.5 | E26: =IFERROR(Schedule!$R$22,0) -> 763066.05 | F26: =IFERROR(Schedule!$B$22,0) -> 961250.66 | G26: =IFERROR(Schedule!$Q$22,0) -> 517884.13 | H26: =IFERROR(Schedule!$D$22,0) -> 22947.514 | I26: =IFERROR(Schedule!$P$22,0) -> 51312.992
A27: 20 | B27: =IFERROR(Schedule!$H$23,0) -> -680294.77 | C27: =IFERROR(Schedule!$S$23,0) -> 493417.63 | D27: =IFERROR(Schedule!$G$23,0) -> 472964.18 | E27: =IFERROR(Schedule!$R$23,0) -> 815911.23 | F27: =IFERROR(Schedule!$B$23,0) -> 994894.43 | G27: =IFERROR(Schedule!$Q$23,0) -> 559314.86 | H27: =IFERROR(Schedule!$D$23,0) -> 23687.677 | I27: =IFERROR(Schedule!$P$23,0) -> 52845.182
A28: 21 | B28: =IFERROR(Schedule!$H$24,0) -> -764347.05 | C28: =IFERROR(Schedule!$S$24,0) -> 531451.04 | D28: =IFERROR(Schedule!$G$24,0) -> 497417.92 | E28: =IFERROR(Schedule!$R$24,0) -> 870334.57 | F28: =IFERROR(Schedule!$B$24,0) -> 1029715.7 | G28: =IFERROR(Schedule!$Q$24,0) -> 604060.05 | H28: =IFERROR(Schedule!$D$24,0) -> 24453.746 | I28: =IFERROR(Schedule!$P$24,0) -> 54423.337
A29: 22 | B29: =IFERROR(Schedule!$H$25,0) -> -855696.05 | C29: =IFERROR(Schedule!$S$25,0) -> 572527.12 | D29: =IFERROR(Schedule!$G$25,0) -> 522664.55 | E29: =IFERROR(Schedule!$R$25,0) -> 926383.41 | F29: =IFERROR(Schedule!$B$25,0) -> 1065755.8 | G29: =IFERROR(Schedule!$Q$25,0) -> 652384.85 | H29: =IFERROR(Schedule!$D$25,0) -> 25246.627 | I29: =IFERROR(Schedule!$P$25,0) -> 56048.837
A30: 23 | B30: =IFERROR(Schedule!$H$26,0) -> -954911.98 | C30: =IFERROR(Schedule!$S$26,0) -> 616889.29 | D30: =IFERROR(Schedule!$G$26,0) -> 548731.81 | E30: =IFERROR(Schedule!$R$26,0) -> 984106.51 | F30: =IFERROR(Schedule!$B$26,0) -> 1103057.2 | G30: =IFERROR(Schedule!$Q$26,0) -> 704575.64 | H30: =IFERROR(Schedule!$D$26,0) -> 26067.259 | I30: =IFERROR(Schedule!$P$26,0) -> 57723.102
A31: 24 | B31: =IFERROR(Schedule!$H$27,0) -> -1062607.8 | C31: =IFERROR(Schedule!$S$27,0) -> 664800.44 | D31: =IFERROR(Schedule!$G$27,0) -> 575648.42 | E31: =IFERROR(Schedule!$R$27,0) -> 1043554.1 | F31: =IFERROR(Schedule!$B$27,0) -> 1141664.2 | G31: =IFERROR(Schedule!$Q$27,0) -> 760941.69 | H31: =IFERROR(Schedule!$D$27,0) -> 26916.613 | I31: =IFERROR(Schedule!$P$27,0) -> 59447.595
A32: 25 | B32: =IFERROR(Schedule!$H$28,0) -> -1179442.1 | C32: =IFERROR(Schedule!$S$28,0) -> 716544.47 | D32: =IFERROR(Schedule!$G$28,0) -> 603444.12 | E32: =IFERROR(Schedule!$R$28,0) -> 1104777.9 | F32: =IFERROR(Schedule!$B$28,0) -> 1181622.5 | G32: =IFERROR(Schedule!$Q$28,0) -> 821817.02 | H32: =IFERROR(Schedule!$D$28,0) -> 27795.695 | I32: =IFERROR(Schedule!$P$28,0) -> 61223.823
A33: 26 | B33: =IFERROR(Schedule!$H$29,0) -> -1306123.1 | C33: =IFERROR(Schedule!$S$29,0) -> 772428.03 | D33: =IFERROR(Schedule!$G$29,0) -> 632149.66 | E33: =IFERROR(Schedule!$R$29,0) -> 1167831.3 | F33: =IFERROR(Schedule!$B$29,0) -> 1222979.3 | G33: =IFERROR(Schedule!$Q$29,0) -> 887562.39 | H33: =IFERROR(Schedule!$D$29,0) -> 28705.544 | I33: =IFERROR(Schedule!$P$29,0) -> 63053.338
A34: 27 | B34: =IFERROR(Schedule!$H$30,0) -> -1443411.6 | C34: =IFERROR(Schedule!$S$30,0) -> 832782.27 | D34: =IFERROR(Schedule!$G$30,0) -> 661796.9 | E34: =IFERROR(Schedule!$R$30,0) -> 1232769 | F34: =IFERROR(Schedule!$B$30,0) -> 1265783.6 | G34: =IFERROR(Schedule!$Q$30,0) -> 958567.38 | H34: =IFERROR(Schedule!$D$30,0) -> 29647.238 | I34: =IFERROR(Schedule!$P$30,0) -> 64937.738
A35: 28 | B35: =IFERROR(Schedule!$H$31,0) -> -1592125 | C35: =IFERROR(Schedule!$S$31,0) -> 897964.85 | D35: =IFERROR(Schedule!$G$31,0) -> 692418.79 | E35: =IFERROR(Schedule!$R$31,0) -> 1299647.7 | F35: =IFERROR(Schedule!$B$31,0) -> 1310086 | G35: =IFERROR(Schedule!$Q$31,0) -> 1035252.8 | H35: =IFERROR(Schedule!$D$31,0) -> 30621.892 | I35: =IFERROR(Schedule!$P$31,0) -> 66878.67
A36: 29 | B36: =IFERROR(Schedule!$H$32,0) -> -1753141.9 | C36: =IFERROR(Schedule!$S$32,0) -> 968362.04 | D36: =IFERROR(Schedule!$G$32,0) -> 724049.45 | E36: =IFERROR(Schedule!$R$32,0) -> 1368525.5 | F36: =IFERROR(Schedule!$B$32,0) -> 1355939 | G36: =IFERROR(Schedule!$Q$32,0) -> 1118073 | H36: =IFERROR(Schedule!$D$32,0) -> 31630.658 | I36: =IFERROR(Schedule!$P$32,0) -> 68877.83
A37: 30 | B37: =IFERROR(Schedule!$H$33,0) -> -1927405.9 | C37: =IFERROR(Schedule!$S$33,0) -> 1044391 | D37: =IFERROR(Schedule!$G$33,0) -> 756724.18 | E37: =IFERROR(Schedule!$R$33,0) -> 1439462.5 | F37: =IFERROR(Schedule!$B$33,0) -> 1403396.9 | G37: =IFERROR(Schedule!$Q$33,0) -> 1207518.8 | H37: =IFERROR(Schedule!$D$33,0) -> 32674.731 | I37: =IFERROR(Schedule!$P$33,0) -> 70936.965
A38: 31 | B38: =IFERROR(Schedule!$H$34,0) -> -2115931.1 | C38: =IFERROR(Schedule!$S$34,0) -> 1126502.3 | D38: =IFERROR(Schedule!$G$34,0) -> 790479.53 | E38: =IFERROR(Schedule!$R$34,0) -> 1512520.3 | F38: =IFERROR(Schedule!$B$34,0) -> 1452515.7 | G38: =IFERROR(Schedule!$Q$34,0) -> 1304120.3 | H38: =IFERROR(Schedule!$D$34,0) -> 33755.346 | I38: =IFERROR(Schedule!$P$34,0) -> 73057.874
A39: 32 | B39: =IFERROR(Schedule!$H$35,0) -> -2319806.5 | C39: =IFERROR(Schedule!$S$35,0) -> 1215182.5 | D39: =IFERROR(Schedule!$G$35,0) -> 825353.31 | E39: =IFERROR(Schedule!$R$35,0) -> 1587762.8 | F39: =IFERROR(Schedule!$B$35,0) -> 1503353.8 | G39: =IFERROR(Schedule!$Q$35,0) -> 1408450 | H39: =IFERROR(Schedule!$D$35,0) -> 34873.783 | I39: =IFERROR(Schedule!$P$35,0) -> 75242.41
A40: 33 | B40: =IFERROR(Schedule!$H$36,0) -> -2540202.1 | C40: =IFERROR(Schedule!$S$36,0) -> 1310957.1 | D40: =IFERROR(Schedule!$G$36,0) -> 861384.68 | E40: =IFERROR(Schedule!$R$36,0) -> 1665255.2 | F40: =IFERROR(Schedule!$B$36,0) -> 1555971.2 | G40: =IFERROR(Schedule!$Q$36,0) -> 1521126 | H40: =IFERROR(Schedule!$D$36,0) -> 36031.366 | I40: =IFERROR(Schedule!$P$36,0) -> 77492.483
A41: 34 | B41: =IFERROR(Schedule!$H$37,0) -> -2778374.4 | C41: =IFERROR(Schedule!$S$37,0) -> 1414393.6 | D41: =IFERROR(Schedule!$G$37,0) -> 898614.14 | E41: =IFERROR(Schedule!$R$37,0) -> 1745065.3 | F41: =IFERROR(Schedule!$B$37,0) -> 1610430.2 | G41: =IFERROR(Schedule!$Q$37,0) -> 1642816 | H41: =IFERROR(Schedule!$D$37,0) -> 37229.464 | I41: =IFERROR(Schedule!$P$37,0) -> 79810.057
A42: 35 | B42: =IFERROR(Schedule!$H$38,0) -> -3035673.2 | C42: =IFERROR(Schedule!$S$38,0) -> 1526105.1 | D42: =IFERROR(Schedule!$G$38,0) -> 937083.64 | E42: =IFERROR(Schedule!$R$38,0) -> 1827262.5 | F42: =IFERROR(Schedule!$B$38,0) -> 1666795.2 | G42: =IFERROR(Schedule!$Q$38,0) -> 1774241.3 | H42: =IFERROR(Schedule!$D$38,0) -> 38469.495 | I42: =IFERROR(Schedule!$P$38,0) -> 82197.159
A43: 36 | B43: =IFERROR(Schedule!$H$39,0) -> -3313547.9 | C43: =IFERROR(Schedule!$S$39,0) -> 1646753.5 | D43: =IFERROR(Schedule!$G$39,0) -> 976836.56 | E43: =IFERROR(Schedule!$R$39,0) -> 1911918.3 | F43: =IFERROR(Schedule!$B$39,0) -> 1725133.1 | G43: =IFERROR(Schedule!$Q$39,0) -> 1916180.6 | H43: =IFERROR(Schedule!$D$39,0) -> 39752.927 | I43: =IFERROR(Schedule!$P$39,0) -> 84655.874
A44: 37 | B44: =IFERROR(Schedule!$H$40,0) -> -3613555.1 | C44: =IFERROR(Schedule!$S$40,0) -> 1777053.8 | D44: =IFERROR(Schedule!$G$40,0) -> 1017917.8 | E44: =IFERROR(Schedule!$R$40,0) -> 1999106.7 | F44: =IFERROR(Schedule!$B$40,0) -> 1785512.7 | G44: =IFERROR(Schedule!$Q$40,0) -> 2069475.1 | H44: =IFERROR(Schedule!$D$40,0) -> 41081.28 | I44: =IFERROR(Schedule!$P$40,0) -> 87188.35
A45: 38 | B45: =IFERROR(Schedule!$H$41,0) -> -3937366.3 | C45: =IFERROR(Schedule!$S$41,0) -> 1917778.1 | D45: =IFERROR(Schedule!$G$41,0) -> 1060374 | E45: =IFERROR(Schedule!$R$41,0) -> 2088903.5 | F45: =IFERROR(Schedule!$B$41,0) -> 1848005.7 | G45: =IFERROR(Schedule!$Q$41,0) -> 2235033.1 | H45: =IFERROR(Schedule!$D$41,0) -> 42456.124 | I45: =IFERROR(Schedule!$P$41,0) -> 89796.8
A46: 39 | B46: =IFERROR(Schedule!$H$42,0) -> -4286776.4 | C46: =IFERROR(Schedule!$S$42,0) -> 2069760.4 | D46: =IFERROR(Schedule!$G$42,0) -> 1104253.1 | E46: =IFERROR(Schedule!$R$42,0) -> 2181387 | F46: =IFERROR(Schedule!$B$42,0) -> 1912685.9 | G46: =IFERROR(Schedule!$Q$42,0) -> 2413835.7 | H46: =IFERROR(Schedule!$D$42,0) -> 43879.089 | I46: =IFERROR(Schedule!$P$42,0) -> 92483.504
A47: 40 | B47: =IFERROR(Schedule!$H$43,0) -> -4663712.5 | C47: =IFERROR(Schedule!$S$43,0) -> 2233901.2 | D47: =IFERROR(Schedule!$G$43,0) -> 1149604.9 | E47: =IFERROR(Schedule!$R$43,0) -> 2276637.8 | F47: =IFERROR(Schedule!$B$43,0) -> 1979629.9 | G47: =IFERROR(Schedule!$Q$43,0) -> 2606942.6 | H47: =IFERROR(Schedule!$D$43,0) -> 45351.857 | I47: =IFERROR(Schedule!$P$43,0) -> 95250.809
A48: 41 | B48: =IFERROR(Schedule!$H$44,0) -> -5070244 | C48: =IFERROR(Schedule!$S$44,0) -> 2411173.3 | D48: =IFERROR(Schedule!$G$44,0) -> 1196481.1 | E48: =IFERROR(Schedule!$R$44,0) -> 2374738.9 | F48: =IFERROR(Schedule!$B$44,0) -> 2048916.9 | G48: =IFERROR(Schedule!$Q$44,0) -> 2815498 | H48: =IFERROR(Schedule!$D$44,0) -> 46876.172 | I48: =IFERROR(Schedule!$P$44,0) -> 98101.134
A49: 42 | B49: =IFERROR(Schedule!$H$45,0) -> -5508592.4 | C49: =IFERROR(Schedule!$S$45,0) -> 2602627.2 | D49: =IFERROR(Schedule!$G$45,0) -> 1244934.9 | E49: =IFERROR(Schedule!$R$45,0) -> 2475775.9 | F49: =IFERROR(Schedule!$B$45,0) -> 2120629 | G49: =IFERROR(Schedule!$Q$45,0) -> 3040737.8 | H49: =IFERROR(Schedule!$D$45,0) -> 48453.838 | I49: =IFERROR(Schedule!$P$45,0) -> 101036.97
A50: 43 | B50: =IFERROR(Schedule!$H$46,0) -> -5981142.7 | C50: =IFERROR(Schedule!$S$46,0) -> 2809397.3 | D50: =IFERROR(Schedule!$G$46,0) -> 1295021.6 | E50: =IFERROR(Schedule!$R$46,0) -> 2579836.8 | F50: =IFERROR(Schedule!$B$46,0) -> 2194851 | G50: =IFERROR(Schedule!$Q$46,0) -> 3283996.9 | H50: =IFERROR(Schedule!$D$46,0) -> 50086.722 | I50: =IFERROR(Schedule!$P$46,0) -> 104060.88
A51: 44 | B51: =IFERROR(Schedule!$H$47,0) -> -6490455.4 | C51: =IFERROR(Schedule!$S$47,0) -> 3032709.1 | D51: =IFERROR(Schedule!$G$47,0) -> 1346798.4 | E51: =IFERROR(Schedule!$R$47,0) -> 2687012.3 | F51: =IFERROR(Schedule!$B$47,0) -> 2271670.8 | G51: =IFERROR(Schedule!$Q$47,0) -> 3546716.6 | H51: =IFERROR(Schedule!$D$47,0) -> 51776.758 | I51: =IFERROR(Schedule!$P$47,0) -> 107175.5
A52: 45 | B52: =IFERROR(Schedule!$H$48,0) -> -7039279.1 | C52: =IFERROR(Schedule!$S$48,0) -> 3273885.8 | D52: =IFERROR(Schedule!$G$48,0) -> 1400324.3 | E52: =IFERROR(Schedule!$R$48,0) -> 2797395.8 | F52: =IFERROR(Schedule!$B$48,0) -> 2351179.3 | G52: =IFERROR(Schedule!$Q$48,0) -> 3830453.9 | H52: =IFERROR(Schedule!$D$48,0) -> 53525.944 | I52: =IFERROR(Schedule!$P$48,0) -> 110383.57
A53: 46 | B53: =IFERROR(Schedule!$H$49,0) -> -7630564.2 | C53: =IFERROR(Schedule!$S$49,0) -> 3534356.7 | D53: =IFERROR(Schedule!$G$49,0) -> 1455660.7 | E53: =IFERROR(Schedule!$R$49,0) -> 2911083.7 | F53: =IFERROR(Schedule!$B$49,0) -> 2433470.6 | G53: =IFERROR(Schedule!$Q$49,0) -> 4136890.2 | H53: =IFERROR(Schedule!$D$49,0) -> 55336.352 | I53: =IFERROR(Schedule!$P$49,0) -> 113687.88
A54: 47 | B54: =IFERROR(Schedule!$H$50,0) -> -8267478 | C54: =IFERROR(Schedule!$S$50,0) -> 3815665.2 | D54: =IFERROR(Schedule!$G$50,0) -> 1512870.8 | E54: =IFERROR(Schedule!$R$50,0) -> 3028175 | F54: =IFERROR(Schedule!$B$50,0) -> 2518642 | G54: =IFERROR(Schedule!$Q$50,0) -> 4467841.5 | H54: =IFERROR(Schedule!$D$50,0) -> 57210.124 | I54: =IFERROR(Schedule!$P$50,0) -> 117091.31
A55: 48 | B55: =IFERROR(Schedule!$H$51,0) -> -8953419.8 | C55: =IFERROR(Schedule!$S$51,0) -> 4119478.5 | D55: =IFERROR(Schedule!$G$51,0) -> 1572020.3 | E55: =IFERROR(Schedule!$R$51,0) -> 3148771.9 | F55: =IFERROR(Schedule!$B$51,0) -> 2606794.5 | G55: =IFERROR(Schedule!$Q$51,0) -> 4825268.8 | H55: =IFERROR(Schedule!$D$51,0) -> 59149.479 | I55: =IFERROR(Schedule!$P$51,0) -> 120596.85
A56: 49 | B56: =IFERROR(Schedule!$H$52,0) -> -9692038.4 | C56: =IFERROR(Schedule!$S$52,0) -> 4447596.7 | D56: =IFERROR(Schedule!$G$52,0) -> 1633177 | E56: =IFERROR(Schedule!$R$52,0) -> 3272979.4 | F56: =IFERROR(Schedule!$B$52,0) -> 2698032.3 | G56: =IFERROR(Schedule!$Q$52,0) -> 5211290.3 | H56: =IFERROR(Schedule!$D$52,0) -> 61156.711 | I56: =IFERROR(Schedule!$P$52,0) -> 124207.56
A57: 50 | B57: =IFERROR(Schedule!$H$53,0) -> -10487250 | C57: =IFERROR(Schedule!$S$53,0) -> 4801964.5 | D57: =IFERROR(Schedule!$G$53,0) -> 1696411.2 | E57: =IFERROR(Schedule!$R$53,0) -> 3400906 | F57: =IFERROR(Schedule!$B$53,0) -> 2792463.4 | G57: =IFERROR(Schedule!$Q$53,0) -> 5628193.5 | H57: =IFERROR(Schedule!$D$53,0) -> 63234.195 | I57: =IFERROR(Schedule!$P$53,0) -> 127926.58
A58: 51 | B58: =IFERROR(Schedule!$H$54,0) -> -11343257 | C58: =IFERROR(Schedule!$S$54,0) -> 5184681.6 | D58: =IFERROR(Schedule!$G$54,0) -> 1761795.6 | E58: =IFERROR(Schedule!$R$54,0) -> 3532663.2 | F58: =IFERROR(Schedule!$B$54,0) -> 2890199.6 | G58: =IFERROR(Schedule!$Q$54,0) -> 6078449 | H58: =IFERROR(Schedule!$D$54,0) -> 65384.392 | I58: =IFERROR(Schedule!$P$54,0) -> 131757.18
A59: 52 | B59: =IFERROR(Schedule!$H$55,0) -> -12264572 | C59: =IFERROR(Schedule!$S$55,0) -> 5598016.2 | D59: =IFERROR(Schedule!$G$55,0) -> 1829405.4 | E59: =IFERROR(Schedule!$R$55,0) -> 3668365.9 | F59: =IFERROR(Schedule!$B$55,0) -> 2991356.6 | G59: =IFERROR(Schedule!$Q$55,0) -> 6564724.9 | H59: =IFERROR(Schedule!$D$55,0) -> 67609.846 | I59: =IFERROR(Schedule!$P$55,0) -> 135702.7
A60: 53 | B60: =IFERROR(Schedule!$H$56,0) -> -13256033 | C60: =IFERROR(Schedule!$S$56,0) -> 6044417.5 | D60: =IFERROR(Schedule!$G$56,0) -> 1899318.6 | E60: =IFERROR(Schedule!$R$56,0) -> 3808132.5 | F60: =IFERROR(Schedule!$B$56,0) -> 3096054.1 | G60: =IFERROR(Schedule!$Q$56,0) -> 7089902.9 | H60: =IFERROR(Schedule!$D$56,0) -> 69913.191 | I60: =IFERROR(Schedule!$P$56,0) -> 139766.58
A61: 54 | B61: =IFERROR(Schedule!$H$57,0) -> -14322838 | C61: =IFERROR(Schedule!$S$57,0) -> 6526530.9 | D61: =IFERROR(Schedule!$G$57,0) -> 1971615.8 | E61: =IFERROR(Schedule!$R$57,0) -> 3952084.8 | F61: =IFERROR(Schedule!$B$57,0) -> 3204416 | G61: =IFERROR(Schedule!$Q$57,0) -> 7657095.1 | H61: =IFERROR(Schedule!$D$57,0) -> 72297.152 | I61: =IFERROR(Schedule!$P$57,0) -> 143952.37
A62: 55 | B62: =IFERROR(Schedule!$H$58,0) -> -15470561 | C62: =IFERROR(Schedule!$S$58,0) -> 7047213.3 | D62: =IFERROR(Schedule!$G$58,0) -> 2046380.3 | E62: =IFERROR(Schedule!$R$58,0) -> 4100348.6 | F62: =IFERROR(Schedule!$B$58,0) -> 3316570.6 | G62: =IFERROR(Schedule!$Q$58,0) -> 8269662.7 | H62: =IFERROR(Schedule!$D$58,0) -> 74764.553 | I62: =IFERROR(Schedule!$P$58,0) -> 148263.75
A63: 56 | B63: =IFERROR(Schedule!$H$59,0) -> -16705183 | C63: =IFERROR(Schedule!$S$59,0) -> 7609550.4 | D63: =IFERROR(Schedule!$G$59,0) -> 2123698.7 | E63: =IFERROR(Schedule!$R$59,0) -> 4253053 | F63: =IFERROR(Schedule!$B$59,0) -> 3432650.5 | G63: =IFERROR(Schedule!$Q$59,0) -> 8931235.8 | H63: =IFERROR(Schedule!$D$59,0) -> 77318.312 | I63: =IFERROR(Schedule!$P$59,0) -> 152704.46
A64: 57 | B64: =IFERROR(Schedule!$H$60,0) -> -18033126 | C64: =IFERROR(Schedule!$S$60,0) -> 8216874.4 | D64: =IFERROR(Schedule!$G$60,0) -> 2203660.1 | E64: =IFERROR(Schedule!$R$60,0) -> 4410331.4 | F64: =IFERROR(Schedule!$B$60,0) -> 3552793.3 | G64: =IFERROR(Schedule!$Q$60,0) -> 9645734.6 | H64: =IFERROR(Schedule!$D$60,0) -> 79961.453 | I64: =IFERROR(Schedule!$P$60,0) -> 157278.39
A65: 58 | B65: =IFERROR(Schedule!$H$61,0) -> -19461277 | C65: =IFERROR(Schedule!$S$61,0) -> 8872784.4 | D65: =IFERROR(Schedule!$G$61,0) -> 2286357.2 | E65: =IFERROR(Schedule!$R$61,0) -> 4572321 | F65: =IFERROR(Schedule!$B$61,0) -> 3677141.1 | G65: =IFERROR(Schedule!$Q$61,0) -> 10417393 | H65: =IFERROR(Schedule!$D$61,0) -> 82697.104 | I65: =IFERROR(Schedule!$P$61,0) -> 161989.54
A66: 59 | B66: =IFERROR(Schedule!$H$62,0) -> -20997028 | C66: =IFERROR(Schedule!$S$62,0) -> 9581167.1 | D66: =IFERROR(Schedule!$G$62,0) -> 2371885.7 | E66: =IFERROR(Schedule!$R$62,0) -> 4739163 | F66: =IFERROR(Schedule!$B$62,0) -> 3805841 | G66: =IFERROR(Schedule!$Q$62,0) -> 11250785 | H66: =IFERROR(Schedule!$D$62,0) -> 85528.502 | I66: =IFERROR(Schedule!$P$62,0) -> 166842.03
A67: 60 | B67: =IFERROR(Schedule!$H$63,0) -> -22648310 | C67: =IFERROR(Schedule!$S$63,0) -> 10346220 | D67: =IFERROR(Schedule!$G$63,0) -> 2460344.7 | E67: =IFERROR(Schedule!$R$63,0) -> 4911003.1 | F67: =IFERROR(Schedule!$B$63,0) -> 3939045.5 | G67: =IFERROR(Schedule!$Q$63,0) -> 12150848 | H67: =IFERROR(Schedule!$D$63,0) -> 88459 | I67: =IFERROR(Schedule!$P$63,0) -> 171840.09
A68: 61 | B68: =IFERROR(Schedule!$H$64,0) -> -24423632 | C68: =IFERROR(Schedule!$S$64,0) -> 11172478 | D68: =IFERROR(Schedule!$G$64,0) -> 2551836.8 | E68: =IFERROR(Schedule!$R$64,0) -> 5087991.2 | F68: =IFERROR(Schedule!$B$64,0) -> 4076912 | G68: =IFERROR(Schedule!$Q$64,0) -> 13122915 | H68: =IFERROR(Schedule!$D$64,0) -> 91492.065 | I68: =IFERROR(Schedule!$P$64,0) -> 176988.09
A69: 62 | B69: =IFERROR(Schedule!$H$65,0) -> -26332125 | C69: =IFERROR(Schedule!$S$65,0) -> 12064836 | D69: =IFERROR(Schedule!$G$65,0) -> 2646468.1 | E69: =IFERROR(Schedule!$R$65,0) -> 5270281.7 | F69: =IFERROR(Schedule!$B$65,0) -> 4219604 | G69: =IFERROR(Schedule!$Q$65,0) -> 14172749 | H69: =IFERROR(Schedule!$D$65,0) -> 94631.287 | I69: =IFERROR(Schedule!$P$65,0) -> 182290.54
A70: 63 | B70: =IFERROR(Schedule!$H$66,0) -> -28383585 | C70: =IFERROR(Schedule!$S$66,0) -> 13028583 | D70: =IFERROR(Schedule!$G$66,0) -> 2744348.4 | E70: =IFERROR(Schedule!$R$66,0) -> 5458033.8 | F70: =IFERROR(Schedule!$B$66,0) -> 4367290.1 | G70: =IFERROR(Schedule!$Q$66,0) -> 15306569 | H70: =IFERROR(Schedule!$D$66,0) -> 97880.382 | I70: =IFERROR(Schedule!$P$66,0) -> 187752.05
A71: 64 | B71: =IFERROR(Schedule!$H$67,0) -> -30588522 | C71: =IFERROR(Schedule!$S$67,0) -> 14069430 | D71: =IFERROR(Schedule!$G$67,0) -> 2845591.6 | E71: =IFERROR(Schedule!$R$67,0) -> 5651411.2 | F71: =IFERROR(Schedule!$B$67,0) -> 4520145.3 | G71: =IFERROR(Schedule!$Q$67,0) -> 16531094 | H71: =IFERROR(Schedule!$D$67,0) -> 101243.2 | I71: =IFERROR(Schedule!$P$67,0) -> 193377.41
A72: 65 | B72: =IFERROR(Schedule!$H$68,0) -> -32958212 | C72: =IFERROR(Schedule!$S$68,0) -> 15193544 | D72: =IFERROR(Schedule!$G$68,0) -> 2950315.3 | E72: =IFERROR(Schedule!$R$68,0) -> 5850582.7 | F72: =IFERROR(Schedule!$B$68,0) -> 4678350.3 | G72: =IFERROR(Schedule!$Q$68,0) -> 17853582 | H72: =IFERROR(Schedule!$D$68,0) -> 104723.71 | I72: =IFERROR(Schedule!$P$68,0) -> 199171.54
A73: 66 | B73: =IFERROR(Schedule!$H$69,0) -> -35504752 | C73: =IFERROR(Schedule!$S$69,0) -> 16407588 | D73: =IFERROR(Schedule!$G$69,0) -> 3058641.4 | E73: =IFERROR(Schedule!$R$69,0) -> 6055722.2 | F73: =IFERROR(Schedule!$B$69,0) -> 4842092.6 | G73: =IFERROR(Schedule!$Q$69,0) -> 19281868 | H73: =IFERROR(Schedule!$D$69,0) -> 108326.04 | I73: =IFERROR(Schedule!$P$69,0) -> 205139.48
A74: 67 | B74: =IFERROR(Schedule!$H$70,0) -> -38241122 | C74: =IFERROR(Schedule!$S$70,0) -> 17718755 | D74: =IFERROR(Schedule!$G$70,0) -> 3170695.8 | E74: =IFERROR(Schedule!$R$70,0) -> 6267008.7 | F74: =IFERROR(Schedule!$B$70,0) -> 5011565.8 | G74: =IFERROR(Schedule!$Q$70,0) -> 20824418 | H74: =IFERROR(Schedule!$D$70,0) -> 112054.45 | I74: =IFERROR(Schedule!$P$70,0) -> 211286.47
A75: 68 | B75: =IFERROR(Schedule!$H$71,0) -> -41181244 | C75: =IFERROR(Schedule!$S$71,0) -> 19134815 | D75: =IFERROR(Schedule!$G$71,0) -> 3286609.2 | E75: =IFERROR(Schedule!$R$71,0) -> 6484626.5 | F75: =IFERROR(Schedule!$B$71,0) -> 5186970.6 | G75: =IFERROR(Schedule!$Q$71,0) -> 22490371 | H75: =IFERROR(Schedule!$D$71,0) -> 115913.35 | I75: =IFERROR(Schedule!$P$71,0) -> 217617.86
A76: 69 | B76: =IFERROR(Schedule!$H$72,0) -> -44340057 | C76: =IFERROR(Schedule!$S$72,0) -> 20664161 | D76: =IFERROR(Schedule!$G$72,0) -> 3406516.5 | E76: =IFERROR(Schedule!$R$72,0) -> 6708765.7 | F76: =IFERROR(Schedule!$B$72,0) -> 5368514.6 | G76: =IFERROR(Schedule!$Q$72,0) -> 24289601 | H76: =IFERROR(Schedule!$D$72,0) -> 119907.32 | I76: =IFERROR(Schedule!$P$72,0) -> 224139.2
A77: 70 | B77: =IFERROR(Schedule!$H$73,0) -> -47733584 | C77: =IFERROR(Schedule!$S$73,0) -> 22315853 | D77: =IFERROR(Schedule!$G$73,0) -> 3530557.6 | E77: =IFERROR(Schedule!$R$73,0) -> 6939621.9 | F77: =IFERROR(Schedule!$B$73,0) -> 5556412.6 | G77: =IFERROR(Schedule!$Q$73,0) -> 26232769 | H77: =IFERROR(Schedule!$D$73,0) -> 124041.08 | I77: =IFERROR(Schedule!$P$73,0) -> 230856.17
A78: 71 | B78: =IFERROR(Schedule!$H$74,0) -> -51379016 | C78: =IFERROR(Schedule!$S$74,0) -> 24099682 | D78: =IFERROR(Schedule!$G$74,0) -> 3658877.1 | E78: =IFERROR(Schedule!$R$74,0) -> 7177396.6 | F78: =IFERROR(Schedule!$B$74,0) -> 5750887.1 | G78: =IFERROR(Schedule!$Q$74,0) -> 28331390 | H78: =IFERROR(Schedule!$D$74,0) -> 128319.52 | I78: =IFERROR(Schedule!$P$74,0) -> 237774.66
A79: 72 | B79: =IFERROR(Schedule!$H$75,0) -> -55294793 | C79: =IFERROR(Schedule!$S$75,0) -> 26026216 | D79: =IFERROR(Schedule!$G$75,0) -> 3791624.8 | E79: =IFERROR(Schedule!$R$75,0) -> 7422297.3 | F79: =IFERROR(Schedule!$B$75,0) -> 5952168.1 | G79: =IFERROR(Schedule!$Q$75,0) -> 30597901 | H79: =IFERROR(Schedule!$D$75,0) -> 132747.7 | I79: =IFERROR(Schedule!$P$75,0) -> 244900.7
A80: 73 | B80: =IFERROR(Schedule!$H$76,0) -> -59500698 | C80: =IFERROR(Schedule!$S$76,0) -> 28106874 | D80: =IFERROR(Schedule!$G$76,0) -> 3928955.7 | E80: =IFERROR(Schedule!$R$76,0) -> 7674537.8 | F80: =IFERROR(Schedule!$B$76,0) -> 6160494 | G80: =IFERROR(Schedule!$Q$76,0) -> 33045734 | H80: =IFERROR(Schedule!$D$76,0) -> 137330.87 | I80: =IFERROR(Schedule!$P$76,0) -> 252240.52
A81: 74 | B81: =IFERROR(Schedule!$H$77,0) -> -64017950 | C81: =IFERROR(Schedule!$S$77,0) -> 30353983 | D81: =IFERROR(Schedule!$G$77,0) -> 4071030.1 | E81: =IFERROR(Schedule!$R$77,0) -> 7934338.3 | F81: =IFERROR(Schedule!$B$77,0) -> 6376111.3 | G81: =IFERROR(Schedule!$Q$77,0) -> 35689392 | H81: =IFERROR(Schedule!$D$77,0) -> 142074.45 | I81: =IFERROR(Schedule!$P$77,0) -> 259800.53
A82: 75 | B82: =IFERROR(Schedule!$H$78,0) -> -68869312 | C82: =IFERROR(Schedule!$S$78,0) -> 32780862 | D82: =IFERROR(Schedule!$G$78,0) -> 4218014.2 | E82: =IFERROR(Schedule!$R$78,0) -> 8201925.7 | F82: =IFERROR(Schedule!$B$78,0) -> 6599275.2 | G82: =IFERROR(Schedule!$Q$78,0) -> 38544544 | H82: =IFERROR(Schedule!$D$78,0) -> 146984.05 | I82: =IFERROR(Schedule!$P$78,0) -> 267587.35
A83: 76 | B83: =IFERROR(Schedule!$H$79,0) -> -74079203 | C83: =IFERROR(Schedule!$S$79,0) -> 35401891 | D83: =IFERROR(Schedule!$G$79,0) -> 4370079.7 | E83: =IFERROR(Schedule!$R$79,0) -> 8477533.4 | F83: =IFERROR(Schedule!$B$79,0) -> 6830249.8 | G83: =IFERROR(Schedule!$Q$79,0) -> 41628107 | H83: =IFERROR(Schedule!$D$79,0) -> 152065.5 | I83: =IFERROR(Schedule!$P$79,0) -> 275607.77
A84: 77 | B84: =IFERROR(Schedule!$H$80,0) -> -79673813 | C84: =IFERROR(Schedule!$S$80,0) -> 38232602 | D84: =IFERROR(Schedule!$G$80,0) -> 4527404.5 | E84: =IFERROR(Schedule!$R$80,0) -> 8761402.2 | F84: =IFERROR(Schedule!$B$80,0) -> 7069308.6 | G84: =IFERROR(Schedule!$Q$80,0) -> 44958356 | H84: =IFERROR(Schedule!$D$80,0) -> 157324.79 | I84: =IFERROR(Schedule!$P$80,0) -> 283868.8
A85: 78 | B85: =IFERROR(Schedule!$H$81,0) -> -85681237 | C85: =IFERROR(Schedule!$S$81,0) -> 41289770 | D85: =IFERROR(Schedule!$G$81,0) -> 4690172.6 | E85: =IFERROR(Schedule!$R$81,0) -> 9053779.9 | F85: =IFERROR(Schedule!$B$81,0) -> 7316734.4 | G85: =IFERROR(Schedule!$Q$81,0) -> 48555024 | H85: =IFERROR(Schedule!$D$81,0) -> 162768.16 | I85: =IFERROR(Schedule!$P$81,0) -> 292377.67
A86: 79 | B86: =IFERROR(Schedule!$H$82,0) -> -92131612 | C86: =IFERROR(Schedule!$S$82,0) -> 44591512 | D86: =IFERROR(Schedule!$G$82,0) -> 4858574.7 | E86: =IFERROR(Schedule!$R$82,0) -> 9354921.7 | F86: =IFERROR(Schedule!$B$82,0) -> 7572820.1 | G86: =IFERROR(Schedule!$Q$82,0) -> 52439426 | H86: =IFERROR(Schedule!$D$82,0) -> 168402.04 | I86: =IFERROR(Schedule!$P$82,0) -> 301141.8
A87: 80 | B87: =IFERROR(Schedule!$H$83,0) -> -99057261 | C87: =IFERROR(Schedule!$S$83,0) -> 48157393 | D87: =IFERROR(Schedule!$G$83,0) -> 5032807.8 | E87: =IFERROR(Schedule!$R$83,0) -> 9665090.6 | F87: =IFERROR(Schedule!$B$83,0) -> 7837868.8 | G87: =IFERROR(Schedule!$Q$83,0) -> 56634580 | H87: =IFERROR(Schedule!$D$83,0) -> 174233.11 | I87: =IFERROR(Schedule!$P$83,0) -> 310168.85
A88: 81 | B88: =IFERROR(Schedule!$H$84,0) -> -1.0649286e+08 | C88: =IFERROR(Schedule!$S$84,0) -> 52008545 | D88: =IFERROR(Schedule!$G$84,0) -> 5213076 | E88: =IFERROR(Schedule!$R$84,0) -> 9984557.3 | F88: =IFERROR(Schedule!$B$84,0) -> 8112194.2 | G88: =IFERROR(Schedule!$Q$84,0) -> 61165347 | H88: =IFERROR(Schedule!$D$84,0) -> 180268.27 | I88: =IFERROR(Schedule!$P$84,0) -> 319466.72
A89: 82 | B89: =IFERROR(Schedule!$H$85,0) -> -1.1447559e+08 | C89: =IFERROR(Schedule!$S$85,0) -> 56167788 | D89: =IFERROR(Schedule!$G$85,0) -> 5399590.7 | E89: =IFERROR(Schedule!$R$85,0) -> 10313601 | F89: =IFERROR(Schedule!$B$85,0) -> 8396121 | G89: =IFERROR(Schedule!$Q$85,0) -> 66058574 | H89: =IFERROR(Schedule!$D$85,0) -> 186514.66 | I89: =IFERROR(Schedule!$P$85,0) -> 329043.52
A90: 83 | B90: =IFERROR(Schedule!$H$86,0) -> -1.2304534e+08 | C90: =IFERROR(Schedule!$S$86,0) -> 60659771 | D90: =IFERROR(Schedule!$G$86,0) -> 5592570.4 | E90: =IFERROR(Schedule!$R$86,0) -> 10652508 | F90: =IFERROR(Schedule!$B$86,0) -> 8689985.2 | G90: =IFERROR(Schedule!$Q$86,0) -> 71343260 | H90: =IFERROR(Schedule!$D$86,0) -> 192979.67 | I90: =IFERROR(Schedule!$P$86,0) -> 338907.62
A91: 84 | B91: =IFERROR(Schedule!$H$87,0) -> -1.3224491e+08 | C91: =IFERROR(Schedule!$S$87,0) -> 65511113 | D91: =IFERROR(Schedule!$G$87,0) -> 5792241.3 | E91: =IFERROR(Schedule!$R$87,0) -> 11001576 | F91: =IFERROR(Schedule!$B$87,0) -> 8994134.7 | G91: =IFERROR(Schedule!$Q$87,0) -> 77050721 | H91: =IFERROR(Schedule!$D$87,0) -> 199670.96 | I91: =IFERROR(Schedule!$P$87,0) -> 349067.65
A92: 85 | B92: =IFERROR(Schedule!$H$88,0) -> -1.4212017e+08 | C92: =IFERROR(Schedule!$S$88,0) -> 70750562 | D92: =IFERROR(Schedule!$G$88,0) -> 5998837.8 | E92: =IFERROR(Schedule!$R$88,0) -> 11361109 | F92: =IFERROR(Schedule!$B$88,0) -> 9308929.4 | G92: =IFERROR(Schedule!$Q$88,0) -> 83214779 | H92: =IFERROR(Schedule!$D$88,0) -> 206596.45 | I92: =IFERROR(Schedule!$P$88,0) -> 359532.48
A93: 86 | B93: =IFERROR(Schedule!$H$89,0) -> -1.5272035e+08 | C93: =IFERROR(Schedule!$S$89,0) -> 76409167 | D93: =IFERROR(Schedule!$G$89,0) -> 6212602.1 | E93: =IFERROR(Schedule!$R$89,0) -> 11731420 | F93: =IFERROR(Schedule!$B$89,0) -> 9634741.9 | G93: =IFERROR(Schedule!$Q$89,0) -> 89871961 | H93: =IFERROR(Schedule!$D$89,0) -> 213764.32 | I93: =IFERROR(Schedule!$P$89,0) -> 370311.26
A94: 87 | B94: =IFERROR(Schedule!$H$90,0) -> -1.6409825e+08 | C94: =IFERROR(Schedule!$S$90,0) -> 82520460 | D94: =IFERROR(Schedule!$G$90,0) -> 6433785.2 | E94: =IFERROR(Schedule!$R$90,0) -> 12112833 | F94: =IFERROR(Schedule!$B$90,0) -> 9971957.9 | G94: =IFERROR(Schedule!$Q$90,0) -> 97061718 | H94: =IFERROR(Schedule!$D$90,0) -> 221183.07 | I94: =IFERROR(Schedule!$P$90,0) -> 381413.39
A95: 88 | B95: =IFERROR(Schedule!$H$91,0) -> -1.7631046e+08 | C95: =IFERROR(Schedule!$S$91,0) -> 89120657 | D95: =IFERROR(Schedule!$G$91,0) -> 6662646.7 | E95: =IFERROR(Schedule!$R$91,0) -> 12505682 | F95: =IFERROR(Schedule!$B$91,0) -> 10320976 | G95: =IFERROR(Schedule!$Q$91,0) -> 1.0482666e+08 | H95: =IFERROR(Schedule!$D$91,0) -> 228861.48 | I95: =IFERROR(Schedule!$P$91,0) -> 392848.6
A96: 89 | B96: =IFERROR(Schedule!$H$92,0) -> -1.8941774e+08 | C96: =IFERROR(Schedule!$S$92,0) -> 96248870 | D96: =IFERROR(Schedule!$G$92,0) -> 6899455.3 | E96: =IFERROR(Schedule!$R$92,0) -> 12910309 | F96: =IFERROR(Schedule!$B$92,0) -> 10682211 | G96: =IFERROR(Schedule!$Q$92,0) -> 1.1321279e+08 | H96: =IFERROR(Schedule!$D$92,0) -> 236808.63 | I96: =IFERROR(Schedule!$P$92,0) -> 404626.85
A97: 90 | B97: =IFERROR(Schedule!$H$93,0) -> -2.034852e+08 | C97: =IFERROR(Schedule!$S$93,0) -> 1.0394734e+08 | D97: =IFERROR(Schedule!$G$93,0) -> 7144489.2 | E97: =IFERROR(Schedule!$R$93,0) -> 13327067 | F97: =IFERROR(Schedule!$B$93,0) -> 11056088 | G97: =IFERROR(Schedule!$Q$93,0) -> 1.2226981e+08 | H97: =IFERROR(Schedule!$D$93,0) -> 245033.94 | I97: =IFERROR(Schedule!$P$93,0) -> 416758.46
A98: 91 | B98: =IFERROR(Schedule!$H$94,0) -> -2.1858271e+08 | C98: =IFERROR(Schedule!$S$94,0) -> 1.1226169e+08 | D98: =IFERROR(Schedule!$G$94,0) -> 7398036.4 | E98: =IFERROR(Schedule!$R$94,0) -> 13756321 | F98: =IFERROR(Schedule!$B$94,0) -> 11443051 | G98: =IFERROR(Schedule!$Q$94,0) -> 1.320514e+08 | H98: =IFERROR(Schedule!$D$94,0) -> 253547.12 | I98: =IFERROR(Schedule!$P$94,0) -> 429254.01
A99: 92 | B99: =IFERROR(Schedule!$H$95,0) -> -2.3478518e+08 | C99: =IFERROR(Schedule!$S$95,0) -> 1.2124118e+08 | D99: =IFERROR(Schedule!$G$95,0) -> 7660394.6 | E99: =IFERROR(Schedule!$R$95,0) -> 14198446 | F99: =IFERROR(Schedule!$B$95,0) -> 11843558 | G99: =IFERROR(Schedule!$Q$95,0) -> 1.4261551e+08 | H99: =IFERROR(Schedule!$D$95,0) -> 262358.27 | I99: =IFERROR(Schedule!$P$95,0) -> 442124.43
A100: 93 | B100: =IFERROR(Schedule!$H$96,0) -> -2.5217297e+08 | C100: =IFERROR(Schedule!$S$96,0) -> 1.3093904e+08 | D100: =IFERROR(Schedule!$G$96,0) -> 7931872.4 | E100: =IFERROR(Schedule!$R$96,0) -> 14653827 | F100: =IFERROR(Schedule!$B$96,0) -> 12258082 | G100: =IFERROR(Schedule!$Q$96,0) -> 1.5402475e+08 | H100: =IFERROR(Schedule!$D$96,0) -> 271477.81 | I100: =IFERROR(Schedule!$P$96,0) -> 455380.97
A101: 94 | B101: =IFERROR(Schedule!$H$97,0) -> -2.7083225e+08 | C101: =IFERROR(Schedule!$S$97,0) -> 1.4141272e+08 | D101: =IFERROR(Schedule!$G$97,0) -> 8212789 | E101: =IFERROR(Schedule!$R$97,0) -> 15122862 | F101: =IFERROR(Schedule!$B$97,0) -> 12687115 | G101: =IFERROR(Schedule!$Q$97,0) -> 1.6634673e+08 | H101: =IFERROR(Schedule!$D$97,0) -> 280916.54 | I101: =IFERROR(Schedule!$P$97,0) -> 469035.2
...

Sheet Expense Breakdown
A1: 📊 ANNUAL EXPENSE BREAKDOWN — Buyer vs. Renter at Selected Year
A2: Year (linked from Dashboard): | B2: =Dashboard!$I6 -> 30 | D2: Change 'View at Year' on Dashboard to update all results & charts
A4: BUYER — Annual Expenses at Selected Year | D4: RENTER — Annual Expenses at Selected Year | G4: Category | H4: Buyer ($) | I4: Renter ($)
A5: Mortgage Payment (P&I) | B5: =IFERROR(INDEX(Schedule!$I:$I,B2+3),0) -> 0 | D5: Rent Payments | E5: =IFERROR(INDEX(Schedule!$T:$T,B2+3),0) -> 70696.965 | G5: Mortgage / Rent | H5: =IFERROR(INDEX(Schedule!$I:$I,B2+3),0) -> 0 | I5: =IFERROR(INDEX(Schedule!$T:$T,B2+3),0) -> 70696.965
A6: Property Tax | B6: =IFERROR(INDEX(Schedule!$J:$J,B2+3),0) -> 16840.762 | D6: Renters Insurance | E6: =IFERROR(INDEX(Schedule!$U:$U,B2+3),0) -> 240 | G6: Property Tax | H6: =IFERROR(INDEX(Schedule!$J:$J,B2+3),0) -> 16840.762 | I6: 0
A7: Homeowner Insurance | B7: =IFERROR(INDEX(Schedule!$K:$K,B2+3),0) -> 1800 | D7: Opp. Cost Invested (notional) | E7: =Dashboard!$F28*12 -> 0 | G7: Insurance | H7: =IFERROR(INDEX(Schedule!$K:$K,B2+3),0) -> 1800 | I7: =IFERROR(INDEX(Schedule!$U:$U,B2+3),0) -> 240
A8: Maintenance & Repairs | B8: =IFERROR(INDEX(Schedule!$L:$L,B2+3),0) -> 14033.969 | D8: — | E8: — | G8: Maintenance | H8: =IFERROR(INDEX(Schedule!$L:$L,B2+3),0) -> 14033.969 | I8: 0
A9: PMI | B9: =IFERROR(INDEX(Schedule!$M:$M,B2+3),0) -> 0 | D9: — | E9: — | G9: PMI / HOA | H9: =IFERROR(INDEX(Schedule!$M:$M,B2+3)+Dashboard!$C15*12,0) -> 0 | I9: 0
A10: HOA Fees | B10: =Dashboard!$C15*12 -> 0 | D10: — | E10: —
A11: TOTAL ANNUAL BUYER COST | B11: =SUM(B5:B10) -> 32674.731 | D11: TOTAL ANNUAL RENTER COST | E11: =E5+E6 -> 70936.965

Sheet FIRE Calculator
A1: 🔥 FIRE CALCULATOR — Financial Independence, Retire Early
A2: 🟡 Yellow = your inputs | How many years until you can retire early?
B4: YOUR FINANCIAL SITUATION
B5: Annual Gross Income | C5: 75000
B6: Annual Expenses | C6: 48000
B7: Current Savings/Investments | C7: 25000
B8: Savings Rate | C8: 0.3
B9: Current Age | C9: 30
B10: INVESTMENT ASSUMPTIONS
B11: Expected Annual Return | C11: 0.07
B12: Inflation Rate | C12: 0.03
B13: Safe Withdrawal Rate | C13: 0.04
B14: Expected Social Security/mo | C14: 0
B15: HOUSING SCENARIO
B16: Monthly Cost if Buying | C16: 2800
B17: Monthly Cost if Renting | C17: 2000
B19: FIRE RESULTS
B20: Your FIRE Number | C20: =C6/C13 -> 1200000
B21: Annual Savings | C21: =C5*C8 -> 22500
B22: Monthly Savings | C22: =C5*C8/12 -> 1875
B23: Savings Rate | C23: =C8 -> 0.3
B24: Years to FIRE (base case) | C24: =IFERROR(LOG((C6/C13*C11+C5*C8)/(C5*C8),1+C11),99) -> 22.977546
B25: Retirement Age (base case) | C25: =C9+C24 -> 52.977546
B26: FIRE Year if Buying (housing cost adj.) | C26: =IFERROR(LOG((C6/C13*C11+C5*C8-(C16-C17)*12)/(C5*C8-(C16-C17)*12),1+C11),99) -> 29.803318
B27: FIRE Year if Renting (housing cost adj.) | C27: =IFERROR(LOG((C6/C13*C11+C5*C8+(C16-C17)*12)/(C5*C8+(C16-C17)*12),1+C11),99) -> 19.001205
B29: FIRE SCHEDULE (Year-by-Year Portfolio Growth)
B30: Year | C30: Portfolio Value | D30: Annual Savings | E30: FIRE Number
B31: 0 | C31: =C7 -> 25000 | D31: =C5*C8 -> 22500 | E31: =C6/C13 -> 1200000
B32: 1 | C32: =C31*(1+C11)+D32 -> 49250 | D32: =C5*C8 -> 22500 | E32: =C6/C13 -> 1200000
B33: 2 | C33: =C32*(1+C11)+D33 -> 75197.5 | D33: =C5*C8 -> 22500 | E33: =C6/C13 -> 1200000
B34: 3 | C34: =C33*(1+C11)+D34 -> 102961.32 | D34: =C5*C8 -> 22500 | E34: =C6/C13 -> 1200000
B35: 4 | C35: =C34*(1+C11)+D35 -> 132668.62 | D35: =C5*C8 -> 22500 | E35: =C6/C13 -> 1200000
B36: 5 | C36: =C35*(1+C11)+D36 -> 164455.42 | D36: =C5*C8 -> 22500 | E36: =C6/C13 -> 1200000
B37: 6 | C37: =C36*(1+C11)+D37 -> 198467.3 | D37: =C5*C8 -> 22500 | E37: =C6/C13 -> 1200000
B38: 7 | C38: =C37*(1+C11)+D38 -> 234860.01 | D38: =C5*C8 -> 22500 | E38: =C6/C13 -> 1200000
B39: 8 | C39: =C38*(1+C11)+D39 -> 273800.21 | D39: =C5*C8 -> 22500 | E39: =C6/C13 -> 1200000
B40: 9 | C40: =C39*(1+C11)+D40 -> 315466.23 | D40: =C5*C8 -> 22500 | E40: =C6/C13 -> 1200000
B41: 10 | C41: =C40*(1+C11)+D41 -> 360048.86 | D41: =C5*C8 -> 22500 | E41: =C6/C13 -> 1200000
B42: 11 | C42: =C41*(1+C11)+D42 -> 407752.28 | D42: =C5*C8 -> 22500 | E42: =C6/C13 -> 1200000
B43: 12 | C43: =C42*(1+C11)+D43 -> 458794.94 | D43: =C5*C8 -> 22500 | E43: =C6/C13 -> 1200000
B44: 13 | C44: =C43*(1+C11)+D44 -> 513410.59 | D44: =C5*C8 -> 22500 | E44: =C6/C13 -> 1200000
B45: 14 | C45: =C44*(1+C11)+D45 -> 571849.33 | D45: =C5*C8 -> 22500 | E45: =C6/C13 -> 1200000
B46: 15 | C46: =C45*(1+C11)+D46 -> 634378.78 | D46: =C5*C8 -> 22500 | E46: =C6/C13 -> 1200000
B47: 16 | C47: =C46*(1+C11)+D47 -> 701285.3 | D47: =C5*C8 -> 22500 | E47: =C6/C13 -> 1200000
B48: 17 | C48: =C47*(1+C11)+D48 -> 772875.27 | D48: =C5*C8 -> 22500 | E48: =C6/C13 -> 1200000
B49: 18 | C49: =C48*(1+C11)+D49 -> 849476.54 | D49: =C5*C8 -> 22500 | E49: =C6/C13 -> 1200000
B50: 19 | C50: =C49*(1+C11)+D50 -> 931439.9 | D50: =C5*C8 -> 22500 | E50: =C6/C13 -> 1200000
B51: 20 | C51: =C50*(1+C11)+D51 -> 1019140.7 | D51: =C5*C8 -> 22500 | E51: =C6/C13 -> 1200000
B52: 21 | C52: =C51*(1+C11)+D52 -> 1112980.5 | D52: =C5*C8 -> 22500 | E52: =C6/C13 -> 1200000
B53: 22 | C53: =C52*(1+C11)+D53 -> 1213389.2 | D53: =C5*C8 -> 22500 | E53: =C6/C13 -> 1200000
B54: 23 | C54: =C53*(1+C11)+D54 -> 1320826.4 | D54: =C5*C8 -> 22500 | E54: =C6/C13 -> 1200000
B55: 24 | C55: =C54*(1+C11)+D55 -> 1435784.3 | D55: =C5*C8 -> 22500 | E55: =C6/C13 -> 1200000
B56: 25 | C56: =C55*(1+C11)+D56 -> 1558789.2 | D56: =C5*C8 -> 22500 | E56: =C6/C13 -> 1200000
B57: 26 | C57: =C56*(1+C11)+D57 -> 1690404.4 | D57: =C5*C8 -> 22500 | E57: =C6/C13 -> 1200000
B58: 27 | C58: =C57*(1+C11)+D58 -> 1831232.7 | D58: =C5*C8 -> 22500 | E58: =C6/C13 -> 1200000
B59: 28 | C59: =C58*(1+C11)+D59 -> 1981919 | D59: =C5*C8 -> 22500 | E59: =C6/C13 -> 1200000
B60: 29 | C60: =C59*(1+C11)+D60 -> 2143153.3 | D60: =C5*C8 -> 22500 | E60: =C6/C13 -> 1200000
B61: 30 | C61: =C60*(1+C11)+D61 -> 2315674.1 | D61: =C5*C8 -> 22500 | E61: =C6/C13 -> 1200000
B62: 31 | C62: =C61*(1+C11)+D62 -> 2500271.3 | D62: =C5*C8 -> 22500 | E62: =C6/C13 -> 1200000
B63: 32 | C63: =C62*(1+C11)+D63 -> 2697790.2 | D63: =C5*C8 -> 22500 | E63: =C6/C13 -> 1200000
B64: 33 | C64: =C63*(1+C11)+D64 -> 2909135.6 | D64: =C5*C8 -> 22500 | E64: =C6/C13 -> 1200000
B65: 34 | C65: =C64*(1+C11)+D65 -> 3135275 | D65: =C5*C8 -> 22500 | E65: =C6/C13 -> 1200000
B66: 35 | C66: =C65*(1+C11)+D66 -> 3377244.3 | D66: =C5*C8 -> 22500 | E66: =C6/C13 -> 1200000
B67: 36 | C67: =C66*(1+C11)+D67 -> 3636151.4 | D67: =C5*C8 -> 22500 | E67: =C6/C13 -> 1200000
B68: 37 | C68: =C67*(1+C11)+D68 -> 3913182 | D68: =C5*C8 -> 22500 | E68: =C6/C13 -> 1200000
B69: 38 | C69: =C68*(1+C11)+D69 -> 4209604.7 | D69: =C5*C8 -> 22500 | E69: =C6/C13 -> 1200000
B70: 39 | C70: =C69*(1+C11)+D70 -> 4526777.1 | D70: =C5*C8 -> 22500 | E70: =C6/C13 -> 1200000
B71: 40 | C71: =C70*(1+C11)+D71 -> 4866151.5 | D71: =C5*C8 -> 22500 | E71: =C6/C13 -> 1200000
B72: 41 | C72: =C71*(1+C11)+D72 -> 5229282.1 | D72: =C5*C8 -> 22500 | E72: =C6/C13 -> 1200000
B73: 42 | C73: =C72*(1+C11)+D73 -> 5617831.8 | D73: =C5*C8 -> 22500 | E73: =C6/C13 -> 1200000
B74: 43 | C74: =C73*(1+C11)+D74 -> 6033580 | D74: =C5*C8 -> 22500 | E74: =C6/C13 -> 1200000
B75: 44 | C75: =C74*(1+C11)+D75 -> 6478430.6 | D75: =C5*C8 -> 22500 | E75: =C6/C13 -> 1200000
B76: 45 | C76: =C75*(1+C11)+D76 -> 6954420.8 | D76: =C5*C8 -> 22500 | E76: =C6/C13 -> 1200000
B77: 46 | C77: =C76*(1+C11)+D77 -> 7463730.2 | D77: =C5*C8 -> 22500 | E77: =C6/C13 -> 1200000
B78: 47 | C78: =C77*(1+C11)+D78 -> 8008691.4 | D78: =C5*C8 -> 22500 | E78: =C6/C13 -> 1200000
B79: 48 | C79: =C78*(1+C11)+D79 -> 8591799.8 | D79: =C5*C8 -> 22500 | E79: =C6/C13 -> 1200000
B80: 49 | C80: =C79*(1+C11)+D80 -> 9215725.7 | D80: =C5*C8 -> 22500 | E80: =C6/C13 -> 1200000
B81: 50 | C81: =C80*(1+C11)+D81 -> 9883326.5 | D81: =C5*C8 -> 22500 | E81: =C6/C13 -> 1200000

Sheet Amortization
A1: Yr | B1: Mo. | C1: Payment | D1: Principal | E1: Interest | F1: Balance | G1: Cum. Interest | H1: Cum. Principal
A2: Monthly amortization (360 months). All formulas locked. Inputs pull from Dashboard.
A3: =INT((1-1)/12)+1 -> 1 | B3: =MOD(1-1,12)+1 -> 1 | C3: =Dashboard!$C26 -> 0 | D3: =Dashboard!$C26-(Dashboard!$C6-Dashboard!$C8)*(Dashboard!$C10/12) -> -2333.3333 | E3: =(Dashboard!$C6-Dashboard!$C8)*(Dashboard!$C10/12) -> 2333.3333 | F3: =MAX((Dashboard!$C6-Dashboard!$C8)-(Dashboard!$C26-(Dashboard!$C6-Dashboard!$C8)*(Dashboard!$C10/12)),0) -> 402333.33 | G3: =(Dashboard!$C6-Dashboard!$C8)*(Dashboard!$C10/12) -> 2333.3333 | H3: =Dashboard!$C26-(Dashboard!$C6-Dashboard!$C8)*(Dashboard!$C10/12) -> -2333.3333
A4: =INT((2-1)/12)+1 -> 1 | B4: =MOD(2-1,12)+1 -> 2 | C4: =Dashboard!$C26 -> 0 | D4: =Dashboard!$C26-F$3*(Dashboard!$C10/12) -> -2346.9444 | E4: =F$3*(Dashboard!$C10/12) -> 2346.9444 | F4: =MAX(F$3-(Dashboard!$C26-F$3*(Dashboard!$C10/12)),0) -> 404680.28 | G4: =G$3+F$3*(Dashboard!$C10/12) -> 4680.2778 | H4: =H$3+Dashboard!$C26-F$3*(Dashboard!$C10/12) -> -4680.2778
A5: =INT((3-1)/12)+1 -> 1 | B5: =MOD(3-1,12)+1 -> 3 | C5: =Dashboard!$C26 -> 0 | D5: =Dashboard!$C26-F$4*(Dashboard!$C10/12) -> -2360.635 | E5: =F$4*(Dashboard!$C10/12) -> 2360.635 | F5: =MAX(F$4-(Dashboard!$C26-F$4*(Dashboard!$C10/12)),0) -> 407040.91 | G5: =G$4+F$4*(Dashboard!$C10/12) -> 7040.9127 | H5: =H$4+Dashboard!$C26-F$4*(Dashboard!$C10/12) -> -7040.9127
A6: =INT((4-1)/12)+1 -> 1 | B6: =MOD(4-1,12)+1 -> 4 | C6: =Dashboard!$C26 -> 0 | D6: =Dashboard!$C26-F$5*(Dashboard!$C10/12) -> -2374.4053 | E6: =F$5*(Dashboard!$C10/12) -> 2374.4053 | F6: =MAX(F$5-(Dashboard!$C26-F$5*(Dashboard!$C10/12)),0) -> 409415.32 | G6: =G$5+F$5*(Dashboard!$C10/12) -> 9415.3181 | H6: =H$5+Dashboard!$C26-F$5*(Dashboard!$C10/12) -> -9415.3181
A7: =INT((5-1)/12)+1 -> 1 | B7: =MOD(5-1,12)+1 -> 5 | C7: =Dashboard!$C26 -> 0 | D7: =Dashboard!$C26-F$6*(Dashboard!$C10/12) -> -2388.256 | E7: =F$6*(Dashboard!$C10/12) -> 2388.256 | F7: =MAX(F$6-(Dashboard!$C26-F$6*(Dashboard!$C10/12)),0) -> 411803.57 | G7: =G$6+F$6*(Dashboard!$C10/12) -> 11803.574 | H7: =H$6+Dashboard!$C26-F$6*(Dashboard!$C10/12) -> -11803.574
A8: =INT((6-1)/12)+1 -> 1 | B8: =MOD(6-1,12)+1 -> 6 | C8: =Dashboard!$C26 -> 0 | D8: =Dashboard!$C26-F$7*(Dashboard!$C10/12) -> -2402.1875 | E8: =F$7*(Dashboard!$C10/12) -> 2402.1875 | F8: =MAX(F$7-(Dashboard!$C26-F$7*(Dashboard!$C10/12)),0) -> 414205.76 | G8: =G$7+F$7*(Dashboard!$C10/12) -> 14205.762 | H8: =H$7+Dashboard!$C26-F$7*(Dashboard!$C10/12) -> -14205.762
A9: =INT((7-1)/12)+1 -> 1 | B9: =MOD(7-1,12)+1 -> 7 | C9: =Dashboard!$C26 -> 0 | D9: =Dashboard!$C26-F$8*(Dashboard!$C10/12) -> -2416.2003 | E9: =F$8*(Dashboard!$C10/12) -> 2416.2003 | F9: =MAX(F$8-(Dashboard!$C26-F$8*(Dashboard!$C10/12)),0) -> 416621.96 | G9: =G$8+F$8*(Dashboard!$C10/12) -> 16621.962 | H9: =H$8+Dashboard!$C26-F$8*(Dashboard!$C10/12) -> -16621.962
A10: =INT((8-1)/12)+1 -> 1 | B10: =MOD(8-1,12)+1 -> 8 | C10: =Dashboard!$C26 -> 0 | D10: =Dashboard!$C26-F$9*(Dashboard!$C10/12) -> -2430.2948 | E10: =F$9*(Dashboard!$C10/12) -> 2430.2948 | F10: =MAX(F$9-(Dashboard!$C26-F$9*(Dashboard!$C10/12)),0) -> 419052.26 | G10: =G$9+F$9*(Dashboard!$C10/12) -> 19052.257 | H10: =H$9+Dashboard!$C26-F$9*(Dashboard!$C10/12) -> -19052.257
A11: =INT((9-1)/12)+1 -> 1 | B11: =MOD(9-1,12)+1 -> 9 | C11: =Dashboard!$C26 -> 0 | D11: =Dashboard!$C26-F$10*(Dashboard!$C10/12) -> -2444.4715 | E11: =F$10*(Dashboard!$C10/12) -> 2444.4715 | F11: =MAX(F$10-(Dashboard!$C26-F$10*(Dashboard!$C10/12)),0) -> 421496.73 | G11: =G$10+F$10*(Dashboard!$C10/12) -> 21496.728 | H11: =H$10+Dashboard!$C26-F$10*(Dashboard!$C10/12) -> -21496.728
A12: =INT((10-1)/12)+1 -> 1 | B12: =MOD(10-1,12)+1 -> 10 | C12: =Dashboard!$C26 -> 0 | D12: =Dashboard!$C26-F$11*(Dashboard!$C10/12) -> -2458.7309 | E12: =F$11*(Dashboard!$C10/12) -> 2458.7309 | F12: =MAX(F$11-(Dashboard!$C26-F$11*(Dashboard!$C10/12)),0) -> 423955.46 | G12: =G$11+F$11*(Dashboard!$C10/12) -> 23955.459 | H12: =H$11+Dashboard!$C26-F$11*(Dashboard!$C10/12) -> -23955.459
A13: =INT((11-1)/12)+1 -> 1 | B13: =MOD(11-1,12)+1 -> 11 | C13: =Dashboard!$C26 -> 0 | D13: =Dashboard!$C26-F$12*(Dashboard!$C10/12) -> -2473.0735 | E13: =F$12*(Dashboard!$C10/12) -> 2473.0735 | F13: =MAX(F$12-(Dashboard!$C26-F$12*(Dashboard!$C10/12)),0) -> 426428.53 | G13: =G$12+F$12*(Dashboard!$C10/12) -> 26428.533 | H13: =H$12+Dashboard!$C26-F$12*(Dashboard!$C10/12) -> -26428.533
A14: =INT((12-1)/12)+1 -> 1 | B14: =MOD(12-1,12)+1 -> 12 | C14: =Dashboard!$C26 -> 0 | D14: =Dashboard!$C26-F$13*(Dashboard!$C10/12) -> -2487.4998 | E14: =F$13*(Dashboard!$C10/12) -> 2487.4998 | F14: =MAX(F$13-(Dashboard!$C26-F$13*(Dashboard!$C10/12)),0) -> 428916.03 | G14: =G$13+F$13*(Dashboard!$C10/12) -> 28916.032 | H14: =H$13+Dashboard!$C26-F$13*(Dashboard!$C10/12) -> -28916.032
A15: =INT((13-1)/12)+1 -> 2 | B15: =MOD(13-1,12)+1 -> 1 | C15: =Dashboard!$C26 -> 0 | D15: =Dashboard!$C26-F$14*(Dashboard!$C10/12) -> -2502.0102 | E15: =F$14*(Dashboard!$C10/12) -> 2502.0102 | F15: =MAX(F$14-(Dashboard!$C26-F$14*(Dashboard!$C10/12)),0) -> 431418.04 | G15: =G$14+F$14*(Dashboard!$C10/12) -> 31418.043 | H15: =H$14+Dashboard!$C26-F$14*(Dashboard!$C10/12) -> -31418.043
A16: =INT((14-1)/12)+1 -> 2 | B16: =MOD(14-1,12)+1 -> 2 | C16: =Dashboard!$C26 -> 0 | D16: =Dashboard!$C26-F$15*(Dashboard!$C10/12) -> -2516.6052 | E16: =F$15*(Dashboard!$C10/12) -> 2516.6052 | F16: =MAX(F$15-(Dashboard!$C26-F$15*(Dashboard!$C10/12)),0) -> 433934.65 | G16: =G$15+F$15*(Dashboard!$C10/12) -> 33934.648 | H16: =H$15+Dashboard!$C26-F$15*(Dashboard!$C10/12) -> -33934.648
A17: =INT((15-1)/12)+1 -> 2 | B17: =MOD(15-1,12)+1 -> 3 | C17: =Dashboard!$C26 -> 0 | D17: =Dashboard!$C26-F$16*(Dashboard!$C10/12) -> -2531.2854 | E17: =F$16*(Dashboard!$C10/12) -> 2531.2854 | F17: =MAX(F$16-(Dashboard!$C26-F$16*(Dashboard!$C10/12)),0) -> 436465.93 | G17: =G$16+F$16*(Dashboard!$C10/12) -> 36465.933 | H17: =H$16+Dashboard!$C26-F$16*(Dashboard!$C10/12) -> -36465.933
A18: =INT((16-1)/12)+1 -> 2 | B18: =MOD(16-1,12)+1 -> 4 | C18: =Dashboard!$C26 -> 0 | D18: =Dashboard!$C26-F$17*(Dashboard!$C10/12) -> -2546.0513 | E18: =F$17*(Dashboard!$C10/12) -> 2546.0513 | F18: =MAX(F$17-(Dashboard!$C26-F$17*(Dashboard!$C10/12)),0) -> 439011.98 | G18: =G$17+F$17*(Dashboard!$C10/12) -> 39011.985 | H18: =H$17+Dashboard!$C26-F$17*(Dashboard!$C10/12) -> -39011.985
A19: =INT((17-1)/12)+1 -> 2 | B19: =MOD(17-1,12)+1 -> 5 | C19: =Dashboard!$C26 -> 0 | D19: =Dashboard!$C26-F$18*(Dashboard!$C10/12) -> -2560.9032 | E19: =F$18*(Dashboard!$C10/12) -> 2560.9032 | F19: =MAX(F$18-(Dashboard!$C26-F$18*(Dashboard!$C10/12)),0) -> 441572.89 | G19: =G$18+F$18*(Dashboard!$C10/12) -> 41572.888 | H19: =H$18+Dashboard!$C26-F$18*(Dashboard!$C10/12) -> -41572.888
A20: =INT((18-1)/12)+1 -> 2 | B20: =MOD(18-1,12)+1 -> 6 | C20: =Dashboard!$C26 -> 0 | D20: =Dashboard!$C26-F$19*(Dashboard!$C10/12) -> -2575.8418 | E20: =F$19*(Dashboard!$C10/12) -> 2575.8418 | F20: =MAX(F$19-(Dashboard!$C26-F$19*(Dashboard!$C10/12)),0) -> 444148.73 | G20: =G$19+F$19*(Dashboard!$C10/12) -> 44148.73 | H20: =H$19+Dashboard!$C26-F$19*(Dashboard!$C10/12) -> -44148.73
A21: =INT((19-1)/12)+1 -> 2 | B21: =MOD(19-1,12)+1 -> 7 | C21: =Dashboard!$C26 -> 0 | D21: =Dashboard!$C26-F$20*(Dashboard!$C10/12) -> -2590.8676 | E21: =F$20*(Dashboard!$C10/12) -> 2590.8676 | F21: =MAX(F$20-(Dashboard!$C26-F$20*(Dashboard!$C10/12)),0) -> 446739.6 | G21: =G$20+F$20*(Dashboard!$C10/12) -> 46739.597 | H21: =H$20+Dashboard!$C26-F$20*(Dashboard!$C10/12) -> -46739.597
A22: =INT((20-1)/12)+1 -> 2 | B22: =MOD(20-1,12)+1 -> 8 | C22: =Dashboard!$C26 -> 0 | D22: =Dashboard!$C26-F$21*(Dashboard!$C10/12) -> -2605.981 | E22: =F$21*(Dashboard!$C10/12) -> 2605.981 | F22: =MAX(F$21-(Dashboard!$C26-F$21*(Dashboard!$C10/12)),0) -> 449345.58 | G22: =G$21+F$21*(Dashboard!$C10/12) -> 49345.578 | H22: =H$21+Dashboard!$C26-F$21*(Dashboard!$C10/12) -> -49345.578
A23: =INT((21-1)/12)+1 -> 2 | B23: =MOD(21-1,12)+1 -> 9 | C23: =Dashboard!$C26 -> 0 | D23: =Dashboard!$C26-F$22*(Dashboard!$C10/12) -> -2621.1825 | E23: =F$22*(Dashboard!$C10/12) -> 2621.1825 | F23: =MAX(F$22-(Dashboard!$C26-F$22*(Dashboard!$C10/12)),0) -> 451966.76 | G23: =G$22+F$22*(Dashboard!$C10/12) -> 51966.761 | H23: =H$22+Dashboard!$C26-F$22*(Dashboard!$C10/12) -> -51966.761
A24: =INT((22-1)/12)+1 -> 2 | B24: =MOD(22-1,12)+1 -> 10 | C24: =Dashboard!$C26 -> 0 | D24: =Dashboard!$C26-F$23*(Dashboard!$C10/12) -> -2636.4728 | E24: =F$23*(Dashboard!$C10/12) -> 2636.4728 | F24: =MAX(F$23-(Dashboard!$C26-F$23*(Dashboard!$C10/12)),0) -> 454603.23 | G24: =G$23+F$23*(Dashboard!$C10/12) -> 54603.233 | H24: =H$23+Dashboard!$C26-F$23*(Dashboard!$C10/12) -> -54603.233
A25: =INT((23-1)/12)+1 -> 2 | B25: =MOD(23-1,12)+1 -> 11 | C25: =Dashboard!$C26 -> 0 | D25: =Dashboard!$C26-F$24*(Dashboard!$C10/12) -> -2651.8522 | E25: =F$24*(Dashboard!$C10/12) -> 2651.8522 | F25: =MAX(F$24-(Dashboard!$C26-F$24*(Dashboard!$C10/12)),0) -> 457255.09 | G25: =G$24+F$24*(Dashboard!$C10/12) -> 57255.086 | H25: =H$24+Dashboard!$C26-F$24*(Dashboard!$C10/12) -> -57255.086
A26: =INT((24-1)/12)+1 -> 2 | B26: =MOD(24-1,12)+1 -> 12 | C26: =Dashboard!$C26 -> 0 | D26: =Dashboard!$C26-F$25*(Dashboard!$C10/12) -> -2667.3213 | E26: =F$25*(Dashboard!$C10/12) -> 2667.3213 | F26: =MAX(F$25-(Dashboard!$C26-F$25*(Dashboard!$C10/12)),0) -> 459922.41 | G26: =G$25+F$25*(Dashboard!$C10/12) -> 59922.407 | H26: =H$25+Dashboard!$C26-F$25*(Dashboard!$C10/12) -> -59922.407
A27: =INT((25-1)/12)+1 -> 3 | B27: =MOD(25-1,12)+1 -> 1 | C27: =Dashboard!$C26 -> 0 | D27: =Dashboard!$C26-F$26*(Dashboard!$C10/12) -> -2682.8807 | E27: =F$26*(Dashboard!$C10/12) -> 2682.8807 | F27: =MAX(F$26-(Dashboard!$C26-F$26*(Dashboard!$C10/12)),0) -> 462605.29 | G27: =G$26+F$26*(Dashboard!$C10/12) -> 62605.288 | H27: =H$26+Dashboard!$C26-F$26*(Dashboard!$C10/12) -> -62605.288
A28: =INT((26-1)/12)+1 -> 3 | B28: =MOD(26-1,12)+1 -> 2 | C28: =Dashboard!$C26 -> 0 | D28: =Dashboard!$C26-F$27*(Dashboard!$C10/12) -> -2698.5308 | E28: =F$27*(Dashboard!$C10/12) -> 2698.5308 | F28: =MAX(F$27-(Dashboard!$C26-F$27*(Dashboard!$C10/12)),0) -> 465303.82 | G28: =G$27+F$27*(Dashboard!$C10/12) -> 65303.819 | H28: =H$27+Dashboard!$C26-F$27*(Dashboard!$C10/12) -> -65303.819
A29: =INT((27-1)/12)+1 -> 3 | B29: =MOD(27-1,12)+1 -> 3 | C29: =Dashboard!$C26 -> 0 | D29: =Dashboard!$C26-F$28*(Dashboard!$C10/12) -> -2714.2723 | E29: =F$28*(Dashboard!$C10/12) -> 2714.2723 | F29: =MAX(F$28-(Dashboard!$C26-F$28*(Dashboard!$C10/12)),0) -> 468018.09 | G29: =G$28+F$28*(Dashboard!$C10/12) -> 68018.091 | H29: =H$28+Dashboard!$C26-F$28*(Dashboard!$C10/12) -> -68018.091
A30: =INT((28-1)/12)+1 -> 3 | B30: =MOD(28-1,12)+1 -> 4 | C30: =Dashboard!$C26 -> 0 | D30: =Dashboard!$C26-F$29*(Dashboard!$C10/12) -> -2730.1055 | E30: =F$29*(Dashboard!$C10/12) -> 2730.1055 | F30: =MAX(F$29-(Dashboard!$C26-F$29*(Dashboard!$C10/12)),0) -> 470748.2 | G30: =G$29+F$29*(Dashboard!$C10/12) -> 70748.196 | H30: =H$29+Dashboard!$C26-F$29*(Dashboard!$C10/12) -> -70748.196
A31: =INT((29-1)/12)+1 -> 3 | B31: =MOD(29-1,12)+1 -> 5 | C31: =Dashboard!$C26 -> 0 | D31: =Dashboard!$C26-F$30*(Dashboard!$C10/12) -> -2746.0311 | E31: =F$30*(Dashboard!$C10/12) -> 2746.0311 | F31: =MAX(F$30-(Dashboard!$C26-F$30*(Dashboard!$C10/12)),0) -> 473494.23 | G31: =G$30+F$30*(Dashboard!$C10/12) -> 73494.228 | H31: =H$30+Dashboard!$C26-F$30*(Dashboard!$C10/12) -> -73494.228
A32: =INT((30-1)/12)+1 -> 3 | B32: =MOD(30-1,12)+1 -> 6 | C32: =Dashboard!$C26 -> 0 | D32: =Dashboard!$C26-F$31*(Dashboard!$C10/12) -> -2762.0497 | E32: =F$31*(Dashboard!$C10/12) -> 2762.0497 | F32: =MAX(F$31-(Dashboard!$C26-F$31*(Dashboard!$C10/12)),0) -> 476256.28 | G32: =G$31+F$31*(Dashboard!$C10/12) -> 76256.277 | H32: =H$31+Dashboard!$C26-F$31*(Dashboard!$C10/12) -> -76256.277
A33: =INT((31-1)/12)+1 -> 3 | B33: =MOD(31-1,12)+1 -> 7 | C33: =Dashboard!$C26 -> 0 | D33: =Dashboard!$C26-F$32*(Dashboard!$C10/12) -> -2778.1616 | E33: =F$32*(Dashboard!$C10/12) -> 2778.1616 | F33: =MAX(F$32-(Dashboard!$C26-F$32*(Dashboard!$C10/12)),0) -> 479034.44 | G33: =G$32+F$32*(Dashboard!$C10/12) -> 79034.439 | H33: =H$32+Dashboard!$C26-F$32*(Dashboard!$C10/12) -> -79034.439
A34: =INT((32-1)/12)+1 -> 3 | B34: =MOD(32-1,12)+1 -> 8 | C34: =Dashboard!$C26 -> 0 | D34: =Dashboard!$C26-F$33*(Dashboard!$C10/12) -> -2794.3676 | E34: =F$33*(Dashboard!$C10/12) -> 2794.3676 | F34: =MAX(F$33-(Dashboard!$C26-F$33*(Dashboard!$C10/12)),0) -> 481828.81 | G34: =G$33+F$33*(Dashboard!$C10/12) -> 81828.806 | H34: =H$33+Dashboard!$C26-F$33*(Dashboard!$C10/12) -> -81828.806
A35: =INT((33-1)/12)+1 -> 3 | B35: =MOD(33-1,12)+1 -> 9 | C35: =Dashboard!$C26 -> 0 | D35: =Dashboard!$C26-F$34*(Dashboard!$C10/12) -> -2810.668 | E35: =F$34*(Dashboard!$C10/12) -> 2810.668 | F35: =MAX(F$34-(Dashboard!$C26-F$34*(Dashboard!$C10/12)),0) -> 484639.47 | G35: =G$34+F$34*(Dashboard!$C10/12) -> 84639.474 | H35: =H$34+Dashboard!$C26-F$34*(Dashboard!$C10/12) -> -84639.474
A36: =INT((34-1)/12)+1 -> 3 | B36: =MOD(34-1,12)+1 -> 10 | C36: =Dashboard!$C26 -> 0 | D36: =Dashboard!$C26-F$35*(Dashboard!$C10/12) -> -2827.0636 | E36: =F$35*(Dashboard!$C10/12) -> 2827.0636 | F36: =MAX(F$35-(Dashboard!$C26-F$35*(Dashboard!$C10/12)),0) -> 487466.54 | G36: =G$35+F$35*(Dashboard!$C10/12) -> 87466.538 | H36: =H$35+Dashboard!$C26-F$35*(Dashboard!$C10/12) -> -87466.538
A37: =INT((35-1)/12)+1 -> 3 | B37: =MOD(35-1,12)+1 -> 11 | C37: =Dashboard!$C26 -> 0 | D37: =Dashboard!$C26-F$36*(Dashboard!$C10/12) -> -2843.5548 | E37: =F$36*(Dashboard!$C10/12) -> 2843.5548 | F37: =MAX(F$36-(Dashboard!$C26-F$36*(Dashboard!$C10/12)),0) -> 490310.09 | G37: =G$36+F$36*(Dashboard!$C10/12) -> 90310.093 | H37: =H$36+Dashboard!$C26-F$36*(Dashboard!$C10/12) -> -90310.093
A38: =INT((36-1)/12)+1 -> 3 | B38: =MOD(36-1,12)+1 -> 12 | C38: =Dashboard!$C26 -> 0 | D38: =Dashboard!$C26-F$37*(Dashboard!$C10/12) -> -2860.1422 | E38: =F$37*(Dashboard!$C10/12) -> 2860.1422 | F38: =MAX(F$37-(Dashboard!$C26-F$37*(Dashboard!$C10/12)),0) -> 493170.23 | G38: =G$37+F$37*(Dashboard!$C10/12) -> 93170.235 | H38: =H$37+Dashboard!$C26-F$37*(Dashboard!$C10/12) -> -93170.235
A39: =INT((37-1)/12)+1 -> 4 | B39: =MOD(37-1,12)+1 -> 1 | C39: =Dashboard!$C26 -> 0 | D39: =Dashboard!$C26-F$38*(Dashboard!$C10/12) -> -2876.8264 | E39: =F$38*(Dashboard!$C10/12) -> 2876.8264 | F39: =MAX(F$38-(Dashboard!$C26-F$38*(Dashboard!$C10/12)),0) -> 496047.06 | G39: =G$38+F$38*(Dashboard!$C10/12) -> 96047.061 | H39: =H$38+Dashboard!$C26-F$38*(Dashboard!$C10/12) -> -96047.061
A40: =INT((38-1)/12)+1 -> 4 | B40: =MOD(38-1,12)+1 -> 2 | C40: =Dashboard!$C26 -> 0 | D40: =Dashboard!$C26-F$39*(Dashboard!$C10/12) -> -2893.6079 | E40: =F$39*(Dashboard!$C10/12) -> 2893.6079 | F40: =MAX(F$39-(Dashboard!$C26-F$39*(Dashboard!$C10/12)),0) -> 498940.67 | G40: =G$39+F$39*(Dashboard!$C10/12) -> 98940.669 | H40: =H$39+Dashboard!$C26-F$39*(Dashboard!$C10/12) -> -98940.669
A41: =INT((39-1)/12)+1 -> 4 | B41: =MOD(39-1,12)+1 -> 3 | C41: =Dashboard!$C26 -> 0 | D41: =Dashboard!$C26-F$40*(Dashboard!$C10/12) -> -2910.4872 | E41: =F$40*(Dashboard!$C10/12) -> 2910.4872 | F41: =MAX(F$40-(Dashboard!$C26-F$40*(Dashboard!$C10/12)),0) -> 501851.16 | G41: =G$40+F$40*(Dashboard!$C10/12) -> 101851.16 | H41: =H$40+Dashboard!$C26-F$40*(Dashboard!$C10/12) -> -101851.16
A42: =INT((40-1)/12)+1 -> 4 | B42: =MOD(40-1,12)+1 -> 4 | C42: =Dashboard!$C26 -> 0 | D42: =Dashboard!$C26-F$41*(Dashboard!$C10/12) -> -2927.4651 | E42: =F$41*(Dashboard!$C10/12) -> 2927.4651 | F42: =MAX(F$41-(Dashboard!$C26-F$41*(Dashboard!$C10/12)),0) -> 504778.62 | G42: =G$41+F$41*(Dashboard!$C10/12) -> 104778.62 | H42: =H$41+Dashboard!$C26-F$41*(Dashboard!$C10/12) -> -104778.62
A43: =INT((41-1)/12)+1 -> 4 | B43: =MOD(41-1,12)+1 -> 5 | C43: =Dashboard!$C26 -> 0 | D43: =Dashboard!$C26-F$42*(Dashboard!$C10/12) -> -2944.542 | E43: =F$42*(Dashboard!$C10/12) -> 2944.542 | F43: =MAX(F$42-(Dashboard!$C26-F$42*(Dashboard!$C10/12)),0) -> 507723.16 | G43: =G$42+F$42*(Dashboard!$C10/12) -> 107723.16 | H43: =H$42+Dashboard!$C26-F$42*(Dashboard!$C10/12) -> -107723.16
A44: =INT((42-1)/12)+1 -> 4 | B44: =MOD(42-1,12)+1 -> 6 | C44: =Dashboard!$C26 -> 0 | D44: =Dashboard!$C26-F$43*(Dashboard!$C10/12) -> -2961.7185 | E44: =F$43*(Dashboard!$C10/12) -> 2961.7185 | F44: =MAX(F$43-(Dashboard!$C26-F$43*(Dashboard!$C10/12)),0) -> 510684.88 | G44: =G$43+F$43*(Dashboard!$C10/12) -> 110684.88 | H44: =H$43+Dashboard!$C26-F$43*(Dashboard!$C10/12) -> -110684.88
A45: =INT((43-1)/12)+1 -> 4 | B45: =MOD(43-1,12)+1 -> 7 | C45: =Dashboard!$C26 -> 0 | D45: =Dashboard!$C26-F$44*(Dashboard!$C10/12) -> -2978.9951 | E45: =F$44*(Dashboard!$C10/12) -> 2978.9951 | F45: =MAX(F$44-(Dashboard!$C26-F$44*(Dashboard!$C10/12)),0) -> 513663.88 | G45: =G$44+F$44*(Dashboard!$C10/12) -> 113663.88 | H45: =H$44+Dashboard!$C26-F$44*(Dashboard!$C10/12) -> -113663.88
A46: =INT((44-1)/12)+1 -> 4 | B46: =MOD(44-1,12)+1 -> 8 | C46: =Dashboard!$C26 -> 0 | D46: =Dashboard!$C26-F$45*(Dashboard!$C10/12) -> -2996.3726 | E46: =F$45*(Dashboard!$C10/12) -> 2996.3726 | F46: =MAX(F$45-(Dashboard!$C26-F$45*(Dashboard!$C10/12)),0) -> 516660.25 | G46: =G$45+F$45*(Dashboard!$C10/12) -> 116660.25 | H46: =H$45+Dashboard!$C26-F$45*(Dashboard!$C10/12) -> -116660.25
A47: =INT((45-1)/12)+1 -> 4 | B47: =MOD(45-1,12)+1 -> 9 | C47: =Dashboard!$C26 -> 0 | D47: =Dashboard!$C26-F$46*(Dashboard!$C10/12) -> -3013.8515 | E47: =F$46*(Dashboard!$C10/12) -> 3013.8515 | F47: =MAX(F$46-(Dashboard!$C26-F$46*(Dashboard!$C10/12)),0) -> 519674.1 | G47: =G$46+F$46*(Dashboard!$C10/12) -> 119674.1 | H47: =H$46+Dashboard!$C26-F$46*(Dashboard!$C10/12) -> -119674.1
A48: =INT((46-1)/12)+1 -> 4 | B48: =MOD(46-1,12)+1 -> 10 | C48: =Dashboard!$C26 -> 0 | D48: =Dashboard!$C26-F$47*(Dashboard!$C10/12) -> -3031.4323 | E48: =F$47*(Dashboard!$C10/12) -> 3031.4323 | F48: =MAX(F$47-(Dashboard!$C26-F$47*(Dashboard!$C10/12)),0) -> 522705.53 | G48: =G$47+F$47*(Dashboard!$C10/12) -> 122705.53 | H48: =H$47+Dashboard!$C26-F$47*(Dashboard!$C10/12) -> -122705.53
A49: =INT((47-1)/12)+1 -> 4 | B49: =MOD(47-1,12)+1 -> 11 | C49: =Dashboard!$C26 -> 0 | D49: =Dashboard!$C26-F$48*(Dashboard!$C10/12) -> -3049.1156 | E49: =F$48*(Dashboard!$C10/12) -> 3049.1156 | F49: =MAX(F$48-(Dashboard!$C26-F$48*(Dashboard!$C10/12)),0) -> 525754.65 | G49: =G$48+F$48*(Dashboard!$C10/12) -> 125754.65 | H49: =H$48+Dashboard!$C26-F$48*(Dashboard!$C10/12) -> -125754.65
A50: =INT((48-1)/12)+1 -> 4 | B50: =MOD(48-1,12)+1 -> 12 | C50: =Dashboard!$C26 -> 0 | D50: =Dashboard!$C26-F$49*(Dashboard!$C10/12) -> -3066.9021 | E50: =F$49*(Dashboard!$C10/12) -> 3066.9021 | F50: =MAX(F$49-(Dashboard!$C26-F$49*(Dashboard!$C10/12)),0) -> 528821.55 | G50: =G$49+F$49*(Dashboard!$C10/12) -> 128821.55 | H50: =H$49+Dashboard!$C26-F$49*(Dashboard!$C10/12) -> -128821.55
A51: =INT((49-1)/12)+1 -> 5 | B51: =MOD(49-1,12)+1 -> 1 | C51: =Dashboard!$C26 -> 0 | D51: =Dashboard!$C26-F$50*(Dashboard!$C10/12) -> -3084.7924 | E51: =F$50*(Dashboard!$C10/12) -> 3084.7924 | F51: =MAX(F$50-(Dashboard!$C26-F$50*(Dashboard!$C10/12)),0) -> 531906.34 | G51: =G$50+F$50*(Dashboard!$C10/12) -> 131906.34 | H51: =H$50+Dashboard!$C26-F$50*(Dashboard!$C10/12) -> -131906.34
A52: =INT((50-1)/12)+1 -> 5 | B52: =MOD(50-1,12)+1 -> 2 | C52: =Dashboard!$C26 -> 0 | D52: =Dashboard!$C26-F$51*(Dashboard!$C10/12) -> -3102.787 | E52: =F$51*(Dashboard!$C10/12) -> 3102.787 | F52: =MAX(F$51-(Dashboard!$C26-F$51*(Dashboard!$C10/12)),0) -> 535009.13 | G52: =G$51+F$51*(Dashboard!$C10/12) -> 135009.13 | H52: =H$51+Dashboard!$C26-F$51*(Dashboard!$C10/12) -> -135009.13
A53: =INT((51-1)/12)+1 -> 5 | B53: =MOD(51-1,12)+1 -> 3 | C53: =Dashboard!$C26 -> 0 | D53: =Dashboard!$C26-F$52*(Dashboard!$C10/12) -> -3120.8866 | E53: =F$52*(Dashboard!$C10/12) -> 3120.8866 | F53: =MAX(F$52-(Dashboard!$C26-F$52*(Dashboard!$C10/12)),0) -> 538130.02 | G53: =G$52+F$52*(Dashboard!$C10/12) -> 138130.02 | H53: =H$52+Dashboard!$C26-F$52*(Dashboard!$C10/12) -> -138130.02
A54: =INT((52-1)/12)+1 -> 5 | B54: =MOD(52-1,12)+1 -> 4 | C54: =Dashboard!$C26 -> 0 | D54: =Dashboard!$C26-F$53*(Dashboard!$C10/12) -> -3139.0918 | E54: =F$53*(Dashboard!$C10/12) -> 3139.0918 | F54: =MAX(F$53-(Dashboard!$C26-F$53*(Dashboard!$C10/12)),0) -> 541269.11 | G54: =G$53+F$53*(Dashboard!$C10/12) -> 141269.11 | H54: =H$53+Dashboard!$C26-F$53*(Dashboard!$C10/12) -> -141269.11
A55: =INT((53-1)/12)+1 -> 5 | B55: =MOD(53-1,12)+1 -> 5 | C55: =Dashboard!$C26 -> 0 | D55: =Dashboard!$C26-F$54*(Dashboard!$C10/12) -> -3157.4031 | E55: =F$54*(Dashboard!$C10/12) -> 3157.4031 | F55: =MAX(F$54-(Dashboard!$C26-F$54*(Dashboard!$C10/12)),0) -> 544426.51 | G55: =G$54+F$54*(Dashboard!$C10/12) -> 144426.51 | H55: =H$54+Dashboard!$C26-F$54*(Dashboard!$C10/12) -> -144426.51
A56: =INT((54-1)/12)+1 -> 5 | B56: =MOD(54-1,12)+1 -> 6 | C56: =Dashboard!$C26 -> 0 | D56: =Dashboard!$C26-F$55*(Dashboard!$C10/12) -> -3175.8213 | E56: =F$55*(Dashboard!$C10/12) -> 3175.8213 | F56: =MAX(F$55-(Dashboard!$C26-F$55*(Dashboard!$C10/12)),0) -> 547602.33 | G56: =G$55+F$55*(Dashboard!$C10/12) -> 147602.33 | H56: =H$55+Dashboard!$C26-F$55*(Dashboard!$C10/12) -> -147602.33
A57: =INT((55-1)/12)+1 -> 5 | B57: =MOD(55-1,12)+1 -> 7 | C57: =Dashboard!$C26 -> 0 | D57: =Dashboard!$C26-F$56*(Dashboard!$C10/12) -> -3194.3469 | E57: =F$56*(Dashboard!$C10/12) -> 3194.3469 | F57: =MAX(F$56-(Dashboard!$C26-F$56*(Dashboard!$C10/12)),0) -> 550796.68 | G57: =G$56+F$56*(Dashboard!$C10/12) -> 150796.68 | H57: =H$56+Dashboard!$C26-F$56*(Dashboard!$C10/12) -> -150796.68
A58: =INT((56-1)/12)+1 -> 5 | B58: =MOD(56-1,12)+1 -> 8 | C58: =Dashboard!$C26 -> 0 | D58: =Dashboard!$C26-F$57*(Dashboard!$C10/12) -> -3212.9806 | E58: =F$57*(Dashboard!$C10/12) -> 3212.9806 | F58: =MAX(F$57-(Dashboard!$C26-F$57*(Dashboard!$C10/12)),0) -> 554009.66 | G58: =G$57+F$57*(Dashboard!$C10/12) -> 154009.66 | H58: =H$57+Dashboard!$C26-F$57*(Dashboard!$C10/12) -> -154009.66
A59: =INT((57-1)/12)+1 -> 5 | B59: =MOD(57-1,12)+1 -> 9 | C59: =Dashboard!$C26 -> 0 | D59: =Dashboard!$C26-F$58*(Dashboard!$C10/12) -> -3231.723 | E59: =F$58*(Dashboard!$C10/12) -> 3231.723 | F59: =MAX(F$58-(Dashboard!$C26-F$58*(Dashboard!$C10/12)),0) -> 557241.38 | G59: =G$58+F$58*(Dashboard!$C10/12) -> 157241.38 | H59: =H$58+Dashboard!$C26-F$58*(Dashboard!$C10/12) -> -157241.38
A60: =INT((58-1)/12)+1 -> 5 | B60: =MOD(58-1,12)+1 -> 10 | C60: =Dashboard!$C26 -> 0 | D60: =Dashboard!$C26-F$59*(Dashboard!$C10/12) -> -3250.5747 | E60: =F$59*(Dashboard!$C10/12) -> 3250.5747 | F60: =MAX(F$59-(Dashboard!$C26-F$59*(Dashboard!$C10/12)),0) -> 560491.96 | G60: =G$59+F$59*(Dashboard!$C10/12) -> 160491.96 | H60: =H$59+Dashboard!$C26-F$59*(Dashboard!$C10/12) -> -160491.96
A61: =INT((59-1)/12)+1 -> 5 | B61: =MOD(59-1,12)+1 -> 11 | C61: =Dashboard!$C26 -> 0 | D61: =Dashboard!$C26-F$60*(Dashboard!$C10/12) -> -3269.5364 | E61: =F$60*(Dashboard!$C10/12) -> 3269.5364 | F61: =MAX(F$60-(Dashboard!$C26-F$60*(Dashboard!$C10/12)),0) -> 563761.5 | G61: =G$60+F$60*(Dashboard!$C10/12) -> 163761.5 | H61: =H$60+Dashboard!$C26-F$60*(Dashboard!$C10/12) -> -163761.5
A62: =INT((60-1)/12)+1 -> 5 | B62: =MOD(60-1,12)+1 -> 12 | C62: =Dashboard!$C26 -> 0 | D62: =Dashboard!$C26-F$61*(Dashboard!$C10/12) -> -3288.6087 | E62: =F$61*(Dashboard!$C10/12) -> 3288.6087 | F62: =MAX(F$61-(Dashboard!$C26-F$61*(Dashboard!$C10/12)),0) -> 567050.1 | G62: =G$61+F$61*(Dashboard!$C10/12) -> 167050.1 | H62: =H$61+Dashboard!$C26-F$61*(Dashboard!$C10/12) -> -167050.1
A63: =INT((61-1)/12)+1 -> 6 | B63: =MOD(61-1,12)+1 -> 1 | C63: =Dashboard!$C26 -> 0 | D63: =Dashboard!$C26-F$62*(Dashboard!$C10/12) -> -3307.7923 | E63: =F$62*(Dashboard!$C10/12) -> 3307.7923 | F63: =MAX(F$62-(Dashboard!$C26-F$62*(Dashboard!$C10/12)),0) -> 570357.9 | G63: =G$62+F$62*(Dashboard!$C10/12) -> 170357.9 | H63: =H$62+Dashboard!$C26-F$62*(Dashboard!$C10/12) -> -170357.9
A64: =INT((62-1)/12)+1 -> 6 | B64: =MOD(62-1,12)+1 -> 2 | C64: =Dashboard!$C26 -> 0 | D64: =Dashboard!$C26-F$63*(Dashboard!$C10/12) -> -3327.0877 | E64: =F$63*(Dashboard!$C10/12) -> 3327.0877 | F64: =MAX(F$63-(Dashboard!$C26-F$63*(Dashboard!$C10/12)),0) -> 573684.98 | G64: =G$63+F$63*(Dashboard!$C10/12) -> 173684.98 | H64: =H$63+Dashboard!$C26-F$63*(Dashboard!$C10/12) -> -173684.98
A65: =INT((63-1)/12)+1 -> 6 | B65: =MOD(63-1,12)+1 -> 3 | C65: =Dashboard!$C26 -> 0 | D65: =Dashboard!$C26-F$64*(Dashboard!$C10/12) -> -3346.4957 | E65: =F$64*(Dashboard!$C10/12) -> 3346.4957 | F65: =MAX(F$64-(Dashboard!$C26-F$64*(Dashboard!$C10/12)),0) -> 577031.48 | G65: =G$64+F$64*(Dashboard!$C10/12) -> 177031.48 | H65: =H$64+Dashboard!$C26-F$64*(Dashboard!$C10/12) -> -177031.48
A66: =INT((64-1)/12)+1 -> 6 | B66: =MOD(64-1,12)+1 -> 4 | C66: =Dashboard!$C26 -> 0 | D66: =Dashboard!$C26-F$65*(Dashboard!$C10/12) -> -3366.017 | E66: =F$65*(Dashboard!$C10/12) -> 3366.017 | F66: =MAX(F$65-(Dashboard!$C26-F$65*(Dashboard!$C10/12)),0) -> 580397.5 | G66: =G$65+F$65*(Dashboard!$C10/12) -> 180397.5 | H66: =H$65+Dashboard!$C26-F$65*(Dashboard!$C10/12) -> -180397.5
A67: =INT((65-1)/12)+1 -> 6 | B67: =MOD(65-1,12)+1 -> 5 | C67: =Dashboard!$C26 -> 0 | D67: =Dashboard!$C26-F$66*(Dashboard!$C10/12) -> -3385.6521 | E67: =F$66*(Dashboard!$C10/12) -> 3385.6521 | F67: =MAX(F$66-(Dashboard!$C26-F$66*(Dashboard!$C10/12)),0) -> 583783.15 | G67: =G$66+F$66*(Dashboard!$C10/12) -> 183783.15 | H67: =H$66+Dashboard!$C26-F$66*(Dashboard!$C10/12) -> -183783.15
A68: =INT((66-1)/12)+1 -> 6 | B68: =MOD(66-1,12)+1 -> 6 | C68: =Dashboard!$C26 -> 0 | D68: =Dashboard!$C26-F$67*(Dashboard!$C10/12) -> -3405.4017 | E68: =F$67*(Dashboard!$C10/12) -> 3405.4017 | F68: =MAX(F$67-(Dashboard!$C26-F$67*(Dashboard!$C10/12)),0) -> 587188.55 | G68: =G$67+F$67*(Dashboard!$C10/12) -> 187188.55 | H68: =H$67+Dashboard!$C26-F$67*(Dashboard!$C10/12) -> -187188.55
A69: =INT((67-1)/12)+1 -> 6 | B69: =MOD(67-1,12)+1 -> 7 | C69: =Dashboard!$C26 -> 0 | D69: =Dashboard!$C26-F$68*(Dashboard!$C10/12) -> -3425.2665 | E69: =F$68*(Dashboard!$C10/12) -> 3425.2665 | F69: =MAX(F$68-(Dashboard!$C26-F$68*(Dashboard!$C10/12)),0) -> 590613.82 | G69: =G$68+F$68*(Dashboard!$C10/12) -> 190613.82 | H69: =H$68+Dashboard!$C26-F$68*(Dashboard!$C10/12) -> -190613.82
A70: =INT((68-1)/12)+1 -> 6 | B70: =MOD(68-1,12)+1 -> 8 | C70: =Dashboard!$C26 -> 0 | D70: =Dashboard!$C26-F$69*(Dashboard!$C10/12) -> -3445.2473 | E70: =F$69*(Dashboard!$C10/12) -> 3445.2473 | F70: =MAX(F$69-(Dashboard!$C26-F$69*(Dashboard!$C10/12)),0) -> 594059.06 | G70: =G$69+F$69*(Dashboard!$C10/12) -> 194059.06 | H70: =H$69+Dashboard!$C26-F$69*(Dashboard!$C10/12) -> -194059.06
A71: =INT((69-1)/12)+1 -> 6 | B71: =MOD(69-1,12)+1 -> 9 | C71: =Dashboard!$C26 -> 0 | D71: =Dashboard!$C26-F$70*(Dashboard!$C10/12) -> -3465.3445 | E71: =F$70*(Dashboard!$C10/12) -> 3465.3445 | F71: =MAX(F$70-(Dashboard!$C26-F$70*(Dashboard!$C10/12)),0) -> 597524.41 | G71: =G$70+F$70*(Dashboard!$C10/12) -> 197524.41 | H71: =H$70+Dashboard!$C26-F$70*(Dashboard!$C10/12) -> -197524.41
A72: =INT((70-1)/12)+1 -> 6 | B72: =MOD(70-1,12)+1 -> 10 | C72: =Dashboard!$C26 -> 0 | D72: =Dashboard!$C26-F$71*(Dashboard!$C10/12) -> -3485.5591 | E72: =F$71*(Dashboard!$C10/12) -> 3485.5591 | F72: =MAX(F$71-(Dashboard!$C26-F$71*(Dashboard!$C10/12)),0) -> 601009.97 | G72: =G$71+F$71*(Dashboard!$C10/12) -> 201009.97 | H72: =H$71+Dashboard!$C26-F$71*(Dashboard!$C10/12) -> -201009.97
A73: =INT((71-1)/12)+1 -> 6 | B73: =MOD(71-1,12)+1 -> 11 | C73: =Dashboard!$C26 -> 0 | D73: =Dashboard!$C26-F$72*(Dashboard!$C10/12) -> -3505.8915 | E73: =F$72*(Dashboard!$C10/12) -> 3505.8915 | F73: =MAX(F$72-(Dashboard!$C26-F$72*(Dashboard!$C10/12)),0) -> 604515.86 | G73: =G$72+F$72*(Dashboard!$C10/12) -> 204515.86 | H73: =H$72+Dashboard!$C26-F$72*(Dashboard!$C10/12) -> -204515.86
A74: =INT((72-1)/12)+1 -> 6 | B74: =MOD(72-1,12)+1 -> 12 | C74: =Dashboard!$C26 -> 0 | D74: =Dashboard!$C26-F$73*(Dashboard!$C10/12) -> -3526.3425 | E74: =F$73*(Dashboard!$C10/12) -> 3526.3425 | F74: =MAX(F$73-(Dashboard!$C26-F$73*(Dashboard!$C10/12)),0) -> 608042.2 | G74: =G$73+F$73*(Dashboard!$C10/12) -> 208042.2 | H74: =H$73+Dashboard!$C26-F$73*(Dashboard!$C10/12) -> -208042.2
A75: =INT((73-1)/12)+1 -> 7 | B75: =MOD(73-1,12)+1 -> 1 | C75: =Dashboard!$C26 -> 0 | D75: =Dashboard!$C26-F$74*(Dashboard!$C10/12) -> -3546.9128 | E75: =F$74*(Dashboard!$C10/12) -> 3546.9128 | F75: =MAX(F$74-(Dashboard!$C26-F$74*(Dashboard!$C10/12)),0) -> 611589.11 | G75: =G$74+F$74*(Dashboard!$C10/12) -> 211589.11 | H75: =H$74+Dashboard!$C26-F$74*(Dashboard!$C10/12) -> -211589.11
A76: =INT((74-1)/12)+1 -> 7 | B76: =MOD(74-1,12)+1 -> 2 | C76: =Dashboard!$C26 -> 0 | D76: =Dashboard!$C26-F$75*(Dashboard!$C10/12) -> -3567.6032 | E76: =F$75*(Dashboard!$C10/12) -> 3567.6032 | F76: =MAX(F$75-(Dashboard!$C26-F$75*(Dashboard!$C10/12)),0) -> 615156.72 | G76: =G$75+F$75*(Dashboard!$C10/12) -> 215156.72 | H76: =H$75+Dashboard!$C26-F$75*(Dashboard!$C10/12) -> -215156.72
A77: =INT((75-1)/12)+1 -> 7 | B77: =MOD(75-1,12)+1 -> 3 | C77: =Dashboard!$C26 -> 0 | D77: =Dashboard!$C26-F$76*(Dashboard!$C10/12) -> -3588.4142 | E77: =F$76*(Dashboard!$C10/12) -> 3588.4142 | F77: =MAX(F$76-(Dashboard!$C26-F$76*(Dashboard!$C10/12)),0) -> 618745.13 | G77: =G$76+F$76*(Dashboard!$C10/12) -> 218745.13 | H77: =H$76+Dashboard!$C26-F$76*(Dashboard!$C10/12) -> -218745.13
A78: =INT((76-1)/12)+1 -> 7 | B78: =MOD(76-1,12)+1 -> 4 | C78: =Dashboard!$C26 -> 0 | D78: =Dashboard!$C26-F$77*(Dashboard!$C10/12) -> -3609.3466 | E78: =F$77*(Dashboard!$C10/12) -> 3609.3466 | F78: =MAX(F$77-(Dashboard!$C26-F$77*(Dashboard!$C10/12)),0) -> 622354.48 | G78: =G$77+F$77*(Dashboard!$C10/12) -> 222354.48 | H78: =H$77+Dashboard!$C26-F$77*(Dashboard!$C10/12) -> -222354.48
A79: =INT((77-1)/12)+1 -> 7 | B79: =MOD(77-1,12)+1 -> 5 | C79: =Dashboard!$C26 -> 0 | D79: =Dashboard!$C26-F$78*(Dashboard!$C10/12) -> -3630.4011 | E79: =F$78*(Dashboard!$C10/12) -> 3630.4011 | F79: =MAX(F$78-(Dashboard!$C26-F$78*(Dashboard!$C10/12)),0) -> 625984.88 | G79: =G$78+F$78*(Dashboard!$C10/12) -> 225984.88 | H79: =H$78+Dashboard!$C26-F$78*(Dashboard!$C10/12) -> -225984.88
A80: =INT((78-1)/12)+1 -> 7 | B80: =MOD(78-1,12)+1 -> 6 | C80: =Dashboard!$C26 -> 0 | D80: =Dashboard!$C26-F$79*(Dashboard!$C10/12) -> -3651.5785 | E80: =F$79*(Dashboard!$C10/12) -> 3651.5785 | F80: =MAX(F$79-(Dashboard!$C26-F$79*(Dashboard!$C10/12)),0) -> 629636.46 | G80: =G$79+F$79*(Dashboard!$C10/12) -> 229636.46 | H80: =H$79+Dashboard!$C26-F$79*(Dashboard!$C10/12) -> -229636.46
A81: =INT((79-1)/12)+1 -> 7 | B81: =MOD(79-1,12)+1 -> 7 | C81: =Dashboard!$C26 -> 0 | D81: =Dashboard!$C26-F$80*(Dashboard!$C10/12) -> -3672.8793 | E81: =F$80*(Dashboard!$C10/12) -> 3672.8793 | F81: =MAX(F$80-(Dashboard!$C26-F$80*(Dashboard!$C10/12)),0) -> 633309.34 | G81: =G$80+F$80*(Dashboard!$C10/12) -> 233309.34 | H81: =H$80+Dashboard!$C26-F$80*(Dashboard!$C10/12) -> -233309.34
A82: =INT((80-1)/12)+1 -> 7 | B82: =MOD(80-1,12)+1 -> 8 | C82: =Dashboard!$C26 -> 0 | D82: =Dashboard!$C26-F$81*(Dashboard!$C10/12) -> -3694.3045 | E82: =F$81*(Dashboard!$C10/12) -> 3694.3045 | F82: =MAX(F$81-(Dashboard!$C26-F$81*(Dashboard!$C10/12)),0) -> 637003.64 | G82: =G$81+F$81*(Dashboard!$C10/12) -> 237003.64 | H82: =H$81+Dashboard!$C26-F$81*(Dashboard!$C10/12) -> -237003.64
A83: =INT((81-1)/12)+1 -> 7 | B83: =MOD(81-1,12)+1 -> 9 | C83: =Dashboard!$C26 -> 0 | D83: =Dashboard!$C26-F$82*(Dashboard!$C10/12) -> -3715.8546 | E83: =F$82*(Dashboard!$C10/12) -> 3715.8546 | F83: =MAX(F$82-(Dashboard!$C26-F$82*(Dashboard!$C10/12)),0) -> 640719.5 | G83: =G$82+F$82*(Dashboard!$C10/12) -> 240719.5 | H83: =H$82+Dashboard!$C26-F$82*(Dashboard!$C10/12) -> -240719.5
A84: =INT((82-1)/12)+1 -> 7 | B84: =MOD(82-1,12)+1 -> 10 | C84: =Dashboard!$C26 -> 0 | D84: =Dashboard!$C26-F$83*(Dashboard!$C10/12) -> -3737.5304 | E84: =F$83*(Dashboard!$C10/12) -> 3737.5304 | F84: =MAX(F$83-(Dashboard!$C26-F$83*(Dashboard!$C10/12)),0) -> 644457.03 | G84: =G$83+F$83*(Dashboard!$C10/12) -> 244457.03 | H84: =H$83+Dashboard!$C26-F$83*(Dashboard!$C10/12) -> -244457.03
A85: =INT((83-1)/12)+1 -> 7 | B85: =MOD(83-1,12)+1 -> 11 | C85: =Dashboard!$C26 -> 0 | D85: =Dashboard!$C26-F$84*(Dashboard!$C10/12) -> -3759.3327 | E85: =F$84*(Dashboard!$C10/12) -> 3759.3327 | F85: =MAX(F$84-(Dashboard!$C26-F$84*(Dashboard!$C10/12)),0) -> 648216.36 | G85: =G$84+F$84*(Dashboard!$C10/12) -> 248216.36 | H85: =H$84+Dashboard!$C26-F$84*(Dashboard!$C10/12) -> -248216.36
A86: =INT((84-1)/12)+1 -> 7 | B86: =MOD(84-1,12)+1 -> 12 | C86: =Dashboard!$C26 -> 0 | D86: =Dashboard!$C26-F$85*(Dashboard!$C10/12) -> -3781.2621 | E86: =F$85*(Dashboard!$C10/12) -> 3781.2621 | F86: =MAX(F$85-(Dashboard!$C26-F$85*(Dashboard!$C10/12)),0) -> 651997.62 | G86: =G$85+F$85*(Dashboard!$C10/12) -> 251997.62 | H86: =H$85+Dashboard!$C26-F$85*(Dashboard!$C10/12) -> -251997.62
A87: =INT((85-1)/12)+1 -> 8 | B87: =MOD(85-1,12)+1 -> 1 | C87: =Dashboard!$C26 -> 0 | D87: =Dashboard!$C26-F$86*(Dashboard!$C10/12) -> -3803.3195 | E87: =F$86*(Dashboard!$C10/12) -> 3803.3195 | F87: =MAX(F$86-(Dashboard!$C26-F$86*(Dashboard!$C10/12)),0) -> 655800.94 | G87: =G$86+F$86*(Dashboard!$C10/12) -> 255800.94 | H87: =H$86+Dashboard!$C26-F$86*(Dashboard!$C10/12) -> -255800.94
A88: =INT((86-1)/12)+1 -> 8 | B88: =MOD(86-1,12)+1 -> 2 | C88: =Dashboard!$C26 -> 0 | D88: =Dashboard!$C26-F$87*(Dashboard!$C10/12) -> -3825.5055 | E88: =F$87*(Dashboard!$C10/12) -> 3825.5055 | F88: =MAX(F$87-(Dashboard!$C26-F$87*(Dashboard!$C10/12)),0) -> 659626.45 | G88: =G$87+F$87*(Dashboard!$C10/12) -> 259626.45 | H88: =H$87+Dashboard!$C26-F$87*(Dashboard!$C10/12) -> -259626.45
A89: =INT((87-1)/12)+1 -> 8 | B89: =MOD(87-1,12)+1 -> 3 | C89: =Dashboard!$C26 -> 0 | D89: =Dashboard!$C26-F$88*(Dashboard!$C10/12) -> -3847.8209 | E89: =F$88*(Dashboard!$C10/12) -> 3847.8209 | F89: =MAX(F$88-(Dashboard!$C26-F$88*(Dashboard!$C10/12)),0) -> 663474.27 | G89: =G$88+F$88*(Dashboard!$C10/12) -> 263474.27 | H89: =H$88+Dashboard!$C26-F$88*(Dashboard!$C10/12) -> -263474.27
A90: =INT((88-1)/12)+1 -> 8 | B90: =MOD(88-1,12)+1 -> 4 | C90: =Dashboard!$C26 -> 0 | D90: =Dashboard!$C26-F$89*(Dashboard!$C10/12) -> -3870.2666 | E90: =F$89*(Dashboard!$C10/12) -> 3870.2666 | F90: =MAX(F$89-(Dashboard!$C26-F$89*(Dashboard!$C10/12)),0) -> 667344.53 | G90: =G$89+F$89*(Dashboard!$C10/12) -> 267344.53 | H90: =H$89+Dashboard!$C26-F$89*(Dashboard!$C10/12) -> -267344.53
A91: =INT((89-1)/12)+1 -> 8 | B91: =MOD(89-1,12)+1 -> 5 | C91: =Dashboard!$C26 -> 0 | D91: =Dashboard!$C26-F$90*(Dashboard!$C10/12) -> -3892.8431 | E91: =F$90*(Dashboard!$C10/12) -> 3892.8431 | F91: =MAX(F$90-(Dashboard!$C26-F$90*(Dashboard!$C10/12)),0) -> 671237.38 | G91: =G$90+F$90*(Dashboard!$C10/12) -> 271237.38 | H91: =H$90+Dashboard!$C26-F$90*(Dashboard!$C10/12) -> -271237.38
A92: =INT((90-1)/12)+1 -> 8 | B92: =MOD(90-1,12)+1 -> 6 | C92: =Dashboard!$C26 -> 0 | D92: =Dashboard!$C26-F$91*(Dashboard!$C10/12) -> -3915.5514 | E92: =F$91*(Dashboard!$C10/12) -> 3915.5514 | F92: =MAX(F$91-(Dashboard!$C26-F$91*(Dashboard!$C10/12)),0) -> 675152.93 | G92: =G$91+F$91*(Dashboard!$C10/12) -> 275152.93 | H92: =H$91+Dashboard!$C26-F$91*(Dashboard!$C10/12) -> -275152.93
A93: =INT((91-1)/12)+1 -> 8 | B93: =MOD(91-1,12)+1 -> 7 | C93: =Dashboard!$C26 -> 0 | D93: =Dashboard!$C26-F$92*(Dashboard!$C10/12) -> -3938.3921 | E93: =F$92*(Dashboard!$C10/12) -> 3938.3921 | F93: =MAX(F$92-(Dashboard!$C26-F$92*(Dashboard!$C10/12)),0) -> 679091.32 | G93: =G$92+F$92*(Dashboard!$C10/12) -> 279091.32 | H93: =H$92+Dashboard!$C26-F$92*(Dashboard!$C10/12) -> -279091.32
A94: =INT((92-1)/12)+1 -> 8 | B94: =MOD(92-1,12)+1 -> 8 | C94: =Dashboard!$C26 -> 0 | D94: =Dashboard!$C26-F$93*(Dashboard!$C10/12) -> -3961.366 | E94: =F$93*(Dashboard!$C10/12) -> 3961.366 | F94: =MAX(F$93-(Dashboard!$C26-F$93*(Dashboard!$C10/12)),0) -> 683052.69 | G94: =G$93+F$93*(Dashboard!$C10/12) -> 283052.69 | H94: =H$93+Dashboard!$C26-F$93*(Dashboard!$C10/12) -> -283052.69
A95: =INT((93-1)/12)+1 -> 8 | B95: =MOD(93-1,12)+1 -> 9 | C95: =Dashboard!$C26 -> 0 | D95: =Dashboard!$C26-F$94*(Dashboard!$C10/12) -> -3984.474 | E95: =F$94*(Dashboard!$C10/12) -> 3984.474 | F95: =MAX(F$94-(Dashboard!$C26-F$94*(Dashboard!$C10/12)),0) -> 687037.16 | G95: =G$94+F$94*(Dashboard!$C10/12) -> 287037.16 | H95: =H$94+Dashboard!$C26-F$94*(Dashboard!$C10/12) -> -287037.16
A96: =INT((94-1)/12)+1 -> 8 | B96: =MOD(94-1,12)+1 -> 10 | C96: =Dashboard!$C26 -> 0 | D96: =Dashboard!$C26-F$95*(Dashboard!$C10/12) -> -4007.7168 | E96: =F$95*(Dashboard!$C10/12) -> 4007.7168 | F96: =MAX(F$95-(Dashboard!$C26-F$95*(Dashboard!$C10/12)),0) -> 691044.88 | G96: =G$95+F$95*(Dashboard!$C10/12) -> 291044.88 | H96: =H$95+Dashboard!$C26-F$95*(Dashboard!$C10/12) -> -291044.88
A97: =INT((95-1)/12)+1 -> 8 | B97: =MOD(95-1,12)+1 -> 11 | C97: =Dashboard!$C26 -> 0 | D97: =Dashboard!$C26-F$96*(Dashboard!$C10/12) -> -4031.0951 | E97: =F$96*(Dashboard!$C10/12) -> 4031.0951 | F97: =MAX(F$96-(Dashboard!$C26-F$96*(Dashboard!$C10/12)),0) -> 695075.97 | G97: =G$96+F$96*(Dashboard!$C10/12) -> 295075.97 | H97: =H$96+Dashboard!$C26-F$96*(Dashboard!$C10/12) -> -295075.97
A98: =INT((96-1)/12)+1 -> 8 | B98: =MOD(96-1,12)+1 -> 12 | C98: =Dashboard!$C26 -> 0 | D98: =Dashboard!$C26-F$97*(Dashboard!$C10/12) -> -4054.6098 | E98: =F$97*(Dashboard!$C10/12) -> 4054.6098 | F98: =MAX(F$97-(Dashboard!$C26-F$97*(Dashboard!$C10/12)),0) -> 699130.58 | G98: =G$97+F$97*(Dashboard!$C10/12) -> 299130.58 | H98: =H$97+Dashboard!$C26-F$97*(Dashboard!$C10/12) -> -299130.58
A99: =INT((97-1)/12)+1 -> 9 | B99: =MOD(97-1,12)+1 -> 1 | C99: =Dashboard!$C26 -> 0 | D99: =Dashboard!$C26-F$98*(Dashboard!$C10/12) -> -4078.2617 | E99: =F$98*(Dashboard!$C10/12) -> 4078.2617 | F99: =MAX(F$98-(Dashboard!$C26-F$98*(Dashboard!$C10/12)),0) -> 703208.84 | G99: =G$98+F$98*(Dashboard!$C10/12) -> 303208.84 | H99: =H$98+Dashboard!$C26-F$98*(Dashboard!$C10/12) -> -303208.84
A100: =INT((98-1)/12)+1 -> 9 | B100: =MOD(98-1,12)+1 -> 2 | C100: =Dashboard!$C26 -> 0 | D100: =Dashboard!$C26-F$99*(Dashboard!$C10/12) -> -4102.0516 | E100: =F$99*(Dashboard!$C10/12) -> 4102.0516 | F100: =MAX(F$99-(Dashboard!$C26-F$99*(Dashboard!$C10/12)),0) -> 707310.9 | G100: =G$99+F$99*(Dashboard!$C10/12) -> 307310.9 | H100: =H$99+Dashboard!$C26-F$99*(Dashboard!$C10/12) -> -307310.9
...
