Workbook

Sheet Start Here
A1: Money Models: a workbook for $100M Money Models
A2: Get paid back before the bill is due. A money model is the order in which you ask a customer to say yes; this workbook walks you through building one.
A4: How to use it
A5: 1. Six planet sheets, one per part of the model. Each has fifteen levels in five bands: Learn (read, answer one question), Numbers (type your figures), Build (the exercises), Prove (what happened when you ran it), Optimize (sharpen it).
A6: 2. Type only in the yellow cells. Blue text is yours; black text is a formula; leave formulas alone.
A7: 3. Every figure on the Dashboard is live. It reads "not yet" until every number it needs is in, so nothing is ever a fake zero.
A8: 4. Plays says which of the nineteen plays your numbers support. Your Model reads the four offers back to you in order.
A9: 5. Do the planets in order, or start where the constraint points: Foundations level 8 tells you.
A11: Use the example numbers? | B11: Yes | C11: Yes: every sheet runs on a made-up six-week fitness challenge, so you can see the whole thing working. No: your own answers, and nothing else.
A13: Legend
A14: Type here | B14: A yellow cell with blue text is yours to fill. Blank means "not known yet"; a typed 0 is a real zero.
A15: Computed | B15: Black text is a formula. Green text is a figure read from another sheet.
A16: not yet | B16: A figure that is still missing an input. The Dashboard says which; the planet sheet says where to type it.
A17: Example | B17: The grey column on every planet sheet: invented numbers for a made-up business, never real ones.
A19: Where you are: levels done, by planet and band (3 of 3 clears a band)
A20: Planet | B20: 1 Learn | C20: 2 Numbers | D20: 3 Build | E20: 4 Prove | F20: 5 Optimize | G20: Done | H20: Sheet
A21: Foundations | B21: =COUNTIFS('1 Foundations'!$H:$H,"Done",'1 Foundations'!$B:$B,"Learn") -> 3 | C21: =COUNTIFS('1 Foundations'!$H:$H,"Done",'1 Foundations'!$B:$B,"Numbers") -> 3 | D21: =COUNTIFS('1 Foundations'!$H:$H,"Done",'1 Foundations'!$B:$B,"Build") -> 3 | E21: =COUNTIFS('1 Foundations'!$H:$H,"Done",'1 Foundations'!$B:$B,"Prove") -> 3 | F21: =COUNTIFS('1 Foundations'!$H:$H,"Done",'1 Foundations'!$B:$B,"Optimize") -> 3 | G21: =COUNTIF('1 Foundations'!$H:$H,"Done")&" of 15" -> 15 of 15 | H21: =HYPERLINK("#'1 Foundations'!A1","Open 1 Foundations") -> Open 1 Foundations
A22: Attraction | B22: =COUNTIFS('2 Attraction'!$H:$H,"Done",'2 Attraction'!$B:$B,"Learn") -> 3 | C22: =COUNTIFS('2 Attraction'!$H:$H,"Done",'2 Attraction'!$B:$B,"Numbers") -> 3 | D22: =COUNTIFS('2 Attraction'!$H:$H,"Done",'2 Attraction'!$B:$B,"Build") -> 3 | E22: =COUNTIFS('2 Attraction'!$H:$H,"Done",'2 Attraction'!$B:$B,"Prove") -> 3 | F22: =COUNTIFS('2 Attraction'!$H:$H,"Done",'2 Attraction'!$B:$B,"Optimize") -> 3 | G22: =COUNTIF('2 Attraction'!$H:$H,"Done")&" of 15" -> 15 of 15 | H22: =HYPERLINK("#'2 Attraction'!A1","Open 2 Attraction") -> Open 2 Attraction
A23: Upsell | B23: =COUNTIFS('3 Upsell'!$H:$H,"Done",'3 Upsell'!$B:$B,"Learn") -> 3 | C23: =COUNTIFS('3 Upsell'!$H:$H,"Done",'3 Upsell'!$B:$B,"Numbers") -> 3 | D23: =COUNTIFS('3 Upsell'!$H:$H,"Done",'3 Upsell'!$B:$B,"Build") -> 3 | E23: =COUNTIFS('3 Upsell'!$H:$H,"Done",'3 Upsell'!$B:$B,"Prove") -> 3 | F23: =COUNTIFS('3 Upsell'!$H:$H,"Done",'3 Upsell'!$B:$B,"Optimize") -> 3 | G23: =COUNTIF('3 Upsell'!$H:$H,"Done")&" of 15" -> 15 of 15 | H23: =HYPERLINK("#'3 Upsell'!A1","Open 3 Upsell") -> Open 3 Upsell
A24: Downsell | B24: =COUNTIFS('4 Downsell'!$H:$H,"Done",'4 Downsell'!$B:$B,"Learn") -> 3 | C24: =COUNTIFS('4 Downsell'!$H:$H,"Done",'4 Downsell'!$B:$B,"Numbers") -> 3 | D24: =COUNTIFS('4 Downsell'!$H:$H,"Done",'4 Downsell'!$B:$B,"Build") -> 3 | E24: =COUNTIFS('4 Downsell'!$H:$H,"Done",'4 Downsell'!$B:$B,"Prove") -> 3 | F24: =COUNTIFS('4 Downsell'!$H:$H,"Done",'4 Downsell'!$B:$B,"Optimize") -> 3 | G24: =COUNTIF('4 Downsell'!$H:$H,"Done")&" of 15" -> 15 of 15 | H24: =HYPERLINK("#'4 Downsell'!A1","Open 4 Downsell") -> Open 4 Downsell
A25: Continuity | B25: =COUNTIFS('5 Continuity'!$H:$H,"Done",'5 Continuity'!$B:$B,"Learn") -> 3 | C25: =COUNTIFS('5 Continuity'!$H:$H,"Done",'5 Continuity'!$B:$B,"Numbers") -> 3 | D25: =COUNTIFS('5 Continuity'!$H:$H,"Done",'5 Continuity'!$B:$B,"Build") -> 3 | E25: =COUNTIFS('5 Continuity'!$H:$H,"Done",'5 Continuity'!$B:$B,"Prove") -> 3 | F25: =COUNTIFS('5 Continuity'!$H:$H,"Done",'5 Continuity'!$B:$B,"Optimize") -> 3 | G25: =COUNTIF('5 Continuity'!$H:$H,"Done")&" of 15" -> 15 of 15 | H25: =HYPERLINK("#'5 Continuity'!A1","Open 5 Continuity") -> Open 5 Continuity
A26: KPIs and Scale | B26: =COUNTIFS('6 KPIs and Scale'!$H:$H,"Done",'6 KPIs and Scale'!$B:$B,"Learn") -> 3 | C26: =COUNTIFS('6 KPIs and Scale'!$H:$H,"Done",'6 KPIs and Scale'!$B:$B,"Numbers") -> 3 | D26: =COUNTIFS('6 KPIs and Scale'!$H:$H,"Done",'6 KPIs and Scale'!$B:$B,"Build") -> 3 | E26: =COUNTIFS('6 KPIs and Scale'!$H:$H,"Done",'6 KPIs and Scale'!$B:$B,"Prove") -> 3 | F26: =COUNTIFS('6 KPIs and Scale'!$H:$H,"Done",'6 KPIs and Scale'!$B:$B,"Optimize") -> 3 | G26: =COUNTIF('6 KPIs and Scale'!$H:$H,"Done")&" of 15" -> 15 of 15 | H26: =HYPERLINK("#'6 KPIs and Scale'!A1","Open 6 KPIs and Scale") -> Open 6 KPIs and Scale
A28: The sun: 30-day ratio | B28: =IF(ISNUMBER(ratio30),ratio30,"not yet") -> 4.7693333 | C28: =IF(ISNUMBER(ratio30),IF(ratio30>=2,"Every customer pays for the next one.",IF(ratio30>=1,"Break even inside the month. Twice the cost is the self-funding line.","Not yet paying back inside 30 days.")),"Needs the Numbers band on Foundations, Attraction, Upsell, Downsell and Continuity.") -> Every customer pays for the next one.
A29: LTGP to CAC | B29: =IF(ISNUMBER(ltgpCac),ltgpCac,"not yet") -> 9.7833333 | C29: How many times over a customer pays for themselves. The book wants at least 3.
A31: About this workbook
A32: Every lesson is a paraphrase in this workbook's own words, never the book's text; the play names are plain-word labels for the book's offer types. Read the book for the reasoning and the stories.
A33: Thresholds (pay a customer back inside 30 days, twice over to self-fund, lifetime gross profit at least three times the cost of a customer) are the book's rules of thumb, not measured findings. Your own numbers decide.
A34: Not financial or business advice. The example numbers are invented. Built from the same tables as the Money Models app in the Personalfinance repository (moneymodels/).

Sheet 1 Foundations
A1: Planet 1 of 6: Foundations
A2: What a money model is, what it costs you to get a customer today, and the one rule the whole book rests on.
A3: Type in the yellow cells (column D). Column F shows the number in use: yours, or the example while the switch on Start Here says Yes.
A4: Level | B4: Band | C4: Title, lesson, questions and boxes | D4: Your answer | E4: Example | F4: In use | G4: Help | H4: Done?
A5: 1 | B5: Learn | C5: What a money model is | G5: About 2 minutes. Read the idea, then answer one check question. | H5: =IF(F7="","",IF(F7="A sequence of offers: the first yes; a bigger yes; a smaller yes after a no; and a repeating yes","Done","Not yet")) -> Done
C6: A money model is a deliberate sequence of offers. Not one product with a price on it: the order in which you ask a customer to say yes, what you ask for each time, and what you do when they say no. The point of the sequence is cash timing. A business that makes plenty of profit over two years can still die in month two, because the money to get the next customer is not back in the bank yet. So the question the whole book asks is: how do you get a customer to pay you more, sooner, than it costs you to get and serve them?
C7: Which of these is a money model? | E7: A sequence of offers: the first yes; a bigger yes; a smaller yes after a no; and a repeating yes | F7: =IF(useExample="Yes",E7,D7) -> A sequence of offers: the first yes; a bigger yes; a smaller yes after a no; and a repeating yes | G7: =IF(F7="","",IF(F7="A sequence of offers: the first yes; a bigger yes; a smaller yes after a no; and a repeating yes","Right. One price is one offer. A money model is the order of offers around it and what each one is for.","Not quite. One price is one offer. A money model is the order of offers around it and what each one is for.")) -> Right. One price is one offer. A money model is the order of offers around it and what each one is for.
C8: Choices: A product with a good price / A sequence of offers: the first yes, a bigger yes, a smaller yes after a no, and a repeating yes / A marketing budget
A10: 2 | B10: Learn | C10: The cash constraint and the 30-day rule | G10: About 2 minutes. Read the idea, then answer one check question. | H10: =IF(F12="","",IF(F12="At least $150; and ideally $300 or more","Done","Not yet")) -> Done
C11: Every customer costs money to get (ads, time, commissions) and money to serve. If that cash comes back in a year, you can only afford as many customers as your savings allow. Growth is capped by your bank balance, not by demand. The rule of thumb the book builds on: get back at least what a customer cost you within 30 days. Get back twice that and every customer pays for the next one. Then growth is funded by customers, not by you or a lender. Thirty days is not magic. It is roughly how long a card bill or an ad invoice gives you before the money is due.
C12: A customer costs $150 to get. What does the model want back from them inside 30 days? | E12: At least $150; and ideally $300 or more | F12: =IF(useExample="Yes",E12,D12) -> At least $150; and ideally $300 or more | G12: =IF(F12="","",IF(F12="At least $150; and ideally $300 or more","Right. Break-even inside 30 days keeps you alive. Twice the cost lets the next customer be bought with this one's money.","Not quite. Break-even inside 30 days keeps you alive. Twice the cost lets the next customer be bought with this one's money.")) -> Right. Break-even inside 30 days keeps you alive. Twice the cost lets the next customer be bought with this one's money.
C13: Choices: At least $150, and ideally $300 or more / Whatever they pay over their lifetime / Nothing, as long as the business is profitable by year end
A15: 3 | B15: Learn | C15: The four kinds of offer | G15: About 2 minutes. Read the idea, then answer one check question. | H15: =IF(F17="","",IF(F17="A downsell: the same promise in a lighter or easier form","Done","Not yet")) -> Done
C16: Attraction offers get the first yes from a stranger. Their job is to bring people in cheaply, not to make the money. Upsell offers ask for a bigger yes right after the first one, when trust is highest. This is where the model earns. Downsell offers turn a no into a smaller yes: same promise, lighter package or easier terms. Continuity offers get the customer to keep paying: a membership, a subscription, a retainer. This is what makes the lifetime value large. Each of the next four planets takes one of these. Do them in order: a great upsell with no one to offer it to is worth nothing.
C17: A customer says no to the bigger package. Which offer comes next? | E17: A downsell: the same promise in a lighter or easier form | F17: =IF(useExample="Yes",E17,D17) -> A downsell: the same promise in a lighter or easier form | G17: =IF(F17="","",IF(F17="A downsell: the same promise in a lighter or easier form","Right. A no to the price or the size is not a no to the result. The downsell keeps the customer and some of the cash.","Not quite. A no to the price or the size is not a no to the result. The downsell keeps the customer and some of the cash.")) -> Right. A no to the price or the size is not a no to the result. The downsell keeps the customer and some of the cash.
C18: Choices: Another attraction offer / A downsell: the same promise in a lighter or easier form / Nothing, the sale is over
A20: 4 | B20: Numbers | C20: What your main offer sells for today | G20: About 1 minute. Type your figures for this part of the model. | H20: =IF(F22<>"","Done","") -> Done
C21: Start with the business as it is. One product or service, the one most customers buy first. Its price, before any discount.
C22: Price of your main offer today | E22: 199 | F22: =IF(useExample="Yes",E22,IF(D22="","",D22)) -> 199 | G22: Dollars. What one customer pays for it. If it is monthly, use one month here; the model will handle the repeat part on the Continuity planet.
A24: 5 | B24: Numbers | C24: What it costs you to deliver one | G24: About 3 minutes. Type your figures for this part of the model. | H24: =IF(F26<>"","Done","") -> Done
C25: Everything you spend to serve one customer for that offer: materials, shipping, contractor hours, software seats, the hours you pay someone for. Not rent, not ads. If you deliver it yourself, count your hours at what you would pay someone else.
C26: Cost to deliver one sale | E26: 60 | F26: =IF(useExample="Yes",E26,IF(D26="","",D26)) -> 60 | G26: Dollars. Only the costs that happen because this one customer bought. Type 0 if there truly are none (a digital file, say).
A28: 6 | B28: Numbers | C28: What a customer costs you to get | G28: About 4 minutes. Type your figures for this part of the model. | H28: =IF(AND(F30<>"",F31<>""),"Done",IF(OR(F30<>"",F31<>""),"Part","")) -> Done
C29: The cost of a customer is everything you spent to get customers in a month, divided by the customers you got. Ads, the person who runs them, referral fees, the free sessions you gave away. Last month is fine. A rough month is better than nothing; you will replace it on the Prove band.
C30: Spent on getting customers last month | E30: 6000 | F30: =IF(useExample="Yes",E30,IF(D30="","",D30)) -> 6000 | G30: Dollars. Ads, agency, commissions, giveaways, the salary of whoever does the marketing.
C31: New customers last month | E31: 40 | F31: =IF(useExample="Yes",E31,IF(D31="","",D31)) -> 40 | G31: People who paid for the first time. Not leads, not sign-ups.
A33: 7 | B33: Build | C33: Exercise: the promise in one line | G33: About 6 minutes. The exercises: pick a play, write the offer, tick the design list. | H33: =IF(AND(F35<>"",F36<>""),"Done",IF(OR(F35<>"",F36<>""),"Part","")) -> Done
C34: Every offer in the model points at the same result. Write it the way the customer would say it, not the way your industry does. 'Lose the first ten pounds in six weeks' beats 'a holistic fitness programme'. This line is reused on every planet: the attraction offer promises it, the upsell gets it faster, the downsell gets it lighter, continuity keeps it.
C35: Who the customer is, in a few words | E35: Busy parents who stopped exercising | F35: =IF(useExample="Yes",E35,IF(D35="","",D35)) -> Busy parents who stopped exercising | G35: One kind of person. 'Busy parents who stopped exercising' is a customer; 'anyone' is not.
C36: The result they want, in their words | E36: Lose the first ten pounds in six weeks | F36: =IF(useExample="Yes",E36,IF(D36="","",D36)) -> Lose the first ten pounds in six weeks | G36: A result with a size and a time if you can: what, how much, by when.
A38: 8 | B38: Build | C38: Exercise: name the constraint | G38: About 2 minutes. The exercises: pick a play, write the offer, tick the design list. | H38: =IF(F40<>"","Done","") -> Done
C39: A business is held back by one thing at a time. Pick the one that is true right now. The model's planets map onto it: not enough customers is an attraction problem; not enough per customer is upsell and downsell; they do not stay is continuity; it costs too much to serve is a margin problem to fix before any of them.
C40: What is holding the business back right now? | E40: Each customer does not pay enough | F40: =IF(useExample="Yes",E40,IF(D40="","",D40)) -> Each customer does not pay enough | G40: Pick one: Not enough customers / Each customer does not pay enough / They do not stay or come back / It costs too much to serve them
A42: 9 | B42: Build | C42: Exercise: map today's sequence | G42: About 5 minutes. The exercises: pick a play, write the offer, tick the design list. | H42: =IF(AND(F44<>"",F45<>"",F46<>"",F47<>""),"Done",IF(OR(F44<>"",F45<>"",F46<>"",F47<>""),"Part","")) -> Done
C43: Write down what a customer is actually offered today, in the order it happens. Most businesses find they have one offer and then silence. That silence is the money model you are about to build.
C44: The first thing a stranger is offered | E44: A $199 six-week class pass | F44: =IF(useExample="Yes",E44,IF(D44="","",D44)) -> A $199 six-week class pass | G44: The ad, the free consult, the intro price. Whatever comes first.
C45: What they are offered after buying | E45: Nothing | F45: =IF(useExample="Yes",E45,IF(D45="","",D45)) -> Nothing | G45: Type 'nothing' if nothing. That is an honest and common answer.
C46: What happens when they say no | E46: Nothing | F46: =IF(useExample="Yes",E46,IF(D46="","",D46)) -> Nothing | G46: A follow-up? A cheaper option? Nothing?
C47: What they pay for on an ongoing basis | E47: Nothing | F47: =IF(useExample="Yes",E47,IF(D47="","",D47)) -> Nothing | G47: A membership, a retainer, refills, or 'nothing'.
A49: 10 | B49: Prove | C49: How long cash takes to come back today | G49: About 3 minutes. Run it for real and type what happened. | H49: =IF(F51<>"","Done","") -> Done
C50: From the day you spend the first dollar on getting a customer to the day their money is in your account. Count the sales cycle, the free trial, the invoice terms. This is the number the model shortens.
C51: Days from first ad dollar to first cash collected | E51: 21 | F51: =IF(useExample="Yes",E51,IF(D51="","",D51)) -> 21 | G51: Days. Typical, not best case. If you invoice on 30-day terms after a two-week trial, that is about 45.
A53: 11 | B53: Prove | C53: Cash per customer in their first 30 days, today | G53: About 6 minutes. Run it for real and type what happened. | H53: =IF(F55<>"","Done","") -> Done
C54: Take last month's new customers and add up everything they paid you in their first 30 days. Divide by how many there were. This is the before picture; the model page shows the after beside it.
C55: Cash collected per new customer in their first 30 days | E55: 199 | F55: =IF(useExample="Yes",E55,IF(D55="","",D55)) -> 199 | G55: Dollars. Collected, not invoiced. A payment plan counts only the payments that landed inside 30 days.
A57: 12 | B57: Prove | C57: Checklist: the numbers audit | G57: About 10 minutes. Run it for real and type what happened. | H57: =IF(COUNTIF(F59:F63,"Yes")=5,"Done",IF(COUNTIF(F59:F63,"Yes")>0,"Part","")) -> Done
C58: Before building anything new, make sure the four foundation figures are real rather than remembered. Tick each once it comes from a statement, a report or a count, not a guess.
C59: Marketing spend is tracked by channel, month by month | E59: Yes | F59: =IF(useExample="Yes",E59,D59) -> Yes | G59: Yes when it is true
C60: New customers are counted with where they came from | E60: Yes | F60: =IF(useExample="Yes",E60,D60) -> Yes | G60: Yes when it is true
C61: The cost to deliver one sale comes from real invoices or hours | E61: Yes | F61: =IF(useExample="Yes",E61,D61) -> Yes | G61: Yes when it is true
C62: The 30-day cash per customer was counted from actual payments | E62: Yes | F62: =IF(useExample="Yes",E62,D62) -> Yes | G62: Yes when it is true
C63: The constraint is written down where the team can see it | E63: Yes | F63: =IF(useExample="Yes",E63,D63) -> Yes | G63: Yes when it is true
A65: 13 | B65: Optimize | C65: Your hours per customer | G65: About 3 minutes. Stack a second play and sharpen the numbers. | H65: =IF(F67<>"","Done","") -> Done
C66: The cost to deliver (level 5) priced your time at what you would pay someone else. This asks for the hours themselves: everything you personally spend on one customer in their first month, selling and serving. The model turns it into gross profit per hour of your time, which is the number that says whether to raise the price, cut delivery, or hire.
C67: Hours of your own time per customer, first month | E67: 6 | F67: =IF(useExample="Yes",E67,IF(D67="","",D67)) -> 6 | G67: Selling, onboarding, delivering, chasing. A rough count is fine.
A69: 14 | B69: Optimize | C69: Exercise: the play you run first | G69: About 1 minute. Stack a second play and sharpen the numbers. | H69: =IF(F71<>"","Done","") -> Done
C70: The constraint you named on level 8 says which planet to build first. Pick it here so the next-up card points at it. You can change your mind later; you cannot build four things at once.
C71: Which part of the model do you build first? | E71: Upsell: earn more from each one | F71: =IF(useExample="Yes",E71,IF(D71="","",D71)) -> Upsell: earn more from each one | G71: Pick one: Attraction: bring more people in / Upsell: earn more from each one / Downsell: lose fewer at the no / Continuity: keep them paying
A73: 15 | B73: Optimize | C73: Checklist: the weekly rhythm | G73: About 5 minutes. Stack a second play and sharpen the numbers. | H73: =IF(COUNTIF(F75:F78,"Yes")=4,"Done",IF(COUNTIF(F75:F78,"Yes")>0,"Part","")) -> Done
C74: The model is not a launch, it is a habit. Once a week, four numbers and one change.
C75: Cost of a customer refreshed for last week | E75: Yes | F75: =IF(useExample="Yes",E75,D75) -> Yes | G75: Yes when it is true
C76: 30-day cash per customer refreshed | E76: Yes | F76: =IF(useExample="Yes",E76,D76) -> Yes | G76: Yes when it is true
C77: The 30-day ratio compared with the two thresholds | E77: Yes | F77: =IF(useExample="Yes",E77,D77) -> Yes | G77: Yes when it is true
C78: One change chosen for next week, and only one | E78: Yes | F78: =IF(useExample="Yes",E78,D78) -> Yes | G78: Yes when it is true

Sheet 2 Attraction
A1: Planet 2 of 6: Attraction
A2: The first yes: the offer that turns a stranger into a customer without draining your cash.
A3: Type in the yellow cells (column D). Column F shows the number in use: yours, or the example while the switch on Start Here says Yes.
A4: Level | B4: Band | C4: Title, lesson, questions and boxes | D4: Your answer | E4: Example | F4: In use | G4: Help | H4: Done?
A5: 1 | B5: Learn | C5: What an attraction offer is for | G5: About 2 minutes. Read the idea, then answer one check question. | H5: =IF(F7="","",IF(F7="Good: the customer cost nothing net; and the upsell and continuity are still to come","Done","Not yet")) -> Done
C6: The attraction offer's job is to turn a stranger into a customer. It is the door, not the room. If it makes a profit on its own, wonderful; if it only covers the cost of getting the customer, that is still a win, because the upsell and continuity are waiting behind it. The mistake is to make the attraction offer the whole business: then every customer must be profitable on day one, and the price has to be high, and fewer people walk through the door. A good attraction offer is easy to say yes to, makes the promise from Foundations level 7 in a small, fast form, and naturally leads to the next offer.
C7: The attraction offer breaks even after covering the cost of the customer. Good or bad? | E7: Good: the customer cost nothing net; and the upsell and continuity are still to come | F7: =IF(useExample="Yes",E7,D7) -> Good: the customer cost nothing net; and the upsell and continuity are still to come | G7: =IF(F7="","",IF(F7="Good: the customer cost nothing net; and the upsell and continuity are still to come","Right. A free customer who then sees an upsell and a continuity offer is the whole idea.","Not quite. A free customer who then sees an upsell and a continuity offer is the whole idea.")) -> Right. A free customer who then sees an upsell and a continuity offer is the whole idea.
C8: Choices: Bad: every offer should make a profit / Good: the customer cost nothing net, and the upsell and continuity are still to come / Neither, it depends on the industry
A10: 2 | B10: Learn | C10: The attraction plays | G10: About 3 minutes. Read the idea, then answer one check question. | H10: =IF(F12="","",IF(F12="The few who hit the stated result and followed every rule","Done","Not yet")) -> Done
C11: Win your money back: the customer pays, and gets it back (or as credit) if they hit a defined result and follow the rules. Most will not hit it; the ones who do are the ones you want to keep. Giveaway: one big prize, many entrants, and everyone who did not win gets an offer. Cheap leads at volume. Decoy: a free or very cheap option beside the real one, so the real one looks like the sensible choice, and the free option filters out people who would never pay. Buy some, get some free: bundle volume up front. The free part is margin you would have spent on getting them back anyway. Pay less now or pay more later: two prices for the same thing, a smaller one paid today and a larger one paid on results or over time. Both close; one brings cash forward. Free with strings: free only when the string (a deposit, a booked call, an upsell moment) makes the free customer pay off.
C12: In 'win your money back', who ends up refunded? | E12: The few who hit the stated result and followed every rule | F12: =IF(useExample="Yes",E12,D12) -> The few who hit the stated result and followed every rule | G12: =IF(F12="","",IF(F12="The few who hit the stated result and followed every rule","Right. The condition is real and reachable. The people who reach it are your best customers, and the refund is cheaper than the ad that would have found them.","Not quite. The condition is real and reachable. The people who reach it are your best customers, and the refund is cheaper than the ad that would have found them.")) -> Right. The condition is real and reachable. The people who reach it are your best customers, and the refund is cheaper than the ad that would have found them.
C13: Choices: Everyone who asks / The few who hit the stated result and followed every rule / Nobody, it is a trick
A15: 3 | B15: Learn | C15: The three parts every attraction offer needs | G15: About 2 minutes. Read the idea, then answer one check question. | H15: =IF(F17="","",IF(F17="'50% off everything this month'","Done","Not yet")) -> Done
C16: A clear result with a time on it. Not 'a great experience'; 'ten pounds in six weeks'. A reason it is cheap or free that the customer believes: a challenge, a first-time price, a limited batch, a prize. Cheap with no reason reads as low quality. A string that leads to the next offer: the results call, the check-in, the thing they have to come in for. That is where the upsell lives.
C17: Which attraction offer is missing something? | E17: '50% off everything this month' | F17: =IF(useExample="Yes",E17,D17) -> '50% off everything this month' | G17: =IF(F17="","",IF(F17="'50% off everything this month'","Right. A discount has no result, no reason and no string. The other two have all three.","Not quite. A discount has no result, no reason and no string. The other two have all three.")) -> Right. A discount has no result, no reason and no string. The other two have all three.
C18: Choices: 'Six-week challenge, $500, win it back if you finish all 18 sessions' / '50% off everything this month' / 'Free strategy session, then we build your plan together'
A20: 4 | B20: Numbers | C20: The attraction offer's price | G20: About 1 minute. Type your figures for this part of the model. | H20: =IF(F22<>"","Done","") -> Done
C21: What the stranger pays for the first yes. Type 0 if the plan is free with strings; that is a real answer and the model will treat it as one.
C22: Price of the attraction offer | E22: 500 | F22: =IF(useExample="Yes",E22,IF(D22="","",D22)) -> 500 | G22: Dollars. The cash collected up front, before any refund or credit.
A24: 5 | B24: Numbers | C24: What the attraction offer costs to deliver | G24: About 3 minutes. Type your figures for this part of the model. | H24: =IF(F26<>"","Done","") -> Done
C25: Same idea as Foundations level 5, for this offer. Include the prize if it is a giveaway (prize cost divided by expected entrants) and the expected refunds if it is win-your-money-back (Prove level 11 sharpens that).
C26: Cost to deliver the attraction offer to one customer | E26: 120 | F26: =IF(useExample="Yes",E26,IF(D26="","",D26)) -> 120 | G26: Dollars. Per customer, all in. 0 is allowed.
A28: 6 | B28: Numbers | C28: Leads, and how many of them buy | G28: About 3 minutes. Type your figures for this part of the model. | H28: =IF(AND(F30<>"",F31<>""),"Done",IF(OR(F30<>"",F31<>""),"Part","")) -> Done
C29: A lead is someone who raised a hand: a form, a call, a walk-in. The share who take the attraction offer is the conversion rate. Together with what you spend (Foundations 6) this gives the cost of a lead.
C30: Leads per month | E30: 400 | F30: =IF(useExample="Yes",E30,IF(D30="","",D30)) -> 400 | G30: People who asked, booked or messaged. Last month is fine.
C31: Share of leads who take the attraction offer | E31: 0.1 | F31: =IF(useExample="Yes",E31,IF(D31="","",D31)) -> 0.1 | G31: Type a percent, e.g. 25%. Buyers divided by leads, as a percent.
A33: 7 | B33: Build | C33: Exercise: pick your attraction play | G33: About 2 minutes. The exercises: pick a play, write the offer, tick the design list. | H33: =IF(F35<>"","Done","") -> Done
C34: The Plays page says which of these the numbers already support for you. Pick one. A second one comes on the Optimize band.
C35: Your attraction play | E35: Win your money back | F35: =IF(useExample="Yes",E35,IF(D35="","",D35)) -> Win your money back | G35: Pick one: Win your money back / Giveaway / Decoy / Buy some; get some free / Pay less now or pay more later / Free with strings
A37: 8 | B37: Build | C37: Exercise: write the offer in one sentence | G37: About 8 minutes. The exercises: pick a play, write the offer, tick the design list. | H37: =IF(AND(F39<>"",F40<>""),"Done",IF(OR(F39<>"",F40<>""),"Part","")) -> Done
C38: Use the frame: 'Get [the result] in [the time] for [the price], and [the reason it is cheap or the condition of the reward].' Then add the string: what happens next that leads to the upsell. Say it out loud. If it takes two breaths, it is too long.
C39: The attraction offer, one sentence | E39: Lose ten pounds in six weeks for $500, and win it all back if you finish every session. | F39: =IF(useExample="Yes",E39,IF(D39="","",D39)) -> Lose ten pounds in six weeks for $500, and win it all back if you finish every session. | G39: Result, time, price, reason.
C40: The string: what leads to the next offer | E40: The week-two results check-in with a coach | F40: =IF(useExample="Yes",E40,IF(D40="","",D40)) -> The week-two results check-in with a coach | G40: The results call, the week-two check-in, the pickup, the delivery.
A42: 9 | B42: Build | C42: Checklist: attraction offer design | G42: About 5 minutes. The exercises: pick a play, write the offer, tick the design list. | H42: =IF(COUNTIF(F44:F50,"Yes")=7,"Done",IF(COUNTIF(F44:F50,"Yes")>0,"Part","")) -> Done
C43: Tick what the offer as written has. Anything unticked is the next thing to fix before it goes out.
C44: Names one result with a size and a time | E44: Yes | F44: =IF(useExample="Yes",E44,D44) -> Yes | G44: Yes when it is true
C45: Gives a believable reason it is cheap or free | E45: Yes | F45: =IF(useExample="Yes",E45,D45) -> Yes | G45: Yes when it is true
C46: Has a deadline or a limited number | E46: Yes | F46: =IF(useExample="Yes",E46,D46) -> Yes | G46: Yes when it is true
C47: Has a string that puts the customer in front of the upsell | E47: Yes | F47: =IF(useExample="Yes",E47,D47) -> Yes | G47: Yes when it is true
C48: Any money-back or reward has a measurable, written condition | E48: Yes | F48: =IF(useExample="Yes",E48,D48) -> Yes | G48: Yes when it is true
C49: The price covers the cost to deliver it | E49: Yes | F49: =IF(useExample="Yes",E49,D49) -> Yes | G49: Yes when it is true
C50: You can count who came in through it | E50: Yes | F50: =IF(useExample="Yes",E50,D50) -> Yes | G50: Yes when it is true
A52: 10 | B52: Prove | C52: How many buyers actually show up | G52: About 2 minutes. Run it for real and type what happened. | H52: =IF(F54<>"","Done","") -> Done
C53: A customer who paid and never came in cannot be upsold. Show rate is the share of attraction buyers who consume the thing (attend, open, start). The upsell take rate on the next planet is measured on these people.
C54: Share of attraction buyers who show up or start | E54: 0.85 | F54: =IF(useExample="Yes",E54,IF(D54="","",D54)) -> 0.85 | G54: Type a percent, e.g. 25%. From your first run. 100 if everyone did.
A56: 11 | B56: Prove | C56: What you actually paid back | G56: About 2 minutes. Run it for real and type what happened. | H56: =IF(F58<>"","Done","") -> Done
C57: For win-your-money-back and any guarantee: the share of buyers who got a refund or credit. Type 0 if the play has no refund. This sharpens the attraction offer's real margin.
C58: Share of attraction buyers refunded or credited | E58: 0.12 | F58: =IF(useExample="Yes",E58,IF(D58="","",D58)) -> 0.12 | G58: Type a percent, e.g. 25%. Refunds paid divided by buyers. 0 if none.
A60: 12 | B60: Prove | C60: Checklist: the first test run | G60: About 5 minutes. Run it for real and type what happened. | H60: =IF(COUNTIF(F62:F67,"Yes")=6,"Done",IF(COUNTIF(F62:F67,"Yes")>0,"Part","")) -> Done
C61: One channel, one offer, one week. The point is to count, not to win.
C62: Ran on one channel only, so the count is clean | E62: Yes | F62: =IF(useExample="Yes",E62,D62) -> Yes | G62: Yes when it is true
C63: Ran for a fixed period with a real deadline | E63: Yes | F63: =IF(useExample="Yes",E63,D63) -> Yes | G63: Yes when it is true
C64: Counted leads | E64: Yes | F64: =IF(useExample="Yes",E64,D64) -> Yes | G64: Yes when it is true
C65: Counted buyers | E65: Yes | F65: =IF(useExample="Yes",E65,D65) -> Yes | G65: Yes when it is true
C66: Counted every dollar spent, including time | E66: Yes | F66: =IF(useExample="Yes",E66,D66) -> Yes | G66: Yes when it is true
C67: Wrote down the top three reasons people said no | E67: Yes | F67: =IF(useExample="Yes",E67,D67) -> Yes | G67: Yes when it is true
A69: 13 | B69: Optimize | C69: Exercise: stack a second play | G69: About 2 minutes. Stack a second play and sharpen the numbers. | H69: =IF(F71<>"","Done","") -> Done
C70: Plays combine. A giveaway feeds a decoy (the losers get the cheap option beside the real one). Win-your-money-back stacks on a challenge. Pick the second play that feeds the first.
C71: The second attraction play | E71: Giveaway | F71: =IF(useExample="Yes",E71,IF(D71="","",D71)) -> Giveaway | G71: Pick one: Win your money back / Giveaway / Decoy / Buy some; get some free / Pay less now or pay more later / Free with strings / None yet
A73: 14 | B73: Optimize | C73: The limit that makes the deadline real | G73: About 1 minute. Stack a second play and sharpen the numbers. | H73: =IF(F75<>"","Done","") -> Done
C74: Scarcity only works when it is true. Decide how many you will take per run (seats, units, slots) and say it. When it sells out, it sells out.
C75: Customers you will take per run | E75: 30 | F75: =IF(useExample="Yes",E75,IF(D75="","",D75)) -> 30 | G75: A number you would actually stop at.
A77: 15 | B77: Optimize | C77: Checklist: sharpening the attraction offer | G77: About 5 minutes. Stack a second play and sharpen the numbers. | H77: =IF(COUNTIF(F79:F83,"Yes")=5,"Done",IF(COUNTIF(F79:F83,"Yes")>0,"Part","")) -> Done
C78: Change one thing per run, in this order. Each tick is one run.
C79: Made the promise bigger or more specific | E79: Yes | F79: =IF(useExample="Yes",E79,D79) -> Yes | G79: Yes when it is true
C80: Shortened the deadline or lowered the cap | E80: Yes | F80: =IF(useExample="Yes",E80,D80) -> Yes | G80: Yes when it is true
C81: Added a bonus that costs you little and them a lot to get elsewhere | E81: Yes | F81: =IF(useExample="Yes",E81,D81) -> Yes | G81: Yes when it is true
C82: Tested a second price point | E82: Yes | F82: =IF(useExample="Yes",E82,D82) -> Yes | G82: Yes when it is true
C83: Cut the cost to deliver without cutting the result | E83: Yes | F83: =IF(useExample="Yes",E83,D83) -> Yes | G83: Yes when it is true

Sheet 3 Upsell
A1: Planet 3 of 6: Upsell
A2: The bigger yes, asked at the moment it is easiest to say. Where the model makes its money.
A3: Type in the yellow cells (column D). Column F shows the number in use: yours, or the example while the switch on Start Here says Yes.
A4: Level | B4: Band | C4: Title, lesson, questions and boxes | D4: Your answer | E4: Example | F4: In use | G4: Help | H4: Done?
A5: 1 | B5: Learn | C5: Why the moment after a yes is worth the most | G5: About 2 minutes. Read the idea, then answer one check question. | H5: =IF(F7="","",IF(F7="Right after the first yes; or right after their first win","Done","Not yet")) -> Done
C6: Someone who just paid you trusts you more than they will at any other point. They have decided you are worth money. Asking for a bigger yes in that window is far cheaper than finding a new customer. The upsell is where the money model makes its money. The attraction offer pays for the customer; the upsell pays for the business. The rule: the upsell must be a faster, bigger or easier way to get the same result they just bought. Not a different product. 'You want this; this gets you there sooner.'
C7: When is the upsell cheapest to make? | E7: Right after the first yes; or right after their first win | F7: =IF(useExample="Yes",E7,D7) -> Right after the first yes; or right after their first win | G7: =IF(F7="","",IF(F7="Right after the first yes; or right after their first win","Right. Trust peaks at the yes and at the first result. Both are upsell moments; the first is the one most businesses skip.","Not quite. Trust peaks at the yes and at the first result. Both are upsell moments; the first is the one most businesses skip.")) -> Right. Trust peaks at the yes and at the first result. Both are upsell moments; the first is the one most businesses skip.
C8: Choices: A month after the first purchase, once they have seen results / Right after the first yes, or right after their first win / Before they buy anything, to anchor high
A10: 2 | B10: Learn | C10: The upsell plays | G10: About 2 minutes. Read the idea, then answer one check question. | H10: =IF(F12="","",IF(F12="Counts it toward the bigger offer; so the first purchase becomes a deposit","Done","Not yet")) -> Done
C11: Classic: the next thing they need to get the result faster or keep it. The membership after the challenge, the installation after the product. Menu: several add-ons, they pick. People say yes to something more often than to one thing. Anchor: show the biggest option first. The one you actually want to sell looks reasonable next to it. Rollover: credit what they just paid toward the bigger thing. 'The $500 you paid comes off the $2,000 programme.' The first purchase becomes a deposit.
C12: What does a rollover upsell do with the money the customer already paid? | E12: Counts it toward the bigger offer; so the first purchase becomes a deposit | F12: =IF(useExample="Yes",E12,D12) -> Counts it toward the bigger offer; so the first purchase becomes a deposit | G12: =IF(F12="","",IF(F12="Counts it toward the bigger offer; so the first purchase becomes a deposit","Right. A customer who has already paid part of the bigger thing is halfway to yes.","Not quite. A customer who has already paid part of the bigger thing is halfway to yes.")) -> Right. A customer who has already paid part of the bigger thing is halfway to yes.
C13: Choices: Refunds it / Counts it toward the bigger offer, so the first purchase becomes a deposit / Ignores it
A15: 3 | B15: Learn | C15: The ask | G15: About 2 minutes. Read the idea, then answer one check question. | H15: =IF(F17="","",IF(F17="Whether every customer was actually offered it","Done","Not yet")) -> Done
C16: An upsell that is never offered has a take rate of zero. Most upsell problems are not the offer; it is that nobody asked. Ask in one sentence, as a service: 'Since you want [result], the people who get there fastest also [next step]. Want me to add it?' Then stop talking. Every customer is asked. Not the ones who look rich. Every one.
C17: The upsell take rate is 5%. What is the first thing to check? | E17: Whether every customer was actually offered it | F17: =IF(useExample="Yes",E17,D17) -> Whether every customer was actually offered it | G17: =IF(F17="","",IF(F17="Whether every customer was actually offered it","Right. Offered-to share times take-rate-when-offered is the real number. Fix the asking before the offer.","Not quite. Offered-to share times take-rate-when-offered is the real number. Fix the asking before the offer.")) -> Right. Offered-to share times take-rate-when-offered is the real number. Fix the asking before the offer.
C18: Choices: The price / Whether every customer was actually offered it / The product
A20: 4 | B20: Numbers | C20: The upsell's price | G20: About 1 minute. Type your figures for this part of the model. | H20: =IF(F22<>"","Done","") -> Done
C21: The bigger yes. If it is a payment plan, type the total here; the Downsell planet handles split terms.
C22: Price of the upsell | E22: 1200 | F22: =IF(useExample="Yes",E22,IF(D22="","",D22)) -> 1200 | G22: Dollars. Total price, before any rollover credit.
A24: 5 | B24: Numbers | C24: What the upsell costs to deliver | G24: About 2 minutes. Type your figures for this part of the model. | H24: =IF(F26<>"","Done","") -> Done
C25: Per customer, all in, for the whole thing you are selling.
C26: Cost to deliver the upsell to one customer | E26: 300 | F26: =IF(useExample="Yes",E26,IF(D26="","",D26)) -> 300 | G26: Dollars. Materials, hours, seats. 0 is allowed.
A28: 6 | B28: Numbers | C28: How many take it | G28: About 2 minutes. Type your figures for this part of the model. | H28: =IF(F30<>"","Done","") -> Done
C29: Of the customers offered the upsell, the share who say yes. If you have not run it yet, use a modest guess (one in five is a common starting point for a well-matched upsell) and mark it to revisit on Prove.
C30: Share of customers offered the upsell who take it | E30: 0.25 | F30: =IF(useExample="Yes",E30,IF(D30="","",D30)) -> 0.25 | G30: Type a percent, e.g. 25%. Takers divided by those asked, as a percent.
A32: 7 | B32: Build | C32: Exercise: pick your upsell play | G32: About 2 minutes. The exercises: pick a play, write the offer, tick the design list. | H32: =IF(F34<>"","Done","") -> Done
C33: Classic if there is an obvious next step. Menu if you have several. Anchor if you have a premium tier. Rollover if the attraction offer's price is a meaningful part of the upsell's.
C34: Your upsell play | E34: Rollover: first payment becomes a deposit | F34: =IF(useExample="Yes",E34,IF(D34="","",D34)) -> Rollover: first payment becomes a deposit | G34: Pick one: Classic: the next step / Menu: they pick from add-ons / Anchor: biggest option first / Rollover: first payment becomes a deposit
A36: 8 | B36: Build | C36: Exercise: write the upsell script | G36: About 8 minutes. The exercises: pick a play, write the offer, tick the design list. | H36: =IF(AND(F38<>"",F39<>""),"Done",IF(OR(F38<>"",F39<>""),"Part","")) -> Done
C37: One sentence to ask, one sentence for the most common no. The frame: 'Since you want [result], most people who get it fastest also [next step]. Want me to add that?'
C38: The ask, in one sentence | E38: Since you want the ten pounds gone for good, the people who keep it off go straight onto the year programme, and the $500 you paid comes off it. Want me to set that up? | F38: =IF(useExample="Yes",E38,IF(D38="","",D38)) -> Since you want the ten pounds gone for good, the people who keep it off go straight onto the year programme, and the $500 you paid comes off it. Want me to set that up? | G38: Say it as a service, not a sale.
C39: What you say to the most common no | E39: Totally fair. Would three payments make it work? | F39: =IF(useExample="Yes",E39,IF(D39="","",D39)) -> Totally fair. Would three payments make it work? | G39: Usually it leads to the downsell.
A41: 9 | B41: Build | C41: Checklist: upsell design | G41: About 5 minutes. The exercises: pick a play, write the offer, tick the design list. | H41: =IF(COUNTIF(F43:F49,"Yes")=7,"Done",IF(COUNTIF(F43:F49,"Yes")>0,"Part","")) -> Done
C42: Tick what is true of the upsell as written.
C43: Offered within minutes of the first yes, or at the first win | E43: Yes | F43: =IF(useExample="Yes",E43,D43) -> Yes | G43: Yes when it is true
C44: Gets the same result faster, bigger or easier | E44: Yes | F44: =IF(useExample="Yes",E44,D44) -> Yes | G44: Yes when it is true
C45: Priced above the attraction offer | E45: Yes | F45: =IF(useExample="Yes",E45,D45) -> Yes | G45: Yes when it is true
C46: Cost to deliver is known | E46: Yes | F46: =IF(useExample="Yes",E46,D46) -> Yes | G46: Yes when it is true
C47: The ask fits in one sentence | E47: Yes | F47: =IF(useExample="Yes",E47,D47) -> Yes | G47: Yes when it is true
C48: A no does not undo the first sale | E48: Yes | F48: =IF(useExample="Yes",E48,D48) -> Yes | G48: Yes when it is true
C49: There is a way to make sure every customer is asked | E49: Yes | F49: =IF(useExample="Yes",E49,D49) -> Yes | G49: Yes when it is true
A51: 10 | B51: Prove | C51: When it is offered | G51: About 1 minute. Run it for real and type what happened. | H51: =IF(F53<>"","Done","") -> Done
C52: Days after the first purchase. Day 0 is at the checkout. This decides whether the upsell's cash lands inside the 30 days.
C53: Days after the first purchase the upsell is offered | E53: 3 | F53: =IF(useExample="Yes",E53,IF(D53="","",D53)) -> 3 | G53: Days. 0 if at checkout. 14 if at the two-week check-in.
A55: 11 | B55: Prove | C55: How many were actually asked | G55: About 2 minutes. Run it for real and type what happened. | H55: =IF(F57<>"","Done","") -> Done
C56: From the first run: of the customers who showed up, the share who were offered the upsell at all. This is the number that is usually the problem.
C57: Share of customers who were offered the upsell | E57: 0.8 | F57: =IF(useExample="Yes",E57,IF(D57="","",D57)) -> 0.8 | G57: Type a percent, e.g. 25%. Asked divided by customers who showed up.
A59: 12 | B59: Prove | C59: Checklist: the first upsell run | G59: About 5 minutes. Run it for real and type what happened. | H59: =IF(COUNTIF(F61:F65,"Yes")=5,"Done",IF(COUNTIF(F61:F65,"Yes")>0,"Part","")) -> Done
C60: Two weeks of asking every customer, counting, and listening.
C61: The script was used word for word | E61: Yes | F61: =IF(useExample="Yes",E61,D61) -> Yes | G61: Yes when it is true
C62: Every customer was asked (a tally proves it) | E62: Yes | F62: =IF(useExample="Yes",E62,D62) -> Yes | G62: Yes when it is true
C63: Counted asked and took | E63: Yes | F63: =IF(useExample="Yes",E63,D63) -> Yes | G63: Yes when it is true
C64: Heard and wrote down the top reason for no | E64: Yes | F64: =IF(useExample="Yes",E64,D64) -> Yes | G64: Yes when it is true
C65: Changed one thing for the next run | E65: Yes | F65: =IF(useExample="Yes",E65,D65) -> Yes | G65: Yes when it is true
A67: 13 | B67: Optimize | C67: A second upsell | G67: About 3 minutes. Stack a second play and sharpen the numbers. | H67: =IF(AND(F69<>"",F70<>""),"Done",IF(OR(F69<>"",F70<>""),"Part","")) -> Done
C68: After the first upsell, a second one to the people who took it: the done-with-you tier, the equipment, the extra seats. Price and expected take.
C69: Price of the second upsell | E69: 2000 | F69: =IF(useExample="Yes",E69,IF(D69="","",D69)) -> 2000 | G69: Dollars. Offered to takers of the first.
C70: Share of first-upsell takers who take it | E70: 0.1 | F70: =IF(useExample="Yes",E70,IF(D70="","",D70)) -> 0.1 | G70: Type a percent, e.g. 25%. A guess is fine to start.
A72: 14 | B72: Optimize | C72: The anchor price | G72: About 2 minutes. Stack a second play and sharpen the numbers. | H72: =IF(F74<>"","Done","") -> Done
C73: The biggest thing you could sell, priced as if someone will buy it. Some will. The rest see the real upsell as reasonable.
C74: Price of your top tier | E74: 2400 | F74: =IF(useExample="Yes",E74,IF(D74="","",D74)) -> 2400 | G74: Dollars. Shown first, sold rarely.
A76: 15 | B76: Optimize | C76: Checklist: sharpening the upsell | G76: About 5 minutes. Stack a second play and sharpen the numbers. | H76: =IF(COUNTIF(F78:F82,"Yes")=5,"Done",IF(COUNTIF(F78:F82,"Yes")>0,"Part","")) -> Done
C77: One per run.
C78: Showed the anchor before the real upsell | E78: Yes | F78: =IF(useExample="Yes",E78,D78) -> Yes | G78: Yes when it is true
C79: Turned one upsell into a short menu | E79: Yes | F79: =IF(useExample="Yes",E79,D79) -> Yes | G79: Yes when it is true
C80: Credited the first payment toward the upsell | E80: Yes | F80: =IF(useExample="Yes",E80,D80) -> Yes | G80: Yes when it is true
C81: Raised the price 10% and watched the take rate | E81: Yes | F81: =IF(useExample="Yes",E81,D81) -> Yes | G81: Yes when it is true
C82: Added a second ask at the customer's first win | E82: Yes | F82: =IF(useExample="Yes",E82,D82) -> Yes | G82: Yes when it is true

Sheet 4 Downsell
A1: Planet 4 of 6: Downsell
A2: The smaller yes after a no. Keeps the customer and recovers cash you would have lost.
A3: Type in the yellow cells (column D). Column F shows the number in use: yours, or the example while the switch on Start Here says Yes.
A4: Level | B4: Band | C4: Title, lesson, questions and boxes | D4: Your answer | E4: Example | F4: In use | G4: Help | H4: Done?
A5: 1 | B5: Learn | C5: A no is not the end | G5: About 2 minutes. Read the idea, then answer one check question. | H5: =IF(F7="","",IF(F7="The same programme at $2;000 in four payments","Done","Not yet")) -> Done
C6: When a customer says no to the upsell, most businesses stop. The customer wanted the result a minute ago; what they said no to was the size or the terms. A downsell offers a smaller yes: the same promise with less in the box, or the same box with easier terms. It recovers cash that was walking out, and it keeps the customer in the sequence for continuity. Order matters: first change the terms (a payment plan), then the package (a lighter version), then the price. Cutting the price first teaches customers to say no.
C7: The customer says no to a $2,000 programme. What is the first downsell to try? | E7: The same programme at $2;000 in four payments | F7: =IF(useExample="Yes",E7,D7) -> The same programme at $2;000 in four payments | G7: =IF(F7="","",IF(F7="The same programme at $2;000 in four payments","Right. Same value, easier terms. Price cuts come last and cost the most.","Not quite. Same value, easier terms. Price cuts come last and cost the most.")) -> Right. Same value, easier terms. Price cuts come last and cost the most.
C8: Choices: $1,000 for the same programme / The same programme at $2,000 in four payments / A different product
A10: 2 | B10: Learn | C10: The downsell plays | G10: About 2 minutes. Read the idea, then answer one check question. | H10: =IF(F12="","",IF(F12="There is a string: a payment if they keep it or do not do the work","Done","Not yet")) -> Done
C11: Payment plan: the same offer split over time. Usually the first thing to try, and often the only one needed. Trial with a string: try it, and pay if you keep it, or pay a penalty if you do not do the work. The string keeps the free part from being free forever. Lighter version: fewer parts, less access, less support, same result more slowly. Keep the promise, shrink the package. Deposit and decide: a small payment to hold the price or the spot, decided later. Cash today, and a reason to come back.
C12: What makes a trial a downsell rather than a giveaway? | E12: There is a string: a payment if they keep it or do not do the work | F12: =IF(useExample="Yes",E12,D12) -> There is a string: a payment if they keep it or do not do the work | G12: =IF(F12="","",IF(F12="There is a string: a payment if they keep it or do not do the work","Right. A trial with no string is a free customer with no path to paying. The string is the point.","Not quite. A trial with no string is a free customer with no path to paying. The string is the point.")) -> Right. A trial with no string is a free customer with no path to paying. The string is the point.
C13: Choices: It is shorter / There is a string: a payment if they keep it or do not do the work / It is only for some people
A15: 3 | B15: Learn | C15: Where the downsell sits | G15: About 2 minutes. Read the idea, then answer one check question. | H15: =IF(F17="","",IF(F17="The one for customers who said no to the upsell","Done","Not yet")) -> Done
C16: There are two nos in the model. The no to the attraction offer (a stranger who did not buy) and the no to the upsell (a customer who did not go bigger). Each can have a downsell. Start with the second. Those people already paid you once, showed up, and heard the upsell. A smaller yes from them is the easiest cash in the business. The downsell after the attraction offer comes on the Optimize band, once the rest works.
C17: Which downsell should be built first? | E17: The one for customers who said no to the upsell | F17: =IF(useExample="Yes",E17,D17) -> The one for customers who said no to the upsell | G17: =IF(F17="","",IF(F17="The one for customers who said no to the upsell","Right. They are warm, present and have already paid. Build where the yes is easiest.","Not quite. They are warm, present and have already paid. Build where the yes is easiest.")) -> Right. They are warm, present and have already paid. Build where the yes is easiest.
C18: Choices: The one for strangers who did not buy the attraction offer / The one for customers who said no to the upsell / Both at once
A20: 4 | B20: Numbers | C20: The downsell's price | G20: About 1 minute. Type your figures for this part of the model. | H20: =IF(F22<>"","Done","") -> Done
C21: What the smaller yes costs the customer in total. For a payment plan on the same upsell, that may equal the upsell price; the terms are what changed.
C22: Price of the downsell | E22: 450 | F22: =IF(useExample="Yes",E22,IF(D22="","",D22)) -> 450 | G22: Dollars. Total over all payments.
A24: 5 | B24: Numbers | C24: What the downsell costs to deliver | G24: About 2 minutes. Type your figures for this part of the model. | H24: =IF(F26<>"","Done","") -> Done
C25: Per customer. A lighter version should cost less to deliver; a payment plan costs the same as the upsell.
C26: Cost to deliver the downsell to one customer | E26: 300 | F26: =IF(useExample="Yes",E26,IF(D26="","",D26)) -> 300 | G26: Dollars. All in. 0 is allowed.
A28: 6 | B28: Numbers | C28: How many take it | G28: About 2 minutes. Type your figures for this part of the model. | H28: =IF(F30<>"","Done","") -> Done
C29: Of the customers who said no to the upsell and were offered the downsell, the share who take it.
C30: Share of upsell nos who take the downsell | E30: 0.4 | F30: =IF(useExample="Yes",E30,IF(D30="","",D30)) -> 0.4 | G30: Type a percent, e.g. 25%. Takers divided by those offered, as a percent.
A32: 7 | B32: Build | C32: Exercise: pick your downsell play | G32: About 2 minutes. The exercises: pick a play, write the offer, tick the design list. | H32: =IF(F34<>"","Done","") -> Done
C33: Payment plan unless there is a clear reason not to. The Plays page says which ones the numbers support.
C34: Your downsell play | E34: Payment plan | F34: =IF(useExample="Yes",E34,IF(D34="","",D34)) -> Payment plan | G34: Pick one: Payment plan / Trial with a string / Lighter version / Deposit and decide
A36: 8 | B36: Build | C36: Exercise: write the downsell script | G36: About 6 minutes. The exercises: pick a play, write the offer, tick the design list. | H36: =IF(AND(F38<>"",F39<>""),"Done",IF(OR(F38<>"",F39<>""),"Part","")) -> Done
C37: It follows the no directly. 'Totally fair. Would it help if we did [terms or lighter version] instead? You would still get [result], just [the change].'
C38: The downsell, in one sentence | E38: No problem. We can do the same programme as three payments of $150; you still get the full year. | F38: =IF(useExample="Yes",E38,IF(D38="","",D38)) -> No problem. We can do the same programme as three payments of $150; you still get the full year. | G38: Acknowledge the no, offer the smaller yes, keep the result.
C39: What exactly is smaller | E39: Nothing is cut; the terms are longer | F39: =IF(useExample="Yes",E39,IF(D39="","",D39)) -> Nothing is cut; the terms are longer | G39: Fewer sessions, longer terms, less support, no guarantee. Name it.
A41: 9 | B41: Build | C41: Checklist: downsell design | G41: About 4 minutes. The exercises: pick a play, write the offer, tick the design list. | H41: =IF(COUNTIF(F43:F48,"Yes")=6,"Done",IF(COUNTIF(F43:F48,"Yes")>0,"Part","")) -> Done
C42: Tick what is true of the downsell as written.
C43: Keeps the same result, only the package or terms shrink | E43: Yes | F43: =IF(useExample="Yes",E43,D43) -> Yes | G43: Yes when it is true
C44: Terms were tried before price | E44: Yes | F44: =IF(useExample="Yes",E44,D44) -> Yes | G44: Yes when it is true
C45: Still covers its cost to deliver | E45: Yes | F45: =IF(useExample="Yes",E45,D45) -> Yes | G45: Yes when it is true
C46: Still puts the customer in front of the continuity offer | E46: Yes | F46: =IF(useExample="Yes",E46,D46) -> Yes | G46: Yes when it is true
C47: Is never advertised, only offered after a no | E47: Yes | F47: =IF(useExample="Yes",E47,D47) -> Yes | G47: Yes when it is true
C48: The offer fits in one sentence | E48: Yes | F48: =IF(useExample="Yes",E48,D48) -> Yes | G48: Yes when it is true
A50: 10 | B50: Prove | C50: The payment plan's shape | G50: About 2 minutes. Run it for real and type what happened. | H50: =IF(AND(F52<>"",F53<>""),"Done",IF(OR(F52<>"",F53<>""),"Part","")) -> Done
C51: How many payments, and how big the first one is. The first payment is what lands inside the 30 days; the rest is a promise.
C52: Number of payments | E52: 3 | F52: =IF(useExample="Yes",E52,IF(D52="","",D52)) -> 3 | G52: 1 if paid in full.
C53: Share of the price paid up front | E53: 0.34 | F53: =IF(useExample="Yes",E53,IF(D53="","",D53)) -> 0.34 | G53: Type a percent, e.g. 25%. The first payment as a percent of the total. 100 if paid in full.
A55: 11 | B55: Prove | C55: How many plans fail | G55: About 2 minutes. Run it for real and type what happened. | H55: =IF(F57<>"","Done","") -> Done
C56: Payment plans leak. The share of plan customers who stop paying before the end. Type 0 if none have.
C57: Share of payment plans that stop early | E57: 0.08 | F57: =IF(useExample="Yes",E57,IF(D57="","",D57)) -> 0.08 | G57: Type a percent, e.g. 25%. Stopped divided by started.
A59: 12 | B59: Prove | C59: Checklist: the first downsell run | G59: About 4 minutes. Run it for real and type what happened. | H59: =IF(COUNTIF(F61:F65,"Yes")=5,"Done",IF(COUNTIF(F61:F65,"Yes")>0,"Part","")) -> Done
C60: Two weeks, every no gets the downsell, count what happens.
C61: Every upsell no was offered the downsell | E61: Yes | F61: =IF(useExample="Yes",E61,D61) -> Yes | G61: Yes when it is true
C62: Counted offered and took | E62: Yes | F62: =IF(useExample="Yes",E62,D62) -> Yes | G62: Yes when it is true
C63: Payment plans are tracked to the last payment | E63: Yes | F63: =IF(useExample="Yes",E63,D63) -> Yes | G63: Yes when it is true
C64: Wrote down why people said no to the downsell too | E64: Yes | F64: =IF(useExample="Yes",E64,D64) -> Yes | G64: Yes when it is true
C65: Changed one thing for the next run | E65: Yes | F65: =IF(useExample="Yes",E65,D65) -> Yes | G65: Yes when it is true
A67: 13 | B67: Optimize | C67: A downsell for the first no | G67: About 3 minutes. Stack a second play and sharpen the numbers. | H67: =IF(AND(F69<>"",F70<>""),"Done",IF(OR(F69<>"",F70<>""),"Part","")) -> Done
C68: For strangers who did not take the attraction offer: a lower entry. A single session, a smaller batch, a deposit. Price and expected take among those who said no.
C69: Price of the entry downsell | E69: 99 | F69: =IF(useExample="Yes",E69,IF(D69="","",D69)) -> 99 | G69: Dollars. Offered to leads who did not buy the attraction offer.
C70: Share of attraction nos who take it | E70: 0.2 | F70: =IF(useExample="Yes",E70,IF(D70="","",D70)) -> 0.2 | G70: Type a percent, e.g. 25%. A guess is fine to start.
A72: 14 | B72: Optimize | C72: Exercise: the second thing you can shrink | G72: About 2 minutes. Stack a second play and sharpen the numbers. | H72: =IF(F74<>"","Done","") -> Done
C73: If the first downsell is a payment plan, the second is a lighter version, and the other way round. Pick what you cut in the second one.
C74: What the second downsell cuts | E74: Support or check-ins | F74: =IF(useExample="Yes",E74,IF(D74="","",D74)) -> Support or check-ins | G74: Pick one: Time with you / Access or seats / Support or check-ins / The guarantee / Speed of the result
A76: 15 | B76: Optimize | C76: Checklist: sharpening the downsell | G76: About 4 minutes. Stack a second play and sharpen the numbers. | H76: =IF(COUNTIF(F78:F82,"Yes")=5,"Done",IF(COUNTIF(F78:F82,"Yes")>0,"Part","")) -> Done
C77: One per run.
C78: Raised the first payment's share | E78: Yes | F78: =IF(useExample="Yes",E78,D78) -> Yes | G78: Yes when it is true
C79: Cut the number of payments | E79: Yes | F79: =IF(useExample="Yes",E79,D79) -> Yes | G79: Yes when it is true
C80: Put every plan on automatic payment | E80: Yes | F80: =IF(useExample="Yes",E80,D80) -> Yes | G80: Yes when it is true
C81: Added the second downsell after the second no | E81: Yes | F81: =IF(useExample="Yes",E81,D81) -> Yes | G81: Yes when it is true
C82: Tested a deposit-and-decide for the walkaways | E82: Yes | F82: =IF(useExample="Yes",E82,D82) -> Yes | G82: Yes when it is true

Sheet 5 Continuity
A1: Planet 5 of 6: Continuity
A2: The yes that repeats: getting customers to keep paying, which is what makes lifetime profit large.
A3: Type in the yellow cells (column D). Column F shows the number in use: yours, or the example while the switch on Start Here says Yes.
A4: Level | B4: Band | C4: Title, lesson, questions and boxes | D4: Your answer | E4: Example | F4: In use | G4: Help | H4: Done?
A5: 1 | B5: Learn | C5: One sale into many | G5: About 2 minutes. Read the idea, then answer one check question. | H5: =IF(F7="","",IF(F7="About 10","Done","Not yet")) -> Done
C6: A customer who pays once is a transaction. A customer who pays every month is an asset. Continuity is what turns the model from a series of launches into a business that grows while you sleep. The lifetime gross profit of a customer is mostly continuity. A $150 a month membership with 8% monthly churn is worth about twelve and a half months, over $1,800 of revenue, from one yes. Every earlier offer should end by placing the customer in front of the continuity offer.
C7: Monthly churn is 10%. On average how many months does a member stay? | E7: About 10 | F7: =IF(useExample="Yes",E7,D7) -> About 10 | G7: =IF(F7="","",IF(F7="About 10","Right. Expected months is one divided by the monthly churn: 1 / 0.10 = 10.","Not quite. Expected months is one divided by the monthly churn: 1 / 0.10 = 10.")) -> Right. Expected months is one divided by the monthly churn: 1 / 0.10 = 10.
C8: Choices: About 10 / About 5 / About 20
A10: 2 | B10: Learn | C10: The continuity plays | G10: About 2 minutes. Read the idea, then answer one check question. | H10: =IF(F12="","",IF(F12="Getting people to stay; by giving them something to wait for","Done","Not yet")) -> Done
C11: Bonus for committing: a gift, worth a lot to them and little to you, for joining the ongoing plan today. Discount for a longer term: pay for a year, get it cheaper. Cash forward, churn removed. Waived fee: the setup or first month is free if they join now. The fee exists so that waiving it means something. Bonuses over time: something new arrives in month two, month three, month six. Reasons to stay, not just reasons to join. The default: the ongoing plan is the normal thing to buy; the one-off is the exception you have to ask for.
C12: What is 'bonuses over time' for? | E12: Getting people to stay; by giving them something to wait for | F12: =IF(useExample="Yes",E12,D12) -> Getting people to stay; by giving them something to wait for | G12: =IF(F12="","",IF(F12="Getting people to stay; by giving them something to wait for","Right. Joining bonuses fight the first no. Bonuses over time fight churn.","Not quite. Joining bonuses fight the first no. Bonuses over time fight churn.")) -> Right. Joining bonuses fight the first no. Bonuses over time fight churn.
C13: Choices: Getting people to join / Getting people to stay, by giving them something to wait for / Raising the price
A15: 3 | B15: Learn | C15: Churn is the tax | G15: About 2 minutes. Read the idea, then answer one check question. | H15: =IF(F17="","",IF(F17="It roughly doubles","Done","Not yet")) -> Done
C16: Churn is the share of members who leave each month. Halving it doubles the value of every customer you already have, without a single new lead. Measure it monthly, by cohort (people who joined the same month). A single average hides a leak in month two. Most churn happens early, before the customer has had a win. The continuity offer's first job is to get them a win fast.
C17: Churn drops from 10% to 5% a month. What happens to the average member's lifetime value? | E17: It roughly doubles | F17: =IF(useExample="Yes",E17,D17) -> It roughly doubles | G17: =IF(F17="","",IF(F17="It roughly doubles","Right. Expected months goes from 10 to 20. Same price, twice the months.","Not quite. Expected months goes from 10 to 20. Same price, twice the months.")) -> Right. Expected months goes from 10 to 20. Same price, twice the months.
C18: Choices: It goes up a little / It roughly doubles / Nothing until you raise prices
A20: 4 | B20: Numbers | C20: The monthly price | G20: About 1 minute. Type your figures for this part of the model. | H20: =IF(F22<>"","Done","") -> Done
C21: What a member pays each month. If it is yearly, divide by twelve here; the yearly option comes on Optimize.
C22: Continuity price per month | E22: 149 | F22: =IF(useExample="Yes",E22,IF(D22="","",D22)) -> 149 | G22: Dollars. Per member, per month.
A24: 5 | B24: Numbers | C24: What a member costs to serve each month | G24: About 2 minutes. Type your figures for this part of the model. | H24: =IF(F26<>"","Done","") -> Done
C25: Per member, per month: the classes they attend, the software seat, the check-in call, the shipment.
C26: Cost to serve one member for a month | E26: 40 | F26: =IF(useExample="Yes",E26,IF(D26="","",D26)) -> 40 | G26: Dollars. All in. 0 is allowed.
A28: 6 | B28: Numbers | C28: Who joins, and who leaves | G28: About 3 minutes. Type your figures for this part of the model. | H28: =IF(AND(F30<>"",F31<>""),"Done",IF(OR(F30<>"",F31<>""),"Part","")) -> Done
C29: The share of customers who join continuity by the end of the sequence, and the share of members who leave each month. If you have no history, guess and revisit on Prove.
C30: Share of customers who join continuity | E30: 0.6 | F30: =IF(useExample="Yes",E30,IF(D30="","",D30)) -> 0.6 | G30: Type a percent, e.g. 25%. Joiners divided by customers who finished the earlier offers.
C31: Monthly churn | E31: 0.08 | F31: =IF(useExample="Yes",E31,IF(D31="","",D31)) -> 0.08 | G31: Type a percent, e.g. 25%. Members who left this month divided by members at the start of it.
A33: 7 | B33: Build | C33: Exercise: pick your continuity play | G33: About 2 minutes. The exercises: pick a play, write the offer, tick the design list. | H33: =IF(F35<>"","Done","") -> Done
C34: The default first: make the ongoing plan the normal purchase. Then one of the others to remove the first no.
C35: Your continuity play | E35: The default | F35: =IF(useExample="Yes",E35,IF(D35="","",D35)) -> The default | G35: Pick one: Bonus for committing / Discount for a longer term / Waived fee / Bonuses over time / The default
A37: 8 | B37: Build | C37: Exercise: write the continuity pitch | G37: About 8 minutes. The exercises: pick a play, write the offer, tick the design list. | H37: =IF(AND(F39<>"",F40<>""),"Done",IF(OR(F39<>"",F40<>""),"Part","")) -> Done
C38: Frame: 'To keep [result] going, most people stay on for [the ongoing plan]. It is [price] a month, and if you start today you also get [bonus].' Then the reason to stay: what arrives later.
C39: The pitch, one or two sentences | E39: To keep the weight off, most people stay on as members: $149 a month, and if you start today the first month's meal plans are included. | F39: =IF(useExample="Yes",E39,IF(D39="","",D39)) -> To keep the weight off, most people stay on as members: $149 a month, and if you start today the first month's meal plans are included. | G39: Result, plan, price, the joining bonus.
C40: The reason to stay past month one | E40: A new eight-week block every two months, and a tracked weigh-in chart | F40: =IF(useExample="Yes",E40,IF(D40="","",D40)) -> A new eight-week block every two months, and a tracked weigh-in chart | G40: What arrives in month two, three, six. A tracked result counts.
A42: 9 | B42: Build | C42: Checklist: continuity design | G42: About 4 minutes. The exercises: pick a play, write the offer, tick the design list. | H42: =IF(COUNTIF(F44:F49,"Yes")=6,"Done",IF(COUNTIF(F44:F49,"Yes")>0,"Part","")) -> Done
C43: Tick what is true of the continuity offer as written.
C44: The ongoing plan is the default purchase | E44: Yes | F44: =IF(useExample="Yes",E44,D44) -> Yes | G44: Yes when it is true
C45: There is a reason to join today | E45: Yes | F45: =IF(useExample="Yes",E45,D45) -> Yes | G45: Yes when it is true
C46: There is a reason to stay past month one | E46: Yes | F46: =IF(useExample="Yes",E46,D46) -> Yes | G46: Yes when it is true
C47: The first month is built to deliver a visible win | E47: Yes | F47: =IF(useExample="Yes",E47,D47) -> Yes | G47: Yes when it is true
C48: Billing is automatic | E48: Yes | F48: =IF(useExample="Yes",E48,D48) -> Yes | G48: Yes when it is true
C49: Churn is measured monthly by cohort | E49: Yes | F49: =IF(useExample="Yes",E49,D49) -> Yes | G49: Yes when it is true
A51: 10 | B51: Prove | C51: When the first month gets charged | G51: About 1 minute. Run it for real and type what happened. | H51: =IF(F53<>"","Done","") -> Done
C52: Days from the first purchase to the first continuity charge. If the membership starts after a six-week challenge, that is about 42, and the first month's cash is outside the 30 days. Charging at signup, with the plan starting later, moves it inside.
C53: Days from the first purchase to the first continuity charge | E53: 42 | F53: =IF(useExample="Yes",E53,IF(D53="","",D53)) -> 42 | G53: Days. 0 if charged at signup.
A55: 11 | B55: Prove | C55: Who is still there at month three | G55: About 3 minutes. Run it for real and type what happened. | H55: =IF(F57<>"","Done","") -> Done
C56: From a cohort that joined at least three months ago: the share still paying. The model compares it with what your churn figure predicts.
C57: Share of a cohort still paying at month three | E57: 0.78 | F57: =IF(useExample="Yes",E57,IF(D57="","",D57)) -> 0.78 | G57: Type a percent, e.g. 25%. Still paying divided by joined.
A59: 12 | B59: Prove | C59: Checklist: the first continuity run | G59: About 4 minutes. Run it for real and type what happened. | H59: =IF(COUNTIF(F61:F65,"Yes")=5,"Done",IF(COUNTIF(F61:F65,"Yes")>0,"Part","")) -> Done
C60: One cohort, followed for three months.
C61: Every finishing customer was offered continuity | E61: Yes | F61: =IF(useExample="Yes",E61,D61) -> Yes | G61: Yes when it is true
C62: The cohort is tagged by joining month | E62: Yes | F62: =IF(useExample="Yes",E62,D62) -> Yes | G62: Yes when it is true
C63: The first-month win is tracked per member | E63: Yes | F63: =IF(useExample="Yes",E63,D63) -> Yes | G63: Yes when it is true
C64: Every leaver was asked why | E64: Yes | F64: =IF(useExample="Yes",E64,D64) -> Yes | G64: Yes when it is true
C65: Changed one thing for the next cohort | E65: Yes | F65: =IF(useExample="Yes",E65,D65) -> Yes | G65: Yes when it is true
A67: 13 | B67: Optimize | C67: The longer-term option | G67: About 3 minutes. Stack a second play and sharpen the numbers. | H67: =IF(AND(F69<>"",F70<>""),"Done",IF(OR(F69<>"",F70<>""),"Part","")) -> Done
C68: A yearly (or six-month) plan at a discount, paid up front. It moves a year of cash into the first 30 days and removes churn for that year. Price and expected take among joiners.
C69: Price of the yearly plan, paid up front | E69: 1490 | F69: =IF(useExample="Yes",E69,IF(D69="","",D69)) -> 1490 | G69: Dollars. Total for the year.
C70: Share of joiners who choose it | E70: 0.15 | F70: =IF(useExample="Yes",E70,IF(D70="","",D70)) -> 0.15 | G70: Type a percent, e.g. 25%. A guess is fine to start.
A72: 14 | B72: Optimize | C72: Exercise: the second reason to stay | G72: About 2 minutes. Stack a second play and sharpen the numbers. | H72: =IF(F74<>"","Done","") -> Done
C73: Pick the retention play you add next. Each one answers 'why stay in month four?'
C74: The next reason to stay | E74: A result they can watch grow | F74: =IF(useExample="Yes",E74,IF(D74="","",D74)) -> A result they can watch grow | G74: Pick one: A bonus that arrives every few months / A group they would miss / A result they can watch grow / A price locked while they stay / Milestones with rewards
A76: 15 | B76: Optimize | C76: Checklist: sharpening continuity | G76: About 4 minutes. Stack a second play and sharpen the numbers. | H76: =IF(COUNTIF(F78:F82,"Yes")=5,"Done",IF(COUNTIF(F78:F82,"Yes")>0,"Part","")) -> Done
C77: One per cohort.
C78: Offered the yearly plan at joining | E78: Yes | F78: =IF(useExample="Yes",E78,D78) -> Yes | G78: Yes when it is true
C79: Added a month-two bonus | E79: Yes | F79: =IF(useExample="Yes",E79,D79) -> Yes | G79: Yes when it is true
C80: Built a save offer for the moment someone cancels | E80: Yes | F80: =IF(useExample="Yes",E80,D80) -> Yes | G80: Yes when it is true
C81: Chased failed payments the same day | E81: Yes | F81: =IF(useExample="Yes",E81,D81) -> Yes | G81: Yes when it is true
C82: Reviewed churn by cohort monthly | E82: Yes | F82: =IF(useExample="Yes",E82,D82) -> Yes | G82: Yes when it is true

Sheet 6 KPIs and Scale
A1: Planet 6 of 6: KPIs and Scale
A2: The six numbers to watch, the two thresholds, and how fast customer money can fund the next customer.
A3: Type in the yellow cells (column D). Column F shows the number in use: yours, or the example while the switch on Start Here says Yes.
A4: Level | B4: Band | C4: Title, lesson, questions and boxes | D4: Your answer | E4: Example | F4: In use | G4: Help | H4: Done?
A5: 1 | B5: Learn | C5: The six numbers | G5: About 3 minutes. Read the idea, then answer one check question. | H5: =IF(F7="","",IF(F7="$380","Done","Not yet")) -> Done
C6: Cost of a customer (CAC): what you spend to get one. Gross profit per sale: price minus the cost to deliver. 30-day cash: gross profit collected from a customer in their first 30 days, across the whole sequence. Lifetime gross profit (LTGP): everything a customer earns you, less delivery, over their whole stay. LTGP to CAC: how many times over a customer pays for themselves. Payback days: how long until a customer has paid back their cost.
C7: Price $500, cost to deliver $120, cost of the customer $150. What is the gross profit per sale? | E7: $380 | F7: =IF(useExample="Yes",E7,D7) -> $380 | G7: =IF(F7="","",IF(F7="$380","Right. Gross profit is price minus delivery cost: 500 minus 120. The cost of the customer is compared against it, not subtracted from it.","Not quite. Gross profit is price minus delivery cost: 500 minus 120. The cost of the customer is compared against it, not subtracted from it.")) -> Right. Gross profit is price minus delivery cost: 500 minus 120. The cost of the customer is compared against it, not subtracted from it.
C8: Choices: $380 / $230 / $350
A10: 2 | B10: Learn | C10: The two thresholds | G10: About 2 minutes. Read the idea, then answer one check question. | H10: =IF(F12="","",IF(F12="Self-funding: each customer pays for the next","Done","Not yet")) -> Done
C11: 30-day cash at least equal to CAC: you break even on each customer before the bills for getting them are due. You are alive. 30-day cash at least twice CAC: each customer funds the next one. You can grow as fast as you can deliver, with no outside money. LTGP at least three times CAC: the business is worth running. Below that, the customers are barely paying for the marketing.
C12: 30-day cash is $300 and CAC is $150. Which is true? | E12: Self-funding: each customer pays for the next | F12: =IF(useExample="Yes",E12,D12) -> Self-funding: each customer pays for the next | G12: =IF(F12="","",IF(F12="Self-funding: each customer pays for the next","Right. Twice the cost inside 30 days is the self-funding line.","Not quite. Twice the cost inside 30 days is the self-funding line.")) -> Right. Twice the cost inside 30 days is the self-funding line.
C13: Choices: Break even only / Self-funding: each customer pays for the next / Losing money
A15: 3 | B15: Learn | C15: The four ways to grow | G15: About 2 minutes. Read the idea, then answer one check question. | H15: =IF(F17="","",IF(F17="A bigger office","Done","Not yet")) -> Done
C16: More customers (attraction). More per customer (upsell, downsell, price). More often (continuity). Less to deliver (margin). Every business grows through those four, and only those four. When you are stuck, the constraint from Foundations level 8 names which one. The model's charts move when you move any of them; try it on the Model page once your numbers are in.
C17: Which of these is not one of the four ways to grow? | E17: A bigger office | F17: =IF(useExample="Yes",E17,D17) -> A bigger office | G17: =IF(F17="","",IF(F17="A bigger office","Right. An office is a cost. Growth comes from customers, price, frequency and margin.","Not quite. An office is a cost. Growth comes from customers, price, frequency and margin.")) -> Right. An office is a cost. Growth comes from customers, price, frequency and margin.
C18: Choices: Customers buy more often / A bigger office / Each sale costs less to deliver
A20: 4 | B20: Numbers | C20: How many you can serve | G20: About 2 minutes. Type your figures for this part of the model. | H20: =IF(F22<>"","Done","") -> Done
C21: The ceiling on the other side: customers you can take on in a month before quality drops. The growth chart flattens here.
C22: Most new customers you can serve in a month | E22: 80 | F22: =IF(useExample="Yes",E22,IF(D22="","",D22)) -> 80 | G22: Honest, at current staff and hours.
A24: 5 | B24: Numbers | C24: What the business costs to keep open | G24: About 3 minutes. Type your figures for this part of the model. | H24: =IF(F26<>"","Done","") -> Done
C25: Rent, salaries, software, insurance: the monthly costs that do not change with one more customer. Gross profit has to cover this before there is any profit.
C26: Fixed costs per month | E26: 9000 | F26: =IF(useExample="Yes",E26,IF(D26="","",D26)) -> 9000 | G26: Dollars. Everything that is due whether or not a customer buys.
A28: 6 | B28: Numbers | C28: The loop: cash in, share back in | G28: About 3 minutes. Type your figures for this part of the model. | H28: =IF(AND(F30<>"",F31<>""),"Done",IF(OR(F30<>"",F31<>""),"Part","")) -> Done
C29: Two figures that decide how fast the model can spin. The cash you can put toward getting customers each month is the ceiling before the model self-funds. The share of each month's 30-day cash you put back into ads is what makes the ceiling rise. 100 is all of it.
C30: Cash available for getting customers each month | E30: 8000 | F30: =IF(useExample="Yes",E30,IF(D30="","",D30)) -> 8000 | G30: Dollars. What you could spend on ads and sales this month without missing payroll or rent.
C31: Share of 30-day cash reinvested in getting customers | E31: 0.5 | F31: =IF(useExample="Yes",E31,IF(D31="","",D31)) -> 0.5 | G31: Type a percent, e.g. 25%. As a percent. 50 is half.
A33: 7 | B33: Build | C33: Exercise: the one number on the wall | G33: About 1 minute. The exercises: pick a play, write the offer, tick the design list. | H33: =IF(F35<>"","Done","") -> Done
C34: Pick the one KPI the whole team sees every week. The constraint says which: customers means CAC or leads; per customer means 30-day cash; stay means churn.
C35: The number you watch weekly | E35: 30-day cash per customer | F35: =IF(useExample="Yes",E35,IF(D35="","",D35)) -> 30-day cash per customer | G35: Pick one: Cost of a customer / 30-day cash per customer / 30-day ratio / Monthly churn / LTGP to CAC / Leads per week
A37: 8 | B37: Build | C37: Exercise: the scoreboard | G37: About 3 minutes. The exercises: pick a play, write the offer, tick the design list. | H37: =IF(AND(F39<>"",F40<>""),"Done",IF(OR(F39<>"",F40<>""),"Part","")) -> Done
C38: Where the numbers live, who updates them, and when. A number nobody owns is a number nobody has.
C39: Where the scoreboard lives | E39: The whiteboard by the front desk | F39: =IF(useExample="Yes",E39,IF(D39="","",D39)) -> The whiteboard by the front desk | G39: A sheet, a whiteboard, this page.
C40: Who updates it, and on which day | E40: Sam, every Monday | F40: =IF(useExample="Yes",E40,IF(D40="","",D40)) -> Sam, every Monday | G40: One name, one day.
A42: 9 | B42: Build | C42: Checklist: what the scoreboard shows | G42: About 5 minutes. The exercises: pick a play, write the offer, tick the design list. | H42: =IF(COUNTIF(F44:F49,"Yes")=6,"Done",IF(COUNTIF(F44:F49,"Yes")>0,"Part","")) -> Done
C43: Tick each row once it is on the board with a real number.
C44: Cost of a customer, this month | E44: Yes | F44: =IF(useExample="Yes",E44,D44) -> Yes | G44: Yes when it is true
C45: 30-day cash per customer | E45: Yes | F45: =IF(useExample="Yes",E45,D45) -> Yes | G45: Yes when it is true
C46: 30-day ratio against the two thresholds | E46: Yes | F46: =IF(useExample="Yes",E46,D46) -> Yes | G46: Yes when it is true
C47: Upsell, downsell and continuity take rates | E47: Yes | F47: =IF(useExample="Yes",E47,D47) -> Yes | G47: Yes when it is true
C48: Monthly churn by cohort | E48: Yes | F48: =IF(useExample="Yes",E48,D48) -> Yes | G48: Yes when it is true
C49: LTGP to CAC | E49: Yes | F49: =IF(useExample="Yes",E49,D49) -> Yes | G49: Yes when it is true
A51: 10 | B51: Prove | C51: The 30-day cash you measured | G51: About 6 minutes. Run it for real and type what happened. | H51: =IF(F53<>"","Done","") -> Done
C52: After running the new sequence for a month: the cash actually collected per new customer in their first 30 days. The model page shows it against what the plan predicted and against the before figure.
C53: Measured 30-day cash per new customer, after the model | E53: 760 | F53: =IF(useExample="Yes",E53,IF(D53="","",D53)) -> 760 | G53: Dollars. Collected, from a real cohort.
A55: 11 | B55: Prove | C55: The customers you got last month | G55: About 2 minutes. Run it for real and type what happened. | H55: =IF(F57<>"","Done","") -> Done
C56: New customers in the first full month of the model, compared with the before figure from Foundations level 6.
C57: New customers last month, after the model | E57: 55 | F57: =IF(useExample="Yes",E57,IF(D57="","",D57)) -> 55 | G57: First-time payers.
A59: 12 | B59: Prove | C59: Checklist: the monthly close | G59: About 6 minutes. Run it for real and type what happened. | H59: =IF(COUNTIF(F61:F66,"Yes")=6,"Done",IF(COUNTIF(F61:F66,"Yes")>0,"Part","")) -> Done
C60: Once a month, in this order.
C61: Total spent on getting customers, by channel | E61: Yes | F61: =IF(useExample="Yes",E61,D61) -> Yes | G61: Yes when it is true
C62: New customers, by source | E62: Yes | F62: =IF(useExample="Yes",E62,D62) -> Yes | G62: Yes when it is true
C63: 30-day cash for last month's cohort | E63: Yes | F63: =IF(useExample="Yes",E63,D63) -> Yes | G63: Yes when it is true
C64: Take rates for each offer | E64: Yes | F64: =IF(useExample="Yes",E64,D64) -> Yes | G64: Yes when it is true
C65: Churn for every open cohort | E65: Yes | F65: =IF(useExample="Yes",E65,D65) -> Yes | G65: Yes when it is true
C66: The numbers on this page updated | E66: Yes | F66: =IF(useExample="Yes",E66,D66) -> Yes | G66: Yes when it is true
A68: 13 | B68: Optimize | C68: A price test | G68: About 1 minute. Stack a second play and sharpen the numbers. | H68: =IF(F70<>"","Done","") -> Done
C69: Raise the upsell price by a set percent for the next run and watch the take rate. Type the raise here; the model shows what take rate would leave you no worse off.
C70: Percent to raise the upsell price in the next run | E70: 0.1 | F70: =IF(useExample="Yes",E70,IF(D70="","",D70)) -> 0.1 | G70: Type a percent, e.g. 25%. 10 is a common first test.
A72: 14 | B72: Optimize | C72: Exercise: the next bottleneck | G72: About 2 minutes. Stack a second play and sharpen the numbers. | H72: =IF(F74<>"","Done","") -> Done
C73: Once the model self-funds, something else stops growth. Name it so the next quarter has a target.
C74: What stops growth next? | E74: Capacity to serve them | F74: =IF(useExample="Yes",E74,IF(D74="","",D74)) -> Capacity to serve them | G74: Pick one: Cash to buy customers / Capacity to serve them / Leads / Conversion of leads / Cost or quality of delivery
A76: 15 | B76: Optimize | C76: Checklist: the quarterly review | G76: About 8 minutes. Stack a second play and sharpen the numbers. | H76: =IF(COUNTIF(F78:F82,"Yes")=5,"Done",IF(COUNTIF(F78:F82,"Yes")>0,"Part","")) -> Done
C77: Every three months, the whole model, top to bottom.
C78: Re-named the constraint | E78: Yes | F78: =IF(useExample="Yes",E78,D78) -> Yes | G78: Yes when it is true
C79: Re-read every offer sentence out loud | E79: Yes | F79: =IF(useExample="Yes",E79,D79) -> Yes | G79: Yes when it is true
C80: Killed or fixed the weakest offer | E80: Yes | F80: =IF(useExample="Yes",E80,D80) -> Yes | G80: Yes when it is true
C81: Checked both thresholds on the quarter's real numbers | E81: Yes | F81: =IF(useExample="Yes",E81,D81) -> Yes | G81: Yes when it is true
C82: Raised capacity or the price if the model is at the ceiling | E82: Yes | F82: =IF(useExample="Yes",E82,D82) -> Yes | G82: Yes when it is true

Sheet Dashboard
A1: Dashboard: every figure the model can compute
A2: Nothing here is typed. Every cell is a formula over the answers on the planet sheets. A figure reads "not yet" until every number it needs is in.
A4: Foundations: the business today
A5: Gross profit per sale, today | B5: =IF(AND(price<>"",deliveryCost<>""),price-deliveryCost,"not yet") -> 139 | G5: What one sale of your main offer leaves after delivering it.
A6: Gross margin, today | B6: =IF(AND(price<>"",deliveryCost<>""),IF(price=0,"no margin",(price-deliveryCost)/price),"not yet") -> 0.69849246 | C6: =IF(ISNUMBER(B6),IF(B6>=0.5,"good",IF(B6>=0.3,"watch","low")),"") -> good | G6: The share of the price you keep after delivery. Above 50% is where most of the plays become affordable.
A7: Cost of a customer (CAC) | B7: =IF(AND(adSpend<>"",newCustomers<>""),IF(newCustomers=0,"no customers",adSpend/newCustomers),"not yet") -> 150 | G7: What you spent to get customers, divided by the customers you got.
A8: First sale minus the cost of the customer | B8: =IF(AND(ISNUMBER(gpPerSale),ISNUMBER(cac)),gpPerSale-cac,"not yet") -> -11 | C8: =IF(ISNUMBER(B8),IF(B8>=0,"pays for itself","the rest of the model covers this"),"") -> the rest of the model covers this | G8: Gross profit on the first sale, less what the customer cost. Negative means the first sale does not pay for the customer, which is exactly what the rest of the model is for.
A9: Cost per lead | B9: =IF(AND(adSpend<>"",leads<>""),IF(leads=0,"no leads",adSpend/leads),"not yet") -> 15 | G9: Spend divided by leads.
A10: Customers the funnel implies | B10: =IF(AND(leads<>"",attrConversion<>""),ROUND(leads*attrConversion,0),"not yet") -> 40 | G10: Leads times the attraction conversion rate. Compare with the customers you counted.
A11: 30-day ratio, today (cash collected / CAC) | B11: =IF(AND(cash30Today<>"",ISNUMBER(cac)),IF(cac=0,"free customers",cash30Today/cac),"not yet") -> 1.3266667 | C11: =IF(ISNUMBER(B11),IF(B11>=2,"self-funding",IF(B11>=1,"break even","losing")),"") -> break even | G11: What the business does now, before the sequence.
A12: Days to get cash back, today | B12: =IF(daysToCash<>"",daysToCash,"not yet") -> 21 | G12: The before figure. The model's payback days go beside it.
A14: The sequence: each offer, per customer
A15: Attraction offer gross profit | B15: =IF(AND(attrPrice<>"",attrCost<>""),attrPrice-attrCost,"not yet") -> 380 | G15: Price less delivery, per buyer.
A16: Upsell gross profit (per taker) | B16: =IF(AND(upPrice<>"",upCost<>""),upPrice-upCost,"not yet") -> 900 | G16: Per taker.
A17: Upsell profit per customer | B17: =IF(AND(ISNUMBER(upGp),upTake<>""),upGp*upTake,"not yet") -> 225 | G17: Upsell gross profit times the take rate: what the upsell adds to every customer on average.
A18: Downsell gross profit (per taker) | B18: =IF(AND(downPrice<>"",downCost<>""),downPrice-downCost,"not yet") -> 150 | G18: Per taker.
A19: Downsell profit per customer | B19: =IF(AND(ISNUMBER(downGp),upTake<>"",downTake<>""),downGp*(1-upTake)*downTake,"not yet") -> 45 | G19: Downsell gross profit, times the share who said no to the upsell, times the downsell take rate.
A20: Continuity gross profit per month | B20: =IF(AND(contPrice<>"",contCost<>""),contPrice-contCost,"not yet") -> 109 | G20: Per member, per month.
A21: Continuity, first month, per customer | B21: =IF(AND(ISNUMBER(contGp),contJoin<>""),contGp*contJoin,"not yet") -> 65.4 | G21: Monthly gross profit times the share who join.
A22: Months a member stays, on average | B22: =IF(churn<>"",IF(churn=0,"nobody leaves",1/churn),"not yet") -> 12.5 | G22: One divided by monthly churn.
A23: Continuity lifetime profit per customer | B23: =IF(AND(ISNUMBER(contGp),contJoin<>"",ISNUMBER(expectedMonths)),contGp*contJoin*expectedMonths,"not yet") -> 817.5 | G23: Monthly gross profit, times the months a member stays, times the share who join.
A25: The headline: the 30-day rule and lifetime value
A26: 30-day cash per customer (planned, gross profit) | B26: =IF(AND(ISNUMBER(attrGp),ISNUMBER(upExpected),ISNUMBER(downExpected),ISNUMBER(contMonth1)),attrGp+upExpected+downExpected+contMonth1,"not yet") -> 715.4 | G26: Gross profit the sequence collects from one customer in their first 30 days, assuming every offer is made inside the month. Prove levels U10, D10 and C10 check that.
A27: 30-day cash collected per customer (before delivery) | B27: =IF(AND(attrPrice<>"",upPrice<>"",upTake<>"",downPrice<>"",downTake<>"",contPrice<>"",contJoin<>""),attrPrice+upPrice*upTake+downPrice*(1-upTake)*downTake+contPrice*contJoin,"not yet") -> 1024.4 | G27: Cash before delivery costs: the figure to compare with what you counted at the bank. The gross profit twin is the headline.
A28: 30-day ratio (planned) | B28: =IF(AND(ISNUMBER(gp30),ISNUMBER(cac)),IF(cac=0,"free customers",gp30/cac),"not yet") -> 4.7693333 | C28: =IF(ISNUMBER(B28),IF(B28>=2,"SELF-FUNDING: each customer pays for the next",IF(B28>=1,"break even inside the month","not paying back inside 30 days")),"") -> SELF-FUNDING: each customer pays for the next | G28: 30-day cash divided by the cost of a customer. 1 is break even, 2 is self-funding.
A29: The most you could pay for a customer | B29: =IF(ISNUMBER(gp30),gp30/2,"not yet") -> 357.7 | G29: Half the 30-day cash: the cost of a customer that still leaves you self-funding.
A30: Lifetime gross profit per customer (LTGP) | B30: =IF(AND(ISNUMBER(attrGp),ISNUMBER(upExpected),ISNUMBER(downExpected),ISNUMBER(contLtgp)),attrGp+upExpected+downExpected+contLtgp,"not yet") -> 1467.5 | G30: Everything the sequence earns from one customer, less delivery, over their whole stay.
A31: LTGP to CAC | B31: =IF(AND(ISNUMBER(ltgp),ISNUMBER(cac)),IF(cac=0,"free customers",ltgp/cac),"not yet") -> 9.7833333 | C31: =IF(ISNUMBER(B31),IF(B31>=3,"good: 3x or more",IF(B31>=1,"thin","losing")),"") -> good: 3x or more | G31: How many times over a customer pays for themselves. The book wants at least 3.
A32: 30-day cash per lead | B32: =IF(AND(ISNUMBER(gp30),attrConversion<>""),gp30*attrConversion,"not yet") -> 71.54 | G32: What a lead is worth to you in the first month, so you know what you can pay for one.
A33: Customers a month to cover fixed costs | B33: =IF(AND(fixedCosts<>"",ISNUMBER(gp30)),IF(gp30<=0,"no profit in 30 days",ROUNDUP(fixedCosts/gp30,0)),"not yet") -> 13 | G33: Fixed costs divided by 30-day cash per customer. Above this, the month is profitable on new customers alone.
A34: Customers you can afford per month | B34: =IF(AND(growthCash<>"",ISNUMBER(cac)),IF(cac=0,"no ceiling",ROUNDDOWN(growthCash/cac,0)),"not yet") -> 53 | G34: Cash for getting customers divided by the cost of one. The scale ceiling before the model self-funds.
A35: Room to grow before capacity | B35: =IF(AND(capacity<>"",newCustomers<>""),capacity-newCustomers,"not yet") -> 40 | G35: Customers per month you could add before you cannot serve them.
A36: Gross profit per hour of your time | B36: =IF(AND(ISNUMBER(gp30),hoursPerCustomer<>""),IF(hoursPerCustomer=0,"no hours",gp30/hoursPerCustomer),"not yet") -> 119.23333 | G36: The 30-day cash per customer divided by the hours you put into one. Raise the price, cut the delivery, or hire, depending on whether you like this number.
A38: Prove: what actually happened
A39: Real upsell take across all customers | B39: =IF(AND(showRate<>"",upOfferedShare<>"",upTake<>""),showRate*upOfferedShare*upTake,"not yet") -> 0.17 | G39: Show rate, times the share asked, times the take rate when asked. The number that actually hits the bank.
A40: Attraction gross profit after refunds | B40: =IF(AND(ISNUMBER(attrGp),attrPrice<>"",refundRate<>""),attrGp-attrPrice*refundRate,"not yet") -> 320 | G40: Gross profit less the price times the refund rate.
A41: Downsell cash inside 30 days (first payment only) | B41: =IF(AND(downPrice<>"",planFirstShare<>"",upTake<>"",downTake<>""),downPrice*planFirstShare*(1-upTake)*downTake,"not yet") -> 45.9 | G41: Only the first payment lands inside the month.
A42: 30-day cash, checked against timing | B42: =IF(AND(ISNUMBER(attrGp),upWhen<>"",ISNUMBER(upExpected),downPrice<>"",planFirstShare<>"",downCost<>"",upTake<>"",downTake<>"",contFirstDays<>"",ISNUMBER(contMonth1)),attrGp+IF(upWhen<=30,upExpected+(downPrice*planFirstShare-downCost)*(1-upTake)*downTake,0)+IF(contFirstDays<=30,contMonth1,0),"not yet") -> 560.9 | G42: The planned 30-day cash, dropping any offer whose cash lands after day 30 and counting only the first plan payment.
A43: Cash lost to failed payment plans, per customer | B43: =IF(AND(downPrice<>"",planFirstShare<>"",planDefault<>"",upTake<>"",downTake<>""),downPrice*(1-planFirstShare)*planDefault*(1-upTake)*downTake,"not yet") -> 7.128 | G43: The unpaid remainder times the default rate, spread over customers.
A44: Month-three retention, predicted by churn | B44: =IF(churn<>"",(1-churn)^3,"not yet") -> 0.778688
A45: Month-three retention, measured | B45: =IF(retain3<>"",retain3,"not yet") -> 0.78
A46: 30-day ratio, measured (cash collected / CAC) | B46: =IF(AND(measuredCash30<>"",ISNUMBER(cac)),IF(cac=0,"free customers",measuredCash30/cac),"not yet") -> 5.0666667 | C46: =IF(ISNUMBER(B46),IF(B46>=2,"self-funding",IF(B46>=1,"break even","losing")),"") -> self-funding | G46: From a real cohort, after the model.
A47: Customer growth since the model | B47: =IF(AND(measuredNewCustomers<>"",newCustomers<>""),IF(newCustomers=0,"no customers before",measuredNewCustomers/newCustomers-1),"not yet") -> 0.375 | G47: New customers after, against before.
A49: Optimize
A50: Cash a full run brings in | B50: =IF(AND(attrCap<>"",ISNUMBER(collected30)),attrCap*collected30,"not yet") -> 30732 | G50: The cap times the 30-day cash per customer.
A51: Second upsell profit per customer | B51: =IF(AND(up2Price<>"",up2Take<>"",upTake<>""),up2Price*up2Take*upTake,"not yet") -> 50 | G51: Price times the second take rate times the first, spread over all customers. Delivery cost is not asked for; treat it as an upper bound.
A52: The upsell as a share of the anchor | B52: =IF(AND(anchorPrice<>"",upPrice<>""),IF(anchorPrice=0,"no anchor",upPrice/anchorPrice),"not yet") -> 0.5 | G52: The upsell as a share of the anchor. Under a third reads as the sensible choice.
A53: Cash the yearly plan moves into month one | B53: =IF(AND(contAnnualPrice<>"",contPrice<>"",contAnnualTake<>"",contJoin<>""),(contAnnualPrice-contPrice)*contAnnualTake*contJoin,"not yet") -> 120.69 | G53: The yearly price less the first month already counted, times the share who choose it, per customer.
A54: 30-day cash with the yearly plan | B54: =IF(AND(ISNUMBER(gp30),ISNUMBER(annualLift)),gp30+annualLift,"not yet") -> 836.09 | G54: Planned 30-day cash plus the yearly plan's lift.
A55: LTGP with the second upsell and the yearly plan | B55: =IF(AND(ISNUMBER(ltgp),ISNUMBER(up2Expected),ISNUMBER(annualLift)),ltgp+up2Expected+annualLift,"not yet") -> 1638.19 | G55: The tier-2 figure plus the Optimize band's additions.
A56: Entry downsell cash per lead | B56: =IF(AND(entryDownPrice<>"",entryDownTake<>"",attrConversion<>""),entryDownPrice*entryDownTake*(1-attrConversion),"not yet") -> 17.82 | G56: Price times the take rate among the leads who did not buy.
A57: 30-day cash per lead with the entry downsell | B57: =IF(AND(ISNUMBER(cashPerLead),ISNUMBER(entryDownExpected)),cashPerLead+entryDownExpected,"not yet") -> 89.36 | G57: Cash per lead, plus what the leads who said no now bring.
A58: Take rate that keeps a price test even | B58: =IF(AND(ISNUMBER(upGp),upPrice<>"",priceRaise<>"",upTake<>""),IF(upGp+upPrice*priceRaise<=0,"no profit",upTake*upGp/(upGp+upPrice*priceRaise)),"not yet") -> 0.22058824 | G58: If the raised price takes at least this share, you are no worse off.
A60: Chart data: the 30-day cash, offer by offer
A61: Offer | B61: Gross profit | C61: Cost of a customer (1x) | D61: Self-funding line (2x)
A62: Attraction | B62: =IF(ISNUMBER(attrGp),attrGp,0) -> 380 | C62: =IF(ISNUMBER(cac),cac,0) -> 150 | D62: =IF(ISNUMBER(cac),2*cac,0) -> 300
A63: Upsell | B63: =IF(ISNUMBER(upExpected),upExpected,0) -> 225 | C63: =IF(ISNUMBER(cac),cac,0) -> 150 | D63: =IF(ISNUMBER(cac),2*cac,0) -> 300
A64: Downsell | B64: =IF(ISNUMBER(downExpected),downExpected,0) -> 45 | C64: =IF(ISNUMBER(cac),cac,0) -> 150 | D64: =IF(ISNUMBER(cac),2*cac,0) -> 300
A65: Continuity, month 1 | B65: =IF(ISNUMBER(contMonth1),contMonth1,0) -> 65.4 | C65: =IF(ISNUMBER(cac),cac,0) -> 150 | D65: =IF(ISNUMBER(cac),2*cac,0) -> 300
A66: Total, 30 days | B66: =IF(ISNUMBER(gp30),gp30,0) -> 715.4 | C66: =IF(ISNUMBER(cac),cac,0) -> 150 | D66: =IF(ISNUMBER(cac),2*cac,0) -> 300
A67: Text in a figure counts as 0 in the charts, so an unfinished chart reads low, never wrong.
A80: Chart data: before, planned, measured (cash collected in 30 days)
B81: Cash collected | C81: Cost of a customer
A82: Before (today) | B82: =IF(cash30Today="",0,cash30Today) -> 199 | C82: =IF(ISNUMBER(cac),cac,0) -> 150
A83: Planned | B83: =IF(ISNUMBER(collected30),collected30,0) -> 1024.4 | C83: =IF(ISNUMBER(cac),cac,0) -> 150
A84: Measured | B84: =IF(measuredCash30="",0,measuredCash30) -> 760 | C84: =IF(ISNUMBER(cac),cac,0) -> 150
A100: Chart data: the funnel, from 100 leads
A101: Stage | B101: People
A102: Leads | B102: =100 -> 100
A103: Take the attraction offer | B103: =IF(attrConversion="",0,100*attrConversion) -> 10
A104: Take the upsell | B104: =IF(upTake="",0,B103*upTake) -> 2.5
A105: Take the downsell | B105: =IF(downTake="",0,(B103-B104)*downTake) -> 3
A106: Join continuity | B106: =IF(contJoin="",0,B103*contJoin) -> 6
A120: Chart data: twelve months if you reinvest the 30-day cash
A121: Month | B121: Budget for customers | C121: Customers, reinvesting | D121: Customers, flat budget | E121: Capacity
A122: 1 | B122: =IF(AND(ISNUMBER(cac),cac>0,ISNUMBER(gp30),growthCash<>"",reinvestShare<>"",capacity<>""),growthCash,0) -> 8000 | C122: =IF(AND(ISNUMBER(cac),cac>0,ISNUMBER(gp30),growthCash<>"",reinvestShare<>"",capacity<>""),MIN(capacity,B122/cac),0) -> 53.333333 | D122: =IF(AND(ISNUMBER(cac),cac>0,ISNUMBER(gp30),growthCash<>"",reinvestShare<>"",capacity<>""),MIN(capacity,growthCash/cac),0) -> 53.333333 | E122: =IF(capacity="",0,capacity) -> 80
A123: 2 | B123: =IF(AND(ISNUMBER(cac),cac>0,ISNUMBER(gp30),growthCash<>"",reinvestShare<>"",capacity<>""),growthCash+reinvestShare*gp30*C122,0) -> 27077.333 | C123: =IF(AND(ISNUMBER(cac),cac>0,ISNUMBER(gp30),growthCash<>"",reinvestShare<>"",capacity<>""),MIN(capacity,B123/cac),0) -> 80 | D123: =IF(AND(ISNUMBER(cac),cac>0,ISNUMBER(gp30),growthCash<>"",reinvestShare<>"",capacity<>""),MIN(capacity,growthCash/cac),0) -> 53.333333 | E123: =IF(capacity="",0,capacity) -> 80
A124: 3 | B124: =IF(AND(ISNUMBER(cac),cac>0,ISNUMBER(gp30),growthCash<>"",reinvestShare<>"",capacity<>""),growthCash+reinvestShare*gp30*C123,0) -> 36616 | C124: =IF(AND(ISNUMBER(cac),cac>0,ISNUMBER(gp30),growthCash<>"",reinvestShare<>"",capacity<>""),MIN(capacity,B124/cac),0) -> 80 | D124: =IF(AND(ISNUMBER(cac),cac>0,ISNUMBER(gp30),growthCash<>"",reinvestShare<>"",capacity<>""),MIN(capacity,growthCash/cac),0) -> 53.333333 | E124: =IF(capacity="",0,capacity) -> 80
A125: 4 | B125: =IF(AND(ISNUMBER(cac),cac>0,ISNUMBER(gp30),growthCash<>"",reinvestShare<>"",capacity<>""),growthCash+reinvestShare*gp30*C124,0) -> 36616 | C125: =IF(AND(ISNUMBER(cac),cac>0,ISNUMBER(gp30),growthCash<>"",reinvestShare<>"",capacity<>""),MIN(capacity,B125/cac),0) -> 80 | D125: =IF(AND(ISNUMBER(cac),cac>0,ISNUMBER(gp30),growthCash<>"",reinvestShare<>"",capacity<>""),MIN(capacity,growthCash/cac),0) -> 53.333333 | E125: =IF(capacity="",0,capacity) -> 80
A126: 5 | B126: =IF(AND(ISNUMBER(cac),cac>0,ISNUMBER(gp30),growthCash<>"",reinvestShare<>"",capacity<>""),growthCash+reinvestShare*gp30*C125,0) -> 36616 | C126: =IF(AND(ISNUMBER(cac),cac>0,ISNUMBER(gp30),growthCash<>"",reinvestShare<>"",capacity<>""),MIN(capacity,B126/cac),0) -> 80 | D126: =IF(AND(ISNUMBER(cac),cac>0,ISNUMBER(gp30),growthCash<>"",reinvestShare<>"",capacity<>""),MIN(capacity,growthCash/cac),0) -> 53.333333 | E126: =IF(capacity="",0,capacity) -> 80
A127: 6 | B127: =IF(AND(ISNUMBER(cac),cac>0,ISNUMBER(gp30),growthCash<>"",reinvestShare<>"",capacity<>""),growthCash+reinvestShare*gp30*C126,0) -> 36616 | C127: =IF(AND(ISNUMBER(cac),cac>0,ISNUMBER(gp30),growthCash<>"",reinvestShare<>"",capacity<>""),MIN(capacity,B127/cac),0) -> 80 | D127: =IF(AND(ISNUMBER(cac),cac>0,ISNUMBER(gp30),growthCash<>"",reinvestShare<>"",capacity<>""),MIN(capacity,growthCash/cac),0) -> 53.333333 | E127: =IF(capacity="",0,capacity) -> 80
A128: 7 | B128: =IF(AND(ISNUMBER(cac),cac>0,ISNUMBER(gp30),growthCash<>"",reinvestShare<>"",capacity<>""),growthCash+reinvestShare*gp30*C127,0) -> 36616 | C128: =IF(AND(ISNUMBER(cac),cac>0,ISNUMBER(gp30),growthCash<>"",reinvestShare<>"",capacity<>""),MIN(capacity,B128/cac),0) -> 80 | D128: =IF(AND(ISNUMBER(cac),cac>0,ISNUMBER(gp30),growthCash<>"",reinvestShare<>"",capacity<>""),MIN(capacity,growthCash/cac),0) -> 53.333333 | E128: =IF(capacity="",0,capacity) -> 80
A129: 8 | B129: =IF(AND(ISNUMBER(cac),cac>0,ISNUMBER(gp30),growthCash<>"",reinvestShare<>"",capacity<>""),growthCash+reinvestShare*gp30*C128,0) -> 36616 | C129: =IF(AND(ISNUMBER(cac),cac>0,ISNUMBER(gp30),growthCash<>"",reinvestShare<>"",capacity<>""),MIN(capacity,B129/cac),0) -> 80 | D129: =IF(AND(ISNUMBER(cac),cac>0,ISNUMBER(gp30),growthCash<>"",reinvestShare<>"",capacity<>""),MIN(capacity,growthCash/cac),0) -> 53.333333 | E129: =IF(capacity="",0,capacity) -> 80
A130: 9 | B130: =IF(AND(ISNUMBER(cac),cac>0,ISNUMBER(gp30),growthCash<>"",reinvestShare<>"",capacity<>""),growthCash+reinvestShare*gp30*C129,0) -> 36616 | C130: =IF(AND(ISNUMBER(cac),cac>0,ISNUMBER(gp30),growthCash<>"",reinvestShare<>"",capacity<>""),MIN(capacity,B130/cac),0) -> 80 | D130: =IF(AND(ISNUMBER(cac),cac>0,ISNUMBER(gp30),growthCash<>"",reinvestShare<>"",capacity<>""),MIN(capacity,growthCash/cac),0) -> 53.333333 | E130: =IF(capacity="",0,capacity) -> 80
A131: 10 | B131: =IF(AND(ISNUMBER(cac),cac>0,ISNUMBER(gp30),growthCash<>"",reinvestShare<>"",capacity<>""),growthCash+reinvestShare*gp30*C130,0) -> 36616 | C131: =IF(AND(ISNUMBER(cac),cac>0,ISNUMBER(gp30),growthCash<>"",reinvestShare<>"",capacity<>""),MIN(capacity,B131/cac),0) -> 80 | D131: =IF(AND(ISNUMBER(cac),cac>0,ISNUMBER(gp30),growthCash<>"",reinvestShare<>"",capacity<>""),MIN(capacity,growthCash/cac),0) -> 53.333333 | E131: =IF(capacity="",0,capacity) -> 80
A132: 11 | B132: =IF(AND(ISNUMBER(cac),cac>0,ISNUMBER(gp30),growthCash<>"",reinvestShare<>"",capacity<>""),growthCash+reinvestShare*gp30*C131,0) -> 36616 | C132: =IF(AND(ISNUMBER(cac),cac>0,ISNUMBER(gp30),growthCash<>"",reinvestShare<>"",capacity<>""),MIN(capacity,B132/cac),0) -> 80 | D132: =IF(AND(ISNUMBER(cac),cac>0,ISNUMBER(gp30),growthCash<>"",reinvestShare<>"",capacity<>""),MIN(capacity,growthCash/cac),0) -> 53.333333 | E132: =IF(capacity="",0,capacity) -> 80
A133: 12 | B133: =IF(AND(ISNUMBER(cac),cac>0,ISNUMBER(gp30),growthCash<>"",reinvestShare<>"",capacity<>""),growthCash+reinvestShare*gp30*C132,0) -> 36616 | C133: =IF(AND(ISNUMBER(cac),cac>0,ISNUMBER(gp30),growthCash<>"",reinvestShare<>"",capacity<>""),MIN(capacity,B133/cac),0) -> 80 | D133: =IF(AND(ISNUMBER(cac),cac>0,ISNUMBER(gp30),growthCash<>"",reinvestShare<>"",capacity<>""),MIN(capacity,growthCash/cac),0) -> 53.333333 | E133: =IF(capacity="",0,capacity) -> 80
A140: Chart data: members left, month by month (100 join)
A141: Month | B141: Members left
A142: 0 | B142: =IF(churn="",0,100*(1-churn)^0) -> 100
A143: 1 | B143: =IF(churn="",0,100*(1-churn)^1) -> 92
A144: 2 | B144: =IF(churn="",0,100*(1-churn)^2) -> 84.64
A145: 3 | B145: =IF(churn="",0,100*(1-churn)^3) -> 77.8688
A146: 4 | B146: =IF(churn="",0,100*(1-churn)^4) -> 71.639296
A147: 5 | B147: =IF(churn="",0,100*(1-churn)^5) -> 65.908152
A148: 6 | B148: =IF(churn="",0,100*(1-churn)^6) -> 60.6355
A149: 7 | B149: =IF(churn="",0,100*(1-churn)^7) -> 55.78466
A150: 8 | B150: =IF(churn="",0,100*(1-churn)^8) -> 51.321887
A151: 9 | B151: =IF(churn="",0,100*(1-churn)^9) -> 47.216136
A152: 10 | B152: =IF(churn="",0,100*(1-churn)^10) -> 43.438845
...

Sheet Your Model
A1: Your money model: the four offers in order
A2: What you wrote on the Build bands, with the price and take rate beside each. Read it top to bottom: that is the sequence a customer walks.
A4: Offer | B4: What you say | C4: Price | D4: Who says yes
A5: 1. Attraction | B5: =IF(attrOffer="","not written yet",attrOffer) -> Lose ten pounds in six weeks for $500, and win it all back if you finish every session. | C5: =IF(attrPrice="","not yet",attrPrice) -> 500 | D5: =IF(attrConversion="","not yet",TEXT(attrConversion,"0%")&" of leads") -> 10% of leads
A6: then the string | B6: =IF(attrString="","not written yet",attrString) -> The week-two results check-in with a coach
A7: 2. Upsell | B7: =IF(upScript="","not written yet",upScript) -> Since you want the ten pounds gone for good, the people who keep it off go straight onto the year programme, and the $500 you paid comes off it. Want me to set that up? | C7: =IF(upPrice="","not yet",upPrice) -> 1200 | D7: =IF(upTake="","not yet",TEXT(upTake,"0%")&" of customers") -> 25% of customers
A8: on a no | B8: =IF(upNoReply="","not written yet",upNoReply) -> Totally fair. Would three payments make it work?
A9: 3. Downsell | B9: =IF(downScript="","not written yet",downScript) -> No problem. We can do the same programme as three payments of $150; you still get the full year. | C9: =IF(downPrice="","not yet",downPrice) -> 450 | D9: =IF(downTake="","not yet",TEXT(downTake,"0%")&" of the nos") -> 40% of the nos
A10: what is smaller | B10: =IF(downCut="","not written yet",downCut) -> Nothing is cut; the terms are longer
A11: 4. Continuity | B11: =IF(contScript="","not written yet",contScript) -> To keep the weight off, most people stay on as members: $149 a month, and if you start today the first month's meal plans are included. | C11: =IF(contPrice="","not yet",contPrice) -> 149 | D11: =IF(contJoin="","not yet",TEXT(contJoin,"0%")&" join"&IF(churn="","",", "&TEXT(churn,"0%")&" leave each month")) -> 60% join, 8% leave each month
A12: the reason to stay | B12: =IF(contHook="","not written yet",contHook) -> A new eight-week block every two months, and a tracked weigh-in chart
A14: The numbers that judge it
A15: 30-day ratio | B15: =IF(ISNUMBER(ratio30),ratio30,ratio30) -> 4.7693333
A16: Payback days | B16: =IF(ISNUMBER(paybackDays),paybackDays,paybackDays) -> 0
A17: LTGP to CAC | B17: =IF(ISNUMBER(ltgpCac),ltgpCac,ltgpCac) -> 9.7833333
A18: Most you could pay for a customer | B18: =IF(ISNUMBER(maxCac),maxCac,maxCac) -> 357.7
A19: The promise | B19: =IF(OR(customer="",promise=""),"not yet","For "&customer&": "&promise) -> For Busy parents who stopped exercising: Lose the first ten pounds in six weeks
A20: The constraint | B20: =IF(constraint="","not yet",constraint) -> Each customer does not pay enough
A21: Where you start | B21: =IF(firstPlanet="","not yet",firstPlanet) -> Upsell: earn more from each one

Sheet Plays
A1: The plays: nineteen ways to build the four offers
A2: A play reads Open when your numbers say it fits, Waiting until then. The five steps under each are the way to run it; mark them Yes as you go.
A4: Planet | B4: Play | C4: What it is, and the steps | D4: Open? / Done? | E4: Opens when
A5: Attraction | B5: Win your money back | C5: The customer pays, and gets it back (or as credit) if they hit a stated result and follow the rules. Most will not; the ones who do are the customers you want. | D5: =IF(AND(AND(ISNUMBER(grossMargin),grossMargin>=0.5),promise<>""),"Open","Waiting") -> Open | E5: gross margin of at least 50%, so a refund does not sink you; a promise with a result you can measure
C6: 1. Write the result and the deadline as a number anyone can check | E6: Yes when done
C7: 2. List every rule they must follow to qualify (attendance, submissions, check-ins) | E7: Yes when done
C8: 3. Decide: cash refund, or credit toward the upsell | E8: Yes when done
C9: 4. Put the refund cost in the attraction offer's delivery cost | E9: Yes when done
C10: 5. Track who qualifies, and offer them the upsell first | E10: Yes when done
A12: Attraction | B12: Giveaway | C12: One big prize, many entrants, and everyone who did not win gets an offer. Cheap leads at volume. | D12: =IF(AND(ISNUMBER(cpl),cpl>=20),"Open","Waiting") -> Waiting | E12: a cost per lead of $20 or more, so cheaper leads matter
C13: 1. Pick a prize worth a lot to the customer and a known cost to you | E13: Yes when done
C14: 2. Set the entry: a form, a follow, a referral | E14: Yes when done
C15: 3. Write the consolation offer every non-winner gets | E15: Yes when done
C16: 4. Set a draw date and announce it | E16: Yes when done
C17: 5. Count entrants, buyers of the consolation offer, and cost | E17: Yes when done
A19: Attraction | B19: Decoy | C19: A free or very cheap option next to the real one, so the real one looks like the sensible choice and the free one filters out people who would never pay. | D19: =IF(AND(ISNUMBER(attrPrice),attrPrice>0),"Open","Waiting") -> Open | E19: a paid attraction offer for the decoy to sit beside
C20: 1. Design the decoy: less of the real thing, clearly worse value per dollar | E20: Yes when done
C21: 2. Show both side by side, the decoy first | E21: Yes when done
C22: 3. Make the decoy's string lead to the paid offer | E22: Yes when done
C23: 4. Count who picks which | E23: Yes when done
C24: 5. Raise the decoy's price if too many take it | E24: Yes when done
A26: Attraction | B26: Buy some, get some free | C26: Bundle volume up front. The free part is margin you would have spent on getting the customer back anyway. | D26: =IF(AND(ISNUMBER(grossMargin),grossMargin>=0.6),"Open","Waiting") -> Open | E26: gross margin of at least 60%, so the free units cost you little
C27: 1. Pick the unit (sessions, months, boxes) | E27: Yes when done
C28: 2. Set the bundle so the free part is under a third of the total | E28: Yes when done
C29: 3. Price the bundle above the single unit times the paid count | E29: Yes when done
C30: 4. Say the free part out loud in the offer | E30: Yes when done
C31: 5. Compare cash per customer with the single-unit offer | E31: Yes when done
A33: Attraction | B33: Pay less now or pay more later | C33: Two prices for the same thing: a smaller one paid today and a larger one paid on results or over time. Both close; one brings cash forward. | D33: =IF(AND(ISNUMBER(price),price>=500),"Open","Waiting") -> Waiting | E33: a main offer of $500 or more, where the two prices differ enough to matter
C34: 1. Set the pay-now price | E34: Yes when done
C35: 2. Set the pay-later price 20 to 40% higher | E35: Yes when done
C36: 3. Decide the later trigger: a date, a result, an instalment | E36: Yes when done
C37: 4. Present both, pay-now first | E37: Yes when done
C38: 5. Track which is chosen and the cash collected inside 30 days | E38: Yes when done
A40: Attraction | B40: Free with strings | C40: Free only when the string (a deposit, a booked call, an upsell moment) makes the free customer pay off. | D40: =IF(AND(AND(ISNUMBER(upExpected),upExpected>=0),ISNUMBER(cac)),"Open","Waiting") -> Open | E40: an upsell with a known profit per customer; the cost of a customer
C41: 1. Name the string: what they must do to get the free thing | E41: Yes when done
C42: 2. Put the upsell inside the string (the results call, the fitting, the pickup) | E42: Yes when done
C43: 3. Take a refundable deposit if no-shows are likely | E43: Yes when done
C44: 4. Count free takers, string completers, and upsell takers | E44: Yes when done
C45: 5. Kill it if free customers do not reach the upsell | E45: Yes when done
A47: Upsell | B47: Classic upsell | C47: The next thing they need to get the result faster or keep it. | D47: =IF(ISNUMBER(attrGp),"Open","Waiting") -> Open | E47: an attraction offer with a price and a cost
C48: 1. Name the next obstacle after the attraction offer | E48: Yes when done
C49: 2. Build the thing that removes it | E49: Yes when done
C50: 3. Price it above the attraction offer | E50: Yes when done
C51: 4. Write the one-sentence ask | E51: Yes when done
C52: 5. Ask every customer, and tally it | E52: Yes when done
A54: Upsell | B54: Menu upsell | C54: Several add-ons, they pick. People say yes to something more often than to one thing. | D54: =IF(AND(ISNUMBER(upTake),upTake<0.3),"Open","Waiting") -> Open | E54: an upsell take rate under 30%, where choice tends to help
C55: 1. List three to five add-ons that each move the result | E55: Yes when done
C56: 2. Price each so any two beat the single upsell | E56: Yes when done
C57: 3. Present the menu after the first yes | E57: Yes when done
C58: 4. Count which combinations sell | E58: Yes when done
C59: 5. Drop the one nobody picks | E59: Yes when done
A61: Upsell | B61: Anchor upsell | C61: Show the biggest option first. The one you want to sell looks reasonable next to it. | D61: =IF(AND(ISNUMBER(upPrice),upPrice>=1000),"Open","Waiting") -> Open | E61: an upsell of $1,000 or more, where the anchor has room above it
C62: 1. Design the top tier as if someone will buy it | E62: Yes when done
C63: 2. Price it at least three times the real upsell | E63: Yes when done
C64: 3. Present it first, then the real one | E64: Yes when done
C65: 4. Count anchor buyers separately | E65: Yes when done
C66: 5. Raise the real upsell's price if the take rate holds | E66: Yes when done
A68: Upsell | B68: Rollover upsell | C68: Credit what they just paid toward the bigger thing. The first purchase becomes a deposit. | D68: =IF(AND(AND(ISNUMBER(attrPrice),attrPrice>0),upPrice<>""),"Open","Waiting") -> Open | E68: a paid attraction offer to roll over; an upsell price
C69: 1. State the credit: 'the [attraction price] you paid comes off' | E69: Yes when done
C70: 2. Set a deadline on the credit (this week, this visit) | E70: Yes when done
C71: 3. Show the upsell price after the credit | E71: Yes when done
C72: 4. Track rollover takers against ordinary takers | E72: Yes when done
C73: 5. Widen the credit if the take rate is low | E73: Yes when done
A75: Downsell | B75: Payment plan | C75: The same offer split over time. Usually the first thing to try. | D75: =IF(AND(ISNUMBER(upPrice),upPrice>=300),"Open","Waiting") -> Open | E75: an upsell of $300 or more, where splitting helps
C76: 1. Set the number of payments (three is common) | E76: Yes when done
C77: 2. Make the first payment the largest | E77: Yes when done
C78: 3. Put every plan on automatic billing | E78: Yes when done
C79: 4. Offer it only after the no, never on the price list | E79: Yes when done
C80: 5. Track plans to their last payment | E80: Yes when done
A82: Downsell | B82: Trial with a string | C82: Try it, and pay if you keep it, or pay a penalty if you do not do the work. | D82: =IF(contPrice<>"","Open","Waiting") -> Open | E82: a continuity offer for the trial to lead into
C83: 1. Set the trial length (shorter than the first win) | E83: Yes when done
C84: 2. Write the string: the payment or penalty, and its trigger | E84: Yes when done
C85: 3. Take card details up front | E85: Yes when done
C86: 4. Check in before the trial ends | E86: Yes when done
C87: 5. Count trial starts, conversions and penalties | E87: Yes when done
A89: Downsell | B89: Lighter version | C89: Fewer parts, less access, less support, same result more slowly. Keep the promise, shrink the package. | D89: =IF(AND(ISNUMBER(upCost),upCost>0),"Open","Waiting") -> Open | E89: an upsell with a delivery cost you can shrink
C90: 1. List the parts of the upsell | E90: Yes when done
C91: 2. Remove the ones that cost you most and the customer least | E91: Yes when done
C92: 3. Price it between the attraction offer and the upsell | E92: Yes when done
C93: 4. Keep the string to continuity | E93: Yes when done
C94: 5. Compare its take rate with the payment plan's | E94: Yes when done
A96: Downsell | B96: Deposit and decide | C96: A small payment to hold the price or the spot, decided later. Cash today, and a reason to come back. | D96: =IF(attrCap<>"","Open","Waiting") -> Open | E96: a cap per run, so holding a spot means something
C97: 1. Set the deposit (5 to 10% of the upsell) | E97: Yes when done
C98: 2. Say what it holds: the price, the spot, the bonus | E98: Yes when done
C99: 3. Set the decide-by date | E99: Yes when done
C100: 4. Follow up the day before | E100: Yes when done
C101: 5. Count deposits, conversions and refunds | E101: Yes when done
A103: Continuity | B103: Bonus for committing | C103: A gift, worth a lot to them and little to you, for joining the ongoing plan today. | D103: =IF(AND(ISNUMBER(contJoin),contJoin<0.7),"Open","Waiting") -> Open | E103: a continuity join rate under 70%, so the first no is the problem
C104: 1. Pick a bonus that costs you under one month's gross profit | E104: Yes when done
C105: 2. Make it available only at joining | E105: Yes when done
C106: 3. Say it in the pitch | E106: Yes when done
C107: 4. Count join rates with and without it | E107: Yes when done
C108: 5. Rotate it every quarter | E108: Yes when done
A110: Continuity | B110: Discount for a longer term | C110: Pay for a year, get it cheaper. Cash forward, churn removed. | D110: =IF(AND(ISNUMBER(expectedMonths),expectedMonths>=6),"Open","Waiting") -> Open | E110: members staying six months or more on average, so a year is believable
C111: 1. Price the year at ten months or so | E111: Yes when done
C112: 2. Offer it at joining and at month three | E112: Yes when done
C113: 3. Show the monthly price beside it | E113: Yes when done
C114: 4. Count yearly takers | E114: Yes when done
C115: 5. Put the cash in the 30-day figure on level C13 | E115: Yes when done
A117: Continuity | B117: Waived fee | C117: The setup or first month is free if they join now. The fee exists so waiving it means something. | D117: =IF(AND(ISNUMBER(contGp),contGp>0),"Open","Waiting") -> Open | E117: a continuity offer that makes a gross profit each month
...
